Workbook

Sheet 📖 Инструкция
B2: 📋 КАЛЬКУЛЯТОР NEV v7
B4: Инструкция · Многоуровневая рецептура · Расчёт сырья · Многовалютные цены
B6: 🎯 ЛИСТЫ ДЛЯ РАБОТЫ
B7: Калькулятор | C7: Расчёт себестоимости готового продукта из каталога
B8: Калькулятор X | C8: Расчёт нового продукта (произвольный состав)
B9: Расчёт сырья | C9: Планирование закупок: ввод заявки → список сырья
B11: 📚 СПРАВОЧНИКИ
B12: Продукты | C12: Каталог готовой продукции (191 наименование)
B13: Полупродукты | C13: Каталог производимых полупродуктов (50)
B14: Сырьё | C14: Каталог покупного сырья (226 позиций, валюты RUB/USD/EUR/CNY)
B15: Курсы ЦБ | C15: История курсов валют (обновляется автоматически)
B16: Потери | C16: Реальные потери производства по данным выпусков (31 артикул)
B18: ⚠️ КАЧЕСТВО ДАННЫХ
B19: ⚠️ Что заполнить | C19: Дашборд: сырьё без цены, ошибки рецептур, нехватка полупродуктов
B21: 🛠 СЛУЖЕБНЫЕ (скрытые)
B22: Рецептуры | C22: Базовая таблица рецептов (read-only)
B23: _Развёртки | C23: Предрасчёт сырья для «Расчёта сырья»
B24: Apps Script код | C24: Код скрипта (см. также отдельный файл)
B27: 🚀 КАК НАЧАТЬ
B28: 1. | C28: Откройте файл в Google Sheets (загрузите на Drive, откройте через Sheets)
B29: 2. | C29: Установите Apps Script: Расширения → Apps Script → вставьте код из листа «Apps Script код» → Сохранить
B30: 3. | C30: Перезагрузите таблицу (F5) — появится меню «🛠 NEV»
B31: 4. | C31: Меню → «💱 Обновить курсы ЦБ» — загрузится актуальный курс. Дальше — обновляется автоматически при открытии
B32: 5. | C32: Откройте «⚠️ Что заполнить» — увидите, какие данные нужно дозаполнить (32 позиции без цен)
B33: 6. | C33: Заполните цены сырья в Сырьё (J=валюта, K=цена, F=дата необязательно)
B34: 7. | C34: Используйте «Калькулятор» для готовых продуктов, «Расчёт сырья» — для заявок
B37: 💡 ВАЖНЫЕ ОСОБЕННОСТИ
B38: • | C38: Курс EUR/RUB в K8 — авто из «Курсы ЦБ», можно перезаписать вручную
B39: • | C39: Цены сырья в 4 валютах: RUB, USD, EUR, CNY. Кросс-курс через ЦБ на дату поступления
B40: • | C40: • Колонка M в Калькуляторе — «Пред. цена €/кг без НДС» (ручной ввод, подменяет J)
B41: • | C41: • Ячейка M11 в Калькуляторе и Калькуляторе X — глобальные потери, % (ручной ввод, напр. 5%). Сбрасывается автоматически при смене продукта в B8.
B42: • | C42: В Расчёте сырья развёртки с потерями 3%, тара/сырьё/полупр. — отдельные секции с подытогами
B43: • | C43: При смене продукта (B8) ручные значения авто-сбрасываются
B44: • | C44: Σ% в L15 (сумма % компонентов): 🟢 ≈100%, 🔴 >100% — ошибка, 🟡 <100% — недозаполнено

Sheet Apps Script код
A1: /**
A2: * Google Apps Script для Калькулятор_NEV (версия 7)
A3: *
A4: * ИЗМЕНЕНИЯ в v7:
A5: * • Основной источник курсов — официальный API ЦБ РФ
A6: * (https://www.cbr.ru/scripts/XML_daily.asp), XML
A7: * • Fallback-источники: cbr-xml-daily.ru → cbr-xml-daily.com
A8: * • Подробное сообщение об ошибке, если ни один источник не отдал данные
A9: *
A10: * Все остальные функции v6 (сброс калькуляторов, M11 для потерь,
A11: * автообновление при открытии) — без изменений.
A12: */
... A461: }

Sheet ⚠️ Что заполнить
B2: ⚠️ ДАШБОРД КАЧЕСТВА ДАННЫХ
B3: Список того, что требует внимания. Обновляется автоматически.
B5: 📊 СВОДКА
B6: Сырья без цены: | C6: =SUMPRODUCT(('Сырьё'!$C$6:$C$233<>"")*(IFERROR('Сырьё'!$K$6:$K$231,0)=0)) -> #N/A
B7: Продуктов с Σ% > 100%: | C7: =COUNTIF(D17:D200,">1.005") -> 58
B8: Продуктов с Σ% < 99%: | C8: =COUNTIFS(D17:D200,">0",D17:D200,"<0.99") -> 0
B9: Полупродуктов без рецептуры: | C9: 56
B12: 🔴 1. СЫРЬЁ БЕЗ ЦЕНЫ — без этих цен себестоимость считается некорректно
B14: № | C14: Наименование | D14: Тип | E14: Поставщик | F14: Артикул
B15: 1 | C15: ='Сырьё'!C6 -> ASTRA11305 | D15: ='Сырьё'!I6 | E15: ='Сырьё'!G6 | F15: ='Сырьё'!H6
B16: 2 | C16: ='Сырьё'!C7 -> ASTRA11306 | D16: ='Сырьё'!I7 | E16: ='Сырьё'!G7 | F16: ='Сырьё'!H7
B17: 3 | C17: ='Сырьё'!C8 -> BLACK (PBl 7) | D17: ='Сырьё'!I8 | E17: ='Сырьё'!G8 | F17: ='Сырьё'!H8
B18: 4 | C18: ='Сырьё'!C22 -> Extender TRIPOL 16 | D18: ='Сырьё'!I22 -> ⚗️ полупр. | E18: ='Сырьё'!G22 | F18: ='Сырьё'!H22
B19: 5 | C19: ='Сырьё'!C34 -> LuWax AF31 | D19: ='Сырьё'!I34 | E19: ='Сырьё'!G34 | F19: ='Сырьё'!H34
B20: 6 | C20: ='Сырьё'!C35 -> MAGENTA (PR 57:1) SURF | D20: ='Сырьё'!I35 | E20: ='Сырьё'!G35 | F20: ='Сырьё'!H35
B21: 7 | C21: ='Сырьё'!C38 -> Neocrylic Resin B 819 | D21: ='Сырьё'!I38 | E21: ='Сырьё'!G38 | F21: ='Сырьё'!H38
B22: 8 | C22: ='Сырьё'!C39 -> Neocrylic Resin BM 619 | D22: ='Сырьё'!I39 | E22: ='Сырьё'!G39 | F22: ='Сырьё'!H39
B23: 9 | C23: ='Сырьё'!C40 -> Neorez u 476 | D23: ='Сырьё'!I40 | E23: ='Сырьё'!G40 | F23: ='Сырьё'!H40
B24: 10 | C24: ='Сырьё'!C44 -> Nitrocellulose L1\8 SEC(IPA) | D24: ='Сырьё'!I44 | E24: ='Сырьё'!G44 | F24: ='Сырьё'!H44
B25: 11 | C25: ='Сырьё'!C57 -> Pigment Red (PR 122) СИНТЕЗ ЦВЕТА | D25: ='Сырьё'!I57 | E25: ='Сырьё'!G57 | F25: ='Сырьё'!H57
B26: 12 | C26: ='Сырьё'!C58 -> Pigment RED (PR 254) ХС | D26: ='Сырьё'!I58 | E26: ='Сырьё'!G58 | F26: ='Сырьё'!H58
B27: 13 | C27: ='Сырьё'!C64 -> Pigment Yellow (PY 74)(синтез цвета) | D27: ='Сырьё'!I64 | E27: ='Сырьё'!G64 | F27: ='Сырьё'!H64
B28: 14 | C28: ='Сырьё'!C65 -> Pigment Yellow (PY 83)радиант | D28: ='Сырьё'!I65 | E28: ='Сырьё'!G65 | F28: ='Сырьё'!H65
B29: 15 | C29: ='Сырьё'!C71 -> Pigment Yellow PY 13 ЕТС | D29: ='Сырьё'!I71 | E29: ='Сырьё'!G71 | F29: ='Сырьё'!H71
B30: 16 | C30: ='Сырьё'!C78 -> Technical extender AL_RESIST | D30: ='Сырьё'!I78 -> ⚗️ полупр. | E30: ='Сырьё'!G78 | F30: ='Сырьё'!H78
B31: 17 | C31: ='Сырьё'!C82 -> Technical Extender SURF ROTO | D31: ='Сырьё'!I82 -> ⚗️ полупр. | E31: ='Сырьё'!G82 | F31: ='Сырьё'!H82
B32: 18 | C32: ='Сырьё'!C86 -> TRIPOL 16 | D32: ='Сырьё'!I86 | E32: ='Сырьё'!G86 | F32: ='Сырьё'!H86
B33: 19 | C33: ='Сырьё'!C91 -> w 106r (для прямой печати ) | D33: ='Сырьё'!I91 | E33: ='Сырьё'!G91 | F33: ='Сырьё'!H91
B34: 20 | C34: ='Сырьё'!C93 -> YELLOW (PY 13) | D34: ='Сырьё'!I93 | E34: ='Сырьё'!G93 | F34: ='Сырьё'!H93
B35: 21 | C35: ='Сырьё'!C94 -> YL-904 | D35: ='Сырьё'!I94 | E35: ='Сырьё'!G94 | F35: ='Сырьё'!H94
B36: 22 | C36: ='Сырьё'!C121 -> Краска NSF/LAM ROTAGRAV | D36: ='Сырьё'!I121 | E36: ='Сырьё'!G121 | F36: ='Сырьё'!H121
B37: 23 | C37: ='Сырьё'!C141 -> Краска NSF/White (PW 6) PV ver1 | D37: ='Сырьё'!I141 | E37: ='Сырьё'!G141 | F37: ='Сырьё'!H141
B38: 24 | C38: ='Сырьё'!C142 -> Краска NSF/White (PW 6) PV ver2 | D38: ='Сырьё'!I142 | E38: ='Сырьё'!G142 | F38: ='Сырьё'!H142
B39: 25 | C39: ='Сырьё'!C156 -> ЛАК НЦ -0711 | D39: ='Сырьё'!I156 -> ⚗️ полупр. | E39: ='Сырьё'!G156 | F39: ='Сырьё'!H156
B40: 26 | C40: ='Сырьё'!C157 -> ЛАК НЦ 35 ROTO | D40: ='Сырьё'!I157 -> ⚗️ полупр. | E40: ='Сырьё'!G157 | F40: ='Сырьё'!H157
B41: 27 | C41: ='Сырьё'!C160 -> Лак покрывной | D41: ='Сырьё'!I160 -> ⚗️ полупр. | E41: ='Сырьё'!G160 | F41: ='Сырьё'!H160
B42: 28 | C42: ='Сырьё'!C161 -> Лак покрывной(холодный клей) | D42: ='Сырьё'!I161 -> ⚗️ полупр. | E42: ='Сырьё'!G161 | F42: ='Сырьё'!H161
B43: 29 | C43: ='Сырьё'!C205 -> Пирогенный диоксид кремния HL-200 | D43: ='Сырьё'!I205 | E43: ='Сырьё'!G205 | F43: ='Сырьё'!H205
B44: 30 | C44: ='Сырьё'!C206 -> покрывной лак | D44: ='Сырьё'!I206 -> ⚗️ полупр. | E44: ='Сырьё'!G206 | F44: ='Сырьё'!H206
B45: 31 | C45: ='Сырьё'!C207 -> покрывной лак (OVERPRINT VARNISH ) | D45: ='Сырьё'!I207 -> ⚗️ полупр. | E45: ='Сырьё'!G207 | F45: ='Сырьё'!H207
B46: 32 | C46: ='Сырьё'!C208 -> Полиуретан DROPACK 5260 | D46: ='Сырьё'!I208 | E46: ='Сырьё'!G208 | F46: ='Сырьё'!H208
B48: 🟡 2. ПРОДУКТЫ С Σ% НЕ РАВНОЙ 100% — проверьте рецептуру
B50: № | C50: Продукт | D50: Σ % | E50: Отклонение | F50: Тип ошибки
B51: 1 | C51: Дисперсия воска YL-904, | D51: 0.586 | E51: -0.414 | F51: Σ < 100%
B52: 2 | C52: Краска NSF/UNI Yellov (PY13) TR ГУ | D52: 0.95 | E52: -0.05 | F52: Σ < 100%
B53: 3 | C53: Краска NSF/UNI Black (PBl 7) TR ГУ | D53: 0.95 | E53: -0.05 | F53: Σ < 100%
B54: 4 | C54: Краска NSF/UNI Cyan Blue (PB 15:3) TR VER 1.3 | D54: 0.965 | E54: -0.035 | F54: Σ < 100%
B55: 5 | C55: INK Orange (PO 34) LAM | D55: 0.98 | E55: -0.02 | F55: Σ < 100%
B56: 6 | C56: NSF/PC Magenta (PR 57:1) ГОТЭК | D56: 1.01 | E56: 0.01 | F56: Σ > 100%
B58: 🟠 3. ПОЛУПРОДУКТЫ БЕЗ РЕЦЕПТУРЫ — добавьте состав в лист «Рецептуры»
B60: № | C60: Полупродукт (нужна рецептура) | D60: Где числится
B61: 1 | C61: Extender 35 АФ | D61: Сырьё (помечено)
B62: 2 | C62: Extender A81 | D62: Сырьё (помечено)
B63: 3 | C63: Extender B-20 | D63: Сырьё (помечено)
B64: 4 | C64: Extender FX IPA | D64: Сырьё (помечено)
B65: 5 | C65: Extender Neocryl Resin | D65: Сырьё (помечено)
B66: 6 | C66: Extender TRIPOL 16 | D66: Сырьё (помечено)
B67: 7 | C67: Technical Extender B-20 | D67: Сырьё (помечено)
B68: 8 | C68: Technical Extender Normal 35 К | D68: Сырьё (помечено)
B69: 9 | C69: Technical Extender Normal L-K | D69: Сырьё (помечено)
B70: 10 | C70: Technical Extender SURF ROTO | D70: Сырьё (помечено)
B71: 11 | C71: Technical Extender UNI ЭЦ | D71: Сырьё (помечено)
B72: 12 | C72: Technical extender AL_RESIST | D72: Сырьё (помечено)
... B116: 56 | C116: покрывной лак (OVERPRINT VARNISH ) | D116: Сырьё (помечено)
B119: 💡 Используйте эту страницу как чек-лист. После заполнения цен в листе «Сырьё», строки в блоке 1 автоматически станут зачёркнутыми и зелёными. Для блока 2 — откройте лист «Рецептуры» и проверьте суммы. Блок 3 — добавьте рецептуры в лист «Рецептуры».

Sheet Калькулятор
T1: {=IF($I$14=0,$B$8,IFERROR(INDEX('Рецептуры'!$F:$F,MATCH($B$8&"|"&$I$14,'Рецептуры'!$K:$K,0)),$B$8))} -> Black (PBl 7) / RASTR
F2: КАЛЬКУЛЯТОР СЕБЕСТОИМОСТИ
F4: Многоуровневая рецептура · €/кг и ₽/кг · с НДС и без НДС
B7: 📦 ПРОДУКТ | F7: 🔖 АРТИКУЛ | G7: 🔎 ПОИСК ПО АРТИКУЛУ | J7: 💱 КУРС EUR / ₽
B8: Black (PBl 7) / RASTR | F8: {=IFERROR(IF(INDEX('Продукты'!$F:$F,MATCH($B$8,'Продукты'!$D:$D,0))=0,IF(INDEX('Полупродукты'!$F:$F,MATCH($B$8,'Полупродукты'!$C:$C,0))=0,"—",INDEX('Полупродукты'!$F:$F,MATCH($B$8,'Полупродукты'!$C:$C,0))),INDEX('Продукты'!$F:$F,MATCH($B$8,'Продукты'!$D:$D,0))),IFERROR(IF(INDEX('Полупродукты'!$F:$F,MATCH($B$8,'Полупродукты'!$C:$C,0))=0,"—",INDEX('Полупродукты'!$F:$F,MATCH($B$8,'Полупродукты'!$C:$C,0))),"—"))} -> — | H8: {=IF($G$8="","",IFERROR(INDEX('Продукты'!$D:$D,MATCH($G$8,'Продукты'!$F:$F,0)),IFERROR(INDEX('Полупродукты'!$C:$C,MATCH($G$8,'Полупродукты'!$F:$F,0)),"❌ артикул не найден")))} | J8: =IFERROR(LOOKUP(2,1/('Курсы ЦБ'!$C$7:$C$1000<>""),'Курсы ЦБ'!$C$7:$C$1000),100) -> 83.6892 | N8: 💼 МИНИ-КАЛЬКУЛЯТОР · ЦЕНА КЛИЕНТУ
B9: нажмите ▼ — выбор из списка | F9: автоматически по B8 | G9: ввод → | H9: ↑ скопируйте имя в B8 | J9: авто из «Курсы ЦБ» (можно перезаписать)
B10: ИТОГОВАЯ СЕБЕСТОИМОСТЬ · 1 КГ ГП | M10: 🔻 ПОТЕРИ
B11: =ROUND(K37,2) -> 3.12 | E11: =ROUND(K37*(1+0.22),2) -> 3.81 | G11: =ROUND(K37*$J$8,2) -> 261.11 | J11: =ROUND(K37*(1+0.22)*$J$8,2) -> 318.55
B12: €/кг без НДС | E12: €/кг с НДС | G12: ₽/кг без НДС | J12: ₽/кг с НДС | M12: ручной ввод, %
B13: =IF($B$8="","← Выберите продукт в B8","Продукт: "&$B$8&" | Артикул: "&$F$8&" | Σ%: "&TEXT($K$15,"0.00%")&IF($G$15<>""," | "&$G$15,"")) -> Продукт: Black (PBl 7) / RASTR | Артикул: — | Σ%: 100,00%
B14: 🔍 Раскрыть полупродукт — введите № строки: | I14: 0 | J14: (0 = основной продукт)
B15: Рецептура | I15: Σ %: | K15: =SUM(H17:H36) -> 1
B16: № | C16: Тип | D16: Компонент | E16: Раздел | F16: Ед. | G16: % ввод ручной | H16: % факт 100% | I16: Кол-во на 1 кг | J16: Цена €/кг база | K16: €/кг без НДС | L16: ₽/кг без НДС | M16: Пред. цена €/кг без НДС | N16: Статья | O16: €/кг с НДС | P16: ₽/кг с НДС
B17: 1 | C17: =IF(D17="","",IF(ISNUMBER(MATCH(D17,'Полупродукты'!$C$6:$C$62,0)),"⚗️ Полупр.","Сырьё")) -> Сырьё | D17: {=IFERROR(INDEX('Рецептуры'!$F:$F,MATCH($T$1&"|"&1,'Рецептуры'!$K:$K,0)),"")} -> Паста NSF/Paste Black (Pbk 7) КП 80 РАСТ | E17: =IF(D17="","","Материал основной") -> Материал основной | F17: =IF(D17="","","кг") -> кг | H17: {=IF(D17="","",IF(G17="",IFERROR(INDEX('Рецептуры'!$G:$G,MATCH($T$1&"|"&1,'Рецептуры'!$K:$K,0)),0),G17))} -> 0.78 | I17: =IF(D17="","",ROUND(H17*(1+IFERROR($M$11,0)),6)) -> 0.78 | J17: =IF(D17="","",IF(AND(M17<>"",M17>0),M17,IFERROR(VLOOKUP(D17,'Полупродукты'!$C$6:$E$62,3,FALSE()),IFERROR(VLOOKUP(D17,'Сырьё'!$C$6:$E$233,3,FALSE()),0)))) -> 3.6225 | K17: =IF(D17="","",ROUND(IFERROR(I17*J17,0),2)) -> 2.83 | L17: =IF(D17="","",ROUND(IFERROR(K17*$J$8,0),2)) -> 236.84 | N17: Себестоимость | O17: =E11 -> 3.81 | P17: =ROUND(O17*$J$8,2) -> 318.86
B18: 2 | C18: =IF(D18="","",IF(ISNUMBER(MATCH(D18,'Полупродукты'!$C$6:$C$62,0)),"⚗️ Полупр.","Сырьё")) -> ⚗️ Полупр. | D18: {=IFERROR(INDEX('Рецептуры'!$F:$F,MATCH($T$1&"|"&2,'Рецептуры'!$K:$K,0)),"")} -> Technical Extender UNI 397 | E18: =IF(D18="","","Материал основной") -> Материал основной | F18: =IF(D18="","","кг") -> кг | H18: {=IF(D18="","",IF(G18="",IFERROR(INDEX('Рецептуры'!$G:$G,MATCH($T$1&"|"&2,'Рецептуры'!$K:$K,0)),0),G18))} -> 0.12 | I18: =IF(D18="","",ROUND(H18*(1+IFERROR($M$11,0)),6)) -> 0.12 | J18: =IF(D18="","",IF(AND(M18<>"",M18>0),M18,IFERROR(VLOOKUP(D18,'Полупродукты'!$C$6:$E$62,3,FALSE()),IFERROR(VLOOKUP(D18,'Сырьё'!$C$6:$E$233,3,FALSE()),0)))) | K18: =IF(D18="","",ROUND(IFERROR(I18*J18,0),2)) -> 0 | L18: =IF(D18="","",ROUND(IFERROR(K18*$J$8,0),2)) -> 0 | N18: Доставка на 1 кг | O18: 0.12 | P18: =ROUND(O18*$J$8,2) -> 10.04
B19: 3 | C19: =IF(D19="","",IF(ISNUMBER(MATCH(D19,'Полупродукты'!$C$6:$C$62,0)),"⚗️ Полупр.","Сырьё")) -> ⚗️ Полупр. | D19: {=IFERROR(INDEX('Рецептуры'!$F:$F,MATCH($T$1&"|"&3,'Рецептуры'!$K:$K,0)),"")} -> Extender SL-2 ЭЦ | E19: =IF(D19="","","Материал основной") -> Материал основной | F19: =IF(D19="","","кг") -> кг | H19: {=IF(D19="","",IF(G19="",IFERROR(INDEX('Рецептуры'!$G:$G,MATCH($T$1&"|"&3,'Рецептуры'!$K:$K,0)),0),G19))} -> 0.05 | I19: =IF(D19="","",ROUND(H19*(1+IFERROR($M$11,0)),6)) -> 0.05 | J19: =IF(D19="","",IF(AND(M19<>"",M19>0),M19,IFERROR(VLOOKUP(D19,'Полупродукты'!$C$6:$E$62,3,FALSE()),IFERROR(VLOOKUP(D19,'Сырьё'!$C$6:$E$233,3,FALSE()),0)))) -> 2.7708 | K19: =IF(D19="","",ROUND(IFERROR(I19*J19,0),2)) -> 0.14 | L19: =IF(D19="","",ROUND(IFERROR(K19*$J$8,0),2)) -> 11.72 | N19: GM2 | O19: 0.65 | P19: =ROUND(O19*$J$8,2) -> 54.4
B20: 4 | C20: =IF(D20="","",IF(ISNUMBER(MATCH(D20,'Полупродукты'!$C$6:$C$62,0)),"⚗️ Полупр.","Сырьё")) -> Сырьё | D20: {=IFERROR(INDEX('Рецептуры'!$F:$F,MATCH($T$1&"|"&4,'Рецептуры'!$K:$K,0)),"")} -> TCA-IAM20 (аналог Титан АП 100/Титан АП 130 Д) | E20: =IF(D20="","","Материал основной") -> Материал основной | F20: =IF(D20="","","кг") -> кг | H20: {=IF(D20="","",IF(G20="",IFERROR(INDEX('Рецептуры'!$G:$G,MATCH($T$1&"|"&4,'Рецептуры'!$K:$K,0)),0),G20))} -> 0.005 | I20: =IF(D20="","",ROUND(H20*(1+IFERROR($M$11,0)),6)) -> 0.005 | J20: =IF(D20="","",IF(AND(M20<>"",M20>0),M20,IFERROR(VLOOKUP(D20,'Полупродукты'!$C$6:$E$62,3,FALSE()),IFERROR(VLOOKUP(D20,'Сырьё'!$C$6:$E$233,3,FALSE()),0)))) -> 14.556 | K20: =IF(D20="","",ROUND(IFERROR(I20*J20,0),2)) -> 0.07 | L20: =IF(D20="","",ROUND(IFERROR(K20*$J$8,0),2)) -> 5.86 | N20: КВ | O20: 0 | P20: =ROUND(O20*$J$8,2) -> 0
B21: 5 | C21: =IF(D21="","",IF(ISNUMBER(MATCH(D21,'Полупродукты'!$C$6:$C$62,0)),"⚗️ Полупр.","Сырьё")) -> Сырьё | D21: {=IFERROR(INDEX('Рецептуры'!$F:$F,MATCH($T$1&"|"&5,'Рецептуры'!$K:$K,0)),"")} -> Этилцеллозольв | E21: =IF(D21="","","Материал основной") -> Материал основной | F21: =IF(D21="","","кг") -> кг | H21: {=IF(D21="","",IF(G21="",IFERROR(INDEX('Рецептуры'!$G:$G,MATCH($T$1&"|"&5,'Рецептуры'!$K:$K,0)),0),G21))} -> 0.045 | I21: =IF(D21="","",ROUND(H21*(1+IFERROR($M$11,0)),6)) -> 0.045 | J21: =IF(D21="","",IF(AND(M21<>"",M21>0),M21,IFERROR(VLOOKUP(D21,'Полупродукты'!$C$6:$E$62,3,FALSE()),IFERROR(VLOOKUP(D21,'Сырьё'!$C$6:$E$233,3,FALSE()),0)))) -> 1.7145 | K21: =IF(D21="","",ROUND(IFERROR(I21*J21,0),2)) -> 0.08 | L21: =IF(D21="","",ROUND(IFERROR(K21*$J$8,0),2)) -> 6.7 | N21: Прочие расходы | O21: 0 | P21: =ROUND(O21*$J$8,2) -> 0
B22: 6 | C22: =IF(D22="","",IF(ISNUMBER(MATCH(D22,'Полупродукты'!$C$6:$C$62,0)),"⚗️ Полупр.","Сырьё")) | D22: {=IFERROR(INDEX('Рецептуры'!$F:$F,MATCH($T$1&"|"&6,'Рецептуры'!$K:$K,0)),"")} | E22: =IF(D22="","","Материал основной") | F22: =IF(D22="","","кг") | H22: {=IF(D22="","",IF(G22="",IFERROR(INDEX('Рецептуры'!$G:$G,MATCH($T$1&"|"&6,'Рецептуры'!$K:$K,0)),0),G22))} | I22: =IF(D22="","",ROUND(H22*(1+IFERROR($M$11,0)),6)) | J22: =IF(D22="","",IF(AND(M22<>"",M22>0),M22,IFERROR(VLOOKUP(D22,'Полупродукты'!$C$6:$E$62,3,FALSE()),IFERROR(VLOOKUP(D22,'Сырьё'!$C$6:$E$233,3,FALSE()),0)))) | K22: =IF(D22="","",ROUND(IFERROR(I22*J22,0),2)) | L22: =IF(D22="","",ROUND(IFERROR(K22*$J$8,0),2)) | N22: Полная стоимость | O22: =ROUND(SUM(O17:O21),2) -> 4.58 | P22: =ROUND(O22*$J$8,2) -> 383.3
B23: 7 | C23: =IF(D23="","",IF(ISNUMBER(MATCH(D23,'Полупродукты'!$C$6:$C$62,0)),"⚗️ Полупр.","Сырьё")) | D23: {=IFERROR(INDEX('Рецептуры'!$F:$F,MATCH($T$1&"|"&7,'Рецептуры'!$K:$K,0)),"")} | E23: =IF(D23="","","Материал основной") | F23: =IF(D23="","","кг") | H23: {=IF(D23="","",IF(G23="",IFERROR(INDEX('Рецептуры'!$G:$G,MATCH($T$1&"|"&7,'Рецептуры'!$K:$K,0)),0),G23))} | I23: =IF(D23="","",ROUND(H23*(1+IFERROR($M$11,0)),6)) | J23: =IF(D23="","",IF(AND(M23<>"",M23>0),M23,IFERROR(VLOOKUP(D23,'Полупродукты'!$C$6:$E$62,3,FALSE()),IFERROR(VLOOKUP(D23,'Сырьё'!$C$6:$E$233,3,FALSE()),0)))) | K23: =IF(D23="","",ROUND(IFERROR(I23*J23,0),2)) | L23: =IF(D23="","",ROUND(IFERROR(K23*$J$8,0),2)) | N23: Наценка, % | O23: 0 | P23: =ROUND(O22*O23*$J$8,2) -> 0
B24: 8 | C24: =IF(D24="","",IF(ISNUMBER(MATCH(D24,'Полупродукты'!$C$6:$C$62,0)),"⚗️ Полупр.","Сырьё")) | D24: {=IFERROR(INDEX('Рецептуры'!$F:$F,MATCH($T$1&"|"&8,'Рецептуры'!$K:$K,0)),"")} | E24: =IF(D24="","","Материал основной") | F24: =IF(D24="","","кг") | H24: {=IF(D24="","",IF(G24="",IFERROR(INDEX('Рецептуры'!$G:$G,MATCH($T$1&"|"&8,'Рецептуры'!$K:$K,0)),0),G24))} | I24: =IF(D24="","",ROUND(H24*(1+IFERROR($M$11,0)),6)) | J24: =IF(D24="","",IF(AND(M24<>"",M24>0),M24,IFERROR(VLOOKUP(D24,'Полупродукты'!$C$6:$E$62,3,FALSE()),IFERROR(VLOOKUP(D24,'Сырьё'!$C$6:$E$233,3,FALSE()),0)))) | K24: =IF(D24="","",ROUND(IFERROR(I24*J24,0),2)) | L24: =IF(D24="","",ROUND(IFERROR(K24*$J$8,0),2)) | N24: Наценка, € | O24: =ROUND(O22*O23,2) -> 0 | P24: =ROUND(O24*$J$8,2) -> 0
B25: 9 | C25: =IF(D25="","",IF(ISNUMBER(MATCH(D25,'Полупродукты'!$C$6:$C$62,0)),"⚗️ Полупр.","Сырьё")) | D25: {=IFERROR(INDEX('Рецептуры'!$F:$F,MATCH($T$1&"|"&9,'Рецептуры'!$K:$K,0)),"")} | E25: =IF(D25="","","Материал основной") | F25: =IF(D25="","","кг") | H25: {=IF(D25="","",IF(G25="",IFERROR(INDEX('Рецептуры'!$G:$G,MATCH($T$1&"|"&9,'Рецептуры'!$K:$K,0)),0),G25))} | I25: =IF(D25="","",ROUND(H25*(1+IFERROR($M$11,0)),6)) | J25: =IF(D25="","",IF(AND(M25<>"",M25>0),M25,IFERROR(VLOOKUP(D25,'Полупродукты'!$C$6:$E$62,3,FALSE()),IFERROR(VLOOKUP(D25,'Сырьё'!$C$6:$E$233,3,FALSE()),0)))) | K25: =IF(D25="","",ROUND(IFERROR(I25*J25,0),2)) | L25: =IF(D25="","",ROUND(IFERROR(K25*$J$8,0),2))
B26: 10 | C26: =IF(D26="","",IF(ISNUMBER(MATCH(D26,'Полупродукты'!$C$6:$C$62,0)),"⚗️ Полупр.","Сырьё")) | D26: {=IFERROR(INDEX('Рецептуры'!$F:$F,MATCH($T$1&"|"&10,'Рецептуры'!$K:$K,0)),"")} | E26: =IF(D26="","","Материал основной") | F26: =IF(D26="","","кг") | H26: {=IF(D26="","",IF(G26="",IFERROR(INDEX('Рецептуры'!$G:$G,MATCH($T$1&"|"&10,'Рецептуры'!$K:$K,0)),0),G26))} | I26: =IF(D26="","",ROUND(H26*(1+IFERROR($M$11,0)),6)) | J26: =IF(D26="","",IF(AND(M26<>"",M26>0),M26,IFERROR(VLOOKUP(D26,'Полупродукты'!$C$6:$E$62,3,FALSE()),IFERROR(VLOOKUP(D26,'Сырьё'!$C$6:$E$233,3,FALSE()),0)))) | K26: =IF(D26="","",ROUND(IFERROR(I26*J26,0),2)) | L26: =IF(D26="","",ROUND(IFERROR(K26*$J$8,0),2)) | N26: ЦЕНА ДЛЯ КЛИЕНТА
B27: 11 | C27: =IF(D27="","",IF(ISNUMBER(MATCH(D27,'Полупродукты'!$C$6:$C$62,0)),"⚗️ Полупр.","Сырьё")) | D27: {=IFERROR(INDEX('Рецептуры'!$F:$F,MATCH($T$1&"|"&11,'Рецептуры'!$K:$K,0)),"")} | E27: =IF(D27="","","Материал основной") | F27: =IF(D27="","","кг") | H27: {=IF(D27="","",IF(G27="",IFERROR(INDEX('Рецептуры'!$G:$G,MATCH($T$1&"|"&11,'Рецептуры'!$K:$K,0)),0),G27))} | I27: =IF(D27="","",ROUND(H27*(1+IFERROR($M$11,0)),6)) | J27: =IF(D27="","",IF(AND(M27<>"",M27>0),M27,IFERROR(VLOOKUP(D27,'Полупродукты'!$C$6:$E$62,3,FALSE()),IFERROR(VLOOKUP(D27,'Сырьё'!$C$6:$E$233,3,FALSE()),0)))) | K27: =IF(D27="","",ROUND(IFERROR(I27*J27,0),2)) | L27: =IF(D27="","",ROUND(IFERROR(K27*$J$8,0),2)) | N27: с НДС | O27: =ROUND(O22*(1+O23),2) -> 4.58 | P27: =ROUND(O27*$J$8,2) -> 383.3
B28: 12 | C28: =IF(D28="","",IF(ISNUMBER(MATCH(D28,'Полупродукты'!$C$6:$C$62,0)),"⚗️ Полупр.","Сырьё")) | D28: {=IFERROR(INDEX('Рецептуры'!$F:$F,MATCH($T$1&"|"&12,'Рецептуры'!$K:$K,0)),"")} | E28: =IF(D28="","","Материал основной") | F28: =IF(D28="","","кг") | H28: {=IF(D28="","",IF(G28="",IFERROR(INDEX('Рецептуры'!$G:$G,MATCH($T$1&"|"&12,'Рецептуры'!$K:$K,0)),0),G28))} | I28: =IF(D28="","",ROUND(H28*(1+IFERROR($M$11,0)),6)) | J28: =IF(D28="","",IF(AND(M28<>"",M28>0),M28,IFERROR(VLOOKUP(D28,'Полупродукты'!$C$6:$E$62,3,FALSE()),IFERROR(VLOOKUP(D28,'Сырьё'!$C$6:$E$233,3,FALSE()),0)))) | K28: =IF(D28="","",ROUND(IFERROR(I28*J28,0),2)) | L28: =IF(D28="","",ROUND(IFERROR(K28*$J$8,0),2)) | N28: без НДС | O28: =ROUND(O27/(1+0.22),2) -> 3.75 | P28: =ROUND(O28*$J$8,2) -> 313.83
B29: 13 | C29: =IF(D29="","",IF(ISNUMBER(MATCH(D29,'Полупродукты'!$C$6:$C$62,0)),"⚗️ Полупр.","Сырьё")) | D29: {=IFERROR(INDEX('Рецептуры'!$F:$F,MATCH($T$1&"|"&13,'Рецептуры'!$K:$K,0)),"")} | E29: =IF(D29="","","Материал основной") | F29: =IF(D29="","","кг") | H29: {=IF(D29="","",IF(G29="",IFERROR(INDEX('Рецептуры'!$G:$G,MATCH($T$1&"|"&13,'Рецептуры'!$K:$K,0)),0),G29))} | I29: =IF(D29="","",ROUND(H29*(1+IFERROR($M$11,0)),6)) | J29: =IF(D29="","",IF(AND(M29<>"",M29>0),M29,IFERROR(VLOOKUP(D29,'Полупродукты'!$C$6:$E$62,3,FALSE()),IFERROR(VLOOKUP(D29,'Сырьё'!$C$6:$E$233,3,FALSE()),0)))) | K29: =IF(D29="","",ROUND(IFERROR(I29*J29,0),2)) | L29: =IF(D29="","",ROUND(IFERROR(K29*$J$8,0),2))
B30: 14 | C30: =IF(D30="","",IF(ISNUMBER(MATCH(D30,'Полупродукты'!$C$6:$C$62,0)),"⚗️ Полупр.","Сырьё")) | D30: {=IFERROR(INDEX('Рецептуры'!$F:$F,MATCH($T$1&"|"&14,'Рецептуры'!$K:$K,0)),"")} | E30: =IF(D30="","","Материал основной") | F30: =IF(D30="","","кг") | H30: {=IF(D30="","",IF(G30="",IFERROR(INDEX('Рецептуры'!$G:$G,MATCH($T$1&"|"&14,'Рецептуры'!$K:$K,0)),0),G30))} | I30: =IF(D30="","",ROUND(H30*(1+IFERROR($M$11,0)),6)) | J30: =IF(D30="","",IF(AND(M30<>"",M30>0),M30,IFERROR(VLOOKUP(D30,'Полупродукты'!$C$6:$E$62,3,FALSE()),IFERROR(VLOOKUP(D30,'Сырьё'!$C$6:$E$233,3,FALSE()),0)))) | K30: =IF(D30="","",ROUND(IFERROR(I30*J30,0),2)) | L30: =IF(D30="","",ROUND(IFERROR(K30*$J$8,0),2))
B31: 15 | C31: =IF(D31="","",IF(ISNUMBER(MATCH(D31,'Полупродукты'!$C$6:$C$62,0)),"⚗️ Полупр.","Сырьё")) | D31: {=IFERROR(INDEX('Рецептуры'!$F:$F,MATCH($T$1&"|"&15,'Рецептуры'!$K:$K,0)),"")} | E31: =IF(D31="","","Материал основной") | F31: =IF(D31="","","кг") | H31: {=IF(D31="","",IF(G31="",IFERROR(INDEX('Рецептуры'!$G:$G,MATCH($T$1&"|"&15,'Рецептуры'!$K:$K,0)),0),G31))} | I31: =IF(D31="","",ROUND(H31*(1+IFERROR($M$11,0)),6)) | J31: =IF(D31="","",IF(AND(M31<>"",M31>0),M31,IFERROR(VLOOKUP(D31,'Полупродукты'!$C$6:$E$62,3,FALSE()),IFERROR(VLOOKUP(D31,'Сырьё'!$C$6:$E$233,3,FALSE()),0)))) | K31: =IF(D31="","",ROUND(IFERROR(I31*J31,0),2)) | L31: =IF(D31="","",ROUND(IFERROR(K31*$J$8,0),2))
B32: 16 | C32: =IF(D32="","",IF(ISNUMBER(MATCH(D32,'Полупродукты'!$C$6:$C$62,0)),"⚗️ Полупр.","Сырьё")) | D32: {=IFERROR(INDEX('Рецептуры'!$F:$F,MATCH($T$1&"|"&16,'Рецептуры'!$K:$K,0)),"")} | E32: =IF(D32="","","Материал основной") | F32: =IF(D32="","","кг") | H32: {=IF(D32="","",IF(G32="",IFERROR(INDEX('Рецептуры'!$G:$G,MATCH($T$1&"|"&16,'Рецептуры'!$K:$K,0)),0),G32))} | I32: =IF(D32="","",ROUND(H32*(1+IFERROR($M$11,0)),6)) | J32: =IF(D32="","",IF(AND(M32<>"",M32>0),M32,IFERROR(VLOOKUP(D32,'Полупродукты'!$C$6:$E$62,3,FALSE()),IFERROR(VLOOKUP(D32,'Сырьё'!$C$6:$E$233,3,FALSE()),0)))) | K32: =IF(D32="","",ROUND(IFERROR(I32*J32,0),2)) | L32: =IF(D32="","",ROUND(IFERROR(K32*$J$8,0),2))
B33: 17 | C33: =IF(D33="","",IF(ISNUMBER(MATCH(D33,'Полупродукты'!$C$6:$C$62,0)),"⚗️ Полупр.","Сырьё")) | D33: {=IFERROR(INDEX('Рецептуры'!$F:$F,MATCH($T$1&"|"&17,'Рецептуры'!$K:$K,0)),"")} | E33: =IF(D33="","","Материал основной") | F33: =IF(D33="","","кг") | H33: {=IF(D33="","",IF(G33="",IFERROR(INDEX('Рецептуры'!$G:$G,MATCH($T$1&"|"&17,'Рецептуры'!$K:$K,0)),0),G33))} | I33: =IF(D33="","",ROUND(H33*(1+IFERROR($M$11,0)),6)) | J33: =IF(D33="","",IF(AND(M33<>"",M33>0),M33,IFERROR(VLOOKUP(D33,'Полупродукты'!$C$6:$E$62,3,FALSE()),IFERROR(VLOOKUP(D33,'Сырьё'!$C$6:$E$233,3,FALSE()),0)))) | K33: =IF(D33="","",ROUND(IFERROR(I33*J33,0),2)) | L33: =IF(D33="","",ROUND(IFERROR(K33*$J$8,0),2))
B34: 18 | C34: =IF(D34="","",IF(ISNUMBER(MATCH(D34,'Полупродукты'!$C$6:$C$62,0)),"⚗️ Полупр.","Сырьё")) | D34: {=IFERROR(INDEX('Рецептуры'!$F:$F,MATCH($T$1&"|"&18,'Рецептуры'!$K:$K,0)),"")} | E34: =IF(D34="","","Материал основной") | F34: =IF(D34="","","кг") | H34: {=IF(D34="","",IF(G34="",IFERROR(INDEX('Рецептуры'!$G:$G,MATCH($T$1&"|"&18,'Рецептуры'!$K:$K,0)),0),G34))} | I34: =IF(D34="","",ROUND(H34*(1+IFERROR($M$11,0)),6)) | J34: =IF(D34="","",IF(AND(M34<>"",M34>0),M34,IFERROR(VLOOKUP(D34,'Полупродукты'!$C$6:$E$62,3,FALSE()),IFERROR(VLOOKUP(D34,'Сырьё'!$C$6:$E$233,3,FALSE()),0)))) | K34: =IF(D34="","",ROUND(IFERROR(I34*J34,0),2)) | L34: =IF(D34="","",ROUND(IFERROR(K34*$J$8,0),2))
B35: 19 | C35: =IF(D35="","",IF(ISNUMBER(MATCH(D35,'Полупродукты'!$C$6:$C$62,0)),"⚗️ Полупр.","Сырьё")) | D35: {=IFERROR(INDEX('Рецептуры'!$F:$F,MATCH($T$1&"|"&19,'Рецептуры'!$K:$K,0)),"")} | E35: =IF(D35="","","Материал основной") | F35: =IF(D35="","","кг") | H35: {=IF(D35="","",IF(G35="",IFERROR(INDEX('Рецептуры'!$G:$G,MATCH($T$1&"|"&19,'Рецептуры'!$K:$K,0)),0),G35))} | I35: =IF(D35="","",ROUND(H35*(1+IFERROR($M$11,0)),6)) | J35: =IF(D35="","",IF(AND(M35<>"",M35>0),M35,IFERROR(VLOOKUP(D35,'Полупродукты'!$C$6:$E$62,3,FALSE()),IFERROR(VLOOKUP(D35,'Сырьё'!$C$6:$E$233,3,FALSE()),0)))) | K35: =IF(D35="","",ROUND(IFERROR(I35*J35,0),2)) | L35: =IF(D35="","",ROUND(IFERROR(K35*$J$8,0),2))
B36: 20 | C36: =IF(D36="","",IF(ISNUMBER(MATCH(D36,'Полупродукты'!$C$6:$C$62,0)),"⚗️ Полупр.","Сырьё")) | D36: {=IFERROR(INDEX('Рецептуры'!$F:$F,MATCH($T$1&"|"&20,'Рецептуры'!$K:$K,0)),"")} | E36: =IF(D36="","","Материал основной") | F36: =IF(D36="","","кг") | H36: {=IF(D36="","",IF(G36="",IFERROR(INDEX('Рецептуры'!$G:$G,MATCH($T$1&"|"&20,'Рецептуры'!$K:$K,0)),0),G36))} | I36: =IF(D36="","",ROUND(H36*(1+IFERROR($M$11,0)),6)) | J36: =IF(D36="","",IF(AND(M36<>"",M36>0),M36,IFERROR(VLOOKUP(D36,'Полупродукты'!$C$6:$E$62,3,FALSE()),IFERROR(VLOOKUP(D36,'Сырьё'!$C$6:$E$233,3,FALSE()),0)))) | K36: =IF(D36="","",ROUND(IFERROR(I36*J36,0),2)) | L36: =IF(D36="","",ROUND(IFERROR(K36*$J$8,0),2))
B37: Σ ИТОГО | H37: =SUM(H17:H36) -> 1 | K37: =ROUND(SUM(K17:K36),2) -> 3.12 | L37: =ROUND(SUM(L17:L36),2) -> 261.12
B39: =IF($I$14=0,"⬇ Чтобы увидеть состав полупродукта — введите № его строки в желтую ячейку справа от 🔍","🔬 Состав полупродукта: "&$T$1) -> ⬇ Чтобы увидеть состав полупродукта — введите № его строки в желтую ячейку справа от 🔍
B40: № | C40: Тип | D40: Компонент | E40: Раздел | F40: Ед. | H40: % массы | I40: Кол-во на 1 кг | J40: Цена €/кг база | K40: €/кг без НДС | L40: ₽/кг без НДС
B41: =IF($I$14=0,"",1) | C41: =IF(OR($I$14=0,D41=""),"",IF(ISNUMBER(MATCH(D41,'Полупродукты'!$C$6:$C$62,0)),"⚗️ Полупр.","Сырьё")) | D41: {=IF($I$14=0,"",IFERROR(INDEX('Рецептуры'!$F:$F,MATCH($T$1&"|"&1,'Рецептуры'!$K:$K,0)),""))} | E41: =IF(D41="","","Материал основной") | F41: =IF(D41="","","кг") | H41: {=IF(OR($I$14=0,D41=""),"",IFERROR(INDEX('Рецептуры'!$G:$G,MATCH($T$1&"|"&1,'Рецептуры'!$K:$K,0)),0))} | I41: =IF(OR($I$14=0,D41=""),"",IFERROR(H41,0)) | J41: =IF(OR($I$14=0,D41=""),"",IFERROR(VLOOKUP(D41,'Полупродукты'!$C$6:$E$62,3,FALSE()),IFERROR(VLOOKUP(D41,'Сырьё'!$C$6:$E$233,3,FALSE()),0))) | K41: =IF(OR($I$14=0,D41=""),"",ROUND(IFERROR(I41*J41,0),2)) | L41: =IF(OR($I$14=0,D41=""),"",ROUND(IFERROR(K41*$J$8,0),2))
B42: =IF($I$14=0,"",2) | C42: =IF(OR($I$14=0,D42=""),"",IF(ISNUMBER(MATCH(D42,'Полупродукты'!$C$6:$C$62,0)),"⚗️ Полупр.","Сырьё")) | D42: {=IF($I$14=0,"",IFERROR(INDEX('Рецептуры'!$F:$F,MATCH($T$1&"|"&2,'Рецептуры'!$K:$K,0)),""))} | E42: =IF(D42="","","Материал основной") | F42: =IF(D42="","","кг") | H42: {=IF(OR($I$14=0,D42=""),"",IFERROR(INDEX('Рецептуры'!$G:$G,MATCH($T$1&"|"&2,'Рецептуры'!$K:$K,0)),0))} | I42: =IF(OR($I$14=0,D42=""),"",IFERROR(H42,0)) | J42: =IF(OR($I$14=0,D42=""),"",IFERROR(VLOOKUP(D42,'Полупродукты'!$C$6:$E$62,3,FALSE()),IFERROR(VLOOKUP(D42,'Сырьё'!$C$6:$E$233,3,FALSE()),0))) | K42: =IF(OR($I$14=0,D42=""),"",ROUND(IFERROR(I42*J42,0),2)) | L42: =IF(OR($I$14=0,D42=""),"",ROUND(IFERROR(K42*$J$8,0),2))
B43: =IF($I$14=0,"",3) | C43: =IF(OR($I$14=0,D43=""),"",IF(ISNUMBER(MATCH(D43,'Полупродукты'!$C$6:$C$62,0)),"⚗️ Полупр.","Сырьё")) | D43: {=IF($I$14=0,"",IFERROR(INDEX('Рецептуры'!$F:$F,MATCH($T$1&"|"&3,'Рецептуры'!$K:$K,0)),""))} | E43: =IF(D43="","","Материал основной") | F43: =IF(D43="","","кг") | H43: {=IF(OR($I$14=0,D43=""),"",IFERROR(INDEX('Рецептуры'!$G:$G,MATCH($T$1&"|"&3,'Рецептуры'!$K:$K,0)),0))} | I43: =IF(OR($I$14=0,D43=""),"",IFERROR(H43,0)) | J43: =IF(OR($I$14=0,D43=""),"",IFERROR(VLOOKUP(D43,'Полупродукты'!$C$6:$E$62,3,FALSE()),IFERROR(VLOOKUP(D43,'Сырьё'!$C$6:$E$233,3,FALSE()),0))) | K43: =IF(OR($I$14=0,D43=""),"",ROUND(IFERROR(I43*J43,0),2)) | L43: =IF(OR($I$14=0,D43=""),"",ROUND(IFERROR(K43*$J$8,0),2))
B44: =IF($I$14=0,"",4) | C44: =IF(OR($I$14=0,D44=""),"",IF(ISNUMBER(MATCH(D44,'Полупродукты'!$C$6:$C$62,0)),"⚗️ Полупр.","Сырьё")) | D44: {=IF($I$14=0,"",IFERROR(INDEX('Рецептуры'!$F:$F,MATCH($T$1&"|"&4,'Рецептуры'!$K:$K,0)),""))} | E44: =IF(D44="","","Материал основной") | F44: =IF(D44="","","кг") | H44: {=IF(OR($I$14=0,D44=""),"",IFERROR(INDEX('Рецептуры'!$G:$G,MATCH($T$1&"|"&4,'Рецептуры'!$K:$K,0)),0))} | I44: =IF(OR($I$14=0,D44=""),"",IFERROR(H44,0)) | J44: =IF(OR($I$14=0,D44=""),"",IFERROR(VLOOKUP(D44,'Полупродукты'!$C$6:$E$62,3,FALSE()),IFERROR(VLOOKUP(D44,'Сырьё'!$C$6:$E$233,3,FALSE()),0))) | K44: =IF(OR($I$14=0,D44=""),"",ROUND(IFERROR(I44*J44,0),2)) | L44: =IF(OR($I$14=0,D44=""),"",ROUND(IFERROR(K44*$J$8,0),2))
B45: =IF($I$14=0,"",5) | C45: =IF(OR($I$14=0,D45=""),"",IF(ISNUMBER(MATCH(D45,'Полупродукты'!$C$6:$C$62,0)),"⚗️ Полупр.","Сырьё")) | D45: {=IF($I$14=0,"",IFERROR(INDEX('Рецептуры'!$F:$F,MATCH($T$1&"|"&5,'Рецептуры'!$K:$K,0)),""))} | E45: =IF(D45="","","Материал основной") | F45: =IF(D45="","","кг") | H45: {=IF(OR($I$14=0,D45=""),"",IFERROR(INDEX('Рецептуры'!$G:$G,MATCH($T$1&"|"&5,'Рецептуры'!$K:$K,0)),0))} | I45: =IF(OR($I$14=0,D45=""),"",IFERROR(H45,0)) | J45: =IF(OR($I$14=0,D45=""),"",IFERROR(VLOOKUP(D45,'Полупродукты'!$C$6:$E$62,3,FALSE()),IFERROR(VLOOKUP(D45,'Сырьё'!$C$6:$E$233,3,FALSE()),0))) | K45: =IF(OR($I$14=0,D45=""),"",ROUND(IFERROR(I45*J45,0),2)) | L45: =IF(OR($I$14=0,D45=""),"",ROUND(IFERROR(K45*$J$8,0),2))
B46: =IF($I$14=0,"",6) | C46: =IF(OR($I$14=0,D46=""),"",IF(ISNUMBER(MATCH(D46,'Полупродукты'!$C$6:$C$62,0)),"⚗️ Полупр.","Сырьё")) | D46: {=IF($I$14=0,"",IFERROR(INDEX('Рецептуры'!$F:$F,MATCH($T$1&"|"&6,'Рецептуры'!$K:$K,0)),""))} | E46: =IF(D46="","","Материал основной") | F46: =IF(D46="","","кг") | H46: {=IF(OR($I$14=0,D46=""),"",IFERROR(INDEX('Рецептуры'!$G:$G,MATCH($T$1&"|"&6,'Рецептуры'!$K:$K,0)),0))} | I46: =IF(OR($I$14=0,D46=""),"",IFERROR(H46,0)) | J46: =IF(OR($I$14=0,D46=""),"",IFERROR(VLOOKUP(D46,'Полупродукты'!$C$6:$E$62,3,FALSE()),IFERROR(VLOOKUP(D46,'Сырьё'!$C$6:$E$233,3,FALSE()),0))) | K46: =IF(OR($I$14=0,D46=""),"",ROUND(IFERROR(I46*J46,0),2)) | L46: =IF(OR($I$14=0,D46=""),"",ROUND(IFERROR(K46*$J$8,0),2))
B47: =IF($I$14=0,"",7) | C47: =IF(OR($I$14=0,D47=""),"",IF(ISNUMBER(MATCH(D47,'Полупродукты'!$C$6:$C$62,0)),"⚗️ Полупр.","Сырьё")) | D47: {=IF($I$14=0,"",IFERROR(INDEX('Рецептуры'!$F:$F,MATCH($T$1&"|"&7,'Рецептуры'!$K:$K,0)),""))} | E47: =IF(D47="","","Материал основной") | F47: =IF(D47="","","кг") | H47: {=IF(OR($I$14=0,D47=""),"",IFERROR(INDEX('Рецептуры'!$G:$G,MATCH($T$1&"|"&7,'Рецептуры'!$K:$K,0)),0))} | I47: =IF(OR($I$14=0,D47=""),"",IFERROR(H47,0)) | J47: =IF(OR($I$14=0,D47=""),"",IFERROR(VLOOKUP(D47,'Полупродукты'!$C$6:$E$62,3,FALSE()),IFERROR(VLOOKUP(D47,'Сырьё'!$C$6:$E$233,3,FALSE()),0))) | K47: =IF(OR($I$14=0,D47=""),"",ROUND(IFERROR(I47*J47,0),2)) | L47: =IF(OR($I$14=0,D47=""),"",ROUND(IFERROR(K47*$J$8,0),2))
B48: =IF($I$14=0,"",8) | C48: =IF(OR($I$14=0,D48=""),"",IF(ISNUMBER(MATCH(D48,'Полупродукты'!$C$6:$C$62,0)),"⚗️ Полупр.","Сырьё")) | D48: {=IF($I$14=0,"",IFERROR(INDEX('Рецептуры'!$F:$F,MATCH($T$1&"|"&8,'Рецептуры'!$K:$K,0)),""))} | E48: =IF(D48="","","Материал основной") | F48: =IF(D48="","","кг") | H48: {=IF(OR($I$14=0,D48=""),"",IFERROR(INDEX('Рецептуры'!$G:$G,MATCH($T$1&"|"&8,'Рецептуры'!$K:$K,0)),0))} | I48: =IF(OR($I$14=0,D48=""),"",IFERROR(H48,0)) | J48: =IF(OR($I$14=0,D48=""),"",IFERROR(VLOOKUP(D48,'Полупродукты'!$C$6:$E$62,3,FALSE()),IFERROR(VLOOKUP(D48,'Сырьё'!$C$6:$E$233,3,FALSE()),0))) | K48: =IF(OR($I$14=0,D48=""),"",ROUND(IFERROR(I48*J48,0),2)) | L48: =IF(OR($I$14=0,D48=""),"",ROUND(IFERROR(K48*$J$8,0),2))
B49: =IF($I$14=0,"",9) | C49: =IF(OR($I$14=0,D49=""),"",IF(ISNUMBER(MATCH(D49,'Полупродукты'!$C$6:$C$62,0)),"⚗️ Полупр.","Сырьё")) | D49: {=IF($I$14=0,"",IFERROR(INDEX('Рецептуры'!$F:$F,MATCH($T$1&"|"&9,'Рецептуры'!$K:$K,0)),""))} | E49: =IF(D49="","","Материал основной") | F49: =IF(D49="","","кг") | H49: {=IF(OR($I$14=0,D49=""),"",IFERROR(INDEX('Рецептуры'!$G:$G,MATCH($T$1&"|"&9,'Рецептуры'!$K:$K,0)),0))} | I49: =IF(OR($I$14=0,D49=""),"",IFERROR(H49,0)) | J49: =IF(OR($I$14=0,D49=""),"",IFERROR(VLOOKUP(D49,'Полупродукты'!$C$6:$E$62,3,FALSE()),IFERROR(VLOOKUP(D49,'Сырьё'!$C$6:$E$233,3,FALSE()),0))) | K49: =IF(OR($I$14=0,D49=""),"",ROUND(IFERROR(I49*J49,0),2)) | L49: =IF(OR($I$14=0,D49=""),"",ROUND(IFERROR(K49*$J$8,0),2))
B50: =IF($I$14=0,"",10) | C50: =IF(OR($I$14=0,D50=""),"",IF(ISNUMBER(MATCH(D50,'Полупродукты'!$C$6:$C$62,0)),"⚗️ Полупр.","Сырьё")) | D50: {=IF($I$14=0,"",IFERROR(INDEX('Рецептуры'!$F:$F,MATCH($T$1&"|"&10,'Рецептуры'!$K:$K,0)),""))} | E50: =IF(D50="","","Материал основной") | F50: =IF(D50="","","кг") | H50: {=IF(OR($I$14=0,D50=""),"",IFERROR(INDEX('Рецептуры'!$G:$G,MATCH($T$1&"|"&10,'Рецептуры'!$K:$K,0)),0))} | I50: =IF(OR($I$14=0,D50=""),"",IFERROR(H50,0)) | J50: =IF(OR($I$14=0,D50=""),"",IFERROR(VLOOKUP(D50,'Полупродукты'!$C$6:$E$62,3,FALSE()),IFERROR(VLOOKUP(D50,'Сырьё'!$C$6:$E$233,3,FALSE()),0))) | K50: =IF(OR($I$14=0,D50=""),"",ROUND(IFERROR(I50*J50,0),2)) | L50: =IF(OR($I$14=0,D50=""),"",ROUND(IFERROR(K50*$J$8,0),2))
B51: =IF($I$14=0,"",11) | C51: =IF(OR($I$14=0,D51=""),"",IF(ISNUMBER(MATCH(D51,'Полупродукты'!$C$6:$C$62,0)),"⚗️ Полупр.","Сырьё")) | D51: {=IF($I$14=0,"",IFERROR(INDEX('Рецептуры'!$F:$F,MATCH($T$1&"|"&11,'Рецептуры'!$K:$K,0)),""))} | E51: =IF(D51="","","Материал основной") | F51: =IF(D51="","","кг") | H51: {=IF(OR($I$14=0,D51=""),"",IFERROR(INDEX('Рецептуры'!$G:$G,MATCH($T$1&"|"&11,'Рецептуры'!$K:$K,0)),0))} | I51: =IF(OR($I$14=0,D51=""),"",IFERROR(H51,0)) | J51: =IF(OR($I$14=0,D51=""),"",IFERROR(VLOOKUP(D51,'Полупродукты'!$C$6:$E$62,3,FALSE()),IFERROR(VLOOKUP(D51,'Сырьё'!$C$6:$E$233,3,FALSE()),0))) | K51: =IF(OR($I$14=0,D51=""),"",ROUND(IFERROR(I51*J51,0),2)) | L51: =IF(OR($I$14=0,D51=""),"",ROUND(IFERROR(K51*$J$8,0),2))
B52: =IF($I$14=0,"",12) | C52: =IF(OR($I$14=0,D52=""),"",IF(ISNUMBER(MATCH(D52,'Полупродукты'!$C$6:$C$62,0)),"⚗️ Полупр.","Сырьё")) | D52: {=IF($I$14=0,"",IFERROR(INDEX('Рецептуры'!$F:$F,MATCH($T$1&"|"&12,'Рецептуры'!$K:$K,0)),""))} | E52: =IF(D52="","","Материал основной") | F52: =IF(D52="","","кг") | H52: {=IF(OR($I$14=0,D52=""),"",IFERROR(INDEX('Рецептуры'!$G:$G,MATCH($T$1&"|"&12,'Рецептуры'!$K:$K,0)),0))} | I52: =IF(OR($I$14=0,D52=""),"",IFERROR(H52,0)) | J52: =IF(OR($I$14=0,D52=""),"",IFERROR(VLOOKUP(D52,'Полупродукты'!$C$6:$E$62,3,FALSE()),IFERROR(VLOOKUP(D52,'Сырьё'!$C$6:$E$233,3,FALSE()),0))) | K52: =IF(OR($I$14=0,D52=""),"",ROUND(IFERROR(I52*J52,0),2)) | L52: =IF(OR($I$14=0,D52=""),"",ROUND(IFERROR(K52*$J$8,0),2))
B53: Σ | H53: =IF($I$14=0,"",SUM(H41:H52)) | K53: =IF($I$14=0,"",ROUND(SUM(K41:K52),2)) | L53: =IF($I$14=0,"",ROUND(SUM(L41:L52),2))
B55: 💡 Розовые строки = полупродукты, зелёные = тара (📦). G (потери) — авто из «Потери», N (пред. цена €/кг) — ручной ввод подменяет K. K8 (курс) — авто из «Курсы ЦБ», можно перезаписать. Σ% (L15): 🟢 ≈100%, 🔴 >100%. См. лист «⚠️ Что заполнить» для проблем с данными.

Sheet Калькулятор X
F2: КАЛЬКУЛЯТОР X · НОВЫЕ ПРОДУКТЫ
F4: Произвольный состав · компоненты и проценты вводятся вручную
B7: 📦 ПРОДУКТ | F7: 🔖 АРТИКУЛ | G7: 🔎 ПОИСК ПО АРТИКУЛУ | J7: 💱 КУРС EUR / ₽
B8: INK Magenta (PR 57:1) гу | F8: {=IFERROR(IF(INDEX('Продукты'!$F:$F,MATCH($B$8,'Продукты'!$D:$D,0))=0,IF(INDEX('Полупродукты'!$F:$F,MATCH($B$8,'Полупродукты'!$C:$C,0))=0,"—",INDEX('Полупродукты'!$F:$F,MATCH($B$8,'Полупродукты'!$C:$C,0))),INDEX('Продукты'!$F:$F,MATCH($B$8,'Продукты'!$D:$D,0))),IFERROR(IF(INDEX('Полупродукты'!$F:$F,MATCH($B$8,'Полупродукты'!$C:$C,0))=0,"—",INDEX('Полупродукты'!$F:$F,MATCH($B$8,'Полупродукты'!$C:$C,0))),"—"))} -> — | H8: {=IF($G$8="","",IFERROR(INDEX('Продукты'!$D:$D,MATCH($G$8,'Продукты'!$F:$F,0)),IFERROR(INDEX('Полупродукты'!$C:$C,MATCH($G$8,'Полупродукты'!$F:$F,0)),"❌ артикул не найден")))} | J8: =IFERROR(LOOKUP(2,1/('Курсы ЦБ'!$C$7:$C$1000<>""),'Курсы ЦБ'!$C$7:$C$1000),100) -> 83.6892 | N8: 💼 МИНИ-КАЛЬКУЛЯТОР · ЦЕНА КЛИЕНТУ
B9: состав вводится вручную ниже | F9: автоматически по B8 | G9: ввод → | H9: ↑ скопируйте имя в B8 | J9: авто из «Курсы ЦБ» (можно перезаписать)
B10: ИТОГОВАЯ СЕБЕСТОИМОСТЬ · 1 КГ ГП | M10: 🔻 ПОТЕРИ
B11: =ROUND(K37,2) -> 0 | E11: =ROUND(K37*(1+0.22),2) -> 0 | G11: =ROUND(K37*$J$8,2) -> 0 | J11: =ROUND(K37*(1+0.22)*$J$8,2) -> 0
B12: €/кг без НДС | E12: €/кг с НДС | G12: ₽/кг без НДС | J12: ₽/кг с НДС | M12: ручной ввод, %
B13: =IF($B$8="","← Выберите продукт в B8","Продукт: "&$B$8&" | Артикул: "&$F$8&" | Σ%: "&TEXT($K$15,"0.00%")&IF($G$15<>""," | "&$G$15,"")) -> Продукт: INK Magenta (PR 57:1) гу | Артикул: — | Σ%: 0,00%
B14: 💡 Заполните название компонента и % в строках ниже. Можно использовать имена с листа «Сырьё» или вводить свои.
B15: Рецептура (ручной ввод) | I15: Σ %: | K15: =SUM(H17:H36) -> 0
B16: № | C16: Тип | D16: Компонент | E16: Раздел | F16: Ед. | G16: % ввод ручной | H16: % факт 100% | I16: Кол-во на 1 кг | J16: Цена €/кг база | K16: €/кг без НДС | L16: ₽/кг без НДС | M16: Пред. цена €/кг без НДС | N16: Статья | O16: €/кг с НДС | P16: ₽/кг с НДС
B17: 1 | C17: =IF(D17="","",IF(ISNUMBER(MATCH(D17,'Полупродукты'!$C$6:$C$62,0)),"⚗️ Полупр.","Сырьё")) | F17: =IF(D17="","","кг") | H17: =IF(D17="","",IFERROR(G17,0)) | I17: =IF(D17="","",ROUND(H17*(1+IFERROR($M$11,0)),6)) | J17: =IF(D17="","",IF(AND(M17<>"",M17>0),M17,IFERROR(VLOOKUP(D17,'Полупродукты'!$C$6:$E$62,3,FALSE()),IFERROR(VLOOKUP(D17,'Сырьё'!$C$6:$E$233,3,FALSE()),0)))) | K17: =IF(D17="","",ROUND(IFERROR(I17*J17,0),2)) | L17: =IF(D17="","",ROUND(IFERROR(K17*$J$8,0),2)) | N17: Себестоимость | O17: =E11 -> 0 | P17: =ROUND(O17*$J$8,2) -> 0
B18: 2 | C18: =IF(D18="","",IF(ISNUMBER(MATCH(D18,'Полупродукты'!$C$6:$C$62,0)),"⚗️ Полупр.","Сырьё")) | F18: =IF(D18="","","кг") | H18: =IF(D18="","",IFERROR(G18,0)) | I18: =IF(D18="","",ROUND(H18*(1+IFERROR($M$11,0)),6)) | J18: =IF(D18="","",IF(AND(M18<>"",M18>0),M18,IFERROR(VLOOKUP(D18,'Полупродукты'!$C$6:$E$62,3,FALSE()),IFERROR(VLOOKUP(D18,'Сырьё'!$C$6:$E$233,3,FALSE()),0)))) | K18: =IF(D18="","",ROUND(IFERROR(I18*J18,0),2)) | L18: =IF(D18="","",ROUND(IFERROR(K18*$J$8,0),2)) | N18: Доставка на 1 кг | O18: 0.1 | P18: =ROUND(O18*$J$8,2) -> 8.37
B19: 3 | C19: =IF(D19="","",IF(ISNUMBER(MATCH(D19,'Полупродукты'!$C$6:$C$62,0)),"⚗️ Полупр.","Сырьё")) | F19: =IF(D19="","","кг") | H19: =IF(D19="","",IFERROR(G19,0)) | I19: =IF(D19="","",ROUND(H19*(1+IFERROR($M$11,0)),6)) | J19: =IF(D19="","",IF(AND(M19<>"",M19>0),M19,IFERROR(VLOOKUP(D19,'Полупродукты'!$C$6:$E$62,3,FALSE()),IFERROR(VLOOKUP(D19,'Сырьё'!$C$6:$E$233,3,FALSE()),0)))) | K19: =IF(D19="","",ROUND(IFERROR(I19*J19,0),2)) | L19: =IF(D19="","",ROUND(IFERROR(K19*$J$8,0),2)) | N19: GM2 | O19: 0.05 | P19: =ROUND(O19*$J$8,2) -> 4.18
B20: 4 | C20: =IF(D20="","",IF(ISNUMBER(MATCH(D20,'Полупродукты'!$C$6:$C$62,0)),"⚗️ Полупр.","Сырьё")) | F20: =IF(D20="","","кг") | H20: =IF(D20="","",IFERROR(G20,0)) | I20: =IF(D20="","",ROUND(H20*(1+IFERROR($M$11,0)),6)) | J20: =IF(D20="","",IF(AND(M20<>"",M20>0),M20,IFERROR(VLOOKUP(D20,'Полупродукты'!$C$6:$E$62,3,FALSE()),IFERROR(VLOOKUP(D20,'Сырьё'!$C$6:$E$233,3,FALSE()),0)))) | K20: =IF(D20="","",ROUND(IFERROR(I20*J20,0),2)) | L20: =IF(D20="","",ROUND(IFERROR(K20*$J$8,0),2)) | N20: КВ | O20: 0 | P20: =ROUND(O20*$J$8,2) -> 0
B21: 5 | C21: =IF(D21="","",IF(ISNUMBER(MATCH(D21,'Полупродукты'!$C$6:$C$62,0)),"⚗️ Полупр.","Сырьё")) | F21: =IF(D21="","","кг") | H21: =IF(D21="","",IFERROR(G21,0)) | I21: =IF(D21="","",ROUND(H21*(1+IFERROR($M$11,0)),6)) | J21: =IF(D21="","",IF(AND(M21<>"",M21>0),M21,IFERROR(VLOOKUP(D21,'Полупродукты'!$C$6:$E$62,3,FALSE()),IFERROR(VLOOKUP(D21,'Сырьё'!$C$6:$E$233,3,FALSE()),0)))) | K21: =IF(D21="","",ROUND(IFERROR(I21*J21,0),2)) | L21: =IF(D21="","",ROUND(IFERROR(K21*$J$8,0),2)) | N21: Прочие расходы | O21: 0 | P21: =ROUND(O21*$J$8,2) -> 0
B22: 6 | C22: =IF(D22="","",IF(ISNUMBER(MATCH(D22,'Полупродукты'!$C$6:$C$62,0)),"⚗️ Полупр.","Сырьё")) | F22: =IF(D22="","","кг") | H22: =IF(D22="","",IFERROR(G22,0)) | I22: =IF(D22="","",ROUND(H22*(1+IFERROR($M$11,0)),6)) | J22: =IF(D22="","",IF(AND(M22<>"",M22>0),M22,IFERROR(VLOOKUP(D22,'Полупродукты'!$C$6:$E$62,3,FALSE()),IFERROR(VLOOKUP(D22,'Сырьё'!$C$6:$E$233,3,FALSE()),0)))) | K22: =IF(D22="","",ROUND(IFERROR(I22*J22,0),2)) | L22: =IF(D22="","",ROUND(IFERROR(K22*$J$8,0),2)) | N22: Полная стоимость | O22: =ROUND(SUM(O17:O21),2) -> 0.15 | P22: =ROUND(O22*$J$8,2) -> 12.55
B23: 7 | C23: =IF(D23="","",IF(ISNUMBER(MATCH(D23,'Полупродукты'!$C$6:$C$62,0)),"⚗️ Полупр.","Сырьё")) | F23: =IF(D23="","","кг") | H23: =IF(D23="","",IFERROR(G23,0)) | I23: =IF(D23="","",ROUND(H23*(1+IFERROR($M$11,0)),6)) | J23: =IF(D23="","",IF(AND(M23<>"",M23>0),M23,IFERROR(VLOOKUP(D23,'Полупродукты'!$C$6:$E$62,3,FALSE()),IFERROR(VLOOKUP(D23,'Сырьё'!$C$6:$E$233,3,FALSE()),0)))) | K23: =IF(D23="","",ROUND(IFERROR(I23*J23,0),2)) | L23: =IF(D23="","",ROUND(IFERROR(K23*$J$8,0),2)) | N23: Наценка, % | O23: 0.2 | P23: =ROUND(O22*O23*$J$8,2) -> 2.51
B24: 8 | C24: =IF(D24="","",IF(ISNUMBER(MATCH(D24,'Полупродукты'!$C$6:$C$62,0)),"⚗️ Полупр.","Сырьё")) | F24: =IF(D24="","","кг") | H24: =IF(D24="","",IFERROR(G24,0)) | I24: =IF(D24="","",ROUND(H24*(1+IFERROR($M$11,0)),6)) | J24: =IF(D24="","",IF(AND(M24<>"",M24>0),M24,IFERROR(VLOOKUP(D24,'Полупродукты'!$C$6:$E$62,3,FALSE()),IFERROR(VLOOKUP(D24,'Сырьё'!$C$6:$E$233,3,FALSE()),0)))) | K24: =IF(D24="","",ROUND(IFERROR(I24*J24,0),2)) | L24: =IF(D24="","",ROUND(IFERROR(K24*$J$8,0),2)) | N24: Наценка, € | O24: =ROUND(O22*O23,2) -> 0.03 | P24: =ROUND(O24*$J$8,2) -> 2.51
B25: 9 | C25: =IF(D25="","",IF(ISNUMBER(MATCH(D25,'Полупродукты'!$C$6:$C$62,0)),"⚗️ Полупр.","Сырьё")) | F25: =IF(D25="","","кг") | H25: =IF(D25="","",IFERROR(G25,0)) | I25: =IF(D25="","",ROUND(H25*(1+IFERROR($M$11,0)),6)) | J25: =IF(D25="","",IF(AND(M25<>"",M25>0),M25,IFERROR(VLOOKUP(D25,'Полупродукты'!$C$6:$E$62,3,FALSE()),IFERROR(VLOOKUP(D25,'Сырьё'!$C$6:$E$233,3,FALSE()),0)))) | K25: =IF(D25="","",ROUND(IFERROR(I25*J25,0),2)) | L25: =IF(D25="","",ROUND(IFERROR(K25*$J$8,0),2))
B26: 10 | C26: =IF(D26="","",IF(ISNUMBER(MATCH(D26,'Полупродукты'!$C$6:$C$62,0)),"⚗️ Полупр.","Сырьё")) | F26: =IF(D26="","","кг") | H26: =IF(D26="","",IFERROR(G26,0)) | I26: =IF(D26="","",ROUND(H26*(1+IFERROR($M$11,0)),6)) | J26: =IF(D26="","",IF(AND(M26<>"",M26>0),M26,IFERROR(VLOOKUP(D26,'Полупродукты'!$C$6:$E$62,3,FALSE()),IFERROR(VLOOKUP(D26,'Сырьё'!$C$6:$E$233,3,FALSE()),0)))) | K26: =IF(D26="","",ROUND(IFERROR(I26*J26,0),2)) | L26: =IF(D26="","",ROUND(IFERROR(K26*$J$8,0),2)) | N26: ЦЕНА ДЛЯ КЛИЕНТА
B27: 11 | C27: =IF(D27="","",IF(ISNUMBER(MATCH(D27,'Полупродукты'!$C$6:$C$62,0)),"⚗️ Полупр.","Сырьё")) | F27: =IF(D27="","","кг") | H27: =IF(D27="","",IFERROR(G27,0)) | I27: =IF(D27="","",ROUND(H27*(1+IFERROR($M$11,0)),6)) | J27: =IF(D27="","",IF(AND(M27<>"",M27>0),M27,IFERROR(VLOOKUP(D27,'Полупродукты'!$C$6:$E$62,3,FALSE()),IFERROR(VLOOKUP(D27,'Сырьё'!$C$6:$E$233,3,FALSE()),0)))) | K27: =IF(D27="","",ROUND(IFERROR(I27*J27,0),2)) | L27: =IF(D27="","",ROUND(IFERROR(K27*$J$8,0),2)) | N27: с НДС | O27: =ROUND(O22*(1+O23),2) -> 0.18 | P27: =ROUND(O27*$J$8,2) -> 15.06
B28: 12 | C28: =IF(D28="","",IF(ISNUMBER(MATCH(D28,'Полупродукты'!$C$6:$C$62,0)),"⚗️ Полупр.","Сырьё")) | F28: =IF(D28="","","кг") | H28: =IF(D28="","",IFERROR(G28,0)) | I28: =IF(D28="","",ROUND(H28*(1+IFERROR($M$11,0)),6)) | J28: =IF(D28="","",IF(AND(M28<>"",M28>0),M28,IFERROR(VLOOKUP(D28,'Полупродукты'!$C$6:$E$62,3,FALSE()),IFERROR(VLOOKUP(D28,'Сырьё'!$C$6:$E$233,3,FALSE()),0)))) | K28: =IF(D28="","",ROUND(IFERROR(I28*J28,0),2)) | L28: =IF(D28="","",ROUND(IFERROR(K28*$J$8,0),2)) | N28: без НДС | O28: =ROUND(O27/(1+0.22),2) -> 0.15 | P28: =ROUND(O28*$J$8,2) -> 12.55
B29: 13 | C29: =IF(D29="","",IF(ISNUMBER(MATCH(D29,'Полупродукты'!$C$6:$C$62,0)),"⚗️ Полупр.","Сырьё")) | F29: =IF(D29="","","кг") | H29: =IF(D29="","",IFERROR(G29,0)) | I29: =IF(D29="","",ROUND(H29*(1+IFERROR($M$11,0)),6)) | J29: =IF(D29="","",IF(AND(M29<>"",M29>0),M29,IFERROR(VLOOKUP(D29,'Полупродукты'!$C$6:$E$62,3,FALSE()),IFERROR(VLOOKUP(D29,'Сырьё'!$C$6:$E$233,3,FALSE()),0)))) | K29: =IF(D29="","",ROUND(IFERROR(I29*J29,0),2)) | L29: =IF(D29="","",ROUND(IFERROR(K29*$J$8,0),2))
B30: 14 | C30: =IF(D30="","",IF(ISNUMBER(MATCH(D30,'Полупродукты'!$C$6:$C$62,0)),"⚗️ Полупр.","Сырьё")) | F30: =IF(D30="","","кг") | H30: =IF(D30="","",IFERROR(G30,0)) | I30: =IF(D30="","",ROUND(H30*(1+IFERROR($M$11,0)),6)) | J30: =IF(D30="","",IF(AND(M30<>"",M30>0),M30,IFERROR(VLOOKUP(D30,'Полупродукты'!$C$6:$E$62,3,FALSE()),IFERROR(VLOOKUP(D30,'Сырьё'!$C$6:$E$233,3,FALSE()),0)))) | K30: =IF(D30="","",ROUND(IFERROR(I30*J30,0),2)) | L30: =IF(D30="","",ROUND(IFERROR(K30*$J$8,0),2))
B31: 15 | C31: =IF(D31="","",IF(ISNUMBER(MATCH(D31,'Полупродукты'!$C$6:$C$62,0)),"⚗️ Полупр.","Сырьё")) | F31: =IF(D31="","","кг") | H31: =IF(D31="","",IFERROR(G31,0)) | I31: =IF(D31="","",ROUND(H31*(1+IFERROR($M$11,0)),6)) | J31: =IF(D31="","",IF(AND(M31<>"",M31>0),M31,IFERROR(VLOOKUP(D31,'Полупродукты'!$C$6:$E$62,3,FALSE()),IFERROR(VLOOKUP(D31,'Сырьё'!$C$6:$E$233,3,FALSE()),0)))) | K31: =IF(D31="","",ROUND(IFERROR(I31*J31,0),2)) | L31: =IF(D31="","",ROUND(IFERROR(K31*$J$8,0),2))
B32: 16 | C32: =IF(D32="","",IF(ISNUMBER(MATCH(D32,'Полупродукты'!$C$6:$C$62,0)),"⚗️ Полупр.","Сырьё")) | F32: =IF(D32="","","кг") | H32: =IF(D32="","",IFERROR(G32,0)) | I32: =IF(D32="","",ROUND(H32*(1+IFERROR($M$11,0)),6)) | J32: =IF(D32="","",IF(AND(M32<>"",M32>0),M32,IFERROR(VLOOKUP(D32,'Полупродукты'!$C$6:$E$62,3,FALSE()),IFERROR(VLOOKUP(D32,'Сырьё'!$C$6:$E$233,3,FALSE()),0)))) | K32: =IF(D32="","",ROUND(IFERROR(I32*J32,0),2)) | L32: =IF(D32="","",ROUND(IFERROR(K32*$J$8,0),2))
B33: 17 | C33: =IF(D33="","",IF(ISNUMBER(MATCH(D33,'Полупродукты'!$C$6:$C$62,0)),"⚗️ Полупр.","Сырьё")) | F33: =IF(D33="","","кг") | H33: =IF(D33="","",IFERROR(G33,0)) | I33: =IF(D33="","",ROUND(H33*(1+IFERROR($M$11,0)),6)) | J33: =IF(D33="","",IF(AND(M33<>"",M33>0),M33,IFERROR(VLOOKUP(D33,'Полупродукты'!$C$6:$E$62,3,FALSE()),IFERROR(VLOOKUP(D33,'Сырьё'!$C$6:$E$233,3,FALSE()),0)))) | K33: =IF(D33="","",ROUND(IFERROR(I33*J33,0),2)) | L33: =IF(D33="","",ROUND(IFERROR(K33*$J$8,0),2))
B34: 18 | C34: =IF(D34="","",IF(ISNUMBER(MATCH(D34,'Полупродукты'!$C$6:$C$62,0)),"⚗️ Полупр.","Сырьё")) | F34: =IF(D34="","","кг") | H34: =IF(D34="","",IFERROR(G34,0)) | I34: =IF(D34="","",ROUND(H34*(1+IFERROR($M$11,0)),6)) | J34: =IF(D34="","",IF(AND(M34<>"",M34>0),M34,IFERROR(VLOOKUP(D34,'Полупродукты'!$C$6:$E$62,3,FALSE()),IFERROR(VLOOKUP(D34,'Сырьё'!$C$6:$E$233,3,FALSE()),0)))) | K34: =IF(D34="","",ROUND(IFERROR(I34*J34,0),2)) | L34: =IF(D34="","",ROUND(IFERROR(K34*$J$8,0),2))
B35: 19 | C35: =IF(D35="","",IF(ISNUMBER(MATCH(D35,'Полупродукты'!$C$6:$C$62,0)),"⚗️ Полупр.","Сырьё")) | F35: =IF(D35="","","кг") | H35: =IF(D35="","",IFERROR(G35,0)) | I35: =IF(D35="","",ROUND(H35*(1+IFERROR($M$11,0)),6)) | J35: =IF(D35="","",IF(AND(M35<>"",M35>0),M35,IFERROR(VLOOKUP(D35,'Полупродукты'!$C$6:$E$62,3,FALSE()),IFERROR(VLOOKUP(D35,'Сырьё'!$C$6:$E$233,3,FALSE()),0)))) | K35: =IF(D35="","",ROUND(IFERROR(I35*J35,0),2)) | L35: =IF(D35="","",ROUND(IFERROR(K35*$J$8,0),2))
B36: 20 | C36: =IF(D36="","",IF(ISNUMBER(MATCH(D36,'Полупродукты'!$C$6:$C$62,0)),"⚗️ Полупр.","Сырьё")) | F36: =IF(D36="","","кг") | H36: =IF(D36="","",IFERROR(G36,0)) | I36: =IF(D36="","",ROUND(H36*(1+IFERROR($M$11,0)),6)) | J36: =IF(D36="","",IF(AND(M36<>"",M36>0),M36,IFERROR(VLOOKUP(D36,'Полупродукты'!$C$6:$E$62,3,FALSE()),IFERROR(VLOOKUP(D36,'Сырьё'!$C$6:$E$233,3,FALSE()),0)))) | K36: =IF(D36="","",ROUND(IFERROR(I36*J36,0),2)) | L36: =IF(D36="","",ROUND(IFERROR(K36*$J$8,0),2))
B37: Σ ИТОГО | H37: =SUM(H17:H36) -> 0 | K37: =ROUND(SUM(K17:K36),2) -> 0 | L37: =ROUND(SUM(L17:L36),2) -> 0
B40: 💡 Калькулятор X — новые продукты. B8: выбрать из списка или ввести своё. N — пред. цена €/кг (ручной ввод). K8 — авто из «Курсы ЦБ». Σ% (L15) контролируется.

Sheet Расчёт сырья
B2: 📋 Расчёт сырья для планирования закупок
B4: Введите продукты заявки в таблицу ниже (B7:B26) и количество в кг (C7:C26). В сводке справа автоматически рассчитается сырьё для закупки (полупродукты раскрываются до базового сырья).
B6: 📦 ЗАЯВКА КЛИЕНТА (ввод) | G6: 🛒 СВОДКА: СЫРЬЁ К ЗАКУПКЕ (авто, с потерями 3%)
A7: № | B7: Продукт | C7: Кол-во, кг | D7: €/кг б.НДС | E7: Сумма, € | G7: № | H7: Компонент | I7: Ед. | J7: Кол-во | K7: Цена €/ед. | L7: Сумма €
A8: 1 | B8: NSF/PC Cyan Blue (PB 15:3) | C8: 600 | D8: =IF(B8="","",SUMPRODUCT(('_Развёртки'!$A$2:$A$1361=B8)*'_Развёртки'!$F$2:$F$1361)) -> 3.7125966 | E8: =IF(OR(B8="",C8=""),"",C8*D8) -> 2227.558 | G8: 📦 ТАРА (упаковка)
A9: 2 | B9: Краска NSF/UNI Magenta (PR 57:1) TR VER 1.3 | C9: 1200 | D9: =IF(B9="","",SUMPRODUCT(('_Развёртки'!$A$2:$A$1361=B9)*'_Развёртки'!$F$2:$F$1361)) -> 3.5113175 | E9: =IF(OR(B9="",C9=""),"",C9*D9) -> 4213.581 | G9: 1 | H9: Бочка стальная 210 л. | I9: =IFERROR(VLOOKUP(H9,'Сырьё'!$C$6:$D$233,2,FALSE()),IFERROR(VLOOKUP(H9,'Полупродукты'!$C$6:$D$60,2,FALSE()),"кг")) -> кг | J9: {=IF(B8="",0,IFERROR(INDEX('_Развёртки'!$C$2:$C$1358,MATCH(B8&"|"&H9,'_Развёртки'!$D$2:$D$1358,0)),0)*N(C8))+IF(B9="",0,IFERROR(INDEX('_Развёртки'!$C$2:$C$1358,MATCH(B9&"|"&H9,'_Развёртки'!$D$2:$D$1358,0)),0)*N(C9))+IF(B10="",0,IFERROR(INDEX('_Развёртки'!$C$2:$C$1358,MATCH(B10&"|"&H9,'_Развёртки'!$D$2:$D$1358,0)),0)*N(C10))+IF(B11="",0,IFERROR(INDEX('_Развёртки'!$C$2:$C$1358,MATCH(B11&"|"&H9,'_Развёртки'!$D$2:$D$1358,0)),0)*N(C11))+IF(B12="",0,IFERROR(INDEX('_Развёртки'!$C$2:$C$1358,MATCH(B12&"|"&H9,'_Развёртки'!$D$2:$D$1358,0)),0)*N(C12))+IF(B13="",0,IFERROR(INDEX('_Развёртки'!$C$2:$C$1358,MATCH(B13&"|"&H9,'_Развёртки'!$D$2:$D$1358,0)),0)*N(C13))+IF(B14="",0,IFERROR(INDEX('_Развёртки'!$C$2:$C$1358,MATCH(B14&"|"&H9,'_Развёртки'!$D$2:$D$1358,0)),0)*N(C14))+IF(B15="",0,IFERROR(INDEX('_Развёртки'!$C$2:$C$1358,MATCH(B15&"|"&H9,'_Развёртки'!$D$2:$D$1358,0)),0)*N(C15))+IF(B16="",0,IFERROR(INDEX('_Развёртки'!$C$2:$C$1358,MATCH(B16&"|"&H9,'_Развёртки'!$D$2:$D$1358,0)),0)*N(C16))+IF(B17="",0,IFERROR(INDEX('_Развёртки'!$C$2:$C$1358,MATCH(B17&"|"&H9,'_Развёртки'!$D$2:$D$1358,0)),0)*N(C17))+IF(B18="",0,IFERROR(INDEX('_Развёртки'!$C$2:$C$1358,MATCH(B18&"|"&H9,'_Развёртки'!$D$2:$D$1358,0)),0)*N(C18))+IF(B19="",0,IFERROR(INDEX('_Развёртки'!$C$2:$C$1358,MATCH(B19&"|"&H9,'_Развёртки'!$D$2:$D$1358,0)),0)*N(C19))+IF(B20="",0,IFERROR(INDEX('_Развёртки'!$C$2:$C$1358,MATCH(B20&"|"&H9,'_Развёртки'!$D$2:$D$1358,0)),0)*N(C20))+IF(B21="",0,IFERROR(INDEX('_Развёртки'!$C$2:$C$1358,MATCH(B21&"|"&H9,'_Развёртки'!$D$2:$D$1358,0)),0)*N(C21))+IF(B22="",0,IFERROR(INDEX('_Развёртки'!$C$2:$C$1358,MATCH(B22&"|"&H9,'_Развёртки'!$D$2:$D$1358,0)),0)*N(C22))+IF(B23="",0,IFERROR(INDEX('_Развёртки'!$C$2:$C$1358,MATCH(B23&"|"&H9,'_Развёртки'!$D$2:$D$1358,0)),0)*N(C23))+IF(B24="",0,IFERROR(INDEX('_Развёртки'!$C$2:$C$1358,MATCH(B24&"|"&H9,'_Развёртки'!$D$2:$D$1358,0)),0)*N(C24))+IF(B25="",0,IFERROR(INDEX('_Развёртки'!$C$2:$C$1358,MATCH(B25&"|"&H9,'_Развёртки'!$D$2:$D$1358,0)),0)*N(C25))+IF(B26="",0,IFERROR(INDEX('_Развёртки'!$C$2:$C$1358,MATCH(B26&"|"&H9,'_Развёртки'!$D$2:$D$1358,0)),0)*N(C26))+IF(B27="",0,IFERROR(INDEX('_Развёртки'!$C$2:$C$1358,MATCH(B27&"|"&H9,'_Развёртки'!$D$2:$D$1358,0)),0)*N(C27))} -> 3.259 | K9: =IFERROR(VLOOKUP(H9,'Сырьё'!$C$6:$E$233,3,FALSE()),IFERROR(VLOOKUP(H9,'Полупродукты'!$C$6:$E$60,3,FALSE()),0)) -> 30.1527 | L9: =IF(J9=0,0,J9*K9) -> 98.267649
A10: 3 | B10: Orange (PO 34) | C10: 20 | D10: =IF(B10="","",SUMPRODUCT(('_Развёртки'!$A$2:$A$1361=B10)*'_Развёртки'!$F$2:$F$1361)) -> 3.7563635 | E10: =IF(OR(B10="",C10=""),"",C10*D10) -> 75.12727 | G10: 2 | H10: Ведро 25 л. | I10: =IFERROR(VLOOKUP(H10,'Сырьё'!$C$6:$D$233,2,FALSE()),IFERROR(VLOOKUP(H10,'Полупродукты'!$C$6:$D$60,2,FALSE()),"кг")) -> кг | J10: {=IF(B8="",0,IFERROR(INDEX('_Развёртки'!$C$2:$C$1358,MATCH(B8&"|"&H10,'_Развёртки'!$D$2:$D$1358,0)),0)*N(C8))+IF(B9="",0,IFERROR(INDEX('_Развёртки'!$C$2:$C$1358,MATCH(B9&"|"&H10,'_Развёртки'!$D$2:$D$1358,0)),0)*N(C9))+IF(B10="",0,IFERROR(INDEX('_Развёртки'!$C$2:$C$1358,MATCH(B10&"|"&H10,'_Развёртки'!$D$2:$D$1358,0)),0)*N(C10))+IF(B11="",0,IFERROR(INDEX('_Развёртки'!$C$2:$C$1358,MATCH(B11&"|"&H10,'_Развёртки'!$D$2:$D$1358,0)),0)*N(C11))+IF(B12="",0,IFERROR(INDEX('_Развёртки'!$C$2:$C$1358,MATCH(B12&"|"&H10,'_Развёртки'!$D$2:$D$1358,0)),0)*N(C12))+IF(B13="",0,IFERROR(INDEX('_Развёртки'!$C$2:$C$1358,MATCH(B13&"|"&H10,'_Развёртки'!$D$2:$D$1358,0)),0)*N(C13))+IF(B14="",0,IFERROR(INDEX('_Развёртки'!$C$2:$C$1358,MATCH(B14&"|"&H10,'_Развёртки'!$D$2:$D$1358,0)),0)*N(C14))+IF(B15="",0,IFERROR(INDEX('_Развёртки'!$C$2:$C$1358,MATCH(B15&"|"&H10,'_Развёртки'!$D$2:$D$1358,0)),0)*N(C15))+IF(B16="",0,IFERROR(INDEX('_Развёртки'!$C$2:$C$1358,MATCH(B16&"|"&H10,'_Развёртки'!$D$2:$D$1358,0)),0)*N(C16))+IF(B17="",0,IFERROR(INDEX('_Развёртки'!$C$2:$C$1358,MATCH(B17&"|"&H10,'_Развёртки'!$D$2:$D$1358,0)),0)*N(C17))+IF(B18="",0,IFERROR(INDEX('_Развёртки'!$C$2:$C$1358,MATCH(B18&"|"&H10,'_Развёртки'!$D$2:$D$1358,0)),0)*N(C18))+IF(B19="",0,IFERROR(INDEX('_Развёртки'!$C$2:$C$1358,MATCH(B19&"|"&H10,'_Развёртки'!$D$2:$D$1358,0)),0)*N(C19))+IF(B20="",0,IFERROR(INDEX('_Развёртки'!$C$2:$C$1358,MATCH(B20&"|"&H10,'_Развёртки'!$D$2:$D$1358,0)),0)*N(C20))+IF(B21="",0,IFERROR(INDEX('_Развёртки'!$C$2:$C$1358,MATCH(B21&"|"&H10,'_Развёртки'!$D$2:$D$1358,0)),0)*N(C21))+IF(B22="",0,IFERROR(INDEX('_Развёртки'!$C$2:$C$1358,MATCH(B22&"|"&H10,'_Развёртки'!$D$2:$D$1358,0)),0)*N(C22))+IF(B23="",0,IFERROR(INDEX('_Развёртки'!$C$2:$C$1358,MATCH(B23&"|"&H10,'_Развёртки'!$D$2:$D$1358,0)),0)*N(C23))+IF(B24="",0,IFERROR(INDEX('_Развёртки'!$C$2:$C$1358,MATCH(B24&"|"&H10,'_Развёртки'!$D$2:$D$1358,0)),0)*N(C24))+IF(B25="",0,IFERROR(INDEX('_Развёртки'!$C$2:$C$1358,MATCH(B25&"|"&H10,'_Развёртки'!$D$2:$D$1358,0)),0)*N(C25))+IF(B26="",0,IFERROR(INDEX('_Развёртки'!$C$2:$C$1358,MATCH(B26&"|"&H10,'_Развёртки'!$D$2:$D$1358,0)),0)*N(C26))+IF(B27="",0,IFERROR(INDEX('_Развёртки'!$C$2:$C$1358,MATCH(B27&"|"&H10,'_Развёртки'!$D$2:$D$1358,0)),0)*N(C27))} -> 145.04138 | K10: =IFERROR(VLOOKUP(H10,'Сырьё'!$C$6:$E$233,3,FALSE()),IFERROR(VLOOKUP(H10,'Полупродукты'!$C$6:$E$60,3,FALSE()),0)) -> 3.7834 | L10: =IF(J10=0,0,J10*K10) -> 548.74956
A11: 4 | B11: Warm Red (PR 53:1) | C11: 1200 | D11: =IF(B11="","",SUMPRODUCT(('_Развёртки'!$A$2:$A$1361=B11)*'_Развёртки'!$F$2:$F$1361)) -> 3.1645346 | E11: =IF(OR(B11="",C11=""),"",C11*D11) -> 3797.4416 | H11: Итого тары: | J11: =SUM(J9:J10) -> 148.30038 | L11: =SUM(L9:L10) -> 647.01721
A12: 5 | B12: Краска NSF/uni White (PW 6) AF35 | C12: 3500 | D12: =IF(B12="","",SUMPRODUCT(('_Развёртки'!$A$2:$A$1361=B12)*'_Развёртки'!$F$2:$F$1361)) -> 2.5218752 | E12: =IF(OR(B12="",C12=""),"",C12*D12) -> 8826.5631
A13: 6 | B13: Краска NSF/UNI Yellow (PY 13) TR VER 1.3 | C13: 1600 | D13: =IF(B13="","",SUMPRODUCT(('_Развёртки'!$A$2:$A$1361=B13)*'_Развёртки'!$F$2:$F$1361)) -> 1.7317047 | E13: =IF(OR(B13="",C13=""),"",C13*D13) -> 2770.7275 | G13: ⚗️ СЫРЬЁ (химия)
A14: 7 | B14: Black (PBl 7) / RASTR | C14: 300 | D14: =IF(B14="","",SUMPRODUCT(('_Развёртки'!$A$2:$A$1361=B14)*'_Развёртки'!$F$2:$F$1361)) -> 3.5118476 | E14: =IF(OR(B14="",C14=""),"",C14*D14) -> 1053.5543 | G14: 3 | H14: ASTRA11305 | I14: =IFERROR(VLOOKUP(H14,'Сырьё'!$C$6:$D$233,2,FALSE()),IFERROR(VLOOKUP(H14,'Полупродукты'!$C$6:$D$60,2,FALSE()),"кг")) -> кг | J14: {=IF(B8="",0,IFERROR(INDEX('_Развёртки'!$C$2:$C$1358,MATCH(B8&"|"&H14,'_Развёртки'!$D$2:$D$1358,0)),0)*N(C8))+IF(B9="",0,IFERROR(INDEX('_Развёртки'!$C$2:$C$1358,MATCH(B9&"|"&H14,'_Развёртки'!$D$2:$D$1358,0)),0)*N(C9))+IF(B10="",0,IFERROR(INDEX('_Развёртки'!$C$2:$C$1358,MATCH(B10&"|"&H14,'_Развёртки'!$D$2:$D$1358,0)),0)*N(C10))+IF(B11="",0,IFERROR(INDEX('_Развёртки'!$C$2:$C$1358,MATCH(B11&"|"&H14,'_Развёртки'!$D$2:$D$1358,0)),0)*N(C11))+IF(B12="",0,IFERROR(INDEX('_Развёртки'!$C$2:$C$1358,MATCH(B12&"|"&H14,'_Развёртки'!$D$2:$D$1358,0)),0)*N(C12))+IF(B13="",0,IFERROR(INDEX('_Развёртки'!$C$2:$C$1358,MATCH(B13&"|"&H14,'_Развёртки'!$D$2:$D$1358,0)),0)*N(C13))+IF(B14="",0,IFERROR(INDEX('_Развёртки'!$C$2:$C$1358,MATCH(B14&"|"&H14,'_Развёртки'!$D$2:$D$1358,0)),0)*N(C14))+IF(B15="",0,IFERROR(INDEX('_Развёртки'!$C$2:$C$1358,MATCH(B15&"|"&H14,'_Развёртки'!$D$2:$D$1358,0)),0)*N(C15))+IF(B16="",0,IFERROR(INDEX('_Развёртки'!$C$2:$C$1358,MATCH(B16&"|"&H14,'_Развёртки'!$D$2:$D$1358,0)),0)*N(C16))+IF(B17="",0,IFERROR(INDEX('_Развёртки'!$C$2:$C$1358,MATCH(B17&"|"&H14,'_Развёртки'!$D$2:$D$1358,0)),0)*N(C17))+IF(B18="",0,IFERROR(INDEX('_Развёртки'!$C$2:$C$1358,MATCH(B18&"|"&H14,'_Развёртки'!$D$2:$D$1358,0)),0)*N(C18))+IF(B19="",0,IFERROR(INDEX('_Развёртки'!$C$2:$C$1358,MATCH(B19&"|"&H14,'_Развёртки'!$D$2:$D$1358,0)),0)*N(C19))+IF(B20="",0,IFERROR(INDEX('_Развёртки'!$C$2:$C$1358,MATCH(B20&"|"&H14,'_Развёртки'!$D$2:$D$1358,0)),0)*N(C20))+IF(B21="",0,IFERROR(INDEX('_Развёртки'!$C$2:$C$1358,MATCH(B21&"|"&H14,'_Развёртки'!$D$2:$D$1358,0)),0)*N(C21))+IF(B22="",0,IFERROR(INDEX('_Развёртки'!$C$2:$C$1358,MATCH(B22&"|"&H14,'_Развёртки'!$D$2:$D$1358,0)),0)*N(C22))+IF(B23="",0,IFERROR(INDEX('_Развёртки'!$C$2:$C$1358,MATCH(B23&"|"&H14,'_Развёртки'!$D$2:$D$1358,0)),0)*N(C23))+IF(B24="",0,IFERROR(INDEX('_Развёртки'!$C$2:$C$1358,MATCH(B24&"|"&H14,'_Развёртки'!$D$2:$D$1358,0)),0)*N(C24))+IF(B25="",0,IFERROR(INDEX('_Развёртки'!$C$2:$C$1358,MATCH(B25&"|"&H14,'_Развёртки'!$D$2:$D$1358,0)),0)*N(C25))+IF(B26="",0,IFERROR(INDEX('_Развёртки'!$C$2:$C$1358,MATCH(B26&"|"&H14,'_Развёртки'!$D$2:$D$1358,0)),0)*N(C26))+IF(B27="",0,IFERROR(INDEX('_Развёртки'!$C$2:$C$1358,MATCH(B27&"|"&H14,'_Развёртки'!$D$2:$D$1358,0)),0)*N(C27))} -> 0 | K14: =IFERROR(VLOOKUP(H14,'Сырьё'!$C$6:$E$233,3,FALSE()),IFERROR(VLOOKUP(H14,'Полупродукты'!$C$6:$E$60,3,FALSE()),0)) -> 0 | L14: =IF(J14=0,0,J14*K14) -> 0
A15: 8 | B15: Краска NSF/LAM Cyan Blue (PB 15:3) | C15: 60 | D15: =IF(B15="","",SUMPRODUCT(('_Развёртки'!$A$2:$A$1361=B15)*'_Развёртки'!$F$2:$F$1361)) -> 4.0520045 | E15: =IF(OR(B15="",C15=""),"",C15*D15) -> 243.12027 | G15: 4 | H15: ASTRA11306 | I15: =IFERROR(VLOOKUP(H15,'Сырьё'!$C$6:$D$233,2,FALSE()),IFERROR(VLOOKUP(H15,'Полупродукты'!$C$6:$D$60,2,FALSE()),"кг")) -> кг | J15: {=IF(B8="",0,IFERROR(INDEX('_Развёртки'!$C$2:$C$1358,MATCH(B8&"|"&H15,'_Развёртки'!$D$2:$D$1358,0)),0)*N(C8))+IF(B9="",0,IFERROR(INDEX('_Развёртки'!$C$2:$C$1358,MATCH(B9&"|"&H15,'_Развёртки'!$D$2:$D$1358,0)),0)*N(C9))+IF(B10="",0,IFERROR(INDEX('_Развёртки'!$C$2:$C$1358,MATCH(B10&"|"&H15,'_Развёртки'!$D$2:$D$1358,0)),0)*N(C10))+IF(B11="",0,IFERROR(INDEX('_Развёртки'!$C$2:$C$1358,MATCH(B11&"|"&H15,'_Развёртки'!$D$2:$D$1358,0)),0)*N(C11))+IF(B12="",0,IFERROR(INDEX('_Развёртки'!$C$2:$C$1358,MATCH(B12&"|"&H15,'_Развёртки'!$D$2:$D$1358,0)),0)*N(C12))+IF(B13="",0,IFERROR(INDEX('_Развёртки'!$C$2:$C$1358,MATCH(B13&"|"&H15,'_Развёртки'!$D$2:$D$1358,0)),0)*N(C13))+IF(B14="",0,IFERROR(INDEX('_Развёртки'!$C$2:$C$1358,MATCH(B14&"|"&H15,'_Развёртки'!$D$2:$D$1358,0)),0)*N(C14))+IF(B15="",0,IFERROR(INDEX('_Развёртки'!$C$2:$C$1358,MATCH(B15&"|"&H15,'_Развёртки'!$D$2:$D$1358,0)),0)*N(C15))+IF(B16="",0,IFERROR(INDEX('_Развёртки'!$C$2:$C$1358,MATCH(B16&"|"&H15,'_Развёртки'!$D$2:$D$1358,0)),0)*N(C16))+IF(B17="",0,IFERROR(INDEX('_Развёртки'!$C$2:$C$1358,MATCH(B17&"|"&H15,'_Развёртки'!$D$2:$D$1358,0)),0)*N(C17))+IF(B18="",0,IFERROR(INDEX('_Развёртки'!$C$2:$C$1358,MATCH(B18&"|"&H15,'_Развёртки'!$D$2:$D$1358,0)),0)*N(C18))+IF(B19="",0,IFERROR(INDEX('_Развёртки'!$C$2:$C$1358,MATCH(B19&"|"&H15,'_Развёртки'!$D$2:$D$1358,0)),0)*N(C19))+IF(B20="",0,IFERROR(INDEX('_Развёртки'!$C$2:$C$1358,MATCH(B20&"|"&H15,'_Развёртки'!$D$2:$D$1358,0)),0)*N(C20))+IF(B21="",0,IFERROR(INDEX('_Развёртки'!$C$2:$C$1358,MATCH(B21&"|"&H15,'_Развёртки'!$D$2:$D$1358,0)),0)*N(C21))+IF(B22="",0,IFERROR(INDEX('_Развёртки'!$C$2:$C$1358,MATCH(B22&"|"&H15,'_Развёртки'!$D$2:$D$1358,0)),0)*N(C22))+IF(B23="",0,IFERROR(INDEX('_Развёртки'!$C$2:$C$1358,MATCH(B23&"|"&H15,'_Развёртки'!$D$2:$D$1358,0)),0)*N(C23))+IF(B24="",0,IFERROR(INDEX('_Развёртки'!$C$2:$C$1358,MATCH(B24&"|"&H15,'_Развёртки'!$D$2:$D$1358,0)),0)*N(C24))+IF(B25="",0,IFERROR(INDEX('_Развёртки'!$C$2:$C$1358,MATCH(B25&"|"&H15,'_Развёртки'!$D$2:$D$1358,0)),0)*N(C25))+IF(B26="",0,IFERROR(INDEX('_Развёртки'!$C$2:$C$1358,MATCH(B26&"|"&H15,'_Развёртки'!$D$2:$D$1358,0)),0)*N(C26))+IF(B27="",0,IFERROR(INDEX('_Развёртки'!$C$2:$C$1358,MATCH(B27&"|"&H15,'_Развёртки'!$D$2:$D$1358,0)),0)*N(C27))} -> 0 | K15: =IFERROR(VLOOKUP(H15,'Сырьё'!$C$6:$E$233,3,FALSE()),IFERROR(VLOOKUP(H15,'Полупродукты'!$C$6:$E$60,3,FALSE()),0)) -> 0 | L15: =IF(J15=0,0,J15*K15) -> 0
A16: 9 | B16: Лак LAM Extender плашка, | C16: 600 | D16: =IF(B16="","",SUMPRODUCT(('_Развёртки'!$A$2:$A$1361=B16)*'_Развёртки'!$F$2:$F$1361)) -> 2.7766843 | E16: =IF(OR(B16="",C16=""),"",C16*D16) -> 1666.0106 | G16: 5 | H16: DOA Plasticiser | I16: =IFERROR(VLOOKUP(H16,'Сырьё'!$C$6:$D$233,2,FALSE()),IFERROR(VLOOKUP(H16,'Полупродукты'!$C$6:$D$60,2,FALSE()),"кг")) -> кг | J16: {=IF(B8="",0,IFERROR(INDEX('_Развёртки'!$C$2:$C$1358,MATCH(B8&"|"&H16,'_Развёртки'!$D$2:$D$1358,0)),0)*N(C8))+IF(B9="",0,IFERROR(INDEX('_Развёртки'!$C$2:$C$1358,MATCH(B9&"|"&H16,'_Развёртки'!$D$2:$D$1358,0)),0)*N(C9))+IF(B10="",0,IFERROR(INDEX('_Развёртки'!$C$2:$C$1358,MATCH(B10&"|"&H16,'_Развёртки'!$D$2:$D$1358,0)),0)*N(C10))+IF(B11="",0,IFERROR(INDEX('_Развёртки'!$C$2:$C$1358,MATCH(B11&"|"&H16,'_Развёртки'!$D$2:$D$1358,0)),0)*N(C11))+IF(B12="",0,IFERROR(INDEX('_Развёртки'!$C$2:$C$1358,MATCH(B12&"|"&H16,'_Развёртки'!$D$2:$D$1358,0)),0)*N(C12))+IF(B13="",0,IFERROR(INDEX('_Развёртки'!$C$2:$C$1358,MATCH(B13&"|"&H16,'_Развёртки'!$D$2:$D$1358,0)),0)*N(C13))+IF(B14="",0,IFERROR(INDEX('_Развёртки'!$C$2:$C$1358,MATCH(B14&"|"&H16,'_Развёртки'!$D$2:$D$1358,0)),0)*N(C14))+IF(B15="",0,IFERROR(INDEX('_Развёртки'!$C$2:$C$1358,MATCH(B15&"|"&H16,'_Развёртки'!$D$2:$D$1358,0)),0)*N(C15))+IF(B16="",0,IFERROR(INDEX('_Развёртки'!$C$2:$C$1358,MATCH(B16&"|"&H16,'_Развёртки'!$D$2:$D$1358,0)),0)*N(C16))+IF(B17="",0,IFERROR(INDEX('_Развёртки'!$C$2:$C$1358,MATCH(B17&"|"&H16,'_Развёртки'!$D$2:$D$1358,0)),0)*N(C17))+IF(B18="",0,IFERROR(INDEX('_Развёртки'!$C$2:$C$1358,MATCH(B18&"|"&H16,'_Развёртки'!$D$2:$D$1358,0)),0)*N(C18))+IF(B19="",0,IFERROR(INDEX('_Развёртки'!$C$2:$C$1358,MATCH(B19&"|"&H16,'_Развёртки'!$D$2:$D$1358,0)),0)*N(C19))+IF(B20="",0,IFERROR(INDEX('_Развёртки'!$C$2:$C$1358,MATCH(B20&"|"&H16,'_Развёртки'!$D$2:$D$1358,0)),0)*N(C20))+IF(B21="",0,IFERROR(INDEX('_Развёртки'!$C$2:$C$1358,MATCH(B21&"|"&H16,'_Развёртки'!$D$2:$D$1358,0)),0)*N(C21))+IF(B22="",0,IFERROR(INDEX('_Развёртки'!$C$2:$C$1358,MATCH(B22&"|"&H16,'_Развёртки'!$D$2:$D$1358,0)),0)*N(C22))+IF(B23="",0,IFERROR(INDEX('_Развёртки'!$C$2:$C$1358,MATCH(B23&"|"&H16,'_Развёртки'!$D$2:$D$1358,0)),0)*N(C23))+IF(B24="",0,IFERROR(INDEX('_Развёртки'!$C$2:$C$1358,MATCH(B24&"|"&H16,'_Развёртки'!$D$2:$D$1358,0)),0)*N(C24))+IF(B25="",0,IFERROR(INDEX('_Развёртки'!$C$2:$C$1358,MATCH(B25&"|"&H16,'_Развёртки'!$D$2:$D$1358,0)),0)*N(C25))+IF(B26="",0,IFERROR(INDEX('_Развёртки'!$C$2:$C$1358,MATCH(B26&"|"&H16,'_Развёртки'!$D$2:$D$1358,0)),0)*N(C26))+IF(B27="",0,IFERROR(INDEX('_Развёртки'!$C$2:$C$1358,MATCH(B27&"|"&H16,'_Развёртки'!$D$2:$D$1358,0)),0)*N(C27))} -> 68.21192 | K16: =IFERROR(VLOOKUP(H16,'Сырьё'!$C$6:$E$233,3,FALSE()),IFERROR(VLOOKUP(H16,'Полупродукты'!$C$6:$E$60,3,FALSE()),0)) -> 2.337 | L16: =IF(J16=0,0,J16*K16) -> 159.41126
A17: 10 | B17: INK Orange (PO 34) LAM | C17: 20 | D17: =IF(B17="","",SUMPRODUCT(('_Развёртки'!$A$2:$A$1361=B17)*'_Развёртки'!$F$2:$F$1361)) -> 4.2233609 | E17: =IF(OR(B17="",C17=""),"",C17*D17) -> 84.467218 | G17: 6 | H17: Dromide 957 | I17: =IFERROR(VLOOKUP(H17,'Сырьё'!$C$6:$D$233,2,FALSE()),IFERROR(VLOOKUP(H17,'Полупродукты'!$C$6:$D$60,2,FALSE()),"кг")) -> кг | J17: {=IF(B8="",0,IFERROR(INDEX('_Развёртки'!$C$2:$C$1358,MATCH(B8&"|"&H17,'_Развёртки'!$D$2:$D$1358,0)),0)*N(C8))+IF(B9="",0,IFERROR(INDEX('_Развёртки'!$C$2:$C$1358,MATCH(B9&"|"&H17,'_Развёртки'!$D$2:$D$1358,0)),0)*N(C9))+IF(B10="",0,IFERROR(INDEX('_Развёртки'!$C$2:$C$1358,MATCH(B10&"|"&H17,'_Развёртки'!$D$2:$D$1358,0)),0)*N(C10))+IF(B11="",0,IFERROR(INDEX('_Развёртки'!$C$2:$C$1358,MATCH(B11&"|"&H17,'_Развёртки'!$D$2:$D$1358,0)),0)*N(C11))+IF(B12="",0,IFERROR(INDEX('_Развёртки'!$C$2:$C$1358,MATCH(B12&"|"&H17,'_Развёртки'!$D$2:$D$1358,0)),0)*N(C12))+IF(B13="",0,IFERROR(INDEX('_Развёртки'!$C$2:$C$1358,MATCH(B13&"|"&H17,'_Развёртки'!$D$2:$D$1358,0)),0)*N(C13))+IF(B14="",0,IFERROR(INDEX('_Развёртки'!$C$2:$C$1358,MATCH(B14&"|"&H17,'_Развёртки'!$D$2:$D$1358,0)),0)*N(C14))+IF(B15="",0,IFERROR(INDEX('_Развёртки'!$C$2:$C$1358,MATCH(B15&"|"&H17,'_Развёртки'!$D$2:$D$1358,0)),0)*N(C15))+IF(B16="",0,IFERROR(INDEX('_Развёртки'!$C$2:$C$1358,MATCH(B16&"|"&H17,'_Развёртки'!$D$2:$D$1358,0)),0)*N(C16))+IF(B17="",0,IFERROR(INDEX('_Развёртки'!$C$2:$C$1358,MATCH(B17&"|"&H17,'_Развёртки'!$D$2:$D$1358,0)),0)*N(C17))+IF(B18="",0,IFERROR(INDEX('_Развёртки'!$C$2:$C$1358,MATCH(B18&"|"&H17,'_Развёртки'!$D$2:$D$1358,0)),0)*N(C18))+IF(B19="",0,IFERROR(INDEX('_Развёртки'!$C$2:$C$1358,MATCH(B19&"|"&H17,'_Развёртки'!$D$2:$D$1358,0)),0)*N(C19))+IF(B20="",0,IFERROR(INDEX('_Развёртки'!$C$2:$C$1358,MATCH(B20&"|"&H17,'_Развёртки'!$D$2:$D$1358,0)),0)*N(C20))+IF(B21="",0,IFERROR(INDEX('_Развёртки'!$C$2:$C$1358,MATCH(B21&"|"&H17,'_Развёртки'!$D$2:$D$1358,0)),0)*N(C21))+IF(B22="",0,IFERROR(INDEX('_Развёртки'!$C$2:$C$1358,MATCH(B22&"|"&H17,'_Развёртки'!$D$2:$D$1358,0)),0)*N(C22))+IF(B23="",0,IFERROR(INDEX('_Развёртки'!$C$2:$C$1358,MATCH(B23&"|"&H17,'_Развёртки'!$D$2:$D$1358,0)),0)*N(C23))+IF(B24="",0,IFERROR(INDEX('_Развёртки'!$C$2:$C$1358,MATCH(B24&"|"&H17,'_Развёртки'!$D$2:$D$1358,0)),0)*N(C24))+IF(B25="",0,IFERROR(INDEX('_Развёртки'!$C$2:$C$1358,MATCH(B25&"|"&H17,'_Развёртки'!$D$2:$D$1358,0)),0)*N(C25))+IF(B26="",0,IFERROR(INDEX('_Развёртки'!$C$2:$C$1358,MATCH(B26&"|"&H17,'_Развёртки'!$D$2:$D$1358,0)),0)*N(C26))+IF(B27="",0,IFERROR(INDEX('_Развёртки'!$C$2:$C$1358,MATCH(B27&"|"&H17,'_Развёртки'!$D$2:$D$1358,0)),0)*N(C27))} -> 0 | K17: =IFERROR(VLOOKUP(H17,'Сырьё'!$C$6:$E$233,3,FALSE()),IFERROR(VLOOKUP(H17,'Полупродукты'!$C$6:$E$60,3,FALSE()),0)) -> 6.305 | L17: =IF(J17=0,0,J17*K17) -> 0
A18: 11 | B18: Ink Rhodamone Red (PR 169) | C18: 240 | D18: =IF(B18="","",SUMPRODUCT(('_Развёртки'!$A$2:$A$1361=B18)*'_Развёртки'!$F$2:$F$1361)) -> 8.4930968 | E18: =IF(OR(B18="",C18=""),"",C18*D18) -> 2038.3432 | G18: 7 | H18: Kaolin К-Brite HK 158 | I18: =IFERROR(VLOOKUP(H18,'Сырьё'!$C$6:$D$233,2,FALSE()),IFERROR(VLOOKUP(H18,'Полупродукты'!$C$6:$D$60,2,FALSE()),"кг")) -> кг | J18: {=IF(B8="",0,IFERROR(INDEX('_Развёртки'!$C$2:$C$1358,MATCH(B8&"|"&H18,'_Развёртки'!$D$2:$D$1358,0)),0)*N(C8))+IF(B9="",0,IFERROR(INDEX('_Развёртки'!$C$2:$C$1358,MATCH(B9&"|"&H18,'_Развёртки'!$D$2:$D$1358,0)),0)*N(C9))+IF(B10="",0,IFERROR(INDEX('_Развёртки'!$C$2:$C$1358,MATCH(B10&"|"&H18,'_Развёртки'!$D$2:$D$1358,0)),0)*N(C10))+IF(B11="",0,IFERROR(INDEX('_Развёртки'!$C$2:$C$1358,MATCH(B11&"|"&H18,'_Развёртки'!$D$2:$D$1358,0)),0)*N(C11))+IF(B12="",0,IFERROR(INDEX('_Развёртки'!$C$2:$C$1358,MATCH(B12&"|"&H18,'_Развёртки'!$D$2:$D$1358,0)),0)*N(C12))+IF(B13="",0,IFERROR(INDEX('_Развёртки'!$C$2:$C$1358,MATCH(B13&"|"&H18,'_Развёртки'!$D$2:$D$1358,0)),0)*N(C13))+IF(B14="",0,IFERROR(INDEX('_Развёртки'!$C$2:$C$1358,MATCH(B14&"|"&H18,'_Развёртки'!$D$2:$D$1358,0)),0)*N(C14))+IF(B15="",0,IFERROR(INDEX('_Развёртки'!$C$2:$C$1358,MATCH(B15&"|"&H18,'_Развёртки'!$D$2:$D$1358,0)),0)*N(C15))+IF(B16="",0,IFERROR(INDEX('_Развёртки'!$C$2:$C$1358,MATCH(B16&"|"&H18,'_Развёртки'!$D$2:$D$1358,0)),0)*N(C16))+IF(B17="",0,IFERROR(INDEX('_Развёртки'!$C$2:$C$1358,MATCH(B17&"|"&H18,'_Развёртки'!$D$2:$D$1358,0)),0)*N(C17))+IF(B18="",0,IFERROR(INDEX('_Развёртки'!$C$2:$C$1358,MATCH(B18&"|"&H18,'_Развёртки'!$D$2:$D$1358,0)),0)*N(C18))+IF(B19="",0,IFERROR(INDEX('_Развёртки'!$C$2:$C$1358,MATCH(B19&"|"&H18,'_Развёртки'!$D$2:$D$1358,0)),0)*N(C19))+IF(B20="",0,IFERROR(INDEX('_Развёртки'!$C$2:$C$1358,MATCH(B20&"|"&H18,'_Развёртки'!$D$2:$D$1358,0)),0)*N(C20))+IF(B21="",0,IFERROR(INDEX('_Развёртки'!$C$2:$C$1358,MATCH(B21&"|"&H18,'_Развёртки'!$D$2:$D$1358,0)),0)*N(C21))+IF(B22="",0,IFERROR(INDEX('_Развёртки'!$C$2:$C$1358,MATCH(B22&"|"&H18,'_Развёртки'!$D$2:$D$1358,0)),0)*N(C22))+IF(B23="",0,IFERROR(INDEX('_Развёртки'!$C$2:$C$1358,MATCH(B23&"|"&H18,'_Развёртки'!$D$2:$D$1358,0)),0)*N(C23))+IF(B24="",0,IFERROR(INDEX('_Развёртки'!$C$2:$C$1358,MATCH(B24&"|"&H18,'_Развёртки'!$D$2:$D$1358,0)),0)*N(C24))+IF(B25="",0,IFERROR(INDEX('_Развёртки'!$C$2:$C$1358,MATCH(B25&"|"&H18,'_Развёртки'!$D$2:$D$1358,0)),0)*N(C25))+IF(B26="",0,IFERROR(INDEX('_Развёртки'!$C$2:$C$1358,MATCH(B26&"|"&H18,'_Развёртки'!$D$2:$D$1358,0)),0)*N(C26))+IF(B27="",0,IFERROR(INDEX('_Развёртки'!$C$2:$C$1358,MATCH(B27&"|"&H18,'_Развёртки'!$D$2:$D$1358,0)),0)*N(C27))} -> 0 | K18: =IFERROR(VLOOKUP(H18,'Сырьё'!$C$6:$E$233,3,FALSE()),IFERROR(VLOOKUP(H18,'Полупродукты'!$C$6:$E$60,3,FALSE()),0)) -> 1.3268 | L18: =IF(J18=0,0,J18*K18) -> 0
A19: 12 | B19: Краска NSF/LAM White (PW 6) | C19: 500 | D19: =IF(B19="","",SUMPRODUCT(('_Развёртки'!$A$2:$A$1361=B19)*'_Развёртки'!$F$2:$F$1361)) -> 3.0222462 | E19: =IF(OR(B19="",C19=""),"",C19*D19) -> 1511.1231 | G19: 8 | H19: LIDA DSS 20000R | I19: =IFERROR(VLOOKUP(H19,'Сырьё'!$C$6:$D$233,2,FALSE()),IFERROR(VLOOKUP(H19,'Полупродукты'!$C$6:$D$60,2,FALSE()),"кг")) -> кг | J19: {=IF(B8="",0,IFERROR(INDEX('_Развёртки'!$C$2:$C$1358,MATCH(B8&"|"&H19,'_Развёртки'!$D$2:$D$1358,0)),0)*N(C8))+IF(B9="",0,IFERROR(INDEX('_Развёртки'!$C$2:$C$1358,MATCH(B9&"|"&H19,'_Развёртки'!$D$2:$D$1358,0)),0)*N(C9))+IF(B10="",0,IFERROR(INDEX('_Развёртки'!$C$2:$C$1358,MATCH(B10&"|"&H19,'_Развёртки'!$D$2:$D$1358,0)),0)*N(C10))+IF(B11="",0,IFERROR(INDEX('_Развёртки'!$C$2:$C$1358,MATCH(B11&"|"&H19,'_Развёртки'!$D$2:$D$1358,0)),0)*N(C11))+IF(B12="",0,IFERROR(INDEX('_Развёртки'!$C$2:$C$1358,MATCH(B12&"|"&H19,'_Развёртки'!$D$2:$D$1358,0)),0)*N(C12))+IF(B13="",0,IFERROR(INDEX('_Развёртки'!$C$2:$C$1358,MATCH(B13&"|"&H19,'_Развёртки'!$D$2:$D$1358,0)),0)*N(C13))+IF(B14="",0,IFERROR(INDEX('_Развёртки'!$C$2:$C$1358,MATCH(B14&"|"&H19,'_Развёртки'!$D$2:$D$1358,0)),0)*N(C14))+IF(B15="",0,IFERROR(INDEX('_Развёртки'!$C$2:$C$1358,MATCH(B15&"|"&H19,'_Развёртки'!$D$2:$D$1358,0)),0)*N(C15))+IF(B16="",0,IFERROR(INDEX('_Развёртки'!$C$2:$C$1358,MATCH(B16&"|"&H19,'_Развёртки'!$D$2:$D$1358,0)),0)*N(C16))+IF(B17="",0,IFERROR(INDEX('_Развёртки'!$C$2:$C$1358,MATCH(B17&"|"&H19,'_Развёртки'!$D$2:$D$1358,0)),0)*N(C17))+IF(B18="",0,IFERROR(INDEX('_Развёртки'!$C$2:$C$1358,MATCH(B18&"|"&H19,'_Развёртки'!$D$2:$D$1358,0)),0)*N(C18))+IF(B19="",0,IFERROR(INDEX('_Развёртки'!$C$2:$C$1358,MATCH(B19&"|"&H19,'_Развёртки'!$D$2:$D$1358,0)),0)*N(C19))+IF(B20="",0,IFERROR(INDEX('_Развёртки'!$C$2:$C$1358,MATCH(B20&"|"&H19,'_Развёртки'!$D$2:$D$1358,0)),0)*N(C20))+IF(B21="",0,IFERROR(INDEX('_Развёртки'!$C$2:$C$1358,MATCH(B21&"|"&H19,'_Развёртки'!$D$2:$D$1358,0)),0)*N(C21))+IF(B22="",0,IFERROR(INDEX('_Развёртки'!$C$2:$C$1358,MATCH(B22&"|"&H19,'_Развёртки'!$D$2:$D$1358,0)),0)*N(C22))+IF(B23="",0,IFERROR(INDEX('_Развёртки'!$C$2:$C$1358,MATCH(B23&"|"&H19,'_Развёртки'!$D$2:$D$1358,0)),0)*N(C23))+IF(B24="",0,IFERROR(INDEX('_Развёртки'!$C$2:$C$1358,MATCH(B24&"|"&H19,'_Развёртки'!$D$2:$D$1358,0)),0)*N(C24))+IF(B25="",0,IFERROR(INDEX('_Развёртки'!$C$2:$C$1358,MATCH(B25&"|"&H19,'_Развёртки'!$D$2:$D$1358,0)),0)*N(C25))+IF(B26="",0,IFERROR(INDEX('_Развёртки'!$C$2:$C$1358,MATCH(B26&"|"&H19,'_Развёртки'!$D$2:$D$1358,0)),0)*N(C26))+IF(B27="",0,IFERROR(INDEX('_Развёртки'!$C$2:$C$1358,MATCH(B27&"|"&H19,'_Развёртки'!$D$2:$D$1358,0)),0)*N(C27))} -> 29.07868 | K19: =IFERROR(VLOOKUP(H19,'Сырьё'!$C$6:$E$233,3,FALSE()),IFERROR(VLOOKUP(H19,'Полупродукты'!$C$6:$E$60,3,FALSE()),0)) -> 8.8284 | L19: =IF(J19=0,0,J19*K19) -> 256.71822
A20: 13 | B20: INK Violet (PV 23) | C20: 100 | D20: =IF(B20="","",SUMPRODUCT(('_Развёртки'!$A$2:$A$1361=B20)*'_Развёртки'!$F$2:$F$1361)) -> 7.2029626 | E20: =IF(OR(B20="",C20=""),"",C20*D20) -> 720.29626 | G20: 9 | H20: Laropal A- 81-К (GNG A-81 A) | I20: =IFERROR(VLOOKUP(H20,'Сырьё'!$C$6:$D$233,2,FALSE()),IFERROR(VLOOKUP(H20,'Полупродукты'!$C$6:$D$60,2,FALSE()),"кг")) -> кг | J20: {=IF(B8="",0,IFERROR(INDEX('_Развёртки'!$C$2:$C$1358,MATCH(B8&"|"&H20,'_Развёртки'!$D$2:$D$1358,0)),0)*N(C8))+IF(B9="",0,IFERROR(INDEX('_Развёртки'!$C$2:$C$1358,MATCH(B9&"|"&H20,'_Развёртки'!$D$2:$D$1358,0)),0)*N(C9))+IF(B10="",0,IFERROR(INDEX('_Развёртки'!$C$2:$C$1358,MATCH(B10&"|"&H20,'_Развёртки'!$D$2:$D$1358,0)),0)*N(C10))+IF(B11="",0,IFERROR(INDEX('_Развёртки'!$C$2:$C$1358,MATCH(B11&"|"&H20,'_Развёртки'!$D$2:$D$1358,0)),0)*N(C11))+IF(B12="",0,IFERROR(INDEX('_Развёртки'!$C$2:$C$1358,MATCH(B12&"|"&H20,'_Развёртки'!$D$2:$D$1358,0)),0)*N(C12))+IF(B13="",0,IFERROR(INDEX('_Развёртки'!$C$2:$C$1358,MATCH(B13&"|"&H20,'_Развёртки'!$D$2:$D$1358,0)),0)*N(C13))+IF(B14="",0,IFERROR(INDEX('_Развёртки'!$C$2:$C$1358,MATCH(B14&"|"&H20,'_Развёртки'!$D$2:$D$1358,0)),0)*N(C14))+IF(B15="",0,IFERROR(INDEX('_Развёртки'!$C$2:$C$1358,MATCH(B15&"|"&H20,'_Развёртки'!$D$2:$D$1358,0)),0)*N(C15))+IF(B16="",0,IFERROR(INDEX('_Развёртки'!$C$2:$C$1358,MATCH(B16&"|"&H20,'_Развёртки'!$D$2:$D$1358,0)),0)*N(C16))+IF(B17="",0,IFERROR(INDEX('_Развёртки'!$C$2:$C$1358,MATCH(B17&"|"&H20,'_Развёртки'!$D$2:$D$1358,0)),0)*N(C17))+IF(B18="",0,IFERROR(INDEX('_Развёртки'!$C$2:$C$1358,MATCH(B18&"|"&H20,'_Развёртки'!$D$2:$D$1358,0)),0)*N(C18))+IF(B19="",0,IFERROR(INDEX('_Развёртки'!$C$2:$C$1358,MATCH(B19&"|"&H20,'_Развёртки'!$D$2:$D$1358,0)),0)*N(C19))+IF(B20="",0,IFERROR(INDEX('_Развёртки'!$C$2:$C$1358,MATCH(B20&"|"&H20,'_Развёртки'!$D$2:$D$1358,0)),0)*N(C20))+IF(B21="",0,IFERROR(INDEX('_Развёртки'!$C$2:$C$1358,MATCH(B21&"|"&H20,'_Развёртки'!$D$2:$D$1358,0)),0)*N(C21))+IF(B22="",0,IFERROR(INDEX('_Развёртки'!$C$2:$C$1358,MATCH(B22&"|"&H20,'_Развёртки'!$D$2:$D$1358,0)),0)*N(C22))+IF(B23="",0,IFERROR(INDEX('_Развёртки'!$C$2:$C$1358,MATCH(B23&"|"&H20,'_Развёртки'!$D$2:$D$1358,0)),0)*N(C23))+IF(B24="",0,IFERROR(INDEX('_Развёртки'!$C$2:$C$1358,MATCH(B24&"|"&H20,'_Развёртки'!$D$2:$D$1358,0)),0)*N(C24))+IF(B25="",0,IFERROR(INDEX('_Развёртки'!$C$2:$C$1358,MATCH(B25&"|"&H20,'_Развёртки'!$D$2:$D$1358,0)),0)*N(C25))+IF(B26="",0,IFERROR(INDEX('_Развёртки'!$C$2:$C$1358,MATCH(B26&"|"&H20,'_Развёртки'!$D$2:$D$1358,0)),0)*N(C26))+IF(B27="",0,IFERROR(INDEX('_Развёртки'!$C$2:$C$1358,MATCH(B27&"|"&H20,'_Развёртки'!$D$2:$D$1358,0)),0)*N(C27))} -> 0 | K20: =IFERROR(VLOOKUP(H20,'Сырьё'!$C$6:$E$233,3,FALSE()),IFERROR(VLOOKUP(H20,'Полупродукты'!$C$6:$E$60,3,FALSE()),0)) -> 3.2337 | L20: =IF(J20=0,0,J20*K20) -> 0
A21: 14 | D21: =IF(B21="","",SUMPRODUCT(('_Развёртки'!$A$2:$A$1361=B21)*'_Развёртки'!$F$2:$F$1361)) | E21: =IF(OR(B21="",C21=""),"",C21*D21) | G21: 10 | H21: LuWax AF31 | I21: =IFERROR(VLOOKUP(H21,'Сырьё'!$C$6:$D$233,2,FALSE()),IFERROR(VLOOKUP(H21,'Полупродукты'!$C$6:$D$60,2,FALSE()),"кг")) -> кг | J21: {=IF(B8="",0,IFERROR(INDEX('_Развёртки'!$C$2:$C$1358,MATCH(B8&"|"&H21,'_Развёртки'!$D$2:$D$1358,0)),0)*N(C8))+IF(B9="",0,IFERROR(INDEX('_Развёртки'!$C$2:$C$1358,MATCH(B9&"|"&H21,'_Развёртки'!$D$2:$D$1358,0)),0)*N(C9))+IF(B10="",0,IFERROR(INDEX('_Развёртки'!$C$2:$C$1358,MATCH(B10&"|"&H21,'_Развёртки'!$D$2:$D$1358,0)),0)*N(C10))+IF(B11="",0,IFERROR(INDEX('_Развёртки'!$C$2:$C$1358,MATCH(B11&"|"&H21,'_Развёртки'!$D$2:$D$1358,0)),0)*N(C11))+IF(B12="",0,IFERROR(INDEX('_Развёртки'!$C$2:$C$1358,MATCH(B12&"|"&H21,'_Развёртки'!$D$2:$D$1358,0)),0)*N(C12))+IF(B13="",0,IFERROR(INDEX('_Развёртки'!$C$2:$C$1358,MATCH(B13&"|"&H21,'_Развёртки'!$D$2:$D$1358,0)),0)*N(C13))+IF(B14="",0,IFERROR(INDEX('_Развёртки'!$C$2:$C$1358,MATCH(B14&"|"&H21,'_Развёртки'!$D$2:$D$1358,0)),0)*N(C14))+IF(B15="",0,IFERROR(INDEX('_Развёртки'!$C$2:$C$1358,MATCH(B15&"|"&H21,'_Развёртки'!$D$2:$D$1358,0)),0)*N(C15))+IF(B16="",0,IFERROR(INDEX('_Развёртки'!$C$2:$C$1358,MATCH(B16&"|"&H21,'_Развёртки'!$D$2:$D$1358,0)),0)*N(C16))+IF(B17="",0,IFERROR(INDEX('_Развёртки'!$C$2:$C$1358,MATCH(B17&"|"&H21,'_Развёртки'!$D$2:$D$1358,0)),0)*N(C17))+IF(B18="",0,IFERROR(INDEX('_Развёртки'!$C$2:$C$1358,MATCH(B18&"|"&H21,'_Развёртки'!$D$2:$D$1358,0)),0)*N(C18))+IF(B19="",0,IFERROR(INDEX('_Развёртки'!$C$2:$C$1358,MATCH(B19&"|"&H21,'_Развёртки'!$D$2:$D$1358,0)),0)*N(C19))+IF(B20="",0,IFERROR(INDEX('_Развёртки'!$C$2:$C$1358,MATCH(B20&"|"&H21,'_Развёртки'!$D$2:$D$1358,0)),0)*N(C20))+IF(B21="",0,IFERROR(INDEX('_Развёртки'!$C$2:$C$1358,MATCH(B21&"|"&H21,'_Развёртки'!$D$2:$D$1358,0)),0)*N(C21))+IF(B22="",0,IFERROR(INDEX('_Развёртки'!$C$2:$C$1358,MATCH(B22&"|"&H21,'_Развёртки'!$D$2:$D$1358,0)),0)*N(C22))+IF(B23="",0,IFERROR(INDEX('_Развёртки'!$C$2:$C$1358,MATCH(B23&"|"&H21,'_Развёртки'!$D$2:$D$1358,0)),0)*N(C23))+IF(B24="",0,IFERROR(INDEX('_Развёртки'!$C$2:$C$1358,MATCH(B24&"|"&H21,'_Развёртки'!$D$2:$D$1358,0)),0)*N(C24))+IF(B25="",0,IFERROR(INDEX('_Развёртки'!$C$2:$C$1358,MATCH(B25&"|"&H21,'_Развёртки'!$D$2:$D$1358,0)),0)*N(C25))+IF(B26="",0,IFERROR(INDEX('_Развёртки'!$C$2:$C$1358,MATCH(B26&"|"&H21,'_Развёртки'!$D$2:$D$1358,0)),0)*N(C26))+IF(B27="",0,IFERROR(INDEX('_Развёртки'!$C$2:$C$1358,MATCH(B27&"|"&H21,'_Развёртки'!$D$2:$D$1358,0)),0)*N(C27))} -> 0 | K21: =IFERROR(VLOOKUP(H21,'Сырьё'!$C$6:$E$233,3,FALSE()),IFERROR(VLOOKUP(H21,'Полупродукты'!$C$6:$E$60,3,FALSE()),0)) -> 0 | L21: =IF(J21=0,0,J21*K21) -> 0
A22: 15 | D22: =IF(B22="","",SUMPRODUCT(('_Развёртки'!$A$2:$A$1361=B22)*'_Развёртки'!$F$2:$F$1361)) | E22: =IF(OR(B22="",C22=""),"",C22*D22) | G22: 11 | H22: Lubrizol Solsperse 12000 | I22: =IFERROR(VLOOKUP(H22,'Сырьё'!$C$6:$D$233,2,FALSE()),IFERROR(VLOOKUP(H22,'Полупродукты'!$C$6:$D$60,2,FALSE()),"кг")) -> кг | J22: {=IF(B8="",0,IFERROR(INDEX('_Развёртки'!$C$2:$C$1358,MATCH(B8&"|"&H22,'_Развёртки'!$D$2:$D$1358,0)),0)*N(C8))+IF(B9="",0,IFERROR(INDEX('_Развёртки'!$C$2:$C$1358,MATCH(B9&"|"&H22,'_Развёртки'!$D$2:$D$1358,0)),0)*N(C9))+IF(B10="",0,IFERROR(INDEX('_Развёртки'!$C$2:$C$1358,MATCH(B10&"|"&H22,'_Развёртки'!$D$2:$D$1358,0)),0)*N(C10))+IF(B11="",0,IFERROR(INDEX('_Развёртки'!$C$2:$C$1358,MATCH(B11&"|"&H22,'_Развёртки'!$D$2:$D$1358,0)),0)*N(C11))+IF(B12="",0,IFERROR(INDEX('_Развёртки'!$C$2:$C$1358,MATCH(B12&"|"&H22,'_Развёртки'!$D$2:$D$1358,0)),0)*N(C12))+IF(B13="",0,IFERROR(INDEX('_Развёртки'!$C$2:$C$1358,MATCH(B13&"|"&H22,'_Развёртки'!$D$2:$D$1358,0)),0)*N(C13))+IF(B14="",0,IFERROR(INDEX('_Развёртки'!$C$2:$C$1358,MATCH(B14&"|"&H22,'_Развёртки'!$D$2:$D$1358,0)),0)*N(C14))+IF(B15="",0,IFERROR(INDEX('_Развёртки'!$C$2:$C$1358,MATCH(B15&"|"&H22,'_Развёртки'!$D$2:$D$1358,0)),0)*N(C15))+IF(B16="",0,IFERROR(INDEX('_Развёртки'!$C$2:$C$1358,MATCH(B16&"|"&H22,'_Развёртки'!$D$2:$D$1358,0)),0)*N(C16))+IF(B17="",0,IFERROR(INDEX('_Развёртки'!$C$2:$C$1358,MATCH(B17&"|"&H22,'_Развёртки'!$D$2:$D$1358,0)),0)*N(C17))+IF(B18="",0,IFERROR(INDEX('_Развёртки'!$C$2:$C$1358,MATCH(B18&"|"&H22,'_Развёртки'!$D$2:$D$1358,0)),0)*N(C18))+IF(B19="",0,IFERROR(INDEX('_Развёртки'!$C$2:$C$1358,MATCH(B19&"|"&H22,'_Развёртки'!$D$2:$D$1358,0)),0)*N(C19))+IF(B20="",0,IFERROR(INDEX('_Развёртки'!$C$2:$C$1358,MATCH(B20&"|"&H22,'_Развёртки'!$D$2:$D$1358,0)),0)*N(C20))+IF(B21="",0,IFERROR(INDEX('_Развёртки'!$C$2:$C$1358,MATCH(B21&"|"&H22,'_Развёртки'!$D$2:$D$1358,0)),0)*N(C21))+IF(B22="",0,IFERROR(INDEX('_Развёртки'!$C$2:$C$1358,MATCH(B22&"|"&H22,'_Развёртки'!$D$2:$D$1358,0)),0)*N(C22))+IF(B23="",0,IFERROR(INDEX('_Развёртки'!$C$2:$C$1358,MATCH(B23&"|"&H22,'_Развёртки'!$D$2:$D$1358,0)),0)*N(C23))+IF(B24="",0,IFERROR(INDEX('_Развёртки'!$C$2:$C$1358,MATCH(B24&"|"&H22,'_Развёртки'!$D$2:$D$1358,0)),0)*N(C24))+IF(B25="",0,IFERROR(INDEX('_Развёртки'!$C$2:$C$1358,MATCH(B25&"|"&H22,'_Развёртки'!$D$2:$D$1358,0)),0)*N(C25))+IF(B26="",0,IFERROR(INDEX('_Развёртки'!$C$2:$C$1358,MATCH(B26&"|"&H22,'_Развёртки'!$D$2:$D$1358,0)),0)*N(C26))+IF(B27="",0,IFERROR(INDEX('_Развёртки'!$C$2:$C$1358,MATCH(B27&"|"&H22,'_Развёртки'!$D$2:$D$1358,0)),0)*N(C27))} -> 2.0472 | K22: =IFERROR(VLOOKUP(H22,'Сырьё'!$C$6:$E$233,3,FALSE()),IFERROR(VLOOKUP(H22,'Полупродукты'!$C$6:$E$60,3,FALSE()),0)) -> 78.7704 | L22: =IF(J22=0,0,J22*K22) -> 161.25876
A23: 16 | D23: =IF(B23="","",SUMPRODUCT(('_Развёртки'!$A$2:$A$1361=B23)*'_Развёртки'!$F$2:$F$1361)) | E23: =IF(OR(B23="",C23=""),"",C23*D23) | G23: 12 | H23: Lubrizol Solsperse 20000 | I23: =IFERROR(VLOOKUP(H23,'Сырьё'!$C$6:$D$233,2,FALSE()),IFERROR(VLOOKUP(H23,'Полупродукты'!$C$6:$D$60,2,FALSE()),"кг")) -> кг | J23: {=IF(B8="",0,IFERROR(INDEX('_Развёртки'!$C$2:$C$1358,MATCH(B8&"|"&H23,'_Развёртки'!$D$2:$D$1358,0)),0)*N(C8))+IF(B9="",0,IFERROR(INDEX('_Развёртки'!$C$2:$C$1358,MATCH(B9&"|"&H23,'_Развёртки'!$D$2:$D$1358,0)),0)*N(C9))+IF(B10="",0,IFERROR(INDEX('_Развёртки'!$C$2:$C$1358,MATCH(B10&"|"&H23,'_Развёртки'!$D$2:$D$1358,0)),0)*N(C10))+IF(B11="",0,IFERROR(INDEX('_Развёртки'!$C$2:$C$1358,MATCH(B11&"|"&H23,'_Развёртки'!$D$2:$D$1358,0)),0)*N(C11))+IF(B12="",0,IFERROR(INDEX('_Развёртки'!$C$2:$C$1358,MATCH(B12&"|"&H23,'_Развёртки'!$D$2:$D$1358,0)),0)*N(C12))+IF(B13="",0,IFERROR(INDEX('_Развёртки'!$C$2:$C$1358,MATCH(B13&"|"&H23,'_Развёртки'!$D$2:$D$1358,0)),0)*N(C13))+IF(B14="",0,IFERROR(INDEX('_Развёртки'!$C$2:$C$1358,MATCH(B14&"|"&H23,'_Развёртки'!$D$2:$D$1358,0)),0)*N(C14))+IF(B15="",0,IFERROR(INDEX('_Развёртки'!$C$2:$C$1358,MATCH(B15&"|"&H23,'_Развёртки'!$D$2:$D$1358,0)),0)*N(C15))+IF(B16="",0,IFERROR(INDEX('_Развёртки'!$C$2:$C$1358,MATCH(B16&"|"&H23,'_Развёртки'!$D$2:$D$1358,0)),0)*N(C16))+IF(B17="",0,IFERROR(INDEX('_Развёртки'!$C$2:$C$1358,MATCH(B17&"|"&H23,'_Развёртки'!$D$2:$D$1358,0)),0)*N(C17))+IF(B18="",0,IFERROR(INDEX('_Развёртки'!$C$2:$C$1358,MATCH(B18&"|"&H23,'_Развёртки'!$D$2:$D$1358,0)),0)*N(C18))+IF(B19="",0,IFERROR(INDEX('_Развёртки'!$C$2:$C$1358,MATCH(B19&"|"&H23,'_Развёртки'!$D$2:$D$1358,0)),0)*N(C19))+IF(B20="",0,IFERROR(INDEX('_Развёртки'!$C$2:$C$1358,MATCH(B20&"|"&H23,'_Развёртки'!$D$2:$D$1358,0)),0)*N(C20))+IF(B21="",0,IFERROR(INDEX('_Развёртки'!$C$2:$C$1358,MATCH(B21&"|"&H23,'_Развёртки'!$D$2:$D$1358,0)),0)*N(C21))+IF(B22="",0,IFERROR(INDEX('_Развёртки'!$C$2:$C$1358,MATCH(B22&"|"&H23,'_Развёртки'!$D$2:$D$1358,0)),0)*N(C22))+IF(B23="",0,IFERROR(INDEX('_Развёртки'!$C$2:$C$1358,MATCH(B23&"|"&H23,'_Развёртки'!$D$2:$D$1358,0)),0)*N(C23))+IF(B24="",0,IFERROR(INDEX('_Развёртки'!$C$2:$C$1358,MATCH(B24&"|"&H23,'_Развёртки'!$D$2:$D$1358,0)),0)*N(C24))+IF(B25="",0,IFERROR(INDEX('_Развёртки'!$C$2:$C$1358,MATCH(B25&"|"&H23,'_Развёртки'!$D$2:$D$1358,0)),0)*N(C25))+IF(B26="",0,IFERROR(INDEX('_Развёртки'!$C$2:$C$1358,MATCH(B26&"|"&H23,'_Развёртки'!$D$2:$D$1358,0)),0)*N(C26))+IF(B27="",0,IFERROR(INDEX('_Развёртки'!$C$2:$C$1358,MATCH(B27&"|"&H23,'_Развёртки'!$D$2:$D$1358,0)),0)*N(C27))} -> 0 | K23: =IFERROR(VLOOKUP(H23,'Сырьё'!$C$6:$E$233,3,FALSE()),IFERROR(VLOOKUP(H23,'Полупродукты'!$C$6:$E$60,3,FALSE()),0)) -> 16.0534 | L23: =IF(J23=0,0,J23*K23) -> 0
A24: 17 | D24: =IF(B24="","",SUMPRODUCT(('_Развёртки'!$A$2:$A$1361=B24)*'_Развёртки'!$F$2:$F$1361)) | E24: =IF(OR(B24="",C24=""),"",C24*D24) | G24: 13 | H24: Lubrizol Solsperse 22000 | I24: =IFERROR(VLOOKUP(H24,'Сырьё'!$C$6:$D$233,2,FALSE()),IFERROR(VLOOKUP(H24,'Полупродукты'!$C$6:$D$60,2,FALSE()),"кг")) -> кг | J24: {=IF(B8="",0,IFERROR(INDEX('_Развёртки'!$C$2:$C$1358,MATCH(B8&"|"&H24,'_Развёртки'!$D$2:$D$1358,0)),0)*N(C8))+IF(B9="",0,IFERROR(INDEX('_Развёртки'!$C$2:$C$1358,MATCH(B9&"|"&H24,'_Развёртки'!$D$2:$D$1358,0)),0)*N(C9))+IF(B10="",0,IFERROR(INDEX('_Развёртки'!$C$2:$C$1358,MATCH(B10&"|"&H24,'_Развёртки'!$D$2:$D$1358,0)),0)*N(C10))+IF(B11="",0,IFERROR(INDEX('_Развёртки'!$C$2:$C$1358,MATCH(B11&"|"&H24,'_Развёртки'!$D$2:$D$1358,0)),0)*N(C11))+IF(B12="",0,IFERROR(INDEX('_Развёртки'!$C$2:$C$1358,MATCH(B12&"|"&H24,'_Развёртки'!$D$2:$D$1358,0)),0)*N(C12))+IF(B13="",0,IFERROR(INDEX('_Развёртки'!$C$2:$C$1358,MATCH(B13&"|"&H24,'_Развёртки'!$D$2:$D$1358,0)),0)*N(C13))+IF(B14="",0,IFERROR(INDEX('_Развёртки'!$C$2:$C$1358,MATCH(B14&"|"&H24,'_Развёртки'!$D$2:$D$1358,0)),0)*N(C14))+IF(B15="",0,IFERROR(INDEX('_Развёртки'!$C$2:$C$1358,MATCH(B15&"|"&H24,'_Развёртки'!$D$2:$D$1358,0)),0)*N(C15))+IF(B16="",0,IFERROR(INDEX('_Развёртки'!$C$2:$C$1358,MATCH(B16&"|"&H24,'_Развёртки'!$D$2:$D$1358,0)),0)*N(C16))+IF(B17="",0,IFERROR(INDEX('_Развёртки'!$C$2:$C$1358,MATCH(B17&"|"&H24,'_Развёртки'!$D$2:$D$1358,0)),0)*N(C17))+IF(B18="",0,IFERROR(INDEX('_Развёртки'!$C$2:$C$1358,MATCH(B18&"|"&H24,'_Развёртки'!$D$2:$D$1358,0)),0)*N(C18))+IF(B19="",0,IFERROR(INDEX('_Развёртки'!$C$2:$C$1358,MATCH(B19&"|"&H24,'_Развёртки'!$D$2:$D$1358,0)),0)*N(C19))+IF(B20="",0,IFERROR(INDEX('_Развёртки'!$C$2:$C$1358,MATCH(B20&"|"&H24,'_Развёртки'!$D$2:$D$1358,0)),0)*N(C20))+IF(B21="",0,IFERROR(INDEX('_Развёртки'!$C$2:$C$1358,MATCH(B21&"|"&H24,'_Развёртки'!$D$2:$D$1358,0)),0)*N(C21))+IF(B22="",0,IFERROR(INDEX('_Развёртки'!$C$2:$C$1358,MATCH(B22&"|"&H24,'_Развёртки'!$D$2:$D$1358,0)),0)*N(C22))+IF(B23="",0,IFERROR(INDEX('_Развёртки'!$C$2:$C$1358,MATCH(B23&"|"&H24,'_Развёртки'!$D$2:$D$1358,0)),0)*N(C23))+IF(B24="",0,IFERROR(INDEX('_Развёртки'!$C$2:$C$1358,MATCH(B24&"|"&H24,'_Развёртки'!$D$2:$D$1358,0)),0)*N(C24))+IF(B25="",0,IFERROR(INDEX('_Развёртки'!$C$2:$C$1358,MATCH(B25&"|"&H24,'_Развёртки'!$D$2:$D$1358,0)),0)*N(C25))+IF(B26="",0,IFERROR(INDEX('_Развёртки'!$C$2:$C$1358,MATCH(B26&"|"&H24,'_Развёртки'!$D$2:$D$1358,0)),0)*N(C26))+IF(B27="",0,IFERROR(INDEX('_Развёртки'!$C$2:$C$1358,MATCH(B27&"|"&H24,'_Развёртки'!$D$2:$D$1358,0)),0)*N(C27))} -> 0.11228 | K24: =IFERROR(VLOOKUP(H24,'Сырьё'!$C$6:$E$233,3,FALSE()),IFERROR(VLOOKUP(H24,'Полупродукты'!$C$6:$E$60,3,FALSE()),0)) -> 80.7112 | L24: =IF(J24=0,0,J24*K24) -> 9.0622535
A25: 18 | D25: =IF(B25="","",SUMPRODUCT(('_Развёртки'!$A$2:$A$1361=B25)*'_Развёртки'!$F$2:$F$1361)) | E25: =IF(OR(B25="",C25=""),"",C25*D25) | G25: 14 | H25: Luvax wax AF-31 | I25: =IFERROR(VLOOKUP(H25,'Сырьё'!$C$6:$D$233,2,FALSE()),IFERROR(VLOOKUP(H25,'Полупродукты'!$C$6:$D$60,2,FALSE()),"кг")) -> кг | J25: {=IF(B8="",0,IFERROR(INDEX('_Развёртки'!$C$2:$C$1358,MATCH(B8&"|"&H25,'_Развёртки'!$D$2:$D$1358,0)),0)*N(C8))+IF(B9="",0,IFERROR(INDEX('_Развёртки'!$C$2:$C$1358,MATCH(B9&"|"&H25,'_Развёртки'!$D$2:$D$1358,0)),0)*N(C9))+IF(B10="",0,IFERROR(INDEX('_Развёртки'!$C$2:$C$1358,MATCH(B10&"|"&H25,'_Развёртки'!$D$2:$D$1358,0)),0)*N(C10))+IF(B11="",0,IFERROR(INDEX('_Развёртки'!$C$2:$C$1358,MATCH(B11&"|"&H25,'_Развёртки'!$D$2:$D$1358,0)),0)*N(C11))+IF(B12="",0,IFERROR(INDEX('_Развёртки'!$C$2:$C$1358,MATCH(B12&"|"&H25,'_Развёртки'!$D$2:$D$1358,0)),0)*N(C12))+IF(B13="",0,IFERROR(INDEX('_Развёртки'!$C$2:$C$1358,MATCH(B13&"|"&H25,'_Развёртки'!$D$2:$D$1358,0)),0)*N(C13))+IF(B14="",0,IFERROR(INDEX('_Развёртки'!$C$2:$C$1358,MATCH(B14&"|"&H25,'_Развёртки'!$D$2:$D$1358,0)),0)*N(C14))+IF(B15="",0,IFERROR(INDEX('_Развёртки'!$C$2:$C$1358,MATCH(B15&"|"&H25,'_Развёртки'!$D$2:$D$1358,0)),0)*N(C15))+IF(B16="",0,IFERROR(INDEX('_Развёртки'!$C$2:$C$1358,MATCH(B16&"|"&H25,'_Развёртки'!$D$2:$D$1358,0)),0)*N(C16))+IF(B17="",0,IFERROR(INDEX('_Развёртки'!$C$2:$C$1358,MATCH(B17&"|"&H25,'_Развёртки'!$D$2:$D$1358,0)),0)*N(C17))+IF(B18="",0,IFERROR(INDEX('_Развёртки'!$C$2:$C$1358,MATCH(B18&"|"&H25,'_Развёртки'!$D$2:$D$1358,0)),0)*N(C18))+IF(B19="",0,IFERROR(INDEX('_Развёртки'!$C$2:$C$1358,MATCH(B19&"|"&H25,'_Развёртки'!$D$2:$D$1358,0)),0)*N(C19))+IF(B20="",0,IFERROR(INDEX('_Развёртки'!$C$2:$C$1358,MATCH(B20&"|"&H25,'_Развёртки'!$D$2:$D$1358,0)),0)*N(C20))+IF(B21="",0,IFERROR(INDEX('_Развёртки'!$C$2:$C$1358,MATCH(B21&"|"&H25,'_Развёртки'!$D$2:$D$1358,0)),0)*N(C21))+IF(B22="",0,IFERROR(INDEX('_Развёртки'!$C$2:$C$1358,MATCH(B22&"|"&H25,'_Развёртки'!$D$2:$D$1358,0)),0)*N(C22))+IF(B23="",0,IFERROR(INDEX('_Развёртки'!$C$2:$C$1358,MATCH(B23&"|"&H25,'_Развёртки'!$D$2:$D$1358,0)),0)*N(C23))+IF(B24="",0,IFERROR(INDEX('_Развёртки'!$C$2:$C$1358,MATCH(B24&"|"&H25,'_Развёртки'!$D$2:$D$1358,0)),0)*N(C24))+IF(B25="",0,IFERROR(INDEX('_Развёртки'!$C$2:$C$1358,MATCH(B25&"|"&H25,'_Развёртки'!$D$2:$D$1358,0)),0)*N(C25))+IF(B26="",0,IFERROR(INDEX('_Развёртки'!$C$2:$C$1358,MATCH(B26&"|"&H25,'_Развёртки'!$D$2:$D$1358,0)),0)*N(C26))+IF(B27="",0,IFERROR(INDEX('_Развёртки'!$C$2:$C$1358,MATCH(B27&"|"&H25,'_Развёртки'!$D$2:$D$1358,0)),0)*N(C27))} -> 0 | K25: =IFERROR(VLOOKUP(H25,'Сырьё'!$C$6:$E$233,3,FALSE()),IFERROR(VLOOKUP(H25,'Полупродукты'!$C$6:$E$60,3,FALSE()),0)) -> 6.879 | L25: =IF(J25=0,0,J25*K25) -> 0
A26: 19 | D26: =IF(B26="","",SUMPRODUCT(('_Развёртки'!$A$2:$A$1361=B26)*'_Развёртки'!$F$2:$F$1361)) | E26: =IF(OR(B26="",C26=""),"",C26*D26) | G26: 15 | H26: NeoCryl B-819 | I26: =IFERROR(VLOOKUP(H26,'Сырьё'!$C$6:$D$233,2,FALSE()),IFERROR(VLOOKUP(H26,'Полупродукты'!$C$6:$D$60,2,FALSE()),"кг")) -> кг | J26: {=IF(B8="",0,IFERROR(INDEX('_Развёртки'!$C$2:$C$1358,MATCH(B8&"|"&H26,'_Развёртки'!$D$2:$D$1358,0)),0)*N(C8))+IF(B9="",0,IFERROR(INDEX('_Развёртки'!$C$2:$C$1358,MATCH(B9&"|"&H26,'_Развёртки'!$D$2:$D$1358,0)),0)*N(C9))+IF(B10="",0,IFERROR(INDEX('_Развёртки'!$C$2:$C$1358,MATCH(B10&"|"&H26,'_Развёртки'!$D$2:$D$1358,0)),0)*N(C10))+IF(B11="",0,IFERROR(INDEX('_Развёртки'!$C$2:$C$1358,MATCH(B11&"|"&H26,'_Развёртки'!$D$2:$D$1358,0)),0)*N(C11))+IF(B12="",0,IFERROR(INDEX('_Развёртки'!$C$2:$C$1358,MATCH(B12&"|"&H26,'_Развёртки'!$D$2:$D$1358,0)),0)*N(C12))+IF(B13="",0,IFERROR(INDEX('_Развёртки'!$C$2:$C$1358,MATCH(B13&"|"&H26,'_Развёртки'!$D$2:$D$1358,0)),0)*N(C13))+IF(B14="",0,IFERROR(INDEX('_Развёртки'!$C$2:$C$1358,MATCH(B14&"|"&H26,'_Развёртки'!$D$2:$D$1358,0)),0)*N(C14))+IF(B15="",0,IFERROR(INDEX('_Развёртки'!$C$2:$C$1358,MATCH(B15&"|"&H26,'_Развёртки'!$D$2:$D$1358,0)),0)*N(C15))+IF(B16="",0,IFERROR(INDEX('_Развёртки'!$C$2:$C$1358,MATCH(B16&"|"&H26,'_Развёртки'!$D$2:$D$1358,0)),0)*N(C16))+IF(B17="",0,IFERROR(INDEX('_Развёртки'!$C$2:$C$1358,MATCH(B17&"|"&H26,'_Развёртки'!$D$2:$D$1358,0)),0)*N(C17))+IF(B18="",0,IFERROR(INDEX('_Развёртки'!$C$2:$C$1358,MATCH(B18&"|"&H26,'_Развёртки'!$D$2:$D$1358,0)),0)*N(C18))+IF(B19="",0,IFERROR(INDEX('_Развёртки'!$C$2:$C$1358,MATCH(B19&"|"&H26,'_Развёртки'!$D$2:$D$1358,0)),0)*N(C19))+IF(B20="",0,IFERROR(INDEX('_Развёртки'!$C$2:$C$1358,MATCH(B20&"|"&H26,'_Развёртки'!$D$2:$D$1358,0)),0)*N(C20))+IF(B21="",0,IFERROR(INDEX('_Развёртки'!$C$2:$C$1358,MATCH(B21&"|"&H26,'_Развёртки'!$D$2:$D$1358,0)),0)*N(C21))+IF(B22="",0,IFERROR(INDEX('_Развёртки'!$C$2:$C$1358,MATCH(B22&"|"&H26,'_Развёртки'!$D$2:$D$1358,0)),0)*N(C22))+IF(B23="",0,IFERROR(INDEX('_Развёртки'!$C$2:$C$1358,MATCH(B23&"|"&H26,'_Развёртки'!$D$2:$D$1358,0)),0)*N(C23))+IF(B24="",0,IFERROR(INDEX('_Развёртки'!$C$2:$C$1358,MATCH(B24&"|"&H26,'_Развёртки'!$D$2:$D$1358,0)),0)*N(C24))+IF(B25="",0,IFERROR(INDEX('_Развёртки'!$C$2:$C$1358,MATCH(B25&"|"&H26,'_Развёртки'!$D$2:$D$1358,0)),0)*N(C25))+IF(B26="",0,IFERROR(INDEX('_Развёртки'!$C$2:$C$1358,MATCH(B26&"|"&H26,'_Развёртки'!$D$2:$D$1358,0)),0)*N(C26))+IF(B27="",0,IFERROR(INDEX('_Развёртки'!$C$2:$C$1358,MATCH(B27&"|"&H26,'_Развёртки'!$D$2:$D$1358,0)),0)*N(C27))} -> 0 | K26: =IFERROR(VLOOKUP(H26,'Сырьё'!$C$6:$E$233,3,FALSE()),IFERROR(VLOOKUP(H26,'Полупродукты'!$C$6:$E$60,3,FALSE()),0)) -> 11.43 | L26: =IF(J26=0,0,J26*K26) -> 0
A27: 20 | D27: =IF(B27="","",SUMPRODUCT(('_Развёртки'!$A$2:$A$1361=B27)*'_Развёртки'!$F$2:$F$1361)) | E27: =IF(OR(B27="",C27=""),"",C27*D27) | G27: 16 | H27: Neocrylic Resin B 819 | I27: =IFERROR(VLOOKUP(H27,'Сырьё'!$C$6:$D$233,2,FALSE()),IFERROR(VLOOKUP(H27,'Полупродукты'!$C$6:$D$60,2,FALSE()),"кг")) -> кг | J27: {=IF(B8="",0,IFERROR(INDEX('_Развёртки'!$C$2:$C$1358,MATCH(B8&"|"&H27,'_Развёртки'!$D$2:$D$1358,0)),0)*N(C8))+IF(B9="",0,IFERROR(INDEX('_Развёртки'!$C$2:$C$1358,MATCH(B9&"|"&H27,'_Развёртки'!$D$2:$D$1358,0)),0)*N(C9))+IF(B10="",0,IFERROR(INDEX('_Развёртки'!$C$2:$C$1358,MATCH(B10&"|"&H27,'_Развёртки'!$D$2:$D$1358,0)),0)*N(C10))+IF(B11="",0,IFERROR(INDEX('_Развёртки'!$C$2:$C$1358,MATCH(B11&"|"&H27,'_Развёртки'!$D$2:$D$1358,0)),0)*N(C11))+IF(B12="",0,IFERROR(INDEX('_Развёртки'!$C$2:$C$1358,MATCH(B12&"|"&H27,'_Развёртки'!$D$2:$D$1358,0)),0)*N(C12))+IF(B13="",0,IFERROR(INDEX('_Развёртки'!$C$2:$C$1358,MATCH(B13&"|"&H27,'_Развёртки'!$D$2:$D$1358,0)),0)*N(C13))+IF(B14="",0,IFERROR(INDEX('_Развёртки'!$C$2:$C$1358,MATCH(B14&"|"&H27,'_Развёртки'!$D$2:$D$1358,0)),0)*N(C14))+IF(B15="",0,IFERROR(INDEX('_Развёртки'!$C$2:$C$1358,MATCH(B15&"|"&H27,'_Развёртки'!$D$2:$D$1358,0)),0)*N(C15))+IF(B16="",0,IFERROR(INDEX('_Развёртки'!$C$2:$C$1358,MATCH(B16&"|"&H27,'_Развёртки'!$D$2:$D$1358,0)),0)*N(C16))+IF(B17="",0,IFERROR(INDEX('_Развёртки'!$C$2:$C$1358,MATCH(B17&"|"&H27,'_Развёртки'!$D$2:$D$1358,0)),0)*N(C17))+IF(B18="",0,IFERROR(INDEX('_Развёртки'!$C$2:$C$1358,MATCH(B18&"|"&H27,'_Развёртки'!$D$2:$D$1358,0)),0)*N(C18))+IF(B19="",0,IFERROR(INDEX('_Развёртки'!$C$2:$C$1358,MATCH(B19&"|"&H27,'_Развёртки'!$D$2:$D$1358,0)),0)*N(C19))+IF(B20="",0,IFERROR(INDEX('_Развёртки'!$C$2:$C$1358,MATCH(B20&"|"&H27,'_Развёртки'!$D$2:$D$1358,0)),0)*N(C20))+IF(B21="",0,IFERROR(INDEX('_Развёртки'!$C$2:$C$1358,MATCH(B21&"|"&H27,'_Развёртки'!$D$2:$D$1358,0)),0)*N(C21))+IF(B22="",0,IFERROR(INDEX('_Развёртки'!$C$2:$C$1358,MATCH(B22&"|"&H27,'_Развёртки'!$D$2:$D$1358,0)),0)*N(C22))+IF(B23="",0,IFERROR(INDEX('_Развёртки'!$C$2:$C$1358,MATCH(B23&"|"&H27,'_Развёртки'!$D$2:$D$1358,0)),0)*N(C23))+IF(B24="",0,IFERROR(INDEX('_Развёртки'!$C$2:$C$1358,MATCH(B24&"|"&H27,'_Развёртки'!$D$2:$D$1358,0)),0)*N(C24))+IF(B25="",0,IFERROR(INDEX('_Развёртки'!$C$2:$C$1358,MATCH(B25&"|"&H27,'_Развёртки'!$D$2:$D$1358,0)),0)*N(C25))+IF(B26="",0,IFERROR(INDEX('_Развёртки'!$C$2:$C$1358,MATCH(B26&"|"&H27,'_Развёртки'!$D$2:$D$1358,0)),0)*N(C26))+IF(B27="",0,IFERROR(INDEX('_Развёртки'!$C$2:$C$1358,MATCH(B27&"|"&H27,'_Развёртки'!$D$2:$D$1358,0)),0)*N(C27))} -> 0 | K27: =IFERROR(VLOOKUP(H27,'Сырьё'!$C$6:$E$233,3,FALSE()),IFERROR(VLOOKUP(H27,'Полупродукты'!$C$6:$E$60,3,FALSE()),0)) -> 0 | L27: =IF(J27=0,0,J27*K27) -> 0
B28: ИТОГО: | C28: =SUM(C8:C27) -> 9940 | E28: =SUM(E8:E27) -> 29227.913 | G28: 17 | H28: Neocrylic Resin BM 619 | I28: =IFERROR(VLOOKUP(H28,'Сырьё'!$C$6:$D$233,2,FALSE()),IFERROR(VLOOKUP(H28,'Полупродукты'!$C$6:$D$60,2,FALSE()),"кг")) -> кг | J28: {=IF(B8="",0,IFERROR(INDEX('_Развёртки'!$C$2:$C$1358,MATCH(B8&"|"&H28,'_Развёртки'!$D$2:$D$1358,0)),0)*N(C8))+IF(B9="",0,IFERROR(INDEX('_Развёртки'!$C$2:$C$1358,MATCH(B9&"|"&H28,'_Развёртки'!$D$2:$D$1358,0)),0)*N(C9))+IF(B10="",0,IFERROR(INDEX('_Развёртки'!$C$2:$C$1358,MATCH(B10&"|"&H28,'_Развёртки'!$D$2:$D$1358,0)),0)*N(C10))+IF(B11="",0,IFERROR(INDEX('_Развёртки'!$C$2:$C$1358,MATCH(B11&"|"&H28,'_Развёртки'!$D$2:$D$1358,0)),0)*N(C11))+IF(B12="",0,IFERROR(INDEX('_Развёртки'!$C$2:$C$1358,MATCH(B12&"|"&H28,'_Развёртки'!$D$2:$D$1358,0)),0)*N(C12))+IF(B13="",0,IFERROR(INDEX('_Развёртки'!$C$2:$C$1358,MATCH(B13&"|"&H28,'_Развёртки'!$D$2:$D$1358,0)),0)*N(C13))+IF(B14="",0,IFERROR(INDEX('_Развёртки'!$C$2:$C$1358,MATCH(B14&"|"&H28,'_Развёртки'!$D$2:$D$1358,0)),0)*N(C14))+IF(B15="",0,IFERROR(INDEX('_Развёртки'!$C$2:$C$1358,MATCH(B15&"|"&H28,'_Развёртки'!$D$2:$D$1358,0)),0)*N(C15))+IF(B16="",0,IFERROR(INDEX('_Развёртки'!$C$2:$C$1358,MATCH(B16&"|"&H28,'_Развёртки'!$D$2:$D$1358,0)),0)*N(C16))+IF(B17="",0,IFERROR(INDEX('_Развёртки'!$C$2:$C$1358,MATCH(B17&"|"&H28,'_Развёртки'!$D$2:$D$1358,0)),0)*N(C17))+IF(B18="",0,IFERROR(INDEX('_Развёртки'!$C$2:$C$1358,MATCH(B18&"|"&H28,'_Развёртки'!$D$2:$D$1358,0)),0)*N(C18))+IF(B19="",0,IFERROR(INDEX('_Развёртки'!$C$2:$C$1358,MATCH(B19&"|"&H28,'_Развёртки'!$D$2:$D$1358,0)),0)*N(C19))+IF(B20="",0,IFERROR(INDEX('_Развёртки'!$C$2:$C$1358,MATCH(B20&"|"&H28,'_Развёртки'!$D$2:$D$1358,0)),0)*N(C20))+IF(B21="",0,IFERROR(INDEX('_Развёртки'!$C$2:$C$1358,MATCH(B21&"|"&H28,'_Развёртки'!$D$2:$D$1358,0)),0)*N(C21))+IF(B22="",0,IFERROR(INDEX('_Развёртки'!$C$2:$C$1358,MATCH(B22&"|"&H28,'_Развёртки'!$D$2:$D$1358,0)),0)*N(C22))+IF(B23="",0,IFERROR(INDEX('_Развёртки'!$C$2:$C$1358,MATCH(B23&"|"&H28,'_Развёртки'!$D$2:$D$1358,0)),0)*N(C23))+IF(B24="",0,IFERROR(INDEX('_Развёртки'!$C$2:$C$1358,MATCH(B24&"|"&H28,'_Развёртки'!$D$2:$D$1358,0)),0)*N(C24))+IF(B25="",0,IFERROR(INDEX('_Развёртки'!$C$2:$C$1358,MATCH(B25&"|"&H28,'_Развёртки'!$D$2:$D$1358,0)),0)*N(C25))+IF(B26="",0,IFERROR(INDEX('_Развёртки'!$C$2:$C$1358,MATCH(B26&"|"&H28,'_Развёртки'!$D$2:$D$1358,0)),0)*N(C26))+IF(B27="",0,IFERROR(INDEX('_Развёртки'!$C$2:$C$1358,MATCH(B27&"|"&H28,'_Развёртки'!$D$2:$D$1358,0)),0)*N(C27))} -> 0 | K28: =IFERROR(VLOOKUP(H28,'Сырьё'!$C$6:$E$233,3,FALSE()),IFERROR(VLOOKUP(H28,'Полупродукты'!$C$6:$E$60,3,FALSE()),0)) -> 0 | L28: =IF(J28=0,0,J28*K28) -> 0
G29: 18 | H29: Nitrocellulose ( SS 30-35) | I29: =IFERROR(VLOOKUP(H29,'Сырьё'!$C$6:$D$233,2,FALSE()),IFERROR(VLOOKUP(H29,'Полупродукты'!$C$6:$D$60,2,FALSE()),"кг")) -> кг | J29: {=IF(B8="",0,IFERROR(INDEX('_Развёртки'!$C$2:$C$1358,MATCH(B8&"|"&H29,'_Развёртки'!$D$2:$D$1358,0)),0)*N(C8))+IF(B9="",0,IFERROR(INDEX('_Развёртки'!$C$2:$C$1358,MATCH(B9&"|"&H29,'_Развёртки'!$D$2:$D$1358,0)),0)*N(C9))+IF(B10="",0,IFERROR(INDEX('_Развёртки'!$C$2:$C$1358,MATCH(B10&"|"&H29,'_Развёртки'!$D$2:$D$1358,0)),0)*N(C10))+IF(B11="",0,IFERROR(INDEX('_Развёртки'!$C$2:$C$1358,MATCH(B11&"|"&H29,'_Развёртки'!$D$2:$D$1358,0)),0)*N(C11))+IF(B12="",0,IFERROR(INDEX('_Развёртки'!$C$2:$C$1358,MATCH(B12&"|"&H29,'_Развёртки'!$D$2:$D$1358,0)),0)*N(C12))+IF(B13="",0,IFERROR(INDEX('_Развёртки'!$C$2:$C$1358,MATCH(B13&"|"&H29,'_Развёртки'!$D$2:$D$1358,0)),0)*N(C13))+IF(B14="",0,IFERROR(INDEX('_Развёртки'!$C$2:$C$1358,MATCH(B14&"|"&H29,'_Развёртки'!$D$2:$D$1358,0)),0)*N(C14))+IF(B15="",0,IFERROR(INDEX('_Развёртки'!$C$2:$C$1358,MATCH(B15&"|"&H29,'_Развёртки'!$D$2:$D$1358,0)),0)*N(C15))+IF(B16="",0,IFERROR(INDEX('_Развёртки'!$C$2:$C$1358,MATCH(B16&"|"&H29,'_Развёртки'!$D$2:$D$1358,0)),0)*N(C16))+IF(B17="",0,IFERROR(INDEX('_Развёртки'!$C$2:$C$1358,MATCH(B17&"|"&H29,'_Развёртки'!$D$2:$D$1358,0)),0)*N(C17))+IF(B18="",0,IFERROR(INDEX('_Развёртки'!$C$2:$C$1358,MATCH(B18&"|"&H29,'_Развёртки'!$D$2:$D$1358,0)),0)*N(C18))+IF(B19="",0,IFERROR(INDEX('_Развёртки'!$C$2:$C$1358,MATCH(B19&"|"&H29,'_Развёртки'!$D$2:$D$1358,0)),0)*N(C19))+IF(B20="",0,IFERROR(INDEX('_Развёртки'!$C$2:$C$1358,MATCH(B20&"|"&H29,'_Развёртки'!$D$2:$D$1358,0)),0)*N(C20))+IF(B21="",0,IFERROR(INDEX('_Развёртки'!$C$2:$C$1358,MATCH(B21&"|"&H29,'_Развёртки'!$D$2:$D$1358,0)),0)*N(C21))+IF(B22="",0,IFERROR(INDEX('_Развёртки'!$C$2:$C$1358,MATCH(B22&"|"&H29,'_Развёртки'!$D$2:$D$1358,0)),0)*N(C22))+IF(B23="",0,IFERROR(INDEX('_Развёртки'!$C$2:$C$1358,MATCH(B23&"|"&H29,'_Развёртки'!$D$2:$D$1358,0)),0)*N(C23))+IF(B24="",0,IFERROR(INDEX('_Развёртки'!$C$2:$C$1358,MATCH(B24&"|"&H29,'_Развёртки'!$D$2:$D$1358,0)),0)*N(C24))+IF(B25="",0,IFERROR(INDEX('_Развёртки'!$C$2:$C$1358,MATCH(B25&"|"&H29,'_Развёртки'!$D$2:$D$1358,0)),0)*N(C25))+IF(B26="",0,IFERROR(INDEX('_Развёртки'!$C$2:$C$1358,MATCH(B26&"|"&H29,'_Развёртки'!$D$2:$D$1358,0)),0)*N(C26))+IF(B27="",0,IFERROR(INDEX('_Развёртки'!$C$2:$C$1358,MATCH(B27&"|"&H29,'_Развёртки'!$D$2:$D$1358,0)),0)*N(C27))} -> 559.93002 | K29: =IFERROR(VLOOKUP(H29,'Сырьё'!$C$6:$E$233,3,FALSE()),IFERROR(VLOOKUP(H29,'Полупродукты'!$C$6:$E$60,3,FALSE()),0)) -> 6.519 | L29: =IF(J29=0,0,J29*K29) -> 3650.1838
G30: 19 | H30: Nitrocellulose L1\8 SEC(IPA) | I30: =IFERROR(VLOOKUP(H30,'Сырьё'!$C$6:$D$233,2,FALSE()),IFERROR(VLOOKUP(H30,'Полупродукты'!$C$6:$D$60,2,FALSE()),"кг")) -> кг | J30: {=IF(B8="",0,IFERROR(INDEX('_Развёртки'!$C$2:$C$1358,MATCH(B8&"|"&H30,'_Развёртки'!$D$2:$D$1358,0)),0)*N(C8))+IF(B9="",0,IFERROR(INDEX('_Развёртки'!$C$2:$C$1358,MATCH(B9&"|"&H30,'_Развёртки'!$D$2:$D$1358,0)),0)*N(C9))+IF(B10="",0,IFERROR(INDEX('_Развёртки'!$C$2:$C$1358,MATCH(B10&"|"&H30,'_Развёртки'!$D$2:$D$1358,0)),0)*N(C10))+IF(B11="",0,IFERROR(INDEX('_Развёртки'!$C$2:$C$1358,MATCH(B11&"|"&H30,'_Развёртки'!$D$2:$D$1358,0)),0)*N(C11))+IF(B12="",0,IFERROR(INDEX('_Развёртки'!$C$2:$C$1358,MATCH(B12&"|"&H30,'_Развёртки'!$D$2:$D$1358,0)),0)*N(C12))+IF(B13="",0,IFERROR(INDEX('_Развёртки'!$C$2:$C$1358,MATCH(B13&"|"&H30,'_Развёртки'!$D$2:$D$1358,0)),0)*N(C13))+IF(B14="",0,IFERROR(INDEX('_Развёртки'!$C$2:$C$1358,MATCH(B14&"|"&H30,'_Развёртки'!$D$2:$D$1358,0)),0)*N(C14))+IF(B15="",0,IFERROR(INDEX('_Развёртки'!$C$2:$C$1358,MATCH(B15&"|"&H30,'_Развёртки'!$D$2:$D$1358,0)),0)*N(C15))+IF(B16="",0,IFERROR(INDEX('_Развёртки'!$C$2:$C$1358,MATCH(B16&"|"&H30,'_Развёртки'!$D$2:$D$1358,0)),0)*N(C16))+IF(B17="",0,IFERROR(INDEX('_Развёртки'!$C$2:$C$1358,MATCH(B17&"|"&H30,'_Развёртки'!$D$2:$D$1358,0)),0)*N(C17))+IF(B18="",0,IFERROR(INDEX('_Развёртки'!$C$2:$C$1358,MATCH(B18&"|"&H30,'_Развёртки'!$D$2:$D$1358,0)),0)*N(C18))+IF(B19="",0,IFERROR(INDEX('_Развёртки'!$C$2:$C$1358,MATCH(B19&"|"&H30,'_Развёртки'!$D$2:$D$1358,0)),0)*N(C19))+IF(B20="",0,IFERROR(INDEX('_Развёртки'!$C$2:$C$1358,MATCH(B20&"|"&H30,'_Развёртки'!$D$2:$D$1358,0)),0)*N(C20))+IF(B21="",0,IFERROR(INDEX('_Развёртки'!$C$2:$C$1358,MATCH(B21&"|"&H30,'_Развёртки'!$D$2:$D$1358,0)),0)*N(C21))+IF(B22="",0,IFERROR(INDEX('_Развёртки'!$C$2:$C$1358,MATCH(B22&"|"&H30,'_Развёртки'!$D$2:$D$1358,0)),0)*N(C22))+IF(B23="",0,IFERROR(INDEX('_Развёртки'!$C$2:$C$1358,MATCH(B23&"|"&H30,'_Развёртки'!$D$2:$D$1358,0)),0)*N(C23))+IF(B24="",0,IFERROR(INDEX('_Развёртки'!$C$2:$C$1358,MATCH(B24&"|"&H30,'_Развёртки'!$D$2:$D$1358,0)),0)*N(C24))+IF(B25="",0,IFERROR(INDEX('_Развёртки'!$C$2:$C$1358,MATCH(B25&"|"&H30,'_Развёртки'!$D$2:$D$1358,0)),0)*N(C25))+IF(B26="",0,IFERROR(INDEX('_Развёртки'!$C$2:$C$1358,MATCH(B26&"|"&H30,'_Развёртки'!$D$2:$D$1358,0)),0)*N(C26))+IF(B27="",0,IFERROR(INDEX('_Развёртки'!$C$2:$C$1358,MATCH(B27&"|"&H30,'_Развёртки'!$D$2:$D$1358,0)),0)*N(C27))} -> 142.2636 | K30: =IFERROR(VLOOKUP(H30,'Сырьё'!$C$6:$E$233,3,FALSE()),IFERROR(VLOOKUP(H30,'Полупродукты'!$C$6:$E$60,3,FALSE()),0)) -> 0 | L30: =IF(J30=0,0,J30*K30) -> 0
G31: 20 | H31: Pigment Black NuTone 310 | I31: =IFERROR(VLOOKUP(H31,'Сырьё'!$C$6:$D$233,2,FALSE()),IFERROR(VLOOKUP(H31,'Полупродукты'!$C$6:$D$60,2,FALSE()),"кг")) -> кг | J31: {=IF(B8="",0,IFERROR(INDEX('_Развёртки'!$C$2:$C$1358,MATCH(B8&"|"&H31,'_Развёртки'!$D$2:$D$1358,0)),0)*N(C8))+IF(B9="",0,IFERROR(INDEX('_Развёртки'!$C$2:$C$1358,MATCH(B9&"|"&H31,'_Развёртки'!$D$2:$D$1358,0)),0)*N(C9))+IF(B10="",0,IFERROR(INDEX('_Развёртки'!$C$2:$C$1358,MATCH(B10&"|"&H31,'_Развёртки'!$D$2:$D$1358,0)),0)*N(C10))+IF(B11="",0,IFERROR(INDEX('_Развёртки'!$C$2:$C$1358,MATCH(B11&"|"&H31,'_Развёртки'!$D$2:$D$1358,0)),0)*N(C11))+IF(B12="",0,IFERROR(INDEX('_Развёртки'!$C$2:$C$1358,MATCH(B12&"|"&H31,'_Развёртки'!$D$2:$D$1358,0)),0)*N(C12))+IF(B13="",0,IFERROR(INDEX('_Развёртки'!$C$2:$C$1358,MATCH(B13&"|"&H31,'_Развёртки'!$D$2:$D$1358,0)),0)*N(C13))+IF(B14="",0,IFERROR(INDEX('_Развёртки'!$C$2:$C$1358,MATCH(B14&"|"&H31,'_Развёртки'!$D$2:$D$1358,0)),0)*N(C14))+IF(B15="",0,IFERROR(INDEX('_Развёртки'!$C$2:$C$1358,MATCH(B15&"|"&H31,'_Развёртки'!$D$2:$D$1358,0)),0)*N(C15))+IF(B16="",0,IFERROR(INDEX('_Развёртки'!$C$2:$C$1358,MATCH(B16&"|"&H31,'_Развёртки'!$D$2:$D$1358,0)),0)*N(C16))+IF(B17="",0,IFERROR(INDEX('_Развёртки'!$C$2:$C$1358,MATCH(B17&"|"&H31,'_Развёртки'!$D$2:$D$1358,0)),0)*N(C17))+IF(B18="",0,IFERROR(INDEX('_Развёртки'!$C$2:$C$1358,MATCH(B18&"|"&H31,'_Развёртки'!$D$2:$D$1358,0)),0)*N(C18))+IF(B19="",0,IFERROR(INDEX('_Развёртки'!$C$2:$C$1358,MATCH(B19&"|"&H31,'_Развёртки'!$D$2:$D$1358,0)),0)*N(C19))+IF(B20="",0,IFERROR(INDEX('_Развёртки'!$C$2:$C$1358,MATCH(B20&"|"&H31,'_Развёртки'!$D$2:$D$1358,0)),0)*N(C20))+IF(B21="",0,IFERROR(INDEX('_Развёртки'!$C$2:$C$1358,MATCH(B21&"|"&H31,'_Развёртки'!$D$2:$D$1358,0)),0)*N(C21))+IF(B22="",0,IFERROR(INDEX('_Развёртки'!$C$2:$C$1358,MATCH(B22&"|"&H31,'_Развёртки'!$D$2:$D$1358,0)),0)*N(C22))+IF(B23="",0,IFERROR(INDEX('_Развёртки'!$C$2:$C$1358,MATCH(B23&"|"&H31,'_Развёртки'!$D$2:$D$1358,0)),0)*N(C23))+IF(B24="",0,IFERROR(INDEX('_Развёртки'!$C$2:$C$1358,MATCH(B24&"|"&H31,'_Развёртки'!$D$2:$D$1358,0)),0)*N(C24))+IF(B25="",0,IFERROR(INDEX('_Развёртки'!$C$2:$C$1358,MATCH(B25&"|"&H31,'_Развёртки'!$D$2:$D$1358,0)),0)*N(C25))+IF(B26="",0,IFERROR(INDEX('_Развёртки'!$C$2:$C$1358,MATCH(B26&"|"&H31,'_Развёртки'!$D$2:$D$1358,0)),0)*N(C26))+IF(B27="",0,IFERROR(INDEX('_Развёртки'!$C$2:$C$1358,MATCH(B27&"|"&H31,'_Развёртки'!$D$2:$D$1358,0)),0)*N(C27))} -> 0 | K31: =IFERROR(VLOOKUP(H31,'Сырьё'!$C$6:$E$233,3,FALSE()),IFERROR(VLOOKUP(H31,'Полупродукты'!$C$6:$E$60,3,FALSE()),0)) -> 3.7202 | L31: =IF(J31=0,0,J31*K31) -> 0
G32: 21 | H32: Pigment Black PBk 7 (PRINTEX 35) | I32: =IFERROR(VLOOKUP(H32,'Сырьё'!$C$6:$D$233,2,FALSE()),IFERROR(VLOOKUP(H32,'Полупродукты'!$C$6:$D$60,2,FALSE()),"кг")) -> кг | J32: {=IF(B8="",0,IFERROR(INDEX('_Развёртки'!$C$2:$C$1358,MATCH(B8&"|"&H32,'_Развёртки'!$D$2:$D$1358,0)),0)*N(C8))+IF(B9="",0,IFERROR(INDEX('_Развёртки'!$C$2:$C$1358,MATCH(B9&"|"&H32,'_Развёртки'!$D$2:$D$1358,0)),0)*N(C9))+IF(B10="",0,IFERROR(INDEX('_Развёртки'!$C$2:$C$1358,MATCH(B10&"|"&H32,'_Развёртки'!$D$2:$D$1358,0)),0)*N(C10))+IF(B11="",0,IFERROR(INDEX('_Развёртки'!$C$2:$C$1358,MATCH(B11&"|"&H32,'_Развёртки'!$D$2:$D$1358,0)),0)*N(C11))+IF(B12="",0,IFERROR(INDEX('_Развёртки'!$C$2:$C$1358,MATCH(B12&"|"&H32,'_Развёртки'!$D$2:$D$1358,0)),0)*N(C12))+IF(B13="",0,IFERROR(INDEX('_Развёртки'!$C$2:$C$1358,MATCH(B13&"|"&H32,'_Развёртки'!$D$2:$D$1358,0)),0)*N(C13))+IF(B14="",0,IFERROR(INDEX('_Развёртки'!$C$2:$C$1358,MATCH(B14&"|"&H32,'_Развёртки'!$D$2:$D$1358,0)),0)*N(C14))+IF(B15="",0,IFERROR(INDEX('_Развёртки'!$C$2:$C$1358,MATCH(B15&"|"&H32,'_Развёртки'!$D$2:$D$1358,0)),0)*N(C15))+IF(B16="",0,IFERROR(INDEX('_Развёртки'!$C$2:$C$1358,MATCH(B16&"|"&H32,'_Развёртки'!$D$2:$D$1358,0)),0)*N(C16))+IF(B17="",0,IFERROR(INDEX('_Развёртки'!$C$2:$C$1358,MATCH(B17&"|"&H32,'_Развёртки'!$D$2:$D$1358,0)),0)*N(C17))+IF(B18="",0,IFERROR(INDEX('_Развёртки'!$C$2:$C$1358,MATCH(B18&"|"&H32,'_Развёртки'!$D$2:$D$1358,0)),0)*N(C18))+IF(B19="",0,IFERROR(INDEX('_Развёртки'!$C$2:$C$1358,MATCH(B19&"|"&H32,'_Развёртки'!$D$2:$D$1358,0)),0)*N(C19))+IF(B20="",0,IFERROR(INDEX('_Развёртки'!$C$2:$C$1358,MATCH(B20&"|"&H32,'_Развёртки'!$D$2:$D$1358,0)),0)*N(C20))+IF(B21="",0,IFERROR(INDEX('_Развёртки'!$C$2:$C$1358,MATCH(B21&"|"&H32,'_Развёртки'!$D$2:$D$1358,0)),0)*N(C21))+IF(B22="",0,IFERROR(INDEX('_Развёртки'!$C$2:$C$1358,MATCH(B22&"|"&H32,'_Развёртки'!$D$2:$D$1358,0)),0)*N(C22))+IF(B23="",0,IFERROR(INDEX('_Развёртки'!$C$2:$C$1358,MATCH(B23&"|"&H32,'_Развёртки'!$D$2:$D$1358,0)),0)*N(C23))+IF(B24="",0,IFERROR(INDEX('_Развёртки'!$C$2:$C$1358,MATCH(B24&"|"&H32,'_Развёртки'!$D$2:$D$1358,0)),0)*N(C24))+IF(B25="",0,IFERROR(INDEX('_Развёртки'!$C$2:$C$1358,MATCH(B25&"|"&H32,'_Развёртки'!$D$2:$D$1358,0)),0)*N(C25))+IF(B26="",0,IFERROR(INDEX('_Развёртки'!$C$2:$C$1358,MATCH(B26&"|"&H32,'_Развёртки'!$D$2:$D$1358,0)),0)*N(C26))+IF(B27="",0,IFERROR(INDEX('_Развёртки'!$C$2:$C$1358,MATCH(B27&"|"&H32,'_Развёртки'!$D$2:$D$1358,0)),0)*N(C27))} -> 0 | K32: =IFERROR(VLOOKUP(H32,'Сырьё'!$C$6:$E$233,3,FALSE()),IFERROR(VLOOKUP(H32,'Полупродукты'!$C$6:$E$60,3,FALSE()),0)) -> 3.8883 | L32: =IF(J32=0,0,J32*K32) -> 0
G33: 22 | H33: Pigment Black PС 406 | I33: =IFERROR(VLOOKUP(H33,'Сырьё'!$C$6:$D$233,2,FALSE()),IFERROR(VLOOKUP(H33,'Полупродукты'!$C$6:$D$60,2,FALSE()),"кг")) -> кг | J33: {=IF(B8="",0,IFERROR(INDEX('_Развёртки'!$C$2:$C$1358,MATCH(B8&"|"&H33,'_Развёртки'!$D$2:$D$1358,0)),0)*N(C8))+IF(B9="",0,IFERROR(INDEX('_Развёртки'!$C$2:$C$1358,MATCH(B9&"|"&H33,'_Развёртки'!$D$2:$D$1358,0)),0)*N(C9))+IF(B10="",0,IFERROR(INDEX('_Развёртки'!$C$2:$C$1358,MATCH(B10&"|"&H33,'_Развёртки'!$D$2:$D$1358,0)),0)*N(C10))+IF(B11="",0,IFERROR(INDEX('_Развёртки'!$C$2:$C$1358,MATCH(B11&"|"&H33,'_Развёртки'!$D$2:$D$1358,0)),0)*N(C11))+IF(B12="",0,IFERROR(INDEX('_Развёртки'!$C$2:$C$1358,MATCH(B12&"|"&H33,'_Развёртки'!$D$2:$D$1358,0)),0)*N(C12))+IF(B13="",0,IFERROR(INDEX('_Развёртки'!$C$2:$C$1358,MATCH(B13&"|"&H33,'_Развёртки'!$D$2:$D$1358,0)),0)*N(C13))+IF(B14="",0,IFERROR(INDEX('_Развёртки'!$C$2:$C$1358,MATCH(B14&"|"&H33,'_Развёртки'!$D$2:$D$1358,0)),0)*N(C14))+IF(B15="",0,IFERROR(INDEX('_Развёртки'!$C$2:$C$1358,MATCH(B15&"|"&H33,'_Развёртки'!$D$2:$D$1358,0)),0)*N(C15))+IF(B16="",0,IFERROR(INDEX('_Развёртки'!$C$2:$C$1358,MATCH(B16&"|"&H33,'_Развёртки'!$D$2:$D$1358,0)),0)*N(C16))+IF(B17="",0,IFERROR(INDEX('_Развёртки'!$C$2:$C$1358,MATCH(B17&"|"&H33,'_Развёртки'!$D$2:$D$1358,0)),0)*N(C17))+IF(B18="",0,IFERROR(INDEX('_Развёртки'!$C$2:$C$1358,MATCH(B18&"|"&H33,'_Развёртки'!$D$2:$D$1358,0)),0)*N(C18))+IF(B19="",0,IFERROR(INDEX('_Развёртки'!$C$2:$C$1358,MATCH(B19&"|"&H33,'_Развёртки'!$D$2:$D$1358,0)),0)*N(C19))+IF(B20="",0,IFERROR(INDEX('_Развёртки'!$C$2:$C$1358,MATCH(B20&"|"&H33,'_Развёртки'!$D$2:$D$1358,0)),0)*N(C20))+IF(B21="",0,IFERROR(INDEX('_Развёртки'!$C$2:$C$1358,MATCH(B21&"|"&H33,'_Развёртки'!$D$2:$D$1358,0)),0)*N(C21))+IF(B22="",0,IFERROR(INDEX('_Развёртки'!$C$2:$C$1358,MATCH(B22&"|"&H33,'_Развёртки'!$D$2:$D$1358,0)),0)*N(C22))+IF(B23="",0,IFERROR(INDEX('_Развёртки'!$C$2:$C$1358,MATCH(B23&"|"&H33,'_Развёртки'!$D$2:$D$1358,0)),0)*N(C23))+IF(B24="",0,IFERROR(INDEX('_Развёртки'!$C$2:$C$1358,MATCH(B24&"|"&H33,'_Развёртки'!$D$2:$D$1358,0)),0)*N(C24))+IF(B25="",0,IFERROR(INDEX('_Развёртки'!$C$2:$C$1358,MATCH(B25&"|"&H33,'_Развёртки'!$D$2:$D$1358,0)),0)*N(C25))+IF(B26="",0,IFERROR(INDEX('_Развёртки'!$C$2:$C$1358,MATCH(B26&"|"&H33,'_Развёртки'!$D$2:$D$1358,0)),0)*N(C26))+IF(B27="",0,IFERROR(INDEX('_Развёртки'!$C$2:$C$1358,MATCH(B27&"|"&H33,'_Развёртки'!$D$2:$D$1358,0)),0)*N(C27))} -> 0 | K33: =IFERROR(VLOOKUP(H33,'Сырьё'!$C$6:$E$233,3,FALSE()),IFERROR(VLOOKUP(H33,'Полупродукты'!$C$6:$E$60,3,FALSE()),0)) -> 3.5357 | L33: =IF(J33=0,0,J33*K33) -> 0
G34: 23 | H34: Pigment Cyan Blue PB 15:3 | I34: =IFERROR(VLOOKUP(H34,'Сырьё'!$C$6:$D$233,2,FALSE()),IFERROR(VLOOKUP(H34,'Полупродукты'!$C$6:$D$60,2,FALSE()),"кг")) -> кг | J34: {=IF(B8="",0,IFERROR(INDEX('_Развёртки'!$C$2:$C$1358,MATCH(B8&"|"&H34,'_Развёртки'!$D$2:$D$1358,0)),0)*N(C8))+IF(B9="",0,IFERROR(INDEX('_Развёртки'!$C$2:$C$1358,MATCH(B9&"|"&H34,'_Развёртки'!$D$2:$D$1358,0)),0)*N(C9))+IF(B10="",0,IFERROR(INDEX('_Развёртки'!$C$2:$C$1358,MATCH(B10&"|"&H34,'_Развёртки'!$D$2:$D$1358,0)),0)*N(C10))+IF(B11="",0,IFERROR(INDEX('_Развёртки'!$C$2:$C$1358,MATCH(B11&"|"&H34,'_Развёртки'!$D$2:$D$1358,0)),0)*N(C11))+IF(B12="",0,IFERROR(INDEX('_Развёртки'!$C$2:$C$1358,MATCH(B12&"|"&H34,'_Развёртки'!$D$2:$D$1358,0)),0)*N(C12))+IF(B13="",0,IFERROR(INDEX('_Развёртки'!$C$2:$C$1358,MATCH(B13&"|"&H34,'_Развёртки'!$D$2:$D$1358,0)),0)*N(C13))+IF(B14="",0,IFERROR(INDEX('_Развёртки'!$C$2:$C$1358,MATCH(B14&"|"&H34,'_Развёртки'!$D$2:$D$1358,0)),0)*N(C14))+IF(B15="",0,IFERROR(INDEX('_Развёртки'!$C$2:$C$1358,MATCH(B15&"|"&H34,'_Развёртки'!$D$2:$D$1358,0)),0)*N(C15))+IF(B16="",0,IFERROR(INDEX('_Развёртки'!$C$2:$C$1358,MATCH(B16&"|"&H34,'_Развёртки'!$D$2:$D$1358,0)),0)*N(C16))+IF(B17="",0,IFERROR(INDEX('_Развёртки'!$C$2:$C$1358,MATCH(B17&"|"&H34,'_Развёртки'!$D$2:$D$1358,0)),0)*N(C17))+IF(B18="",0,IFERROR(INDEX('_Развёртки'!$C$2:$C$1358,MATCH(B18&"|"&H34,'_Развёртки'!$D$2:$D$1358,0)),0)*N(C18))+IF(B19="",0,IFERROR(INDEX('_Развёртки'!$C$2:$C$1358,MATCH(B19&"|"&H34,'_Развёртки'!$D$2:$D$1358,0)),0)*N(C19))+IF(B20="",0,IFERROR(INDEX('_Развёртки'!$C$2:$C$1358,MATCH(B20&"|"&H34,'_Развёртки'!$D$2:$D$1358,0)),0)*N(C20))+IF(B21="",0,IFERROR(INDEX('_Развёртки'!$C$2:$C$1358,MATCH(B21&"|"&H34,'_Развёртки'!$D$2:$D$1358,0)),0)*N(C21))+IF(B22="",0,IFERROR(INDEX('_Развёртки'!$C$2:$C$1358,MATCH(B22&"|"&H34,'_Развёртки'!$D$2:$D$1358,0)),0)*N(C22))+IF(B23="",0,IFERROR(INDEX('_Развёртки'!$C$2:$C$1358,MATCH(B23&"|"&H34,'_Развёртки'!$D$2:$D$1358,0)),0)*N(C23))+IF(B24="",0,IFERROR(INDEX('_Развёртки'!$C$2:$C$1358,MATCH(B24&"|"&H34,'_Развёртки'!$D$2:$D$1358,0)),0)*N(C24))+IF(B25="",0,IFERROR(INDEX('_Развёртки'!$C$2:$C$1358,MATCH(B25&"|"&H34,'_Развёртки'!$D$2:$D$1358,0)),0)*N(C25))+IF(B26="",0,IFERROR(INDEX('_Развёртки'!$C$2:$C$1358,MATCH(B26&"|"&H34,'_Развёртки'!$D$2:$D$1358,0)),0)*N(C26))+IF(B27="",0,IFERROR(INDEX('_Развёртки'!$C$2:$C$1358,MATCH(B27&"|"&H34,'_Развёртки'!$D$2:$D$1358,0)),0)*N(C27))} -> 114.63918 | K34: =IFERROR(VLOOKUP(H34,'Сырьё'!$C$6:$E$233,3,FALSE()),IFERROR(VLOOKUP(H34,'Полупродукты'!$C$6:$E$60,3,FALSE()),0)) -> 7.3406 | L34: =IF(J34=0,0,J34*K34) -> 841.52036
G35: 24 | H35: Pigment Green PG 7 NC | I35: =IFERROR(VLOOKUP(H35,'Сырьё'!$C$6:$D$233,2,FALSE()),IFERROR(VLOOKUP(H35,'Полупродукты'!$C$6:$D$60,2,FALSE()),"кг")) -> кг | J35: {=IF(B8="",0,IFERROR(INDEX('_Развёртки'!$C$2:$C$1358,MATCH(B8&"|"&H35,'_Развёртки'!$D$2:$D$1358,0)),0)*N(C8))+IF(B9="",0,IFERROR(INDEX('_Развёртки'!$C$2:$C$1358,MATCH(B9&"|"&H35,'_Развёртки'!$D$2:$D$1358,0)),0)*N(C9))+IF(B10="",0,IFERROR(INDEX('_Развёртки'!$C$2:$C$1358,MATCH(B10&"|"&H35,'_Развёртки'!$D$2:$D$1358,0)),0)*N(C10))+IF(B11="",0,IFERROR(INDEX('_Развёртки'!$C$2:$C$1358,MATCH(B11&"|"&H35,'_Развёртки'!$D$2:$D$1358,0)),0)*N(C11))+IF(B12="",0,IFERROR(INDEX('_Развёртки'!$C$2:$C$1358,MATCH(B12&"|"&H35,'_Развёртки'!$D$2:$D$1358,0)),0)*N(C12))+IF(B13="",0,IFERROR(INDEX('_Развёртки'!$C$2:$C$1358,MATCH(B13&"|"&H35,'_Развёртки'!$D$2:$D$1358,0)),0)*N(C13))+IF(B14="",0,IFERROR(INDEX('_Развёртки'!$C$2:$C$1358,MATCH(B14&"|"&H35,'_Развёртки'!$D$2:$D$1358,0)),0)*N(C14))+IF(B15="",0,IFERROR(INDEX('_Развёртки'!$C$2:$C$1358,MATCH(B15&"|"&H35,'_Развёртки'!$D$2:$D$1358,0)),0)*N(C15))+IF(B16="",0,IFERROR(INDEX('_Развёртки'!$C$2:$C$1358,MATCH(B16&"|"&H35,'_Развёртки'!$D$2:$D$1358,0)),0)*N(C16))+IF(B17="",0,IFERROR(INDEX('_Развёртки'!$C$2:$C$1358,MATCH(B17&"|"&H35,'_Развёртки'!$D$2:$D$1358,0)),0)*N(C17))+IF(B18="",0,IFERROR(INDEX('_Развёртки'!$C$2:$C$1358,MATCH(B18&"|"&H35,'_Развёртки'!$D$2:$D$1358,0)),0)*N(C18))+IF(B19="",0,IFERROR(INDEX('_Развёртки'!$C$2:$C$1358,MATCH(B19&"|"&H35,'_Развёртки'!$D$2:$D$1358,0)),0)*N(C19))+IF(B20="",0,IFERROR(INDEX('_Развёртки'!$C$2:$C$1358,MATCH(B20&"|"&H35,'_Развёртки'!$D$2:$D$1358,0)),0)*N(C20))+IF(B21="",0,IFERROR(INDEX('_Развёртки'!$C$2:$C$1358,MATCH(B21&"|"&H35,'_Развёртки'!$D$2:$D$1358,0)),0)*N(C21))+IF(B22="",0,IFERROR(INDEX('_Развёртки'!$C$2:$C$1358,MATCH(B22&"|"&H35,'_Развёртки'!$D$2:$D$1358,0)),0)*N(C22))+IF(B23="",0,IFERROR(INDEX('_Развёртки'!$C$2:$C$1358,MATCH(B23&"|"&H35,'_Развёртки'!$D$2:$D$1358,0)),0)*N(C23))+IF(B24="",0,IFERROR(INDEX('_Развёртки'!$C$2:$C$1358,MATCH(B24&"|"&H35,'_Развёртки'!$D$2:$D$1358,0)),0)*N(C24))+IF(B25="",0,IFERROR(INDEX('_Развёртки'!$C$2:$C$1358,MATCH(B25&"|"&H35,'_Развёртки'!$D$2:$D$1358,0)),0)*N(C25))+IF(B26="",0,IFERROR(INDEX('_Развёртки'!$C$2:$C$1358,MATCH(B26&"|"&H35,'_Развёртки'!$D$2:$D$1358,0)),0)*N(C26))+IF(B27="",0,IFERROR(INDEX('_Развёртки'!$C$2:$C$1358,MATCH(B27&"|"&H35,'_Развёртки'!$D$2:$D$1358,0)),0)*N(C27))} -> 0 | K35: =IFERROR(VLOOKUP(H35,'Сырьё'!$C$6:$E$233,3,FALSE()),IFERROR(VLOOKUP(H35,'Полупродукты'!$C$6:$E$60,3,FALSE()),0)) -> 8.4 | L35: =IF(J35=0,0,J35*K35) -> 0
G36: 25 | H36: Pigment Magenta PR 57:1 от Химсвет | I36: =IFERROR(VLOOKUP(H36,'Сырьё'!$C$6:$D$233,2,FALSE()),IFERROR(VLOOKUP(H36,'Полупродукты'!$C$6:$D$60,2,FALSE()),"кг")) -> кг | J36: {=IF(B8="",0,IFERROR(INDEX('_Развёртки'!$C$2:$C$1358,MATCH(B8&"|"&H36,'_Развёртки'!$D$2:$D$1358,0)),0)*N(C8))+IF(B9="",0,IFERROR(INDEX('_Развёртки'!$C$2:$C$1358,MATCH(B9&"|"&H36,'_Развёртки'!$D$2:$D$1358,0)),0)*N(C9))+IF(B10="",0,IFERROR(INDEX('_Развёртки'!$C$2:$C$1358,MATCH(B10&"|"&H36,'_Развёртки'!$D$2:$D$1358,0)),0)*N(C10))+IF(B11="",0,IFERROR(INDEX('_Развёртки'!$C$2:$C$1358,MATCH(B11&"|"&H36,'_Развёртки'!$D$2:$D$1358,0)),0)*N(C11))+IF(B12="",0,IFERROR(INDEX('_Развёртки'!$C$2:$C$1358,MATCH(B12&"|"&H36,'_Развёртки'!$D$2:$D$1358,0)),0)*N(C12))+IF(B13="",0,IFERROR(INDEX('_Развёртки'!$C$2:$C$1358,MATCH(B13&"|"&H36,'_Развёртки'!$D$2:$D$1358,0)),0)*N(C13))+IF(B14="",0,IFERROR(INDEX('_Развёртки'!$C$2:$C$1358,MATCH(B14&"|"&H36,'_Развёртки'!$D$2:$D$1358,0)),0)*N(C14))+IF(B15="",0,IFERROR(INDEX('_Развёртки'!$C$2:$C$1358,MATCH(B15&"|"&H36,'_Развёртки'!$D$2:$D$1358,0)),0)*N(C15))+IF(B16="",0,IFERROR(INDEX('_Развёртки'!$C$2:$C$1358,MATCH(B16&"|"&H36,'_Развёртки'!$D$2:$D$1358,0)),0)*N(C16))+IF(B17="",0,IFERROR(INDEX('_Развёртки'!$C$2:$C$1358,MATCH(B17&"|"&H36,'_Развёртки'!$D$2:$D$1358,0)),0)*N(C17))+IF(B18="",0,IFERROR(INDEX('_Развёртки'!$C$2:$C$1358,MATCH(B18&"|"&H36,'_Развёртки'!$D$2:$D$1358,0)),0)*N(C18))+IF(B19="",0,IFERROR(INDEX('_Развёртки'!$C$2:$C$1358,MATCH(B19&"|"&H36,'_Развёртки'!$D$2:$D$1358,0)),0)*N(C19))+IF(B20="",0,IFERROR(INDEX('_Развёртки'!$C$2:$C$1358,MATCH(B20&"|"&H36,'_Развёртки'!$D$2:$D$1358,0)),0)*N(C20))+IF(B21="",0,IFERROR(INDEX('_Развёртки'!$C$2:$C$1358,MATCH(B21&"|"&H36,'_Развёртки'!$D$2:$D$1358,0)),0)*N(C21))+IF(B22="",0,IFERROR(INDEX('_Развёртки'!$C$2:$C$1358,MATCH(B22&"|"&H36,'_Развёртки'!$D$2:$D$1358,0)),0)*N(C22))+IF(B23="",0,IFERROR(INDEX('_Развёртки'!$C$2:$C$1358,MATCH(B23&"|"&H36,'_Развёртки'!$D$2:$D$1358,0)),0)*N(C23))+IF(B24="",0,IFERROR(INDEX('_Развёртки'!$C$2:$C$1358,MATCH(B24&"|"&H36,'_Развёртки'!$D$2:$D$1358,0)),0)*N(C24))+IF(B25="",0,IFERROR(INDEX('_Развёртки'!$C$2:$C$1358,MATCH(B25&"|"&H36,'_Развёртки'!$D$2:$D$1358,0)),0)*N(C25))+IF(B26="",0,IFERROR(INDEX('_Развёртки'!$C$2:$C$1358,MATCH(B26&"|"&H36,'_Развёртки'!$D$2:$D$1358,0)),0)*N(C26))+IF(B27="",0,IFERROR(INDEX('_Развёртки'!$C$2:$C$1358,MATCH(B27&"|"&H36,'_Развёртки'!$D$2:$D$1358,0)),0)*N(C27))} -> 1.2054 | K36: =IFERROR(VLOOKUP(H36,'Сырьё'!$C$6:$E$233,3,FALSE()),IFERROR(VLOOKUP(H36,'Полупродукты'!$C$6:$E$60,3,FALSE()),0)) -> 5.6362 | L36: =IF(J36=0,0,J36*K36) -> 6.7938755
G37: 26 | H37: Pigment Orange PO 34 | I37: =IFERROR(VLOOKUP(H37,'Сырьё'!$C$6:$D$233,2,FALSE()),IFERROR(VLOOKUP(H37,'Полупродукты'!$C$6:$D$60,2,FALSE()),"кг")) -> кг | J37: {=IF(B8="",0,IFERROR(INDEX('_Развёртки'!$C$2:$C$1358,MATCH(B8&"|"&H37,'_Развёртки'!$D$2:$D$1358,0)),0)*N(C8))+IF(B9="",0,IFERROR(INDEX('_Развёртки'!$C$2:$C$1358,MATCH(B9&"|"&H37,'_Развёртки'!$D$2:$D$1358,0)),0)*N(C9))+IF(B10="",0,IFERROR(INDEX('_Развёртки'!$C$2:$C$1358,MATCH(B10&"|"&H37,'_Развёртки'!$D$2:$D$1358,0)),0)*N(C10))+IF(B11="",0,IFERROR(INDEX('_Развёртки'!$C$2:$C$1358,MATCH(B11&"|"&H37,'_Развёртки'!$D$2:$D$1358,0)),0)*N(C11))+IF(B12="",0,IFERROR(INDEX('_Развёртки'!$C$2:$C$1358,MATCH(B12&"|"&H37,'_Развёртки'!$D$2:$D$1358,0)),0)*N(C12))+IF(B13="",0,IFERROR(INDEX('_Развёртки'!$C$2:$C$1358,MATCH(B13&"|"&H37,'_Развёртки'!$D$2:$D$1358,0)),0)*N(C13))+IF(B14="",0,IFERROR(INDEX('_Развёртки'!$C$2:$C$1358,MATCH(B14&"|"&H37,'_Развёртки'!$D$2:$D$1358,0)),0)*N(C14))+IF(B15="",0,IFERROR(INDEX('_Развёртки'!$C$2:$C$1358,MATCH(B15&"|"&H37,'_Развёртки'!$D$2:$D$1358,0)),0)*N(C15))+IF(B16="",0,IFERROR(INDEX('_Развёртки'!$C$2:$C$1358,MATCH(B16&"|"&H37,'_Развёртки'!$D$2:$D$1358,0)),0)*N(C16))+IF(B17="",0,IFERROR(INDEX('_Развёртки'!$C$2:$C$1358,MATCH(B17&"|"&H37,'_Развёртки'!$D$2:$D$1358,0)),0)*N(C17))+IF(B18="",0,IFERROR(INDEX('_Развёртки'!$C$2:$C$1358,MATCH(B18&"|"&H37,'_Развёртки'!$D$2:$D$1358,0)),0)*N(C18))+IF(B19="",0,IFERROR(INDEX('_Развёртки'!$C$2:$C$1358,MATCH(B19&"|"&H37,'_Развёртки'!$D$2:$D$1358,0)),0)*N(C19))+IF(B20="",0,IFERROR(INDEX('_Развёртки'!$C$2:$C$1358,MATCH(B20&"|"&H37,'_Развёртки'!$D$2:$D$1358,0)),0)*N(C20))+IF(B21="",0,IFERROR(INDEX('_Развёртки'!$C$2:$C$1358,MATCH(B21&"|"&H37,'_Развёртки'!$D$2:$D$1358,0)),0)*N(C21))+IF(B22="",0,IFERROR(INDEX('_Развёртки'!$C$2:$C$1358,MATCH(B22&"|"&H37,'_Развёртки'!$D$2:$D$1358,0)),0)*N(C22))+IF(B23="",0,IFERROR(INDEX('_Развёртки'!$C$2:$C$1358,MATCH(B23&"|"&H37,'_Развёртки'!$D$2:$D$1358,0)),0)*N(C23))+IF(B24="",0,IFERROR(INDEX('_Развёртки'!$C$2:$C$1358,MATCH(B24&"|"&H37,'_Развёртки'!$D$2:$D$1358,0)),0)*N(C24))+IF(B25="",0,IFERROR(INDEX('_Развёртки'!$C$2:$C$1358,MATCH(B25&"|"&H37,'_Развёртки'!$D$2:$D$1358,0)),0)*N(C25))+IF(B26="",0,IFERROR(INDEX('_Развёртки'!$C$2:$C$1358,MATCH(B26&"|"&H37,'_Развёртки'!$D$2:$D$1358,0)),0)*N(C26))+IF(B27="",0,IFERROR(INDEX('_Развёртки'!$C$2:$C$1358,MATCH(B27&"|"&H37,'_Развёртки'!$D$2:$D$1358,0)),0)*N(C27))} -> 4.7174 | K37: =IFERROR(VLOOKUP(H37,'Сырьё'!$C$6:$E$233,3,FALSE()),IFERROR(VLOOKUP(H37,'Полупродукты'!$C$6:$E$60,3,FALSE()),0)) -> 12.0149 | L37: =IF(J37=0,0,J37*K37) -> 56.679089
G38: 27 | H38: Pigment PW 6 White Белый R-996 (LOMON) | I38: =IFERROR(VLOOKUP(H38,'Сырьё'!$C$6:$D$233,2,FALSE()),IFERROR(VLOOKUP(H38,'Полупродукты'!$C$6:$D$60,2,FALSE()),"кг")) -> кг | J38: {=IF(B8="",0,IFERROR(INDEX('_Развёртки'!$C$2:$C$1358,MATCH(B8&"|"&H38,'_Развёртки'!$D$2:$D$1358,0)),0)*N(C8))+IF(B9="",0,IFERROR(INDEX('_Развёртки'!$C$2:$C$1358,MATCH(B9&"|"&H38,'_Развёртки'!$D$2:$D$1358,0)),0)*N(C9))+IF(B10="",0,IFERROR(INDEX('_Развёртки'!$C$2:$C$1358,MATCH(B10&"|"&H38,'_Развёртки'!$D$2:$D$1358,0)),0)*N(C10))+IF(B11="",0,IFERROR(INDEX('_Развёртки'!$C$2:$C$1358,MATCH(B11&"|"&H38,'_Развёртки'!$D$2:$D$1358,0)),0)*N(C11))+IF(B12="",0,IFERROR(INDEX('_Развёртки'!$C$2:$C$1358,MATCH(B12&"|"&H38,'_Развёртки'!$D$2:$D$1358,0)),0)*N(C12))+IF(B13="",0,IFERROR(INDEX('_Развёртки'!$C$2:$C$1358,MATCH(B13&"|"&H38,'_Развёртки'!$D$2:$D$1358,0)),0)*N(C13))+IF(B14="",0,IFERROR(INDEX('_Развёртки'!$C$2:$C$1358,MATCH(B14&"|"&H38,'_Развёртки'!$D$2:$D$1358,0)),0)*N(C14))+IF(B15="",0,IFERROR(INDEX('_Развёртки'!$C$2:$C$1358,MATCH(B15&"|"&H38,'_Развёртки'!$D$2:$D$1358,0)),0)*N(C15))+IF(B16="",0,IFERROR(INDEX('_Развёртки'!$C$2:$C$1358,MATCH(B16&"|"&H38,'_Развёртки'!$D$2:$D$1358,0)),0)*N(C16))+IF(B17="",0,IFERROR(INDEX('_Развёртки'!$C$2:$C$1358,MATCH(B17&"|"&H38,'_Развёртки'!$D$2:$D$1358,0)),0)*N(C17))+IF(B18="",0,IFERROR(INDEX('_Развёртки'!$C$2:$C$1358,MATCH(B18&"|"&H38,'_Развёртки'!$D$2:$D$1358,0)),0)*N(C18))+IF(B19="",0,IFERROR(INDEX('_Развёртки'!$C$2:$C$1358,MATCH(B19&"|"&H38,'_Развёртки'!$D$2:$D$1358,0)),0)*N(C19))+IF(B20="",0,IFERROR(INDEX('_Развёртки'!$C$2:$C$1358,MATCH(B20&"|"&H38,'_Развёртки'!$D$2:$D$1358,0)),0)*N(C20))+IF(B21="",0,IFERROR(INDEX('_Развёртки'!$C$2:$C$1358,MATCH(B21&"|"&H38,'_Развёртки'!$D$2:$D$1358,0)),0)*N(C21))+IF(B22="",0,IFERROR(INDEX('_Развёртки'!$C$2:$C$1358,MATCH(B22&"|"&H38,'_Развёртки'!$D$2:$D$1358,0)),0)*N(C22))+IF(B23="",0,IFERROR(INDEX('_Развёртки'!$C$2:$C$1358,MATCH(B23&"|"&H38,'_Развёртки'!$D$2:$D$1358,0)),0)*N(C23))+IF(B24="",0,IFERROR(INDEX('_Развёртки'!$C$2:$C$1358,MATCH(B24&"|"&H38,'_Развёртки'!$D$2:$D$1358,0)),0)*N(C24))+IF(B25="",0,IFERROR(INDEX('_Развёртки'!$C$2:$C$1358,MATCH(B25&"|"&H38,'_Развёртки'!$D$2:$D$1358,0)),0)*N(C25))+IF(B26="",0,IFERROR(INDEX('_Развёртки'!$C$2:$C$1358,MATCH(B26&"|"&H38,'_Развёртки'!$D$2:$D$1358,0)),0)*N(C26))+IF(B27="",0,IFERROR(INDEX('_Развёртки'!$C$2:$C$1358,MATCH(B27&"|"&H38,'_Развёртки'!$D$2:$D$1358,0)),0)*N(C27))} -> 0 | K38: =IFERROR(VLOOKUP(H38,'Сырьё'!$C$6:$E$233,3,FALSE()),IFERROR(VLOOKUP(H38,'Полупродукты'!$C$6:$E$60,3,FALSE()),0)) -> 2.53 | L38: =IF(J38=0,0,J38*K38) -> 0
G39: 28 | H39: Pigment RED (PR 254) ХС | I39: =IFERROR(VLOOKUP(H39,'Сырьё'!$C$6:$D$233,2,FALSE()),IFERROR(VLOOKUP(H39,'Полупродукты'!$C$6:$D$60,2,FALSE()),"кг")) -> кг | J39: {=IF(B8="",0,IFERROR(INDEX('_Развёртки'!$C$2:$C$1358,MATCH(B8&"|"&H39,'_Развёртки'!$D$2:$D$1358,0)),0)*N(C8))+IF(B9="",0,IFERROR(INDEX('_Развёртки'!$C$2:$C$1358,MATCH(B9&"|"&H39,'_Развёртки'!$D$2:$D$1358,0)),0)*N(C9))+IF(B10="",0,IFERROR(INDEX('_Развёртки'!$C$2:$C$1358,MATCH(B10&"|"&H39,'_Развёртки'!$D$2:$D$1358,0)),0)*N(C10))+IF(B11="",0,IFERROR(INDEX('_Развёртки'!$C$2:$C$1358,MATCH(B11&"|"&H39,'_Развёртки'!$D$2:$D$1358,0)),0)*N(C11))+IF(B12="",0,IFERROR(INDEX('_Развёртки'!$C$2:$C$1358,MATCH(B12&"|"&H39,'_Развёртки'!$D$2:$D$1358,0)),0)*N(C12))+IF(B13="",0,IFERROR(INDEX('_Развёртки'!$C$2:$C$1358,MATCH(B13&"|"&H39,'_Развёртки'!$D$2:$D$1358,0)),0)*N(C13))+IF(B14="",0,IFERROR(INDEX('_Развёртки'!$C$2:$C$1358,MATCH(B14&"|"&H39,'_Развёртки'!$D$2:$D$1358,0)),0)*N(C14))+IF(B15="",0,IFERROR(INDEX('_Развёртки'!$C$2:$C$1358,MATCH(B15&"|"&H39,'_Развёртки'!$D$2:$D$1358,0)),0)*N(C15))+IF(B16="",0,IFERROR(INDEX('_Развёртки'!$C$2:$C$1358,MATCH(B16&"|"&H39,'_Развёртки'!$D$2:$D$1358,0)),0)*N(C16))+IF(B17="",0,IFERROR(INDEX('_Развёртки'!$C$2:$C$1358,MATCH(B17&"|"&H39,'_Развёртки'!$D$2:$D$1358,0)),0)*N(C17))+IF(B18="",0,IFERROR(INDEX('_Развёртки'!$C$2:$C$1358,MATCH(B18&"|"&H39,'_Развёртки'!$D$2:$D$1358,0)),0)*N(C18))+IF(B19="",0,IFERROR(INDEX('_Развёртки'!$C$2:$C$1358,MATCH(B19&"|"&H39,'_Развёртки'!$D$2:$D$1358,0)),0)*N(C19))+IF(B20="",0,IFERROR(INDEX('_Развёртки'!$C$2:$C$1358,MATCH(B20&"|"&H39,'_Развёртки'!$D$2:$D$1358,0)),0)*N(C20))+IF(B21="",0,IFERROR(INDEX('_Развёртки'!$C$2:$C$1358,MATCH(B21&"|"&H39,'_Развёртки'!$D$2:$D$1358,0)),0)*N(C21))+IF(B22="",0,IFERROR(INDEX('_Развёртки'!$C$2:$C$1358,MATCH(B22&"|"&H39,'_Развёртки'!$D$2:$D$1358,0)),0)*N(C22))+IF(B23="",0,IFERROR(INDEX('_Развёртки'!$C$2:$C$1358,MATCH(B23&"|"&H39,'_Развёртки'!$D$2:$D$1358,0)),0)*N(C23))+IF(B24="",0,IFERROR(INDEX('_Развёртки'!$C$2:$C$1358,MATCH(B24&"|"&H39,'_Развёртки'!$D$2:$D$1358,0)),0)*N(C24))+IF(B25="",0,IFERROR(INDEX('_Развёртки'!$C$2:$C$1358,MATCH(B25&"|"&H39,'_Развёртки'!$D$2:$D$1358,0)),0)*N(C25))+IF(B26="",0,IFERROR(INDEX('_Развёртки'!$C$2:$C$1358,MATCH(B26&"|"&H39,'_Развёртки'!$D$2:$D$1358,0)),0)*N(C26))+IF(B27="",0,IFERROR(INDEX('_Развёртки'!$C$2:$C$1358,MATCH(B27&"|"&H39,'_Развёртки'!$D$2:$D$1358,0)),0)*N(C27))} -> 0 | K39: =IFERROR(VLOOKUP(H39,'Сырьё'!$C$6:$E$233,3,FALSE()),IFERROR(VLOOKUP(H39,'Полупродукты'!$C$6:$E$60,3,FALSE()),0)) -> 0 | L39: =IF(J39=0,0,J39*K39) -> 0
G40: 29 | H40: Pigment Red (PR 122) СИНТЕЗ ЦВЕТА | I40: =IFERROR(VLOOKUP(H40,'Сырьё'!$C$6:$D$233,2,FALSE()),IFERROR(VLOOKUP(H40,'Полупродукты'!$C$6:$D$60,2,FALSE()),"кг")) -> кг | J40: {=IF(B8="",0,IFERROR(INDEX('_Развёртки'!$C$2:$C$1358,MATCH(B8&"|"&H40,'_Развёртки'!$D$2:$D$1358,0)),0)*N(C8))+IF(B9="",0,IFERROR(INDEX('_Развёртки'!$C$2:$C$1358,MATCH(B9&"|"&H40,'_Развёртки'!$D$2:$D$1358,0)),0)*N(C9))+IF(B10="",0,IFERROR(INDEX('_Развёртки'!$C$2:$C$1358,MATCH(B10&"|"&H40,'_Развёртки'!$D$2:$D$1358,0)),0)*N(C10))+IF(B11="",0,IFERROR(INDEX('_Развёртки'!$C$2:$C$1358,MATCH(B11&"|"&H40,'_Развёртки'!$D$2:$D$1358,0)),0)*N(C11))+IF(B12="",0,IFERROR(INDEX('_Развёртки'!$C$2:$C$1358,MATCH(B12&"|"&H40,'_Развёртки'!$D$2:$D$1358,0)),0)*N(C12))+IF(B13="",0,IFERROR(INDEX('_Развёртки'!$C$2:$C$1358,MATCH(B13&"|"&H40,'_Развёртки'!$D$2:$D$1358,0)),0)*N(C13))+IF(B14="",0,IFERROR(INDEX('_Развёртки'!$C$2:$C$1358,MATCH(B14&"|"&H40,'_Развёртки'!$D$2:$D$1358,0)),0)*N(C14))+IF(B15="",0,IFERROR(INDEX('_Развёртки'!$C$2:$C$1358,MATCH(B15&"|"&H40,'_Развёртки'!$D$2:$D$1358,0)),0)*N(C15))+IF(B16="",0,IFERROR(INDEX('_Развёртки'!$C$2:$C$1358,MATCH(B16&"|"&H40,'_Развёртки'!$D$2:$D$1358,0)),0)*N(C16))+IF(B17="",0,IFERROR(INDEX('_Развёртки'!$C$2:$C$1358,MATCH(B17&"|"&H40,'_Развёртки'!$D$2:$D$1358,0)),0)*N(C17))+IF(B18="",0,IFERROR(INDEX('_Развёртки'!$C$2:$C$1358,MATCH(B18&"|"&H40,'_Развёртки'!$D$2:$D$1358,0)),0)*N(C18))+IF(B19="",0,IFERROR(INDEX('_Развёртки'!$C$2:$C$1358,MATCH(B19&"|"&H40,'_Развёртки'!$D$2:$D$1358,0)),0)*N(C19))+IF(B20="",0,IFERROR(INDEX('_Развёртки'!$C$2:$C$1358,MATCH(B20&"|"&H40,'_Развёртки'!$D$2:$D$1358,0)),0)*N(C20))+IF(B21="",0,IFERROR(INDEX('_Развёртки'!$C$2:$C$1358,MATCH(B21&"|"&H40,'_Развёртки'!$D$2:$D$1358,0)),0)*N(C21))+IF(B22="",0,IFERROR(INDEX('_Развёртки'!$C$2:$C$1358,MATCH(B22&"|"&H40,'_Развёртки'!$D$2:$D$1358,0)),0)*N(C22))+IF(B23="",0,IFERROR(INDEX('_Развёртки'!$C$2:$C$1358,MATCH(B23&"|"&H40,'_Развёртки'!$D$2:$D$1358,0)),0)*N(C23))+IF(B24="",0,IFERROR(INDEX('_Развёртки'!$C$2:$C$1358,MATCH(B24&"|"&H40,'_Развёртки'!$D$2:$D$1358,0)),0)*N(C24))+IF(B25="",0,IFERROR(INDEX('_Развёртки'!$C$2:$C$1358,MATCH(B25&"|"&H40,'_Развёртки'!$D$2:$D$1358,0)),0)*N(C25))+IF(B26="",0,IFERROR(INDEX('_Развёртки'!$C$2:$C$1358,MATCH(B26&"|"&H40,'_Развёртки'!$D$2:$D$1358,0)),0)*N(C26))+IF(B27="",0,IFERROR(INDEX('_Развёртки'!$C$2:$C$1358,MATCH(B27&"|"&H40,'_Развёртки'!$D$2:$D$1358,0)),0)*N(C27))} -> 0 | K40: =IFERROR(VLOOKUP(H40,'Сырьё'!$C$6:$E$233,3,FALSE()),IFERROR(VLOOKUP(H40,'Полупродукты'!$C$6:$E$60,3,FALSE()),0)) -> 0 | L40: =IF(J40=0,0,J40*K40) -> 0
G41: 30 | H41: Pigment Red 146 (FBB) (Формула успеха) | I41: =IFERROR(VLOOKUP(H41,'Сырьё'!$C$6:$D$233,2,FALSE()),IFERROR(VLOOKUP(H41,'Полупродукты'!$C$6:$D$60,2,FALSE()),"кг")) -> кг | J41: {=IF(B8="",0,IFERROR(INDEX('_Развёртки'!$C$2:$C$1358,MATCH(B8&"|"&H41,'_Развёртки'!$D$2:$D$1358,0)),0)*N(C8))+IF(B9="",0,IFERROR(INDEX('_Развёртки'!$C$2:$C$1358,MATCH(B9&"|"&H41,'_Развёртки'!$D$2:$D$1358,0)),0)*N(C9))+IF(B10="",0,IFERROR(INDEX('_Развёртки'!$C$2:$C$1358,MATCH(B10&"|"&H41,'_Развёртки'!$D$2:$D$1358,0)),0)*N(C10))+IF(B11="",0,IFERROR(INDEX('_Развёртки'!$C$2:$C$1358,MATCH(B11&"|"&H41,'_Развёртки'!$D$2:$D$1358,0)),0)*N(C11))+IF(B12="",0,IFERROR(INDEX('_Развёртки'!$C$2:$C$1358,MATCH(B12&"|"&H41,'_Развёртки'!$D$2:$D$1358,0)),0)*N(C12))+IF(B13="",0,IFERROR(INDEX('_Развёртки'!$C$2:$C$1358,MATCH(B13&"|"&H41,'_Развёртки'!$D$2:$D$1358,0)),0)*N(C13))+IF(B14="",0,IFERROR(INDEX('_Развёртки'!$C$2:$C$1358,MATCH(B14&"|"&H41,'_Развёртки'!$D$2:$D$1358,0)),0)*N(C14))+IF(B15="",0,IFERROR(INDEX('_Развёртки'!$C$2:$C$1358,MATCH(B15&"|"&H41,'_Развёртки'!$D$2:$D$1358,0)),0)*N(C15))+IF(B16="",0,IFERROR(INDEX('_Развёртки'!$C$2:$C$1358,MATCH(B16&"|"&H41,'_Развёртки'!$D$2:$D$1358,0)),0)*N(C16))+IF(B17="",0,IFERROR(INDEX('_Развёртки'!$C$2:$C$1358,MATCH(B17&"|"&H41,'_Развёртки'!$D$2:$D$1358,0)),0)*N(C17))+IF(B18="",0,IFERROR(INDEX('_Развёртки'!$C$2:$C$1358,MATCH(B18&"|"&H41,'_Развёртки'!$D$2:$D$1358,0)),0)*N(C18))+IF(B19="",0,IFERROR(INDEX('_Развёртки'!$C$2:$C$1358,MATCH(B19&"|"&H41,'_Развёртки'!$D$2:$D$1358,0)),0)*N(C19))+IF(B20="",0,IFERROR(INDEX('_Развёртки'!$C$2:$C$1358,MATCH(B20&"|"&H41,'_Развёртки'!$D$2:$D$1358,0)),0)*N(C20))+IF(B21="",0,IFERROR(INDEX('_Развёртки'!$C$2:$C$1358,MATCH(B21&"|"&H41,'_Развёртки'!$D$2:$D$1358,0)),0)*N(C21))+IF(B22="",0,IFERROR(INDEX('_Развёртки'!$C$2:$C$1358,MATCH(B22&"|"&H41,'_Развёртки'!$D$2:$D$1358,0)),0)*N(C22))+IF(B23="",0,IFERROR(INDEX('_Развёртки'!$C$2:$C$1358,MATCH(B23&"|"&H41,'_Развёртки'!$D$2:$D$1358,0)),0)*N(C23))+IF(B24="",0,IFERROR(INDEX('_Развёртки'!$C$2:$C$1358,MATCH(B24&"|"&H41,'_Развёртки'!$D$2:$D$1358,0)),0)*N(C24))+IF(B25="",0,IFERROR(INDEX('_Развёртки'!$C$2:$C$1358,MATCH(B25&"|"&H41,'_Развёртки'!$D$2:$D$1358,0)),0)*N(C25))+IF(B26="",0,IFERROR(INDEX('_Развёртки'!$C$2:$C$1358,MATCH(B26&"|"&H41,'_Развёртки'!$D$2:$D$1358,0)),0)*N(C26))+IF(B27="",0,IFERROR(INDEX('_Развёртки'!$C$2:$C$1358,MATCH(B27&"|"&H41,'_Развёртки'!$D$2:$D$1358,0)),0)*N(C27))} -> 0 | K41: =IFERROR(VLOOKUP(H41,'Сырьё'!$C$6:$E$233,3,FALSE()),IFERROR(VLOOKUP(H41,'Полупродукты'!$C$6:$E$60,3,FALSE()),0)) -> 18.9593 | L41: =IF(J41=0,0,J41*K41) -> 0
G42: 31 | H42: Pigment Silver ROTOVARIO 530-944 / ADD-B01M | I42: =IFERROR(VLOOKUP(H42,'Сырьё'!$C$6:$D$233,2,FALSE()),IFERROR(VLOOKUP(H42,'Полупродукты'!$C$6:$D$60,2,FALSE()),"кг")) -> кг | J42: {=IF(B8="",0,IFERROR(INDEX('_Развёртки'!$C$2:$C$1358,MATCH(B8&"|"&H42,'_Развёртки'!$D$2:$D$1358,0)),0)*N(C8))+IF(B9="",0,IFERROR(INDEX('_Развёртки'!$C$2:$C$1358,MATCH(B9&"|"&H42,'_Развёртки'!$D$2:$D$1358,0)),0)*N(C9))+IF(B10="",0,IFERROR(INDEX('_Развёртки'!$C$2:$C$1358,MATCH(B10&"|"&H42,'_Развёртки'!$D$2:$D$1358,0)),0)*N(C10))+IF(B11="",0,IFERROR(INDEX('_Развёртки'!$C$2:$C$1358,MATCH(B11&"|"&H42,'_Развёртки'!$D$2:$D$1358,0)),0)*N(C11))+IF(B12="",0,IFERROR(INDEX('_Развёртки'!$C$2:$C$1358,MATCH(B12&"|"&H42,'_Развёртки'!$D$2:$D$1358,0)),0)*N(C12))+IF(B13="",0,IFERROR(INDEX('_Развёртки'!$C$2:$C$1358,MATCH(B13&"|"&H42,'_Развёртки'!$D$2:$D$1358,0)),0)*N(C13))+IF(B14="",0,IFERROR(INDEX('_Развёртки'!$C$2:$C$1358,MATCH(B14&"|"&H42,'_Развёртки'!$D$2:$D$1358,0)),0)*N(C14))+IF(B15="",0,IFERROR(INDEX('_Развёртки'!$C$2:$C$1358,MATCH(B15&"|"&H42,'_Развёртки'!$D$2:$D$1358,0)),0)*N(C15))+IF(B16="",0,IFERROR(INDEX('_Развёртки'!$C$2:$C$1358,MATCH(B16&"|"&H42,'_Развёртки'!$D$2:$D$1358,0)),0)*N(C16))+IF(B17="",0,IFERROR(INDEX('_Развёртки'!$C$2:$C$1358,MATCH(B17&"|"&H42,'_Развёртки'!$D$2:$D$1358,0)),0)*N(C17))+IF(B18="",0,IFERROR(INDEX('_Развёртки'!$C$2:$C$1358,MATCH(B18&"|"&H42,'_Развёртки'!$D$2:$D$1358,0)),0)*N(C18))+IF(B19="",0,IFERROR(INDEX('_Развёртки'!$C$2:$C$1358,MATCH(B19&"|"&H42,'_Развёртки'!$D$2:$D$1358,0)),0)*N(C19))+IF(B20="",0,IFERROR(INDEX('_Развёртки'!$C$2:$C$1358,MATCH(B20&"|"&H42,'_Развёртки'!$D$2:$D$1358,0)),0)*N(C20))+IF(B21="",0,IFERROR(INDEX('_Развёртки'!$C$2:$C$1358,MATCH(B21&"|"&H42,'_Развёртки'!$D$2:$D$1358,0)),0)*N(C21))+IF(B22="",0,IFERROR(INDEX('_Развёртки'!$C$2:$C$1358,MATCH(B22&"|"&H42,'_Развёртки'!$D$2:$D$1358,0)),0)*N(C22))+IF(B23="",0,IFERROR(INDEX('_Развёртки'!$C$2:$C$1358,MATCH(B23&"|"&H42,'_Развёртки'!$D$2:$D$1358,0)),0)*N(C23))+IF(B24="",0,IFERROR(INDEX('_Развёртки'!$C$2:$C$1358,MATCH(B24&"|"&H42,'_Развёртки'!$D$2:$D$1358,0)),0)*N(C24))+IF(B25="",0,IFERROR(INDEX('_Развёртки'!$C$2:$C$1358,MATCH(B25&"|"&H42,'_Развёртки'!$D$2:$D$1358,0)),0)*N(C25))+IF(B26="",0,IFERROR(INDEX('_Развёртки'!$C$2:$C$1358,MATCH(B26&"|"&H42,'_Развёртки'!$D$2:$D$1358,0)),0)*N(C26))+IF(B27="",0,IFERROR(INDEX('_Развёртки'!$C$2:$C$1358,MATCH(B27&"|"&H42,'_Развёртки'!$D$2:$D$1358,0)),0)*N(C27))} -> 0 | K42: =IFERROR(VLOOKUP(H42,'Сырьё'!$C$6:$E$233,3,FALSE()),IFERROR(VLOOKUP(H42,'Полупродукты'!$C$6:$E$60,3,FALSE()),0)) -> 19.1461 | L42: =IF(J42=0,0,J42*K42) -> 0
G43: 32 | H43: Pigment Violet PV23 | I43: =IFERROR(VLOOKUP(H43,'Сырьё'!$C$6:$D$233,2,FALSE()),IFERROR(VLOOKUP(H43,'Полупродукты'!$C$6:$D$60,2,FALSE()),"кг")) -> кг | J43: {=IF(B8="",0,IFERROR(INDEX('_Развёртки'!$C$2:$C$1358,MATCH(B8&"|"&H43,'_Развёртки'!$D$2:$D$1358,0)),0)*N(C8))+IF(B9="",0,IFERROR(INDEX('_Развёртки'!$C$2:$C$1358,MATCH(B9&"|"&H43,'_Развёртки'!$D$2:$D$1358,0)),0)*N(C9))+IF(B10="",0,IFERROR(INDEX('_Развёртки'!$C$2:$C$1358,MATCH(B10&"|"&H43,'_Развёртки'!$D$2:$D$1358,0)),0)*N(C10))+IF(B11="",0,IFERROR(INDEX('_Развёртки'!$C$2:$C$1358,MATCH(B11&"|"&H43,'_Развёртки'!$D$2:$D$1358,0)),0)*N(C11))+IF(B12="",0,IFERROR(INDEX('_Развёртки'!$C$2:$C$1358,MATCH(B12&"|"&H43,'_Развёртки'!$D$2:$D$1358,0)),0)*N(C12))+IF(B13="",0,IFERROR(INDEX('_Развёртки'!$C$2:$C$1358,MATCH(B13&"|"&H43,'_Развёртки'!$D$2:$D$1358,0)),0)*N(C13))+IF(B14="",0,IFERROR(INDEX('_Развёртки'!$C$2:$C$1358,MATCH(B14&"|"&H43,'_Развёртки'!$D$2:$D$1358,0)),0)*N(C14))+IF(B15="",0,IFERROR(INDEX('_Развёртки'!$C$2:$C$1358,MATCH(B15&"|"&H43,'_Развёртки'!$D$2:$D$1358,0)),0)*N(C15))+IF(B16="",0,IFERROR(INDEX('_Развёртки'!$C$2:$C$1358,MATCH(B16&"|"&H43,'_Развёртки'!$D$2:$D$1358,0)),0)*N(C16))+IF(B17="",0,IFERROR(INDEX('_Развёртки'!$C$2:$C$1358,MATCH(B17&"|"&H43,'_Развёртки'!$D$2:$D$1358,0)),0)*N(C17))+IF(B18="",0,IFERROR(INDEX('_Развёртки'!$C$2:$C$1358,MATCH(B18&"|"&H43,'_Развёртки'!$D$2:$D$1358,0)),0)*N(C18))+IF(B19="",0,IFERROR(INDEX('_Развёртки'!$C$2:$C$1358,MATCH(B19&"|"&H43,'_Развёртки'!$D$2:$D$1358,0)),0)*N(C19))+IF(B20="",0,IFERROR(INDEX('_Развёртки'!$C$2:$C$1358,MATCH(B20&"|"&H43,'_Развёртки'!$D$2:$D$1358,0)),0)*N(C20))+IF(B21="",0,IFERROR(INDEX('_Развёртки'!$C$2:$C$1358,MATCH(B21&"|"&H43,'_Развёртки'!$D$2:$D$1358,0)),0)*N(C21))+IF(B22="",0,IFERROR(INDEX('_Развёртки'!$C$2:$C$1358,MATCH(B22&"|"&H43,'_Развёртки'!$D$2:$D$1358,0)),0)*N(C22))+IF(B23="",0,IFERROR(INDEX('_Развёртки'!$C$2:$C$1358,MATCH(B23&"|"&H43,'_Развёртки'!$D$2:$D$1358,0)),0)*N(C23))+IF(B24="",0,IFERROR(INDEX('_Развёртки'!$C$2:$C$1358,MATCH(B24&"|"&H43,'_Развёртки'!$D$2:$D$1358,0)),0)*N(C24))+IF(B25="",0,IFERROR(INDEX('_Развёртки'!$C$2:$C$1358,MATCH(B25&"|"&H43,'_Развёртки'!$D$2:$D$1358,0)),0)*N(C25))+IF(B26="",0,IFERROR(INDEX('_Развёртки'!$C$2:$C$1358,MATCH(B26&"|"&H43,'_Развёртки'!$D$2:$D$1358,0)),0)*N(C26))+IF(B27="",0,IFERROR(INDEX('_Развёртки'!$C$2:$C$1358,MATCH(B27&"|"&H43,'_Развёртки'!$D$2:$D$1358,0)),0)*N(C27))} -> 0 | K43: =IFERROR(VLOOKUP(H43,'Сырьё'!$C$6:$E$233,3,FALSE()),IFERROR(VLOOKUP(H43,'Полупродукты'!$C$6:$E$60,3,FALSE()),0)) -> 51.1495 | L43: =IF(J43=0,0,J43*K43) -> 0
G44: 33 | H44: Pigment Warm Red PR 53:1 ЕТС | I44: =IFERROR(VLOOKUP(H44,'Сырьё'!$C$6:$D$233,2,FALSE()),IFERROR(VLOOKUP(H44,'Полупродукты'!$C$6:$D$60,2,FALSE()),"кг")) -> кг | J44: {=IF(B8="",0,IFERROR(INDEX('_Развёртки'!$C$2:$C$1358,MATCH(B8&"|"&H44,'_Развёртки'!$D$2:$D$1358,0)),0)*N(C8))+IF(B9="",0,IFERROR(INDEX('_Развёртки'!$C$2:$C$1358,MATCH(B9&"|"&H44,'_Развёртки'!$D$2:$D$1358,0)),0)*N(C9))+IF(B10="",0,IFERROR(INDEX('_Развёртки'!$C$2:$C$1358,MATCH(B10&"|"&H44,'_Развёртки'!$D$2:$D$1358,0)),0)*N(C10))+IF(B11="",0,IFERROR(INDEX('_Развёртки'!$C$2:$C$1358,MATCH(B11&"|"&H44,'_Развёртки'!$D$2:$D$1358,0)),0)*N(C11))+IF(B12="",0,IFERROR(INDEX('_Развёртки'!$C$2:$C$1358,MATCH(B12&"|"&H44,'_Развёртки'!$D$2:$D$1358,0)),0)*N(C12))+IF(B13="",0,IFERROR(INDEX('_Развёртки'!$C$2:$C$1358,MATCH(B13&"|"&H44,'_Развёртки'!$D$2:$D$1358,0)),0)*N(C13))+IF(B14="",0,IFERROR(INDEX('_Развёртки'!$C$2:$C$1358,MATCH(B14&"|"&H44,'_Развёртки'!$D$2:$D$1358,0)),0)*N(C14))+IF(B15="",0,IFERROR(INDEX('_Развёртки'!$C$2:$C$1358,MATCH(B15&"|"&H44,'_Развёртки'!$D$2:$D$1358,0)),0)*N(C15))+IF(B16="",0,IFERROR(INDEX('_Развёртки'!$C$2:$C$1358,MATCH(B16&"|"&H44,'_Развёртки'!$D$2:$D$1358,0)),0)*N(C16))+IF(B17="",0,IFERROR(INDEX('_Развёртки'!$C$2:$C$1358,MATCH(B17&"|"&H44,'_Развёртки'!$D$2:$D$1358,0)),0)*N(C17))+IF(B18="",0,IFERROR(INDEX('_Развёртки'!$C$2:$C$1358,MATCH(B18&"|"&H44,'_Развёртки'!$D$2:$D$1358,0)),0)*N(C18))+IF(B19="",0,IFERROR(INDEX('_Развёртки'!$C$2:$C$1358,MATCH(B19&"|"&H44,'_Развёртки'!$D$2:$D$1358,0)),0)*N(C19))+IF(B20="",0,IFERROR(INDEX('_Развёртки'!$C$2:$C$1358,MATCH(B20&"|"&H44,'_Развёртки'!$D$2:$D$1358,0)),0)*N(C20))+IF(B21="",0,IFERROR(INDEX('_Развёртки'!$C$2:$C$1358,MATCH(B21&"|"&H44,'_Развёртки'!$D$2:$D$1358,0)),0)*N(C21))+IF(B22="",0,IFERROR(INDEX('_Развёртки'!$C$2:$C$1358,MATCH(B22&"|"&H44,'_Развёртки'!$D$2:$D$1358,0)),0)*N(C22))+IF(B23="",0,IFERROR(INDEX('_Развёртки'!$C$2:$C$1358,MATCH(B23&"|"&H44,'_Развёртки'!$D$2:$D$1358,0)),0)*N(C23))+IF(B24="",0,IFERROR(INDEX('_Развёртки'!$C$2:$C$1358,MATCH(B24&"|"&H44,'_Развёртки'!$D$2:$D$1358,0)),0)*N(C24))+IF(B25="",0,IFERROR(INDEX('_Развёртки'!$C$2:$C$1358,MATCH(B25&"|"&H44,'_Развёртки'!$D$2:$D$1358,0)),0)*N(C25))+IF(B26="",0,IFERROR(INDEX('_Развёртки'!$C$2:$C$1358,MATCH(B26&"|"&H44,'_Развёртки'!$D$2:$D$1358,0)),0)*N(C26))+IF(B27="",0,IFERROR(INDEX('_Развёртки'!$C$2:$C$1358,MATCH(B27&"|"&H44,'_Развёртки'!$D$2:$D$1358,0)),0)*N(C27))} -> 191.58 | K44: =IFERROR(VLOOKUP(H44,'Сырьё'!$C$6:$E$233,3,FALSE()),IFERROR(VLOOKUP(H44,'Полупродукты'!$C$6:$E$60,3,FALSE()),0)) -> 6.2082 | L44: =IF(J44=0,0,J44*K44) -> 1189.367
G45: 34 | H45: Pigment Yellow (PY 74)(синтез цвета) | I45: =IFERROR(VLOOKUP(H45,'Сырьё'!$C$6:$D$233,2,FALSE()),IFERROR(VLOOKUP(H45,'Полупродукты'!$C$6:$D$60,2,FALSE()),"кг")) -> кг | J45: {=IF(B8="",0,IFERROR(INDEX('_Развёртки'!$C$2:$C$1358,MATCH(B8&"|"&H45,'_Развёртки'!$D$2:$D$1358,0)),0)*N(C8))+IF(B9="",0,IFERROR(INDEX('_Развёртки'!$C$2:$C$1358,MATCH(B9&"|"&H45,'_Развёртки'!$D$2:$D$1358,0)),0)*N(C9))+IF(B10="",0,IFERROR(INDEX('_Развёртки'!$C$2:$C$1358,MATCH(B10&"|"&H45,'_Развёртки'!$D$2:$D$1358,0)),0)*N(C10))+IF(B11="",0,IFERROR(INDEX('_Развёртки'!$C$2:$C$1358,MATCH(B11&"|"&H45,'_Развёртки'!$D$2:$D$1358,0)),0)*N(C11))+IF(B12="",0,IFERROR(INDEX('_Развёртки'!$C$2:$C$1358,MATCH(B12&"|"&H45,'_Развёртки'!$D$2:$D$1358,0)),0)*N(C12))+IF(B13="",0,IFERROR(INDEX('_Развёртки'!$C$2:$C$1358,MATCH(B13&"|"&H45,'_Развёртки'!$D$2:$D$1358,0)),0)*N(C13))+IF(B14="",0,IFERROR(INDEX('_Развёртки'!$C$2:$C$1358,MATCH(B14&"|"&H45,'_Развёртки'!$D$2:$D$1358,0)),0)*N(C14))+IF(B15="",0,IFERROR(INDEX('_Развёртки'!$C$2:$C$1358,MATCH(B15&"|"&H45,'_Развёртки'!$D$2:$D$1358,0)),0)*N(C15))+IF(B16="",0,IFERROR(INDEX('_Развёртки'!$C$2:$C$1358,MATCH(B16&"|"&H45,'_Развёртки'!$D$2:$D$1358,0)),0)*N(C16))+IF(B17="",0,IFERROR(INDEX('_Развёртки'!$C$2:$C$1358,MATCH(B17&"|"&H45,'_Развёртки'!$D$2:$D$1358,0)),0)*N(C17))+IF(B18="",0,IFERROR(INDEX('_Развёртки'!$C$2:$C$1358,MATCH(B18&"|"&H45,'_Развёртки'!$D$2:$D$1358,0)),0)*N(C18))+IF(B19="",0,IFERROR(INDEX('_Развёртки'!$C$2:$C$1358,MATCH(B19&"|"&H45,'_Развёртки'!$D$2:$D$1358,0)),0)*N(C19))+IF(B20="",0,IFERROR(INDEX('_Развёртки'!$C$2:$C$1358,MATCH(B20&"|"&H45,'_Развёртки'!$D$2:$D$1358,0)),0)*N(C20))+IF(B21="",0,IFERROR(INDEX('_Развёртки'!$C$2:$C$1358,MATCH(B21&"|"&H45,'_Развёртки'!$D$2:$D$1358,0)),0)*N(C21))+IF(B22="",0,IFERROR(INDEX('_Развёртки'!$C$2:$C$1358,MATCH(B22&"|"&H45,'_Развёртки'!$D$2:$D$1358,0)),0)*N(C22))+IF(B23="",0,IFERROR(INDEX('_Развёртки'!$C$2:$C$1358,MATCH(B23&"|"&H45,'_Развёртки'!$D$2:$D$1358,0)),0)*N(C23))+IF(B24="",0,IFERROR(INDEX('_Развёртки'!$C$2:$C$1358,MATCH(B24&"|"&H45,'_Развёртки'!$D$2:$D$1358,0)),0)*N(C24))+IF(B25="",0,IFERROR(INDEX('_Развёртки'!$C$2:$C$1358,MATCH(B25&"|"&H45,'_Развёртки'!$D$2:$D$1358,0)),0)*N(C25))+IF(B26="",0,IFERROR(INDEX('_Развёртки'!$C$2:$C$1358,MATCH(B26&"|"&H45,'_Развёртки'!$D$2:$D$1358,0)),0)*N(C26))+IF(B27="",0,IFERROR(INDEX('_Развёртки'!$C$2:$C$1358,MATCH(B27&"|"&H45,'_Развёртки'!$D$2:$D$1358,0)),0)*N(C27))} -> 0 | K45: =IFERROR(VLOOKUP(H45,'Сырьё'!$C$6:$E$233,3,FALSE()),IFERROR(VLOOKUP(H45,'Полупродукты'!$C$6:$E$60,3,FALSE()),0)) -> 0 | L45: =IF(J45=0,0,J45*K45) -> 0
G46: 35 | H46: Pigment Yellow (PY 83)радиант | I46: =IFERROR(VLOOKUP(H46,'Сырьё'!$C$6:$D$233,2,FALSE()),IFERROR(VLOOKUP(H46,'Полупродукты'!$C$6:$D$60,2,FALSE()),"кг")) -> кг | J46: {=IF(B8="",0,IFERROR(INDEX('_Развёртки'!$C$2:$C$1358,MATCH(B8&"|"&H46,'_Развёртки'!$D$2:$D$1358,0)),0)*N(C8))+IF(B9="",0,IFERROR(INDEX('_Развёртки'!$C$2:$C$1358,MATCH(B9&"|"&H46,'_Развёртки'!$D$2:$D$1358,0)),0)*N(C9))+IF(B10="",0,IFERROR(INDEX('_Развёртки'!$C$2:$C$1358,MATCH(B10&"|"&H46,'_Развёртки'!$D$2:$D$1358,0)),0)*N(C10))+IF(B11="",0,IFERROR(INDEX('_Развёртки'!$C$2:$C$1358,MATCH(B11&"|"&H46,'_Развёртки'!$D$2:$D$1358,0)),0)*N(C11))+IF(B12="",0,IFERROR(INDEX('_Развёртки'!$C$2:$C$1358,MATCH(B12&"|"&H46,'_Развёртки'!$D$2:$D$1358,0)),0)*N(C12))+IF(B13="",0,IFERROR(INDEX('_Развёртки'!$C$2:$C$1358,MATCH(B13&"|"&H46,'_Развёртки'!$D$2:$D$1358,0)),0)*N(C13))+IF(B14="",0,IFERROR(INDEX('_Развёртки'!$C$2:$C$1358,MATCH(B14&"|"&H46,'_Развёртки'!$D$2:$D$1358,0)),0)*N(C14))+IF(B15="",0,IFERROR(INDEX('_Развёртки'!$C$2:$C$1358,MATCH(B15&"|"&H46,'_Развёртки'!$D$2:$D$1358,0)),0)*N(C15))+IF(B16="",0,IFERROR(INDEX('_Развёртки'!$C$2:$C$1358,MATCH(B16&"|"&H46,'_Развёртки'!$D$2:$D$1358,0)),0)*N(C16))+IF(B17="",0,IFERROR(INDEX('_Развёртки'!$C$2:$C$1358,MATCH(B17&"|"&H46,'_Развёртки'!$D$2:$D$1358,0)),0)*N(C17))+IF(B18="",0,IFERROR(INDEX('_Развёртки'!$C$2:$C$1358,MATCH(B18&"|"&H46,'_Развёртки'!$D$2:$D$1358,0)),0)*N(C18))+IF(B19="",0,IFERROR(INDEX('_Развёртки'!$C$2:$C$1358,MATCH(B19&"|"&H46,'_Развёртки'!$D$2:$D$1358,0)),0)*N(C19))+IF(B20="",0,IFERROR(INDEX('_Развёртки'!$C$2:$C$1358,MATCH(B20&"|"&H46,'_Развёртки'!$D$2:$D$1358,0)),0)*N(C20))+IF(B21="",0,IFERROR(INDEX('_Развёртки'!$C$2:$C$1358,MATCH(B21&"|"&H46,'_Развёртки'!$D$2:$D$1358,0)),0)*N(C21))+IF(B22="",0,IFERROR(INDEX('_Развёртки'!$C$2:$C$1358,MATCH(B22&"|"&H46,'_Развёртки'!$D$2:$D$1358,0)),0)*N(C22))+IF(B23="",0,IFERROR(INDEX('_Развёртки'!$C$2:$C$1358,MATCH(B23&"|"&H46,'_Развёртки'!$D$2:$D$1358,0)),0)*N(C23))+IF(B24="",0,IFERROR(INDEX('_Развёртки'!$C$2:$C$1358,MATCH(B24&"|"&H46,'_Развёртки'!$D$2:$D$1358,0)),0)*N(C24))+IF(B25="",0,IFERROR(INDEX('_Развёртки'!$C$2:$C$1358,MATCH(B25&"|"&H46,'_Развёртки'!$D$2:$D$1358,0)),0)*N(C25))+IF(B26="",0,IFERROR(INDEX('_Развёртки'!$C$2:$C$1358,MATCH(B26&"|"&H46,'_Развёртки'!$D$2:$D$1358,0)),0)*N(C26))+IF(B27="",0,IFERROR(INDEX('_Развёртки'!$C$2:$C$1358,MATCH(B27&"|"&H46,'_Развёртки'!$D$2:$D$1358,0)),0)*N(C27))} -> 0 | K46: =IFERROR(VLOOKUP(H46,'Сырьё'!$C$6:$E$233,3,FALSE()),IFERROR(VLOOKUP(H46,'Полупродукты'!$C$6:$E$60,3,FALSE()),0)) -> 0 | L46: =IF(J46=0,0,J46*K46) -> 0
G47: 36 | H47: Pigment Yellow PY 13 ЕТС | I47: =IFERROR(VLOOKUP(H47,'Сырьё'!$C$6:$D$233,2,FALSE()),IFERROR(VLOOKUP(H47,'Полупродукты'!$C$6:$D$60,2,FALSE()),"кг")) -> кг | J47: {=IF(B8="",0,IFERROR(INDEX('_Развёртки'!$C$2:$C$1358,MATCH(B8&"|"&H47,'_Развёртки'!$D$2:$D$1358,0)),0)*N(C8))+IF(B9="",0,IFERROR(INDEX('_Развёртки'!$C$2:$C$1358,MATCH(B9&"|"&H47,'_Развёртки'!$D$2:$D$1358,0)),0)*N(C9))+IF(B10="",0,IFERROR(INDEX('_Развёртки'!$C$2:$C$1358,MATCH(B10&"|"&H47,'_Развёртки'!$D$2:$D$1358,0)),0)*N(C10))+IF(B11="",0,IFERROR(INDEX('_Развёртки'!$C$2:$C$1358,MATCH(B11&"|"&H47,'_Развёртки'!$D$2:$D$1358,0)),0)*N(C11))+IF(B12="",0,IFERROR(INDEX('_Развёртки'!$C$2:$C$1358,MATCH(B12&"|"&H47,'_Развёртки'!$D$2:$D$1358,0)),0)*N(C12))+IF(B13="",0,IFERROR(INDEX('_Развёртки'!$C$2:$C$1358,MATCH(B13&"|"&H47,'_Развёртки'!$D$2:$D$1358,0)),0)*N(C13))+IF(B14="",0,IFERROR(INDEX('_Развёртки'!$C$2:$C$1358,MATCH(B14&"|"&H47,'_Развёртки'!$D$2:$D$1358,0)),0)*N(C14))+IF(B15="",0,IFERROR(INDEX('_Развёртки'!$C$2:$C$1358,MATCH(B15&"|"&H47,'_Развёртки'!$D$2:$D$1358,0)),0)*N(C15))+IF(B16="",0,IFERROR(INDEX('_Развёртки'!$C$2:$C$1358,MATCH(B16&"|"&H47,'_Развёртки'!$D$2:$D$1358,0)),0)*N(C16))+IF(B17="",0,IFERROR(INDEX('_Развёртки'!$C$2:$C$1358,MATCH(B17&"|"&H47,'_Развёртки'!$D$2:$D$1358,0)),0)*N(C17))+IF(B18="",0,IFERROR(INDEX('_Развёртки'!$C$2:$C$1358,MATCH(B18&"|"&H47,'_Развёртки'!$D$2:$D$1358,0)),0)*N(C18))+IF(B19="",0,IFERROR(INDEX('_Развёртки'!$C$2:$C$1358,MATCH(B19&"|"&H47,'_Развёртки'!$D$2:$D$1358,0)),0)*N(C19))+IF(B20="",0,IFERROR(INDEX('_Развёртки'!$C$2:$C$1358,MATCH(B20&"|"&H47,'_Развёртки'!$D$2:$D$1358,0)),0)*N(C20))+IF(B21="",0,IFERROR(INDEX('_Развёртки'!$C$2:$C$1358,MATCH(B21&"|"&H47,'_Развёртки'!$D$2:$D$1358,0)),0)*N(C21))+IF(B22="",0,IFERROR(INDEX('_Развёртки'!$C$2:$C$1358,MATCH(B22&"|"&H47,'_Развёртки'!$D$2:$D$1358,0)),0)*N(C22))+IF(B23="",0,IFERROR(INDEX('_Развёртки'!$C$2:$C$1358,MATCH(B23&"|"&H47,'_Развёртки'!$D$2:$D$1358,0)),0)*N(C23))+IF(B24="",0,IFERROR(INDEX('_Развёртки'!$C$2:$C$1358,MATCH(B24&"|"&H47,'_Развёртки'!$D$2:$D$1358,0)),0)*N(C24))+IF(B25="",0,IFERROR(INDEX('_Развёртки'!$C$2:$C$1358,MATCH(B25&"|"&H47,'_Развёртки'!$D$2:$D$1358,0)),0)*N(C25))+IF(B26="",0,IFERROR(INDEX('_Развёртки'!$C$2:$C$1358,MATCH(B26&"|"&H47,'_Развёртки'!$D$2:$D$1358,0)),0)*N(C26))+IF(B27="",0,IFERROR(INDEX('_Развёртки'!$C$2:$C$1358,MATCH(B27&"|"&H47,'_Развёртки'!$D$2:$D$1358,0)),0)*N(C27))} -> 230.5888 | K47: =IFERROR(VLOOKUP(H47,'Сырьё'!$C$6:$E$233,3,FALSE()),IFERROR(VLOOKUP(H47,'Полупродукты'!$C$6:$E$60,3,FALSE()),0)) -> 0 | L47: =IF(J47=0,0,J47*K47) -> 0
G48: 37 | H48: Pigment Yellow PY 13 Пигмент органический Liperm BH-TXL (Радиант Кем.) | I48: =IFERROR(VLOOKUP(H48,'Сырьё'!$C$6:$D$233,2,FALSE()),IFERROR(VLOOKUP(H48,'Полупродукты'!$C$6:$D$60,2,FALSE()),"кг")) -> кг | J48: {=IF(B8="",0,IFERROR(INDEX('_Развёртки'!$C$2:$C$1358,MATCH(B8&"|"&H48,'_Развёртки'!$D$2:$D$1358,0)),0)*N(C8))+IF(B9="",0,IFERROR(INDEX('_Развёртки'!$C$2:$C$1358,MATCH(B9&"|"&H48,'_Развёртки'!$D$2:$D$1358,0)),0)*N(C9))+IF(B10="",0,IFERROR(INDEX('_Развёртки'!$C$2:$C$1358,MATCH(B10&"|"&H48,'_Развёртки'!$D$2:$D$1358,0)),0)*N(C10))+IF(B11="",0,IFERROR(INDEX('_Развёртки'!$C$2:$C$1358,MATCH(B11&"|"&H48,'_Развёртки'!$D$2:$D$1358,0)),0)*N(C11))+IF(B12="",0,IFERROR(INDEX('_Развёртки'!$C$2:$C$1358,MATCH(B12&"|"&H48,'_Развёртки'!$D$2:$D$1358,0)),0)*N(C12))+IF(B13="",0,IFERROR(INDEX('_Развёртки'!$C$2:$C$1358,MATCH(B13&"|"&H48,'_Развёртки'!$D$2:$D$1358,0)),0)*N(C13))+IF(B14="",0,IFERROR(INDEX('_Развёртки'!$C$2:$C$1358,MATCH(B14&"|"&H48,'_Развёртки'!$D$2:$D$1358,0)),0)*N(C14))+IF(B15="",0,IFERROR(INDEX('_Развёртки'!$C$2:$C$1358,MATCH(B15&"|"&H48,'_Развёртки'!$D$2:$D$1358,0)),0)*N(C15))+IF(B16="",0,IFERROR(INDEX('_Развёртки'!$C$2:$C$1358,MATCH(B16&"|"&H48,'_Развёртки'!$D$2:$D$1358,0)),0)*N(C16))+IF(B17="",0,IFERROR(INDEX('_Развёртки'!$C$2:$C$1358,MATCH(B17&"|"&H48,'_Развёртки'!$D$2:$D$1358,0)),0)*N(C17))+IF(B18="",0,IFERROR(INDEX('_Развёртки'!$C$2:$C$1358,MATCH(B18&"|"&H48,'_Развёртки'!$D$2:$D$1358,0)),0)*N(C18))+IF(B19="",0,IFERROR(INDEX('_Развёртки'!$C$2:$C$1358,MATCH(B19&"|"&H48,'_Развёртки'!$D$2:$D$1358,0)),0)*N(C19))+IF(B20="",0,IFERROR(INDEX('_Развёртки'!$C$2:$C$1358,MATCH(B20&"|"&H48,'_Развёртки'!$D$2:$D$1358,0)),0)*N(C20))+IF(B21="",0,IFERROR(INDEX('_Развёртки'!$C$2:$C$1358,MATCH(B21&"|"&H48,'_Развёртки'!$D$2:$D$1358,0)),0)*N(C21))+IF(B22="",0,IFERROR(INDEX('_Развёртки'!$C$2:$C$1358,MATCH(B22&"|"&H48,'_Развёртки'!$D$2:$D$1358,0)),0)*N(C22))+IF(B23="",0,IFERROR(INDEX('_Развёртки'!$C$2:$C$1358,MATCH(B23&"|"&H48,'_Развёртки'!$D$2:$D$1358,0)),0)*N(C23))+IF(B24="",0,IFERROR(INDEX('_Развёртки'!$C$2:$C$1358,MATCH(B24&"|"&H48,'_Развёртки'!$D$2:$D$1358,0)),0)*N(C24))+IF(B25="",0,IFERROR(INDEX('_Развёртки'!$C$2:$C$1358,MATCH(B25&"|"&H48,'_Развёртки'!$D$2:$D$1358,0)),0)*N(C25))+IF(B26="",0,IFERROR(INDEX('_Развёртки'!$C$2:$C$1358,MATCH(B26&"|"&H48,'_Развёртки'!$D$2:$D$1358,0)),0)*N(C26))+IF(B27="",0,IFERROR(INDEX('_Развёртки'!$C$2:$C$1358,MATCH(B27&"|"&H48,'_Развёртки'!$D$2:$D$1358,0)),0)*N(C27))} -> 0 | K48: =IFERROR(VLOOKUP(H48,'Сырьё'!$C$6:$E$233,3,FALSE()),IFERROR(VLOOKUP(H48,'Полупродукты'!$C$6:$E$60,3,FALSE()),0)) -> 5.1326 | L48: =IF(J48=0,0,J48*K48) -> 0
G49: 38 | H49: RPC Additive | I49: =IFERROR(VLOOKUP(H49,'Сырьё'!$C$6:$D$233,2,FALSE()),IFERROR(VLOOKUP(H49,'Полупродукты'!$C$6:$D$60,2,FALSE()),"кг")) -> кг | J49: {=IF(B8="",0,IFERROR(INDEX('_Развёртки'!$C$2:$C$1358,MATCH(B8&"|"&H49,'_Развёртки'!$D$2:$D$1358,0)),0)*N(C8))+IF(B9="",0,IFERROR(INDEX('_Развёртки'!$C$2:$C$1358,MATCH(B9&"|"&H49,'_Развёртки'!$D$2:$D$1358,0)),0)*N(C9))+IF(B10="",0,IFERROR(INDEX('_Развёртки'!$C$2:$C$1358,MATCH(B10&"|"&H49,'_Развёртки'!$D$2:$D$1358,0)),0)*N(C10))+IF(B11="",0,IFERROR(INDEX('_Развёртки'!$C$2:$C$1358,MATCH(B11&"|"&H49,'_Развёртки'!$D$2:$D$1358,0)),0)*N(C11))+IF(B12="",0,IFERROR(INDEX('_Развёртки'!$C$2:$C$1358,MATCH(B12&"|"&H49,'_Развёртки'!$D$2:$D$1358,0)),0)*N(C12))+IF(B13="",0,IFERROR(INDEX('_Развёртки'!$C$2:$C$1358,MATCH(B13&"|"&H49,'_Развёртки'!$D$2:$D$1358,0)),0)*N(C13))+IF(B14="",0,IFERROR(INDEX('_Развёртки'!$C$2:$C$1358,MATCH(B14&"|"&H49,'_Развёртки'!$D$2:$D$1358,0)),0)*N(C14))+IF(B15="",0,IFERROR(INDEX('_Развёртки'!$C$2:$C$1358,MATCH(B15&"|"&H49,'_Развёртки'!$D$2:$D$1358,0)),0)*N(C15))+IF(B16="",0,IFERROR(INDEX('_Развёртки'!$C$2:$C$1358,MATCH(B16&"|"&H49,'_Развёртки'!$D$2:$D$1358,0)),0)*N(C16))+IF(B17="",0,IFERROR(INDEX('_Развёртки'!$C$2:$C$1358,MATCH(B17&"|"&H49,'_Развёртки'!$D$2:$D$1358,0)),0)*N(C17))+IF(B18="",0,IFERROR(INDEX('_Развёртки'!$C$2:$C$1358,MATCH(B18&"|"&H49,'_Развёртки'!$D$2:$D$1358,0)),0)*N(C18))+IF(B19="",0,IFERROR(INDEX('_Развёртки'!$C$2:$C$1358,MATCH(B19&"|"&H49,'_Развёртки'!$D$2:$D$1358,0)),0)*N(C19))+IF(B20="",0,IFERROR(INDEX('_Развёртки'!$C$2:$C$1358,MATCH(B20&"|"&H49,'_Развёртки'!$D$2:$D$1358,0)),0)*N(C20))+IF(B21="",0,IFERROR(INDEX('_Развёртки'!$C$2:$C$1358,MATCH(B21&"|"&H49,'_Развёртки'!$D$2:$D$1358,0)),0)*N(C21))+IF(B22="",0,IFERROR(INDEX('_Развёртки'!$C$2:$C$1358,MATCH(B22&"|"&H49,'_Развёртки'!$D$2:$D$1358,0)),0)*N(C22))+IF(B23="",0,IFERROR(INDEX('_Развёртки'!$C$2:$C$1358,MATCH(B23&"|"&H49,'_Развёртки'!$D$2:$D$1358,0)),0)*N(C23))+IF(B24="",0,IFERROR(INDEX('_Развёртки'!$C$2:$C$1358,MATCH(B24&"|"&H49,'_Развёртки'!$D$2:$D$1358,0)),0)*N(C24))+IF(B25="",0,IFERROR(INDEX('_Развёртки'!$C$2:$C$1358,MATCH(B25&"|"&H49,'_Развёртки'!$D$2:$D$1358,0)),0)*N(C25))+IF(B26="",0,IFERROR(INDEX('_Развёртки'!$C$2:$C$1358,MATCH(B26&"|"&H49,'_Развёртки'!$D$2:$D$1358,0)),0)*N(C26))+IF(B27="",0,IFERROR(INDEX('_Развёртки'!$C$2:$C$1358,MATCH(B27&"|"&H49,'_Развёртки'!$D$2:$D$1358,0)),0)*N(C27))} -> 252.418 | K49: =IFERROR(VLOOKUP(H49,'Сырьё'!$C$6:$E$233,3,FALSE()),IFERROR(VLOOKUP(H49,'Полупродукты'!$C$6:$E$60,3,FALSE()),0)) -> 3.2853 | L49: =IF(J49=0,0,J49*K49) -> 829.26886
G50: 39 | H50: RPC Additive 397 | I50: =IFERROR(VLOOKUP(H50,'Сырьё'!$C$6:$D$233,2,FALSE()),IFERROR(VLOOKUP(H50,'Полупродукты'!$C$6:$D$60,2,FALSE()),"кг")) -> кг | J50: {=IF(B8="",0,IFERROR(INDEX('_Развёртки'!$C$2:$C$1358,MATCH(B8&"|"&H50,'_Развёртки'!$D$2:$D$1358,0)),0)*N(C8))+IF(B9="",0,IFERROR(INDEX('_Развёртки'!$C$2:$C$1358,MATCH(B9&"|"&H50,'_Развёртки'!$D$2:$D$1358,0)),0)*N(C9))+IF(B10="",0,IFERROR(INDEX('_Развёртки'!$C$2:$C$1358,MATCH(B10&"|"&H50,'_Развёртки'!$D$2:$D$1358,0)),0)*N(C10))+IF(B11="",0,IFERROR(INDEX('_Развёртки'!$C$2:$C$1358,MATCH(B11&"|"&H50,'_Развёртки'!$D$2:$D$1358,0)),0)*N(C11))+IF(B12="",0,IFERROR(INDEX('_Развёртки'!$C$2:$C$1358,MATCH(B12&"|"&H50,'_Развёртки'!$D$2:$D$1358,0)),0)*N(C12))+IF(B13="",0,IFERROR(INDEX('_Развёртки'!$C$2:$C$1358,MATCH(B13&"|"&H50,'_Развёртки'!$D$2:$D$1358,0)),0)*N(C13))+IF(B14="",0,IFERROR(INDEX('_Развёртки'!$C$2:$C$1358,MATCH(B14&"|"&H50,'_Развёртки'!$D$2:$D$1358,0)),0)*N(C14))+IF(B15="",0,IFERROR(INDEX('_Развёртки'!$C$2:$C$1358,MATCH(B15&"|"&H50,'_Развёртки'!$D$2:$D$1358,0)),0)*N(C15))+IF(B16="",0,IFERROR(INDEX('_Развёртки'!$C$2:$C$1358,MATCH(B16&"|"&H50,'_Развёртки'!$D$2:$D$1358,0)),0)*N(C16))+IF(B17="",0,IFERROR(INDEX('_Развёртки'!$C$2:$C$1358,MATCH(B17&"|"&H50,'_Развёртки'!$D$2:$D$1358,0)),0)*N(C17))+IF(B18="",0,IFERROR(INDEX('_Развёртки'!$C$2:$C$1358,MATCH(B18&"|"&H50,'_Развёртки'!$D$2:$D$1358,0)),0)*N(C18))+IF(B19="",0,IFERROR(INDEX('_Развёртки'!$C$2:$C$1358,MATCH(B19&"|"&H50,'_Развёртки'!$D$2:$D$1358,0)),0)*N(C19))+IF(B20="",0,IFERROR(INDEX('_Развёртки'!$C$2:$C$1358,MATCH(B20&"|"&H50,'_Развёртки'!$D$2:$D$1358,0)),0)*N(C20))+IF(B21="",0,IFERROR(INDEX('_Развёртки'!$C$2:$C$1358,MATCH(B21&"|"&H50,'_Развёртки'!$D$2:$D$1358,0)),0)*N(C21))+IF(B22="",0,IFERROR(INDEX('_Развёртки'!$C$2:$C$1358,MATCH(B22&"|"&H50,'_Развёртки'!$D$2:$D$1358,0)),0)*N(C22))+IF(B23="",0,IFERROR(INDEX('_Развёртки'!$C$2:$C$1358,MATCH(B23&"|"&H50,'_Развёртки'!$D$2:$D$1358,0)),0)*N(C23))+IF(B24="",0,IFERROR(INDEX('_Развёртки'!$C$2:$C$1358,MATCH(B24&"|"&H50,'_Развёртки'!$D$2:$D$1358,0)),0)*N(C24))+IF(B25="",0,IFERROR(INDEX('_Развёртки'!$C$2:$C$1358,MATCH(B25&"|"&H50,'_Развёртки'!$D$2:$D$1358,0)),0)*N(C25))+IF(B26="",0,IFERROR(INDEX('_Развёртки'!$C$2:$C$1358,MATCH(B26&"|"&H50,'_Развёртки'!$D$2:$D$1358,0)),0)*N(C26))+IF(B27="",0,IFERROR(INDEX('_Развёртки'!$C$2:$C$1358,MATCH(B27&"|"&H50,'_Развёртки'!$D$2:$D$1358,0)),0)*N(C27))} -> 749.93536 | K50: =IFERROR(VLOOKUP(H50,'Сырьё'!$C$6:$E$233,3,FALSE()),IFERROR(VLOOKUP(H50,'Полупродукты'!$C$6:$E$60,3,FALSE()),0)) -> 3.3046 | L50: =IF(J50=0,0,J50*K50) -> 2478.2364
G51: 40 | H51: TCA-IAM20 (аналог Титан АП 100/Титан АП 130 Д) | I51: =IFERROR(VLOOKUP(H51,'Сырьё'!$C$6:$D$233,2,FALSE()),IFERROR(VLOOKUP(H51,'Полупродукты'!$C$6:$D$60,2,FALSE()),"кг")) -> кг | J51: {=IF(B8="",0,IFERROR(INDEX('_Развёртки'!$C$2:$C$1358,MATCH(B8&"|"&H51,'_Развёртки'!$D$2:$D$1358,0)),0)*N(C8))+IF(B9="",0,IFERROR(INDEX('_Развёртки'!$C$2:$C$1358,MATCH(B9&"|"&H51,'_Развёртки'!$D$2:$D$1358,0)),0)*N(C9))+IF(B10="",0,IFERROR(INDEX('_Развёртки'!$C$2:$C$1358,MATCH(B10&"|"&H51,'_Развёртки'!$D$2:$D$1358,0)),0)*N(C10))+IF(B11="",0,IFERROR(INDEX('_Развёртки'!$C$2:$C$1358,MATCH(B11&"|"&H51,'_Развёртки'!$D$2:$D$1358,0)),0)*N(C11))+IF(B12="",0,IFERROR(INDEX('_Развёртки'!$C$2:$C$1358,MATCH(B12&"|"&H51,'_Развёртки'!$D$2:$D$1358,0)),0)*N(C12))+IF(B13="",0,IFERROR(INDEX('_Развёртки'!$C$2:$C$1358,MATCH(B13&"|"&H51,'_Развёртки'!$D$2:$D$1358,0)),0)*N(C13))+IF(B14="",0,IFERROR(INDEX('_Развёртки'!$C$2:$C$1358,MATCH(B14&"|"&H51,'_Развёртки'!$D$2:$D$1358,0)),0)*N(C14))+IF(B15="",0,IFERROR(INDEX('_Развёртки'!$C$2:$C$1358,MATCH(B15&"|"&H51,'_Развёртки'!$D$2:$D$1358,0)),0)*N(C15))+IF(B16="",0,IFERROR(INDEX('_Развёртки'!$C$2:$C$1358,MATCH(B16&"|"&H51,'_Развёртки'!$D$2:$D$1358,0)),0)*N(C16))+IF(B17="",0,IFERROR(INDEX('_Развёртки'!$C$2:$C$1358,MATCH(B17&"|"&H51,'_Развёртки'!$D$2:$D$1358,0)),0)*N(C17))+IF(B18="",0,IFERROR(INDEX('_Развёртки'!$C$2:$C$1358,MATCH(B18&"|"&H51,'_Развёртки'!$D$2:$D$1358,0)),0)*N(C18))+IF(B19="",0,IFERROR(INDEX('_Развёртки'!$C$2:$C$1358,MATCH(B19&"|"&H51,'_Развёртки'!$D$2:$D$1358,0)),0)*N(C19))+IF(B20="",0,IFERROR(INDEX('_Развёртки'!$C$2:$C$1358,MATCH(B20&"|"&H51,'_Развёртки'!$D$2:$D$1358,0)),0)*N(C20))+IF(B21="",0,IFERROR(INDEX('_Развёртки'!$C$2:$C$1358,MATCH(B21&"|"&H51,'_Развёртки'!$D$2:$D$1358,0)),0)*N(C21))+IF(B22="",0,IFERROR(INDEX('_Развёртки'!$C$2:$C$1358,MATCH(B22&"|"&H51,'_Развёртки'!$D$2:$D$1358,0)),0)*N(C22))+IF(B23="",0,IFERROR(INDEX('_Развёртки'!$C$2:$C$1358,MATCH(B23&"|"&H51,'_Развёртки'!$D$2:$D$1358,0)),0)*N(C23))+IF(B24="",0,IFERROR(INDEX('_Развёртки'!$C$2:$C$1358,MATCH(B24&"|"&H51,'_Развёртки'!$D$2:$D$1358,0)),0)*N(C24))+IF(B25="",0,IFERROR(INDEX('_Развёртки'!$C$2:$C$1358,MATCH(B25&"|"&H51,'_Развёртки'!$D$2:$D$1358,0)),0)*N(C25))+IF(B26="",0,IFERROR(INDEX('_Развёртки'!$C$2:$C$1358,MATCH(B26&"|"&H51,'_Развёртки'!$D$2:$D$1358,0)),0)*N(C26))+IF(B27="",0,IFERROR(INDEX('_Развёртки'!$C$2:$C$1358,MATCH(B27&"|"&H51,'_Развёртки'!$D$2:$D$1358,0)),0)*N(C27))} -> 56.135 | K51: =IFERROR(VLOOKUP(H51,'Сырьё'!$C$6:$E$233,3,FALSE()),IFERROR(VLOOKUP(H51,'Полупродукты'!$C$6:$E$60,3,FALSE()),0)) -> 14.556 | L51: =IF(J51=0,0,J51*K51) -> 817.10106
G52: 41 | H52: Vinil resin (MVOH) | I52: =IFERROR(VLOOKUP(H52,'Сырьё'!$C$6:$D$233,2,FALSE()),IFERROR(VLOOKUP(H52,'Полупродукты'!$C$6:$D$60,2,FALSE()),"кг")) -> кг | J52: {=IF(B8="",0,IFERROR(INDEX('_Развёртки'!$C$2:$C$1358,MATCH(B8&"|"&H52,'_Развёртки'!$D$2:$D$1358,0)),0)*N(C8))+IF(B9="",0,IFERROR(INDEX('_Развёртки'!$C$2:$C$1358,MATCH(B9&"|"&H52,'_Развёртки'!$D$2:$D$1358,0)),0)*N(C9))+IF(B10="",0,IFERROR(INDEX('_Развёртки'!$C$2:$C$1358,MATCH(B10&"|"&H52,'_Развёртки'!$D$2:$D$1358,0)),0)*N(C10))+IF(B11="",0,IFERROR(INDEX('_Развёртки'!$C$2:$C$1358,MATCH(B11&"|"&H52,'_Развёртки'!$D$2:$D$1358,0)),0)*N(C11))+IF(B12="",0,IFERROR(INDEX('_Развёртки'!$C$2:$C$1358,MATCH(B12&"|"&H52,'_Развёртки'!$D$2:$D$1358,0)),0)*N(C12))+IF(B13="",0,IFERROR(INDEX('_Развёртки'!$C$2:$C$1358,MATCH(B13&"|"&H52,'_Развёртки'!$D$2:$D$1358,0)),0)*N(C13))+IF(B14="",0,IFERROR(INDEX('_Развёртки'!$C$2:$C$1358,MATCH(B14&"|"&H52,'_Развёртки'!$D$2:$D$1358,0)),0)*N(C14))+IF(B15="",0,IFERROR(INDEX('_Развёртки'!$C$2:$C$1358,MATCH(B15&"|"&H52,'_Развёртки'!$D$2:$D$1358,0)),0)*N(C15))+IF(B16="",0,IFERROR(INDEX('_Развёртки'!$C$2:$C$1358,MATCH(B16&"|"&H52,'_Развёртки'!$D$2:$D$1358,0)),0)*N(C16))+IF(B17="",0,IFERROR(INDEX('_Развёртки'!$C$2:$C$1358,MATCH(B17&"|"&H52,'_Развёртки'!$D$2:$D$1358,0)),0)*N(C17))+IF(B18="",0,IFERROR(INDEX('_Развёртки'!$C$2:$C$1358,MATCH(B18&"|"&H52,'_Развёртки'!$D$2:$D$1358,0)),0)*N(C18))+IF(B19="",0,IFERROR(INDEX('_Развёртки'!$C$2:$C$1358,MATCH(B19&"|"&H52,'_Развёртки'!$D$2:$D$1358,0)),0)*N(C19))+IF(B20="",0,IFERROR(INDEX('_Развёртки'!$C$2:$C$1358,MATCH(B20&"|"&H52,'_Развёртки'!$D$2:$D$1358,0)),0)*N(C20))+IF(B21="",0,IFERROR(INDEX('_Развёртки'!$C$2:$C$1358,MATCH(B21&"|"&H52,'_Развёртки'!$D$2:$D$1358,0)),0)*N(C21))+IF(B22="",0,IFERROR(INDEX('_Развёртки'!$C$2:$C$1358,MATCH(B22&"|"&H52,'_Развёртки'!$D$2:$D$1358,0)),0)*N(C22))+IF(B23="",0,IFERROR(INDEX('_Развёртки'!$C$2:$C$1358,MATCH(B23&"|"&H52,'_Развёртки'!$D$2:$D$1358,0)),0)*N(C23))+IF(B24="",0,IFERROR(INDEX('_Развёртки'!$C$2:$C$1358,MATCH(B24&"|"&H52,'_Развёртки'!$D$2:$D$1358,0)),0)*N(C24))+IF(B25="",0,IFERROR(INDEX('_Развёртки'!$C$2:$C$1358,MATCH(B25&"|"&H52,'_Развёртки'!$D$2:$D$1358,0)),0)*N(C25))+IF(B26="",0,IFERROR(INDEX('_Развёртки'!$C$2:$C$1358,MATCH(B26&"|"&H52,'_Развёртки'!$D$2:$D$1358,0)),0)*N(C26))+IF(B27="",0,IFERROR(INDEX('_Развёртки'!$C$2:$C$1358,MATCH(B27&"|"&H52,'_Развёртки'!$D$2:$D$1358,0)),0)*N(C27))} -> 0 | K52: =IFERROR(VLOOKUP(H52,'Сырьё'!$C$6:$E$233,3,FALSE()),IFERROR(VLOOKUP(H52,'Полупродукты'!$C$6:$E$60,3,FALSE()),0)) -> 6.4085 | L52: =IF(J52=0,0,J52*K52) -> 0
G53: 42 | H53: Wax-Erucamide paste | I53: =IFERROR(VLOOKUP(H53,'Сырьё'!$C$6:$D$233,2,FALSE()),IFERROR(VLOOKUP(H53,'Полупродукты'!$C$6:$D$60,2,FALSE()),"кг")) -> кг | J53: {=IF(B8="",0,IFERROR(INDEX('_Развёртки'!$C$2:$C$1358,MATCH(B8&"|"&H53,'_Развёртки'!$D$2:$D$1358,0)),0)*N(C8))+IF(B9="",0,IFERROR(INDEX('_Развёртки'!$C$2:$C$1358,MATCH(B9&"|"&H53,'_Развёртки'!$D$2:$D$1358,0)),0)*N(C9))+IF(B10="",0,IFERROR(INDEX('_Развёртки'!$C$2:$C$1358,MATCH(B10&"|"&H53,'_Развёртки'!$D$2:$D$1358,0)),0)*N(C10))+IF(B11="",0,IFERROR(INDEX('_Развёртки'!$C$2:$C$1358,MATCH(B11&"|"&H53,'_Развёртки'!$D$2:$D$1358,0)),0)*N(C11))+IF(B12="",0,IFERROR(INDEX('_Развёртки'!$C$2:$C$1358,MATCH(B12&"|"&H53,'_Развёртки'!$D$2:$D$1358,0)),0)*N(C12))+IF(B13="",0,IFERROR(INDEX('_Развёртки'!$C$2:$C$1358,MATCH(B13&"|"&H53,'_Развёртки'!$D$2:$D$1358,0)),0)*N(C13))+IF(B14="",0,IFERROR(INDEX('_Развёртки'!$C$2:$C$1358,MATCH(B14&"|"&H53,'_Развёртки'!$D$2:$D$1358,0)),0)*N(C14))+IF(B15="",0,IFERROR(INDEX('_Развёртки'!$C$2:$C$1358,MATCH(B15&"|"&H53,'_Развёртки'!$D$2:$D$1358,0)),0)*N(C15))+IF(B16="",0,IFERROR(INDEX('_Развёртки'!$C$2:$C$1358,MATCH(B16&"|"&H53,'_Развёртки'!$D$2:$D$1358,0)),0)*N(C16))+IF(B17="",0,IFERROR(INDEX('_Развёртки'!$C$2:$C$1358,MATCH(B17&"|"&H53,'_Развёртки'!$D$2:$D$1358,0)),0)*N(C17))+IF(B18="",0,IFERROR(INDEX('_Развёртки'!$C$2:$C$1358,MATCH(B18&"|"&H53,'_Развёртки'!$D$2:$D$1358,0)),0)*N(C18))+IF(B19="",0,IFERROR(INDEX('_Развёртки'!$C$2:$C$1358,MATCH(B19&"|"&H53,'_Развёртки'!$D$2:$D$1358,0)),0)*N(C19))+IF(B20="",0,IFERROR(INDEX('_Развёртки'!$C$2:$C$1358,MATCH(B20&"|"&H53,'_Развёртки'!$D$2:$D$1358,0)),0)*N(C20))+IF(B21="",0,IFERROR(INDEX('_Развёртки'!$C$2:$C$1358,MATCH(B21&"|"&H53,'_Развёртки'!$D$2:$D$1358,0)),0)*N(C21))+IF(B22="",0,IFERROR(INDEX('_Развёртки'!$C$2:$C$1358,MATCH(B22&"|"&H53,'_Развёртки'!$D$2:$D$1358,0)),0)*N(C22))+IF(B23="",0,IFERROR(INDEX('_Развёртки'!$C$2:$C$1358,MATCH(B23&"|"&H53,'_Развёртки'!$D$2:$D$1358,0)),0)*N(C23))+IF(B24="",0,IFERROR(INDEX('_Развёртки'!$C$2:$C$1358,MATCH(B24&"|"&H53,'_Развёртки'!$D$2:$D$1358,0)),0)*N(C24))+IF(B25="",0,IFERROR(INDEX('_Развёртки'!$C$2:$C$1358,MATCH(B25&"|"&H53,'_Развёртки'!$D$2:$D$1358,0)),0)*N(C25))+IF(B26="",0,IFERROR(INDEX('_Развёртки'!$C$2:$C$1358,MATCH(B26&"|"&H53,'_Развёртки'!$D$2:$D$1358,0)),0)*N(C26))+IF(B27="",0,IFERROR(INDEX('_Развёртки'!$C$2:$C$1358,MATCH(B27&"|"&H53,'_Развёртки'!$D$2:$D$1358,0)),0)*N(C27))} -> 5.15 | K53: =IFERROR(VLOOKUP(H53,'Сырьё'!$C$6:$E$233,3,FALSE()),IFERROR(VLOOKUP(H53,'Полупродукты'!$C$6:$E$60,3,FALSE()),0)) -> 4.7016 | L53: =IF(J53=0,0,J53*K53) -> 24.21324
G54: 43 | H54: YL-904 | I54: =IFERROR(VLOOKUP(H54,'Сырьё'!$C$6:$D$233,2,FALSE()),IFERROR(VLOOKUP(H54,'Полупродукты'!$C$6:$D$60,2,FALSE()),"кг")) -> кг | J54: {=IF(B8="",0,IFERROR(INDEX('_Развёртки'!$C$2:$C$1358,MATCH(B8&"|"&H54,'_Развёртки'!$D$2:$D$1358,0)),0)*N(C8))+IF(B9="",0,IFERROR(INDEX('_Развёртки'!$C$2:$C$1358,MATCH(B9&"|"&H54,'_Развёртки'!$D$2:$D$1358,0)),0)*N(C9))+IF(B10="",0,IFERROR(INDEX('_Развёртки'!$C$2:$C$1358,MATCH(B10&"|"&H54,'_Развёртки'!$D$2:$D$1358,0)),0)*N(C10))+IF(B11="",0,IFERROR(INDEX('_Развёртки'!$C$2:$C$1358,MATCH(B11&"|"&H54,'_Развёртки'!$D$2:$D$1358,0)),0)*N(C11))+IF(B12="",0,IFERROR(INDEX('_Развёртки'!$C$2:$C$1358,MATCH(B12&"|"&H54,'_Развёртки'!$D$2:$D$1358,0)),0)*N(C12))+IF(B13="",0,IFERROR(INDEX('_Развёртки'!$C$2:$C$1358,MATCH(B13&"|"&H54,'_Развёртки'!$D$2:$D$1358,0)),0)*N(C13))+IF(B14="",0,IFERROR(INDEX('_Развёртки'!$C$2:$C$1358,MATCH(B14&"|"&H54,'_Развёртки'!$D$2:$D$1358,0)),0)*N(C14))+IF(B15="",0,IFERROR(INDEX('_Развёртки'!$C$2:$C$1358,MATCH(B15&"|"&H54,'_Развёртки'!$D$2:$D$1358,0)),0)*N(C15))+IF(B16="",0,IFERROR(INDEX('_Развёртки'!$C$2:$C$1358,MATCH(B16&"|"&H54,'_Развёртки'!$D$2:$D$1358,0)),0)*N(C16))+IF(B17="",0,IFERROR(INDEX('_Развёртки'!$C$2:$C$1358,MATCH(B17&"|"&H54,'_Развёртки'!$D$2:$D$1358,0)),0)*N(C17))+IF(B18="",0,IFERROR(INDEX('_Развёртки'!$C$2:$C$1358,MATCH(B18&"|"&H54,'_Развёртки'!$D$2:$D$1358,0)),0)*N(C18))+IF(B19="",0,IFERROR(INDEX('_Развёртки'!$C$2:$C$1358,MATCH(B19&"|"&H54,'_Развёртки'!$D$2:$D$1358,0)),0)*N(C19))+IF(B20="",0,IFERROR(INDEX('_Развёртки'!$C$2:$C$1358,MATCH(B20&"|"&H54,'_Развёртки'!$D$2:$D$1358,0)),0)*N(C20))+IF(B21="",0,IFERROR(INDEX('_Развёртки'!$C$2:$C$1358,MATCH(B21&"|"&H54,'_Развёртки'!$D$2:$D$1358,0)),0)*N(C21))+IF(B22="",0,IFERROR(INDEX('_Развёртки'!$C$2:$C$1358,MATCH(B22&"|"&H54,'_Развёртки'!$D$2:$D$1358,0)),0)*N(C22))+IF(B23="",0,IFERROR(INDEX('_Развёртки'!$C$2:$C$1358,MATCH(B23&"|"&H54,'_Развёртки'!$D$2:$D$1358,0)),0)*N(C23))+IF(B24="",0,IFERROR(INDEX('_Развёртки'!$C$2:$C$1358,MATCH(B24&"|"&H54,'_Развёртки'!$D$2:$D$1358,0)),0)*N(C24))+IF(B25="",0,IFERROR(INDEX('_Развёртки'!$C$2:$C$1358,MATCH(B25&"|"&H54,'_Развёртки'!$D$2:$D$1358,0)),0)*N(C25))+IF(B26="",0,IFERROR(INDEX('_Развёртки'!$C$2:$C$1358,MATCH(B26&"|"&H54,'_Развёртки'!$D$2:$D$1358,0)),0)*N(C26))+IF(B27="",0,IFERROR(INDEX('_Развёртки'!$C$2:$C$1358,MATCH(B27&"|"&H54,'_Развёртки'!$D$2:$D$1358,0)),0)*N(C27))} -> 0 | K54: =IFERROR(VLOOKUP(H54,'Сырьё'!$C$6:$E$233,3,FALSE()),IFERROR(VLOOKUP(H54,'Полупродукты'!$C$6:$E$60,3,FALSE()),0)) -> 0 | L54: =IF(J54=0,0,J54*K54) -> 0
G55: 44 | H55: YL-904 (Восковая добавка для ОС) | I55: =IFERROR(VLOOKUP(H55,'Сырьё'!$C$6:$D$233,2,FALSE()),IFERROR(VLOOKUP(H55,'Полупродукты'!$C$6:$D$60,2,FALSE()),"кг")) -> кг | J55: {=IF(B8="",0,IFERROR(INDEX('_Развёртки'!$C$2:$C$1358,MATCH(B8&"|"&H55,'_Развёртки'!$D$2:$D$1358,0)),0)*N(C8))+IF(B9="",0,IFERROR(INDEX('_Развёртки'!$C$2:$C$1358,MATCH(B9&"|"&H55,'_Развёртки'!$D$2:$D$1358,0)),0)*N(C9))+IF(B10="",0,IFERROR(INDEX('_Развёртки'!$C$2:$C$1358,MATCH(B10&"|"&H55,'_Развёртки'!$D$2:$D$1358,0)),0)*N(C10))+IF(B11="",0,IFERROR(INDEX('_Развёртки'!$C$2:$C$1358,MATCH(B11&"|"&H55,'_Развёртки'!$D$2:$D$1358,0)),0)*N(C11))+IF(B12="",0,IFERROR(INDEX('_Развёртки'!$C$2:$C$1358,MATCH(B12&"|"&H55,'_Развёртки'!$D$2:$D$1358,0)),0)*N(C12))+IF(B13="",0,IFERROR(INDEX('_Развёртки'!$C$2:$C$1358,MATCH(B13&"|"&H55,'_Развёртки'!$D$2:$D$1358,0)),0)*N(C13))+IF(B14="",0,IFERROR(INDEX('_Развёртки'!$C$2:$C$1358,MATCH(B14&"|"&H55,'_Развёртки'!$D$2:$D$1358,0)),0)*N(C14))+IF(B15="",0,IFERROR(INDEX('_Развёртки'!$C$2:$C$1358,MATCH(B15&"|"&H55,'_Развёртки'!$D$2:$D$1358,0)),0)*N(C15))+IF(B16="",0,IFERROR(INDEX('_Развёртки'!$C$2:$C$1358,MATCH(B16&"|"&H55,'_Развёртки'!$D$2:$D$1358,0)),0)*N(C16))+IF(B17="",0,IFERROR(INDEX('_Развёртки'!$C$2:$C$1358,MATCH(B17&"|"&H55,'_Развёртки'!$D$2:$D$1358,0)),0)*N(C17))+IF(B18="",0,IFERROR(INDEX('_Развёртки'!$C$2:$C$1358,MATCH(B18&"|"&H55,'_Развёртки'!$D$2:$D$1358,0)),0)*N(C18))+IF(B19="",0,IFERROR(INDEX('_Развёртки'!$C$2:$C$1358,MATCH(B19&"|"&H55,'_Развёртки'!$D$2:$D$1358,0)),0)*N(C19))+IF(B20="",0,IFERROR(INDEX('_Развёртки'!$C$2:$C$1358,MATCH(B20&"|"&H55,'_Развёртки'!$D$2:$D$1358,0)),0)*N(C20))+IF(B21="",0,IFERROR(INDEX('_Развёртки'!$C$2:$C$1358,MATCH(B21&"|"&H55,'_Развёртки'!$D$2:$D$1358,0)),0)*N(C21))+IF(B22="",0,IFERROR(INDEX('_Развёртки'!$C$2:$C$1358,MATCH(B22&"|"&H55,'_Развёртки'!$D$2:$D$1358,0)),0)*N(C22))+IF(B23="",0,IFERROR(INDEX('_Развёртки'!$C$2:$C$1358,MATCH(B23&"|"&H55,'_Развёртки'!$D$2:$D$1358,0)),0)*N(C23))+IF(B24="",0,IFERROR(INDEX('_Развёртки'!$C$2:$C$1358,MATCH(B24&"|"&H55,'_Развёртки'!$D$2:$D$1358,0)),0)*N(C24))+IF(B25="",0,IFERROR(INDEX('_Развёртки'!$C$2:$C$1358,MATCH(B25&"|"&H55,'_Развёртки'!$D$2:$D$1358,0)),0)*N(C25))+IF(B26="",0,IFERROR(INDEX('_Развёртки'!$C$2:$C$1358,MATCH(B26&"|"&H55,'_Развёртки'!$D$2:$D$1358,0)),0)*N(C26))+IF(B27="",0,IFERROR(INDEX('_Развёртки'!$C$2:$C$1358,MATCH(B27&"|"&H55,'_Развёртки'!$D$2:$D$1358,0)),0)*N(C27))} -> 0 | K55: =IFERROR(VLOOKUP(H55,'Сырьё'!$C$6:$E$233,3,FALSE()),IFERROR(VLOOKUP(H55,'Полупродукты'!$C$6:$E$60,3,FALSE()),0)) -> 16.0088 | L55: =IF(J55=0,0,J55*K55) -> 0
G56: 45 | H56: Диоксид кремния Fusil 200 (Радиант Кем.) | I56: =IFERROR(VLOOKUP(H56,'Сырьё'!$C$6:$D$233,2,FALSE()),IFERROR(VLOOKUP(H56,'Полупродукты'!$C$6:$D$60,2,FALSE()),"кг")) -> шт | J56: {=IF(B8="",0,IFERROR(INDEX('_Развёртки'!$C$2:$C$1358,MATCH(B8&"|"&H56,'_Развёртки'!$D$2:$D$1358,0)),0)*N(C8))+IF(B9="",0,IFERROR(INDEX('_Развёртки'!$C$2:$C$1358,MATCH(B9&"|"&H56,'_Развёртки'!$D$2:$D$1358,0)),0)*N(C9))+IF(B10="",0,IFERROR(INDEX('_Развёртки'!$C$2:$C$1358,MATCH(B10&"|"&H56,'_Развёртки'!$D$2:$D$1358,0)),0)*N(C10))+IF(B11="",0,IFERROR(INDEX('_Развёртки'!$C$2:$C$1358,MATCH(B11&"|"&H56,'_Развёртки'!$D$2:$D$1358,0)),0)*N(C11))+IF(B12="",0,IFERROR(INDEX('_Развёртки'!$C$2:$C$1358,MATCH(B12&"|"&H56,'_Развёртки'!$D$2:$D$1358,0)),0)*N(C12))+IF(B13="",0,IFERROR(INDEX('_Развёртки'!$C$2:$C$1358,MATCH(B13&"|"&H56,'_Развёртки'!$D$2:$D$1358,0)),0)*N(C13))+IF(B14="",0,IFERROR(INDEX('_Развёртки'!$C$2:$C$1358,MATCH(B14&"|"&H56,'_Развёртки'!$D$2:$D$1358,0)),0)*N(C14))+IF(B15="",0,IFERROR(INDEX('_Развёртки'!$C$2:$C$1358,MATCH(B15&"|"&H56,'_Развёртки'!$D$2:$D$1358,0)),0)*N(C15))+IF(B16="",0,IFERROR(INDEX('_Развёртки'!$C$2:$C$1358,MATCH(B16&"|"&H56,'_Развёртки'!$D$2:$D$1358,0)),0)*N(C16))+IF(B17="",0,IFERROR(INDEX('_Развёртки'!$C$2:$C$1358,MATCH(B17&"|"&H56,'_Развёртки'!$D$2:$D$1358,0)),0)*N(C17))+IF(B18="",0,IFERROR(INDEX('_Развёртки'!$C$2:$C$1358,MATCH(B18&"|"&H56,'_Развёртки'!$D$2:$D$1358,0)),0)*N(C18))+IF(B19="",0,IFERROR(INDEX('_Развёртки'!$C$2:$C$1358,MATCH(B19&"|"&H56,'_Развёртки'!$D$2:$D$1358,0)),0)*N(C19))+IF(B20="",0,IFERROR(INDEX('_Развёртки'!$C$2:$C$1358,MATCH(B20&"|"&H56,'_Развёртки'!$D$2:$D$1358,0)),0)*N(C20))+IF(B21="",0,IFERROR(INDEX('_Развёртки'!$C$2:$C$1358,MATCH(B21&"|"&H56,'_Развёртки'!$D$2:$D$1358,0)),0)*N(C21))+IF(B22="",0,IFERROR(INDEX('_Развёртки'!$C$2:$C$1358,MATCH(B22&"|"&H56,'_Развёртки'!$D$2:$D$1358,0)),0)*N(C22))+IF(B23="",0,IFERROR(INDEX('_Развёртки'!$C$2:$C$1358,MATCH(B23&"|"&H56,'_Развёртки'!$D$2:$D$1358,0)),0)*N(C23))+IF(B24="",0,IFERROR(INDEX('_Развёртки'!$C$2:$C$1358,MATCH(B24&"|"&H56,'_Развёртки'!$D$2:$D$1358,0)),0)*N(C24))+IF(B25="",0,IFERROR(INDEX('_Развёртки'!$C$2:$C$1358,MATCH(B25&"|"&H56,'_Развёртки'!$D$2:$D$1358,0)),0)*N(C25))+IF(B26="",0,IFERROR(INDEX('_Развёртки'!$C$2:$C$1358,MATCH(B26&"|"&H56,'_Развёртки'!$D$2:$D$1358,0)),0)*N(C26))+IF(B27="",0,IFERROR(INDEX('_Развёртки'!$C$2:$C$1358,MATCH(B27&"|"&H56,'_Развёртки'!$D$2:$D$1358,0)),0)*N(C27))} -> 0 | K56: =IFERROR(VLOOKUP(H56,'Сырьё'!$C$6:$E$233,3,FALSE()),IFERROR(VLOOKUP(H56,'Полупродукты'!$C$6:$E$60,3,FALSE()),0)) -> 4.6836 | L56: =IF(J56=0,0,J56*K56) -> 0
G57: 46 | H57: Диоксид титана BR-3661 | I57: =IFERROR(VLOOKUP(H57,'Сырьё'!$C$6:$D$233,2,FALSE()),IFERROR(VLOOKUP(H57,'Полупродукты'!$C$6:$D$60,2,FALSE()),"кг")) -> кг | J57: {=IF(B8="",0,IFERROR(INDEX('_Развёртки'!$C$2:$C$1358,MATCH(B8&"|"&H57,'_Развёртки'!$D$2:$D$1358,0)),0)*N(C8))+IF(B9="",0,IFERROR(INDEX('_Развёртки'!$C$2:$C$1358,MATCH(B9&"|"&H57,'_Развёртки'!$D$2:$D$1358,0)),0)*N(C9))+IF(B10="",0,IFERROR(INDEX('_Развёртки'!$C$2:$C$1358,MATCH(B10&"|"&H57,'_Развёртки'!$D$2:$D$1358,0)),0)*N(C10))+IF(B11="",0,IFERROR(INDEX('_Развёртки'!$C$2:$C$1358,MATCH(B11&"|"&H57,'_Развёртки'!$D$2:$D$1358,0)),0)*N(C11))+IF(B12="",0,IFERROR(INDEX('_Развёртки'!$C$2:$C$1358,MATCH(B12&"|"&H57,'_Развёртки'!$D$2:$D$1358,0)),0)*N(C12))+IF(B13="",0,IFERROR(INDEX('_Развёртки'!$C$2:$C$1358,MATCH(B13&"|"&H57,'_Развёртки'!$D$2:$D$1358,0)),0)*N(C13))+IF(B14="",0,IFERROR(INDEX('_Развёртки'!$C$2:$C$1358,MATCH(B14&"|"&H57,'_Развёртки'!$D$2:$D$1358,0)),0)*N(C14))+IF(B15="",0,IFERROR(INDEX('_Развёртки'!$C$2:$C$1358,MATCH(B15&"|"&H57,'_Развёртки'!$D$2:$D$1358,0)),0)*N(C15))+IF(B16="",0,IFERROR(INDEX('_Развёртки'!$C$2:$C$1358,MATCH(B16&"|"&H57,'_Развёртки'!$D$2:$D$1358,0)),0)*N(C16))+IF(B17="",0,IFERROR(INDEX('_Развёртки'!$C$2:$C$1358,MATCH(B17&"|"&H57,'_Развёртки'!$D$2:$D$1358,0)),0)*N(C17))+IF(B18="",0,IFERROR(INDEX('_Развёртки'!$C$2:$C$1358,MATCH(B18&"|"&H57,'_Развёртки'!$D$2:$D$1358,0)),0)*N(C18))+IF(B19="",0,IFERROR(INDEX('_Развёртки'!$C$2:$C$1358,MATCH(B19&"|"&H57,'_Развёртки'!$D$2:$D$1358,0)),0)*N(C19))+IF(B20="",0,IFERROR(INDEX('_Развёртки'!$C$2:$C$1358,MATCH(B20&"|"&H57,'_Развёртки'!$D$2:$D$1358,0)),0)*N(C20))+IF(B21="",0,IFERROR(INDEX('_Развёртки'!$C$2:$C$1358,MATCH(B21&"|"&H57,'_Развёртки'!$D$2:$D$1358,0)),0)*N(C21))+IF(B22="",0,IFERROR(INDEX('_Развёртки'!$C$2:$C$1358,MATCH(B22&"|"&H57,'_Развёртки'!$D$2:$D$1358,0)),0)*N(C22))+IF(B23="",0,IFERROR(INDEX('_Развёртки'!$C$2:$C$1358,MATCH(B23&"|"&H57,'_Развёртки'!$D$2:$D$1358,0)),0)*N(C23))+IF(B24="",0,IFERROR(INDEX('_Развёртки'!$C$2:$C$1358,MATCH(B24&"|"&H57,'_Развёртки'!$D$2:$D$1358,0)),0)*N(C24))+IF(B25="",0,IFERROR(INDEX('_Развёртки'!$C$2:$C$1358,MATCH(B25&"|"&H57,'_Развёртки'!$D$2:$D$1358,0)),0)*N(C25))+IF(B26="",0,IFERROR(INDEX('_Развёртки'!$C$2:$C$1358,MATCH(B26&"|"&H57,'_Развёртки'!$D$2:$D$1358,0)),0)*N(C26))+IF(B27="",0,IFERROR(INDEX('_Развёртки'!$C$2:$C$1358,MATCH(B27&"|"&H57,'_Развёртки'!$D$2:$D$1358,0)),0)*N(C27))} -> 1528.9065 | K57: =IFERROR(VLOOKUP(H57,'Сырьё'!$C$6:$E$233,3,FALSE()),IFERROR(VLOOKUP(H57,'Полупродукты'!$C$6:$E$60,3,FALSE()),0)) -> 2.8015 | L57: =IF(J57=0,0,J57*K57) -> 4283.2316
G58: 47 | H58: Диоксид титана Kronos 2190 | I58: =IFERROR(VLOOKUP(H58,'Сырьё'!$C$6:$D$233,2,FALSE()),IFERROR(VLOOKUP(H58,'Полупродукты'!$C$6:$D$60,2,FALSE()),"кг")) -> шт | J58: {=IF(B8="",0,IFERROR(INDEX('_Развёртки'!$C$2:$C$1358,MATCH(B8&"|"&H58,'_Развёртки'!$D$2:$D$1358,0)),0)*N(C8))+IF(B9="",0,IFERROR(INDEX('_Развёртки'!$C$2:$C$1358,MATCH(B9&"|"&H58,'_Развёртки'!$D$2:$D$1358,0)),0)*N(C9))+IF(B10="",0,IFERROR(INDEX('_Развёртки'!$C$2:$C$1358,MATCH(B10&"|"&H58,'_Развёртки'!$D$2:$D$1358,0)),0)*N(C10))+IF(B11="",0,IFERROR(INDEX('_Развёртки'!$C$2:$C$1358,MATCH(B11&"|"&H58,'_Развёртки'!$D$2:$D$1358,0)),0)*N(C11))+IF(B12="",0,IFERROR(INDEX('_Развёртки'!$C$2:$C$1358,MATCH(B12&"|"&H58,'_Развёртки'!$D$2:$D$1358,0)),0)*N(C12))+IF(B13="",0,IFERROR(INDEX('_Развёртки'!$C$2:$C$1358,MATCH(B13&"|"&H58,'_Развёртки'!$D$2:$D$1358,0)),0)*N(C13))+IF(B14="",0,IFERROR(INDEX('_Развёртки'!$C$2:$C$1358,MATCH(B14&"|"&H58,'_Развёртки'!$D$2:$D$1358,0)),0)*N(C14))+IF(B15="",0,IFERROR(INDEX('_Развёртки'!$C$2:$C$1358,MATCH(B15&"|"&H58,'_Развёртки'!$D$2:$D$1358,0)),0)*N(C15))+IF(B16="",0,IFERROR(INDEX('_Развёртки'!$C$2:$C$1358,MATCH(B16&"|"&H58,'_Развёртки'!$D$2:$D$1358,0)),0)*N(C16))+IF(B17="",0,IFERROR(INDEX('_Развёртки'!$C$2:$C$1358,MATCH(B17&"|"&H58,'_Развёртки'!$D$2:$D$1358,0)),0)*N(C17))+IF(B18="",0,IFERROR(INDEX('_Развёртки'!$C$2:$C$1358,MATCH(B18&"|"&H58,'_Развёртки'!$D$2:$D$1358,0)),0)*N(C18))+IF(B19="",0,IFERROR(INDEX('_Развёртки'!$C$2:$C$1358,MATCH(B19&"|"&H58,'_Развёртки'!$D$2:$D$1358,0)),0)*N(C19))+IF(B20="",0,IFERROR(INDEX('_Развёртки'!$C$2:$C$1358,MATCH(B20&"|"&H58,'_Развёртки'!$D$2:$D$1358,0)),0)*N(C20))+IF(B21="",0,IFERROR(INDEX('_Развёртки'!$C$2:$C$1358,MATCH(B21&"|"&H58,'_Развёртки'!$D$2:$D$1358,0)),0)*N(C21))+IF(B22="",0,IFERROR(INDEX('_Развёртки'!$C$2:$C$1358,MATCH(B22&"|"&H58,'_Развёртки'!$D$2:$D$1358,0)),0)*N(C22))+IF(B23="",0,IFERROR(INDEX('_Развёртки'!$C$2:$C$1358,MATCH(B23&"|"&H58,'_Развёртки'!$D$2:$D$1358,0)),0)*N(C23))+IF(B24="",0,IFERROR(INDEX('_Развёртки'!$C$2:$C$1358,MATCH(B24&"|"&H58,'_Развёртки'!$D$2:$D$1358,0)),0)*N(C24))+IF(B25="",0,IFERROR(INDEX('_Развёртки'!$C$2:$C$1358,MATCH(B25&"|"&H58,'_Развёртки'!$D$2:$D$1358,0)),0)*N(C25))+IF(B26="",0,IFERROR(INDEX('_Развёртки'!$C$2:$C$1358,MATCH(B26&"|"&H58,'_Развёртки'!$D$2:$D$1358,0)),0)*N(C26))+IF(B27="",0,IFERROR(INDEX('_Развёртки'!$C$2:$C$1358,MATCH(B27&"|"&H58,'_Развёртки'!$D$2:$D$1358,0)),0)*N(C27))} -> 0 | K58: =IFERROR(VLOOKUP(H58,'Сырьё'!$C$6:$E$233,3,FALSE()),IFERROR(VLOOKUP(H58,'Полупродукты'!$C$6:$E$60,3,FALSE()),0)) -> 4.0017 | L58: =IF(J58=0,0,J58*K58) -> 0
G59: 48 | H59: Изопропанол | I59: =IFERROR(VLOOKUP(H59,'Сырьё'!$C$6:$D$233,2,FALSE()),IFERROR(VLOOKUP(H59,'Полупродукты'!$C$6:$D$60,2,FALSE()),"кг")) -> кг | J59: {=IF(B8="",0,IFERROR(INDEX('_Развёртки'!$C$2:$C$1358,MATCH(B8&"|"&H59,'_Развёртки'!$D$2:$D$1358,0)),0)*N(C8))+IF(B9="",0,IFERROR(INDEX('_Развёртки'!$C$2:$C$1358,MATCH(B9&"|"&H59,'_Развёртки'!$D$2:$D$1358,0)),0)*N(C9))+IF(B10="",0,IFERROR(INDEX('_Развёртки'!$C$2:$C$1358,MATCH(B10&"|"&H59,'_Развёртки'!$D$2:$D$1358,0)),0)*N(C10))+IF(B11="",0,IFERROR(INDEX('_Развёртки'!$C$2:$C$1358,MATCH(B11&"|"&H59,'_Развёртки'!$D$2:$D$1358,0)),0)*N(C11))+IF(B12="",0,IFERROR(INDEX('_Развёртки'!$C$2:$C$1358,MATCH(B12&"|"&H59,'_Развёртки'!$D$2:$D$1358,0)),0)*N(C12))+IF(B13="",0,IFERROR(INDEX('_Развёртки'!$C$2:$C$1358,MATCH(B13&"|"&H59,'_Развёртки'!$D$2:$D$1358,0)),0)*N(C13))+IF(B14="",0,IFERROR(INDEX('_Развёртки'!$C$2:$C$1358,MATCH(B14&"|"&H59,'_Развёртки'!$D$2:$D$1358,0)),0)*N(C14))+IF(B15="",0,IFERROR(INDEX('_Развёртки'!$C$2:$C$1358,MATCH(B15&"|"&H59,'_Развёртки'!$D$2:$D$1358,0)),0)*N(C15))+IF(B16="",0,IFERROR(INDEX('_Развёртки'!$C$2:$C$1358,MATCH(B16&"|"&H59,'_Развёртки'!$D$2:$D$1358,0)),0)*N(C16))+IF(B17="",0,IFERROR(INDEX('_Развёртки'!$C$2:$C$1358,MATCH(B17&"|"&H59,'_Развёртки'!$D$2:$D$1358,0)),0)*N(C17))+IF(B18="",0,IFERROR(INDEX('_Развёртки'!$C$2:$C$1358,MATCH(B18&"|"&H59,'_Развёртки'!$D$2:$D$1358,0)),0)*N(C18))+IF(B19="",0,IFERROR(INDEX('_Развёртки'!$C$2:$C$1358,MATCH(B19&"|"&H59,'_Развёртки'!$D$2:$D$1358,0)),0)*N(C19))+IF(B20="",0,IFERROR(INDEX('_Развёртки'!$C$2:$C$1358,MATCH(B20&"|"&H59,'_Развёртки'!$D$2:$D$1358,0)),0)*N(C20))+IF(B21="",0,IFERROR(INDEX('_Развёртки'!$C$2:$C$1358,MATCH(B21&"|"&H59,'_Развёртки'!$D$2:$D$1358,0)),0)*N(C21))+IF(B22="",0,IFERROR(INDEX('_Развёртки'!$C$2:$C$1358,MATCH(B22&"|"&H59,'_Развёртки'!$D$2:$D$1358,0)),0)*N(C22))+IF(B23="",0,IFERROR(INDEX('_Развёртки'!$C$2:$C$1358,MATCH(B23&"|"&H59,'_Развёртки'!$D$2:$D$1358,0)),0)*N(C23))+IF(B24="",0,IFERROR(INDEX('_Развёртки'!$C$2:$C$1358,MATCH(B24&"|"&H59,'_Развёртки'!$D$2:$D$1358,0)),0)*N(C24))+IF(B25="",0,IFERROR(INDEX('_Развёртки'!$C$2:$C$1358,MATCH(B25&"|"&H59,'_Развёртки'!$D$2:$D$1358,0)),0)*N(C25))+IF(B26="",0,IFERROR(INDEX('_Развёртки'!$C$2:$C$1358,MATCH(B26&"|"&H59,'_Развёртки'!$D$2:$D$1358,0)),0)*N(C26))+IF(B27="",0,IFERROR(INDEX('_Развёртки'!$C$2:$C$1358,MATCH(B27&"|"&H59,'_Развёртки'!$D$2:$D$1358,0)),0)*N(C27))} -> 1426.7781 | K59: =IFERROR(VLOOKUP(H59,'Сырьё'!$C$6:$E$233,3,FALSE()),IFERROR(VLOOKUP(H59,'Полупродукты'!$C$6:$E$60,3,FALSE()),0)) -> 1.2831 | L59: =IF(J59=0,0,J59*K59) -> 1830.699
G60: 49 | H60: Ковелос R902 | I60: =IFERROR(VLOOKUP(H60,'Сырьё'!$C$6:$D$233,2,FALSE()),IFERROR(VLOOKUP(H60,'Полупродукты'!$C$6:$D$60,2,FALSE()),"кг")) -> кг | J60: {=IF(B8="",0,IFERROR(INDEX('_Развёртки'!$C$2:$C$1358,MATCH(B8&"|"&H60,'_Развёртки'!$D$2:$D$1358,0)),0)*N(C8))+IF(B9="",0,IFERROR(INDEX('_Развёртки'!$C$2:$C$1358,MATCH(B9&"|"&H60,'_Развёртки'!$D$2:$D$1358,0)),0)*N(C9))+IF(B10="",0,IFERROR(INDEX('_Развёртки'!$C$2:$C$1358,MATCH(B10&"|"&H60,'_Развёртки'!$D$2:$D$1358,0)),0)*N(C10))+IF(B11="",0,IFERROR(INDEX('_Развёртки'!$C$2:$C$1358,MATCH(B11&"|"&H60,'_Развёртки'!$D$2:$D$1358,0)),0)*N(C11))+IF(B12="",0,IFERROR(INDEX('_Развёртки'!$C$2:$C$1358,MATCH(B12&"|"&H60,'_Развёртки'!$D$2:$D$1358,0)),0)*N(C12))+IF(B13="",0,IFERROR(INDEX('_Развёртки'!$C$2:$C$1358,MATCH(B13&"|"&H60,'_Развёртки'!$D$2:$D$1358,0)),0)*N(C13))+IF(B14="",0,IFERROR(INDEX('_Развёртки'!$C$2:$C$1358,MATCH(B14&"|"&H60,'_Развёртки'!$D$2:$D$1358,0)),0)*N(C14))+IF(B15="",0,IFERROR(INDEX('_Развёртки'!$C$2:$C$1358,MATCH(B15&"|"&H60,'_Развёртки'!$D$2:$D$1358,0)),0)*N(C15))+IF(B16="",0,IFERROR(INDEX('_Развёртки'!$C$2:$C$1358,MATCH(B16&"|"&H60,'_Развёртки'!$D$2:$D$1358,0)),0)*N(C16))+IF(B17="",0,IFERROR(INDEX('_Развёртки'!$C$2:$C$1358,MATCH(B17&"|"&H60,'_Развёртки'!$D$2:$D$1358,0)),0)*N(C17))+IF(B18="",0,IFERROR(INDEX('_Развёртки'!$C$2:$C$1358,MATCH(B18&"|"&H60,'_Развёртки'!$D$2:$D$1358,0)),0)*N(C18))+IF(B19="",0,IFERROR(INDEX('_Развёртки'!$C$2:$C$1358,MATCH(B19&"|"&H60,'_Развёртки'!$D$2:$D$1358,0)),0)*N(C19))+IF(B20="",0,IFERROR(INDEX('_Развёртки'!$C$2:$C$1358,MATCH(B20&"|"&H60,'_Развёртки'!$D$2:$D$1358,0)),0)*N(C20))+IF(B21="",0,IFERROR(INDEX('_Развёртки'!$C$2:$C$1358,MATCH(B21&"|"&H60,'_Развёртки'!$D$2:$D$1358,0)),0)*N(C21))+IF(B22="",0,IFERROR(INDEX('_Развёртки'!$C$2:$C$1358,MATCH(B22&"|"&H60,'_Развёртки'!$D$2:$D$1358,0)),0)*N(C22))+IF(B23="",0,IFERROR(INDEX('_Развёртки'!$C$2:$C$1358,MATCH(B23&"|"&H60,'_Развёртки'!$D$2:$D$1358,0)),0)*N(C23))+IF(B24="",0,IFERROR(INDEX('_Развёртки'!$C$2:$C$1358,MATCH(B24&"|"&H60,'_Развёртки'!$D$2:$D$1358,0)),0)*N(C24))+IF(B25="",0,IFERROR(INDEX('_Развёртки'!$C$2:$C$1358,MATCH(B25&"|"&H60,'_Развёртки'!$D$2:$D$1358,0)),0)*N(C25))+IF(B26="",0,IFERROR(INDEX('_Развёртки'!$C$2:$C$1358,MATCH(B26&"|"&H60,'_Развёртки'!$D$2:$D$1358,0)),0)*N(C26))+IF(B27="",0,IFERROR(INDEX('_Развёртки'!$C$2:$C$1358,MATCH(B27&"|"&H60,'_Развёртки'!$D$2:$D$1358,0)),0)*N(C27))} -> 0 | K60: =IFERROR(VLOOKUP(H60,'Сырьё'!$C$6:$E$233,3,FALSE()),IFERROR(VLOOKUP(H60,'Полупродукты'!$C$6:$E$60,3,FALSE()),0)) -> 6.1299 | L60: =IF(J60=0,0,J60*K60) -> 0
G61: 50 | H61: Матирующая добавка 412 | I61: =IFERROR(VLOOKUP(H61,'Сырьё'!$C$6:$D$233,2,FALSE()),IFERROR(VLOOKUP(H61,'Полупродукты'!$C$6:$D$60,2,FALSE()),"кг")) -> кг | J61: {=IF(B8="",0,IFERROR(INDEX('_Развёртки'!$C$2:$C$1358,MATCH(B8&"|"&H61,'_Развёртки'!$D$2:$D$1358,0)),0)*N(C8))+IF(B9="",0,IFERROR(INDEX('_Развёртки'!$C$2:$C$1358,MATCH(B9&"|"&H61,'_Развёртки'!$D$2:$D$1358,0)),0)*N(C9))+IF(B10="",0,IFERROR(INDEX('_Развёртки'!$C$2:$C$1358,MATCH(B10&"|"&H61,'_Развёртки'!$D$2:$D$1358,0)),0)*N(C10))+IF(B11="",0,IFERROR(INDEX('_Развёртки'!$C$2:$C$1358,MATCH(B11&"|"&H61,'_Развёртки'!$D$2:$D$1358,0)),0)*N(C11))+IF(B12="",0,IFERROR(INDEX('_Развёртки'!$C$2:$C$1358,MATCH(B12&"|"&H61,'_Развёртки'!$D$2:$D$1358,0)),0)*N(C12))+IF(B13="",0,IFERROR(INDEX('_Развёртки'!$C$2:$C$1358,MATCH(B13&"|"&H61,'_Развёртки'!$D$2:$D$1358,0)),0)*N(C13))+IF(B14="",0,IFERROR(INDEX('_Развёртки'!$C$2:$C$1358,MATCH(B14&"|"&H61,'_Развёртки'!$D$2:$D$1358,0)),0)*N(C14))+IF(B15="",0,IFERROR(INDEX('_Развёртки'!$C$2:$C$1358,MATCH(B15&"|"&H61,'_Развёртки'!$D$2:$D$1358,0)),0)*N(C15))+IF(B16="",0,IFERROR(INDEX('_Развёртки'!$C$2:$C$1358,MATCH(B16&"|"&H61,'_Развёртки'!$D$2:$D$1358,0)),0)*N(C16))+IF(B17="",0,IFERROR(INDEX('_Развёртки'!$C$2:$C$1358,MATCH(B17&"|"&H61,'_Развёртки'!$D$2:$D$1358,0)),0)*N(C17))+IF(B18="",0,IFERROR(INDEX('_Развёртки'!$C$2:$C$1358,MATCH(B18&"|"&H61,'_Развёртки'!$D$2:$D$1358,0)),0)*N(C18))+IF(B19="",0,IFERROR(INDEX('_Развёртки'!$C$2:$C$1358,MATCH(B19&"|"&H61,'_Развёртки'!$D$2:$D$1358,0)),0)*N(C19))+IF(B20="",0,IFERROR(INDEX('_Развёртки'!$C$2:$C$1358,MATCH(B20&"|"&H61,'_Развёртки'!$D$2:$D$1358,0)),0)*N(C20))+IF(B21="",0,IFERROR(INDEX('_Развёртки'!$C$2:$C$1358,MATCH(B21&"|"&H61,'_Развёртки'!$D$2:$D$1358,0)),0)*N(C21))+IF(B22="",0,IFERROR(INDEX('_Развёртки'!$C$2:$C$1358,MATCH(B22&"|"&H61,'_Развёртки'!$D$2:$D$1358,0)),0)*N(C22))+IF(B23="",0,IFERROR(INDEX('_Развёртки'!$C$2:$C$1358,MATCH(B23&"|"&H61,'_Развёртки'!$D$2:$D$1358,0)),0)*N(C23))+IF(B24="",0,IFERROR(INDEX('_Развёртки'!$C$2:$C$1358,MATCH(B24&"|"&H61,'_Развёртки'!$D$2:$D$1358,0)),0)*N(C24))+IF(B25="",0,IFERROR(INDEX('_Развёртки'!$C$2:$C$1358,MATCH(B25&"|"&H61,'_Развёртки'!$D$2:$D$1358,0)),0)*N(C25))+IF(B26="",0,IFERROR(INDEX('_Развёртки'!$C$2:$C$1358,MATCH(B26&"|"&H61,'_Развёртки'!$D$2:$D$1358,0)),0)*N(C26))+IF(B27="",0,IFERROR(INDEX('_Развёртки'!$C$2:$C$1358,MATCH(B27&"|"&H61,'_Развёртки'!$D$2:$D$1358,0)),0)*N(C27))} -> 0 | K61: =IFERROR(VLOOKUP(H61,'Сырьё'!$C$6:$E$233,3,FALSE()),IFERROR(VLOOKUP(H61,'Полупродукты'!$C$6:$E$60,3,FALSE()),0)) -> 7.2777 | L61: =IF(J61=0,0,J61*K61) -> 0
G62: 51 | H62: Метоксипропанол | I62: =IFERROR(VLOOKUP(H62,'Сырьё'!$C$6:$D$233,2,FALSE()),IFERROR(VLOOKUP(H62,'Полупродукты'!$C$6:$D$60,2,FALSE()),"кг")) -> шт | J62: {=IF(B8="",0,IFERROR(INDEX('_Развёртки'!$C$2:$C$1358,MATCH(B8&"|"&H62,'_Развёртки'!$D$2:$D$1358,0)),0)*N(C8))+IF(B9="",0,IFERROR(INDEX('_Развёртки'!$C$2:$C$1358,MATCH(B9&"|"&H62,'_Развёртки'!$D$2:$D$1358,0)),0)*N(C9))+IF(B10="",0,IFERROR(INDEX('_Развёртки'!$C$2:$C$1358,MATCH(B10&"|"&H62,'_Развёртки'!$D$2:$D$1358,0)),0)*N(C10))+IF(B11="",0,IFERROR(INDEX('_Развёртки'!$C$2:$C$1358,MATCH(B11&"|"&H62,'_Развёртки'!$D$2:$D$1358,0)),0)*N(C11))+IF(B12="",0,IFERROR(INDEX('_Развёртки'!$C$2:$C$1358,MATCH(B12&"|"&H62,'_Развёртки'!$D$2:$D$1358,0)),0)*N(C12))+IF(B13="",0,IFERROR(INDEX('_Развёртки'!$C$2:$C$1358,MATCH(B13&"|"&H62,'_Развёртки'!$D$2:$D$1358,0)),0)*N(C13))+IF(B14="",0,IFERROR(INDEX('_Развёртки'!$C$2:$C$1358,MATCH(B14&"|"&H62,'_Развёртки'!$D$2:$D$1358,0)),0)*N(C14))+IF(B15="",0,IFERROR(INDEX('_Развёртки'!$C$2:$C$1358,MATCH(B15&"|"&H62,'_Развёртки'!$D$2:$D$1358,0)),0)*N(C15))+IF(B16="",0,IFERROR(INDEX('_Развёртки'!$C$2:$C$1358,MATCH(B16&"|"&H62,'_Развёртки'!$D$2:$D$1358,0)),0)*N(C16))+IF(B17="",0,IFERROR(INDEX('_Развёртки'!$C$2:$C$1358,MATCH(B17&"|"&H62,'_Развёртки'!$D$2:$D$1358,0)),0)*N(C17))+IF(B18="",0,IFERROR(INDEX('_Развёртки'!$C$2:$C$1358,MATCH(B18&"|"&H62,'_Развёртки'!$D$2:$D$1358,0)),0)*N(C18))+IF(B19="",0,IFERROR(INDEX('_Развёртки'!$C$2:$C$1358,MATCH(B19&"|"&H62,'_Развёртки'!$D$2:$D$1358,0)),0)*N(C19))+IF(B20="",0,IFERROR(INDEX('_Развёртки'!$C$2:$C$1358,MATCH(B20&"|"&H62,'_Развёртки'!$D$2:$D$1358,0)),0)*N(C20))+IF(B21="",0,IFERROR(INDEX('_Развёртки'!$C$2:$C$1358,MATCH(B21&"|"&H62,'_Развёртки'!$D$2:$D$1358,0)),0)*N(C21))+IF(B22="",0,IFERROR(INDEX('_Развёртки'!$C$2:$C$1358,MATCH(B22&"|"&H62,'_Развёртки'!$D$2:$D$1358,0)),0)*N(C22))+IF(B23="",0,IFERROR(INDEX('_Развёртки'!$C$2:$C$1358,MATCH(B23&"|"&H62,'_Развёртки'!$D$2:$D$1358,0)),0)*N(C23))+IF(B24="",0,IFERROR(INDEX('_Развёртки'!$C$2:$C$1358,MATCH(B24&"|"&H62,'_Развёртки'!$D$2:$D$1358,0)),0)*N(C24))+IF(B25="",0,IFERROR(INDEX('_Развёртки'!$C$2:$C$1358,MATCH(B25&"|"&H62,'_Развёртки'!$D$2:$D$1358,0)),0)*N(C25))+IF(B26="",0,IFERROR(INDEX('_Развёртки'!$C$2:$C$1358,MATCH(B26&"|"&H62,'_Развёртки'!$D$2:$D$1358,0)),0)*N(C26))+IF(B27="",0,IFERROR(INDEX('_Развёртки'!$C$2:$C$1358,MATCH(B27&"|"&H62,'_Развёртки'!$D$2:$D$1358,0)),0)*N(C27))} -> 0 | K62: =IFERROR(VLOOKUP(H62,'Сырьё'!$C$6:$E$233,3,FALSE()),IFERROR(VLOOKUP(H62,'Полупродукты'!$C$6:$E$60,3,FALSE()),0)) -> 1.8685 | L62: =IF(J62=0,0,J62*K62) -> 0
G63: 52 | H63: Н-пропанол | I63: =IFERROR(VLOOKUP(H63,'Сырьё'!$C$6:$D$233,2,FALSE()),IFERROR(VLOOKUP(H63,'Полупродукты'!$C$6:$D$60,2,FALSE()),"кг")) -> кг | J63: {=IF(B8="",0,IFERROR(INDEX('_Развёртки'!$C$2:$C$1358,MATCH(B8&"|"&H63,'_Развёртки'!$D$2:$D$1358,0)),0)*N(C8))+IF(B9="",0,IFERROR(INDEX('_Развёртки'!$C$2:$C$1358,MATCH(B9&"|"&H63,'_Развёртки'!$D$2:$D$1358,0)),0)*N(C9))+IF(B10="",0,IFERROR(INDEX('_Развёртки'!$C$2:$C$1358,MATCH(B10&"|"&H63,'_Развёртки'!$D$2:$D$1358,0)),0)*N(C10))+IF(B11="",0,IFERROR(INDEX('_Развёртки'!$C$2:$C$1358,MATCH(B11&"|"&H63,'_Развёртки'!$D$2:$D$1358,0)),0)*N(C11))+IF(B12="",0,IFERROR(INDEX('_Развёртки'!$C$2:$C$1358,MATCH(B12&"|"&H63,'_Развёртки'!$D$2:$D$1358,0)),0)*N(C12))+IF(B13="",0,IFERROR(INDEX('_Развёртки'!$C$2:$C$1358,MATCH(B13&"|"&H63,'_Развёртки'!$D$2:$D$1358,0)),0)*N(C13))+IF(B14="",0,IFERROR(INDEX('_Развёртки'!$C$2:$C$1358,MATCH(B14&"|"&H63,'_Развёртки'!$D$2:$D$1358,0)),0)*N(C14))+IF(B15="",0,IFERROR(INDEX('_Развёртки'!$C$2:$C$1358,MATCH(B15&"|"&H63,'_Развёртки'!$D$2:$D$1358,0)),0)*N(C15))+IF(B16="",0,IFERROR(INDEX('_Развёртки'!$C$2:$C$1358,MATCH(B16&"|"&H63,'_Развёртки'!$D$2:$D$1358,0)),0)*N(C16))+IF(B17="",0,IFERROR(INDEX('_Развёртки'!$C$2:$C$1358,MATCH(B17&"|"&H63,'_Развёртки'!$D$2:$D$1358,0)),0)*N(C17))+IF(B18="",0,IFERROR(INDEX('_Развёртки'!$C$2:$C$1358,MATCH(B18&"|"&H63,'_Развёртки'!$D$2:$D$1358,0)),0)*N(C18))+IF(B19="",0,IFERROR(INDEX('_Развёртки'!$C$2:$C$1358,MATCH(B19&"|"&H63,'_Развёртки'!$D$2:$D$1358,0)),0)*N(C19))+IF(B20="",0,IFERROR(INDEX('_Развёртки'!$C$2:$C$1358,MATCH(B20&"|"&H63,'_Развёртки'!$D$2:$D$1358,0)),0)*N(C20))+IF(B21="",0,IFERROR(INDEX('_Развёртки'!$C$2:$C$1358,MATCH(B21&"|"&H63,'_Развёртки'!$D$2:$D$1358,0)),0)*N(C21))+IF(B22="",0,IFERROR(INDEX('_Развёртки'!$C$2:$C$1358,MATCH(B22&"|"&H63,'_Развёртки'!$D$2:$D$1358,0)),0)*N(C22))+IF(B23="",0,IFERROR(INDEX('_Развёртки'!$C$2:$C$1358,MATCH(B23&"|"&H63,'_Развёртки'!$D$2:$D$1358,0)),0)*N(C23))+IF(B24="",0,IFERROR(INDEX('_Развёртки'!$C$2:$C$1358,MATCH(B24&"|"&H63,'_Развёртки'!$D$2:$D$1358,0)),0)*N(C24))+IF(B25="",0,IFERROR(INDEX('_Развёртки'!$C$2:$C$1358,MATCH(B25&"|"&H63,'_Развёртки'!$D$2:$D$1358,0)),0)*N(C25))+IF(B26="",0,IFERROR(INDEX('_Развёртки'!$C$2:$C$1358,MATCH(B26&"|"&H63,'_Развёртки'!$D$2:$D$1358,0)),0)*N(C26))+IF(B27="",0,IFERROR(INDEX('_Развёртки'!$C$2:$C$1358,MATCH(B27&"|"&H63,'_Развёртки'!$D$2:$D$1358,0)),0)*N(C27))} -> 6.36026 | K63: =IFERROR(VLOOKUP(H63,'Сырьё'!$C$6:$E$233,3,FALSE()),IFERROR(VLOOKUP(H63,'Полупродукты'!$C$6:$E$60,3,FALSE()),0)) -> 1.4708 | L63: =IF(J63=0,0,J63*K63) -> 9.3546704
G64: 53 | H64: Н-пропилацетат | I64: =IFERROR(VLOOKUP(H64,'Сырьё'!$C$6:$D$233,2,FALSE()),IFERROR(VLOOKUP(H64,'Полупродукты'!$C$6:$D$60,2,FALSE()),"кг")) -> кг | J64: {=IF(B8="",0,IFERROR(INDEX('_Развёртки'!$C$2:$C$1358,MATCH(B8&"|"&H64,'_Развёртки'!$D$2:$D$1358,0)),0)*N(C8))+IF(B9="",0,IFERROR(INDEX('_Развёртки'!$C$2:$C$1358,MATCH(B9&"|"&H64,'_Развёртки'!$D$2:$D$1358,0)),0)*N(C9))+IF(B10="",0,IFERROR(INDEX('_Развёртки'!$C$2:$C$1358,MATCH(B10&"|"&H64,'_Развёртки'!$D$2:$D$1358,0)),0)*N(C10))+IF(B11="",0,IFERROR(INDEX('_Развёртки'!$C$2:$C$1358,MATCH(B11&"|"&H64,'_Развёртки'!$D$2:$D$1358,0)),0)*N(C11))+IF(B12="",0,IFERROR(INDEX('_Развёртки'!$C$2:$C$1358,MATCH(B12&"|"&H64,'_Развёртки'!$D$2:$D$1358,0)),0)*N(C12))+IF(B13="",0,IFERROR(INDEX('_Развёртки'!$C$2:$C$1358,MATCH(B13&"|"&H64,'_Развёртки'!$D$2:$D$1358,0)),0)*N(C13))+IF(B14="",0,IFERROR(INDEX('_Развёртки'!$C$2:$C$1358,MATCH(B14&"|"&H64,'_Развёртки'!$D$2:$D$1358,0)),0)*N(C14))+IF(B15="",0,IFERROR(INDEX('_Развёртки'!$C$2:$C$1358,MATCH(B15&"|"&H64,'_Развёртки'!$D$2:$D$1358,0)),0)*N(C15))+IF(B16="",0,IFERROR(INDEX('_Развёртки'!$C$2:$C$1358,MATCH(B16&"|"&H64,'_Развёртки'!$D$2:$D$1358,0)),0)*N(C16))+IF(B17="",0,IFERROR(INDEX('_Развёртки'!$C$2:$C$1358,MATCH(B17&"|"&H64,'_Развёртки'!$D$2:$D$1358,0)),0)*N(C17))+IF(B18="",0,IFERROR(INDEX('_Развёртки'!$C$2:$C$1358,MATCH(B18&"|"&H64,'_Развёртки'!$D$2:$D$1358,0)),0)*N(C18))+IF(B19="",0,IFERROR(INDEX('_Развёртки'!$C$2:$C$1358,MATCH(B19&"|"&H64,'_Развёртки'!$D$2:$D$1358,0)),0)*N(C19))+IF(B20="",0,IFERROR(INDEX('_Развёртки'!$C$2:$C$1358,MATCH(B20&"|"&H64,'_Развёртки'!$D$2:$D$1358,0)),0)*N(C20))+IF(B21="",0,IFERROR(INDEX('_Развёртки'!$C$2:$C$1358,MATCH(B21&"|"&H64,'_Развёртки'!$D$2:$D$1358,0)),0)*N(C21))+IF(B22="",0,IFERROR(INDEX('_Развёртки'!$C$2:$C$1358,MATCH(B22&"|"&H64,'_Развёртки'!$D$2:$D$1358,0)),0)*N(C22))+IF(B23="",0,IFERROR(INDEX('_Развёртки'!$C$2:$C$1358,MATCH(B23&"|"&H64,'_Развёртки'!$D$2:$D$1358,0)),0)*N(C23))+IF(B24="",0,IFERROR(INDEX('_Развёртки'!$C$2:$C$1358,MATCH(B24&"|"&H64,'_Развёртки'!$D$2:$D$1358,0)),0)*N(C24))+IF(B25="",0,IFERROR(INDEX('_Развёртки'!$C$2:$C$1358,MATCH(B25&"|"&H64,'_Развёртки'!$D$2:$D$1358,0)),0)*N(C25))+IF(B26="",0,IFERROR(INDEX('_Развёртки'!$C$2:$C$1358,MATCH(B26&"|"&H64,'_Развёртки'!$D$2:$D$1358,0)),0)*N(C26))+IF(B27="",0,IFERROR(INDEX('_Развёртки'!$C$2:$C$1358,MATCH(B27&"|"&H64,'_Развёртки'!$D$2:$D$1358,0)),0)*N(C27))} -> 28.1602 | K64: =IFERROR(VLOOKUP(H64,'Сырьё'!$C$6:$E$233,3,FALSE()),IFERROR(VLOOKUP(H64,'Полупродукты'!$C$6:$E$60,3,FALSE()),0)) -> 2.0494 | L64: =IF(J64=0,0,J64*K64) -> 57.711514
G65: 54 | H65: Нитроцеллюлоза LX 5/8 IPA WET | I65: =IFERROR(VLOOKUP(H65,'Сырьё'!$C$6:$D$233,2,FALSE()),IFERROR(VLOOKUP(H65,'Полупродукты'!$C$6:$D$60,2,FALSE()),"кг")) -> кг | J65: {=IF(B8="",0,IFERROR(INDEX('_Развёртки'!$C$2:$C$1358,MATCH(B8&"|"&H65,'_Развёртки'!$D$2:$D$1358,0)),0)*N(C8))+IF(B9="",0,IFERROR(INDEX('_Развёртки'!$C$2:$C$1358,MATCH(B9&"|"&H65,'_Развёртки'!$D$2:$D$1358,0)),0)*N(C9))+IF(B10="",0,IFERROR(INDEX('_Развёртки'!$C$2:$C$1358,MATCH(B10&"|"&H65,'_Развёртки'!$D$2:$D$1358,0)),0)*N(C10))+IF(B11="",0,IFERROR(INDEX('_Развёртки'!$C$2:$C$1358,MATCH(B11&"|"&H65,'_Развёртки'!$D$2:$D$1358,0)),0)*N(C11))+IF(B12="",0,IFERROR(INDEX('_Развёртки'!$C$2:$C$1358,MATCH(B12&"|"&H65,'_Развёртки'!$D$2:$D$1358,0)),0)*N(C12))+IF(B13="",0,IFERROR(INDEX('_Развёртки'!$C$2:$C$1358,MATCH(B13&"|"&H65,'_Развёртки'!$D$2:$D$1358,0)),0)*N(C13))+IF(B14="",0,IFERROR(INDEX('_Развёртки'!$C$2:$C$1358,MATCH(B14&"|"&H65,'_Развёртки'!$D$2:$D$1358,0)),0)*N(C14))+IF(B15="",0,IFERROR(INDEX('_Развёртки'!$C$2:$C$1358,MATCH(B15&"|"&H65,'_Развёртки'!$D$2:$D$1358,0)),0)*N(C15))+IF(B16="",0,IFERROR(INDEX('_Развёртки'!$C$2:$C$1358,MATCH(B16&"|"&H65,'_Развёртки'!$D$2:$D$1358,0)),0)*N(C16))+IF(B17="",0,IFERROR(INDEX('_Развёртки'!$C$2:$C$1358,MATCH(B17&"|"&H65,'_Развёртки'!$D$2:$D$1358,0)),0)*N(C17))+IF(B18="",0,IFERROR(INDEX('_Развёртки'!$C$2:$C$1358,MATCH(B18&"|"&H65,'_Развёртки'!$D$2:$D$1358,0)),0)*N(C18))+IF(B19="",0,IFERROR(INDEX('_Развёртки'!$C$2:$C$1358,MATCH(B19&"|"&H65,'_Развёртки'!$D$2:$D$1358,0)),0)*N(C19))+IF(B20="",0,IFERROR(INDEX('_Развёртки'!$C$2:$C$1358,MATCH(B20&"|"&H65,'_Развёртки'!$D$2:$D$1358,0)),0)*N(C20))+IF(B21="",0,IFERROR(INDEX('_Развёртки'!$C$2:$C$1358,MATCH(B21&"|"&H65,'_Развёртки'!$D$2:$D$1358,0)),0)*N(C21))+IF(B22="",0,IFERROR(INDEX('_Развёртки'!$C$2:$C$1358,MATCH(B22&"|"&H65,'_Развёртки'!$D$2:$D$1358,0)),0)*N(C22))+IF(B23="",0,IFERROR(INDEX('_Развёртки'!$C$2:$C$1358,MATCH(B23&"|"&H65,'_Развёртки'!$D$2:$D$1358,0)),0)*N(C23))+IF(B24="",0,IFERROR(INDEX('_Развёртки'!$C$2:$C$1358,MATCH(B24&"|"&H65,'_Развёртки'!$D$2:$D$1358,0)),0)*N(C24))+IF(B25="",0,IFERROR(INDEX('_Развёртки'!$C$2:$C$1358,MATCH(B25&"|"&H65,'_Развёртки'!$D$2:$D$1358,0)),0)*N(C25))+IF(B26="",0,IFERROR(INDEX('_Развёртки'!$C$2:$C$1358,MATCH(B26&"|"&H65,'_Развёртки'!$D$2:$D$1358,0)),0)*N(C26))+IF(B27="",0,IFERROR(INDEX('_Развёртки'!$C$2:$C$1358,MATCH(B27&"|"&H65,'_Развёртки'!$D$2:$D$1358,0)),0)*N(C27))} -> 15.7493 | K65: =IFERROR(VLOOKUP(H65,'Сырьё'!$C$6:$E$233,3,FALSE()),IFERROR(VLOOKUP(H65,'Полупродукты'!$C$6:$E$60,3,FALSE()),0)) -> 6.9052 | L65: =IF(J65=0,0,J65*K65) -> 108.75207
G66: 55 | H66: Пигмент красный 169 | I66: =IFERROR(VLOOKUP(H66,'Сырьё'!$C$6:$D$233,2,FALSE()),IFERROR(VLOOKUP(H66,'Полупродукты'!$C$6:$D$60,2,FALSE()),"кг")) -> кг | J66: {=IF(B8="",0,IFERROR(INDEX('_Развёртки'!$C$2:$C$1358,MATCH(B8&"|"&H66,'_Развёртки'!$D$2:$D$1358,0)),0)*N(C8))+IF(B9="",0,IFERROR(INDEX('_Развёртки'!$C$2:$C$1358,MATCH(B9&"|"&H66,'_Развёртки'!$D$2:$D$1358,0)),0)*N(C9))+IF(B10="",0,IFERROR(INDEX('_Развёртки'!$C$2:$C$1358,MATCH(B10&"|"&H66,'_Развёртки'!$D$2:$D$1358,0)),0)*N(C10))+IF(B11="",0,IFERROR(INDEX('_Развёртки'!$C$2:$C$1358,MATCH(B11&"|"&H66,'_Развёртки'!$D$2:$D$1358,0)),0)*N(C11))+IF(B12="",0,IFERROR(INDEX('_Развёртки'!$C$2:$C$1358,MATCH(B12&"|"&H66,'_Развёртки'!$D$2:$D$1358,0)),0)*N(C12))+IF(B13="",0,IFERROR(INDEX('_Развёртки'!$C$2:$C$1358,MATCH(B13&"|"&H66,'_Развёртки'!$D$2:$D$1358,0)),0)*N(C13))+IF(B14="",0,IFERROR(INDEX('_Развёртки'!$C$2:$C$1358,MATCH(B14&"|"&H66,'_Развёртки'!$D$2:$D$1358,0)),0)*N(C14))+IF(B15="",0,IFERROR(INDEX('_Развёртки'!$C$2:$C$1358,MATCH(B15&"|"&H66,'_Развёртки'!$D$2:$D$1358,0)),0)*N(C15))+IF(B16="",0,IFERROR(INDEX('_Развёртки'!$C$2:$C$1358,MATCH(B16&"|"&H66,'_Развёртки'!$D$2:$D$1358,0)),0)*N(C16))+IF(B17="",0,IFERROR(INDEX('_Развёртки'!$C$2:$C$1358,MATCH(B17&"|"&H66,'_Развёртки'!$D$2:$D$1358,0)),0)*N(C17))+IF(B18="",0,IFERROR(INDEX('_Развёртки'!$C$2:$C$1358,MATCH(B18&"|"&H66,'_Развёртки'!$D$2:$D$1358,0)),0)*N(C18))+IF(B19="",0,IFERROR(INDEX('_Развёртки'!$C$2:$C$1358,MATCH(B19&"|"&H66,'_Развёртки'!$D$2:$D$1358,0)),0)*N(C19))+IF(B20="",0,IFERROR(INDEX('_Развёртки'!$C$2:$C$1358,MATCH(B20&"|"&H66,'_Развёртки'!$D$2:$D$1358,0)),0)*N(C20))+IF(B21="",0,IFERROR(INDEX('_Развёртки'!$C$2:$C$1358,MATCH(B21&"|"&H66,'_Развёртки'!$D$2:$D$1358,0)),0)*N(C21))+IF(B22="",0,IFERROR(INDEX('_Развёртки'!$C$2:$C$1358,MATCH(B22&"|"&H66,'_Развёртки'!$D$2:$D$1358,0)),0)*N(C22))+IF(B23="",0,IFERROR(INDEX('_Развёртки'!$C$2:$C$1358,MATCH(B23&"|"&H66,'_Развёртки'!$D$2:$D$1358,0)),0)*N(C23))+IF(B24="",0,IFERROR(INDEX('_Развёртки'!$C$2:$C$1358,MATCH(B24&"|"&H66,'_Развёртки'!$D$2:$D$1358,0)),0)*N(C24))+IF(B25="",0,IFERROR(INDEX('_Развёртки'!$C$2:$C$1358,MATCH(B25&"|"&H66,'_Развёртки'!$D$2:$D$1358,0)),0)*N(C25))+IF(B26="",0,IFERROR(INDEX('_Развёртки'!$C$2:$C$1358,MATCH(B26&"|"&H66,'_Развёртки'!$D$2:$D$1358,0)),0)*N(C26))+IF(B27="",0,IFERROR(INDEX('_Развёртки'!$C$2:$C$1358,MATCH(B27&"|"&H66,'_Развёртки'!$D$2:$D$1358,0)),0)*N(C27))} -> 29.43528 | K66: =IFERROR(VLOOKUP(H66,'Сырьё'!$C$6:$E$233,3,FALSE()),IFERROR(VLOOKUP(H66,'Полупродукты'!$C$6:$E$60,3,FALSE()),0)) -> 53.4751 | L66: =IF(J66=0,0,J66*K66) -> 1574.0545
G67: 56 | H67: Полиуретан DROPACK 5260 | I67: =IFERROR(VLOOKUP(H67,'Сырьё'!$C$6:$D$233,2,FALSE()),IFERROR(VLOOKUP(H67,'Полупродукты'!$C$6:$D$60,2,FALSE()),"кг")) -> кг | J67: {=IF(B8="",0,IFERROR(INDEX('_Развёртки'!$C$2:$C$1358,MATCH(B8&"|"&H67,'_Развёртки'!$D$2:$D$1358,0)),0)*N(C8))+IF(B9="",0,IFERROR(INDEX('_Развёртки'!$C$2:$C$1358,MATCH(B9&"|"&H67,'_Развёртки'!$D$2:$D$1358,0)),0)*N(C9))+IF(B10="",0,IFERROR(INDEX('_Развёртки'!$C$2:$C$1358,MATCH(B10&"|"&H67,'_Развёртки'!$D$2:$D$1358,0)),0)*N(C10))+IF(B11="",0,IFERROR(INDEX('_Развёртки'!$C$2:$C$1358,MATCH(B11&"|"&H67,'_Развёртки'!$D$2:$D$1358,0)),0)*N(C11))+IF(B12="",0,IFERROR(INDEX('_Развёртки'!$C$2:$C$1358,MATCH(B12&"|"&H67,'_Развёртки'!$D$2:$D$1358,0)),0)*N(C12))+IF(B13="",0,IFERROR(INDEX('_Развёртки'!$C$2:$C$1358,MATCH(B13&"|"&H67,'_Развёртки'!$D$2:$D$1358,0)),0)*N(C13))+IF(B14="",0,IFERROR(INDEX('_Развёртки'!$C$2:$C$1358,MATCH(B14&"|"&H67,'_Развёртки'!$D$2:$D$1358,0)),0)*N(C14))+IF(B15="",0,IFERROR(INDEX('_Развёртки'!$C$2:$C$1358,MATCH(B15&"|"&H67,'_Развёртки'!$D$2:$D$1358,0)),0)*N(C15))+IF(B16="",0,IFERROR(INDEX('_Развёртки'!$C$2:$C$1358,MATCH(B16&"|"&H67,'_Развёртки'!$D$2:$D$1358,0)),0)*N(C16))+IF(B17="",0,IFERROR(INDEX('_Развёртки'!$C$2:$C$1358,MATCH(B17&"|"&H67,'_Развёртки'!$D$2:$D$1358,0)),0)*N(C17))+IF(B18="",0,IFERROR(INDEX('_Развёртки'!$C$2:$C$1358,MATCH(B18&"|"&H67,'_Развёртки'!$D$2:$D$1358,0)),0)*N(C18))+IF(B19="",0,IFERROR(INDEX('_Развёртки'!$C$2:$C$1358,MATCH(B19&"|"&H67,'_Развёртки'!$D$2:$D$1358,0)),0)*N(C19))+IF(B20="",0,IFERROR(INDEX('_Развёртки'!$C$2:$C$1358,MATCH(B20&"|"&H67,'_Развёртки'!$D$2:$D$1358,0)),0)*N(C20))+IF(B21="",0,IFERROR(INDEX('_Развёртки'!$C$2:$C$1358,MATCH(B21&"|"&H67,'_Развёртки'!$D$2:$D$1358,0)),0)*N(C21))+IF(B22="",0,IFERROR(INDEX('_Развёртки'!$C$2:$C$1358,MATCH(B22&"|"&H67,'_Развёртки'!$D$2:$D$1358,0)),0)*N(C22))+IF(B23="",0,IFERROR(INDEX('_Развёртки'!$C$2:$C$1358,MATCH(B23&"|"&H67,'_Развёртки'!$D$2:$D$1358,0)),0)*N(C23))+IF(B24="",0,IFERROR(INDEX('_Развёртки'!$C$2:$C$1358,MATCH(B24&"|"&H67,'_Развёртки'!$D$2:$D$1358,0)),0)*N(C24))+IF(B25="",0,IFERROR(INDEX('_Развёртки'!$C$2:$C$1358,MATCH(B25&"|"&H67,'_Развёртки'!$D$2:$D$1358,0)),0)*N(C25))+IF(B26="",0,IFERROR(INDEX('_Развёртки'!$C$2:$C$1358,MATCH(B26&"|"&H67,'_Развёртки'!$D$2:$D$1358,0)),0)*N(C26))+IF(B27="",0,IFERROR(INDEX('_Развёртки'!$C$2:$C$1358,MATCH(B27&"|"&H67,'_Развёртки'!$D$2:$D$1358,0)),0)*N(C27))} -> 0 | K67: =IFERROR(VLOOKUP(H67,'Сырьё'!$C$6:$E$233,3,FALSE()),IFERROR(VLOOKUP(H67,'Полупродукты'!$C$6:$E$60,3,FALSE()),0)) -> 0 | L67: =IF(J67=0,0,J67*K67) -> 0
G68: 57 | H68: Полиуретан TEXAFLEX IV 509 LV | I68: =IFERROR(VLOOKUP(H68,'Сырьё'!$C$6:$D$233,2,FALSE()),IFERROR(VLOOKUP(H68,'Полупродукты'!$C$6:$D$60,2,FALSE()),"кг")) -> кг | J68: {=IF(B8="",0,IFERROR(INDEX('_Развёртки'!$C$2:$C$1358,MATCH(B8&"|"&H68,'_Развёртки'!$D$2:$D$1358,0)),0)*N(C8))+IF(B9="",0,IFERROR(INDEX('_Развёртки'!$C$2:$C$1358,MATCH(B9&"|"&H68,'_Развёртки'!$D$2:$D$1358,0)),0)*N(C9))+IF(B10="",0,IFERROR(INDEX('_Развёртки'!$C$2:$C$1358,MATCH(B10&"|"&H68,'_Развёртки'!$D$2:$D$1358,0)),0)*N(C10))+IF(B11="",0,IFERROR(INDEX('_Развёртки'!$C$2:$C$1358,MATCH(B11&"|"&H68,'_Развёртки'!$D$2:$D$1358,0)),0)*N(C11))+IF(B12="",0,IFERROR(INDEX('_Развёртки'!$C$2:$C$1358,MATCH(B12&"|"&H68,'_Развёртки'!$D$2:$D$1358,0)),0)*N(C12))+IF(B13="",0,IFERROR(INDEX('_Развёртки'!$C$2:$C$1358,MATCH(B13&"|"&H68,'_Развёртки'!$D$2:$D$1358,0)),0)*N(C13))+IF(B14="",0,IFERROR(INDEX('_Развёртки'!$C$2:$C$1358,MATCH(B14&"|"&H68,'_Развёртки'!$D$2:$D$1358,0)),0)*N(C14))+IF(B15="",0,IFERROR(INDEX('_Развёртки'!$C$2:$C$1358,MATCH(B15&"|"&H68,'_Развёртки'!$D$2:$D$1358,0)),0)*N(C15))+IF(B16="",0,IFERROR(INDEX('_Развёртки'!$C$2:$C$1358,MATCH(B16&"|"&H68,'_Развёртки'!$D$2:$D$1358,0)),0)*N(C16))+IF(B17="",0,IFERROR(INDEX('_Развёртки'!$C$2:$C$1358,MATCH(B17&"|"&H68,'_Развёртки'!$D$2:$D$1358,0)),0)*N(C17))+IF(B18="",0,IFERROR(INDEX('_Развёртки'!$C$2:$C$1358,MATCH(B18&"|"&H68,'_Развёртки'!$D$2:$D$1358,0)),0)*N(C18))+IF(B19="",0,IFERROR(INDEX('_Развёртки'!$C$2:$C$1358,MATCH(B19&"|"&H68,'_Развёртки'!$D$2:$D$1358,0)),0)*N(C19))+IF(B20="",0,IFERROR(INDEX('_Развёртки'!$C$2:$C$1358,MATCH(B20&"|"&H68,'_Развёртки'!$D$2:$D$1358,0)),0)*N(C20))+IF(B21="",0,IFERROR(INDEX('_Развёртки'!$C$2:$C$1358,MATCH(B21&"|"&H68,'_Развёртки'!$D$2:$D$1358,0)),0)*N(C21))+IF(B22="",0,IFERROR(INDEX('_Развёртки'!$C$2:$C$1358,MATCH(B22&"|"&H68,'_Развёртки'!$D$2:$D$1358,0)),0)*N(C22))+IF(B23="",0,IFERROR(INDEX('_Развёртки'!$C$2:$C$1358,MATCH(B23&"|"&H68,'_Развёртки'!$D$2:$D$1358,0)),0)*N(C23))+IF(B24="",0,IFERROR(INDEX('_Развёртки'!$C$2:$C$1358,MATCH(B24&"|"&H68,'_Развёртки'!$D$2:$D$1358,0)),0)*N(C24))+IF(B25="",0,IFERROR(INDEX('_Развёртки'!$C$2:$C$1358,MATCH(B25&"|"&H68,'_Развёртки'!$D$2:$D$1358,0)),0)*N(C25))+IF(B26="",0,IFERROR(INDEX('_Развёртки'!$C$2:$C$1358,MATCH(B26&"|"&H68,'_Развёртки'!$D$2:$D$1358,0)),0)*N(C26))+IF(B27="",0,IFERROR(INDEX('_Развёртки'!$C$2:$C$1358,MATCH(B27&"|"&H68,'_Развёртки'!$D$2:$D$1358,0)),0)*N(C27))} -> 0 | K68: =IFERROR(VLOOKUP(H68,'Сырьё'!$C$6:$E$233,3,FALSE()),IFERROR(VLOOKUP(H68,'Полупродукты'!$C$6:$E$60,3,FALSE()),0)) -> 5.0212 | L68: =IF(J68=0,0,J68*K68) -> 0
