Workbook

Sheet новы
A2: пп | B2: Дата выпуска продукции | C2: курс | D2: № ЗП | E2: Продукт | F2: Вес готового продукта | G2: Израсходовано по факту | H2: Израсходовано по факту Polyether Polyol Puranol D220, LE-220A Пропиленгликоль | I2: Потери, кг | J2: % потерь | K2: СС 1С на дату выпуска, EUR | L2: % пропиленгликоля в составе + полиол | M2: СС КГ, РУБ, Б/НДС | N2: СС Факт , EUR, Б/НДС | O2: СС Партии, EUR, Б/НДС | P2: СС Партии, РУБ, Б/НДС | R2: Примечание
B3: 45992 | C3: =VLOOKUP(B:B,'Курс валют'!A:D,4,0) -> 90.819 | D3: 01L2503-6 | E3: клей Starkbond 521 A бочка 220кг | F3: 4400 | G3: 4473.24 | H3: 78.84 | I3: =G3-F3 -> 73.24 | J3: =I3/F3*100 -> 1.6645455 | K3: 2.57 | L3: =H3/F3*100 -> 1.7918182 | M3: =P3/F3 -> 228.4578 | N3: =(F3*K3-H3*3.04)/F3 -> 2.5155287 | O3: =N3*F3 -> 11068.326 | P3: =O3*C3 -> 1005214.3
B4: 45994 | C4: =VLOOKUP(B:B,'Курс валют'!A:D,4,0) -> 89.8514 | D4: 03L2501-10 | E4: клей Starkbond 521 A бочка 220кг | F4: 11000 | G4: 11333.1 | H4: 197.1 | I4: =G4-F4 -> 333.1 | J4: =I4/F4*100 -> 3.0281818 | K4: 2.61 | L4: =H4/F4*100 -> 1.7918182 | M4: =P4/F4 -> 229.61783 | N4: =(F4*K4-H4*3.04)/F4 -> 2.5555287 | O4: =N4*F4 -> 28110.816 | P4: =O4*C4 -> 2525796.2
B5: 45995 | C5: =VLOOKUP(B:B,'Курс валют'!A:D,4,0) -> 90.5903 | D5: 04L2501-09 | E5: клей Starkbond 521 A бочка 220кг | F5: 9900 | G5: 9965.8 | H5: 177.39 | I5: =G5-F5 -> 65.8 | J5: =I5/F5*100 -> 0.66464646 | K5: 2.57 | L5: =H5/F5*100 -> 1.7918182 | M5: =P5/F5 -> 227.8825 | N5: =(F5*K5-H5*3.04)/F5 -> 2.5155287 | O5: =N5*F5 -> 24903.734 | P5: =O5*C5 -> 2256036.8
B6: 45996 | C6: =VLOOKUP(B:B,'Курс валют'!A:D,4,0) -> 89.9011 | D6: 05L2501-10 | E6: клей Starkbond 521 A бочка 220кг | F6: 11000 | G6: 11093.1 | H6: 4072.29 | I6: =G6-F6 -> 93.1 | J6: =I6/F6*100 -> 0.84636364 | K6: 3.57 | L6: =H6/F6*100 -> 37.020818 | M6: =P6/F6 -> 219.76927 | N6: =(F6*K6-H6*3.04)/F6 -> 2.4445671 | O6: =N6*F6 -> 26890.238 | P6: =O6*C6 -> 2417462
B7: 45997 | C7: =VLOOKUP(B:B,'Курс валют'!A:D,4,0) -> 88.7028 | D7: 06L2501-09 | E7: клей Starkbond 521 A бочка 220кг | F7: 9900 | G7: 9983.8 | H7: 4532.49 | I7: =G7-F7 -> 83.8 | J7: =I7/F7*100 -> 0.84646465 | K7: 3.84 | L7: =H7/F7*100 -> 45.782727 | M7: =P7/F7 -> 217.16265 | N7: =(F7*K7-H7*3.04)/F7 -> 2.4482051 | O7: =N7*F7 -> 24237.23 | P7: =O7*C7 -> 2149910.2
B8: 45998 | C8: =VLOOKUP(B:B,'Курс валют'!A:D,4,0) -> 88.7028 | D8: 07L2501-10 | E8: клей Starkbond 521 A бочка 220кг | F8: 11000 | G8: 11093.1 | H8: 5036.1 | I8: =G8-F8 -> 93.1 | J8: =I8/F8*100 -> 0.84636364 | K8: 3.52 | L8: =H8/F8*100 -> 45.782727 | M8: =P8/F8 -> 188.77775 | N8: =(F8*K8-H8*3.04)/F8 -> 2.1282051 | O8: =N8*F8 -> 23410.256 | P8: =O8*C8 -> 2076555.3
B9: 45999 | C9: =VLOOKUP(B:B,'Курс валют'!A:D,4,0) -> 88.7028 | D9: 08L2501-10 | E9: клей Starkbond 521 A бочка 220кг | F9: 11000 | G9: 11093.1 | H9: =5036.1-96.88 -> 4939.22 | I9: =G9-F9 -> 93.1 | J9: =I9/F9*100 -> 0.84636364 | K9: 3.5 | L9: =H9/F9*100 -> 44.902 | M9: =P9/F9 -> 189.37863 | N9: =(F9*K9-H9*3.04)/F9 -> 2.1349792 | O9: =N9*F9 -> 23484.771 | P9: =O9*C9 -> 2083165
B10: 46000 | C10: =VLOOKUP(B:B,'Курс валют'!A:D,4,0) -> 89.7054 | D10: 09L2502-10 | E10: клей Starkbond 521 A бочка 220кг | F10: 9900 | G10: 9988.3 | H10: 1868.79 | I10: =G10-F10 -> 88.3 | J10: =I10/F10*100 -> 0.89191919 | K10: 2.71 | L10: =H10/F10*100 -> 18.876667 | M10: =P10/F10 -> 191.62413 | N10: =(F10*K10-H10*3.04)/F10 -> 2.1361493 | O10: =N10*F10 -> 21147.878 | P10: =O10*C10 -> 1897078.9
B11: 46001 | C11: =VLOOKUP(B:B,'Курс валют'!A:D,4,0) -> 89.4267 | D11: 10L2501-10 | E11: клей Starkbond 521 A бочка 220кг | F11: 11000 | G11: 11118.1 | H11: 5031.1 | I11: =G11-F11 -> 118.1 | J11: =I11/F11*100 -> 1.0736364 | K11: 3.52 | L11: =H11/F11*100 -> 45.737273 | M11: =P11/F11 -> 190.44193 | N11: =(F11*K11-H11*3.04)/F11 -> 2.1295869 | O11: =N11*F11 -> 23425.456 | P11: =O11*C11 -> 2094861.2

Sheet Курс валют
A1: 45536 | B1: 1 | C1: EUR | D1: 100.7622 | E1: RUB
A2: 45537 | B2: 1 | C2: EUR | D2: 100.7622 | E2: RUB
A3: 45538 | B3: 1 | C3: EUR | D3: 99.2613 | E3: RUB
A4: 45539 | B4: 1 | C4: EUR | D4: 97.8121 | E4: RUB
A5: 45540 | B5: 1 | C5: EUR | D5: 98.0725 | E5: RUB
A6: 45541 | B6: 1 | C6: EUR | D6: 99.1927 | E6: RUB
A7: 45542 | B7: 1 | C7: EUR | D7: 99.7156 | E7: RUB
A8: 45543 | B8: 1 | C8: EUR | D8: 99.7156 | E8: RUB
A9: 45544 | B9: 1 | C9: EUR | D9: 99.7156 | E9: RUB
A10: 45545 | B10: 1 | C10: EUR | D10: 99.9067 | E10: RUB
A11: 45546 | B11: 1 | C11: EUR | D11: 100.4995 | E11: RUB
A12: 45547 | B12: 1 | C12: EUR | D12: 100.7421 | E12: RUB
... A460: 45997 | B460: 1 | C460: EUR | D460: 88.7028 | E460: RUB
A461: 45998 | B461: 1 | C461: EUR | D461: 88.7028 | E461: RUB | F461: 93.5626
A462: 45999 | B462: 1 | C462: EUR | D462: 88.7028 | E462: RUB
A463: 46000 | B463: 1 | C463: EUR | D463: 89.7054 | E463: RUB
A464: 46001 | B464: 1 | C464: EUR | D464: 89.4267 | E464: RUB
A465: 46002 | B465: 1 | C465: EUR | D465: 91.3806 | E465: RUB
A466: 46003 | B466: 1 | C466: EUR | D466: 92.9384 | E466: RUB
A467: 46004 | B467: 1 | C467: EUR | D467: 93.5626 | E467: RUB
A468: 46005 | B468: 1 | C468: EUR | D468: 93.5626 | E468: RUB
A469: 46006 | B469: 1 | C469: EUR | D469: 93.5626 | E469: RUB
A470: 46007 | B470: 1 | C470: EUR | D470: 93.2274 | E470: RUB
A471: 46008 | B471: 1 | C471: EUR | D471: 93.8054 | E471: RUB
A472: 46009 | B472: 1 | C472: EUR | D472: 94.1478 | E472: RUB
A473: 46010 | B473: 1 | C473: EUR | D473: 94.2524 | E473: RUB
... A652: 46189 | B652: 1 | C652: EUR | D652: 83.8044 | E652: RUB
A653: 46190 | B653: 1 | C653: EUR | E653: RUB
A654: 46191 | B654: 1 | C654: EUR | E654: RUB
A655: 46192 | B655: 1 | C655: EUR | E655: RUB
A656: 46193 | B656: 1 | C656: EUR | E656: RUB
A657: 46194 | B657: 1 | C657: EUR | E657: RUB
A658: 46195 | B658: 1 | C658: EUR | E658: RUB
A659: 46196 | B659: 1 | C659: EUR | E659: RUB
A660: 46197 | B660: 1 | C660: EUR | E660: RUB
A661: 46198 | B661: 1 | C661: EUR | E661: RUB
A662: 46199 | B662: 1 | C662: EUR | E662: RUB
E663: RUB
E664: RUB
E665: RUB

Sheet Формула Среднего
A1: Продукт | B1: Сентябрь 24 | C1: Октябрь 24 | D1: Ноябрь 24 | E1: Декабрь 24 | F1: Январь 25 | G1: Февраль 2025 | H1: Март 25 | I1: Апрель 25 | J1: Май 25 | K1: Июнь 25 | L1: Июль 25 | M1: Август 25 | N1: Сентябрь 25 | O1: Октябрь 25 | P1: Ноябрь 25 | Q1: Декабрь 25 | R1: Январь 26 | S1: Февраль 26 | T1: Март 26 | U1: Апрель 2026 | V1: Май 2026 | W1: Июнь 2026 | X1: Июль 2026
A2: Отвердитель Starkbond 521C 10.0 бочка 200кг | B2: =IFERROR(AVERAGEIFS('Сентябрь 2024'!$K:$K,'Сентябрь 2024'!$E:$E,$A:$A),"-") -> 1.946 | C2: =IFERROR(AVERAGEIFS('Октябрь 2024'!$K:$K,'Октябрь 2024'!$E:$E,$A:$A),"-") -> 2.77 | D2: =IFERROR(AVERAGEIFS('Ноябрь 2024'!$K:$K,'Ноябрь 2024'!$E:$E,$A:$A),"-") -> 1.9733333 | E2: =IFERROR(AVERAGEIFS('Декабрь 2024'!$K:$K,'Декабрь 2024'!$E:$E,$A:$A),"-") -> - | F2: =IFERROR(AVERAGEIFS('Январь 2025'!$K:$K,'Январь 2025'!$E:$E,$A:$A),"-") -> 2.0853846 | G2: =IFERROR(AVERAGEIFS('Февраль 2025 '!K:K,'Февраль 2025 '!E:E,A:A),"-") -> 2.02 | H2: =IFERROR(AVERAGEIFS('Март 2025'!$K:$K,'Март 2025'!$E:$E,$A:$A),"-") -> 2.0116667 | I2: =IFERROR(AVERAGEIFS('Апрель 2025'!$K:$K,'Апрель 2025'!$E:$E,$A:$A),"-") -> 1.9366667 | J2: =IFERROR(AVERAGEIFS('Май 2025'!$K:$K,'Май 2025'!$E:$E,$A:$A),"-") -> 1.8828571 | K2: =IFERROR(AVERAGEIFS('Июнь 2025'!$K:$K,'Июнь 2025'!$E:$E,$A:$A),"-") -> 1.8633333 | L2: =IFERROR(AVERAGEIFS('Июль 2025'!$K:$K,'Июль 2025'!$E:$E,$A:$A),"-") -> 2.2175 | M2: =IFERROR(AVERAGEIFS('Август 2025'!$K:$K,'Август 2025'!$E:$E,$A:$A),"-") -> 1.8766667 | N2: =IFERROR(AVERAGEIFS('Сентябрь 2025'!$K:$K,'Сентябрь 2025'!$E:$E,$A:$A),"-") -> 2.02 | O2: =IFERROR(AVERAGEIFS('Октябрь 2025'!$K:$K,'Октябрь 2025'!$E:$E,$A:$A),"-") -> 1.9028571 | P2: =IFERROR(AVERAGEIFS('Ноябрь 2025'!$K:$K,'Ноябрь 2025'!$E:$E,$A:$A),"-") -> 1.9333333 | Q2: =IFERROR(AVERAGEIFS('Декабрь 2025'!$K:$K,'Декабрь 2025'!$E:$E,$A:$A),"-") -> 1.9184615 | R2: =IFERROR(AVERAGEIFS('Январь 2026'!$K:$K,'Январь 2026'!$E:$E,$A:$A),"-") -> 1.97 | S2: =IFERROR(AVERAGEIFS('Февраль 2026'!$K:$K,'Февраль 2026'!$E:$E,$A:$A),"-") -> 1.95 | T2: =IFERROR(AVERAGEIFS('Март 2026'!$K:$K,'Март 2026'!$E:$E,$A:$A),"-") -> 1.9616667 | U2: =IFERROR(AVERAGEIFS('Апрель 2026'!$K:$K,'Апрель 2026'!$E:$E,$A:$A),"-") -> 1.886 | V2: =IFERROR(AVERAGEIFS('Май 2026'!$K:$K,'Май 2026'!$E:$E,$A:$A),"-") -> - | W2: =IFERROR(AVERAGEIFS('Июнь 2026'!$K:$K,'Июнь 2026'!$E:$E,$A:$A),"-") -> - | X2: =IFERROR(AVERAGEIFS('Июль 2026'!$K:$K,'Июль 2026'!$E:$E,$A:$A),"-") -> -
A3: клей Starkbond 521 A бочка 220кг | B3: =IFERROR(AVERAGEIFS('Сентябрь 2024'!$K:$K,'Сентябрь 2024'!$E:$E,$A:$A),"-") -> 3.998125 | C3: =IFERROR(AVERAGEIFS('Октябрь 2024'!$K:$K,'Октябрь 2024'!$E:$E,$A:$A),"-") -> 4.01 | D3: =IFERROR(AVERAGEIFS('Ноябрь 2024'!$K:$K,'Ноябрь 2024'!$E:$E,$A:$A),"-") -> 3.805625 | E3: =IFERROR(AVERAGEIFS('Декабрь 2024'!$K:$K,'Декабрь 2024'!$E:$E,$A:$A),"-") -> 3.58625 | F3: =IFERROR(AVERAGEIFS('Январь 2025'!$K:$K,'Январь 2025'!$E:$E,$A:$A),"-") -> 3.6981818 | G3: =IFERROR(AVERAGEIFS('Февраль 2025 '!K:K,'Февраль 2025 '!E:E,A:A),"-") -> 3.7193333 | H3: =IFERROR(AVERAGEIFS('Март 2025'!$K:$K,'Март 2025'!$E:$E,$A:$A),"-") -> 2.7869231 | I3: =IFERROR(AVERAGEIFS('Апрель 2025'!$K:$K,'Апрель 2025'!$E:$E,$A:$A),"-") -> 2.788125 | J3: =IFERROR(AVERAGEIFS('Май 2025'!$K:$K,'Май 2025'!$E:$E,$A:$A),"-") -> 3.1246667 | K3: =IFERROR(AVERAGEIFS('Июнь 2025'!$K:$K,'Июнь 2025'!$E:$E,$A:$A),"-") -> 3.7633333 | L3: =IFERROR(AVERAGEIFS('Июль 2025'!$K:$K,'Июль 2025'!$E:$E,$A:$A),"-") -> 2.4871429 | M3: =IFERROR(AVERAGEIFS('Август 2025'!$K:$K,'Август 2025'!$E:$E,$A:$A),"-") -> 2.6475 | N3: =IFERROR(AVERAGEIFS('Сентябрь 2025'!$K:$K,'Сентябрь 2025'!$E:$E,$A:$A),"-") -> 3.6257143 | O3: =IFERROR(AVERAGEIFS('Октябрь 2025'!$K:$K,'Октябрь 2025'!$E:$E,$A:$A),"-") -> 3.3088235 | P3: =IFERROR(AVERAGEIFS('Ноябрь 2025'!$K:$K,'Ноябрь 2025'!$E:$E,$A:$A),"-") -> 3.0361538 | Q3: =IFERROR(AVERAGEIFS('Декабрь 2025'!$K:$K,'Декабрь 2025'!$E:$E,$A:$A),"-") -> 3.4235294 | R3: =IFERROR(AVERAGEIFS('Январь 2026'!$K:$K,'Январь 2026'!$E:$E,$A:$A),"-") -> - | S3: =IFERROR(AVERAGEIFS('Февраль 2026'!$K:$K,'Февраль 2026'!$E:$E,$A:$A),"-") -> 3.1130952 | T3: =IFERROR(AVERAGEIFS('Март 2026'!$K:$K,'Март 2026'!$E:$E,$A:$A),"-") -> 2.9145536 | U3: =IFERROR(AVERAGEIFS('Апрель 2026'!$K:$K,'Апрель 2026'!$E:$E,$A:$A),"-") -> 6.4107246 | V3: =IFERROR(AVERAGEIFS('Май 2026'!$K:$K,'Май 2026'!$E:$E,$A:$A),"-") -> 5.2023469 | W3: =IFERROR(AVERAGEIFS('Июнь 2026'!$K:$K,'Июнь 2026'!$E:$E,$A:$A),"-") -> - | X3: =IFERROR(AVERAGEIFS('Июль 2026'!$K:$K,'Июль 2026'!$E:$E,$A:$A),"-") -> -
A4: Отвердитель Starkbond 521C 11.0 бочка 200кг | B4: =IFERROR(AVERAGEIFS('Сентябрь 2024'!$K:$K,'Сентябрь 2024'!$E:$E,$A:$A),"-") -> 1.94 | C4: =IFERROR(AVERAGEIFS('Октябрь 2024'!$K:$K,'Октябрь 2024'!$E:$E,$A:$A),"-") -> 1.99 | D4: =IFERROR(AVERAGEIFS('Ноябрь 2024'!$K:$K,'Ноябрь 2024'!$E:$E,$A:$A),"-") -> 1.9966667 | E4: =IFERROR(AVERAGEIFS('Декабрь 2024'!$K:$K,'Декабрь 2024'!$E:$E,$A:$A),"-") -> - | F4: =IFERROR(AVERAGEIFS('Январь 2025'!$K:$K,'Январь 2025'!$E:$E,$A:$A),"-") -> 2.18 | G4: =IFERROR(AVERAGEIFS('Февраль 2025 '!K:K,'Февраль 2025 '!E:E,A:A),"-") -> - | H4: =IFERROR(AVERAGEIFS('Март 2025'!$K:$K,'Март 2025'!$E:$E,$A:$A),"-") -> 2.18 | I4: =IFERROR(AVERAGEIFS('Апрель 2025'!$K:$K,'Апрель 2025'!$E:$E,$A:$A),"-") -> 2.03 | J4: =IFERROR(AVERAGEIFS('Май 2025'!$K:$K,'Май 2025'!$E:$E,$A:$A),"-") -> - | K4: =IFERROR(AVERAGEIFS('Июнь 2025'!$K:$K,'Июнь 2025'!$E:$E,$A:$A),"-") -> 1.89 | L4: =IFERROR(AVERAGEIFS('Июль 2025'!$K:$K,'Июль 2025'!$E:$E,$A:$A),"-") -> 1.99 | M4: =IFERROR(AVERAGEIFS('Август 2025'!$K:$K,'Август 2025'!$E:$E,$A:$A),"-") -> 1.99 | N4: =IFERROR(AVERAGEIFS('Сентябрь 2025'!$K:$K,'Сентябрь 2025'!$E:$E,$A:$A),"-") -> 1.9266667 | O4: =IFERROR(AVERAGEIFS('Октябрь 2025'!$K:$K,'Октябрь 2025'!$E:$E,$A:$A),"-") -> 1.89375 | P4: =IFERROR(AVERAGEIFS('Ноябрь 2025'!$K:$K,'Ноябрь 2025'!$E:$E,$A:$A),"-") -> 1.91 | Q4: =IFERROR(AVERAGEIFS('Декабрь 2025'!$K:$K,'Декабрь 2025'!$E:$E,$A:$A),"-") -> 2.0478571 | R4: =IFERROR(AVERAGEIFS('Январь 2026'!$K:$K,'Январь 2026'!$E:$E,$A:$A),"-") -> 2.001 | S4: =IFERROR(AVERAGEIFS('Февраль 2026'!$K:$K,'Февраль 2026'!$E:$E,$A:$A),"-") -> - | T4: =IFERROR(AVERAGEIFS('Март 2026'!$K:$K,'Март 2026'!$E:$E,$A:$A),"-") -> 1.9721667 | U4: =IFERROR(AVERAGEIFS('Апрель 2026'!$K:$K,'Апрель 2026'!$E:$E,$A:$A),"-") -> 1.8911429 | V4: =IFERROR(AVERAGEIFS('Май 2026'!$K:$K,'Май 2026'!$E:$E,$A:$A),"-") -> 1.9107692 | W4: =IFERROR(AVERAGEIFS('Июнь 2026'!$K:$K,'Июнь 2026'!$E:$E,$A:$A),"-") -> - | X4: =IFERROR(AVERAGEIFS('Июль 2026'!$K:$K,'Июль 2026'!$E:$E,$A:$A),"-") -> -
A5: отвердитель Starkbond 746/1 С бочка 200кг | B5: =IFERROR(AVERAGEIFS('Сентябрь 2024'!$K:$K,'Сентябрь 2024'!$E:$E,$A:$A),"-") -> - | C5: =IFERROR(AVERAGEIFS('Октябрь 2024'!$K:$K,'Октябрь 2024'!$E:$E,$A:$A),"-") -> - | D5: =IFERROR(AVERAGEIFS('Ноябрь 2024'!$K:$K,'Ноябрь 2024'!$E:$E,$A:$A),"-") -> - | E5: =IFERROR(AVERAGEIFS('Декабрь 2024'!$K:$K,'Декабрь 2024'!$E:$E,$A:$A),"-") -> - | F5: =IFERROR(AVERAGEIFS('Январь 2025'!$K:$K,'Январь 2025'!$E:$E,$A:$A),"-") -> - | G5: =IFERROR(AVERAGEIFS('Февраль 2025 '!K:K,'Февраль 2025 '!E:E,A:A),"-") -> 2.62 | H5: =IFERROR(AVERAGEIFS('Март 2025'!$K:$K,'Март 2025'!$E:$E,$A:$A),"-") -> 2.715 | I5: =IFERROR(AVERAGEIFS('Апрель 2025'!$K:$K,'Апрель 2025'!$E:$E,$A:$A),"-") -> - | J5: =IFERROR(AVERAGEIFS('Май 2025'!$K:$K,'Май 2025'!$E:$E,$A:$A),"-") -> - | K5: =IFERROR(AVERAGEIFS('Июнь 2025'!$K:$K,'Июнь 2025'!$E:$E,$A:$A),"-") -> - | L5: =IFERROR(AVERAGEIFS('Июль 2025'!$K:$K,'Июль 2025'!$E:$E,$A:$A),"-") -> - | M5: =IFERROR(AVERAGEIFS('Август 2025'!$K:$K,'Август 2025'!$E:$E,$A:$A),"-") -> - | N5: =IFERROR(AVERAGEIFS('Сентябрь 2025'!$K:$K,'Сентябрь 2025'!$E:$E,$A:$A),"-") -> 2.69 | O5: =IFERROR(AVERAGEIFS('Октябрь 2025'!$K:$K,'Октябрь 2025'!$E:$E,$A:$A),"-") -> 2.6 | P5: =IFERROR(AVERAGEIFS('Ноябрь 2025'!$K:$K,'Ноябрь 2025'!$E:$E,$A:$A),"-") -> 2.68 | Q5: =IFERROR(AVERAGEIFS('Декабрь 2025'!$K:$K,'Декабрь 2025'!$E:$E,$A:$A),"-") -> - | R5: =IFERROR(AVERAGEIFS('Январь 2026'!$K:$K,'Январь 2026'!$E:$E,$A:$A),"-") -> 2.74 | S5: =IFERROR(AVERAGEIFS('Февраль 2026'!$K:$K,'Февраль 2026'!$E:$E,$A:$A),"-") -> - | T5: =IFERROR(AVERAGEIFS('Март 2026'!$K:$K,'Март 2026'!$E:$E,$A:$A),"-") -> 2.75 | U5: =IFERROR(AVERAGEIFS('Апрель 2026'!$K:$K,'Апрель 2026'!$E:$E,$A:$A),"-") -> 2.765 | V5: =IFERROR(AVERAGEIFS('Май 2026'!$K:$K,'Май 2026'!$E:$E,$A:$A),"-") -> 2.78 | W5: =IFERROR(AVERAGEIFS('Июнь 2026'!$K:$K,'Июнь 2026'!$E:$E,$A:$A),"-") -> - | X5: =IFERROR(AVERAGEIFS('Июль 2026'!$K:$K,'Июль 2026'!$E:$E,$A:$A),"-") -> -
A6: Отвердитель Starkbond 525C 2.0 Бочка 200 кг | B6: =IFERROR(AVERAGEIFS('Сентябрь 2024'!$K:$K,'Сентябрь 2024'!$E:$E,$A:$A),"-") -> 3.42 | C6: =IFERROR(AVERAGEIFS('Октябрь 2024'!$K:$K,'Октябрь 2024'!$E:$E,$A:$A),"-") -> 3.33 | D6: =IFERROR(AVERAGEIFS('Ноябрь 2024'!$K:$K,'Ноябрь 2024'!$E:$E,$A:$A),"-") -> 3.22 | E6: =IFERROR(AVERAGEIFS('Декабрь 2024'!$K:$K,'Декабрь 2024'!$E:$E,$A:$A),"-") -> - | F6: =IFERROR(AVERAGEIFS('Январь 2025'!$K:$K,'Январь 2025'!$E:$E,$A:$A),"-") -> - | G6: =IFERROR(AVERAGEIFS('Февраль 2025 '!K:K,'Февраль 2025 '!E:E,A:A),"-") -> 3.19 | H6: =IFERROR(AVERAGEIFS('Март 2025'!$K:$K,'Март 2025'!$E:$E,$A:$A),"-") -> 3.185 | I6: =IFERROR(AVERAGEIFS('Апрель 2025'!$K:$K,'Апрель 2025'!$E:$E,$A:$A),"-") -> - | J6: =IFERROR(AVERAGEIFS('Май 2025'!$K:$K,'Май 2025'!$E:$E,$A:$A),"-") -> - | K6: =IFERROR(AVERAGEIFS('Июнь 2025'!$K:$K,'Июнь 2025'!$E:$E,$A:$A),"-") -> - | L6: =IFERROR(AVERAGEIFS('Июль 2025'!$K:$K,'Июль 2025'!$E:$E,$A:$A),"-") -> - | M6: =IFERROR(AVERAGEIFS('Август 2025'!$K:$K,'Август 2025'!$E:$E,$A:$A),"-") -> - | N6: =IFERROR(AVERAGEIFS('Сентябрь 2025'!$K:$K,'Сентябрь 2025'!$E:$E,$A:$A),"-") -> - | O6: =IFERROR(AVERAGEIFS('Октябрь 2025'!$K:$K,'Октябрь 2025'!$E:$E,$A:$A),"-") -> - | P6: =IFERROR(AVERAGEIFS('Ноябрь 2025'!$K:$K,'Ноябрь 2025'!$E:$E,$A:$A),"-") -> - | Q6: =IFERROR(AVERAGEIFS('Декабрь 2025'!$K:$K,'Декабрь 2025'!$E:$E,$A:$A),"-") -> - | R6: =IFERROR(AVERAGEIFS('Январь 2026'!$K:$K,'Январь 2026'!$E:$E,$A:$A),"-") -> - | S6: =IFERROR(AVERAGEIFS('Февраль 2026'!$K:$K,'Февраль 2026'!$E:$E,$A:$A),"-") -> - | T6: =IFERROR(AVERAGEIFS('Март 2026'!$K:$K,'Март 2026'!$E:$E,$A:$A),"-") -> - | U6: =IFERROR(AVERAGEIFS('Апрель 2026'!$K:$K,'Апрель 2026'!$E:$E,$A:$A),"-") -> - | V6: =IFERROR(AVERAGEIFS('Май 2026'!$K:$K,'Май 2026'!$E:$E,$A:$A),"-") -> - | W6: =IFERROR(AVERAGEIFS('Июнь 2026'!$K:$K,'Июнь 2026'!$E:$E,$A:$A),"-") -> - | X6: =IFERROR(AVERAGEIFS('Июль 2026'!$K:$K,'Июль 2026'!$E:$E,$A:$A),"-") -> -
A7: Отвердитель Starkbond 525C 3.0 Бочка 200 кг | B7: =IFERROR(AVERAGEIFS('Сентябрь 2024'!$K:$K,'Сентябрь 2024'!$E:$E,$A:$A),"-") -> - | C7: =IFERROR(AVERAGEIFS('Октябрь 2024'!$K:$K,'Октябрь 2024'!$E:$E,$A:$A),"-") -> - | D7: =IFERROR(AVERAGEIFS('Ноябрь 2024'!$K:$K,'Ноябрь 2024'!$E:$E,$A:$A),"-") -> - | E7: =IFERROR(AVERAGEIFS('Декабрь 2024'!$K:$K,'Декабрь 2024'!$E:$E,$A:$A),"-") -> - | F7: =IFERROR(AVERAGEIFS('Январь 2025'!$K:$K,'Январь 2025'!$E:$E,$A:$A),"-") -> 3.01 | G7: =IFERROR(AVERAGEIFS('Февраль 2025 '!K:K,'Февраль 2025 '!E:E,A:A),"-") -> - | H7: =IFERROR(AVERAGEIFS('Март 2025'!$K:$K,'Март 2025'!$E:$E,$A:$A),"-") -> 2.9 | I7: =IFERROR(AVERAGEIFS('Апрель 2025'!$K:$K,'Апрель 2025'!$E:$E,$A:$A),"-") -> - | J7: =IFERROR(AVERAGEIFS('Май 2025'!$K:$K,'Май 2025'!$E:$E,$A:$A),"-") -> 3.225 | K7: =IFERROR(AVERAGEIFS('Июнь 2025'!$K:$K,'Июнь 2025'!$E:$E,$A:$A),"-") -> 2.7133333 | L7: =IFERROR(AVERAGEIFS('Июль 2025'!$K:$K,'Июль 2025'!$E:$E,$A:$A),"-") -> 2.5933333 | M7: =IFERROR(AVERAGEIFS('Август 2025'!$K:$K,'Август 2025'!$E:$E,$A:$A),"-") -> - | N7: =IFERROR(AVERAGEIFS('Сентябрь 2025'!$K:$K,'Сентябрь 2025'!$E:$E,$A:$A),"-") -> - | O7: =IFERROR(AVERAGEIFS('Октябрь 2025'!$K:$K,'Октябрь 2025'!$E:$E,$A:$A),"-") -> - | P7: =IFERROR(AVERAGEIFS('Ноябрь 2025'!$K:$K,'Ноябрь 2025'!$E:$E,$A:$A),"-") -> - | Q7: =IFERROR(AVERAGEIFS('Декабрь 2025'!$K:$K,'Декабрь 2025'!$E:$E,$A:$A),"-") -> 2.53 | R7: =IFERROR(AVERAGEIFS('Январь 2026'!$K:$K,'Январь 2026'!$E:$E,$A:$A),"-") -> - | S7: =IFERROR(AVERAGEIFS('Февраль 2026'!$K:$K,'Февраль 2026'!$E:$E,$A:$A),"-") -> - | T7: =IFERROR(AVERAGEIFS('Март 2026'!$K:$K,'Март 2026'!$E:$E,$A:$A),"-") -> - | U7: =IFERROR(AVERAGEIFS('Апрель 2026'!$K:$K,'Апрель 2026'!$E:$E,$A:$A),"-") -> - | V7: =IFERROR(AVERAGEIFS('Май 2026'!$K:$K,'Май 2026'!$E:$E,$A:$A),"-") -> 2.5725 | W7: =IFERROR(AVERAGEIFS('Июнь 2026'!$K:$K,'Июнь 2026'!$E:$E,$A:$A),"-") -> - | X7: =IFERROR(AVERAGEIFS('Июль 2026'!$K:$K,'Июль 2026'!$E:$E,$A:$A),"-") -> -
A8: отвердитель Starkbond 525C v0 (ведро 22 кг) | B8: =IFERROR(AVERAGEIFS('Сентябрь 2024'!$K:$K,'Сентябрь 2024'!$E:$E,$A:$A),"-") -> - | C8: =IFERROR(AVERAGEIFS('Октябрь 2024'!$K:$K,'Октябрь 2024'!$E:$E,$A:$A),"-") -> - | D8: =IFERROR(AVERAGEIFS('Ноябрь 2024'!$K:$K,'Ноябрь 2024'!$E:$E,$A:$A),"-") -> - | E8: =IFERROR(AVERAGEIFS('Декабрь 2024'!$K:$K,'Декабрь 2024'!$E:$E,$A:$A),"-") -> - | F8: =IFERROR(AVERAGEIFS('Январь 2025'!$K:$K,'Январь 2025'!$E:$E,$A:$A),"-") -> - | G8: =IFERROR(AVERAGEIFS('Февраль 2025 '!K:K,'Февраль 2025 '!E:E,A:A),"-") -> - | H8: =IFERROR(AVERAGEIFS('Март 2025'!$K:$K,'Март 2025'!$E:$E,$A:$A),"-") -> 2.86 | I8: =IFERROR(AVERAGEIFS('Апрель 2025'!$K:$K,'Апрель 2025'!$E:$E,$A:$A),"-") -> - | J8: =IFERROR(AVERAGEIFS('Май 2025'!$K:$K,'Май 2025'!$E:$E,$A:$A),"-") -> - | K8: =IFERROR(AVERAGEIFS('Июнь 2025'!$K:$K,'Июнь 2025'!$E:$E,$A:$A),"-") -> - | L8: =IFERROR(AVERAGEIFS('Июль 2025'!$K:$K,'Июль 2025'!$E:$E,$A:$A),"-") -> - | M8: =IFERROR(AVERAGEIFS('Август 2025'!$K:$K,'Август 2025'!$E:$E,$A:$A),"-") -> - | N8: =IFERROR(AVERAGEIFS('Сентябрь 2025'!$K:$K,'Сентябрь 2025'!$E:$E,$A:$A),"-") -> - | O8: =IFERROR(AVERAGEIFS('Октябрь 2025'!$K:$K,'Октябрь 2025'!$E:$E,$A:$A),"-") -> - | P8: =IFERROR(AVERAGEIFS('Ноябрь 2025'!$K:$K,'Ноябрь 2025'!$E:$E,$A:$A),"-") -> - | Q8: =IFERROR(AVERAGEIFS('Декабрь 2025'!$K:$K,'Декабрь 2025'!$E:$E,$A:$A),"-") -> - | R8: =IFERROR(AVERAGEIFS('Январь 2026'!$K:$K,'Январь 2026'!$E:$E,$A:$A),"-") -> - | S8: =IFERROR(AVERAGEIFS('Февраль 2026'!$K:$K,'Февраль 2026'!$E:$E,$A:$A),"-") -> - | T8: =IFERROR(AVERAGEIFS('Март 2026'!$K:$K,'Март 2026'!$E:$E,$A:$A),"-") -> - | U8: =IFERROR(AVERAGEIFS('Апрель 2026'!$K:$K,'Апрель 2026'!$E:$E,$A:$A),"-") -> - | V8: =IFERROR(AVERAGEIFS('Май 2026'!$K:$K,'Май 2026'!$E:$E,$A:$A),"-") -> - | W8: =IFERROR(AVERAGEIFS('Июнь 2026'!$K:$K,'Июнь 2026'!$E:$E,$A:$A),"-") -> - | X8: =IFERROR(AVERAGEIFS('Июль 2026'!$K:$K,'Июль 2026'!$E:$E,$A:$A),"-") -> -
A9: Клей Starkbond 745/41 А (бочка 200 кг) | B9: =IFERROR(AVERAGEIFS('Сентябрь 2024'!$K:$K,'Сентябрь 2024'!$E:$E,$A:$A),"-") -> 3.24625 | C9: =IFERROR(AVERAGEIFS('Октябрь 2024'!$K:$K,'Октябрь 2024'!$E:$E,$A:$A),"-") -> - | D9: =IFERROR(AVERAGEIFS('Ноябрь 2024'!$K:$K,'Ноябрь 2024'!$E:$E,$A:$A),"-") -> 3.03 | E9: =IFERROR(AVERAGEIFS('Декабрь 2024'!$K:$K,'Декабрь 2024'!$E:$E,$A:$A),"-") -> - | F9: =IFERROR(AVERAGEIFS('Январь 2025'!$K:$K,'Январь 2025'!$E:$E,$A:$A),"-") -> - | G9: =IFERROR(AVERAGEIFS('Февраль 2025 '!K:K,'Февраль 2025 '!E:E,A:A),"-") -> 3.07 | H9: =IFERROR(AVERAGEIFS('Март 2025'!$K:$K,'Март 2025'!$E:$E,$A:$A),"-") -> 3.12 | I9: =IFERROR(AVERAGEIFS('Апрель 2025'!$K:$K,'Апрель 2025'!$E:$E,$A:$A),"-") -> 3.1766667 | J9: =IFERROR(AVERAGEIFS('Май 2025'!$K:$K,'Май 2025'!$E:$E,$A:$A),"-") -> 3.15625 | K9: =IFERROR(AVERAGEIFS('Июнь 2025'!$K:$K,'Июнь 2025'!$E:$E,$A:$A),"-") -> - | L9: =IFERROR(AVERAGEIFS('Июль 2025'!$K:$K,'Июль 2025'!$E:$E,$A:$A),"-") -> - | M9: =IFERROR(AVERAGEIFS('Август 2025'!$K:$K,'Август 2025'!$E:$E,$A:$A),"-") -> 2.3375 | N9: =IFERROR(AVERAGEIFS('Сентябрь 2025'!$K:$K,'Сентябрь 2025'!$E:$E,$A:$A),"-") -> 2.48 | O9: =IFERROR(AVERAGEIFS('Октябрь 2025'!$K:$K,'Октябрь 2025'!$E:$E,$A:$A),"-") -> 2.296 | P9: =IFERROR(AVERAGEIFS('Ноябрь 2025'!$K:$K,'Ноябрь 2025'!$E:$E,$A:$A),"-") -> 2.3 | Q9: =IFERROR(AVERAGEIFS('Декабрь 2025'!$K:$K,'Декабрь 2025'!$E:$E,$A:$A),"-") -> 2.38 | R9: =IFERROR(AVERAGEIFS('Январь 2026'!$K:$K,'Январь 2026'!$E:$E,$A:$A),"-") -> 2.24 | S9: =IFERROR(AVERAGEIFS('Февраль 2026'!$K:$K,'Февраль 2026'!$E:$E,$A:$A),"-") -> 2.3433333 | T9: =IFERROR(AVERAGEIFS('Март 2026'!$K:$K,'Март 2026'!$E:$E,$A:$A),"-") -> 2.37 | U9: =IFERROR(AVERAGEIFS('Апрель 2026'!$K:$K,'Апрель 2026'!$E:$E,$A:$A),"-") -> 2.36 | V9: =IFERROR(AVERAGEIFS('Май 2026'!$K:$K,'Май 2026'!$E:$E,$A:$A),"-") -> 2.43 | W9: =IFERROR(AVERAGEIFS('Июнь 2026'!$K:$K,'Июнь 2026'!$E:$E,$A:$A),"-") -> - | X9: =IFERROR(AVERAGEIFS('Июль 2026'!$K:$K,'Июль 2026'!$E:$E,$A:$A),"-") -> -
A10: Клей Starkbond 525A бочка 200 кг | B10: =IFERROR(AVERAGEIFS('Сентябрь 2024'!$K:$K,'Сентябрь 2024'!$E:$E,$A:$A),"-") -> - | C10: =IFERROR(AVERAGEIFS('Октябрь 2024'!$K:$K,'Октябрь 2024'!$E:$E,$A:$A),"-") -> - | D10: =IFERROR(AVERAGEIFS('Ноябрь 2024'!$K:$K,'Ноябрь 2024'!$E:$E,$A:$A),"-") -> - | E10: =IFERROR(AVERAGEIFS('Декабрь 2024'!$K:$K,'Декабрь 2024'!$E:$E,$A:$A),"-") -> - | F10: =IFERROR(AVERAGEIFS('Январь 2025'!$K:$K,'Январь 2025'!$E:$E,$A:$A),"-") -> 3.91 | G10: =IFERROR(AVERAGEIFS('Февраль 2025 '!K:K,'Февраль 2025 '!E:E,A:A),"-") -> - | H10: =IFERROR(AVERAGEIFS('Март 2025'!$K:$K,'Март 2025'!$E:$E,$A:$A),"-") -> - | I10: =IFERROR(AVERAGEIFS('Апрель 2025'!$K:$K,'Апрель 2025'!$E:$E,$A:$A),"-") -> 2.78 | J10: =IFERROR(AVERAGEIFS('Май 2025'!$K:$K,'Май 2025'!$E:$E,$A:$A),"-") -> 2.66875 | K10: =IFERROR(AVERAGEIFS('Июнь 2025'!$K:$K,'Июнь 2025'!$E:$E,$A:$A),"-") -> 3.7985714 | L10: =IFERROR(AVERAGEIFS('Июль 2025'!$K:$K,'Июль 2025'!$E:$E,$A:$A),"-") -> 3.0855556 | M10: =IFERROR(AVERAGEIFS('Август 2025'!$K:$K,'Август 2025'!$E:$E,$A:$A),"-") -> - | N10: =IFERROR(AVERAGEIFS('Сентябрь 2025'!$K:$K,'Сентябрь 2025'!$E:$E,$A:$A),"-") -> - | O10: =IFERROR(AVERAGEIFS('Октябрь 2025'!$K:$K,'Октябрь 2025'!$E:$E,$A:$A),"-") -> - | P10: =IFERROR(AVERAGEIFS('Ноябрь 2025'!$K:$K,'Ноябрь 2025'!$E:$E,$A:$A),"-") -> - | Q10: =IFERROR(AVERAGEIFS('Декабрь 2025'!$K:$K,'Декабрь 2025'!$E:$E,$A:$A),"-") -> - | R10: =IFERROR(AVERAGEIFS('Январь 2026'!$K:$K,'Январь 2026'!$E:$E,$A:$A),"-") -> - | S10: =IFERROR(AVERAGEIFS('Февраль 2026'!$K:$K,'Февраль 2026'!$E:$E,$A:$A),"-") -> 2.44 | T10: =IFERROR(AVERAGEIFS('Март 2026'!$K:$K,'Март 2026'!$E:$E,$A:$A),"-") -> - | U10: =IFERROR(AVERAGEIFS('Апрель 2026'!$K:$K,'Апрель 2026'!$E:$E,$A:$A),"-") -> - | V10: =IFERROR(AVERAGEIFS('Май 2026'!$K:$K,'Май 2026'!$E:$E,$A:$A),"-") -> 2.6 | W10: =IFERROR(AVERAGEIFS('Июнь 2026'!$K:$K,'Июнь 2026'!$E:$E,$A:$A),"-") -> - | X10: =IFERROR(AVERAGEIFS('Июль 2026'!$K:$K,'Июль 2026'!$E:$E,$A:$A),"-") -> -
A11: Клей Starkbond 522A бочка 220 кг | B11: =IFERROR(AVERAGEIFS('Сентябрь 2024'!$K:$K,'Сентябрь 2024'!$E:$E,$A:$A),"-") -> 3.86 | C11: =IFERROR(AVERAGEIFS('Октябрь 2024'!$K:$K,'Октябрь 2024'!$E:$E,$A:$A),"-") -> - | D11: =IFERROR(AVERAGEIFS('Ноябрь 2024'!$K:$K,'Ноябрь 2024'!$E:$E,$A:$A),"-") -> 3.7216667 | E11: =IFERROR(AVERAGEIFS('Декабрь 2024'!$K:$K,'Декабрь 2024'!$E:$E,$A:$A),"-") -> 3.598 | F11: =IFERROR(AVERAGEIFS('Январь 2025'!$K:$K,'Январь 2025'!$E:$E,$A:$A),"-") -> - | G11: =IFERROR(AVERAGEIFS('Февраль 2025 '!K:K,'Февраль 2025 '!E:E,A:A),"-") -> 3.0633333 | H11: =IFERROR(AVERAGEIFS('Март 2025'!$K:$K,'Март 2025'!$E:$E,$A:$A),"-") -> - | I11: =IFERROR(AVERAGEIFS('Апрель 2025'!$K:$K,'Апрель 2025'!$E:$E,$A:$A),"-") -> 2.85 | J11: =IFERROR(AVERAGEIFS('Май 2025'!$K:$K,'Май 2025'!$E:$E,$A:$A),"-") -> - | K11: =IFERROR(AVERAGEIFS('Июнь 2025'!$K:$K,'Июнь 2025'!$E:$E,$A:$A),"-") -> 3.7566667 | L11: =IFERROR(AVERAGEIFS('Июль 2025'!$K:$K,'Июль 2025'!$E:$E,$A:$A),"-") -> 2.62 | M11: =IFERROR(AVERAGEIFS('Август 2025'!$K:$K,'Август 2025'!$E:$E,$A:$A),"-") -> 2.6128571 | N11: =IFERROR(AVERAGEIFS('Сентябрь 2025'!$K:$K,'Сентябрь 2025'!$E:$E,$A:$A),"-") -> 3.0866667 | O11: =IFERROR(AVERAGEIFS('Октябрь 2025'!$K:$K,'Октябрь 2025'!$E:$E,$A:$A),"-") -> 3.0075 | P11: =IFERROR(AVERAGEIFS('Ноябрь 2025'!$K:$K,'Ноябрь 2025'!$E:$E,$A:$A),"-") -> 2.8933333 | Q11: =IFERROR(AVERAGEIFS('Декабрь 2025'!$K:$K,'Декабрь 2025'!$E:$E,$A:$A),"-") -> 3.2975 | R11: =IFERROR(AVERAGEIFS('Январь 2026'!$K:$K,'Январь 2026'!$E:$E,$A:$A),"-") -> 3.7175 | S11: =IFERROR(AVERAGEIFS('Февраль 2026'!$K:$K,'Февраль 2026'!$E:$E,$A:$A),"-") -> 2.3172414 | T11: =IFERROR(AVERAGEIFS('Март 2026'!$K:$K,'Март 2026'!$E:$E,$A:$A),"-") -> 3.1984615 | U11: =IFERROR(AVERAGEIFS('Апрель 2026'!$K:$K,'Апрель 2026'!$E:$E,$A:$A),"-") -> 2.4441667 | V11: =IFERROR(AVERAGEIFS('Май 2026'!$K:$K,'Май 2026'!$E:$E,$A:$A),"-") -> 2.466129 | W11: =IFERROR(AVERAGEIFS('Июнь 2026'!$K:$K,'Июнь 2026'!$E:$E,$A:$A),"-") -> - | X11: =IFERROR(AVERAGEIFS('Июль 2026'!$K:$K,'Июль 2026'!$E:$E,$A:$A),"-") -> -
A12: Отвердитель Starkbond 747С ведро 5 кг | B12: =IFERROR(AVERAGEIFS('Сентябрь 2024'!$K:$K,'Сентябрь 2024'!$E:$E,$A:$A),"-") -> - | C12: =IFERROR(AVERAGEIFS('Октябрь 2024'!$K:$K,'Октябрь 2024'!$E:$E,$A:$A),"-") -> - | D12: =IFERROR(AVERAGEIFS('Ноябрь 2024'!$K:$K,'Ноябрь 2024'!$E:$E,$A:$A),"-") -> - | E12: =IFERROR(AVERAGEIFS('Декабрь 2024'!$K:$K,'Декабрь 2024'!$E:$E,$A:$A),"-") -> - | F12: =IFERROR(AVERAGEIFS('Январь 2025'!$K:$K,'Январь 2025'!$E:$E,$A:$A),"-") -> - | G12: =IFERROR(AVERAGEIFS('Февраль 2025 '!K:K,'Февраль 2025 '!E:E,A:A),"-") -> - | H12: =IFERROR(AVERAGEIFS('Март 2025'!$K:$K,'Март 2025'!$E:$E,$A:$A),"-") -> 3.17 | I12: =IFERROR(AVERAGEIFS('Апрель 2025'!$K:$K,'Апрель 2025'!$E:$E,$A:$A),"-") -> - | J12: =IFERROR(AVERAGEIFS('Май 2025'!$K:$K,'Май 2025'!$E:$E,$A:$A),"-") -> - | K12: =IFERROR(AVERAGEIFS('Июнь 2025'!$K:$K,'Июнь 2025'!$E:$E,$A:$A),"-") -> - | L12: =IFERROR(AVERAGEIFS('Июль 2025'!$K:$K,'Июль 2025'!$E:$E,$A:$A),"-") -> - | M12: =IFERROR(AVERAGEIFS('Август 2025'!$K:$K,'Август 2025'!$E:$E,$A:$A),"-") -> - | N12: =IFERROR(AVERAGEIFS('Сентябрь 2025'!$K:$K,'Сентябрь 2025'!$E:$E,$A:$A),"-") -> - | O12: =IFERROR(AVERAGEIFS('Октябрь 2025'!$K:$K,'Октябрь 2025'!$E:$E,$A:$A),"-") -> - | P12: =IFERROR(AVERAGEIFS('Ноябрь 2025'!$K:$K,'Ноябрь 2025'!$E:$E,$A:$A),"-") -> - | Q12: =IFERROR(AVERAGEIFS('Декабрь 2025'!$K:$K,'Декабрь 2025'!$E:$E,$A:$A),"-") -> - | R12: =IFERROR(AVERAGEIFS('Январь 2026'!$K:$K,'Январь 2026'!$E:$E,$A:$A),"-") -> - | S12: =IFERROR(AVERAGEIFS('Февраль 2026'!$K:$K,'Февраль 2026'!$E:$E,$A:$A),"-") -> - | T12: =IFERROR(AVERAGEIFS('Март 2026'!$K:$K,'Март 2026'!$E:$E,$A:$A),"-") -> - | U12: =IFERROR(AVERAGEIFS('Апрель 2026'!$K:$K,'Апрель 2026'!$E:$E,$A:$A),"-") -> - | V12: =IFERROR(AVERAGEIFS('Май 2026'!$K:$K,'Май 2026'!$E:$E,$A:$A),"-") -> - | W12: =IFERROR(AVERAGEIFS('Июнь 2026'!$K:$K,'Июнь 2026'!$E:$E,$A:$A),"-") -> - | X12: =IFERROR(AVERAGEIFS('Июль 2026'!$K:$K,'Июль 2026'!$E:$E,$A:$A),"-") -> -
A13: Клей Starkbond 2014 бочка 225кг | B13: =IFERROR(AVERAGEIFS('Сентябрь 2024'!$K:$K,'Сентябрь 2024'!$E:$E,$A:$A),"-") -> 3.2353333 | C13: =IFERROR(AVERAGEIFS('Октябрь 2024'!$K:$K,'Октябрь 2024'!$E:$E,$A:$A),"-") -> 3.3494118 | D13: =IFERROR(AVERAGEIFS('Ноябрь 2024'!$K:$K,'Ноябрь 2024'!$E:$E,$A:$A),"-") -> 3.1477778 | E13: =IFERROR(AVERAGEIFS('Декабрь 2024'!$K:$K,'Декабрь 2024'!$E:$E,$A:$A),"-") -> 2.76 | F13: =IFERROR(AVERAGEIFS('Январь 2025'!$K:$K,'Январь 2025'!$E:$E,$A:$A),"-") -> 3.18 | G13: =IFERROR(AVERAGEIFS('Февраль 2025 '!K:K,'Февраль 2025 '!E:E,A:A),"-") -> 3.3223077 | H13: =IFERROR(AVERAGEIFS('Март 2025'!$K:$K,'Март 2025'!$E:$E,$A:$A),"-") -> 2.50875 | I13: =IFERROR(AVERAGEIFS('Апрель 2025'!$K:$K,'Апрель 2025'!$E:$E,$A:$A),"-") -> 2.1714286 | J13: =IFERROR(AVERAGEIFS('Май 2025'!$K:$K,'Май 2025'!$E:$E,$A:$A),"-") -> 2.6966667 | K13: =IFERROR(AVERAGEIFS('Июнь 2025'!$K:$K,'Июнь 2025'!$E:$E,$A:$A),"-") -> - | L13: =IFERROR(AVERAGEIFS('Июль 2025'!$K:$K,'Июль 2025'!$E:$E,$A:$A),"-") -> 2.5082353 | M13: =IFERROR(AVERAGEIFS('Август 2025'!$K:$K,'Август 2025'!$E:$E,$A:$A),"-") -> 2.4675 | N13: =IFERROR(AVERAGEIFS('Сентябрь 2025'!$K:$K,'Сентябрь 2025'!$E:$E,$A:$A),"-") -> 3.1866667 | O13: =IFERROR(AVERAGEIFS('Октябрь 2025'!$K:$K,'Октябрь 2025'!$E:$E,$A:$A),"-") -> 3.1 | P13: =IFERROR(AVERAGEIFS('Ноябрь 2025'!$K:$K,'Ноябрь 2025'!$E:$E,$A:$A),"-") -> 3.075 | Q13: =IFERROR(AVERAGEIFS('Декабрь 2025'!$K:$K,'Декабрь 2025'!$E:$E,$A:$A),"-") -> - | R13: =IFERROR(AVERAGEIFS('Январь 2026'!$K:$K,'Январь 2026'!$E:$E,$A:$A),"-") -> - | S13: =IFERROR(AVERAGEIFS('Февраль 2026'!$K:$K,'Февраль 2026'!$E:$E,$A:$A),"-") -> 3.29 | T13: =IFERROR(AVERAGEIFS('Март 2026'!$K:$K,'Март 2026'!$E:$E,$A:$A),"-") -> - | U13: =IFERROR(AVERAGEIFS('Апрель 2026'!$K:$K,'Апрель 2026'!$E:$E,$A:$A),"-") -> 1.9558333 | V13: =IFERROR(AVERAGEIFS('Май 2026'!$K:$K,'Май 2026'!$E:$E,$A:$A),"-") -> 2.092 | W13: =IFERROR(AVERAGEIFS('Июнь 2026'!$K:$K,'Июнь 2026'!$E:$E,$A:$A),"-") -> - | X13: =IFERROR(AVERAGEIFS('Июль 2026'!$K:$K,'Июль 2026'!$E:$E,$A:$A),"-") -> -
... A85: Sancos Pro Safety 145 канистра 11,59 кг | B85: =IFERROR(AVERAGEIFS('Сентябрь 2024'!$K:$K,'Сентябрь 2024'!$E:$E,$A:$A),"-") -> - | C85: =IFERROR(AVERAGEIFS('Октябрь 2024'!$K:$K,'Октябрь 2024'!$E:$E,$A:$A),"-") -> - | D85: =IFERROR(AVERAGEIFS('Ноябрь 2024'!$K:$K,'Ноябрь 2024'!$E:$E,$A:$A),"-") -> - | E85: =IFERROR(AVERAGEIFS('Декабрь 2024'!$K:$K,'Декабрь 2024'!$E:$E,$A:$A),"-") -> - | F85: =IFERROR(AVERAGEIFS('Январь 2025'!$K:$K,'Январь 2025'!$E:$E,$A:$A),"-") -> - | G85: =IFERROR(AVERAGEIFS('Февраль 2025 '!K:K,'Февраль 2025 '!E:E,A:A),"-") -> - | H85: =IFERROR(AVERAGEIFS('Март 2025'!$K:$K,'Март 2025'!$E:$E,$A:$A),"-") -> - | I85: =IFERROR(AVERAGEIFS('Апрель 2025'!$K:$K,'Апрель 2025'!$E:$E,$A:$A),"-") -> - | J85: =IFERROR(AVERAGEIFS('Май 2025'!$K:$K,'Май 2025'!$E:$E,$A:$A),"-") -> - | K85: =IFERROR(AVERAGEIFS('Июнь 2025'!$K:$K,'Июнь 2025'!$E:$E,$A:$A),"-") -> - | L85: =IFERROR(AVERAGEIFS('Июль 2025'!$K:$K,'Июль 2025'!$E:$E,$A:$A),"-") -> - | M85: =IFERROR(AVERAGEIFS('Август 2025'!$K:$K,'Август 2025'!$E:$E,$A:$A),"-") -> - | N85: =IFERROR(AVERAGEIFS('Сентябрь 2025'!$K:$K,'Сентябрь 2025'!$E:$E,$A:$A),"-") -> 1.48 | O85: =IFERROR(AVERAGEIFS('Октябрь 2025'!$K:$K,'Октябрь 2025'!$E:$E,$A:$A),"-") -> - | P85: =IFERROR(AVERAGEIFS('Ноябрь 2025'!$K:$K,'Ноябрь 2025'!$E:$E,$A:$A),"-") -> - | Q85: =IFERROR(AVERAGEIFS('Декабрь 2025'!$K:$K,'Декабрь 2025'!$E:$E,$A:$A),"-") -> - | R85: =IFERROR(AVERAGEIFS('Январь 2026'!$K:$K,'Январь 2026'!$E:$E,$A:$A),"-") -> - | S85: =IFERROR(AVERAGEIFS('Февраль 2026'!$K:$K,'Февраль 2026'!$E:$E,$A:$A),"-") -> - | T85: =IFERROR(AVERAGEIFS('Март 2026'!$K:$K,'Март 2026'!$E:$E,$A:$A),"-") -> 1.98 | U85: =IFERROR(AVERAGEIFS('Апрель 2026'!$K:$K,'Апрель 2026'!$E:$E,$A:$A),"-") -> - | V85: =IFERROR(AVERAGEIFS('Май 2026'!$K:$K,'Май 2026'!$E:$E,$A:$A),"-") -> - | W85: =IFERROR(AVERAGEIFS('Июнь 2026'!$K:$K,'Июнь 2026'!$E:$E,$A:$A),"-") -> - | X85: =IFERROR(AVERAGEIFS('Июль 2026'!$K:$K,'Июль 2026'!$E:$E,$A:$A),"-") -> -
B86: =IFERROR(AVERAGEIFS('Сентябрь 2024'!$K:$K,'Сентябрь 2024'!$E:$E,$A:$A),"-") -> - | C86: =IFERROR(AVERAGEIFS('Октябрь 2024'!$K:$K,'Октябрь 2024'!$E:$E,$A:$A),"-") -> - | D86: =IFERROR(AVERAGEIFS('Ноябрь 2024'!$K:$K,'Ноябрь 2024'!$E:$E,$A:$A),"-") -> - | E86: =IFERROR(AVERAGEIFS('Декабрь 2024'!$K:$K,'Декабрь 2024'!$E:$E,$A:$A),"-") -> - | F86: =IFERROR(AVERAGEIFS('Январь 2025'!$K:$K,'Январь 2025'!$E:$E,$A:$A),"-") -> - | G86: =IFERROR(AVERAGEIFS('Февраль 2025 '!K:K,'Февраль 2025 '!E:E,A:A),"-") -> - | H86: =IFERROR(AVERAGEIFS('Март 2025'!$K:$K,'Март 2025'!$E:$E,$A:$A),"-") -> - | I86: =IFERROR(AVERAGEIFS('Апрель 2025'!$K:$K,'Апрель 2025'!$E:$E,$A:$A),"-") -> - | J86: =IFERROR(AVERAGEIFS('Май 2025'!$K:$K,'Май 2025'!$E:$E,$A:$A),"-") -> - | K86: =IFERROR(AVERAGEIFS('Июнь 2025'!$K:$K,'Июнь 2025'!$E:$E,$A:$A),"-") -> - | L86: =IFERROR(AVERAGEIFS('Июль 2025'!$K:$K,'Июль 2025'!$E:$E,$A:$A),"-") -> - | M86: =IFERROR(AVERAGEIFS('Август 2025'!$K:$K,'Август 2025'!$E:$E,$A:$A),"-") -> - | N86: =IFERROR(AVERAGEIFS('Сентябрь 2025'!$K:$K,'Сентябрь 2025'!$E:$E,$A:$A),"-") -> - | O86: =IFERROR(AVERAGEIFS('Октябрь 2025'!$K:$K,'Октябрь 2025'!$E:$E,$A:$A),"-") -> - | P86: =IFERROR(AVERAGEIFS('Ноябрь 2025'!$K:$K,'Ноябрь 2025'!$E:$E,$A:$A),"-") -> - | Q86: =IFERROR(AVERAGEIFS('Декабрь 2025'!$K:$K,'Декабрь 2025'!$E:$E,$A:$A),"-") -> - | R86: =IFERROR(AVERAGEIFS('Январь 2026'!$K:$K,'Январь 2026'!$E:$E,$A:$A),"-") -> - | S86: =IFERROR(AVERAGEIFS('Февраль 2026'!$K:$K,'Февраль 2026'!$E:$E,$A:$A),"-") -> - | T86: =IFERROR(AVERAGEIFS('Март 2026'!$K:$K,'Март 2026'!$E:$E,$A:$A),"-") -> - | U86: =IFERROR(AVERAGEIFS('Апрель 2026'!$K:$K,'Апрель 2026'!$E:$E,$A:$A),"-") -> - | V86: =IFERROR(AVERAGEIFS('Май 2026'!$K:$K,'Май 2026'!$E:$E,$A:$A),"-") -> - | W86: =IFERROR(AVERAGEIFS('Июнь 2026'!$K:$K,'Июнь 2026'!$E:$E,$A:$A),"-") -> - | X86: =IFERROR(AVERAGEIFS('Июль 2026'!$K:$K,'Июль 2026'!$E:$E,$A:$A),"-") -> -
B87: =IFERROR(AVERAGEIFS('Сентябрь 2024'!$K:$K,'Сентябрь 2024'!$E:$E,$A:$A),"-") -> - | C87: =IFERROR(AVERAGEIFS('Октябрь 2024'!$K:$K,'Октябрь 2024'!$E:$E,$A:$A),"-") -> - | D87: =IFERROR(AVERAGEIFS('Ноябрь 2024'!$K:$K,'Ноябрь 2024'!$E:$E,$A:$A),"-") -> - | E87: =IFERROR(AVERAGEIFS('Декабрь 2024'!$K:$K,'Декабрь 2024'!$E:$E,$A:$A),"-") -> - | F87: =IFERROR(AVERAGEIFS('Январь 2025'!$K:$K,'Январь 2025'!$E:$E,$A:$A),"-") -> - | G87: =IFERROR(AVERAGEIFS('Февраль 2025 '!K:K,'Февраль 2025 '!E:E,A:A),"-") -> - | H87: =IFERROR(AVERAGEIFS('Март 2025'!$K:$K,'Март 2025'!$E:$E,$A:$A),"-") -> - | I87: =IFERROR(AVERAGEIFS('Апрель 2025'!$K:$K,'Апрель 2025'!$E:$E,$A:$A),"-") -> - | J87: =IFERROR(AVERAGEIFS('Май 2025'!$K:$K,'Май 2025'!$E:$E,$A:$A),"-") -> - | K87: =IFERROR(AVERAGEIFS('Июнь 2025'!$K:$K,'Июнь 2025'!$E:$E,$A:$A),"-") -> - | L87: =IFERROR(AVERAGEIFS('Июль 2025'!$K:$K,'Июль 2025'!$E:$E,$A:$A),"-") -> - | M87: =IFERROR(AVERAGEIFS('Август 2025'!$K:$K,'Август 2025'!$E:$E,$A:$A),"-") -> - | N87: =IFERROR(AVERAGEIFS('Сентябрь 2025'!$K:$K,'Сентябрь 2025'!$E:$E,$A:$A),"-") -> - | O87: =IFERROR(AVERAGEIFS('Октябрь 2025'!$K:$K,'Октябрь 2025'!$E:$E,$A:$A),"-") -> - | P87: =IFERROR(AVERAGEIFS('Ноябрь 2025'!$K:$K,'Ноябрь 2025'!$E:$E,$A:$A),"-") -> - | Q87: =IFERROR(AVERAGEIFS('Декабрь 2025'!$K:$K,'Декабрь 2025'!$E:$E,$A:$A),"-") -> - | R87: =IFERROR(AVERAGEIFS('Январь 2026'!$K:$K,'Январь 2026'!$E:$E,$A:$A),"-") -> - | S87: =IFERROR(AVERAGEIFS('Февраль 2026'!$K:$K,'Февраль 2026'!$E:$E,$A:$A),"-") -> - | T87: =IFERROR(AVERAGEIFS('Март 2026'!$K:$K,'Март 2026'!$E:$E,$A:$A),"-") -> - | U87: =IFERROR(AVERAGEIFS('Апрель 2026'!$K:$K,'Апрель 2026'!$E:$E,$A:$A),"-") -> - | V87: =IFERROR(AVERAGEIFS('Май 2026'!$K:$K,'Май 2026'!$E:$E,$A:$A),"-") -> - | W87: =IFERROR(AVERAGEIFS('Июнь 2026'!$K:$K,'Июнь 2026'!$E:$E,$A:$A),"-") -> - | X87: =IFERROR(AVERAGEIFS('Июль 2026'!$K:$K,'Июль 2026'!$E:$E,$A:$A),"-") -> -
B88: =IFERROR(AVERAGEIFS('Сентябрь 2024'!$K:$K,'Сентябрь 2024'!$E:$E,$A:$A),"-") -> - | C88: =IFERROR(AVERAGEIFS('Октябрь 2024'!$K:$K,'Октябрь 2024'!$E:$E,$A:$A),"-") -> - | D88: =IFERROR(AVERAGEIFS('Ноябрь 2024'!$K:$K,'Ноябрь 2024'!$E:$E,$A:$A),"-") -> - | E88: =IFERROR(AVERAGEIFS('Декабрь 2024'!$K:$K,'Декабрь 2024'!$E:$E,$A:$A),"-") -> - | F88: =IFERROR(AVERAGEIFS('Январь 2025'!$K:$K,'Январь 2025'!$E:$E,$A:$A),"-") -> - | G88: =IFERROR(AVERAGEIFS('Февраль 2025 '!K:K,'Февраль 2025 '!E:E,A:A),"-") -> - | H88: =IFERROR(AVERAGEIFS('Март 2025'!$K:$K,'Март 2025'!$E:$E,$A:$A),"-") -> - | I88: =IFERROR(AVERAGEIFS('Апрель 2025'!$K:$K,'Апрель 2025'!$E:$E,$A:$A),"-") -> - | J88: =IFERROR(AVERAGEIFS('Май 2025'!$K:$K,'Май 2025'!$E:$E,$A:$A),"-") -> - | K88: =IFERROR(AVERAGEIFS('Июнь 2025'!$K:$K,'Июнь 2025'!$E:$E,$A:$A),"-") -> - | L88: =IFERROR(AVERAGEIFS('Июль 2025'!$K:$K,'Июль 2025'!$E:$E,$A:$A),"-") -> - | M88: =IFERROR(AVERAGEIFS('Август 2025'!$K:$K,'Август 2025'!$E:$E,$A:$A),"-") -> - | N88: =IFERROR(AVERAGEIFS('Сентябрь 2025'!$K:$K,'Сентябрь 2025'!$E:$E,$A:$A),"-") -> - | O88: =IFERROR(AVERAGEIFS('Октябрь 2025'!$K:$K,'Октябрь 2025'!$E:$E,$A:$A),"-") -> - | P88: =IFERROR(AVERAGEIFS('Ноябрь 2025'!$K:$K,'Ноябрь 2025'!$E:$E,$A:$A),"-") -> - | Q88: =IFERROR(AVERAGEIFS('Декабрь 2025'!$K:$K,'Декабрь 2025'!$E:$E,$A:$A),"-") -> - | R88: =IFERROR(AVERAGEIFS('Январь 2026'!$K:$K,'Январь 2026'!$E:$E,$A:$A),"-") -> - | S88: =IFERROR(AVERAGEIFS('Февраль 2026'!$K:$K,'Февраль 2026'!$E:$E,$A:$A),"-") -> - | T88: =IFERROR(AVERAGEIFS('Март 2026'!$K:$K,'Март 2026'!$E:$E,$A:$A),"-") -> - | U88: =IFERROR(AVERAGEIFS('Апрель 2026'!$K:$K,'Апрель 2026'!$E:$E,$A:$A),"-") -> - | V88: =IFERROR(AVERAGEIFS('Май 2026'!$K:$K,'Май 2026'!$E:$E,$A:$A),"-") -> - | W88: =IFERROR(AVERAGEIFS('Июнь 2026'!$K:$K,'Июнь 2026'!$E:$E,$A:$A),"-") -> - | X88: =IFERROR(AVERAGEIFS('Июль 2026'!$K:$K,'Июль 2026'!$E:$E,$A:$A),"-") -> -
B89: =IFERROR(AVERAGEIFS('Сентябрь 2024'!$K:$K,'Сентябрь 2024'!$E:$E,$A:$A),"-") -> - | C89: =IFERROR(AVERAGEIFS('Октябрь 2024'!$K:$K,'Октябрь 2024'!$E:$E,$A:$A),"-") -> - | D89: =IFERROR(AVERAGEIFS('Ноябрь 2024'!$K:$K,'Ноябрь 2024'!$E:$E,$A:$A),"-") -> - | E89: =IFERROR(AVERAGEIFS('Декабрь 2024'!$K:$K,'Декабрь 2024'!$E:$E,$A:$A),"-") -> - | F89: =IFERROR(AVERAGEIFS('Январь 2025'!$K:$K,'Январь 2025'!$E:$E,$A:$A),"-") -> - | G89: =IFERROR(AVERAGEIFS('Февраль 2025 '!K:K,'Февраль 2025 '!E:E,A:A),"-") -> - | H89: =IFERROR(AVERAGEIFS('Март 2025'!$K:$K,'Март 2025'!$E:$E,$A:$A),"-") -> - | I89: =IFERROR(AVERAGEIFS('Апрель 2025'!$K:$K,'Апрель 2025'!$E:$E,$A:$A),"-") -> - | J89: =IFERROR(AVERAGEIFS('Май 2025'!$K:$K,'Май 2025'!$E:$E,$A:$A),"-") -> - | K89: =IFERROR(AVERAGEIFS('Июнь 2025'!$K:$K,'Июнь 2025'!$E:$E,$A:$A),"-") -> - | L89: =IFERROR(AVERAGEIFS('Июль 2025'!$K:$K,'Июль 2025'!$E:$E,$A:$A),"-") -> - | M89: =IFERROR(AVERAGEIFS('Август 2025'!$K:$K,'Август 2025'!$E:$E,$A:$A),"-") -> - | N89: =IFERROR(AVERAGEIFS('Сентябрь 2025'!$K:$K,'Сентябрь 2025'!$E:$E,$A:$A),"-") -> - | O89: =IFERROR(AVERAGEIFS('Октябрь 2025'!$K:$K,'Октябрь 2025'!$E:$E,$A:$A),"-") -> - | P89: =IFERROR(AVERAGEIFS('Ноябрь 2025'!$K:$K,'Ноябрь 2025'!$E:$E,$A:$A),"-") -> - | Q89: =IFERROR(AVERAGEIFS('Декабрь 2025'!$K:$K,'Декабрь 2025'!$E:$E,$A:$A),"-") -> - | R89: =IFERROR(AVERAGEIFS('Январь 2026'!$K:$K,'Январь 2026'!$E:$E,$A:$A),"-") -> - | S89: =IFERROR(AVERAGEIFS('Февраль 2026'!$K:$K,'Февраль 2026'!$E:$E,$A:$A),"-") -> - | T89: =IFERROR(AVERAGEIFS('Март 2026'!$K:$K,'Март 2026'!$E:$E,$A:$A),"-") -> - | U89: =IFERROR(AVERAGEIFS('Апрель 2026'!$K:$K,'Апрель 2026'!$E:$E,$A:$A),"-") -> - | V89: =IFERROR(AVERAGEIFS('Май 2026'!$K:$K,'Май 2026'!$E:$E,$A:$A),"-") -> - | W89: =IFERROR(AVERAGEIFS('Июнь 2026'!$K:$K,'Июнь 2026'!$E:$E,$A:$A),"-") -> - | X89: =IFERROR(AVERAGEIFS('Июль 2026'!$K:$K,'Июль 2026'!$E:$E,$A:$A),"-") -> -
B90: =IFERROR(AVERAGEIFS('Сентябрь 2024'!$K:$K,'Сентябрь 2024'!$E:$E,$A:$A),"-") -> - | C90: =IFERROR(AVERAGEIFS('Октябрь 2024'!$K:$K,'Октябрь 2024'!$E:$E,$A:$A),"-") -> - | D90: =IFERROR(AVERAGEIFS('Ноябрь 2024'!$K:$K,'Ноябрь 2024'!$E:$E,$A:$A),"-") -> - | E90: =IFERROR(AVERAGEIFS('Декабрь 2024'!$K:$K,'Декабрь 2024'!$E:$E,$A:$A),"-") -> - | F90: =IFERROR(AVERAGEIFS('Январь 2025'!$K:$K,'Январь 2025'!$E:$E,$A:$A),"-") -> - | G90: =IFERROR(AVERAGEIFS('Февраль 2025 '!K:K,'Февраль 2025 '!E:E,A:A),"-") -> - | H90: =IFERROR(AVERAGEIFS('Март 2025'!$K:$K,'Март 2025'!$E:$E,$A:$A),"-") -> - | I90: =IFERROR(AVERAGEIFS('Апрель 2025'!$K:$K,'Апрель 2025'!$E:$E,$A:$A),"-") -> - | J90: =IFERROR(AVERAGEIFS('Май 2025'!$K:$K,'Май 2025'!$E:$E,$A:$A),"-") -> - | K90: =IFERROR(AVERAGEIFS('Июнь 2025'!$K:$K,'Июнь 2025'!$E:$E,$A:$A),"-") -> - | L90: =IFERROR(AVERAGEIFS('Июль 2025'!$K:$K,'Июль 2025'!$E:$E,$A:$A),"-") -> - | M90: =IFERROR(AVERAGEIFS('Август 2025'!$K:$K,'Август 2025'!$E:$E,$A:$A),"-") -> - | N90: =IFERROR(AVERAGEIFS('Сентябрь 2025'!$K:$K,'Сентябрь 2025'!$E:$E,$A:$A),"-") -> - | O90: =IFERROR(AVERAGEIFS('Октябрь 2025'!$K:$K,'Октябрь 2025'!$E:$E,$A:$A),"-") -> - | P90: =IFERROR(AVERAGEIFS('Ноябрь 2025'!$K:$K,'Ноябрь 2025'!$E:$E,$A:$A),"-") -> - | Q90: =IFERROR(AVERAGEIFS('Декабрь 2025'!$K:$K,'Декабрь 2025'!$E:$E,$A:$A),"-") -> - | R90: =IFERROR(AVERAGEIFS('Январь 2026'!$K:$K,'Январь 2026'!$E:$E,$A:$A),"-") -> - | S90: =IFERROR(AVERAGEIFS('Февраль 2026'!$K:$K,'Февраль 2026'!$E:$E,$A:$A),"-") -> - | T90: =IFERROR(AVERAGEIFS('Март 2026'!$K:$K,'Март 2026'!$E:$E,$A:$A),"-") -> - | U90: =IFERROR(AVERAGEIFS('Апрель 2026'!$K:$K,'Апрель 2026'!$E:$E,$A:$A),"-") -> - | V90: =IFERROR(AVERAGEIFS('Май 2026'!$K:$K,'Май 2026'!$E:$E,$A:$A),"-") -> - | W90: =IFERROR(AVERAGEIFS('Июнь 2026'!$K:$K,'Июнь 2026'!$E:$E,$A:$A),"-") -> - | X90: =IFERROR(AVERAGEIFS('Июль 2026'!$K:$K,'Июль 2026'!$E:$E,$A:$A),"-") -> -
B91: =IFERROR(AVERAGEIFS('Сентябрь 2024'!$K:$K,'Сентябрь 2024'!$E:$E,$A:$A),"-") -> - | C91: =IFERROR(AVERAGEIFS('Октябрь 2024'!$K:$K,'Октябрь 2024'!$E:$E,$A:$A),"-") -> - | D91: =IFERROR(AVERAGEIFS('Ноябрь 2024'!$K:$K,'Ноябрь 2024'!$E:$E,$A:$A),"-") -> - | E91: =IFERROR(AVERAGEIFS('Декабрь 2024'!$K:$K,'Декабрь 2024'!$E:$E,$A:$A),"-") -> - | F91: =IFERROR(AVERAGEIFS('Январь 2025'!$K:$K,'Январь 2025'!$E:$E,$A:$A),"-") -> - | G91: =IFERROR(AVERAGEIFS('Февраль 2025 '!K:K,'Февраль 2025 '!E:E,A:A),"-") -> - | H91: =IFERROR(AVERAGEIFS('Март 2025'!$K:$K,'Март 2025'!$E:$E,$A:$A),"-") -> - | I91: =IFERROR(AVERAGEIFS('Апрель 2025'!$K:$K,'Апрель 2025'!$E:$E,$A:$A),"-") -> - | J91: =IFERROR(AVERAGEIFS('Май 2025'!$K:$K,'Май 2025'!$E:$E,$A:$A),"-") -> - | K91: =IFERROR(AVERAGEIFS('Июнь 2025'!$K:$K,'Июнь 2025'!$E:$E,$A:$A),"-") -> - | L91: =IFERROR(AVERAGEIFS('Июль 2025'!$K:$K,'Июль 2025'!$E:$E,$A:$A),"-") -> - | M91: =IFERROR(AVERAGEIFS('Август 2025'!$K:$K,'Август 2025'!$E:$E,$A:$A),"-") -> - | N91: =IFERROR(AVERAGEIFS('Сентябрь 2025'!$K:$K,'Сентябрь 2025'!$E:$E,$A:$A),"-") -> - | O91: =IFERROR(AVERAGEIFS('Октябрь 2025'!$K:$K,'Октябрь 2025'!$E:$E,$A:$A),"-") -> - | P91: =IFERROR(AVERAGEIFS('Ноябрь 2025'!$K:$K,'Ноябрь 2025'!$E:$E,$A:$A),"-") -> - | Q91: =IFERROR(AVERAGEIFS('Декабрь 2025'!$K:$K,'Декабрь 2025'!$E:$E,$A:$A),"-") -> - | R91: =IFERROR(AVERAGEIFS('Январь 2026'!$K:$K,'Январь 2026'!$E:$E,$A:$A),"-") -> - | S91: =IFERROR(AVERAGEIFS('Февраль 2026'!$K:$K,'Февраль 2026'!$E:$E,$A:$A),"-") -> - | T91: =IFERROR(AVERAGEIFS('Март 2026'!$K:$K,'Март 2026'!$E:$E,$A:$A),"-") -> - | U91: =IFERROR(AVERAGEIFS('Апрель 2026'!$K:$K,'Апрель 2026'!$E:$E,$A:$A),"-") -> - | V91: =IFERROR(AVERAGEIFS('Май 2026'!$K:$K,'Май 2026'!$E:$E,$A:$A),"-") -> - | W91: =IFERROR(AVERAGEIFS('Июнь 2026'!$K:$K,'Июнь 2026'!$E:$E,$A:$A),"-") -> - | X91: =IFERROR(AVERAGEIFS('Июль 2026'!$K:$K,'Июль 2026'!$E:$E,$A:$A),"-") -> -
B92: =IFERROR(AVERAGEIFS('Сентябрь 2024'!$K:$K,'Сентябрь 2024'!$E:$E,$A:$A),"-") -> - | C92: =IFERROR(AVERAGEIFS('Октябрь 2024'!$K:$K,'Октябрь 2024'!$E:$E,$A:$A),"-") -> - | D92: =IFERROR(AVERAGEIFS('Ноябрь 2024'!$K:$K,'Ноябрь 2024'!$E:$E,$A:$A),"-") -> - | E92: =IFERROR(AVERAGEIFS('Декабрь 2024'!$K:$K,'Декабрь 2024'!$E:$E,$A:$A),"-") -> - | F92: =IFERROR(AVERAGEIFS('Январь 2025'!$K:$K,'Январь 2025'!$E:$E,$A:$A),"-") -> - | G92: =IFERROR(AVERAGEIFS('Февраль 2025 '!K:K,'Февраль 2025 '!E:E,A:A),"-") -> - | H92: =IFERROR(AVERAGEIFS('Март 2025'!$K:$K,'Март 2025'!$E:$E,$A:$A),"-") -> - | I92: =IFERROR(AVERAGEIFS('Апрель 2025'!$K:$K,'Апрель 2025'!$E:$E,$A:$A),"-") -> - | J92: =IFERROR(AVERAGEIFS('Май 2025'!$K:$K,'Май 2025'!$E:$E,$A:$A),"-") -> - | K92: =IFERROR(AVERAGEIFS('Июнь 2025'!$K:$K,'Июнь 2025'!$E:$E,$A:$A),"-") -> - | L92: =IFERROR(AVERAGEIFS('Июль 2025'!$K:$K,'Июль 2025'!$E:$E,$A:$A),"-") -> - | M92: =IFERROR(AVERAGEIFS('Август 2025'!$K:$K,'Август 2025'!$E:$E,$A:$A),"-") -> - | N92: =IFERROR(AVERAGEIFS('Сентябрь 2025'!$K:$K,'Сентябрь 2025'!$E:$E,$A:$A),"-") -> - | O92: =IFERROR(AVERAGEIFS('Октябрь 2025'!$K:$K,'Октябрь 2025'!$E:$E,$A:$A),"-") -> - | P92: =IFERROR(AVERAGEIFS('Ноябрь 2025'!$K:$K,'Ноябрь 2025'!$E:$E,$A:$A),"-") -> - | Q92: =IFERROR(AVERAGEIFS('Декабрь 2025'!$K:$K,'Декабрь 2025'!$E:$E,$A:$A),"-") -> - | R92: =IFERROR(AVERAGEIFS('Январь 2026'!$K:$K,'Январь 2026'!$E:$E,$A:$A),"-") -> - | S92: =IFERROR(AVERAGEIFS('Февраль 2026'!$K:$K,'Февраль 2026'!$E:$E,$A:$A),"-") -> - | T92: =IFERROR(AVERAGEIFS('Март 2026'!$K:$K,'Март 2026'!$E:$E,$A:$A),"-") -> - | U92: =IFERROR(AVERAGEIFS('Апрель 2026'!$K:$K,'Апрель 2026'!$E:$E,$A:$A),"-") -> - | V92: =IFERROR(AVERAGEIFS('Май 2026'!$K:$K,'Май 2026'!$E:$E,$A:$A),"-") -> - | W92: =IFERROR(AVERAGEIFS('Июнь 2026'!$K:$K,'Июнь 2026'!$E:$E,$A:$A),"-") -> - | X92: =IFERROR(AVERAGEIFS('Июль 2026'!$K:$K,'Июль 2026'!$E:$E,$A:$A),"-") -> -
B93: =IFERROR(AVERAGEIFS('Сентябрь 2024'!$K:$K,'Сентябрь 2024'!$E:$E,$A:$A),"-") -> - | C93: =IFERROR(AVERAGEIFS('Октябрь 2024'!$K:$K,'Октябрь 2024'!$E:$E,$A:$A),"-") -> - | D93: =IFERROR(AVERAGEIFS('Ноябрь 2024'!$K:$K,'Ноябрь 2024'!$E:$E,$A:$A),"-") -> - | E93: =IFERROR(AVERAGEIFS('Декабрь 2024'!$K:$K,'Декабрь 2024'!$E:$E,$A:$A),"-") -> - | F93: =IFERROR(AVERAGEIFS('Январь 2025'!$K:$K,'Январь 2025'!$E:$E,$A:$A),"-") -> - | G93: =IFERROR(AVERAGEIFS('Февраль 2025 '!K:K,'Февраль 2025 '!E:E,A:A),"-") -> - | H93: =IFERROR(AVERAGEIFS('Март 2025'!$K:$K,'Март 2025'!$E:$E,$A:$A),"-") -> - | I93: =IFERROR(AVERAGEIFS('Апрель 2025'!$K:$K,'Апрель 2025'!$E:$E,$A:$A),"-") -> - | J93: =IFERROR(AVERAGEIFS('Май 2025'!$K:$K,'Май 2025'!$E:$E,$A:$A),"-") -> - | K93: =IFERROR(AVERAGEIFS('Июнь 2025'!$K:$K,'Июнь 2025'!$E:$E,$A:$A),"-") -> - | L93: =IFERROR(AVERAGEIFS('Июль 2025'!$K:$K,'Июль 2025'!$E:$E,$A:$A),"-") -> - | M93: =IFERROR(AVERAGEIFS('Август 2025'!$K:$K,'Август 2025'!$E:$E,$A:$A),"-") -> - | N93: =IFERROR(AVERAGEIFS('Сентябрь 2025'!$K:$K,'Сентябрь 2025'!$E:$E,$A:$A),"-") -> - | O93: =IFERROR(AVERAGEIFS('Октябрь 2025'!$K:$K,'Октябрь 2025'!$E:$E,$A:$A),"-") -> - | P93: =IFERROR(AVERAGEIFS('Ноябрь 2025'!$K:$K,'Ноябрь 2025'!$E:$E,$A:$A),"-") -> - | Q93: =IFERROR(AVERAGEIFS('Декабрь 2025'!$K:$K,'Декабрь 2025'!$E:$E,$A:$A),"-") -> - | R93: =IFERROR(AVERAGEIFS('Январь 2026'!$K:$K,'Январь 2026'!$E:$E,$A:$A),"-") -> - | S93: =IFERROR(AVERAGEIFS('Февраль 2026'!$K:$K,'Февраль 2026'!$E:$E,$A:$A),"-") -> - | T93: =IFERROR(AVERAGEIFS('Март 2026'!$K:$K,'Март 2026'!$E:$E,$A:$A),"-") -> - | U93: =IFERROR(AVERAGEIFS('Апрель 2026'!$K:$K,'Апрель 2026'!$E:$E,$A:$A),"-") -> - | V93: =IFERROR(AVERAGEIFS('Май 2026'!$K:$K,'Май 2026'!$E:$E,$A:$A),"-") -> - | W93: =IFERROR(AVERAGEIFS('Июнь 2026'!$K:$K,'Июнь 2026'!$E:$E,$A:$A),"-") -> - | X93: =IFERROR(AVERAGEIFS('Июль 2026'!$K:$K,'Июль 2026'!$E:$E,$A:$A),"-") -> -
B94: =IFERROR(AVERAGEIFS('Сентябрь 2024'!$K:$K,'Сентябрь 2024'!$E:$E,$A:$A),"-") -> - | C94: =IFERROR(AVERAGEIFS('Октябрь 2024'!$K:$K,'Октябрь 2024'!$E:$E,$A:$A),"-") -> - | D94: =IFERROR(AVERAGEIFS('Ноябрь 2024'!$K:$K,'Ноябрь 2024'!$E:$E,$A:$A),"-") -> - | E94: =IFERROR(AVERAGEIFS('Декабрь 2024'!$K:$K,'Декабрь 2024'!$E:$E,$A:$A),"-") -> - | F94: =IFERROR(AVERAGEIFS('Январь 2025'!$K:$K,'Январь 2025'!$E:$E,$A:$A),"-") -> - | G94: =IFERROR(AVERAGEIFS('Февраль 2025 '!K:K,'Февраль 2025 '!E:E,A:A),"-") -> - | H94: =IFERROR(AVERAGEIFS('Март 2025'!$K:$K,'Март 2025'!$E:$E,$A:$A),"-") -> - | I94: =IFERROR(AVERAGEIFS('Апрель 2025'!$K:$K,'Апрель 2025'!$E:$E,$A:$A),"-") -> - | J94: =IFERROR(AVERAGEIFS('Май 2025'!$K:$K,'Май 2025'!$E:$E,$A:$A),"-") -> - | K94: =IFERROR(AVERAGEIFS('Июнь 2025'!$K:$K,'Июнь 2025'!$E:$E,$A:$A),"-") -> - | L94: =IFERROR(AVERAGEIFS('Июль 2025'!$K:$K,'Июль 2025'!$E:$E,$A:$A),"-") -> - | M94: =IFERROR(AVERAGEIFS('Август 2025'!$K:$K,'Август 2025'!$E:$E,$A:$A),"-") -> - | N94: =IFERROR(AVERAGEIFS('Сентябрь 2025'!$K:$K,'Сентябрь 2025'!$E:$E,$A:$A),"-") -> - | O94: =IFERROR(AVERAGEIFS('Октябрь 2025'!$K:$K,'Октябрь 2025'!$E:$E,$A:$A),"-") -> - | P94: =IFERROR(AVERAGEIFS('Ноябрь 2025'!$K:$K,'Ноябрь 2025'!$E:$E,$A:$A),"-") -> - | Q94: =IFERROR(AVERAGEIFS('Декабрь 2025'!$K:$K,'Декабрь 2025'!$E:$E,$A:$A),"-") -> - | R94: =IFERROR(AVERAGEIFS('Январь 2026'!$K:$K,'Январь 2026'!$E:$E,$A:$A),"-") -> - | S94: =IFERROR(AVERAGEIFS('Февраль 2026'!$K:$K,'Февраль 2026'!$E:$E,$A:$A),"-") -> - | T94: =IFERROR(AVERAGEIFS('Март 2026'!$K:$K,'Март 2026'!$E:$E,$A:$A),"-") -> - | U94: =IFERROR(AVERAGEIFS('Апрель 2026'!$K:$K,'Апрель 2026'!$E:$E,$A:$A),"-") -> - | V94: =IFERROR(AVERAGEIFS('Май 2026'!$K:$K,'Май 2026'!$E:$E,$A:$A),"-") -> - | W94: =IFERROR(AVERAGEIFS('Июнь 2026'!$K:$K,'Июнь 2026'!$E:$E,$A:$A),"-") -> - | X94: =IFERROR(AVERAGEIFS('Июль 2026'!$K:$K,'Июль 2026'!$E:$E,$A:$A),"-") -> -
B95: =IFERROR(AVERAGEIFS('Сентябрь 2024'!$K:$K,'Сентябрь 2024'!$E:$E,$A:$A),"-") -> - | C95: =IFERROR(AVERAGEIFS('Октябрь 2024'!$K:$K,'Октябрь 2024'!$E:$E,$A:$A),"-") -> - | D95: =IFERROR(AVERAGEIFS('Ноябрь 2024'!$K:$K,'Ноябрь 2024'!$E:$E,$A:$A),"-") -> - | E95: =IFERROR(AVERAGEIFS('Декабрь 2024'!$K:$K,'Декабрь 2024'!$E:$E,$A:$A),"-") -> - | F95: =IFERROR(AVERAGEIFS('Январь 2025'!$K:$K,'Январь 2025'!$E:$E,$A:$A),"-") -> - | G95: =IFERROR(AVERAGEIFS('Февраль 2025 '!K:K,'Февраль 2025 '!E:E,A:A),"-") -> - | H95: =IFERROR(AVERAGEIFS('Март 2025'!$K:$K,'Март 2025'!$E:$E,$A:$A),"-") -> - | I95: =IFERROR(AVERAGEIFS('Апрель 2025'!$K:$K,'Апрель 2025'!$E:$E,$A:$A),"-") -> - | J95: =IFERROR(AVERAGEIFS('Май 2025'!$K:$K,'Май 2025'!$E:$E,$A:$A),"-") -> - | K95: =IFERROR(AVERAGEIFS('Июнь 2025'!$K:$K,'Июнь 2025'!$E:$E,$A:$A),"-") -> - | L95: =IFERROR(AVERAGEIFS('Июль 2025'!$K:$K,'Июль 2025'!$E:$E,$A:$A),"-") -> - | M95: =IFERROR(AVERAGEIFS('Август 2025'!$K:$K,'Август 2025'!$E:$E,$A:$A),"-") -> - | N95: =IFERROR(AVERAGEIFS('Сентябрь 2025'!$K:$K,'Сентябрь 2025'!$E:$E,$A:$A),"-") -> - | O95: =IFERROR(AVERAGEIFS('Октябрь 2025'!$K:$K,'Октябрь 2025'!$E:$E,$A:$A),"-") -> - | P95: =IFERROR(AVERAGEIFS('Ноябрь 2025'!$K:$K,'Ноябрь 2025'!$E:$E,$A:$A),"-") -> - | Q95: =IFERROR(AVERAGEIFS('Декабрь 2025'!$K:$K,'Декабрь 2025'!$E:$E,$A:$A),"-") -> - | R95: =IFERROR(AVERAGEIFS('Январь 2026'!$K:$K,'Январь 2026'!$E:$E,$A:$A),"-") -> - | S95: =IFERROR(AVERAGEIFS('Февраль 2026'!$K:$K,'Февраль 2026'!$E:$E,$A:$A),"-") -> - | T95: =IFERROR(AVERAGEIFS('Март 2026'!$K:$K,'Март 2026'!$E:$E,$A:$A),"-") -> - | U95: =IFERROR(AVERAGEIFS('Апрель 2026'!$K:$K,'Апрель 2026'!$E:$E,$A:$A),"-") -> - | V95: =IFERROR(AVERAGEIFS('Май 2026'!$K:$K,'Май 2026'!$E:$E,$A:$A),"-") -> - | W95: =IFERROR(AVERAGEIFS('Июнь 2026'!$K:$K,'Июнь 2026'!$E:$E,$A:$A),"-") -> - | X95: =IFERROR(AVERAGEIFS('Июль 2026'!$K:$K,'Июль 2026'!$E:$E,$A:$A),"-") -> -
B96: =IFERROR(AVERAGEIFS('Сентябрь 2024'!$K:$K,'Сентябрь 2024'!$E:$E,$A:$A),"-") -> - | C96: =IFERROR(AVERAGEIFS('Октябрь 2024'!$K:$K,'Октябрь 2024'!$E:$E,$A:$A),"-") -> - | D96: =IFERROR(AVERAGEIFS('Ноябрь 2024'!$K:$K,'Ноябрь 2024'!$E:$E,$A:$A),"-") -> - | E96: =IFERROR(AVERAGEIFS('Декабрь 2024'!$K:$K,'Декабрь 2024'!$E:$E,$A:$A),"-") -> - | F96: =IFERROR(AVERAGEIFS('Январь 2025'!$K:$K,'Январь 2025'!$E:$E,$A:$A),"-") -> - | G96: =IFERROR(AVERAGEIFS('Февраль 2025 '!K:K,'Февраль 2025 '!E:E,A:A),"-") -> - | H96: =IFERROR(AVERAGEIFS('Март 2025'!$K:$K,'Март 2025'!$E:$E,$A:$A),"-") -> - | I96: =IFERROR(AVERAGEIFS('Апрель 2025'!$K:$K,'Апрель 2025'!$E:$E,$A:$A),"-") -> - | J96: =IFERROR(AVERAGEIFS('Май 2025'!$K:$K,'Май 2025'!$E:$E,$A:$A),"-") -> - | K96: =IFERROR(AVERAGEIFS('Июнь 2025'!$K:$K,'Июнь 2025'!$E:$E,$A:$A),"-") -> - | L96: =IFERROR(AVERAGEIFS('Июль 2025'!$K:$K,'Июль 2025'!$E:$E,$A:$A),"-") -> - | M96: =IFERROR(AVERAGEIFS('Август 2025'!$K:$K,'Август 2025'!$E:$E,$A:$A),"-") -> - | N96: =IFERROR(AVERAGEIFS('Сентябрь 2025'!$K:$K,'Сентябрь 2025'!$E:$E,$A:$A),"-") -> - | O96: =IFERROR(AVERAGEIFS('Октябрь 2025'!$K:$K,'Октябрь 2025'!$E:$E,$A:$A),"-") -> - | P96: =IFERROR(AVERAGEIFS('Ноябрь 2025'!$K:$K,'Ноябрь 2025'!$E:$E,$A:$A),"-") -> - | Q96: =IFERROR(AVERAGEIFS('Декабрь 2025'!$K:$K,'Декабрь 2025'!$E:$E,$A:$A),"-") -> - | R96: =IFERROR(AVERAGEIFS('Январь 2026'!$K:$K,'Январь 2026'!$E:$E,$A:$A),"-") -> - | S96: =IFERROR(AVERAGEIFS('Февраль 2026'!$K:$K,'Февраль 2026'!$E:$E,$A:$A),"-") -> - | T96: =IFERROR(AVERAGEIFS('Март 2026'!$K:$K,'Март 2026'!$E:$E,$A:$A),"-") -> - | U96: =IFERROR(AVERAGEIFS('Апрель 2026'!$K:$K,'Апрель 2026'!$E:$E,$A:$A),"-") -> - | V96: =IFERROR(AVERAGEIFS('Май 2026'!$K:$K,'Май 2026'!$E:$E,$A:$A),"-") -> - | W96: =IFERROR(AVERAGEIFS('Июнь 2026'!$K:$K,'Июнь 2026'!$E:$E,$A:$A),"-") -> - | X96: =IFERROR(AVERAGEIFS('Июль 2026'!$K:$K,'Июль 2026'!$E:$E,$A:$A),"-") -> -
B97: =IFERROR(AVERAGEIFS('Сентябрь 2024'!$K:$K,'Сентябрь 2024'!$E:$E,$A:$A),"-") -> - | C97: =IFERROR(AVERAGEIFS('Октябрь 2024'!$K:$K,'Октябрь 2024'!$E:$E,$A:$A),"-") -> - | D97: =IFERROR(AVERAGEIFS('Ноябрь 2024'!$K:$K,'Ноябрь 2024'!$E:$E,$A:$A),"-") -> - | E97: =IFERROR(AVERAGEIFS('Декабрь 2024'!$K:$K,'Декабрь 2024'!$E:$E,$A:$A),"-") -> - | F97: =IFERROR(AVERAGEIFS('Январь 2025'!$K:$K,'Январь 2025'!$E:$E,$A:$A),"-") -> - | G97: =IFERROR(AVERAGEIFS('Февраль 2025 '!K:K,'Февраль 2025 '!E:E,A:A),"-") -> - | H97: =IFERROR(AVERAGEIFS('Март 2025'!$K:$K,'Март 2025'!$E:$E,$A:$A),"-") -> - | I97: =IFERROR(AVERAGEIFS('Апрель 2025'!$K:$K,'Апрель 2025'!$E:$E,$A:$A),"-") -> - | J97: =IFERROR(AVERAGEIFS('Май 2025'!$K:$K,'Май 2025'!$E:$E,$A:$A),"-") -> - | K97: =IFERROR(AVERAGEIFS('Июнь 2025'!$K:$K,'Июнь 2025'!$E:$E,$A:$A),"-") -> - | L97: =IFERROR(AVERAGEIFS('Июль 2025'!$K:$K,'Июль 2025'!$E:$E,$A:$A),"-") -> - | M97: =IFERROR(AVERAGEIFS('Август 2025'!$K:$K,'Август 2025'!$E:$E,$A:$A),"-") -> - | N97: =IFERROR(AVERAGEIFS('Сентябрь 2025'!$K:$K,'Сентябрь 2025'!$E:$E,$A:$A),"-") -> - | O97: =IFERROR(AVERAGEIFS('Октябрь 2025'!$K:$K,'Октябрь 2025'!$E:$E,$A:$A),"-") -> - | P97: =IFERROR(AVERAGEIFS('Ноябрь 2025'!$K:$K,'Ноябрь 2025'!$E:$E,$A:$A),"-") -> - | Q97: =IFERROR(AVERAGEIFS('Декабрь 2025'!$K:$K,'Декабрь 2025'!$E:$E,$A:$A),"-") -> - | R97: =IFERROR(AVERAGEIFS('Январь 2026'!$K:$K,'Январь 2026'!$E:$E,$A:$A),"-") -> - | S97: =IFERROR(AVERAGEIFS('Февраль 2026'!$K:$K,'Февраль 2026'!$E:$E,$A:$A),"-") -> - | T97: =IFERROR(AVERAGEIFS('Март 2026'!$K:$K,'Март 2026'!$E:$E,$A:$A),"-") -> - | U97: =IFERROR(AVERAGEIFS('Апрель 2026'!$K:$K,'Апрель 2026'!$E:$E,$A:$A),"-") -> - | V97: =IFERROR(AVERAGEIFS('Май 2026'!$K:$K,'Май 2026'!$E:$E,$A:$A),"-") -> - | W97: =IFERROR(AVERAGEIFS('Июнь 2026'!$K:$K,'Июнь 2026'!$E:$E,$A:$A),"-") -> - | X97: =IFERROR(AVERAGEIFS('Июль 2026'!$K:$K,'Июль 2026'!$E:$E,$A:$A),"-") -> -
... B109: =IFERROR(AVERAGEIFS('Сентябрь 2024'!$K:$K,'Сентябрь 2024'!$E:$E,$A:$A),"-") -> - | C109: =IFERROR(AVERAGEIFS('Октябрь 2024'!$K:$K,'Октябрь 2024'!$E:$E,$A:$A),"-") -> - | D109: =IFERROR(AVERAGEIFS('Ноябрь 2024'!$K:$K,'Ноябрь 2024'!$E:$E,$A:$A),"-") -> - | E109: =IFERROR(AVERAGEIFS('Декабрь 2024'!$K:$K,'Декабрь 2024'!$E:$E,$A:$A),"-") -> - | F109: =IFERROR(AVERAGEIFS('Январь 2025'!$K:$K,'Январь 2025'!$E:$E,$A:$A),"-") -> - | G109: =IFERROR(AVERAGEIFS('Февраль 2025 '!K:K,'Февраль 2025 '!E:E,A:A),"-") -> - | H109: =IFERROR(AVERAGEIFS('Март 2025'!$K:$K,'Март 2025'!$E:$E,$A:$A),"-") -> - | I109: =IFERROR(AVERAGEIFS('Апрель 2025'!$K:$K,'Апрель 2025'!$E:$E,$A:$A),"-") -> - | J109: =IFERROR(AVERAGEIFS('Май 2025'!$K:$K,'Май 2025'!$E:$E,$A:$A),"-") -> - | K109: =IFERROR(AVERAGEIFS('Июнь 2025'!$K:$K,'Июнь 2025'!$E:$E,$A:$A),"-") -> - | L109: =IFERROR(AVERAGEIFS('Июль 2025'!$K:$K,'Июль 2025'!$E:$E,$A:$A),"-") -> - | M109: =IFERROR(AVERAGEIFS('Август 2025'!$K:$K,'Август 2025'!$E:$E,$A:$A),"-") -> - | N109: =IFERROR(AVERAGEIFS('Сентябрь 2025'!$K:$K,'Сентябрь 2025'!$E:$E,$A:$A),"-") -> - | O109: =IFERROR(AVERAGEIFS('Октябрь 2025'!$K:$K,'Октябрь 2025'!$E:$E,$A:$A),"-") -> - | P109: =IFERROR(AVERAGEIFS('Ноябрь 2025'!$K:$K,'Ноябрь 2025'!$E:$E,$A:$A),"-") -> - | Q109: =IFERROR(AVERAGEIFS('Декабрь 2025'!$K:$K,'Декабрь 2025'!$E:$E,$A:$A),"-") -> - | R109: =IFERROR(AVERAGEIFS('Январь 2026'!$K:$K,'Январь 2026'!$E:$E,$A:$A),"-") -> - | S109: =IFERROR(AVERAGEIFS('Февраль 2026'!$K:$K,'Февраль 2026'!$E:$E,$A:$A),"-") -> - | T109: =IFERROR(AVERAGEIFS('Март 2026'!$K:$K,'Март 2026'!$E:$E,$A:$A),"-") -> - | U109: =IFERROR(AVERAGEIFS('Апрель 2026'!$K:$K,'Апрель 2026'!$E:$E,$A:$A),"-") -> - | V109: =IFERROR(AVERAGEIFS('Май 2026'!$K:$K,'Май 2026'!$E:$E,$A:$A),"-") -> - | W109: =IFERROR(AVERAGEIFS('Июнь 2026'!$K:$K,'Июнь 2026'!$E:$E,$A:$A),"-") -> - | X109: =IFERROR(AVERAGEIFS('Июль 2026'!$K:$K,'Июль 2026'!$E:$E,$A:$A),"-") -> -
B110: =IFERROR(AVERAGEIFS('Сентябрь 2024'!$K:$K,'Сентябрь 2024'!$E:$E,$A:$A),"-") -> - | C110: =IFERROR(AVERAGEIFS('Октябрь 2024'!$K:$K,'Октябрь 2024'!$E:$E,$A:$A),"-") -> - | D110: =IFERROR(AVERAGEIFS('Ноябрь 2024'!$K:$K,'Ноябрь 2024'!$E:$E,$A:$A),"-") -> - | E110: =IFERROR(AVERAGEIFS('Декабрь 2024'!$K:$K,'Декабрь 2024'!$E:$E,$A:$A),"-") -> - | F110: =IFERROR(AVERAGEIFS('Январь 2025'!$K:$K,'Январь 2025'!$E:$E,$A:$A),"-") -> - | G110: =IFERROR(AVERAGEIFS('Февраль 2025 '!K:K,'Февраль 2025 '!E:E,A:A),"-") -> - | H110: =IFERROR(AVERAGEIFS('Март 2025'!$K:$K,'Март 2025'!$E:$E,$A:$A),"-") -> - | I110: =IFERROR(AVERAGEIFS('Апрель 2025'!$K:$K,'Апрель 2025'!$E:$E,$A:$A),"-") -> - | J110: =IFERROR(AVERAGEIFS('Май 2025'!$K:$K,'Май 2025'!$E:$E,$A:$A),"-") -> - | K110: =IFERROR(AVERAGEIFS('Июнь 2025'!$K:$K,'Июнь 2025'!$E:$E,$A:$A),"-") -> - | L110: =IFERROR(AVERAGEIFS('Июль 2025'!$K:$K,'Июль 2025'!$E:$E,$A:$A),"-") -> - | M110: =IFERROR(AVERAGEIFS('Август 2025'!$K:$K,'Август 2025'!$E:$E,$A:$A),"-") -> - | N110: =IFERROR(AVERAGEIFS('Сентябрь 2025'!$K:$K,'Сентябрь 2025'!$E:$E,$A:$A),"-") -> - | O110: =IFERROR(AVERAGEIFS('Октябрь 2025'!$K:$K,'Октябрь 2025'!$E:$E,$A:$A),"-") -> - | P110: =IFERROR(AVERAGEIFS('Ноябрь 2025'!$K:$K,'Ноябрь 2025'!$E:$E,$A:$A),"-") -> - | Q110: =IFERROR(AVERAGEIFS('Декабрь 2025'!$K:$K,'Декабрь 2025'!$E:$E,$A:$A),"-") -> - | R110: =IFERROR(AVERAGEIFS('Январь 2026'!$K:$K,'Январь 2026'!$E:$E,$A:$A),"-") -> - | S110: =IFERROR(AVERAGEIFS('Февраль 2026'!$K:$K,'Февраль 2026'!$E:$E,$A:$A),"-") -> - | T110: =IFERROR(AVERAGEIFS('Март 2026'!$K:$K,'Март 2026'!$E:$E,$A:$A),"-") -> - | U110: =IFERROR(AVERAGEIFS('Апрель 2026'!$K:$K,'Апрель 2026'!$E:$E,$A:$A),"-") -> - | V110: =IFERROR(AVERAGEIFS('Май 2026'!$K:$K,'Май 2026'!$E:$E,$A:$A),"-") -> - | W110: =IFERROR(AVERAGEIFS('Май 2026'!$K:$K,'Май 2026'!$E:$E,$A:$A),"-") -> - | X110: =IFERROR(AVERAGEIFS('Май 2026'!$K:$K,'Май 2026'!$E:$E,$A:$A),"-") -> -
B111: =IFERROR(AVERAGEIFS('Сентябрь 2024'!$K:$K,'Сентябрь 2024'!$E:$E,$A:$A),"-") -> - | C111: =IFERROR(AVERAGEIFS('Октябрь 2024'!$K:$K,'Октябрь 2024'!$E:$E,$A:$A),"-") -> - | D111: =IFERROR(AVERAGEIFS('Ноябрь 2024'!$K:$K,'Ноябрь 2024'!$E:$E,$A:$A),"-") -> - | E111: =IFERROR(AVERAGEIFS('Декабрь 2024'!$K:$K,'Декабрь 2024'!$E:$E,$A:$A),"-") -> - | F111: =IFERROR(AVERAGEIFS('Январь 2025'!$K:$K,'Январь 2025'!$E:$E,$A:$A),"-") -> - | G111: =IFERROR(AVERAGEIFS('Февраль 2025 '!K:K,'Февраль 2025 '!E:E,A:A),"-") -> - | H111: =IFERROR(AVERAGEIFS('Март 2025'!$K:$K,'Март 2025'!$E:$E,$A:$A),"-") -> - | I111: =IFERROR(AVERAGEIFS('Апрель 2025'!$K:$K,'Апрель 2025'!$E:$E,$A:$A),"-") -> - | J111: =IFERROR(AVERAGEIFS('Май 2025'!$K:$K,'Май 2025'!$E:$E,$A:$A),"-") -> - | K111: =IFERROR(AVERAGEIFS('Июнь 2025'!$K:$K,'Июнь 2025'!$E:$E,$A:$A),"-") -> - | L111: =IFERROR(AVERAGEIFS('Июль 2025'!$K:$K,'Июль 2025'!$E:$E,$A:$A),"-") -> - | M111: =IFERROR(AVERAGEIFS('Август 2025'!$K:$K,'Август 2025'!$E:$E,$A:$A),"-") -> - | N111: =IFERROR(AVERAGEIFS('Сентябрь 2025'!$K:$K,'Сентябрь 2025'!$E:$E,$A:$A),"-") -> - | O111: =IFERROR(AVERAGEIFS('Октябрь 2025'!$K:$K,'Октябрь 2025'!$E:$E,$A:$A),"-") -> - | P111: =IFERROR(AVERAGEIFS('Ноябрь 2025'!$K:$K,'Ноябрь 2025'!$E:$E,$A:$A),"-") -> - | Q111: =IFERROR(AVERAGEIFS('Декабрь 2025'!$K:$K,'Декабрь 2025'!$E:$E,$A:$A),"-") -> - | R111: =IFERROR(AVERAGEIFS('Январь 2026'!$K:$K,'Январь 2026'!$E:$E,$A:$A),"-") -> - | S111: =IFERROR(AVERAGEIFS('Февраль 2026'!$K:$K,'Февраль 2026'!$E:$E,$A:$A),"-") -> - | T111: =IFERROR(AVERAGEIFS('Март 2026'!$K:$K,'Март 2026'!$E:$E,$A:$A),"-") -> - | U111: =IFERROR(AVERAGEIFS('Апрель 2026'!$K:$K,'Апрель 2026'!$E:$E,$A:$A),"-") -> - | V111: =IFERROR(AVERAGEIFS('Май 2026'!$K:$K,'Май 2026'!$E:$E,$A:$A),"-") -> - | W111: =IFERROR(AVERAGEIFS('Май 2026'!$K:$K,'Май 2026'!$E:$E,$A:$A),"-") -> - | X111: =IFERROR(AVERAGEIFS('Май 2026'!$K:$K,'Май 2026'!$E:$E,$A:$A),"-") -> -
B112: =IFERROR(AVERAGEIFS('Сентябрь 2024'!$K:$K,'Сентябрь 2024'!$E:$E,$A:$A),"-") -> - | C112: =IFERROR(AVERAGEIFS('Октябрь 2024'!$K:$K,'Октябрь 2024'!$E:$E,$A:$A),"-") -> - | D112: =IFERROR(AVERAGEIFS('Ноябрь 2024'!$K:$K,'Ноябрь 2024'!$E:$E,$A:$A),"-") -> - | E112: =IFERROR(AVERAGEIFS('Декабрь 2024'!$K:$K,'Декабрь 2024'!$E:$E,$A:$A),"-") -> - | F112: =IFERROR(AVERAGEIFS('Январь 2025'!$K:$K,'Январь 2025'!$E:$E,$A:$A),"-") -> - | G112: =IFERROR(AVERAGEIFS('Февраль 2025 '!K:K,'Февраль 2025 '!E:E,A:A),"-") -> - | H112: =IFERROR(AVERAGEIFS('Март 2025'!$K:$K,'Март 2025'!$E:$E,$A:$A),"-") -> - | I112: =IFERROR(AVERAGEIFS('Апрель 2025'!$K:$K,'Апрель 2025'!$E:$E,$A:$A),"-") -> - | J112: =IFERROR(AVERAGEIFS('Май 2025'!$K:$K,'Май 2025'!$E:$E,$A:$A),"-") -> - | K112: =IFERROR(AVERAGEIFS('Июнь 2025'!$K:$K,'Июнь 2025'!$E:$E,$A:$A),"-") -> - | L112: =IFERROR(AVERAGEIFS('Июль 2025'!$K:$K,'Июль 2025'!$E:$E,$A:$A),"-") -> - | M112: =IFERROR(AVERAGEIFS('Август 2025'!$K:$K,'Август 2025'!$E:$E,$A:$A),"-") -> - | N112: =IFERROR(AVERAGEIFS('Сентябрь 2025'!$K:$K,'Сентябрь 2025'!$E:$E,$A:$A),"-") -> - | O112: =IFERROR(AVERAGEIFS('Октябрь 2025'!$K:$K,'Октябрь 2025'!$E:$E,$A:$A),"-") -> - | P112: =IFERROR(AVERAGEIFS('Ноябрь 2025'!$K:$K,'Ноябрь 2025'!$E:$E,$A:$A),"-") -> - | Q112: =IFERROR(AVERAGEIFS('Декабрь 2025'!$K:$K,'Декабрь 2025'!$E:$E,$A:$A),"-") -> - | R112: =IFERROR(AVERAGEIFS('Январь 2026'!$K:$K,'Январь 2026'!$E:$E,$A:$A),"-") -> - | S112: =IFERROR(AVERAGEIFS('Февраль 2026'!$K:$K,'Февраль 2026'!$E:$E,$A:$A),"-") -> - | T112: =IFERROR(AVERAGEIFS('Март 2026'!$K:$K,'Март 2026'!$E:$E,$A:$A),"-") -> - | U112: =IFERROR(AVERAGEIFS('Апрель 2026'!$K:$K,'Апрель 2026'!$E:$E,$A:$A),"-") -> - | V112: =IFERROR(AVERAGEIFS('Май 2026'!$K:$K,'Май 2026'!$E:$E,$A:$A),"-") -> - | W112: =IFERROR(AVERAGEIFS('Май 2026'!$K:$K,'Май 2026'!$E:$E,$A:$A),"-") -> - | X112: =IFERROR(AVERAGEIFS('Май 2026'!$K:$K,'Май 2026'!$E:$E,$A:$A),"-") -> -
B113: =IFERROR(AVERAGEIFS('Сентябрь 2024'!$K:$K,'Сентябрь 2024'!$E:$E,$A:$A),"-") -> - | C113: =IFERROR(AVERAGEIFS('Октябрь 2024'!$K:$K,'Октябрь 2024'!$E:$E,$A:$A),"-") -> - | D113: =IFERROR(AVERAGEIFS('Ноябрь 2024'!$K:$K,'Ноябрь 2024'!$E:$E,$A:$A),"-") -> - | E113: =IFERROR(AVERAGEIFS('Декабрь 2024'!$K:$K,'Декабрь 2024'!$E:$E,$A:$A),"-") -> - | F113: =IFERROR(AVERAGEIFS('Январь 2025'!$K:$K,'Январь 2025'!$E:$E,$A:$A),"-") -> - | G113: =IFERROR(AVERAGEIFS('Февраль 2025 '!K:K,'Февраль 2025 '!E:E,A:A),"-") -> - | H113: =IFERROR(AVERAGEIFS('Март 2025'!$K:$K,'Март 2025'!$E:$E,$A:$A),"-") -> - | I113: =IFERROR(AVERAGEIFS('Апрель 2025'!$K:$K,'Апрель 2025'!$E:$E,$A:$A),"-") -> - | J113: =IFERROR(AVERAGEIFS('Май 2025'!$K:$K,'Май 2025'!$E:$E,$A:$A),"-") -> - | K113: =IFERROR(AVERAGEIFS('Июнь 2025'!$K:$K,'Июнь 2025'!$E:$E,$A:$A),"-") -> - | L113: =IFERROR(AVERAGEIFS('Июль 2025'!$K:$K,'Июль 2025'!$E:$E,$A:$A),"-") -> - | M113: =IFERROR(AVERAGEIFS('Август 2025'!$K:$K,'Август 2025'!$E:$E,$A:$A),"-") -> - | N113: =IFERROR(AVERAGEIFS('Сентябрь 2025'!$K:$K,'Сентябрь 2025'!$E:$E,$A:$A),"-") -> - | O113: =IFERROR(AVERAGEIFS('Октябрь 2025'!$K:$K,'Октябрь 2025'!$E:$E,$A:$A),"-") -> - | P113: =IFERROR(AVERAGEIFS('Ноябрь 2025'!$K:$K,'Ноябрь 2025'!$E:$E,$A:$A),"-") -> - | Q113: =IFERROR(AVERAGEIFS('Декабрь 2025'!$K:$K,'Декабрь 2025'!$E:$E,$A:$A),"-") -> - | R113: =IFERROR(AVERAGEIFS('Январь 2026'!$K:$K,'Январь 2026'!$E:$E,$A:$A),"-") -> - | S113: =IFERROR(AVERAGEIFS('Февраль 2026'!$K:$K,'Февраль 2026'!$E:$E,$A:$A),"-") -> - | T113: =IFERROR(AVERAGEIFS('Март 2026'!$K:$K,'Март 2026'!$E:$E,$A:$A),"-") -> - | U113: =IFERROR(AVERAGEIFS('Апрель 2026'!$K:$K,'Апрель 2026'!$E:$E,$A:$A),"-") -> - | V113: =IFERROR(AVERAGEIFS('Май 2026'!$K:$K,'Май 2026'!$E:$E,$A:$A),"-") -> - | W113: =IFERROR(AVERAGEIFS('Май 2026'!$K:$K,'Май 2026'!$E:$E,$A:$A),"-") -> - | X113: =IFERROR(AVERAGEIFS('Май 2026'!$K:$K,'Май 2026'!$E:$E,$A:$A),"-") -> -
B114: =IFERROR(AVERAGEIFS('Сентябрь 2024'!$K:$K,'Сентябрь 2024'!$E:$E,$A:$A),"-") -> - | C114: =IFERROR(AVERAGEIFS('Октябрь 2024'!$K:$K,'Октябрь 2024'!$E:$E,$A:$A),"-") -> - | D114: =IFERROR(AVERAGEIFS('Ноябрь 2024'!$K:$K,'Ноябрь 2024'!$E:$E,$A:$A),"-") -> - | E114: =IFERROR(AVERAGEIFS('Декабрь 2024'!$K:$K,'Декабрь 2024'!$E:$E,$A:$A),"-") -> - | F114: =IFERROR(AVERAGEIFS('Январь 2025'!$K:$K,'Январь 2025'!$E:$E,$A:$A),"-") -> - | G114: =IFERROR(AVERAGEIFS('Февраль 2025 '!K:K,'Февраль 2025 '!E:E,A:A),"-") -> - | H114: =IFERROR(AVERAGEIFS('Март 2025'!$K:$K,'Март 2025'!$E:$E,$A:$A),"-") -> - | I114: =IFERROR(AVERAGEIFS('Апрель 2025'!$K:$K,'Апрель 2025'!$E:$E,$A:$A),"-") -> - | J114: =IFERROR(AVERAGEIFS('Май 2025'!$K:$K,'Май 2025'!$E:$E,$A:$A),"-") -> - | K114: =IFERROR(AVERAGEIFS('Июнь 2025'!$K:$K,'Июнь 2025'!$E:$E,$A:$A),"-") -> - | L114: =IFERROR(AVERAGEIFS('Июль 2025'!$K:$K,'Июль 2025'!$E:$E,$A:$A),"-") -> - | M114: =IFERROR(AVERAGEIFS('Август 2025'!$K:$K,'Август 2025'!$E:$E,$A:$A),"-") -> - | N114: =IFERROR(AVERAGEIFS('Сентябрь 2025'!$K:$K,'Сентябрь 2025'!$E:$E,$A:$A),"-") -> - | O114: =IFERROR(AVERAGEIFS('Октябрь 2025'!$K:$K,'Октябрь 2025'!$E:$E,$A:$A),"-") -> - | P114: =IFERROR(AVERAGEIFS('Ноябрь 2025'!$K:$K,'Ноябрь 2025'!$E:$E,$A:$A),"-") -> - | Q114: =IFERROR(AVERAGEIFS('Декабрь 2025'!$K:$K,'Декабрь 2025'!$E:$E,$A:$A),"-") -> - | R114: =IFERROR(AVERAGEIFS('Январь 2026'!$K:$K,'Январь 2026'!$E:$E,$A:$A),"-") -> - | S114: =IFERROR(AVERAGEIFS('Февраль 2026'!$K:$K,'Февраль 2026'!$E:$E,$A:$A),"-") -> - | T114: =IFERROR(AVERAGEIFS('Март 2026'!$K:$K,'Март 2026'!$E:$E,$A:$A),"-") -> - | U114: =IFERROR(AVERAGEIFS('Апрель 2026'!$K:$K,'Апрель 2026'!$E:$E,$A:$A),"-") -> - | V114: =IFERROR(AVERAGEIFS('Май 2026'!$K:$K,'Май 2026'!$E:$E,$A:$A),"-") -> - | W114: =IFERROR(AVERAGEIFS('Май 2026'!$K:$K,'Май 2026'!$E:$E,$A:$A),"-") -> - | X114: =IFERROR(AVERAGEIFS('Май 2026'!$K:$K,'Май 2026'!$E:$E,$A:$A),"-") -> -
B115: =IFERROR(AVERAGEIFS('Сентябрь 2024'!$K:$K,'Сентябрь 2024'!$E:$E,$A:$A),"-") -> - | C115: =IFERROR(AVERAGEIFS('Октябрь 2024'!$K:$K,'Октябрь 2024'!$E:$E,$A:$A),"-") -> - | D115: =IFERROR(AVERAGEIFS('Ноябрь 2024'!$K:$K,'Ноябрь 2024'!$E:$E,$A:$A),"-") -> - | E115: =IFERROR(AVERAGEIFS('Декабрь 2024'!$K:$K,'Декабрь 2024'!$E:$E,$A:$A),"-") -> - | F115: =IFERROR(AVERAGEIFS('Январь 2025'!$K:$K,'Январь 2025'!$E:$E,$A:$A),"-") -> - | G115: =IFERROR(AVERAGEIFS('Февраль 2025 '!K:K,'Февраль 2025 '!E:E,A:A),"-") -> - | H115: =IFERROR(AVERAGEIFS('Март 2025'!$K:$K,'Март 2025'!$E:$E,$A:$A),"-") -> - | I115: =IFERROR(AVERAGEIFS('Апрель 2025'!$K:$K,'Апрель 2025'!$E:$E,$A:$A),"-") -> - | J115: =IFERROR(AVERAGEIFS('Май 2025'!$K:$K,'Май 2025'!$E:$E,$A:$A),"-") -> - | K115: =IFERROR(AVERAGEIFS('Июнь 2025'!$K:$K,'Июнь 2025'!$E:$E,$A:$A),"-") -> - | L115: =IFERROR(AVERAGEIFS('Июль 2025'!$K:$K,'Июль 2025'!$E:$E,$A:$A),"-") -> - | M115: =IFERROR(AVERAGEIFS('Август 2025'!$K:$K,'Август 2025'!$E:$E,$A:$A),"-") -> - | N115: =IFERROR(AVERAGEIFS('Сентябрь 2025'!$K:$K,'Сентябрь 2025'!$E:$E,$A:$A),"-") -> - | O115: =IFERROR(AVERAGEIFS('Октябрь 2025'!$K:$K,'Октябрь 2025'!$E:$E,$A:$A),"-") -> - | P115: =IFERROR(AVERAGEIFS('Ноябрь 2025'!$K:$K,'Ноябрь 2025'!$E:$E,$A:$A),"-") -> - | Q115: =IFERROR(AVERAGEIFS('Декабрь 2025'!$K:$K,'Декабрь 2025'!$E:$E,$A:$A),"-") -> - | R115: =IFERROR(AVERAGEIFS('Январь 2026'!$K:$K,'Январь 2026'!$E:$E,$A:$A),"-") -> - | S115: =IFERROR(AVERAGEIFS('Февраль 2026'!$K:$K,'Февраль 2026'!$E:$E,$A:$A),"-") -> - | T115: =IFERROR(AVERAGEIFS('Март 2026'!$K:$K,'Март 2026'!$E:$E,$A:$A),"-") -> - | U115: =IFERROR(AVERAGEIFS('Апрель 2026'!$K:$K,'Апрель 2026'!$E:$E,$A:$A),"-") -> - | V115: =IFERROR(AVERAGEIFS('Май 2026'!$K:$K,'Май 2026'!$E:$E,$A:$A),"-") -> - | W115: =IFERROR(AVERAGEIFS('Май 2026'!$K:$K,'Май 2026'!$E:$E,$A:$A),"-") -> - | X115: =IFERROR(AVERAGEIFS('Май 2026'!$K:$K,'Май 2026'!$E:$E,$A:$A),"-") -> -
B116: =IFERROR(AVERAGEIFS('Сентябрь 2024'!$K:$K,'Сентябрь 2024'!$E:$E,$A:$A),"-") -> - | C116: =IFERROR(AVERAGEIFS('Октябрь 2024'!$K:$K,'Октябрь 2024'!$E:$E,$A:$A),"-") -> - | D116: =IFERROR(AVERAGEIFS('Ноябрь 2024'!$K:$K,'Ноябрь 2024'!$E:$E,$A:$A),"-") -> - | E116: =IFERROR(AVERAGEIFS('Декабрь 2024'!$K:$K,'Декабрь 2024'!$E:$E,$A:$A),"-") -> - | F116: =IFERROR(AVERAGEIFS('Январь 2025'!$K:$K,'Январь 2025'!$E:$E,$A:$A),"-") -> - | G116: =IFERROR(AVERAGEIFS('Февраль 2025 '!K:K,'Февраль 2025 '!E:E,A:A),"-") -> - | H116: =IFERROR(AVERAGEIFS('Март 2025'!$K:$K,'Март 2025'!$E:$E,$A:$A),"-") -> - | I116: =IFERROR(AVERAGEIFS('Апрель 2025'!$K:$K,'Апрель 2025'!$E:$E,$A:$A),"-") -> - | J116: =IFERROR(AVERAGEIFS('Май 2025'!$K:$K,'Май 2025'!$E:$E,$A:$A),"-") -> - | K116: =IFERROR(AVERAGEIFS('Июнь 2025'!$K:$K,'Июнь 2025'!$E:$E,$A:$A),"-") -> - | L116: =IFERROR(AVERAGEIFS('Июль 2025'!$K:$K,'Июль 2025'!$E:$E,$A:$A),"-") -> - | M116: =IFERROR(AVERAGEIFS('Август 2025'!$K:$K,'Август 2025'!$E:$E,$A:$A),"-") -> - | N116: =IFERROR(AVERAGEIFS('Сентябрь 2025'!$K:$K,'Сентябрь 2025'!$E:$E,$A:$A),"-") -> - | O116: =IFERROR(AVERAGEIFS('Октябрь 2025'!$K:$K,'Октябрь 2025'!$E:$E,$A:$A),"-") -> - | P116: =IFERROR(AVERAGEIFS('Ноябрь 2025'!$K:$K,'Ноябрь 2025'!$E:$E,$A:$A),"-") -> - | Q116: =IFERROR(AVERAGEIFS('Декабрь 2025'!$K:$K,'Декабрь 2025'!$E:$E,$A:$A),"-") -> - | R116: =IFERROR(AVERAGEIFS('Январь 2026'!$K:$K,'Январь 2026'!$E:$E,$A:$A),"-") -> - | S116: =IFERROR(AVERAGEIFS('Февраль 2026'!$K:$K,'Февраль 2026'!$E:$E,$A:$A),"-") -> - | T116: =IFERROR(AVERAGEIFS('Март 2026'!$K:$K,'Март 2026'!$E:$E,$A:$A),"-") -> - | U116: =IFERROR(AVERAGEIFS('Апрель 2026'!$K:$K,'Апрель 2026'!$E:$E,$A:$A),"-") -> - | V116: =IFERROR(AVERAGEIFS('Май 2026'!$K:$K,'Май 2026'!$E:$E,$A:$A),"-") -> - | W116: =IFERROR(AVERAGEIFS('Май 2026'!$K:$K,'Май 2026'!$E:$E,$A:$A),"-") -> - | X116: =IFERROR(AVERAGEIFS('Май 2026'!$K:$K,'Май 2026'!$E:$E,$A:$A),"-") -> -
B117: =IFERROR(AVERAGEIFS('Сентябрь 2024'!$K:$K,'Сентябрь 2024'!$E:$E,$A:$A),"-") -> - | C117: =IFERROR(AVERAGEIFS('Октябрь 2024'!$K:$K,'Октябрь 2024'!$E:$E,$A:$A),"-") -> - | D117: =IFERROR(AVERAGEIFS('Ноябрь 2024'!$K:$K,'Ноябрь 2024'!$E:$E,$A:$A),"-") -> - | E117: =IFERROR(AVERAGEIFS('Декабрь 2024'!$K:$K,'Декабрь 2024'!$E:$E,$A:$A),"-") -> - | F117: =IFERROR(AVERAGEIFS('Январь 2025'!$K:$K,'Январь 2025'!$E:$E,$A:$A),"-") -> - | G117: =IFERROR(AVERAGEIFS('Февраль 2025 '!K:K,'Февраль 2025 '!E:E,A:A),"-") -> - | H117: =IFERROR(AVERAGEIFS('Март 2025'!$K:$K,'Март 2025'!$E:$E,$A:$A),"-") -> - | I117: =IFERROR(AVERAGEIFS('Апрель 2025'!$K:$K,'Апрель 2025'!$E:$E,$A:$A),"-") -> - | J117: =IFERROR(AVERAGEIFS('Май 2025'!$K:$K,'Май 2025'!$E:$E,$A:$A),"-") -> - | K117: =IFERROR(AVERAGEIFS('Июнь 2025'!$K:$K,'Июнь 2025'!$E:$E,$A:$A),"-") -> - | L117: =IFERROR(AVERAGEIFS('Июль 2025'!$K:$K,'Июль 2025'!$E:$E,$A:$A),"-") -> - | M117: =IFERROR(AVERAGEIFS('Август 2025'!$K:$K,'Август 2025'!$E:$E,$A:$A),"-") -> - | N117: =IFERROR(AVERAGEIFS('Сентябрь 2025'!$K:$K,'Сентябрь 2025'!$E:$E,$A:$A),"-") -> - | O117: =IFERROR(AVERAGEIFS('Октябрь 2025'!$K:$K,'Октябрь 2025'!$E:$E,$A:$A),"-") -> - | P117: =IFERROR(AVERAGEIFS('Ноябрь 2025'!$K:$K,'Ноябрь 2025'!$E:$E,$A:$A),"-") -> - | Q117: =IFERROR(AVERAGEIFS('Декабрь 2025'!$K:$K,'Декабрь 2025'!$E:$E,$A:$A),"-") -> - | R117: =IFERROR(AVERAGEIFS('Январь 2026'!$K:$K,'Январь 2026'!$E:$E,$A:$A),"-") -> - | S117: =IFERROR(AVERAGEIFS('Февраль 2026'!$K:$K,'Февраль 2026'!$E:$E,$A:$A),"-") -> - | T117: =IFERROR(AVERAGEIFS('Март 2026'!$K:$K,'Март 2026'!$E:$E,$A:$A),"-") -> - | U117: =IFERROR(AVERAGEIFS('Апрель 2026'!$K:$K,'Апрель 2026'!$E:$E,$A:$A),"-") -> - | V117: =IFERROR(AVERAGEIFS('Май 2026'!$K:$K,'Май 2026'!$E:$E,$A:$A),"-") -> - | W117: =IFERROR(AVERAGEIFS('Май 2026'!$K:$K,'Май 2026'!$E:$E,$A:$A),"-") -> - | X117: =IFERROR(AVERAGEIFS('Май 2026'!$K:$K,'Май 2026'!$E:$E,$A:$A),"-") -> -
B118: =IFERROR(AVERAGEIFS('Сентябрь 2024'!$K:$K,'Сентябрь 2024'!$E:$E,$A:$A),"-") -> - | C118: =IFERROR(AVERAGEIFS('Октябрь 2024'!$K:$K,'Октябрь 2024'!$E:$E,$A:$A),"-") -> - | D118: =IFERROR(AVERAGEIFS('Ноябрь 2024'!$K:$K,'Ноябрь 2024'!$E:$E,$A:$A),"-") -> - | E118: =IFERROR(AVERAGEIFS('Декабрь 2024'!$K:$K,'Декабрь 2024'!$E:$E,$A:$A),"-") -> - | F118: =IFERROR(AVERAGEIFS('Январь 2025'!$K:$K,'Январь 2025'!$E:$E,$A:$A),"-") -> - | G118: =IFERROR(AVERAGEIFS('Февраль 2025 '!K:K,'Февраль 2025 '!E:E,A:A),"-") -> - | H118: =IFERROR(AVERAGEIFS('Март 2025'!$K:$K,'Март 2025'!$E:$E,$A:$A),"-") -> - | I118: =IFERROR(AVERAGEIFS('Апрель 2025'!$K:$K,'Апрель 2025'!$E:$E,$A:$A),"-") -> - | J118: =IFERROR(AVERAGEIFS('Май 2025'!$K:$K,'Май 2025'!$E:$E,$A:$A),"-") -> - | K118: =IFERROR(AVERAGEIFS('Июнь 2025'!$K:$K,'Июнь 2025'!$E:$E,$A:$A),"-") -> - | L118: =IFERROR(AVERAGEIFS('Июль 2025'!$K:$K,'Июль 2025'!$E:$E,$A:$A),"-") -> - | M118: =IFERROR(AVERAGEIFS('Август 2025'!$K:$K,'Август 2025'!$E:$E,$A:$A),"-") -> - | N118: =IFERROR(AVERAGEIFS('Сентябрь 2025'!$K:$K,'Сентябрь 2025'!$E:$E,$A:$A),"-") -> - | O118: =IFERROR(AVERAGEIFS('Октябрь 2025'!$K:$K,'Октябрь 2025'!$E:$E,$A:$A),"-") -> - | P118: =IFERROR(AVERAGEIFS('Ноябрь 2025'!$K:$K,'Ноябрь 2025'!$E:$E,$A:$A),"-") -> - | Q118: =IFERROR(AVERAGEIFS('Декабрь 2025'!$K:$K,'Декабрь 2025'!$E:$E,$A:$A),"-") -> - | R118: =IFERROR(AVERAGEIFS('Январь 2026'!$K:$K,'Январь 2026'!$E:$E,$A:$A),"-") -> - | S118: =IFERROR(AVERAGEIFS('Февраль 2026'!$K:$K,'Февраль 2026'!$E:$E,$A:$A),"-") -> - | T118: =IFERROR(AVERAGEIFS('Март 2026'!$K:$K,'Март 2026'!$E:$E,$A:$A),"-") -> - | U118: =IFERROR(AVERAGEIFS('Апрель 2026'!$K:$K,'Апрель 2026'!$E:$E,$A:$A),"-") -> - | V118: =IFERROR(AVERAGEIFS('Май 2026'!$K:$K,'Май 2026'!$E:$E,$A:$A),"-") -> - | W118: =IFERROR(AVERAGEIFS('Май 2026'!$K:$K,'Май 2026'!$E:$E,$A:$A),"-") -> - | X118: =IFERROR(AVERAGEIFS('Май 2026'!$K:$K,'Май 2026'!$E:$E,$A:$A),"-") -> -
B119: =IFERROR(AVERAGEIFS('Сентябрь 2024'!$K:$K,'Сентябрь 2024'!$E:$E,$A:$A),"-") -> - | C119: =IFERROR(AVERAGEIFS('Октябрь 2024'!$K:$K,'Октябрь 2024'!$E:$E,$A:$A),"-") -> - | D119: =IFERROR(AVERAGEIFS('Ноябрь 2024'!$K:$K,'Ноябрь 2024'!$E:$E,$A:$A),"-") -> - | E119: =IFERROR(AVERAGEIFS('Декабрь 2024'!$K:$K,'Декабрь 2024'!$E:$E,$A:$A),"-") -> - | F119: =IFERROR(AVERAGEIFS('Январь 2025'!$K:$K,'Январь 2025'!$E:$E,$A:$A),"-") -> - | G119: =IFERROR(AVERAGEIFS('Февраль 2025 '!K:K,'Февраль 2025 '!E:E,A:A),"-") -> - | H119: =IFERROR(AVERAGEIFS('Март 2025'!$K:$K,'Март 2025'!$E:$E,$A:$A),"-") -> - | I119: =IFERROR(AVERAGEIFS('Апрель 2025'!$K:$K,'Апрель 2025'!$E:$E,$A:$A),"-") -> - | J119: =IFERROR(AVERAGEIFS('Май 2025'!$K:$K,'Май 2025'!$E:$E,$A:$A),"-") -> - | K119: =IFERROR(AVERAGEIFS('Июнь 2025'!$K:$K,'Июнь 2025'!$E:$E,$A:$A),"-") -> - | L119: =IFERROR(AVERAGEIFS('Июль 2025'!$K:$K,'Июль 2025'!$E:$E,$A:$A),"-") -> - | M119: =IFERROR(AVERAGEIFS('Август 2025'!$K:$K,'Август 2025'!$E:$E,$A:$A),"-") -> - | N119: =IFERROR(AVERAGEIFS('Сентябрь 2025'!$K:$K,'Сентябрь 2025'!$E:$E,$A:$A),"-") -> - | O119: =IFERROR(AVERAGEIFS('Октябрь 2025'!$K:$K,'Октябрь 2025'!$E:$E,$A:$A),"-") -> - | P119: =IFERROR(AVERAGEIFS('Ноябрь 2025'!$K:$K,'Ноябрь 2025'!$E:$E,$A:$A),"-") -> - | Q119: =IFERROR(AVERAGEIFS('Декабрь 2025'!$K:$K,'Декабрь 2025'!$E:$E,$A:$A),"-") -> - | R119: =IFERROR(AVERAGEIFS('Январь 2026'!$K:$K,'Январь 2026'!$E:$E,$A:$A),"-") -> - | S119: =IFERROR(AVERAGEIFS('Февраль 2026'!$K:$K,'Февраль 2026'!$E:$E,$A:$A),"-") -> - | T119: =IFERROR(AVERAGEIFS('Март 2026'!$K:$K,'Март 2026'!$E:$E,$A:$A),"-") -> - | U119: =IFERROR(AVERAGEIFS('Апрель 2026'!$K:$K,'Апрель 2026'!$E:$E,$A:$A),"-") -> - | V119: =IFERROR(AVERAGEIFS('Май 2026'!$K:$K,'Май 2026'!$E:$E,$A:$A),"-") -> - | W119: =IFERROR(AVERAGEIFS('Май 2026'!$K:$K,'Май 2026'!$E:$E,$A:$A),"-") -> - | X119: =IFERROR(AVERAGEIFS('Май 2026'!$K:$K,'Май 2026'!$E:$E,$A:$A),"-") -> -
B120: =IFERROR(AVERAGEIFS('Сентябрь 2024'!$K:$K,'Сентябрь 2024'!$E:$E,$A:$A),"-") -> - | C120: =IFERROR(AVERAGEIFS('Октябрь 2024'!$K:$K,'Октябрь 2024'!$E:$E,$A:$A),"-") -> - | D120: =IFERROR(AVERAGEIFS('Ноябрь 2024'!$K:$K,'Ноябрь 2024'!$E:$E,$A:$A),"-") -> - | E120: =IFERROR(AVERAGEIFS('Декабрь 2024'!$K:$K,'Декабрь 2024'!$E:$E,$A:$A),"-") -> - | F120: =IFERROR(AVERAGEIFS('Январь 2025'!$K:$K,'Январь 2025'!$E:$E,$A:$A),"-") -> - | G120: =IFERROR(AVERAGEIFS('Февраль 2025 '!K:K,'Февраль 2025 '!E:E,A:A),"-") -> - | H120: =IFERROR(AVERAGEIFS('Март 2025'!$K:$K,'Март 2025'!$E:$E,$A:$A),"-") -> - | I120: =IFERROR(AVERAGEIFS('Апрель 2025'!$K:$K,'Апрель 2025'!$E:$E,$A:$A),"-") -> - | J120: =IFERROR(AVERAGEIFS('Май 2025'!$K:$K,'Май 2025'!$E:$E,$A:$A),"-") -> - | K120: =IFERROR(AVERAGEIFS('Июнь 2025'!$K:$K,'Июнь 2025'!$E:$E,$A:$A),"-") -> - | L120: =IFERROR(AVERAGEIFS('Июль 2025'!$K:$K,'Июль 2025'!$E:$E,$A:$A),"-") -> - | M120: =IFERROR(AVERAGEIFS('Август 2025'!$K:$K,'Август 2025'!$E:$E,$A:$A),"-") -> - | N120: =IFERROR(AVERAGEIFS('Сентябрь 2025'!$K:$K,'Сентябрь 2025'!$E:$E,$A:$A),"-") -> - | O120: =IFERROR(AVERAGEIFS('Октябрь 2025'!$K:$K,'Октябрь 2025'!$E:$E,$A:$A),"-") -> - | P120: =IFERROR(AVERAGEIFS('Ноябрь 2025'!$K:$K,'Ноябрь 2025'!$E:$E,$A:$A),"-") -> - | Q120: =IFERROR(AVERAGEIFS('Декабрь 2025'!$K:$K,'Декабрь 2025'!$E:$E,$A:$A),"-") -> - | R120: =IFERROR(AVERAGEIFS('Январь 2026'!$K:$K,'Январь 2026'!$E:$E,$A:$A),"-") -> - | S120: =IFERROR(AVERAGEIFS('Февраль 2026'!$K:$K,'Февраль 2026'!$E:$E,$A:$A),"-") -> - | T120: =IFERROR(AVERAGEIFS('Март 2026'!$K:$K,'Март 2026'!$E:$E,$A:$A),"-") -> - | U120: =IFERROR(AVERAGEIFS('Апрель 2026'!$K:$K,'Апрель 2026'!$E:$E,$A:$A),"-") -> - | V120: =IFERROR(AVERAGEIFS('Май 2026'!$K:$K,'Май 2026'!$E:$E,$A:$A),"-") -> - | W120: =IFERROR(AVERAGEIFS('Май 2026'!$K:$K,'Май 2026'!$E:$E,$A:$A),"-") -> - | X120: =IFERROR(AVERAGEIFS('Май 2026'!$K:$K,'Май 2026'!$E:$E,$A:$A),"-") -> -
B121: =IFERROR(AVERAGEIFS('Сентябрь 2024'!$K:$K,'Сентябрь 2024'!$E:$E,$A:$A),"-") -> - | C121: =IFERROR(AVERAGEIFS('Октябрь 2024'!$K:$K,'Октябрь 2024'!$E:$E,$A:$A),"-") -> - | D121: =IFERROR(AVERAGEIFS('Ноябрь 2024'!$K:$K,'Ноябрь 2024'!$E:$E,$A:$A),"-") -> - | E121: =IFERROR(AVERAGEIFS('Декабрь 2024'!$K:$K,'Декабрь 2024'!$E:$E,$A:$A),"-") -> - | F121: =IFERROR(AVERAGEIFS('Январь 2025'!$K:$K,'Январь 2025'!$E:$E,$A:$A),"-") -> - | G121: =IFERROR(AVERAGEIFS('Февраль 2025 '!K:K,'Февраль 2025 '!E:E,A:A),"-") -> - | H121: =IFERROR(AVERAGEIFS('Март 2025'!$K:$K,'Март 2025'!$E:$E,$A:$A),"-") -> - | I121: =IFERROR(AVERAGEIFS('Апрель 2025'!$K:$K,'Апрель 2025'!$E:$E,$A:$A),"-") -> - | J121: =IFERROR(AVERAGEIFS('Май 2025'!$K:$K,'Май 2025'!$E:$E,$A:$A),"-") -> - | K121: =IFERROR(AVERAGEIFS('Июнь 2025'!$K:$K,'Июнь 2025'!$E:$E,$A:$A),"-") -> - | L121: =IFERROR(AVERAGEIFS('Июль 2025'!$K:$K,'Июль 2025'!$E:$E,$A:$A),"-") -> - | M121: =IFERROR(AVERAGEIFS('Август 2025'!$K:$K,'Август 2025'!$E:$E,$A:$A),"-") -> - | N121: =IFERROR(AVERAGEIFS('Сентябрь 2025'!$K:$K,'Сентябрь 2025'!$E:$E,$A:$A),"-") -> - | O121: =IFERROR(AVERAGEIFS('Октябрь 2025'!$K:$K,'Октябрь 2025'!$E:$E,$A:$A),"-") -> - | P121: =IFERROR(AVERAGEIFS('Ноябрь 2025'!$K:$K,'Ноябрь 2025'!$E:$E,$A:$A),"-") -> - | Q121: =IFERROR(AVERAGEIFS('Декабрь 2025'!$K:$K,'Декабрь 2025'!$E:$E,$A:$A),"-") -> - | R121: =IFERROR(AVERAGEIFS('Январь 2026'!$K:$K,'Январь 2026'!$E:$E,$A:$A),"-") -> - | S121: =IFERROR(AVERAGEIFS('Февраль 2026'!$K:$K,'Февраль 2026'!$E:$E,$A:$A),"-") -> - | T121: =IFERROR(AVERAGEIFS('Март 2026'!$K:$K,'Март 2026'!$E:$E,$A:$A),"-") -> - | U121: =IFERROR(AVERAGEIFS('Апрель 2026'!$K:$K,'Апрель 2026'!$E:$E,$A:$A),"-") -> - | V121: =IFERROR(AVERAGEIFS('Май 2026'!$K:$K,'Май 2026'!$E:$E,$A:$A),"-") -> - | W121: =IFERROR(AVERAGEIFS('Май 2026'!$K:$K,'Май 2026'!$E:$E,$A:$A),"-") -> - | X121: =IFERROR(AVERAGEIFS('Май 2026'!$K:$K,'Май 2026'!$E:$E,$A:$A),"-") -> -
... B123: =IFERROR(AVERAGEIFS('Сентябрь 2024'!$K:$K,'Сентябрь 2024'!$E:$E,$A:$A),"-") -> - | C123: =IFERROR(AVERAGEIFS('Октябрь 2024'!$K:$K,'Октябрь 2024'!$E:$E,$A:$A),"-") -> - | D123: =IFERROR(AVERAGEIFS('Ноябрь 2024'!$K:$K,'Ноябрь 2024'!$E:$E,$A:$A),"-") -> - | E123: =IFERROR(AVERAGEIFS('Декабрь 2024'!$K:$K,'Декабрь 2024'!$E:$E,$A:$A),"-") -> - | F123: =IFERROR(AVERAGEIFS('Январь 2025'!$K:$K,'Январь 2025'!$E:$E,$A:$A),"-") -> - | G123: =IFERROR(AVERAGEIFS('Февраль 2025 '!K:K,'Февраль 2025 '!E:E,A:A),"-") -> - | H123: =IFERROR(AVERAGEIFS('Март 2025'!$K:$K,'Март 2025'!$E:$E,$A:$A),"-") -> - | I123: =IFERROR(AVERAGEIFS('Апрель 2025'!$K:$K,'Апрель 2025'!$E:$E,$A:$A),"-") -> - | J123: =IFERROR(AVERAGEIFS('Май 2025'!$K:$K,'Май 2025'!$E:$E,$A:$A),"-") -> - | K123: =IFERROR(AVERAGEIFS('Июнь 2025'!$K:$K,'Июнь 2025'!$E:$E,$A:$A),"-") -> - | L123: =IFERROR(AVERAGEIFS('Июль 2025'!$K:$K,'Июль 2025'!$E:$E,$A:$A),"-") -> - | M123: =IFERROR(AVERAGEIFS('Август 2025'!$K:$K,'Август 2025'!$E:$E,$A:$A),"-") -> - | N123: =IFERROR(AVERAGEIFS('Сентябрь 2025'!$K:$K,'Сентябрь 2025'!$E:$E,$A:$A),"-") -> - | O123: =IFERROR(AVERAGEIFS('Октябрь 2025'!$K:$K,'Октябрь 2025'!$E:$E,$A:$A),"-") -> - | P123: =IFERROR(AVERAGEIFS('Ноябрь 2025'!$K:$K,'Ноябрь 2025'!$E:$E,$A:$A),"-") -> - | Q123: =IFERROR(AVERAGEIFS('Декабрь 2025'!$K:$K,'Декабрь 2025'!$E:$E,$A:$A),"-") -> - | R123: =IFERROR(AVERAGEIFS('Январь 2026'!$K:$K,'Январь 2026'!$E:$E,$A:$A),"-") -> - | S123: =IFERROR(AVERAGEIFS('Февраль 2026'!$K:$K,'Февраль 2026'!$E:$E,$A:$A),"-") -> - | T123: =IFERROR(AVERAGEIFS('Март 2026'!$K:$K,'Март 2026'!$E:$E,$A:$A),"-") -> - | U123: =IFERROR(AVERAGEIFS('Апрель 2026'!$K:$K,'Апрель 2026'!$E:$E,$A:$A),"-") -> - | V123: =IFERROR(AVERAGEIFS('Май 2026'!$K:$K,'Май 2026'!$E:$E,$A:$A),"-") -> - | W123: =IFERROR(AVERAGEIFS('Май 2026'!$K:$K,'Май 2026'!$E:$E,$A:$A),"-") -> - | X123: =IFERROR(AVERAGEIFS('Май 2026'!$K:$K,'Май 2026'!$E:$E,$A:$A),"-") -> -
B124: =IFERROR(AVERAGEIFS('Сентябрь 2024'!$K:$K,'Сентябрь 2024'!$E:$E,$A:$A),"-") -> - | C124: =IFERROR(AVERAGEIFS('Октябрь 2024'!$K:$K,'Октябрь 2024'!$E:$E,$A:$A),"-") -> - | D124: =IFERROR(AVERAGEIFS('Ноябрь 2024'!$K:$K,'Ноябрь 2024'!$E:$E,$A:$A),"-") -> - | E124: =IFERROR(AVERAGEIFS('Декабрь 2024'!$K:$K,'Декабрь 2024'!$E:$E,$A:$A),"-") -> - | F124: =IFERROR(AVERAGEIFS('Январь 2025'!$K:$K,'Январь 2025'!$E:$E,$A:$A),"-") -> - | G124: =IFERROR(AVERAGEIFS('Февраль 2025 '!K:K,'Февраль 2025 '!E:E,A:A),"-") -> - | H124: =IFERROR(AVERAGEIFS('Март 2025'!$K:$K,'Март 2025'!$E:$E,$A:$A),"-") -> - | I124: =IFERROR(AVERAGEIFS('Апрель 2025'!$K:$K,'Апрель 2025'!$E:$E,$A:$A),"-") -> - | J124: =IFERROR(AVERAGEIFS('Май 2025'!$K:$K,'Май 2025'!$E:$E,$A:$A),"-") -> - | K124: =IFERROR(AVERAGEIFS('Июнь 2025'!$K:$K,'Июнь 2025'!$E:$E,$A:$A),"-") -> - | L124: =IFERROR(AVERAGEIFS('Июль 2025'!$K:$K,'Июль 2025'!$E:$E,$A:$A),"-") -> - | M124: =IFERROR(AVERAGEIFS('Август 2025'!$K:$K,'Август 2025'!$E:$E,$A:$A),"-") -> - | N124: =IFERROR(AVERAGEIFS('Сентябрь 2025'!$K:$K,'Сентябрь 2025'!$E:$E,$A:$A),"-") -> - | O124: =IFERROR(AVERAGEIFS('Октябрь 2025'!$K:$K,'Октябрь 2025'!$E:$E,$A:$A),"-") -> - | P124: =IFERROR(AVERAGEIFS('Ноябрь 2025'!$K:$K,'Ноябрь 2025'!$E:$E,$A:$A),"-") -> - | Q124: =IFERROR(AVERAGEIFS('Декабрь 2025'!$K:$K,'Декабрь 2025'!$E:$E,$A:$A),"-") -> - | R124: =IFERROR(AVERAGEIFS('Январь 2026'!$K:$K,'Январь 2026'!$E:$E,$A:$A),"-") -> - | S124: =IFERROR(AVERAGEIFS('Февраль 2026'!$K:$K,'Февраль 2026'!$E:$E,$A:$A),"-") -> - | T124: =IFERROR(AVERAGEIFS('Март 2026'!$K:$K,'Март 2026'!$E:$E,$A:$A),"-") -> -
B125: =IFERROR(AVERAGEIFS('Сентябрь 2024'!$K:$K,'Сентябрь 2024'!$E:$E,$A:$A),"-") -> - | C125: =IFERROR(AVERAGEIFS('Октябрь 2024'!$K:$K,'Октябрь 2024'!$E:$E,$A:$A),"-") -> - | D125: =IFERROR(AVERAGEIFS('Ноябрь 2024'!$K:$K,'Ноябрь 2024'!$E:$E,$A:$A),"-") -> - | E125: =IFERROR(AVERAGEIFS('Декабрь 2024'!$K:$K,'Декабрь 2024'!$E:$E,$A:$A),"-") -> - | F125: =IFERROR(AVERAGEIFS('Январь 2025'!$K:$K,'Январь 2025'!$E:$E,$A:$A),"-") -> - | G125: =IFERROR(AVERAGEIFS('Февраль 2025 '!K:K,'Февраль 2025 '!E:E,A:A),"-") -> - | H125: =IFERROR(AVERAGEIFS('Март 2025'!$K:$K,'Март 2025'!$E:$E,$A:$A),"-") -> - | I125: =IFERROR(AVERAGEIFS('Апрель 2025'!$K:$K,'Апрель 2025'!$E:$E,$A:$A),"-") -> - | J125: =IFERROR(AVERAGEIFS('Май 2025'!$K:$K,'Май 2025'!$E:$E,$A:$A),"-") -> - | K125: =IFERROR(AVERAGEIFS('Июнь 2025'!$K:$K,'Июнь 2025'!$E:$E,$A:$A),"-") -> - | L125: =IFERROR(AVERAGEIFS('Июль 2025'!$K:$K,'Июль 2025'!$E:$E,$A:$A),"-") -> - | M125: =IFERROR(AVERAGEIFS('Август 2025'!$K:$K,'Август 2025'!$E:$E,$A:$A),"-") -> - | N125: =IFERROR(AVERAGEIFS('Сентябрь 2025'!$K:$K,'Сентябрь 2025'!$E:$E,$A:$A),"-") -> - | O125: =IFERROR(AVERAGEIFS('Октябрь 2025'!$K:$K,'Октябрь 2025'!$E:$E,$A:$A),"-") -> - | P125: =IFERROR(AVERAGEIFS('Ноябрь 2025'!$K:$K,'Ноябрь 2025'!$E:$E,$A:$A),"-") -> - | Q125: =IFERROR(AVERAGEIFS('Декабрь 2025'!$K:$K,'Декабрь 2025'!$E:$E,$A:$A),"-") -> - | R125: =IFERROR(AVERAGEIFS('Январь 2026'!$K:$K,'Январь 2026'!$E:$E,$A:$A),"-") -> - | S125: =IFERROR(AVERAGEIFS('Февраль 2026'!$K:$K,'Февраль 2026'!$E:$E,$A:$A),"-") -> - | T125: =IFERROR(AVERAGEIFS('Март 2026'!$K:$K,'Март 2026'!$E:$E,$A:$A),"-") -> -
B126: =IFERROR(AVERAGEIFS('Сентябрь 2024'!$K:$K,'Сентябрь 2024'!$E:$E,$A:$A),"-") -> - | C126: =IFERROR(AVERAGEIFS('Октябрь 2024'!$K:$K,'Октябрь 2024'!$E:$E,$A:$A),"-") -> - | D126: =IFERROR(AVERAGEIFS('Ноябрь 2024'!$K:$K,'Ноябрь 2024'!$E:$E,$A:$A),"-") -> - | E126: =IFERROR(AVERAGEIFS('Декабрь 2024'!$K:$K,'Декабрь 2024'!$E:$E,$A:$A),"-") -> - | F126: =IFERROR(AVERAGEIFS('Январь 2025'!$K:$K,'Январь 2025'!$E:$E,$A:$A),"-") -> - | G126: =IFERROR(AVERAGEIFS('Февраль 2025 '!K:K,'Февраль 2025 '!E:E,A:A),"-") -> - | H126: =IFERROR(AVERAGEIFS('Март 2025'!$K:$K,'Март 2025'!$E:$E,$A:$A),"-") -> - | I126: =IFERROR(AVERAGEIFS('Апрель 2025'!$K:$K,'Апрель 2025'!$E:$E,$A:$A),"-") -> - | J126: =IFERROR(AVERAGEIFS('Май 2025'!$K:$K,'Май 2025'!$E:$E,$A:$A),"-") -> - | K126: =IFERROR(AVERAGEIFS('Июнь 2025'!$K:$K,'Июнь 2025'!$E:$E,$A:$A),"-") -> - | L126: =IFERROR(AVERAGEIFS('Июль 2025'!$K:$K,'Июль 2025'!$E:$E,$A:$A),"-") -> - | M126: =IFERROR(AVERAGEIFS('Август 2025'!$K:$K,'Август 2025'!$E:$E,$A:$A),"-") -> - | N126: =IFERROR(AVERAGEIFS('Сентябрь 2025'!$K:$K,'Сентябрь 2025'!$E:$E,$A:$A),"-") -> - | O126: =IFERROR(AVERAGEIFS('Октябрь 2025'!$K:$K,'Октябрь 2025'!$E:$E,$A:$A),"-") -> - | P126: =IFERROR(AVERAGEIFS('Ноябрь 2025'!$K:$K,'Ноябрь 2025'!$E:$E,$A:$A),"-") -> - | Q126: =IFERROR(AVERAGEIFS('Декабрь 2025'!$K:$K,'Декабрь 2025'!$E:$E,$A:$A),"-") -> - | R126: =IFERROR(AVERAGEIFS('Январь 2026'!$K:$K,'Январь 2026'!$E:$E,$A:$A),"-") -> - | S126: =IFERROR(AVERAGEIFS('Февраль 2026'!$K:$K,'Февраль 2026'!$E:$E,$A:$A),"-") -> - | T126: =IFERROR(AVERAGEIFS('Март 2026'!$K:$K,'Март 2026'!$E:$E,$A:$A),"-") -> -
B127: =IFERROR(AVERAGEIFS('Сентябрь 2024'!$K:$K,'Сентябрь 2024'!$E:$E,$A:$A),"-") -> - | C127: =IFERROR(AVERAGEIFS('Октябрь 2024'!$K:$K,'Октябрь 2024'!$E:$E,$A:$A),"-") -> - | D127: =IFERROR(AVERAGEIFS('Ноябрь 2024'!$K:$K,'Ноябрь 2024'!$E:$E,$A:$A),"-") -> - | E127: =IFERROR(AVERAGEIFS('Декабрь 2024'!$K:$K,'Декабрь 2024'!$E:$E,$A:$A),"-") -> - | F127: =IFERROR(AVERAGEIFS('Январь 2025'!$K:$K,'Январь 2025'!$E:$E,$A:$A),"-") -> - | G127: =IFERROR(AVERAGEIFS('Февраль 2025 '!K:K,'Февраль 2025 '!E:E,A:A),"-") -> - | H127: =IFERROR(AVERAGEIFS('Март 2025'!$K:$K,'Март 2025'!$E:$E,$A:$A),"-") -> - | I127: =IFERROR(AVERAGEIFS('Апрель 2025'!$K:$K,'Апрель 2025'!$E:$E,$A:$A),"-") -> - | J127: =IFERROR(AVERAGEIFS('Май 2025'!$K:$K,'Май 2025'!$E:$E,$A:$A),"-") -> - | K127: =IFERROR(AVERAGEIFS('Июнь 2025'!$K:$K,'Июнь 2025'!$E:$E,$A:$A),"-") -> - | L127: =IFERROR(AVERAGEIFS('Июль 2025'!$K:$K,'Июль 2025'!$E:$E,$A:$A),"-") -> - | M127: =IFERROR(AVERAGEIFS('Август 2025'!$K:$K,'Август 2025'!$E:$E,$A:$A),"-") -> - | N127: =IFERROR(AVERAGEIFS('Сентябрь 2025'!$K:$K,'Сентябрь 2025'!$E:$E,$A:$A),"-") -> - | O127: =IFERROR(AVERAGEIFS('Октябрь 2025'!$K:$K,'Октябрь 2025'!$E:$E,$A:$A),"-") -> - | P127: =IFERROR(AVERAGEIFS('Ноябрь 2025'!$K:$K,'Ноябрь 2025'!$E:$E,$A:$A),"-") -> - | Q127: =IFERROR(AVERAGEIFS('Декабрь 2025'!$K:$K,'Декабрь 2025'!$E:$E,$A:$A),"-") -> - | R127: =IFERROR(AVERAGEIFS('Январь 2026'!$K:$K,'Январь 2026'!$E:$E,$A:$A),"-") -> - | S127: =IFERROR(AVERAGEIFS('Февраль 2026'!$K:$K,'Февраль 2026'!$E:$E,$A:$A),"-") -> - | T127: =IFERROR(AVERAGEIFS('Март 2026'!$K:$K,'Март 2026'!$E:$E,$A:$A),"-") -> -
B128: =IFERROR(AVERAGEIFS('Сентябрь 2024'!$K:$K,'Сентябрь 2024'!$E:$E,$A:$A),"-") -> - | C128: =IFERROR(AVERAGEIFS('Октябрь 2024'!$K:$K,'Октябрь 2024'!$E:$E,$A:$A),"-") -> - | D128: =IFERROR(AVERAGEIFS('Ноябрь 2024'!$K:$K,'Ноябрь 2024'!$E:$E,$A:$A),"-") -> - | E128: =IFERROR(AVERAGEIFS('Декабрь 2024'!$K:$K,'Декабрь 2024'!$E:$E,$A:$A),"-") -> - | F128: =IFERROR(AVERAGEIFS('Январь 2025'!$K:$K,'Январь 2025'!$E:$E,$A:$A),"-") -> - | G128: =IFERROR(AVERAGEIFS('Февраль 2025 '!K:K,'Февраль 2025 '!E:E,A:A),"-") -> - | H128: =IFERROR(AVERAGEIFS('Март 2025'!$K:$K,'Март 2025'!$E:$E,$A:$A),"-") -> - | I128: =IFERROR(AVERAGEIFS('Апрель 2025'!$K:$K,'Апрель 2025'!$E:$E,$A:$A),"-") -> - | J128: =IFERROR(AVERAGEIFS('Май 2025'!$K:$K,'Май 2025'!$E:$E,$A:$A),"-") -> - | K128: =IFERROR(AVERAGEIFS('Июнь 2025'!$K:$K,'Июнь 2025'!$E:$E,$A:$A),"-") -> - | L128: =IFERROR(AVERAGEIFS('Июль 2025'!$K:$K,'Июль 2025'!$E:$E,$A:$A),"-") -> - | M128: =IFERROR(AVERAGEIFS('Август 2025'!$K:$K,'Август 2025'!$E:$E,$A:$A),"-") -> - | N128: =IFERROR(AVERAGEIFS('Сентябрь 2025'!$K:$K,'Сентябрь 2025'!$E:$E,$A:$A),"-") -> - | O128: =IFERROR(AVERAGEIFS('Октябрь 2025'!$K:$K,'Октябрь 2025'!$E:$E,$A:$A),"-") -> - | P128: =IFERROR(AVERAGEIFS('Ноябрь 2025'!$K:$K,'Ноябрь 2025'!$E:$E,$A:$A),"-") -> - | Q128: =IFERROR(AVERAGEIFS('Декабрь 2025'!$K:$K,'Декабрь 2025'!$E:$E,$A:$A),"-") -> - | R128: =IFERROR(AVERAGEIFS('Январь 2026'!$K:$K,'Январь 2026'!$E:$E,$A:$A),"-") -> - | S128: =IFERROR(AVERAGEIFS('Февраль 2026'!$K:$K,'Февраль 2026'!$E:$E,$A:$A),"-") -> - | T128: =IFERROR(AVERAGEIFS('Март 2026'!$K:$K,'Март 2026'!$E:$E,$A:$A),"-") -> -
B129: =IFERROR(AVERAGEIFS('Сентябрь 2024'!$K:$K,'Сентябрь 2024'!$E:$E,$A:$A),"-") -> - | C129: =IFERROR(AVERAGEIFS('Октябрь 2024'!$K:$K,'Октябрь 2024'!$E:$E,$A:$A),"-") -> - | D129: =IFERROR(AVERAGEIFS('Ноябрь 2024'!$K:$K,'Ноябрь 2024'!$E:$E,$A:$A),"-") -> - | E129: =IFERROR(AVERAGEIFS('Декабрь 2024'!$K:$K,'Декабрь 2024'!$E:$E,$A:$A),"-") -> - | F129: =IFERROR(AVERAGEIFS('Январь 2025'!$K:$K,'Январь 2025'!$E:$E,$A:$A),"-") -> - | G129: =IFERROR(AVERAGEIFS('Февраль 2025 '!K:K,'Февраль 2025 '!E:E,A:A),"-") -> - | H129: =IFERROR(AVERAGEIFS('Март 2025'!$K:$K,'Март 2025'!$E:$E,$A:$A),"-") -> - | I129: =IFERROR(AVERAGEIFS('Апрель 2025'!$K:$K,'Апрель 2025'!$E:$E,$A:$A),"-") -> - | J129: =IFERROR(AVERAGEIFS('Май 2025'!$K:$K,'Май 2025'!$E:$E,$A:$A),"-") -> - | K129: =IFERROR(AVERAGEIFS('Июнь 2025'!$K:$K,'Июнь 2025'!$E:$E,$A:$A),"-") -> - | L129: =IFERROR(AVERAGEIFS('Июль 2025'!$K:$K,'Июль 2025'!$E:$E,$A:$A),"-") -> - | M129: =IFERROR(AVERAGEIFS('Август 2025'!$K:$K,'Август 2025'!$E:$E,$A:$A),"-") -> - | N129: =IFERROR(AVERAGEIFS('Сентябрь 2025'!$K:$K,'Сентябрь 2025'!$E:$E,$A:$A),"-") -> - | O129: =IFERROR(AVERAGEIFS('Октябрь 2025'!$K:$K,'Октябрь 2025'!$E:$E,$A:$A),"-") -> - | P129: =IFERROR(AVERAGEIFS('Ноябрь 2025'!$K:$K,'Ноябрь 2025'!$E:$E,$A:$A),"-") -> - | Q129: =IFERROR(AVERAGEIFS('Декабрь 2025'!$K:$K,'Декабрь 2025'!$E:$E,$A:$A),"-") -> - | R129: =IFERROR(AVERAGEIFS('Январь 2026'!$K:$K,'Январь 2026'!$E:$E,$A:$A),"-") -> - | S129: =IFERROR(AVERAGEIFS('Февраль 2026'!$K:$K,'Февраль 2026'!$E:$E,$A:$A),"-") -> - | T129: =IFERROR(AVERAGEIFS('Март 2026'!$K:$K,'Март 2026'!$E:$E,$A:$A),"-") -> -
B130: =IFERROR(AVERAGEIFS('Сентябрь 2024'!$K:$K,'Сентябрь 2024'!$E:$E,$A:$A),"-") -> - | C130: =IFERROR(AVERAGEIFS('Октябрь 2024'!$K:$K,'Октябрь 2024'!$E:$E,$A:$A),"-") -> - | D130: =IFERROR(AVERAGEIFS('Ноябрь 2024'!$K:$K,'Ноябрь 2024'!$E:$E,$A:$A),"-") -> - | E130: =IFERROR(AVERAGEIFS('Декабрь 2024'!$K:$K,'Декабрь 2024'!$E:$E,$A:$A),"-") -> - | F130: =IFERROR(AVERAGEIFS('Январь 2025'!$K:$K,'Январь 2025'!$E:$E,$A:$A),"-") -> - | G130: =IFERROR(AVERAGEIFS('Февраль 2025 '!K:K,'Февраль 2025 '!E:E,A:A),"-") -> - | H130: =IFERROR(AVERAGEIFS('Март 2025'!$K:$K,'Март 2025'!$E:$E,$A:$A),"-") -> - | I130: =IFERROR(AVERAGEIFS('Апрель 2025'!$K:$K,'Апрель 2025'!$E:$E,$A:$A),"-") -> - | J130: =IFERROR(AVERAGEIFS('Май 2025'!$K:$K,'Май 2025'!$E:$E,$A:$A),"-") -> - | K130: =IFERROR(AVERAGEIFS('Июнь 2025'!$K:$K,'Июнь 2025'!$E:$E,$A:$A),"-") -> - | L130: =IFERROR(AVERAGEIFS('Июль 2025'!$K:$K,'Июль 2025'!$E:$E,$A:$A),"-") -> - | M130: =IFERROR(AVERAGEIFS('Август 2025'!$K:$K,'Август 2025'!$E:$E,$A:$A),"-") -> - | N130: =IFERROR(AVERAGEIFS('Сентябрь 2025'!$K:$K,'Сентябрь 2025'!$E:$E,$A:$A),"-") -> - | O130: =IFERROR(AVERAGEIFS('Октябрь 2025'!$K:$K,'Октябрь 2025'!$E:$E,$A:$A),"-") -> - | P130: =IFERROR(AVERAGEIFS('Ноябрь 2025'!$K:$K,'Ноябрь 2025'!$E:$E,$A:$A),"-") -> - | Q130: =IFERROR(AVERAGEIFS('Декабрь 2025'!$K:$K,'Декабрь 2025'!$E:$E,$A:$A),"-") -> - | R130: =IFERROR(AVERAGEIFS('Январь 2026'!$K:$K,'Январь 2026'!$E:$E,$A:$A),"-") -> - | S130: =IFERROR(AVERAGEIFS('Февраль 2026'!$K:$K,'Февраль 2026'!$E:$E,$A:$A),"-") -> - | T130: =IFERROR(AVERAGEIFS('Март 2026'!$K:$K,'Март 2026'!$E:$E,$A:$A),"-") -> -
B131: =IFERROR(AVERAGEIFS('Сентябрь 2024'!$K:$K,'Сентябрь 2024'!$E:$E,$A:$A),"-") -> - | C131: =IFERROR(AVERAGEIFS('Октябрь 2024'!$K:$K,'Октябрь 2024'!$E:$E,$A:$A),"-") -> - | D131: =IFERROR(AVERAGEIFS('Ноябрь 2024'!$K:$K,'Ноябрь 2024'!$E:$E,$A:$A),"-") -> - | E131: =IFERROR(AVERAGEIFS('Декабрь 2024'!$K:$K,'Декабрь 2024'!$E:$E,$A:$A),"-") -> - | F131: =IFERROR(AVERAGEIFS('Январь 2025'!$K:$K,'Январь 2025'!$E:$E,$A:$A),"-") -> - | G131: =IFERROR(AVERAGEIFS('Февраль 2025 '!K:K,'Февраль 2025 '!E:E,A:A),"-") -> - | H131: =IFERROR(AVERAGEIFS('Март 2025'!$K:$K,'Март 2025'!$E:$E,$A:$A),"-") -> - | I131: =IFERROR(AVERAGEIFS('Апрель 2025'!$K:$K,'Апрель 2025'!$E:$E,$A:$A),"-") -> - | J131: =IFERROR(AVERAGEIFS('Май 2025'!$K:$K,'Май 2025'!$E:$E,$A:$A),"-") -> - | K131: =IFERROR(AVERAGEIFS('Июнь 2025'!$K:$K,'Июнь 2025'!$E:$E,$A:$A),"-") -> - | L131: =IFERROR(AVERAGEIFS('Июль 2025'!$K:$K,'Июль 2025'!$E:$E,$A:$A),"-") -> - | M131: =IFERROR(AVERAGEIFS('Август 2025'!$K:$K,'Август 2025'!$E:$E,$A:$A),"-") -> - | N131: =IFERROR(AVERAGEIFS('Сентябрь 2025'!$K:$K,'Сентябрь 2025'!$E:$E,$A:$A),"-") -> - | O131: =IFERROR(AVERAGEIFS('Октябрь 2025'!$K:$K,'Октябрь 2025'!$E:$E,$A:$A),"-") -> - | P131: =IFERROR(AVERAGEIFS('Ноябрь 2025'!$K:$K,'Ноябрь 2025'!$E:$E,$A:$A),"-") -> - | Q131: =IFERROR(AVERAGEIFS('Декабрь 2025'!$K:$K,'Декабрь 2025'!$E:$E,$A:$A),"-") -> - | R131: =IFERROR(AVERAGEIFS('Январь 2026'!$K:$K,'Январь 2026'!$E:$E,$A:$A),"-") -> - | S131: =IFERROR(AVERAGEIFS('Февраль 2026'!$K:$K,'Февраль 2026'!$E:$E,$A:$A),"-") -> - | T131: =IFERROR(AVERAGEIFS('Март 2026'!$K:$K,'Март 2026'!$E:$E,$A:$A),"-") -> -

Sheet Июнь 2026
A1: пп | B1: Дата выпуска продукции | C1: курс | D1: № ЗП | E1: Продукт | F1: Вес готового продукта | G1: Израсходовано по факту | H1: Израсходовано по факту Polyether Polyol Puranol D220, LE-220A Пропиленгликоль | I1: Потери, кг | J1: % потерь | K1: СС 1С на дату выпуска, EUR | L1: % пропиленгликоля в составе + полиол | M1: СС КГ, РУБ, Б/НДС | N1: СС Факт , EUR, Б/НДС | O1: СС Партии, EUR, Б/НДС | P1: СС Партии, РУБ, Б/НДС | R1: Примечание
B2: 46174 | C2: =VLOOKUP(B:B,'Курс валют'!A:D,4,0) -> 82.6369 | D2: 01F2601 | E2: Отвердитель Starkbond 521C 3.0 бочка 200кг | F2: 800 | G2: 805 | H2: 0 | I2: =G2-F2 -> 5 | J2: =I2/F2*100 -> 0.625 | K2: 1.85 | L2: =H2/F2*100 -> 0 | M2: =P2/F2 -> 152.87826 | N2: =(F2*K2-H2*3.04)/F2 -> 1.85 | O2: =N2*F2 -> 1480 | P2: =O2*C2 -> 122302.61
B3: 46174 | C3: =VLOOKUP(B:B,'Курс валют'!A:D,4,0) -> 82.6369 | D3: 01F2602 | E3: Отвердитель Starkbond 521C 3.0 бочка 200кг | F3: 800 | G3: 805 | H3: 0 | I3: =G3-F3 -> 5 | J3: =I3/F3*100 -> 0.625 | K3: 1.84 | L3: =H3/F3*100 -> 0 | M3: =P3/F3 -> 152.0519 | N3: =(F3*K3-H3*30.4)/F3 -> 1.84 | O3: =N3*F3 -> 1472 | P3: =O3*C3 -> 121641.52
B4: 46174 | C4: =VLOOKUP(B:B,'Курс валют'!A:D,4,0) -> 82.6369 | D4: 01F2603 | E4: Отвердитель Starkbond 521C 3.0 бочка 200кг | F4: 800 | G4: 805 | H4: 0 | I4: =G4-F4 -> 5 | J4: =I4/F4*100 -> 0.625 | K4: 1.84 | L4: =H4/F4*100 -> 0 | M4: =P4/F4 -> 152.0519 | N4: =(F4*K4-H4*30.4)/F4 -> 1.84 | O4: =N4*F4 -> 1472 | P4: =O4*C4 -> 121641.52
B5: 46174 | C5: =VLOOKUP(B:B,'Курс валют'!A:D,4,0) -> 82.6369 | D5: 01F2604 | E5: Отвердитель Starkbond 521C 3.0 бочка 200кг | F5: 800 | G5: 805 | H5: 0 | I5: =G5-F5 -> 5 | J5: =I5/F5*100 -> 0.625 | K5: 1.84 | L5: =H5/F5*100 -> 0 | M5: =P5/F5 -> 152.0519 | N5: =(F5*K5-H5*30.4)/F5 -> 1.84 | O5: =N5*F5 -> 1472 | P5: =O5*C5 -> 121641.52
B6: 46174 | C6: =VLOOKUP(B:B,'Курс валют'!A:D,4,0) -> 82.6369 | D6: 01F2605 | E6: Отвердитель Starkbond 521C 3.0 бочка 200кг | F6: 800 | G6: 805 | H6: 0 | I6: =G6-F6 -> 5 | J6: =I6/F6*100 -> 0.625 | K6: 1.83 | L6: =H6/F6*100 -> 0 | M6: =P6/F6 -> 151.22553 | N6: =(F6*K6-H6*30.4)/F6 -> 1.83 | O6: =N6*F6 -> 1464 | P6: =O6*C6 -> 120980.42
B7: 46174 | C7: =VLOOKUP(B:B,'Курс валют'!A:D,4,0) -> 82.6369 | D7: 01F2606 | E7: Отвердитель Starkbond 521C 3.0 бочка 200кг | F7: 800 | G7: 805 | H7: 0 | I7: =G7-F7 -> 5 | J7: =I7/F7*100 -> 0.625 | K7: 1.84 | L7: =H7/F7*100 -> 0 | M7: =P7/F7 -> 152.0519 | N7: =(F7*K7-H7*30.4)/F7 -> 1.84 | O7: =N7*F7 -> 1472 | P7: =O7*C7 -> 121641.52
B8: 46174 | C8: =VLOOKUP(B:B,'Курс валют'!A:D,4,0) -> 82.6369 | D8: 01F2607 | E8: Отвердитель Starkbond 521C 3.0 бочка 200кг | F8: 800 | G8: 805 | H8: 0 | I8: =G8-F8 -> 5 | J8: =I8/F8*100 -> 0.625 | K8: 1.83 | L8: =H8/F8*100 -> 0 | M8: =P8/F8 -> 151.22553 | N8: =(F8*K8-H8*30.4)/F8 -> 1.83 | O8: =N8*F8 -> 1464 | P8: =O8*C8 -> 120980.42
B9: 46174 | C9: =VLOOKUP(B:B,'Курс валют'!A:D,4,0) -> 82.6369 | D9: 01F2608 | E9: Отвердитель Starkbond 521C 3.0 бочка 200кг | F9: 800 | G9: 805 | H9: 0 | I9: =G9-F9 -> 5 | J9: =I9/F9*100 -> 0.625 | K9: 1.84 | L9: =H9/F9*100 -> 0 | M9: =P9/F9 -> 152.0519 | N9: =(F9*K9-H9*30.4)/F9 -> 1.84 | O9: =N9*F9 -> 1472 | P9: =O9*C9 -> 121641.52
B10: 46174 | C10: =VLOOKUP(B:B,'Курс валют'!A:D,4,0) -> 82.6369 | D10: 01F2609 | E10: Отвердитель Starkbond 521C 3.0 бочка 200кг | F10: 800 | G10: 805 | H10: 0 | I10: =G10-F10 -> 5 | J10: =I10/F10*100 -> 0.625 | K10: 1.84 | L10: =H10/F10*100 -> 0 | M10: =P10/F10 -> 152.0519 | N10: =(F10*K10-H10*30.4)/F10 -> 1.84 | O10: =N10*F10 -> 1472 | P10: =O10*C10 -> 121641.52
B11: 46174 | C11: =VLOOKUP(B:B,'Курс валют'!A:D,4,0) -> 82.6369 | D11: 01F2610 | E11: Отвердитель Starkbond 521C 3.0 бочка 200кг | F11: 800 | G11: 805 | H11: 0 | I11: =G11-F11 -> 5 | J11: =I11/F11*100 -> 0.625 | K11: 1.83 | L11: =H11/F11*100 -> 0 | M11: =P11/F11 -> 151.22553 | N11: =(F11*K11-H11*30.4)/F11 -> 1.83 | O11: =N11*F11 -> 1464 | P11: =O11*C11 -> 120980.42
B12: 46174 | C12: =VLOOKUP(B:B,'Курс валют'!A:D,4,0) -> 82.6369 | D12: 01F26R11 | E12: Клей Starkbond 745/41 А (бочка 200 кг) | F12: 2000 | G12: 2033.55 | H12: 0 | I12: =G12-F12 -> 33.55 | J12: =I12/F12*100 -> 1.6775 | K12: 2.43 | L12: =H12/F12*100 -> 0 | M12: =P12/F12 -> 200.80767 | N12: =(F12*K12-H12*30.4)/F12 -> 2.43 | O12: =N12*F12 -> 4860 | P12: =O12*C12 -> 401615.33
B13: 46175 | C13: =VLOOKUP(B:B,'Курс валют'!A:D,4,0) -> 86.2499 | D13: 02F2601 | E13: Отвердитель Starkbond 521C 11.0 бочка 200кг | F13: 800 | G13: 806.14 | H13: 0 | I13: =G13-F13 -> 6.14 | J13: =I13/F13*100 -> 0.7675 | K13: 1.93 | L13: =H13/F13*100 -> 0 | M13: =P13/F13 -> 166.46231 | N13: =(F13*K13-H13*3.04)/F13 -> 1.93 | O13: =N13*F13 -> 1544 | P13: =O13*C13 -> 133169.85
B14: 46175 | C14: =VLOOKUP(B:B,'Курс валют'!A:D,4,0) -> 86.2499 | D14: 02F2602 | E14: Отвердитель Starkbond 521C 11.0 бочка 200кг | F14: 800 | G14: 806.14 | H14: 0 | I14: =G14-F14 -> 6.14 | J14: =I14/F14*100 -> 0.7675 | K14: 1.92 | L14: =H14/F14*100 -> 0 | M14: =P14/F14 -> 165.59981 | N14: =(F14*K14-H14*30.4)/F14 -> 1.92 | O14: =N14*F14 -> 1536 | P14: =O14*C14 -> 132479.85
B15: 46175 | C15: =VLOOKUP(B:B,'Курс валют'!A:D,4,0) -> 86.2499 | D15: 02F2603 | E15: Отвердитель Starkbond 521C 11.0 бочка 200кг | F15: 800 | G15: 806.14 | H15: 0 | I15: =G15-F15 -> 6.14 | J15: =I15/F15*100 -> 0.7675 | K15: 1.92 | L15: =H15/F15*100 -> 0 | M15: =P15/F15 -> 165.59981 | N15: =(F15*K15-H15*30.4)/F15 -> 1.92 | O15: =N15*F15 -> 1536 | P15: =O15*C15 -> 132479.85
B16: 46175 | C16: =VLOOKUP(B:B,'Курс валют'!A:D,4,0) -> 86.2499 | D16: 02F2604 | E16: Отвердитель Starkbond 521C 11.0 бочка 200кг | F16: 800 | G16: 806.14 | H16: 0 | I16: =G16-F16 -> 6.14 | J16: =I16/F16*100 -> 0.7675 | K16: 1.93 | L16: =H16/F16*100 -> 0 | M16: =P16/F16 -> 166.46231 | N16: =(F16*K16-H16*30.4)/F16 -> 1.93 | O16: =N16*F16 -> 1544 | P16: =O16*C16 -> 133169.85
B17: 46175 | C17: =VLOOKUP(B:B,'Курс валют'!A:D,4,0) -> 86.2499 | D17: 02F2605 | E17: Отвердитель Starkbond 521C 11.0 бочка 200кг | F17: 800 | G17: 806.14 | H17: 0 | I17: =G17-F17 -> 6.14 | J17: =I17/F17*100 -> 0.7675 | K17: 1.93 | L17: =H17/F17*100 -> 0 | M17: =P17/F17 -> 166.46231 | N17: =(F17*K17-H17*30.4)/F17 -> 1.93 | O17: =N17*F17 -> 1544 | P17: =O17*C17 -> 133169.85
B18: 46175 | C18: =VLOOKUP(B:B,'Курс валют'!A:D,4,0) -> 86.2499 | D18: 02F2606 | E18: Отвердитель Starkbond 521C 11.0 бочка 200кг | F18: 800 | G18: 806.14 | H18: 0 | I18: =G18-F18 -> 6.14 | J18: =I18/F18*100 -> 0.7675 | K18: 1.91 | L18: =H18/F18*100 -> 0 | M18: =P18/F18 -> 164.73731 | N18: =(F18*K18-H18*30.4)/F18 -> 1.91 | O18: =N18*F18 -> 1528 | P18: =O18*C18 -> 131789.85
B19: 46175 | C19: =VLOOKUP(B:B,'Курс валют'!A:D,4,0) -> 86.2499 | D19: 02F2607 | E19: Отвердитель Starkbond 521C 11.0 бочка 200кг | F19: 800 | G19: 806.14 | H19: 0 | I19: =G19-F19 -> 6.14 | J19: =I19/F19*100 -> 0.7675 | K19: 1.91 | L19: =H19/F19*100 -> 0 | M19: =P19/F19 -> 164.73731 | N19: =(F19*K19-H19*30.4)/F19 -> 1.91 | O19: =N19*F19 -> 1528 | P19: =O19*C19 -> 131789.85
B20: 46175 | C20: =VLOOKUP(B:B,'Курс валют'!A:D,4,0) -> 86.2499 | D20: 02F2608 | E20: Отвердитель Starkbond 521C 11.0 бочка 200кг | F20: 800 | G20: 806.14 | H20: 0 | I20: =G20-F20 -> 6.14 | J20: =I20/F20*100 -> 0.7675 | K20: 1.91 | L20: =H20/F20*100 -> 0 | M20: =P20/F20 -> 164.73731 | N20: =(F20*K20-H20*30.4)/F20 -> 1.91 | O20: =N20*F20 -> 1528 | P20: =O20*C20 -> 131789.85
B21: 46175 | C21: =VLOOKUP(B:B,'Курс валют'!A:D,4,0) -> 86.2499 | D21: 02F26R11 | E21: Клей Starkbond 745/41 А (бочка 200 кг) | F21: 2000 | G21: 2033.55 | H21: 0 | I21: =G21-F21 -> 33.55 | J21: =I21/F21*100 -> 1.6775 | K21: 2.44 | L21: =H21/F21*100 -> 0 | M21: =P21/F21 -> 210.44976 | N21: =(F21*K21-H21*30.4)/F21 -> 2.44 | O21: =N21*F21 -> 4880 | P21: =O21*C21 -> 420899.51
B22: 46175 | C22: =VLOOKUP(B:B,'Курс валют'!A:D,4,0) -> 86.2499 | D22: 02F2609 | E22: Отвердитель Starkbond 521C 11.0 бочка 200кг | F22: 800 | G22: 806.14 | H22: 0 | I22: =G22-F22 -> 6.14 | J22: =I22/F22*100 -> 0.7675 | K22: 1.91 | L22: =H22/F22*100 -> 0 | M22: =P22/F22 -> 164.73731 | N22: =(F22*K22-H22*30.4)/F22 -> 1.91 | O22: =N22*F22 -> 1528 | P22: =O22*C22 -> 131789.85
B23: 46175 | C23: =VLOOKUP(B:B,'Курс валют'!A:D,4,0) -> 86.2499 | D23: 02F2610 | E23: Отвердитель Starkbond 521C 11.0 бочка 200кг | F23: 800 | G23: 806.14 | H23: 0 | I23: =G23-F23 -> 6.14 | J23: =I23/F23*100 -> 0.7675 | K23: 1.92 | L23: =H23/F23*100 -> 0 | M23: =P23/F23 -> 165.59981 | N23: =(F23*K23-H23*30.4)/F23 -> 1.92 | O23: =N23*F23 -> 1536 | P23: =O23*C23 -> 132479.85
B24: 46176 | C24: =VLOOKUP(B:B,'Курс валют'!A:D,4,0) -> 84.6096 | D24: 03F2601 | E24: Отвердитель Starkbond 521C 11.0 бочка 200кг | F24: 800 | G24: 807.54 | H24: 0 | I24: =G24-F24 -> 7.54 | J24: =I24/F24*100 -> 0.9425 | K24: 1.92 | L24: =H24/F24*100 -> 0 | M24: =P24/F24 -> 162.45043 | N24: =(F24*K24-H24*3.04)/F24 -> 1.92 | O24: =N24*F24 -> 1536 | P24: =O24*C24 -> 129960.35
B25: 46176 | C25: =VLOOKUP(B:B,'Курс валют'!A:D,4,0) -> 84.6096 | D25: 03F2602 | E25: Отвердитель Starkbond 521C 11.0 бочка 200кг | F25: 800 | G25: 807.54 | H25: 0 | I25: 2.5 | J25: =I25/F25*100 -> 0.3125 | K25: 1.92 | L25: =H25/F25*100 -> 0 | M25: =P25/F25 -> 162.45043 | N25: =(F25*K25-H25*3.04)/F25 -> 1.92 | O25: =N25*F25 -> 1536 | P25: =O25*C25 -> 129960.35
B26: 46176 | C26: =VLOOKUP(B:B,'Курс валют'!A:D,4,0) -> 84.6096 | D26: 03F2603 | E26: Отвердитель Starkbond 521C 11.0 бочка 200кг | F26: 800 | G26: 807.54 | H26: 0 | I26: =G26-F26 -> 7.54 | J26: =I26/F26*100 -> 0.9425 | K26: 1.92 | L26: =H26/F26*100 -> 0 | M26: =P26/F26 -> 162.45043 | N26: =(F26*K26-H26*3.04)/F26 -> 1.92 | O26: =N26*F26 -> 1536 | P26: =O26*C26 -> 129960.35
B27: 46176 | C27: =VLOOKUP(B:B,'Курс валют'!A:D,4,0) -> 84.6096 | D27: 03F26R11 | E27: Клей Starkbond 2014 бочка 225кг | F27: 1800 | G27: 1841.1 | H27: 0 | I27: =G27-F27 -> 41.1 | J27: =I27/F27*100 -> 2.2833333 | L27: =H27/F27*100 -> 0 | M27: =P27/F27 -> 0 | N27: =(F27*K27-H27*3.04)/F27 -> 0 | O27: =N27*F27 -> 0 | P27: =O27*C27 -> 0 | R27: 2014 (1800) Тестовый Изоцианат COSMONATE PH
B28: 46176 | C28: =VLOOKUP(B:B,'Курс валют'!A:D,4,0) -> 84.6096 | D28: 03F2604 | E28: Отвердитель Starkbond 521C 11.0 бочка 200кг | F28: 800 | G28: 807.54 | H28: 0 | I28: =G28-F28 -> 7.54 | J28: =I28/F28*100 -> 0.9425 | K28: 1.92 | L28: =H28/F28*100 -> 0 | M28: =P28/F28 -> 162.45043 | N28: =(F28*K28-H28*3.04)/F28 -> 1.92 | O28: =N28*F28 -> 1536 | P28: =O28*C28 -> 129960.35
B29: 46176 | C29: =VLOOKUP(B:B,'Курс валют'!A:D,4,0) -> 84.6096 | D29: 03F2605 | E29: Отвердитель Starkbond 521C 11.0 бочка 200кг | F29: 800 | G29: 807.54 | H29: 0 | I29: =G29-F29 -> 7.54 | J29: =I29/F29*100 -> 0.9425 | K29: 1.92 | L29: =H29/F29*100 -> 0 | M29: =P29/F29 -> 162.45043 | N29: =(F29*K29-H29*3.04)/F29 -> 1.92 | O29: =N29*F29 -> 1536 | P29: =O29*C29 -> 129960.35
B30: 46176 | C30: =VLOOKUP(B:B,'Курс валют'!A:D,4,0) -> 84.6096 | D30: 03F2606 | E30: Отвердитель Starkbond 521C 11.0 бочка 200кг | F30: 800 | G30: 807.54 | H30: 0 | I30: =G30-F30 -> 7.54 | J30: =I30/F30*100 -> 0.9425 | K30: 1.92 | L30: =H30/F30*100 -> 0 | M30: =P30/F30 -> 162.45043 | N30: =(F30*K30-H30*3.04)/F30 -> 1.92 | O30: =N30*F30 -> 1536 | P30: =O30*C30 -> 129960.35
B31: 46176 | C31: =VLOOKUP(B:B,'Курс валют'!A:D,4,0) -> 84.6096 | D31: 03F2607 | E31: Отвердитель Starkbond 521C 11.0 бочка 200кг | F31: 800 | G31: 807.54 | H31: 0 | I31: =G31-F31 -> 7.54 | J31: =I31/F31*100 -> 0.9425 | K31: 1.92 | L31: =H31/F31*100 -> 0 | M31: =P31/F31 -> 162.45043 | N31: =(F31*K31-H31*3.04)/F31 -> 1.92 | O31: =N31*F31 -> 1536 | P31: =O31*C31 -> 129960.35
B32: 46176 | C32: =VLOOKUP(B:B,'Курс валют'!A:D,4,0) -> 84.6096 | D32: 03F2608 | E32: Отвердитель Starkbond 521C 11.0 бочка 200кг | F32: 800 | G32: 807.54 | H32: 0 | I32: =G32-F32 -> 7.54 | J32: =I32/F32*100 -> 0.9425 | K32: 1.92 | L32: =H32/F32*100 -> 0 | M32: =P32/F32 -> 162.45043 | N32: =(F32*K32-H32*3.04)/F32 -> 1.92 | O32: =N32*F32 -> 1536 | P32: =O32*C32 -> 129960.35
B33: 46176 | C33: =VLOOKUP(B:B,'Курс валют'!A:D,4,0) -> 84.6096 | D33: 03F2609 | E33: Отвердитель Starkbond 521C 11.0 бочка 200кг | F33: 800 | G33: 807.54 | H33: 0 | I33: =G33-F33 -> 7.54 | J33: =I33/F33*100 -> 0.9425 | K33: 1.92 | L33: =H33/F33*100 -> 0 | M33: =P33/F33 -> 162.45043 | N33: =(F33*K33-H33*3.04)/F33 -> 1.92 | O33: =N33*F33 -> 1536 | P33: =O33*C33 -> 129960.35
B34: 46176 | C34: =VLOOKUP(B:B,'Курс валют'!A:D,4,0) -> 84.6096 | D34: 03F2610 | E34: Отвердитель Starkbond 521C 11.0 бочка 200кг | F34: 800 | G34: 807.54 | H34: 0 | I34: =G34-F34 -> 7.54 | J34: =I34/F34*100 -> 0.9425 | K34: 1.92 | L34: =H34/F34*100 -> 0 | M34: =P34/F34 -> 162.45043 | N34: =(F34*K34-H34*3.04)/F34 -> 1.92 | O34: =N34*F34 -> 1536 | P34: =O34*C34 -> 129960.35
B35: 46177 | C35: =VLOOKUP(B:B,'Курс валют'!A:D,4,0) -> 85.1243 | D35: 04F2601 | E35: Отвердитель Starkbond 521C 10.0 бочка 200кг | F35: 800 | G35: 806.62 | H35: 0 | I35: =G35-F35 -> 6.62 | J35: =I35/F35*100 -> 0.8275 | K35: 1.9 | L35: =H35/F35*100 -> 0 | M35: =P35/F35 -> 161.73617 | N35: =(F35*K35-H35*3.04)/F35 -> 1.9 | O35: =N35*F35 -> 1520 | P35: =O35*C35 -> 129388.94
B36: 46177 | C36: =VLOOKUP(B:B,'Курс валют'!A:D,4,0) -> 85.1243 | D36: 04F2602 | E36: Отвердитель Starkbond 521C 10.0 бочка 200кг | F36: 800 | G36: 806.62 | H36: 0 | I36: =G36-F36 -> 6.62 | J36: =I36/F36*100 -> 0.8275 | K36: 1.89 | L36: =H36/F36*100 -> 0 | M36: =P36/F36 -> 160.88493 | N36: =(F36*K36-H36*3.04)/F36 -> 1.89 | O36: =N36*F36 -> 1512 | P36: =O36*C36 -> 128707.94
B37: 46177 | C37: =VLOOKUP(B:B,'Курс валют'!A:D,4,0) -> 85.1243 | D37: 04F2603 | E37: Отвердитель Starkbond 521C 10.0 бочка 200кг | F37: 800 | G37: 806.62 | H37: 0 | I37: =G37-F37 -> 6.62 | J37: =I37/F37*100 -> 0.8275 | K37: 1.89 | L37: =H37/F37*100 -> 0 | M37: =P37/F37 -> 160.88493 | N37: =(F37*K37-H37*22.5)/F37 -> 1.89 | O37: =N37*F37 -> 1512 | P37: =O37*C37 -> 128707.94
B38: 46177 | C38: =VLOOKUP(B:B,'Курс валют'!A:D,4,0) -> 85.1243 | D38: 04F2604 | E38: Отвердитель Starkbond 521C 10.0 бочка 200кг | F38: 800 | G38: 806.62 | H38: 0 | I38: =G38-F38 -> 6.62 | J38: =I38/F38*100 -> 0.8275 | K38: 1.89 | L38: =H38/F38*100 -> 0 | M38: =P38/F38 -> 160.88493 | N38: =(F38*K38-H38*3.04)/F38 -> 1.89 | O38: =N38*F38 -> 1512 | P38: =O38*C38 -> 128707.94
B39: 46177 | C39: =VLOOKUP(B:B,'Курс валют'!A:D,4,0) -> 85.1243 | D39: 04F2605 | E39: Отвердитель Starkbond 521C 10.0 бочка 200кг | F39: 800 | G39: 806.62 | H39: 0 | I39: =G39-F39 -> 6.62 | J39: =I39/F39*100 -> 0.8275 | K39: 1.9 | L39: =H39/F39*100 -> 0 | M39: =P39/F39 -> 161.73617 | N39: =(F39*K39-H39*3.04)/F39 -> 1.9 | O39: =N39*F39 -> 1520 | P39: =O39*C39 -> 129388.94
B40: 46177 | C40: =VLOOKUP(B:B,'Курс валют'!A:D,4,0) -> 85.1243 | D40: 13А2609 | E40: Отвердитель Starkbond 521C 11.0 ведро 11кг | F40: 99 | G40: 99 | H40: 0 | I40: =G40-F40 -> 0 | J40: =I40/F40*100 -> 0 | K40: 2.42 | L40: =H40/F40*100 -> 0 | M40: =P40/F40 -> 206.00081 | N40: =(F40*K40-H40*3.04)/F40 -> 2.42 | O40: =N40*F40 -> 239.58 | P40: =O40*C40 -> 20394.08 | R40: Акт №44 от 04.06.26 Продление ГП, смена партии 04FP2609
B41: 46177 | C41: =VLOOKUP(B:B,'Курс валют'!A:D,4,0) -> 85.1243 | D41: 04F2606 | E41: Отвердитель Starkbond 521C 10.0 бочка 200кг | F41: 800 | G41: 806.62 | H41: 0 | I41: =G41-F41 -> 6.62 | J41: =I41/F41*100 -> 0.8275 | K41: 1.89 | L41: =H41/F41*100 -> 0 | M41: =P41/F41 -> 160.88493 | N41: =(F41*K41-H41*3.04)/F41 -> 1.89 | O41: =N41*F41 -> 1512 | P41: =O41*C41 -> 128707.94
B42: 46177 | C42: =VLOOKUP(B:B,'Курс валют'!A:D,4,0) -> 85.1243 | D42: 02F26R03 | E42: Клей Starkbond 746/4А (ведро 20кг) | F42: 40 | G42: 40 | H42: 0 | I42: =G42-F42 -> 0 | J42: =I42/F42*100 -> 0 | K42: 3.32 | L42: =H42/F42*100 -> 0 | M42: =P42/F42 -> 282.61268 | N42: =(F42*K42-H42*3.04)/F42 -> 3.32 | O42: =N42*F42 -> 132.8 | P42: =O42*C42 -> 11304.507 | R42: смена номенклатуры
B43: 46177 | C43: =VLOOKUP(B:B,'Курс валют'!A:D,4,0) -> 85.1243 | D43: 04F2607 | E43: Отвердитель Starkbond 521C 10.0 бочка 200кг | F43: 800 | G43: 806.62 | H43: 0 | I43: =G43-F43 -> 6.62 | J43: =I43/F43*100 -> 0.8275 | K43: 1.89 | L43: =H43/F43*100 -> 0 | M43: =P43/F43 -> 160.88493 | N43: =(F43*K43-H43*3.04)/F43 -> 1.89 | O43: =N43*F43 -> 1512 | P43: =O43*C43 -> 128707.94
B44: 46177 | C44: =VLOOKUP(B:B,'Курс валют'!A:D,4,0) -> 85.1243 | D44: 04F2608 | E44: Отвердитель Starkbond 521C 10.0 бочка 200кг | F44: 800 | G44: 806.62 | H44: 0 | I44: =G44-F44 -> 6.62 | J44: =I44/F44*100 -> 0.8275 | K44: 1.89 | L44: =H44/F44*100 -> 0 | M44: =P44/F44 -> 160.88493 | N44: =(F44*K44-H44*3.04)/F44 -> 1.89 | O44: =N44*F44 -> 1512 | P44: =O44*C44 -> 128707.94
B45: 46177 | C45: =VLOOKUP(B:B,'Курс валют'!A:D,4,0) -> 85.1243 | D45: 04F26R11 | E45: Клей Starkbond 2014 бочка 225кг | F45: 2250 | G45: 2295.4 | H45: 0 | I45: =G45-F45 -> 45.4 | J45: =I45/F45*100 -> 2.0177778 | K45: 2.18 | L45: =H45/F45*100 -> 0 | M45: =P45/F45 -> 185.57097 | N45: =(F45*K45-H45*3.04)/F45 -> 2.18 | O45: =N45*F45 -> 4905 | P45: =O45*C45 -> 417534.69
B46: 46177 | C46: =VLOOKUP(B:B,'Курс валют'!A:D,4,0) -> 85.1243 | D46: 04F2609 | E46: Отвердитель Starkbond 521C 10.0 бочка 200кг | F46: 800 | G46: 806.62 | H46: 0 | I46: =G46-F46 -> 6.62 | J46: =I46/F46*100 -> 0.8275 | K46: 1.9 | L46: =H46/F46*100 -> 0 | M46: =P46/F46 -> 161.73617 | N46: =(F46*K46-H46*3.04)/F46 -> 1.9 | O46: =N46*F46 -> 1520 | P46: =O46*C46 -> 129388.94
B47: 46177 | C47: =VLOOKUP(B:B,'Курс валют'!A:D,4,0) -> 85.1243 | D47: 04F2610 | E47: Отвердитель Starkbond 521C 10.0 бочка 200кг | F47: 800 | G47: 806.62 | H47: 0 | I47: =G47-F47 -> 6.62 | J47: =I47/F47*100 -> 0.8275 | K47: 1.89 | L47: =H47/F47*100 -> 0 | M47: =P47/F47 -> 160.88493 | N47: =(F47*K47-H47*3.04)/F47 -> 1.89 | O47: =N47*F47 -> 1512 | P47: =O47*C47 -> 128707.94
B48: 46178 | C48: =VLOOKUP(B:B,'Курс валют'!A:D,4,0) -> 86.2712 | D48: 25K2501R019 | E48: Отвердитель Starkbond 521C бочка 200кг | F48: 200 | G48: 200 | H48: 0 | I48: =G48-F48 -> 0 | J48: =I48/F48*100 -> 0 | K48: 2.3 | L48: =H48/F48*100 -> 0 | M48: =P48/F48 -> 198.42376 | N48: =(F48*K48-H48*3.04)/F48 -> 2.3 | O48: =N48*F48 -> 460 | P48: =O48*C48 -> 39684.752 | R48: Акт №45 продление ГП
B49: 46178 | C49: =VLOOKUP(B:B,'Курс валют'!A:D,4,0) -> 86.2712 | D49: 25K2502R019 | E49: Отвердитель Starkbond 521C бочка 200кг | F49: 200 | G49: 200 | H49: 0 | I49: =G49-F49 -> 0 | J49: =I49/F49*100 -> 0 | K49: 2.3 | L49: =H49/F49*100 -> 0 | M49: =P49/F49 -> 198.42376 | N49: =(F49*K49-H49*3.04)/F49 -> 2.3 | O49: =N49*F49 -> 460 | P49: =O49*C49 -> 39684.752 | R49: Акт №45 продление ГП
B50: 46178 | C50: =VLOOKUP(B:B,'Курс валют'!A:D,4,0) -> 86.2712 | D50: 25K2503R019 | E50: Отвердитель Starkbond 521C бочка 200кг | F50: 200 | G50: 200 | H50: 0 | I50: =G50-F50 -> 0 | J50: =I50/F50*100 -> 0 | K50: 2.3 | L50: =H50/F50*100 -> 0 | M50: =P50/F50 -> 198.42376 | N50: =(F50*K50-H50*3.04)/F50 -> 2.3 | O50: =N50*F50 -> 460 | P50: =O50*C50 -> 39684.752 | R50: Акт №45 продление ГП
B51: 46178 | C51: =VLOOKUP(B:B,'Курс валют'!A:D,4,0) -> 86.2712 | D51: 25K2504R019 | E51: Отвердитель Starkbond 521C бочка 200кг | F51: 200 | G51: 200 | H51: 0 | I51: =G51-F51 -> 0 | J51: =I51/F51*100 -> 0 | K51: 2.3 | L51: =H51/F51*100 -> 0 | M51: =P51/F51 -> 198.42376 | N51: =(F51*K51-H51*3.04)/F51 -> 2.3 | O51: =N51*F51 -> 460 | P51: =O51*C51 -> 39684.752 | R51: Акт №45 продление ГП
B52: 46178 | C52: =VLOOKUP(B:B,'Курс валют'!A:D,4,0) -> 86.2712 | D52: 25K2509R019 | E52: Отвердитель Starkbond 521C бочка 200кг | F52: 200 | G52: 200 | H52: 0 | I52: =G52-F52 -> 0 | J52: =I52/F52*100 -> 0 | K52: 2.3 | L52: =H52/F52*100 -> 0 | M52: =P52/F52 -> 198.42376 | N52: =(F52*K52-H52*3.04)/F52 -> 2.3 | O52: =N52*F52 -> 460 | P52: =O52*C52 -> 39684.752 | R52: Акт №45 продление ГП
B53: 46178 | C53: =VLOOKUP(B:B,'Курс валют'!A:D,4,0) -> 86.2712 | D53: ШККА-000243 | E53: Отвердитель Starkbond 521C бочка 200кг | F53: 971 | G53: 1000 | H53: 0 | I53: =G53-F53 -> 29 | J53: =I53/F53*100 -> 2.9866117 | K53: 2.49 | L53: =H53/F53*100 -> 0 | M53: =P53/F53 -> 214.81529 | N53: =(F53*K53-H53*3.04)/F53 -> 2.49 | O53: =N53*F53 -> 2417.79 | P53: =O53*C53 -> 208585.64 | R53: Фильтрация Отвердитель Starkbond 521C бочка 200кг - 14B2517EX06R0190, 25K2501EX06R0190
B54: 46178 | C54: =VLOOKUP(B:B,'Курс валют'!A:D,4,0) -> 86.2712 | D54: 05F2601 | E54: клей Starkbond 521 A бочка 220кг | F54: 1100 | G54: 1108.5 | H54: 0 | I54: =G54-F54 -> 8.5 | J54: =I54/F54*100 -> 0.77272727 | K54: 2.81 | L54: =H54/F54*100 -> 0 | M54: =P54/F54 -> 242.42207 | N54: =(F54*K54-H54*3.04)/F54 -> 2.81 | O54: =N54*F54 -> 3091 | P54: =O54*C54 -> 266664.28
B55: 46178 | C55: =VLOOKUP(B:B,'Курс валют'!A:D,4,0) -> 86.2712 | D55: 05F2602 | E55: клей Starkbond 521 A бочка 220кг | F55: 1100 | G55: 1108.5 | H55: 0 | I55: =G55-F55 -> 8.5 | J55: =I55/F55*100 -> 0.77272727 | K55: 2.41 | L55: =H55/F55*100 -> 0 | M55: =P55/F55 -> 207.91359 | N55: =(F55*K55-H55*3.04)/F55 -> 2.41 | O55: =N55*F55 -> 2651 | P55: =O55*C55 -> 228704.95
B56: 46178 | C56: =VLOOKUP(B:B,'Курс валют'!A:D,4,0) -> 86.2712 | D56: 05F2603 | E56: клей Starkbond 521 A бочка 220кг | F56: 1100 | G56: 1108.5 | H56: 0 | I56: =G56-F56 -> 8.5 | J56: =I56/F56*100 -> 0.77272727 | K56: 2.41 | L56: =H56/F56*100 -> 0 | M56: =P56/F56 -> 207.91359 | N56: =(F56*K56-H56*3.04)/F56 -> 2.41 | O56: =N56*F56 -> 2651 | P56: =O56*C56 -> 228704.95
B57: 46178 | C57: =VLOOKUP(B:B,'Курс валют'!A:D,4,0) -> 86.2712 | D57: 05F2604 | E57: клей Starkbond 521 A бочка 220кг | F57: 1100 | G57: 1108.5 | H57: 0 | I57: =G57-F57 -> 8.5 | J57: =I57/F57*100 -> 0.77272727 | K57: 2.41 | L57: =H57/F57*100 -> 0 | M57: =P57/F57 -> 207.91359 | N57: =(F57*K57-H57*3.04)/F57 -> 2.41 | O57: =N57*F57 -> 2651 | P57: =O57*C57 -> 228704.95
B58: 46178 | C58: =VLOOKUP(B:B,'Курс валют'!A:D,4,0) -> 86.2712 | D58: 05F2605 | E58: клей Starkbond 521 A бочка 220кг | F58: 1100 | G58: 1108.5 | H58: 0 | I58: =G58-F58 -> 8.5 | J58: =I58/F58*100 -> 0.77272727 | K58: 2.41 | L58: =H58/F58*100 -> 0 | M58: =P58/F58 -> 207.91359 | N58: =(F58*K58-H58*3.04)/F58 -> 2.41 | O58: =N58*F58 -> 2651 | P58: =O58*C58 -> 228704.95
B59: 46178 | C59: =VLOOKUP(B:B,'Курс валют'!A:D,4,0) -> 86.2712 | D59: 05F2606 | E59: клей Starkbond 521 A бочка 220кг | F59: 1100 | G59: 1108.5 | H59: 0 | I59: =G59-F59 -> 8.5 | J59: =I59/F59*100 -> 0.77272727 | K59: 2.41 | L59: =H59/F59*100 -> 0 | M59: =P59/F59 -> 207.91359 | N59: =(F59*K59-H59*3.04)/F59 -> 2.41 | O59: =N59*F59 -> 2651 | P59: =O59*C59 -> 228704.95
B60: 46178 | C60: =VLOOKUP(B:B,'Курс валют'!A:D,4,0) -> 86.2712 | D60: 05F2607 | E60: клей Starkbond 521 A бочка 220кг | F60: 1100 | G60: 1108.5 | H60: 0 | I60: =G60-F60 -> 8.5 | J60: =I60/F60*100 -> 0.77272727 | K60: 2.41 | L60: =H60/F60*100 -> 0 | M60: =P60/F60 -> 207.91359 | N60: =(F60*K60-H60*3.04)/F60 -> 2.41 | O60: =N60*F60 -> 2651 | P60: =O60*C60 -> 228704.95
B61: 46178 | C61: =VLOOKUP(B:B,'Курс валют'!A:D,4,0) -> 86.2712 | D61: 05F26R11 | E61: Клей Starkbond 2014 бочка 225кг | F61: 2250 | G61: 2295.4 | H61: 0 | I61: =G61-F61 -> 45.4 | J61: =I61/F61*100 -> 2.0177778 | K61: 2.16 | L61: =H61/F61*100 -> 0 | M61: =P61/F61 -> 186.34579 | N61: =(F61*K61-H61*3.04)/F61 -> 2.16 | O61: =N61*F61 -> 4860 | P61: =O61*C61 -> 419278.03
B62: 46178 | C62: =VLOOKUP(B:B,'Курс валют'!A:D,4,0) -> 86.2712 | D62: 05F2608 | E62: клей Starkbond 521 A бочка 220кг | F62: 1100 | G62: 1108.5 | H62: 0 | I62: =G62-F62 -> 8.5 | J62: =I62/F62*100 -> 0.77272727 | K62: 2.41 | L62: =H62/F62*100 -> 0 | M62: =P62/F62 -> 207.91359 | N62: =(F62*K62-H62*3.04)/F62 -> 2.41 | O62: =N62*F62 -> 2651 | P62: =O62*C62 -> 228704.95
B63: 46178 | C63: =VLOOKUP(B:B,'Курс валют'!A:D,4,0) -> 86.2712 | D63: 05F2609 | E63: клей Starkbond 521 A бочка 220кг | F63: 1100 | G63: 1108.5 | H63: 0 | I63: =G63-F63 -> 8.5 | J63: =I63/F63*100 -> 0.77272727 | K63: 2.41 | L63: =H63/F63*100 -> 0 | M63: =P63/F63 -> 207.91359 | N63: =(F63*K63-H63*3.04)/F63 -> 2.41 | O63: =N63*F63 -> 2651 | P63: =O63*C63 -> 228704.95
B64: 46178 | C64: =VLOOKUP(B:B,'Курс валют'!A:D,4,0) -> 86.2712 | D64: 05F2610 | E64: клей Starkbond 521 A бочка 220кг | F64: 1100 | G64: 1108.5 | H64: 0 | I64: =G64-F64 -> 8.5 | J64: =I64/F64*100 -> 0.77272727 | K64: 2.41 | L64: =H64/F64*100 -> 0 | M64: =P64/F64 -> 207.91359 | N64: =(F64*K64-H64*3.04)/F64 -> 2.41 | O64: =N64*F64 -> 2651 | P64: =O64*C64 -> 228704.95
B65: 46179 | C65: =VLOOKUP(B:B,'Курс валют'!A:D,4,0) -> 85.5582 | D65: 06F26R11 | E65: Клей Starkbond 2014 бочка 225кг | F65: 2250 | G65: 2295.4 | H65: 0 | I65: =G65-F65 -> 45.4 | J65: =I65/F65*100 -> 2.0177778 | K65: 2.16 | L65: =H65/F65*100 -> 0 | M65: =P65/F65 -> 184.80571 | N65: =(F65*K65-H65*3.04)/F65 -> 2.16 | O65: =N65*F65 -> 4860 | P65: =O65*C65 -> 415812.85
... B70: 46179 | C70: =VLOOKUP(B:B,'Курс валют'!A:D,4,0) -> 85.5582 | D70: 06F2605 | E70: клей Starkbond 521 A бочка 220кг | F70: 1100 | G70: 1108.5 | H70: 0 | I70: =G70-F70 -> 8.5 | J70: =I70/F70*100 -> 0.77272727 | K70: 2.41 | L70: =H70/F70*100 -> 0 | M70: =P70/F70 -> 206.19526 | N70: =(F70*K70-H70*3.04)/F70 -> 2.41 | O70: =N70*F70 -> 2651 | P70: =O70*C70 -> 226814.79
B71: 46179 | C71: =VLOOKUP(B:B,'Курс валют'!A:D,4,0) -> 85.5582 | D71: 06F2611 | E71: Клей Starkbond 521A ведро 22 кг | F71: 220 | G71: 220 | H71: 0 | I71: =G71-F71 -> 0 | J71: =I71/F71*100 -> 0 | K71: 2.61 | L71: =H71/F71*100 -> 0 | M71: =P71/F71 -> 223.3069 | N71: =(F71*K71-H71*3.04)/F71 -> 2.61 | O71: =N71*F71 -> 574.2 | P71: =O71*C71 -> 49127.518 | R71: фасовка
B72: 46179 | C72: =VLOOKUP(B:B,'Курс валют'!A:D,4,0) -> 85.5582 | D72: 06F2612 | E72: Отвердитель Starkbond 525C 6.0 ведро 20кг | F72: 200 | G72: 200 | H72: 0 | I72: =G72-F72 -> 0 | J72: =I72/F72*100 -> 0 | K72: 2.85 | L72: =H72/F72*100 -> 0 | M72: =P72/F72 -> 243.84087 | N72: =(F72*K72-H72*3.04)/F72 -> 2.85 | O72: =N72*F72 -> 570 | P72: =O72*C72 -> 48768.174 | R72: фасовка
B73: 46179 | C73: =VLOOKUP(B:B,'Курс валют'!A:D,4,0) -> 85.5582 | D73: 06F2606 | E73: клей Starkbond 521 A бочка 220кг | F73: 1100 | G73: 1108.5 | H73: 0 | I73: =G73-F73 -> 8.5 | J73: =I73/F73*100 -> 0.77272727 | K73: 2.41 | L73: =H73/F73*100 -> 0 | M73: =P73/F73 -> 206.19526 | N73: =(F73*K73-H73*3.04)/F73 -> 2.41 | O73: =N73*F73 -> 2651 | P73: =O73*C73 -> 226814.79
B74: 46179 | C74: =VLOOKUP(B:B,'Курс валют'!A:D,4,0) -> 85.5582 | D74: 06F2607 | E74: клей Starkbond 521 A бочка 220кг | F74: 1100 | G74: 1108.5 | H74: 0 | I74: =G74-F74 -> 8.5 | J74: =I74/F74*100 -> 0.77272727 | K74: 2.41 | L74: =H74/F74*100 -> 0 | M74: =P74/F74 -> 206.19526 | N74: =(F74*K74-H74*3.04)/F74 -> 2.41 | O74: =N74*F74 -> 2651 | P74: =O74*C74 -> 226814.79
B75: 46179 | C75: =VLOOKUP(B:B,'Курс валют'!A:D,4,0) -> 85.5582 | D75: 06F2608 | E75: клей Starkbond 521 A бочка 220кг | F75: 1100 | G75: 1108.5 | H75: 0 | I75: =G75-F75 -> 8.5 | J75: =I75/F75*100 -> 0.77272727 | K75: 2.41 | L75: =H75/F75*100 -> 0 | M75: =P75/F75 -> 206.19526 | N75: =(F75*K75-H75*3.04)/F75 -> 2.41 | O75: =N75*F75 -> 2651 | P75: =O75*C75 -> 226814.79
B76: 46179 | C76: =VLOOKUP(B:B,'Курс валют'!A:D,4,0) -> 85.5582 | D76: 06F2609 | E76: клей Starkbond 521 A бочка 220кг | F76: 1100 | G76: 1108.5 | H76: 0 | I76: =G76-F76 -> 8.5 | J76: =I76/F76*100 -> 0.77272727 | K76: 2.41 | L76: =H76/F76*100 -> 0 | M76: =P76/F76 -> 206.19526 | N76: =(F76*K76-H76*3.04)/F76 -> 2.41 | O76: =N76*F76 -> 2651 | P76: =O76*C76 -> 226814.79
B77: 46179 | C77: =VLOOKUP(B:B,'Курс валют'!A:D,4,0) -> 85.5582 | D77: 06F2610 | E77: клей Starkbond 521 A бочка 220кг | F77: 1100 | G77: 1108.5 | H77: 0 | I77: =G77-F77 -> 8.5 | J77: =I77/F77*100 -> 0.77272727 | K77: 2.41 | L77: =H77/F77*100 -> 0 | M77: =P77/F77 -> 206.19526 | N77: =(F77*K77-H77*3.04)/F77 -> 2.41 | O77: =N77*F77 -> 2651 | P77: =O77*C77 -> 226814.79
B78: 46180 | C78: =VLOOKUP(B:B,'Курс валют'!A:D,4,0) -> 85.5582 | D78: 07F26R11 | E78: Клей Starkbond 2014 бочка 225кг | F78: 2250 | G78: 2295.4 | H78: 0 | I78: =G78-F78 -> 45.4 | J78: =I78/F78*100 -> 2.0177778 | K78: 2.16 | L78: =H78/F78*100 -> 0 | M78: =P78/F78 -> 184.80571 | N78: =(F78*K78-H78*3.04)/F78 -> 2.16 | O78: =N78*F78 -> 4860 | P78: =O78*C78 -> 415812.85
B79: 46180 | C79: =VLOOKUP(B:B,'Курс валют'!A:D,4,0) -> 85.5582 | D79: 07F2601 | E79: клей Starkbond 521 A бочка 220кг | F79: 1100 | G79: 1108.5 | H79: 0 | I79: =G79-F79 -> 8.5 | J79: =I79/F79*100 -> 0.77272727 | K79: 2.4 | L79: =H79/F79*100 -> 0 | M79: =P79/F79 -> 205.33968 | N79: =(F79*K79-H79*3.04)/F79 -> 2.4 | O79: =N79*F79 -> 2640 | P79: =O79*C79 -> 225873.65
B80: 46180 | C80: =VLOOKUP(B:B,'Курс валют'!A:D,4,0) -> 85.5582 | D80: 07F2602 | E80: клей Starkbond 521 A бочка 220кг | F80: 1100 | G80: 1108.5 | H80: 0 | I80: =G80-F80 -> 8.5 | J80: =I80/F80*100 -> 0.77272727 | K80: 2.4 | L80: =H80/F80*100 -> 0 | M80: =P80/F80 -> 205.33968 | N80: =(F80*K80-H80*3.04)/F80 -> 2.4 | O80: =N80*F80 -> 2640 | P80: =O80*C80 -> 225873.65
B81: 46180 | C81: =VLOOKUP(B:B,'Курс валют'!A:D,4,0) -> 85.5582 | D81: 07F2603 | E81: клей Starkbond 521 A бочка 220кг | F81: 1100 | G81: 1108.5 | H81: 0 | I81: =G81-F81 -> 8.5 | J81: =I81/F81*100 -> 0.77272727 | K81: 2.4 | L81: =H81/F81*100 -> 0 | M81: =P81/F81 -> 205.33968 | N81: =(F81*K81-H81*3.04)/F81 -> 2.4 | O81: =N81*F81 -> 2640 | P81: =O81*C81 -> 225873.65
B82: 46180 | C82: =VLOOKUP(B:B,'Курс валют'!A:D,4,0) -> 85.5582 | D82: 07F2604 | E82: клей Starkbond 521 A бочка 220кг | F82: 1100 | G82: 1108.5 | H82: 0 | I82: =G82-F82 -> 8.5 | J82: =I82/F82*100 -> 0.77272727 | K82: 2.4 | L82: =H82/F82*100 -> 0 | M82: =P82/F82 -> 205.33968 | N82: =(F82*K82-H82*3.04)/F82 -> 2.4 | O82: =N82*F82 -> 2640 | P82: =O82*C82 -> 225873.65
B83: 46180 | C83: =VLOOKUP(B:B,'Курс валют'!A:D,4,0) -> 85.5582 | D83: 07F2605 | E83: клей Starkbond 521 A бочка 220кг | F83: 1100 | G83: 1108.5 | H83: 0 | I83: =G83-F83 -> 8.5 | J83: =I83/F83*100 -> 0.77272727 | K83: 2.4 | L83: =H83/F83*100 -> 0 | M83: =P83/F83 -> 205.33968 | N83: =(F83*K83-H83*3.04)/F83 -> 2.4 | O83: =N83*F83 -> 2640 | P83: =O83*C83 -> 225873.65
B84: 46180 | C84: =VLOOKUP(B:B,'Курс валют'!A:D,4,0) -> 85.5582 | D84: 07F2606 | E84: клей Starkbond 521 A бочка 220кг | F84: 1100 | G84: 1108.5 | H84: 0 | I84: =G84-F84 -> 8.5 | J84: =I84/F84*100 -> 0.77272727 | K84: 2.4 | L84: =H84/F84*100 -> 0 | M84: =P84/F84 -> 205.33968 | N84: =(F84*K84-H84*3.04)/F84 -> 2.4 | O84: =N84*F84 -> 2640 | P84: =O84*C84 -> 225873.65
... B106: 46182 | C106: =VLOOKUP(B:B,'Курс валют'!A:D,4,0) -> 85.2798 | D106: 09F2606 | E106: клей Starkbond 521 A бочка 220кг | F106: 1100 | G106: 1108.5 | H106: 0 | I106: =G106-F106 -> 8.5 | J106: =I106/F106*100 -> 0.77272727 | K106: 2.38 | L106: =H106/F106*100 -> 0 | M106: =P106/F106 -> 202.96592 | N106: =(F106*K106-H106*3.04)/F106 -> 2.38 | O106: =N106*F106 -> 2618 | P106: =O106*C106 -> 223262.52
B107: 46182 | C107: =VLOOKUP(B:B,'Курс валют'!A:D,4,0) -> 85.2798 | D107: 18L2506 | E107: Отвердитель Starkbond 521C 10.0 ведро 20кг | F107: 80 | G107: 80 | H107: 0 | I107: =G107-F107 -> 0 | J107: =I107/F107*100 -> 0 | K107: 2.16 | L107: =H107/F107*100 -> 0 | M107: =P107/F107 -> 184.20437 | N107: =(F107*K107-H107*3.04)/F107 -> 2.16 | O107: =N107*F107 -> 172.8 | P107: =O107*C107 -> 14736.349 | R107: Акт №46 продление ГП
B108: 46182 | C108: =VLOOKUP(B:B,'Курс валют'!A:D,4,0) -> 85.2798 | D108: 09F2607 | E108: клей Starkbond 521 A бочка 220кг | F108: 1100 | G108: 1108.5 | H108: 0 | I108: =G108-F108 -> 8.5 | J108: =I108/F108*100 -> 0.77272727 | K108: 2.38 | L108: =H108/F108*100 -> 0 | M108: =P108/F108 -> 202.96592 | N108: =(F108*K108-H108*3.04)/F108 -> 2.38 | O108: =N108*F108 -> 2618 | P108: =O108*C108 -> 223262.52
B109: 46182 | C109: =VLOOKUP(B:B,'Курс валют'!A:D,4,0) -> 85.2798 | D109: 09F2608 | E109: клей Starkbond 521 A бочка 220кг | F109: 1100 | G109: 1108.5 | H109: 0 | I109: =G109-F109 -> 8.5 | J109: =I109/F109*100 -> 0.77272727 | K109: 2.38 | L109: =H109/F109*100 -> 0 | M109: =P109/F109 -> 202.96592 | N109: =(F109*K109-H109*3.04)/F109 -> 2.38 | O109: =N109*F109 -> 2618 | P109: =O109*C109 -> 223262.52
B110: 46182 | C110: =VLOOKUP(B:B,'Курс валют'!A:D,4,0) -> 85.2798 | D110: 09F2609 | E110: клей Starkbond 521 A бочка 220кг | F110: 1100 | G110: 1108.5 | H110: 0 | I110: =G110-F110 -> 8.5 | J110: =I110/F110*100 -> 0.77272727 | K110: 2.38 | L110: =H110/F110*100 -> 0 | M110: =P110/F110 -> 202.96592 | N110: =(F110*K110-H110*3.04)/F110 -> 2.38 | O110: =N110*F110 -> 2618 | P110: =O110*C110 -> 223262.52
B111: 46182 | C111: =VLOOKUP(B:B,'Курс валют'!A:D,4,0) -> 85.2798 | D111: 09F2610 | E111: клей Starkbond 521 A бочка 220кг | F111: 1100 | G111: 1108.5 | H111: 0 | I111: =G111-F111 -> 8.5 | J111: =I111/F111*100 -> 0.77272727 | K111: 2.38 | L111: =H111/F111*100 -> 0 | M111: =P111/F111 -> 202.96592 | N111: =(F111*K111-H111*3.04)/F111 -> 2.38 | O111: =N111*F111 -> 2618 | P111: =O111*C111 -> 223262.52
B112: 46182 | C112: =VLOOKUP(B:B,'Курс валют'!A:D,4,0) -> 85.2798 | D112: 09F2611 | E112: Клей Starkbond 525A 3.0 ведро 20 кг | F112: 20 | G112: 22.11 | H112: 0 | I112: =G112-F112 -> 2.11 | J112: =I112/F112*100 -> 10.55 | K112: 2.2 | L112: =H112/F112*100 -> 0 | M112: =P112/F112 -> 187.61556 | N112: =(F112*K112-H112*3.04)/F112 -> 2.2 | O112: =N112*F112 -> 44 | P112: =O112*C112 -> 3752.3112
B113: 46182 | C113: =VLOOKUP(B:B,'Курс валют'!A:D,4,0) -> 85.2798 | D113: 09F2612 | E113: Клей Starkbond 525A 4.0 ведро 20 кг | F113: 20 | G113: 22.11 | H113: 0 | I113: =G113-F113 -> 2.11 | J113: =I113/F113*100 -> 10.55 | K113: 2.28 | L113: =H113/F113*100 -> 0 | M113: =P113/F113 -> 194.43794 | N113: =(F113*K113-H113*3.04)/F113 -> 2.28 | O113: =N113*F113 -> 45.6 | P113: =O113*C113 -> 3888.7589
B114: 46182 | C114: =VLOOKUP(B:B,'Курс валют'!A:D,4,0) -> 85.2798 | D114: 09F2613 | E114: Отвердитель Starkbond 525C 7.0 ведро 20 кг | F114: 24 | G114: 26.95 | H114: 0 | I114: =G114-F114 -> 2.95 | J114: =I114/F114*100 -> 12.291667 | K114: 3.44 | L114: =H114/F114*100 -> 0 | M114: =P114/F114 -> 293.36251 | N114: =(F114*K114-H114*3.04)/F114 -> 3.44 | O114: =N114*F114 -> 82.56 | P114: =O114*C114 -> 7040.7003
B115: 46183 | C115: =VLOOKUP(B:B,'Курс валют'!A:D,4,0) -> 82.7785 | D115: 10F26R11 | E115: Клей Starkbond 2014 бочка 225кг | F115: 2250 | G115: 2294.7 | H115: 0 | I115: =G115-F115 -> 44.7 | J115: =I115/F115*100 -> 1.9866667 | K115: 2.14 | L115: =H115/F115*100 -> 0 | M115: =P115/F115 -> 177.14599 | N115: =(F115*K115-H115*3.04)/F115 -> 2.14 | O115: =N115*F115 -> 4815 | P115: =O115*C115 -> 398578.48
B116: 46183 | C116: =VLOOKUP(B:B,'Курс валют'!A:D,4,0) -> 82.7785 | D116: 10F2601 | E116: Клей Starkbond 522A бочка 220 кг | F116: 1100 | G116: 1108.01 | H116: 0 | I116: =G116-F116 -> 8.01 | J116: =I116/F116*100 -> 0.72818182 | K116: 2.47 | L116: =H116/F116*100 -> 0 | M116: =P116/F116 -> 204.4629 | N116: =(F116*K116-H116*3.04)/F116 -> 2.47 | O116: =N116*F116 -> 2717 | P116: =O116*C116 -> 224909.18
B117: 46183 | C117: =VLOOKUP(B:B,'Курс валют'!A:D,4,0) -> 82.7785 | D117: 10F2602 | E117: Клей Starkbond 522A бочка 220 кг | F117: 1100 | G117: 1108.01 | H117: 0 | I117: =G117-F117 -> 8.01 | J117: =I117/F117*100 -> 0.72818182 | K117: 2.46 | L117: =H117/F117*100 -> 0 | M117: =P117/F117 -> 203.63511 | N117: =(F117*K117-H117*3.04)/F117 -> 2.46 | O117: =N117*F117 -> 2706 | P117: =O117*C117 -> 223998.62
B118: 46183 | C118: =VLOOKUP(B:B,'Курс валют'!A:D,4,0) -> 82.7785 | D118: 10F2603 | E118: Клей Starkbond 522A бочка 220 кг | F118: 1100 | G118: 1108.01 | H118: 0 | I118: =G118-F118 -> 8.01 | J118: =I118/F118*100 -> 0.72818182 | K118: 2.46 | L118: =H118/F118*100 -> 0 | M118: =P118/F118 -> 203.63511 | N118: =(F118*K118-H118*3.04)/F118 -> 2.46 | O118: =N118*F118 -> 2706 | P118: =O118*C118 -> 223998.62
B119: 46183 | C119: =VLOOKUP(B:B,'Курс валют'!A:D,4,0) -> 82.7785 | D119: 10F2604 | E119: Клей Starkbond 522A бочка 220 кг | F119: 1100 | G119: 1108.01 | H119: 0 | I119: =G119-F119 -> 8.01 | J119: =I119/F119*100 -> 0.72818182 | K119: 2.47 | L119: =H119/F119*100 -> 0 | M119: =P119/F119 -> 204.4629 | N119: =(F119*K119-H119*3.04)/F119 -> 2.47 | O119: =N119*F119 -> 2717 | P119: =O119*C119 -> 224909.18
... B135: 46184 | C135: =VLOOKUP(B:B,'Курс валют'!A:D,4,0) -> 83.0816 | D135: 11F2610 | E135: Клей Starkbond 522A бочка 220 кг | F135: 1100 | G135: 1108.01 | H135: 0 | I135: =G135-F135 -> 8.01 | J135: =I135/F135*100 -> 0.72818182 | K135: 2.46 | L135: =H135/F135*100 -> 0 | M135: =P135/F135 -> 204.38074 | N135: =(F135*K135-H135*3.04)/F135 -> 2.46 | O135: =N135*F135 -> 2706 | P135: =O135*C135 -> 224818.81
B136: 46184 | C136: =VLOOKUP(B:B,'Курс валют'!A:D,4,0) -> 83.0816 | D136: 11F2611 | E136: клей Starkbond 521 A бочка 220кг | F136: 55 | G136: 57 | H136: 0 | I136: =G136-F136 -> 2 | J136: =I136/F136*100 -> 3.6363636 | K136: 7.87 | L136: =H136/F136*100 -> 0 | M136: =P136/F136 -> 653.85219 | N136: =(F136*K136-H136*3.04)/F136 -> 7.87 | O136: =N136*F136 -> 432.85 | P136: =O136*C136 -> 35961.871 | R136: 521A (55) 11F2611R0190 Образец (PREPOLYMER Polyurethane Binder)
B137: 46184 | C137: =VLOOKUP(B:B,'Курс валют'!A:D,4,0) -> 83.0816 | D137: 11F2612 | E137: клей Starkbond 521 A бочка 220кг | F137: 65 | G137: 68.2 | H137: 0 | I137: =G137-F137 -> 3.2 | J137: =I137/F137*100 -> 4.9230769 | K137: 5.29 | L137: =H137/F137*100 -> 0 | M137: =P137/F137 -> 439.50166 | N137: =(F137*K137-H137*3.04)/F137 -> 5.29 | O137: =N137*F137 -> 343.85 | P137: =O137*C137 -> 28567.608 | R137: 521A (65) 11F2612R0190 Образец (PREPOLYMER HC-8419V)
B138: 46184 | C138: =VLOOKUP(B:B,'Курс валют'!A:D,4,0) -> 83.0816 | D138: 11F2613 | E138: клей Starkbond 521 A бочка 220кг | F138: 70 | G138: 71.8 | H138: 0 | I138: =G138-F138 -> 1.8 | J138: =I138/F138*100 -> 2.5714286 | K138: 3.64 | L138: =H138/F138*100 -> 0 | M138: =P138/F138 -> 302.41702 | N138: =(F138*K138-H138*3.04)/F138 -> 3.64 | O138: =N138*F138 -> 254.8 | P138: =O138*C138 -> 21169.192 | R138: 521A (70) 11F2613R0190 Образец (PREPOLYMER Madisonol P5191)
B139: 46185 | C139: =VLOOKUP(B:B,'Курс валют'!A:D,4,0) -> 82.9743 | D139: 12F2601 | E139: клей Starkbond 521 A бочка 220кг | F139: 1100 | G139: 1108.5 | H139: 0 | I139: =G139-F139 -> 8.5 | J139: =I139/F139*100 -> 0.77272727 | K139: 2.38 | L139: =H139/F139*100 -> 0 | M139: =P139/F139 -> 197.47883 | N139: =(F139*K139-H139*3.04)/F139 -> 2.38 | O139: =N139*F139 -> 2618 | P139: =O139*C139 -> 217226.72
B140: 46185 | C140: =VLOOKUP(B:B,'Курс валют'!A:D,4,0) -> 82.9743 | D140: 12F2602 | E140: клей Starkbond 521 A бочка 220кг | F140: 1100 | G140: 1108.5 | H140: 0 | I140: =G140-F140 -> 8.5 | J140: =I140/F140*100 -> 0.77272727 | K140: 2.38 | L140: =H140/F140*100 -> 0 | M140: =P140/F140 -> 197.47883 | N140: =(F140*K140-H140*3.04)/F140 -> 2.38 | O140: =N140*F140 -> 2618 | P140: =O140*C140 -> 217226.72
...

Sheet Май 2026
A1: пп | B1: Дата выпуска продукции | C1: курс | D1: № ЗП | E1: Продукт | F1: Вес готового продукта | G1: Израсходовано по факту | H1: Израсходовано по факту Polyether Polyol Puranol D220, LE-220A Пропиленгликоль | I1: Потери, кг | J1: % потерь | K1: СС 1С на дату выпуска, EUR | L1: % пропиленгликоля в составе + полиол | M1: СС КГ, РУБ, Б/НДС | N1: СС Факт , EUR, Б/НДС | O1: СС Партии, EUR, Б/НДС | P1: СС Партии, РУБ, Б/НДС | R1: Примечание
B2: 46143 | C2: =VLOOKUP(B:B,'Курс валют'!A:D,4,0) -> 88.6429 | D2: 01E26R11 | E2: Клей Starkbond 745/41 А (бочка 200 кг) | F2: 2000 | G2: 2054.55 | H2: 0 | I2: =G2-F2 -> 54.55 | J2: =I2/F2*100 -> 2.7275 | K2: 2.43 | L2: =H2/F2*100 -> 0 | M2: =P2/F2 -> 215.40225 | N2: =(F2*K2-H2*3.04)/F2 -> 2.43 | O2: =N2*F2 -> 4860 | P2: =O2*C2 -> 430804.49
B3: 46143 | C3: =VLOOKUP(B:B,'Курс валют'!A:D,4,0) -> 88.6429 | D3: 01E2601 | E3: клей Starkbond 521 A бочка 220кг | F3: 1100 | G3: 1106.3 | H3: 484.5 | I3: =G3-F3 -> 6.3 | J3: =I3/F3*100 -> 0.57272727 | K3: 15.73 | L3: =H3/F3*100 -> 44.045455 | M3: =P3/F3 -> 207.4405 | N3: =(F3*K3-H3*30.4)/F3 -> 2.3401818 | O3: =N3*F3 -> 2574.2 | P3: =O3*C3 -> 228184.55
B4: 46143 | C4: =VLOOKUP(B:B,'Курс валют'!A:D,4,0) -> 88.6429 | D4: 01E2602 | E4: клей Starkbond 521 A бочка 220кг | F4: 1100 | G4: 1106.3 | H4: 484.5 | I4: =G4-F4 -> 6.3 | J4: =I4/F4*100 -> 0.57272727 | K4: 15.73 | L4: =H4/F4*100 -> 44.045455 | M4: =P4/F4 -> 207.4405 | N4: =(F4*K4-H4*30.4)/F4 -> 2.3401818 | O4: =N4*F4 -> 2574.2 | P4: =O4*C4 -> 228184.55
B5: 46143 | C5: =VLOOKUP(B:B,'Курс валют'!A:D,4,0) -> 88.6429 | D5: 01E2603 | E5: клей Starkbond 521 A бочка 220кг | F5: 1100 | G5: 1106.3 | H5: 484.5 | I5: =G5-F5 -> 6.3 | J5: =I5/F5*100 -> 0.57272727 | K5: 15.73 | L5: =H5/F5*100 -> 44.045455 | M5: =P5/F5 -> 207.4405 | N5: =(F5*K5-H5*30.4)/F5 -> 2.3401818 | O5: =N5*F5 -> 2574.2 | P5: =O5*C5 -> 228184.55
B6: 46143 | C6: =VLOOKUP(B:B,'Курс валют'!A:D,4,0) -> 88.6429 | D6: 01E2604 | E6: клей Starkbond 521 A бочка 220кг | F6: 1100 | G6: 1106.3 | H6: 484.5 | I6: =G6-F6 -> 6.3 | J6: =I6/F6*100 -> 0.57272727 | K6: 15.73 | L6: =H6/F6*100 -> 44.045455 | M6: =P6/F6 -> 207.4405 | N6: =(F6*K6-H6*30.4)/F6 -> 2.3401818 | O6: =N6*F6 -> 2574.2 | P6: =O6*C6 -> 228184.55
B7: 46143 | C7: =VLOOKUP(B:B,'Курс валют'!A:D,4,0) -> 88.6429 | D7: 01E2605 | E7: клей Starkbond 521 A бочка 220кг | F7: 1100 | G7: 1106.3 | H7: 484.5 | I7: =G7-F7 -> 6.3 | J7: =I7/F7*100 -> 0.57272727 | K7: 15.73 | L7: =H7/F7*100 -> 44.045455 | M7: =P7/F7 -> 207.4405 | N7: =(F7*K7-H7*30.4)/F7 -> 2.3401818 | O7: =N7*F7 -> 2574.2 | P7: =O7*C7 -> 228184.55
B8: 46143 | C8: =VLOOKUP(B:B,'Курс валют'!A:D,4,0) -> 88.6429 | D8: 01E2606 | E8: клей Starkbond 521 A бочка 220кг | F8: 1100 | G8: 1106.3 | H8: 484.5 | I8: =G8-F8 -> 6.3 | J8: =I8/F8*100 -> 0.57272727 | K8: 15.73 | L8: =H8/F8*100 -> 44.045455 | M8: =P8/F8 -> 207.4405 | N8: =(F8*K8-H8*30.4)/F8 -> 2.3401818 | O8: =N8*F8 -> 2574.2 | P8: =O8*C8 -> 228184.55
B9: 46143 | C9: =VLOOKUP(B:B,'Курс валют'!A:D,4,0) -> 88.6429 | D9: 01E2607 | E9: клей Starkbond 521 A бочка 220кг | F9: 1100 | G9: 1106.3 | H9: 484.5 | I9: =G9-F9 -> 6.3 | J9: =I9/F9*100 -> 0.57272727 | K9: 15.73 | L9: =H9/F9*100 -> 44.045455 | M9: =P9/F9 -> 207.4405 | N9: =(F9*K9-H9*30.4)/F9 -> 2.3401818 | O9: =N9*F9 -> 2574.2 | P9: =O9*C9 -> 228184.55
B10: 46143 | C10: =VLOOKUP(B:B,'Курс валют'!A:D,4,0) -> 88.6429 | D10: 01E2608 | E10: клей Starkbond 521 A бочка 220кг | F10: 1100 | G10: 1106.3 | H10: 484.5 | I10: =G10-F10 -> 6.3 | J10: =I10/F10*100 -> 0.57272727 | K10: 15.73 | L10: =H10/F10*100 -> 44.045455 | M10: =P10/F10 -> 207.4405 | N10: =(F10*K10-H10*30.4)/F10 -> 2.3401818 | O10: =N10*F10 -> 2574.2 | P10: =O10*C10 -> 228184.55
B11: 46143 | C11: =VLOOKUP(B:B,'Курс валют'!A:D,4,0) -> 88.6429 | D11: 01E2609 | E11: клей Starkbond 521 A бочка 220кг | F11: 1100 | G11: 1106.3 | H11: 484.5 | I11: =G11-F11 -> 6.3 | J11: =I11/F11*100 -> 0.57272727 | K11: 15.73 | L11: =H11/F11*100 -> 44.045455 | M11: =P11/F11 -> 207.4405 | N11: =(F11*K11-H11*30.4)/F11 -> 2.3401818 | O11: =N11*F11 -> 2574.2 | P11: =O11*C11 -> 228184.55
B12: 46143 | C12: =VLOOKUP(B:B,'Курс валют'!A:D,4,0) -> 88.6429 | D12: 01E2610 | E12: клей Starkbond 521 A бочка 220кг | F12: 1100 | G12: 1106.3 | H12: 484.5 | I12: =G12-F12 -> 6.3 | J12: =I12/F12*100 -> 0.57272727 | K12: 15.73 | L12: =H12/F12*100 -> 44.045455 | M12: =P12/F12 -> 207.4405 | N12: =(F12*K12-H12*30.4)/F12 -> 2.3401818 | O12: =N12*F12 -> 2574.2 | P12: =O12*C12 -> 228184.55
B13: 46144 | C13: =VLOOKUP(B:B,'Курс валют'!A:D,4,0) -> 88.6429 | D13: 02E26R11 | E13: Клей Starkbond 745/41 А (бочка 200 кг) | F13: 2000 | G13: 2054.55 | H13: 0 | I13: =G13-F13 -> 54.55 | J13: =I13/F13*100 -> 2.7275 | K13: 2.43 | L13: =H13/F13*100 -> 0 | M13: =P13/F13 -> 215.40225 | N13: =(F13*K13-H13*3.04)/F13 -> 2.43 | O13: =N13*F13 -> 4860 | P13: =O13*C13 -> 430804.49
B14: 46144 | C14: =VLOOKUP(B:B,'Курс валют'!A:D,4,0) -> 88.6429 | D14: 02E2601 | E14: клей Starkbond 521 A бочка 220кг | F14: 1100 | G14: 1106.3 | H14: 484.5 | I14: =G14-F14 -> 6.3 | J14: =I14/F14*100 -> 0.57272727 | K14: 15.73 | L14: =H14/F14*100 -> 44.045455 | M14: =P14/F14 -> 207.4405 | N14: =(F14*K14-H14*30.4)/F14 -> 2.3401818 | O14: =N14*F14 -> 2574.2 | P14: =O14*C14 -> 228184.55
B15: 46144 | C15: =VLOOKUP(B:B,'Курс валют'!A:D,4,0) -> 88.6429 | D15: 02E2602 | E15: клей Starkbond 521 A бочка 220кг | F15: 1100 | G15: 1106.3 | H15: 484.5 | I15: =G15-F15 -> 6.3 | J15: =I15/F15*100 -> 0.57272727 | K15: 15.73 | L15: =H15/F15*100 -> 44.045455 | M15: =P15/F15 -> 207.4405 | N15: =(F15*K15-H15*30.4)/F15 -> 2.3401818 | O15: =N15*F15 -> 2574.2 | P15: =O15*C15 -> 228184.55
B16: 46144 | C16: =VLOOKUP(B:B,'Курс валют'!A:D,4,0) -> 88.6429 | D16: 02E2603 | E16: клей Starkbond 521 A бочка 220кг | F16: 1100 | G16: 1106.3 | H16: 484.5 | I16: =G16-F16 -> 6.3 | J16: =I16/F16*100 -> 0.57272727 | K16: 15.73 | L16: =H16/F16*100 -> 44.045455 | M16: =P16/F16 -> 207.4405 | N16: =(F16*K16-H16*30.4)/F16 -> 2.3401818 | O16: =N16*F16 -> 2574.2 | P16: =O16*C16 -> 228184.55
B17: 46144 | C17: =VLOOKUP(B:B,'Курс валют'!A:D,4,0) -> 88.6429 | D17: 02E2604 | E17: клей Starkbond 521 A бочка 220кг | F17: 1100 | G17: 1106.3 | H17: 484.5 | I17: =G17-F17 -> 6.3 | J17: =I17/F17*100 -> 0.57272727 | K17: 15.73 | L17: =H17/F17*100 -> 44.045455 | M17: =P17/F17 -> 207.4405 | N17: =(F17*K17-H17*30.4)/F17 -> 2.3401818 | O17: =N17*F17 -> 2574.2 | P17: =O17*C17 -> 228184.55
B18: 46144 | C18: =VLOOKUP(B:B,'Курс валют'!A:D,4,0) -> 88.6429 | D18: 02E2605 | E18: клей Starkbond 521 A бочка 220кг | F18: 1100 | G18: 1106.3 | H18: 484.5 | I18: =G18-F18 -> 6.3 | J18: =I18/F18*100 -> 0.57272727 | K18: 15.73 | L18: =H18/F18*100 -> 44.045455 | M18: =P18/F18 -> 207.4405 | N18: =(F18*K18-H18*30.4)/F18 -> 2.3401818 | O18: =N18*F18 -> 2574.2 | P18: =O18*C18 -> 228184.55
B19: 46144 | C19: =VLOOKUP(B:B,'Курс валют'!A:D,4,0) -> 88.6429 | D19: 02E2606 | E19: клей Starkbond 521 A бочка 220кг | F19: 1100 | G19: 1106.3 | H19: 484.5 | I19: =G19-F19 -> 6.3 | J19: =I19/F19*100 -> 0.57272727 | K19: 15.73 | L19: =H19/F19*100 -> 44.045455 | M19: =P19/F19 -> 207.4405 | N19: =(F19*K19-H19*30.4)/F19 -> 2.3401818 | O19: =N19*F19 -> 2574.2 | P19: =O19*C19 -> 228184.55
B20: 46144 | C20: =VLOOKUP(B:B,'Курс валют'!A:D,4,0) -> 88.6429 | D20: 02E2607 | E20: клей Starkbond 521 A бочка 220кг | F20: 1100 | G20: 1106.3 | H20: 484.5 | I20: =G20-F20 -> 6.3 | J20: =I20/F20*100 -> 0.57272727 | K20: 15.73 | L20: =H20/F20*100 -> 44.045455 | M20: =P20/F20 -> 207.4405 | N20: =(F20*K20-H20*30.4)/F20 -> 2.3401818 | O20: =N20*F20 -> 2574.2 | P20: =O20*C20 -> 228184.55
B21: 46144 | C21: =VLOOKUP(B:B,'Курс валют'!A:D,4,0) -> 88.6429 | D21: 02E2608 | E21: клей Starkbond 521 A бочка 220кг | F21: 1100 | G21: 1106.3 | H21: 484.5 | I21: =G21-F21 -> 6.3 | J21: =I21/F21*100 -> 0.57272727 | K21: 15.73 | L21: =H21/F21*100 -> 44.045455 | M21: =P21/F21 -> 207.4405 | N21: =(F21*K21-H21*30.4)/F21 -> 2.3401818 | O21: =N21*F21 -> 2574.2 | P21: =O21*C21 -> 228184.55
B22: 46144 | C22: =VLOOKUP(B:B,'Курс валют'!A:D,4,0) -> 88.6429 | D22: 02E2609 | E22: клей Starkbond 521 A бочка 220кг | F22: 1100 | G22: 1106.3 | H22: 484.5 | I22: =G22-F22 -> 6.3 | J22: =I22/F22*100 -> 0.57272727 | K22: 15.73 | L22: =H22/F22*100 -> 44.045455 | M22: =P22/F22 -> 207.4405 | N22: =(F22*K22-H22*30.4)/F22 -> 2.3401818 | O22: =N22*F22 -> 2574.2 | P22: =O22*C22 -> 228184.55
B23: 46144 | C23: =VLOOKUP(B:B,'Курс валют'!A:D,4,0) -> 88.6429 | D23: 02E2610 | E23: клей Starkbond 521 A бочка 220кг | F23: 1100 | G23: 1106.3 | H23: 484.5 | I23: =G23-F23 -> 6.3 | J23: =I23/F23*100 -> 0.57272727 | K23: 15.73 | L23: =H23/F23*100 -> 44.045455 | M23: =P23/F23 -> 207.4405 | N23: =(F23*K23-H23*30.4)/F23 -> 2.3401818 | O23: =N23*F23 -> 2574.2 | P23: =O23*C23 -> 228184.55
B24: 46145 | C24: =VLOOKUP(B:B,'Курс валют'!A:D,4,0) -> 88.6429 | D24: 03E26R11 | E24: Клей Starkbond 745/41 А (бочка 200 кг) | F24: 2000 | G24: 2054.55 | H24: 0 | I24: =G24-F24 -> 54.55 | J24: =I24/F24*100 -> 2.7275 | K24: 2.43 | L24: =H24/F24*100 -> 0 | M24: =P24/F24 -> 215.40225 | N24: =(F24*K24-H24*3.04)/F24 -> 2.43 | O24: =N24*F24 -> 4860 | P24: =O24*C24 -> 430804.49
B25: 46145 | C25: =VLOOKUP(B:B,'Курс валют'!A:D,4,0) -> 88.6429 | D25: 03E2615 | E25: Отвердитель Starkbond 747/2C ведро 6 кг | F25: 6 | G25: 7.283 | H25: 0 | I25: 2.5 | J25: =I25/F25*100 -> 41.666667 | K25: 3.61 | L25: =H25/F25*100 -> 0 | M25: =P25/F25 -> 320.00087 | N25: =(F25*K25-H25*3.04)/F25 -> 3.61 | O25: =N25*F25 -> 21.66 | P25: =O25*C25 -> 1920.0052
B26: 46145 | C26: =VLOOKUP(B:B,'Курс валют'!A:D,4,0) -> 88.6429 | D26: 03E2601 | E26: Отвердитель Starkbond 521C 3.0 бочка 200кг | F26: 800 | G26: 805 | H26: 0 | I26: =G26-F26 -> 5 | J26: =I26/F26*100 -> 0.625 | K26: 1.84 | L26: =H26/F26*100 -> 0 | M26: =P26/F26 -> 163.10294 | N26: =(F26*K26-H26*3.04)/F26 -> 1.84 | O26: =N26*F26 -> 1472 | P26: =O26*C26 -> 130482.35
B27: 46145 | C27: =VLOOKUP(B:B,'Курс валют'!A:D,4,0) -> 88.6429 | D27: 03E2602 | E27: Отвердитель Starkbond 521C 3.0 бочка 200кг | F27: 800 | G27: 805 | H27: 0 | I27: =G27-F27 -> 5 | J27: =I27/F27*100 -> 0.625 | K27: 1.84 | L27: =H27/F27*100 -> 0 | M27: =P27/F27 -> 163.10294 | N27: =(F27*K27-H27*3.04)/F27 -> 1.84 | O27: =N27*F27 -> 1472 | P27: =O27*C27 -> 130482.35
B28: 46145 | C28: =VLOOKUP(B:B,'Курс валют'!A:D,4,0) -> 88.6429 | D28: 03E2603 | E28: Отвердитель Starkbond 521C 3.0 бочка 200кг | F28: 800 | G28: 805 | H28: 0 | I28: =G28-F28 -> 5 | J28: =I28/F28*100 -> 0.625 | K28: 1.84 | L28: =H28/F28*100 -> 0 | M28: =P28/F28 -> 163.10294 | N28: =(F28*K28-H28*3.04)/F28 -> 1.84 | O28: =N28*F28 -> 1472 | P28: =O28*C28 -> 130482.35
B29: 46145 | C29: =VLOOKUP(B:B,'Курс валют'!A:D,4,0) -> 88.6429 | D29: 03E2604 | E29: Отвердитель Starkbond 521C 3.0 бочка 200кг | F29: 800 | G29: 805 | H29: 0 | I29: =G29-F29 -> 5 | J29: =I29/F29*100 -> 0.625 | K29: 1.84 | L29: =H29/F29*100 -> 0 | M29: =P29/F29 -> 163.10294 | N29: =(F29*K29-H29*3.04)/F29 -> 1.84 | O29: =N29*F29 -> 1472 | P29: =O29*C29 -> 130482.35
B30: 46145 | C30: =VLOOKUP(B:B,'Курс валют'!A:D,4,0) -> 88.6429 | D30: 03E2605 | E30: Отвердитель Starkbond 521C 3.0 бочка 200кг | F30: 800 | G30: 805 | H30: 0 | I30: =G30-F30 -> 5 | J30: =I30/F30*100 -> 0.625 | K30: 1.84 | L30: =H30/F30*100 -> 0 | M30: =P30/F30 -> 163.10294 | N30: =(F30*K30-H30*3.04)/F30 -> 1.84 | O30: =N30*F30 -> 1472 | P30: =O30*C30 -> 130482.35
B31: 46145 | C31: =VLOOKUP(B:B,'Курс валют'!A:D,4,0) -> 88.6429 | D31: 03E2606 | E31: Отвердитель Starkbond 521C 3.0 бочка 200кг | F31: 800 | G31: 805 | H31: 0 | I31: =G31-F31 -> 5 | J31: =I31/F31*100 -> 0.625 | K31: 1.84 | L31: =H31/F31*100 -> 0 | M31: =P31/F31 -> 163.10294 | N31: =(F31*K31-H31*3.04)/F31 -> 1.84 | O31: =N31*F31 -> 1472 | P31: =O31*C31 -> 130482.35
B32: 46145 | C32: =VLOOKUP(B:B,'Курс валют'!A:D,4,0) -> 88.6429 | D32: 03E2607 | E32: Отвердитель Starkbond 521C 3.0 бочка 200кг | F32: 800 | G32: 805 | H32: 0 | I32: =G32-F32 -> 5 | J32: =I32/F32*100 -> 0.625 | K32: 1.84 | L32: =H32/F32*100 -> 0 | M32: =P32/F32 -> 163.10294 | N32: =(F32*K32-H32*3.04)/F32 -> 1.84 | O32: =N32*F32 -> 1472 | P32: =O32*C32 -> 130482.35
B33: 46145 | C33: =VLOOKUP(B:B,'Курс валют'!A:D,4,0) -> 88.6429 | D33: 03E2608 | E33: Отвердитель Starkbond 521C 3.0 бочка 200кг | F33: 800 | G33: 805 | H33: 0 | I33: =G33-F33 -> 5 | J33: =I33/F33*100 -> 0.625 | K33: 1.84 | L33: =H33/F33*100 -> 0 | M33: =P33/F33 -> 163.10294 | N33: =(F33*K33-H33*3.04)/F33 -> 1.84 | O33: =N33*F33 -> 1472 | P33: =O33*C33 -> 130482.35
B34: 46145 | C34: =VLOOKUP(B:B,'Курс валют'!A:D,4,0) -> 88.6429 | D34: 03E2609 | E34: Отвердитель Starkbond 521C 3.0 бочка 200кг | F34: 800 | G34: 805 | H34: 0 | I34: =G34-F34 -> 5 | J34: =I34/F34*100 -> 0.625 | K34: 1.84 | L34: =H34/F34*100 -> 0 | M34: =P34/F34 -> 163.10294 | N34: =(F34*K34-H34*3.04)/F34 -> 1.84 | O34: =N34*F34 -> 1472 | P34: =O34*C34 -> 130482.35
B35: 46145 | C35: =VLOOKUP(B:B,'Курс валют'!A:D,4,0) -> 88.6429 | D35: 03E2610 | E35: Отвердитель Starkbond 521C 3.0 бочка 200кг | F35: 800 | G35: 805 | H35: 0 | I35: =G35-F35 -> 5 | J35: =I35/F35*100 -> 0.625 | K35: 1.84 | L35: =H35/F35*100 -> 0 | M35: =P35/F35 -> 163.10294 | N35: =(F35*K35-H35*3.04)/F35 -> 1.84 | O35: =N35*F35 -> 1472 | P35: =O35*C35 -> 130482.35
B36: 46146 | C36: =VLOOKUP(B:B,'Курс валют'!A:D,4,0) -> 88.6429 | D36: 04E26R21 | E36: Sancos PRONATE 501B бочка 240 кг | F36: 1920 | G36: 1953.03 | H36: 0 | I36: =G36-F36 -> 33.03 | J36: =I36/F36*100 -> 1.7203125 | K36: 2.64 | L36: =H36/F36*100 -> 0 | M36: =P36/F36 -> 234.01726 | N36: =(F36*K36-H36*3.04)/F36 -> 2.64 | O36: =N36*F36 -> 5068.8 | P36: =O36*C36 -> 449313.13
B37: 46146 | C37: =VLOOKUP(B:B,'Курс валют'!A:D,4,0) -> 88.6429 | D37: 04E2601 | E37: клей Starkbond 521 A бочка 220кг | F37: 1100 | G37: 1106.5 | H37: 484.5 | I37: =G37-F37 -> 6.5 | J37: =I37/F37*100 -> 0.59090909 | K37: 12.29 | L37: =H37/F37*100 -> 44.045455 | M37: =P37/F37 -> 210.94996 | N37: =(F37*K37-H37*22.5)/F37 -> 2.3797727 | O37: =N37*F37 -> 2617.75 | P37: =O37*C37 -> 232044.95
B38: 46146 | C38: =VLOOKUP(B:B,'Курс валют'!A:D,4,0) -> 88.6429 | D38: 04E2602 | E38: клей Starkbond 521 A бочка 220кг | F38: 1100 | G38: 1106.5 | H38: 0 | I38: =G38-F38 -> 6.5 | J38: =I38/F38*100 -> 0.59090909 | K38: 2.36 | L38: =H38/F38*100 -> 0 | M38: =P38/F38 -> 209.19724 | N38: =(F38*K38-H38*3.04)/F38 -> 2.36 | O38: =N38*F38 -> 2596 | P38: =O38*C38 -> 230116.97
B39: 46146 | C39: =VLOOKUP(B:B,'Курс валют'!A:D,4,0) -> 88.6429 | D39: 04E2603 | E39: клей Starkbond 521 A бочка 220кг | F39: 1100 | G39: 1106.5 | H39: 0 | I39: =G39-F39 -> 6.5 | J39: =I39/F39*100 -> 0.59090909 | K39: 2.36 | L39: =H39/F39*100 -> 0 | M39: =P39/F39 -> 209.19724 | N39: =(F39*K39-H39*3.04)/F39 -> 2.36 | O39: =N39*F39 -> 2596 | P39: =O39*C39 -> 230116.97
B40: 46146 | C40: =VLOOKUP(B:B,'Курс валют'!A:D,4,0) -> 88.6429 | D40: 04E2604 | E40: клей Starkbond 521 A бочка 220кг | F40: 1100 | G40: 1106.5 | H40: 0 | I40: =G40-F40 -> 6.5 | J40: =I40/F40*100 -> 0.59090909 | K40: 2.36 | L40: =H40/F40*100 -> 0 | M40: =P40/F40 -> 209.19724 | N40: =(F40*K40-H40*3.04)/F40 -> 2.36 | O40: =N40*F40 -> 2596 | P40: =O40*C40 -> 230116.97
B41: 46146 | C41: =VLOOKUP(B:B,'Курс валют'!A:D,4,0) -> 88.6429 | D41: 04E2605 | E41: клей Starkbond 521 A бочка 220кг | F41: 1100 | G41: 1106.5 | H41: 0 | I41: =G41-F41 -> 6.5 | J41: =I41/F41*100 -> 0.59090909 | K41: 2.36 | L41: =H41/F41*100 -> 0 | M41: =P41/F41 -> 209.19724 | N41: =(F41*K41-H41*3.04)/F41 -> 2.36 | O41: =N41*F41 -> 2596 | P41: =O41*C41 -> 230116.97
B42: 46146 | C42: =VLOOKUP(B:B,'Курс валют'!A:D,4,0) -> 88.6429 | D42: 04E2606 | E42: клей Starkbond 521 A бочка 220кг | F42: 1100 | G42: 1106.5 | H42: 0 | I42: =G42-F42 -> 6.5 | J42: =I42/F42*100 -> 0.59090909 | K42: 2.36 | L42: =H42/F42*100 -> 0 | M42: =P42/F42 -> 209.19724 | N42: =(F42*K42-H42*3.04)/F42 -> 2.36 | O42: =N42*F42 -> 2596 | P42: =O42*C42 -> 230116.97
B43: 46146 | C43: =VLOOKUP(B:B,'Курс валют'!A:D,4,0) -> 88.6429 | D43: 04E2607 | E43: клей Starkbond 521 A бочка 220кг | F43: 1100 | G43: 1106.5 | H43: 0 | I43: =G43-F43 -> 6.5 | J43: =I43/F43*100 -> 0.59090909 | K43: 2.36 | L43: =H43/F43*100 -> 0 | M43: =P43/F43 -> 209.19724 | N43: =(F43*K43-H43*3.04)/F43 -> 2.36 | O43: =N43*F43 -> 2596 | P43: =O43*C43 -> 230116.97
B44: 46146 | C44: =VLOOKUP(B:B,'Курс валют'!A:D,4,0) -> 88.6429 | D44: 04E2608 | E44: клей Starkbond 521 A бочка 220кг | F44: 1100 | G44: 1106.5 | H44: 0 | I44: =G44-F44 -> 6.5 | J44: =I44/F44*100 -> 0.59090909 | K44: 2.36 | L44: =H44/F44*100 -> 0 | M44: =P44/F44 -> 209.19724 | N44: =(F44*K44-H44*3.04)/F44 -> 2.36 | O44: =N44*F44 -> 2596 | P44: =O44*C44 -> 230116.97
B45: 46146 | C45: =VLOOKUP(B:B,'Курс валют'!A:D,4,0) -> 88.6429 | D45: 04E26R11 | E45: Клей Starkbond 2025 RC7 LV 220 кг | F45: 1980 | G45: 2004.32 | H45: 0 | I45: =G45-F45 -> 24.32 | J45: =I45/F45*100 -> 1.2282828 | K45: 1.82 | L45: =H45/F45*100 -> 0 | M45: =P45/F45 -> 161.33008 | N45: =(F45*K45-H45*3.04)/F45 -> 1.82 | O45: =N45*F45 -> 3603.6 | P45: =O45*C45 -> 319433.55
B46: 46146 | C46: =VLOOKUP(B:B,'Курс валют'!A:D,4,0) -> 88.6429 | D46: 04E2609 | E46: клей Starkbond 521 A бочка 220кг | F46: 1100 | G46: 1106.5 | H46: 0 | I46: =G46-F46 -> 6.5 | J46: =I46/F46*100 -> 0.59090909 | K46: 2.36 | L46: =H46/F46*100 -> 0 | M46: =P46/F46 -> 209.19724 | N46: =(F46*K46-H46*3.04)/F46 -> 2.36 | O46: =N46*F46 -> 2596 | P46: =O46*C46 -> 230116.97
B47: 46146 | C47: =VLOOKUP(B:B,'Курс валют'!A:D,4,0) -> 88.6429 | D47: 04E2610 | E47: клей Starkbond 521 A бочка 220кг | F47: 1100 | G47: 1106.5 | H47: 0 | I47: =G47-F47 -> 6.5 | J47: =I47/F47*100 -> 0.59090909 | K47: 2.36 | L47: =H47/F47*100 -> 0 | M47: =P47/F47 -> 209.19724 | N47: =(F47*K47-H47*3.04)/F47 -> 2.36 | O47: =N47*F47 -> 2596 | P47: =O47*C47 -> 230116.97
B48: 46147 | C48: =VLOOKUP(B:B,'Курс валют'!A:D,4,0) -> 88.2651 | D48: 05E2601 | E48: клей Starkbond 521 A бочка 220кг | F48: 1100 | G48: 1108.5 | H48: 0 | I48: =G48-F48 -> 8.5 | J48: =I48/F48*100 -> 0.77272727 | K48: 2.37 | L48: =H48/F48*100 -> 0 | M48: =P48/F48 -> 209.18829 | N48: =(F48*K48-H48*3.04)/F48 -> 2.37 | O48: =N48*F48 -> 2607 | P48: =O48*C48 -> 230107.12
B49: 46147 | C49: =VLOOKUP(B:B,'Курс валют'!A:D,4,0) -> 88.2651 | D49: 05E2602 | E49: клей Starkbond 521 A бочка 220кг | F49: 1100 | G49: 1108.5 | H49: 0 | I49: =G49-F49 -> 8.5 | J49: =I49/F49*100 -> 0.77272727 | K49: 2.36 | L49: =H49/F49*100 -> 0 | M49: =P49/F49 -> 208.30564 | N49: =(F49*K49-H49*3.04)/F49 -> 2.36 | O49: =N49*F49 -> 2596 | P49: =O49*C49 -> 229136.2
... B59: 46147 | C59: =VLOOKUP(B:B,'Курс валют'!A:D,4,0) -> 88.2651 | D59: 05E2610 | E59: клей Starkbond 521 A бочка 220кг | F59: 1100 | G59: 1108.5 | H59: 0 | I59: =G59-F59 -> 8.5 | J59: =I59/F59*100 -> 0.77272727 | K59: 2.37 | L59: =H59/F59*100 -> 0 | M59: =P59/F59 -> 209.18829 | N59: =(F59*K59-H59*3.04)/F59 -> 2.37 | O59: =N59*F59 -> 2607 | P59: =O59*C59 -> 230107.12
B60: 46147 | C60: =VLOOKUP(B:B,'Курс валют'!A:D,4,0) -> 88.2651 | D60: 24K25R21EX06 | E60: Sancos PRONATE 501B бочка 80 кг | F60: 160 | G60: 160 | H60: 0 | I60: =G60-F60 -> 0 | J60: =I60/F60*100 -> 0 | K60: 2.71 | L60: =H60/F60*100 -> 0 | M60: =P60/F60 -> 239.19842 | N60: =(F60*K60-H60*3.04)/F60 -> 2.71 | O60: =N60*F60 -> 433.6 | P60: =O60*C60 -> 38271.747 | R60: Акт № 41 о продлении срока годности ГП
B61: 46147 | C61: =VLOOKUP(B:B,'Курс валют'!A:D,4,0) -> 88.2651 | D61: 22E25R11EX06 | E61: Starkbond 2004 бочка 225 кг | F61: 900 | G61: 900 | H61: 0 | I61: =G61-F61 -> 0 | J61: =I61/F61*100 -> 0 | K61: 3.97 | L61: =H61/F61*100 -> 0 | M61: =P61/F61 -> 350.41245 | N61: =(F61*K61-H61*3.04)/F61 -> 3.97 | O61: =N61*F61 -> 3573 | P61: =O61*C61 -> 315371.2 | R61: Акт № 41 о продлении срока годности ГП
B62: 46147 | C62: =VLOOKUP(B:B,'Курс валют'!A:D,4,0) -> 88.2651 | D62: 23E25R11EX06 | E62: Starkbond 2004 бочка 225 кг | F62: 675 | G62: 675 | H62: 0 | I62: =G62-F62 -> 0 | J62: =I62/F62*100 -> 0 | K62: 3.97 | L62: =H62/F62*100 -> 0 | M62: =P62/F62 -> 350.41245 | N62: =(F62*K62-H62*3.04)/F62 -> 3.97 | O62: =N62*F62 -> 2679.75 | P62: =O62*C62 -> 236528.4 | R62: Акт № 41 о продлении срока годности ГП
B63: 46147 | C63: =VLOOKUP(B:B,'Курс валют'!A:D,4,0) -> 88.2651 | D63: 23E25R11EX06 | E63: Starkbond 2004 бочка 225 кг | F63: 225 | G63: 225 | H63: 0 | I63: =G63-F63 -> 0 | J63: =I63/F63*100 -> 0 | K63: 3.97 | L63: =H63/F63*100 -> 0 | M63: =P63/F63 -> 350.41245 | N63: =(F63*K63-H63*3.04)/F63 -> 3.97 | O63: =N63*F63 -> 893.25 | P63: =O63*C63 -> 78842.801 | R63: Акт № 41 о продлении срока годности ГП
B64: 46147 | C64: =VLOOKUP(B:B,'Курс валют'!A:D,4,0) -> 88.2651 | D64: 21E25R11EX06 | E64: Starkbond 2015 бочка 220кг | F64: 220 | G64: 220 | H64: 0 | I64: =G64-F64 -> 0 | J64: =I64/F64*100 -> 0 | K64: 3.22 | L64: =H64/F64*100 -> 0 | M64: =P64/F64 -> 284.21362 | N64: =(F64*K64-H64*3.04)/F64 -> 3.22 | O64: =N64*F64 -> 708.4 | P64: =O64*C64 -> 62526.997 | R64: Акт № 41 о продлении срока годности ГП
B65: 46147 | C65: =VLOOKUP(B:B,'Курс валют'!A:D,4,0) -> 88.2651 | D65: 04E25R11EX06 | E65: Клей Starkbond 2025 RC7 LV ведро 20кг | F65: 20 | G65: 20 | H65: 0 | I65: =G65-F65 -> 0 | J65: =I65/F65*100 -> 0 | K65: 2.2 | L65: =H65/F65*100 -> 0 | M65: =P65/F65 -> 194.18322 | N65: =(F65*K65-H65*3.04)/F65 -> 2.2 | O65: =N65*F65 -> 44 | P65: =O65*C65 -> 3883.6644 | R65: Акт № 41 о продлении срока годности ГП
B66: 46147 | C66: =VLOOKUP(B:B,'Курс валют'!A:D,4,0) -> 88.2651 | D66: 04K25R11EX06 | E66: Клей Starkbond 745/41 А (ведро 20кг) | F66: 640 | G66: 640 | H66: 0 | I66: =G66-F66 -> 0 | J66: =I66/F66*100 -> 0 | K66: 2.47 | L66: =H66/F66*100 -> 0 | M66: =P66/F66 -> 218.0148 | N66: =(F66*K66-H66*3.04)/F66 -> 2.47 | O66: =N66*F66 -> 1580.8 | P66: =O66*C66 -> 139529.47 | R66: Акт № 41 о продлении срока годности ГП
B67: 46148 | C67: =VLOOKUP(B:B,'Курс валют'!A:D,4,0) -> 88.3463 | D67: 06E2611 | E67: SANCOS PRO SAFETY 145 канистра 23,18 кг | F67: 927.2 | G67: 940 | H67: 0 | I67: =G67-F67 -> 12.8 | J67: =I67/F67*100 -> 1.3805004 | K67: 1.83 | L67: =H67/F67*100 -> 0 | M67: =P67/F67 -> 161.67373 | N67: =(F67*K67-H67*3.04)/F67 -> 1.83 | O67: =N67*F67 -> 1696.776 | P67: =O67*C67 -> 149903.88
B68: 46148 | C68: =VLOOKUP(B:B,'Курс валют'!A:D,4,0) -> 88.3463 | D68: 06E26R11 | E68: Клей Starkbond 2025 RC7 LV 220 кг | F68: 1760 | G68: 1781.32 | H68: 0 | I68: =G68-F68 -> 21.32 | J68: =I68/F68*100 -> 1.2113636 | K68: 1.82 | L68: =H68/F68*100 -> 0 | M68: =P68/F68 -> 160.79027 | N68: =(F68*K68-H68*3.04)/F68 -> 1.82 | O68: =N68*F68 -> 3203.2 | P68: =O68*C68 -> 282990.87
B69: 46148 | C69: =VLOOKUP(B:B,'Курс валют'!A:D,4,0) -> 88.3463 | D69: 06E26R21 | E69: Sancos PRONATE 501B бочка 240 кг | F69: 2160 | G69: 2187.8 | H69: 0 | I69: =G69-F69 -> 27.8 | J69: =I69/F69*100 -> 1.287037 | K69: 2.63 | L69: =H69/F69*100 -> 0 | M69: =P69/F69 -> 232.35077 | N69: =(F69*K69-H69*3.04)/F69 -> 2.63 | O69: =N69*F69 -> 5680.8 | P69: =O69*C69 -> 501877.66
B70: 46149 | C70: =VLOOKUP(B:B,'Курс валют'!A:D,4,0) -> 88.06 | D70: 07E26R11 | E70: Клей Starkbond 2014 бочка 225кг | F70: 2250 | G70: 2293.65 | H70: 0 | I70: =G70-F70 -> 43.65 | J70: =I70/F70*100 -> 1.94 | K70: 2.07 | L70: =H70/F70*100 -> 0 | M70: =P70/F70 -> 182.2842 | N70: =(F70*K70-H70*3.04)/F70 -> 2.07 | O70: =N70*F70 -> 4657.5 | P70: =O70*C70 -> 410139.45
B71: 46149 | C71: =VLOOKUP(B:B,'Курс валют'!A:D,4,0) -> 88.06 | D71: 07E26R21 | E71: Sancos PRONATE 501B бочка 240 кг | F71: 2160 | G71: 2187.8 | H71: 0 | I71: =G71-F71 -> 27.8 | J71: =I71/F71*100 -> 1.287037 | K71: 2.63 | L71: =H71/F71*100 -> 0 | M71: =P71/F71 -> 231.5978 | N71: =(F71*K71-H71*3.04)/F71 -> 2.63 | O71: =N71*F71 -> 5680.8 | P71: =O71*C71 -> 500251.25
B72: 46149 | C72: =VLOOKUP(B:B,'Курс валют'!A:D,4,0) -> 88.06 | D72: 07E2601 | E72: Sancos PROPOL 101A бочка 180 кг | F72: 6480 | G72: 6532 | H72: 0 | I72: =G72-F72 -> 52 | J72: =I72/F72*100 -> 0.80246914 | K72: 2.3 | L72: =H72/F72*100 -> 0 | M72: =P72/F72 -> 202.538 | N72: =(F72*K72-H72*3.04)/F72 -> 2.3 | O72: =N72*F72 -> 14904 | P72: =O72*C72 -> 1312446.2
B73: 46149 | C73: =VLOOKUP(B:B,'Курс валют'!A:D,4,0) -> 88.06 | D73: 16C2601 | E73: SANCOS PRO SAFETY 160 А канистра 11,59 кг | F73: 11.59 | G73: 11.59 | H73: 0 | I73: =G73-F73 -> 0 | J73: =I73/F73*100 -> 0 | K73: 2.05 | L73: =H73/F73*100 -> 0 | M73: =P73/F73 -> 180.523 | N73: =(F73*K73-H73*3.04)/F73 -> 2.05 | O73: =N73*F73 -> 23.7595 | P73: =O73*C73 -> 2092.2616 | R73: смена номенклатуры для отгрузки Спецзаказ (заказ клиента ШККА-000196 от 04.05.26)
B74: 46150 | C74: =VLOOKUP(B:B,'Курс валют'!A:D,4,0) -> 87.8897 | D74: 08E2601 | E74: Отвердитель Starkbond 521C 11.0 бочка 200кг | F74: 800 | G74: 805.14 | H74: 0 | I74: =G74-F74 -> 5.14 | J74: =I74/F74*100 -> 0.6425 | K74: 1.92 | L74: =H74/F74*100 -> 0 | M74: =P74/F74 -> 168.74822 | N74: =(F74*K74-H74*3.04)/F74 -> 1.92 | O74: =N74*F74 -> 1536 | P74: =O74*C74 -> 134998.58
B75: 46150 | C75: =VLOOKUP(B:B,'Курс валют'!A:D,4,0) -> 87.8897 | D75: 08E2602 | E75: Отвердитель Starkbond 521C 11.0 бочка 200кг | F75: 800 | G75: 805.14 | H75: 0 | I75: =G75-F75 -> 5.14 | J75: =I75/F75*100 -> 0.6425 | K75: 1.91 | L75: =H75/F75*100 -> 0 | M75: =P75/F75 -> 167.86933 | N75: =(F75*K75-H75*3.04)/F75 -> 1.91 | O75: =N75*F75 -> 1528 | P75: =O75*C75 -> 134295.46
B76: 46150 | C76: =VLOOKUP(B:B,'Курс валют'!A:D,4,0) -> 87.8897 | D76: 08E2603 | E76: Отвердитель Starkbond 521C 11.0 бочка 200кг | F76: 800 | G76: 805.14 | H76: 0 | I76: =G76-F76 -> 5.14 | J76: =I76/F76*100 -> 0.6425 | K76: 1.91 | L76: =H76/F76*100 -> 0 | M76: =P76/F76 -> 167.86933 | N76: =(F76*K76-H76*3.04)/F76 -> 1.91 | O76: =N76*F76 -> 1528 | P76: =O76*C76 -> 134295.46
B77: 46150 | C77: =VLOOKUP(B:B,'Курс валют'!A:D,4,0) -> 87.8897 | D77: 08E2604 | E77: Отвердитель Starkbond 521C 11.0 бочка 200кг | F77: 800 | G77: 805.14 | H77: 0 | I77: =G77-F77 -> 5.14 | J77: =I77/F77*100 -> 0.6425 | K77: 1.91 | L77: =H77/F77*100 -> 0 | M77: =P77/F77 -> 167.86933 | N77: =(F77*K77-H77*3.04)/F77 -> 1.91 | O77: =N77*F77 -> 1528 | P77: =O77*C77 -> 134295.46
B78: 46150 | C78: =VLOOKUP(B:B,'Курс валют'!A:D,4,0) -> 87.8897 | D78: 08E2605 | E78: Отвердитель Starkbond 521C 11.0 бочка 200кг | F78: 800 | G78: 805.14 | H78: 0 | I78: =G78-F78 -> 5.14 | J78: =I78/F78*100 -> 0.6425 | K78: 1.91 | L78: =H78/F78*100 -> 0 | M78: =P78/F78 -> 167.86933 | N78: =(F78*K78-H78*3.04)/F78 -> 1.91 | O78: =N78*F78 -> 1528 | P78: =O78*C78 -> 134295.46
B79: 46150 | C79: =VLOOKUP(B:B,'Курс валют'!A:D,4,0) -> 87.8897 | D79: 08E2606 | E79: Отвердитель Starkbond 521C 11.0 бочка 200кг | F79: 800 | G79: 805.14 | H79: 0 | I79: =G79-F79 -> 5.14 | J79: =I79/F79*100 -> 0.6425 | K79: 1.92 | L79: =H79/F79*100 -> 0 | M79: =P79/F79 -> 168.74822 | N79: =(F79*K79-H79*3.04)/F79 -> 1.92 | O79: =N79*F79 -> 1536 | P79: =O79*C79 -> 134998.58
B80: 46150 | C80: =VLOOKUP(B:B,'Курс валют'!A:D,4,0) -> 87.8897 | D80: 08E26R21 | E80: Sancos PRONATE 501B бочка 240 кг | F80: 2160 | G80: 2187.44 | H80: 0 | I80: =G80-F80 -> 27.44 | J80: =I80/F80*100 -> 1.2703704 | K80: 2.63 | L80: =H80/F80*100 -> 0 | M80: =P80/F80 -> 231.14991 | N80: =(F80*K80-H80*3.04)/F80 -> 2.63 | O80: =N80*F80 -> 5680.8 | P80: =O80*C80 -> 499283.81
B81: 46150 | C81: =VLOOKUP(B:B,'Курс валют'!A:D,4,0) -> 87.8897 | D81: 08E2607 | E81: Отвердитель Starkbond 521C 11.0 бочка 200кг | F81: 800 | G81: 805.14 | H81: 0 | I81: =G81-F81 -> 5.14 | J81: =I81/F81*100 -> 0.6425 | K81: 1.91 | L81: =H81/F81*100 -> 0 | M81: =P81/F81 -> 167.86933 | N81: =(F81*K81-H81*3.04)/F81 -> 1.91 | O81: =N81*F81 -> 1528 | P81: =O81*C81 -> 134295.46
B82: 46150 | C82: =VLOOKUP(B:B,'Курс валют'!A:D,4,0) -> 87.8897 | D82: 08E2608 | E82: Отвердитель Starkbond 521C 11.0 бочка 200кг | F82: 800 | G82: 805.14 | H82: 0 | I82: =G82-F82 -> 5.14 | J82: =I82/F82*100 -> 0.6425 | K82: 1.91 | L82: =H82/F82*100 -> 0 | M82: =P82/F82 -> 167.86933 | N82: =(F82*K82-H82*3.04)/F82 -> 1.91 | O82: =N82*F82 -> 1528 | P82: =O82*C82 -> 134295.46
B83: 46150 | C83: =VLOOKUP(B:B,'Курс валют'!A:D,4,0) -> 87.8897 | D83: 08E26R11 | E83: Клей Starkbond 2014 бочка 225кг | F83: 2250 | G83: 2293.65 | H83: 0 | I83: =G83-F83 -> 43.65 | J83: =I83/F83*100 -> 1.94 | K83: 2.07 | L83: =H83/F83*100 -> 0 | M83: =P83/F83 -> 181.93168 | N83: =(F83*K83-H83*3.04)/F83 -> 2.07 | O83: =N83*F83 -> 4657.5 | P83: =O83*C83 -> 409346.28
B84: 46150 | C84: =VLOOKUP(B:B,'Курс валют'!A:D,4,0) -> 87.8897 | D84: 08E2609 | E84: Отвердитель Starkbond 521C 11.0 бочка 200кг | F84: 800 | G84: 805.14 | H84: 0 | I84: =G84-F84 -> 5.14 | J84: =I84/F84*100 -> 0.6425 | K84: 1.91 | L84: =H84/F84*100 -> 0 | M84: =P84/F84 -> 167.86933 | N84: =(F84*K84-H84*3.04)/F84 -> 1.91 | O84: =N84*F84 -> 1528 | P84: =O84*C84 -> 134295.46
B85: 46150 | C85: =VLOOKUP(B:B,'Курс валют'!A:D,4,0) -> 87.8897 | D85: 08E2610 | E85: Отвердитель Starkbond 521C 11.0 бочка 200кг | F85: 800 | G85: 805.14 | H85: 0 | I85: =G85-F85 -> 5.14 | J85: =I85/F85*100 -> 0.6425 | K85: 1.92 | L85: =H85/F85*100 -> 0 | M85: =P85/F85 -> 168.74822 | N85: =(F85*K85-H85*3.04)/F85 -> 1.92 | O85: =N85*F85 -> 1536 | P85: =O85*C85 -> 134998.58
... B132: 46156 | C132: =VLOOKUP(B:B,'Курс валют'!A:D,4,0) -> 85.9017 | D132: 14E2603 | E132: клей Starkbond 521 A бочка 220кг | F132: 1100 | G132: 1108.5 | H132: 0 | I132: =G132-F132 -> 8.5 | J132: =I132/F132*100 -> 0.77272727 | K132: 2.37 | L132: =H132/F132*100 -> 0 | M132: =P132/F132 -> 203.58703 | N132: =(F132*K132-H132*3.04)/F132 -> 2.37 | O132: =N132*F132 -> 2607 | P132: =O132*C132 -> 223945.73
B133: 46156 | C133: =VLOOKUP(B:B,'Курс валют'!A:D,4,0) -> 85.9017 | D133: 06E25R11EX06R0190 | E133: Клей Starkbond 525A бочка 200 кг | F133: 1000 | G133: 1000 | H133: 0 | I133: =G133-F133 -> 0 | J133: =I133/F133*100 -> 0 | K133: 2.6 | L133: =H133/F133*100 -> 0 | M133: =P133/F133 -> 223.34442 | N133: =(F133*K133-H133*3.04)/F133 -> 2.6 | O133: =N133*F133 -> 2600 | P133: =O133*C133 -> 223344.42 | R133: Акт № 42 о продлении срока годности ГП адресное хранение
B134: 46156 | C134: =VLOOKUP(B:B,'Курс валют'!A:D,4,0) -> 85.9017 | D134: 27DP2601 | E134: Отвердитель Starkbond 525C 3.0 Бочка 200 кг | F134: 800 | G134: 800 | H134: 0 | I134: =G134-F134 -> 0 | J134: =I134/F134*100 -> 0 | K134: 2.9 | L134: =H134/F134*100 -> 0 | M134: =P134/F134 -> 249.11493 | N134: =(F134*K134-H134*3.04)/F134 -> 2.9 | O134: =N134*F134 -> 2320 | P134: =O134*C134 -> 199291.94 | R134: Акт № 38 о продлении срока годности ГП 27.04.26
B135: 46156 | C135: =VLOOKUP(B:B,'Курс валют'!A:D,4,0) -> 85.9017 | D135: 27DP2601. | E135: Отвердитель Starkbond 525C 3.0 Бочка 200 кг | F135: 400 | G135: 400 | H135: 0 | I135: =G135-F135 -> 0 | J135: =I135/F135*100 -> 0 | K135: 2.54 | L135: =H135/F135*100 -> 0 | M135: =P135/F135 -> 218.19032 | N135: =(F135*K135-H135*3.04)/F135 -> 2.54 | O135: =N135*F135 -> 1016 | P135: =O135*C135 -> 87276.127 | R135: Акт № 38 о продлении срока годности ГП 27.04.26
B136: 46156 | C136: =VLOOKUP(B:B,'Курс валют'!A:D,4,0) -> 85.9017 | D136: 28I2215EX35R0190 | E136: Отвердитель Starkbond 521C бочка 200кг | F136: 200 | G136: 200 | H136: 0 | I136: =G136-F136 -> 0 | J136: =I136/F136*100 -> 0 | K136: 1.98 | L136: =H136/F136*100 -> 0 | M136: =P136/F136 -> 170.08537 | N136: =(F136*K136-H136*3.04)/F136 -> 1.98 | O136: =N136*F136 -> 396 | P136: =O136*C136 -> 34017.073 | R136: Акт №25 от 20.02.26 продление ГП адресного хранения
B137: 46156 | C137: =VLOOKUP(B:B,'Курс валют'!A:D,4,0) -> 85.9017 | D137: 30H2416EX13R0190 | E137: Отвердитель Starkbond 521C бочка 200кг | F137: 800 | G137: 800 | H137: 0 | I137: =G137-F137 -> 0 | J137: =I137/F137*100 -> 0 | K137: 1.98 | L137: =H137/F137*100 -> 0 | M137: =P137/F137 -> 170.08537 | N137: =(F137*K137-H137*3.04)/F137 -> 1.98 | O137: =N137*F137 -> 1584 | P137: =O137*C137 -> 136068.29 | R137: Акт №25 от 20.02.26 продление ГП адресного хранения
B138: 46156 | C138: =VLOOKUP(B:B,'Курс валют'!A:D,4,0) -> 85.9017 | D138: 25F2501EX03R0190 | E138: Отвердитель Starkbond 525C 3.0 Бочка 200 кг | F138: 185 | G138: 185 | H138: 0 | I138: =G138-F138 -> 0 | J138: =I138/F138*100 -> 0 | K138: 2.54 | L138: =H138/F138*100 -> 0 | M138: =P138/F138 -> 218.19032 | N138: =(F138*K138-H138*3.04)/F138 -> 2.54 | O138: =N138*F138 -> 469.9 | P138: =O138*C138 -> 40365.209 | R138: Акт № 40 о продлении срока годности ГП 30.04.26
B139: 46156 | C139: =VLOOKUP(B:B,'Курс валют'!A:D,4,0) -> 85.9017 | D139: 15E2501EX03R0190 | E139: Отвердитель Starkbond 525C 3.0 Бочка 200 кг | F139: 200 | G139: 200 | H139: 0 | I139: =G139-F139 -> 0 | J139: =I139/F139*100 -> 0 | K139: 2.9 | L139: =H139/F139*100 -> 0 | M139: =P139/F139 -> 249.11493 | N139: =(F139*K139-H139*3.04)/F139 -> 2.9 | O139: =N139*F139 -> 580 | P139: =O139*C139 -> 49822.986 | R139: Акт № 40 о продлении срока годности ГП 30.04.26
B140: 46156 | C140: =VLOOKUP(B:B,'Курс валют'!A:D,4,0) -> 85.9017 | D140: 14E2604 | E140: клей Starkbond 521 A бочка 220кг | F140: 1100 | G140: 1108.5 | H140: 0 | I140: =G140-F140 -> 8.5 | J140: =I140/F140*100 -> 0.77272727 | K140: 2.37 | L140: =H140/F140*100 -> 0 | M140: =P140/F140 -> 203.58703 | N140: =(F140*K140-H140*3.04)/F140 -> 2.37 | O140: =N140*F140 -> 2607 | P140: =O140*C140 -> 223945.73
B141: 46156 | C141: =VLOOKUP(B:B,'Курс валют'!A:D,4,0) -> 85.9017 | D141: 14E2605 | E141: клей Starkbond 521 A бочка 220кг | F141: 1100 | G141: 1108.5 | H141: 0 | I141: =G141-F141 -> 8.5 | J141: =I141/F141*100 -> 0.77272727 | K141: 2.37 | L141: =H141/F141*100 -> 0 | M141: =P141/F141 -> 203.58703 | N141: =(F141*K141-H141*3.04)/F141 -> 2.37 | O141: =N141*F141 -> 2607 | P141: =O141*C141 -> 223945.73
B142: 46156 | C142: =VLOOKUP(B:B,'Курс валют'!A:D,4,0) -> 85.9017 | D142: 14E2606 | E142: клей Starkbond 521 A бочка 220кг | F142: 1100 | G142: 1108.5 | H142: 0 | I142: =G142-F142 -> 8.5 | J142: =I142/F142*100 -> 0.77272727 | K142: 2.37 | L142: =H142/F142*100 -> 0 | M142: =P142/F142 -> 203.58703 | N142: =(F142*K142-H142*3.04)/F142 -> 2.37 | O142: =N142*F142 -> 2607 | P142: =O142*C142 -> 223945.73
B143: 46156 | C143: =VLOOKUP(B:B,'Курс валют'!A:D,4,0) -> 85.9017 | D143: 14E2607 | E143: клей Starkbond 521 A бочка 220кг | F143: 1100 | G143: 1108.5 | H143: 0 | I143: =G143-F143 -> 8.5 | J143: =I143/F143*100 -> 0.77272727 | K143: 2.37 | L143: =H143/F143*100 -> 0 | M143: =P143/F143 -> 203.58703 | N143: =(F143*K143-H143*3.04)/F143 -> 2.37 | O143: =N143*F143 -> 2607 | P143: =O143*C143 -> 223945.73
B144: 46156 | C144: =VLOOKUP(B:B,'Курс валют'!A:D,4,0) -> 85.9017 | D144: 14E2608 | E144: клей Starkbond 521 A бочка 220кг | F144: 1100 | G144: 1108.5 | H144: 0 | I144: =G144-F144 -> 8.5 | J144: =I144/F144*100 -> 0.77272727 | K144: 2.37 | L144: =H144/F144*100 -> 0 | M144: =P144/F144 -> 203.58703 | N144: =(F144*K144-H144*3.04)/F144 -> 2.37 | O144: =N144*F144 -> 2607 | P144: =O144*C144 -> 223945.73
B145: 46156 | C145: =VLOOKUP(B:B,'Курс валют'!A:D,4,0) -> 85.9017 | D145: 14E2609 | E145: клей Starkbond 521 A бочка 220кг | F145: 1100 | G145: 1108.5 | H145: 0 | I145: =G145-F145 -> 8.5 | J145: =I145/F145*100 -> 0.77272727 | K145: 2.37 | L145: =H145/F145*100 -> 0 | M145: =P145/F145 -> 203.58703 | N145: =(F145*K145-H145*3.04)/F145 -> 2.37 | O145: =N145*F145 -> 2607 | P145: =O145*C145 -> 223945.73
B146: 46156 | C146: =VLOOKUP(B:B,'Курс валют'!A:D,4,0) -> 85.9017 | D146: 14E2610 | E146: клей Starkbond 521 A бочка 220кг | F146: 1100 | G146: 1108.5 | H146: 0 | I146: =G146-F146 -> 8.5 | J146: =I146/F146*100 -> 0.77272727 | K146: 2.37 | L146: =H146/F146*100 -> 0 | M146: =P146/F146 -> 203.58703 | N146: =(F146*K146-H146*3.04)/F146 -> 2.37 | O146: =N146*F146 -> 2607 | P146: =O146*C146 -> 223945.73
B147: 46157 | C147: =VLOOKUP(B:B,'Курс валют'!A:D,4,0) -> 86.2899 | D147: 15E2601 | E147: клей Starkbond 521 A бочка 220кг | F147: 1100 | G147: 1108.5 | H147: 0 | I147: =G147-F147 -> 8.5 | J147: =I147/F147*100 -> 0.77272727 | K147: 2.37 | L147: =H147/F147*100 -> 0 | M147: =P147/F147 -> 204.50706 | N147: =(F147*K147-H147*3.04)/F147 -> 2.37 | O147: =N147*F147 -> 2607 | P147: =O147*C147 -> 224957.77
B148: 46157 | C148: =VLOOKUP(B:B,'Курс валют'!A:D,4,0) -> 86.2899 | D148: 15E2611 | E148: Отвердитель Starkbond 525 C 6.0 бочка 200 кг | F148: 1000 | G148: 1009.2 | H148: 0 | I148: =G148-F148 -> 9.2 | J148: =I148/F148*100 -> 0.92 | K148: 2.58 | L148: =H148/F148*100 -> 0 | M148: =P148/F148 -> 222.62794 | N148: =(F148*K148-H148*3.04)/F148 -> 2.58 | O148: =N148*F148 -> 2580 | P148: =O148*C148 -> 222627.94
B149: 46157 | C149: =VLOOKUP(B:B,'Курс валют'!A:D,4,0) -> 86.2899 | D149: 15E2612 | E149: Отвердитель Starkbond 525 C 6.0 бочка 200 кг | F149: 1000 | G149: 1009.2 | H149: 0 | I149: =G149-F149 -> 9.2 | J149: =I149/F149*100 -> 0.92 | K149: 2.55 | L149: =H149/F149*100 -> 0 | M149: =P149/F149 -> 220.03924 | N149: =(F149*K149-H149*3.04)/F149 -> 2.55 | O149: =N149*F149 -> 2550 | P149: =O149*C149 -> 220039.24
B150: 46157 | C150: =VLOOKUP(B:B,'Курс валют'!A:D,4,0) -> 86.2899 | D150: 15E2602 | E150: клей Starkbond 521 A бочка 220кг | F150: 1100 | G150: 1108.5 | H150: 0 | I150: =G150-F150 -> 8.5 | J150: =I150/F150*100 -> 0.77272727 | K150: 2.37 | L150: =H150/F150*100 -> 0 | M150: =P150/F150 -> 204.50706 | N150: =(F150*K150-H150*3.04)/F150 -> 2.37 | O150: =N150*F150 -> 2607 | P150: =O150*C150 -> 224957.77
B151: 46157 | C151: =VLOOKUP(B:B,'Курс валют'!A:D,4,0) -> 86.2899 | D151: 15E2603 | E151: клей Starkbond 521 A бочка 220кг | F151: 1100 | G151: 1108.5 | H151: 0 | I151: =G151-F151 -> 8.5 | J151: =I151/F151*100 -> 0.77272727 | K151: 2.37 | L151: =H151/F151*100 -> 0 | M151: =P151/F151 -> 204.50706 | N151: =(F151*K151-H151*3.04)/F151 -> 2.37 | O151: =N151*F151 -> 2607 | P151: =O151*C151 -> 224957.77
... B181: 46159 | C181: =VLOOKUP(B:B,'Курс валют'!A:D,4,0) -> 85.183 | D181: 17E2608 | E181: Клей Starkbond 522A бочка 220 кг | F181: 1100 | G181: 1108.01 | H181: 0 | I181: =G181-F181 -> 8.01 | J181: =I181/F181*100 -> 0.72818182 | K181: 2.48 | L181: =H181/F181*100 -> 0 | M181: =P181/F181 -> 211.25384 | N181: =(F181*K181-H181*3.04)/F181 -> 2.48 | O181: =N181*F181 -> 2728 | P181: =O181*C181 -> 232379.22
B182: 46159 | C182: =VLOOKUP(B:B,'Курс валют'!A:D,4,0) -> 85.183 | D182: 17E2611 | E182: Клей Starkbond 521A ведро 22 кг | F182: 440 | G182: 440 | H182: 0 | I182: =G182-F182 -> 0 | J182: =I182/F182*100 -> 0 | K182: 2.42 | L182: =H182/F182*100 -> 0 | M182: =P182/F182 -> 206.14286 | N182: =(F182*K182-H182*3.04)/F182 -> 2.42 | O182: =N182*F182 -> 1064.8 | P182: =O182*C182 -> 90702.858 | R182: Фасовка 521А 440кг (15E2608, 15E2607)
B183: 46159 | C183: =VLOOKUP(B:B,'Курс валют'!A:D,4,0) -> 85.183 | D183: 17E2612 | E183: Отвердитель Starkbond 525C 6.0 ведро 20кг | F183: 200 | G183: 200 | H183: 0 | I183: =G183-F183 -> 0 | J183: =I183/F183*100 -> 0 | K183: 2.84 | L183: =H183/F183*100 -> 0 | M183: =P183/F183 -> 241.91972 | N183: =(F183*K183-H183*3.04)/F183 -> 2.84 | O183: =N183*F183 -> 568 | P183: =O183*C183 -> 48383.944 | R183: Фасовка 525C 6.0 200 (22C2612)
B184: 46161 | C184: =VLOOKUP(B:B,'Курс валют'!A:D,4,0) -> 84.0742 | D184: 19E2601 | E184: Клей Starkbond 522A бочка 220 кг | F184: 1100 | G184: 1108.01 | H184: 0 | I184: =G184-F184 -> 8.01 | J184: =I184/F184*100 -> 0.72818182 | K184: 2.49 | L184: =H184/F184*100 -> 0 | M184: =P184/F184 -> 209.34476 | N184: =(F184*K184-H184*3.04)/F184 -> 2.49 | O184: =N184*F184 -> 2739 | P184: =O184*C184 -> 230279.23
...

Sheet Апрель 2026
A1: пп | B1: Дата выпуска продукции | C1: курс | D1: № ЗП | E1: Продукт | F1: Вес готового продукта | G1: Израсходовано по факту | H1: Израсходовано по факту Polyether Polyol Puranol D220, LE-220A Пропиленгликоль | I1: Потери, кг | J1: % потерь | K1: СС 1С на дату выпуска, EUR | L1: % пропиленгликоля в составе + полиол | M1: СС КГ, РУБ, Б/НДС | N1: СС Факт , EUR, Б/НДС | O1: СС Партии, EUR, Б/НДС | P1: СС Партии, РУБ, Б/НДС | R1: Примечание
B2: 46113 | C2: =VLOOKUP(B:B,'Курс валют'!A:D,4,0) -> 93.2739 | D2: 01D2612 | E2: Отвердитель Starkbond 525C 7.0 ведро 20 кг | F2: 40 | G2: 43.01 | H2: 0 | I2: =G2-F2 -> 3.01 | J2: =I2/F2*100 -> 7.525 | K2: 2.98 | L2: =H2/F2*100 -> 0 | M2: =P2/F2 -> 277.95622 | N2: =(F2*K2-H2*3.04)/F2 -> 2.98 | O2: =N2*F2 -> 119.2 | P2: =O2*C2 -> 11118.249
B3: 46113 | C3: =VLOOKUP(B:B,'Курс валют'!A:D,4,0) -> 93.2739 | D3: 01D2611 | E3: Клей Starkbond 525A 2.0 ведро 20 кг | F3: 80 | G3: 83 | H3: 0 | I3: =G3-F3 -> 3 | J3: =I3/F3*100 -> 3.75 | K3: 2.7 | L3: =H3/F3*100 -> 0 | M3: =P3/F3 -> 251.83953 | N3: =(F3*K3-H3*3.04)/F3 -> 2.7 | O3: =N3*F3 -> 216 | P3: =O3*C3 -> 20147.162
B4: 46113 | C4: =VLOOKUP(B:B,'Курс валют'!A:D,4,0) -> 93.2739 | D4: 01D2601 | E4: Отвердитель Starkbond 521C 3.0 бочка 200кг | F4: 800 | G4: 804.5 | H4: 0 | I4: =G4-F4 -> 4.5 | J4: =I4/F4*100 -> 0.5625 | K4: 1.86 | L4: =H4/F4*100 -> 0 | M4: =P4/F4 -> 173.48945 | N4: =(F4*K4-H4*3.04)/F4 -> 1.86 | O4: =N4*F4 -> 1488 | P4: =O4*C4 -> 138791.56
B5: 46113 | C5: =VLOOKUP(B:B,'Курс валют'!A:D,4,0) -> 93.2739 | D5: 01D2602 | E5: Отвердитель Starkbond 521C 3.0 бочка 200кг | F5: 800 | G5: 804.5 | H5: 0 | I5: =G5-F5 -> 4.5 | J5: =I5/F5*100 -> 0.5625 | K5: 1.85 | L5: =H5/F5*100 -> 0 | M5: =P5/F5 -> 172.55671 | N5: =(F5*K5-H5*3.04)/F5 -> 1.85 | O5: =N5*F5 -> 1480 | P5: =O5*C5 -> 138045.37
B6: 46113 | C6: =VLOOKUP(B:B,'Курс валют'!A:D,4,0) -> 93.2739 | D6: 01D2603 | E6: Отвердитель Starkbond 521C 3.0 бочка 200кг | F6: 800 | G6: 804.5 | H6: 0 | I6: =G6-F6 -> 4.5 | J6: =I6/F6*100 -> 0.5625 | K6: 1.85 | L6: =H6/F6*100 -> 0 | M6: =P6/F6 -> 172.55671 | N6: =(F6*K6-H6*3.04)/F6 -> 1.85 | O6: =N6*F6 -> 1480 | P6: =O6*C6 -> 138045.37
B7: 46113 | C7: =VLOOKUP(B:B,'Курс валют'!A:D,4,0) -> 93.2739 | D7: 01D2604 | E7: Отвердитель Starkbond 521C 3.0 бочка 200кг | F7: 800 | G7: 804.5 | H7: 0 | I7: =G7-F7 -> 4.5 | J7: =I7/F7*100 -> 0.5625 | K7: 1.85 | L7: =H7/F7*100 -> 0 | M7: =P7/F7 -> 172.55671 | N7: =(F7*K7-H7*3.04)/F7 -> 1.85 | O7: =N7*F7 -> 1480 | P7: =O7*C7 -> 138045.37
B8: 46113 | C8: =VLOOKUP(B:B,'Курс валют'!A:D,4,0) -> 93.2739 | D8: 01D2605 | E8: Отвердитель Starkbond 521C 3.0 бочка 200кг | F8: 800 | G8: 804.5 | H8: 0 | I8: =G8-F8 -> 4.5 | J8: =I8/F8*100 -> 0.5625 | K8: 1.85 | L8: =H8/F8*100 -> 0 | M8: =P8/F8 -> 172.55671 | N8: =(F8*K8-H8*3.04)/F8 -> 1.85 | O8: =N8*F8 -> 1480 | P8: =O8*C8 -> 138045.37
B9: 46113 | C9: =VLOOKUP(B:B,'Курс валют'!A:D,4,0) -> 93.2739 | D9: 09H25R11. | E9: Starkbond 2015 ведро 10 кг | F9: 10 | G9: 10 | H9: 0 | I9: =G9-F9 -> 0 | J9: =I9/F9*100 -> 0 | K9: 3.08 | L9: =H9/F9*100 -> 0 | M9: =P9/F9 -> 287.28361 | N9: =(F9*K9-H9*3.04)/F9 -> 3.08 | O9: =N9*F9 -> 30.8 | P9: =O9*C9 -> 2872.8361 | R9: Фасовка 2015- 10кг
B10: 46113 | C10: =VLOOKUP(B:B,'Курс валют'!A:D,4,0) -> 93.2739 | D10: 01D2606 | E10: Отвердитель Starkbond 521C 3.0 бочка 200кг | F10: 800 | G10: 804.5 | H10: 0 | I10: =G10-F10 -> 4.5 | J10: =I10/F10*100 -> 0.5625 | K10: 1.85 | L10: =H10/F10*100 -> 0 | M10: =P10/F10 -> 172.55671 | N10: =(F10*K10-H10*3.04)/F10 -> 1.85 | O10: =N10*F10 -> 1480 | P10: =O10*C10 -> 138045.37
B11: 46113 | C11: =VLOOKUP(B:B,'Курс валют'!A:D,4,0) -> 93.2739 | D11: 01D26R11 | E11: Клей Starkbond 745/41 А (бочка 200 кг) | F11: 2000 | G11: 2056.55 | H11: 0 | I11: =G11-F11 -> 56.55 | J11: =I11/F11*100 -> 2.8275 | K11: 2.37 | L11: =H11/F11*100 -> 0 | M11: =P11/F11 -> 221.05914 | N11: =(F11*K11-H11*3.04)/F11 -> 2.37 | O11: =N11*F11 -> 4740 | P11: =O11*C11 -> 442118.29
B12: 46113 | C12: =VLOOKUP(B:B,'Курс валют'!A:D,4,0) -> 93.2739 | D12: 01D2607 | E12: Отвердитель Starkbond 521C 3.0 бочка 200кг | F12: 800 | G12: 804.5 | H12: 0 | I12: =G12-F12 -> 4.5 | J12: =I12/F12*100 -> 0.5625 | K12: 1.86 | L12: =H12/F12*100 -> 0 | M12: =P12/F12 -> 173.48945 | N12: =(F12*K12-H12*3.04)/F12 -> 1.86 | O12: =N12*F12 -> 1488 | P12: =O12*C12 -> 138791.56
B13: 46113 | C13: =VLOOKUP(B:B,'Курс валют'!A:D,4,0) -> 93.2739 | D13: 01D2608 | E13: Отвердитель Starkbond 521C 3.0 бочка 200кг | F13: 800 | G13: 804.5 | H13: 0 | I13: =G13-F13 -> 4.5 | J13: =I13/F13*100 -> 0.5625 | K13: 1.85 | L13: =H13/F13*100 -> 0 | M13: =P13/F13 -> 172.55671 | N13: =(F13*K13-H13*3.04)/F13 -> 1.85 | O13: =N13*F13 -> 1480 | P13: =O13*C13 -> 138045.37
B14: 46113 | C14: =VLOOKUP(B:B,'Курс валют'!A:D,4,0) -> 93.2739 | D14: 01D2609 | E14: Отвердитель Starkbond 521C 3.0 бочка 200кг | F14: 800 | G14: 804.5 | H14: 0 | I14: =G14-F14 -> 4.5 | J14: =I14/F14*100 -> 0.5625 | K14: 1.85 | L14: =H14/F14*100 -> 0 | M14: =P14/F14 -> 172.55671 | N14: =(F14*K14-H14*3.04)/F14 -> 1.85 | O14: =N14*F14 -> 1480 | P14: =O14*C14 -> 138045.37
B15: 46113 | C15: =VLOOKUP(B:B,'Курс валют'!A:D,4,0) -> 93.2739 | D15: 01D2610 | E15: Отвердитель Starkbond 521C 3.0 бочка 200кг | F15: 800 | G15: 804.5 | H15: 0 | I15: =G15-F15 -> 4.5 | J15: =I15/F15*100 -> 0.5625 | K15: 1.85 | L15: =H15/F15*100 -> 0 | M15: =P15/F15 -> 172.55671 | N15: =(F15*K15-H15*3.04)/F15 -> 1.85 | O15: =N15*F15 -> 1480 | P15: =O15*C15 -> 138045.37
B16: 46114 | C16: =VLOOKUP(B:B,'Курс валют'!A:D,4,0) -> 93.4443 | D16: 02D2601 | E16: Отвердитель Starkbond 521C 11.0 бочка 200кг | F16: 800 | G16: 805.14 | H16: 0 | I16: =G16-F16 -> 5.14 | J16: =I16/F16*100 -> 0.6425 | K16: 1.93 | L16: =H16/F16*100 -> 0 | M16: =P16/F16 -> 180.3475 | N16: =(F16*K16-H16*3.04)/F16 -> 1.93 | O16: =N16*F16 -> 1544 | P16: =O16*C16 -> 144278
B17: 46114 | C17: =VLOOKUP(B:B,'Курс валют'!A:D,4,0) -> 93.4443 | D17: 02D2602 | E17: Отвердитель Starkbond 521C 11.0 бочка 200кг | F17: 800 | G17: 805.14 | H17: 0 | I17: =G17-F17 -> 5.14 | J17: =I17/F17*100 -> 0.6425 | K17: 1.92 | L17: =H17/F17*100 -> 0 | M17: =P17/F17 -> 179.41306 | N17: =(F17*K17-H17*3.04)/F17 -> 1.92 | O17: =N17*F17 -> 1536 | P17: =O17*C17 -> 143530.44
B18: 46114 | C18: =VLOOKUP(B:B,'Курс валют'!A:D,4,0) -> 93.4443 | D18: 02D2603 | E18: Отвердитель Starkbond 521C 11.0 бочка 200кг | F18: 800 | G18: 805.14 | H18: 0 | I18: =G18-F18 -> 5.14 | J18: =I18/F18*100 -> 0.6425 | K18: 1.92 | L18: =H18/F18*100 -> 0 | M18: =P18/F18 -> 179.41306 | N18: =(F18*K18-H18*3.04)/F18 -> 1.92 | O18: =N18*F18 -> 1536 | P18: =O18*C18 -> 143530.44
B19: 46114 | C19: =VLOOKUP(B:B,'Курс валют'!A:D,4,0) -> 93.4443 | D19: 02D2604 | E19: Отвердитель Starkbond 521C 11.0 бочка 200кг | F19: 800 | G19: 805.14 | H19: 0 | I19: =G19-F19 -> 5.14 | J19: =I19/F19*100 -> 0.6425 | K19: 1.92 | L19: =H19/F19*100 -> 0 | M19: =P19/F19 -> 179.41306 | N19: =(F19*K19-H19*3.04)/F19 -> 1.92 | O19: =N19*F19 -> 1536 | P19: =O19*C19 -> 143530.44
B20: 46114 | C20: =VLOOKUP(B:B,'Курс валют'!A:D,4,0) -> 93.4443 | D20: 02D2605 | E20: Отвердитель Starkbond 521C 11.0 бочка 200кг | F20: 800 | G20: 805.14 | H20: 0 | I20: =G20-F20 -> 5.14 | J20: =I20/F20*100 -> 0.6425 | K20: 1.92 | L20: =H20/F20*100 -> 0 | M20: =P20/F20 -> 179.41306 | N20: =(F20*K20-H20*3.04)/F20 -> 1.92 | O20: =N20*F20 -> 1536 | P20: =O20*C20 -> 143530.44
B21: 46114 | C21: =VLOOKUP(B:B,'Курс валют'!A:D,4,0) -> 93.4443 | D21: 02D2606 | E21: Отвердитель Starkbond 521C 11.0 бочка 200кг | F21: 800 | G21: 805.14 | H21: 0 | I21: =G21-F21 -> 5.14 | J21: =I21/F21*100 -> 0.6425 | K21: 1.93 | L21: =H21/F21*100 -> 0 | M21: =P21/F21 -> 180.3475 | N21: =(F21*K21-H21*3.04)/F21 -> 1.93 | O21: =N21*F21 -> 1544 | P21: =O21*C21 -> 144278
... B24: 46114 | C24: =VLOOKUP(B:B,'Курс валют'!A:D,4,0) -> 93.4443 | D24: 02D2609 | E24: Отвердитель Starkbond 521C 11.0 бочка 200кг | F24: 800 | G24: 805.14 | H24: 0 | I24: =G24-F24 -> 5.14 | J24: =I24/F24*100 -> 0.6425 | K24: 1.92 | L24: =H24/F24*100 -> 0 | M24: =P24/F24 -> 179.41306 | N24: =(F24*K24-H24*3.04)/F24 -> 1.92 | O24: =N24*F24 -> 1536 | P24: =O24*C24 -> 143530.44
B25: 46114 | C25: =VLOOKUP(B:B,'Курс валют'!A:D,4,0) -> 93.4443 | D25: 02D2610 | E25: Отвердитель Starkbond 521C 11.0 бочка 200кг | F25: 800 | G25: 805.14 | H25: 0 | I25: 2.5 | J25: =I25/F25*100 -> 0.3125 | K25: 1.92 | L25: =H25/F25*100 -> 0 | M25: =P25/F25 -> 179.41306 | N25: =(F25*K25-H25*3.04)/F25 -> 1.92 | O25: =N25*F25 -> 1536 | P25: =O25*C25 -> 143530.44
B26: 46114 | C26: =VLOOKUP(B:B,'Курс валют'!A:D,4,0) -> 93.4443 | D26: 02D26R11 | E26: Клей Starkbond 2025 RC7 LV 220 кг | F26: 2200 | G26: 2239.305 | H26: 0 | I26: =G26-F26 -> 39.305 | J26: =I26/F26*100 -> 1.7865909 | K26: 1.91 | L26: =H26/F26*100 -> 0 | M26: =P26/F26 -> 178.47861 | N26: =(F26*K26-H26*3.04)/F26 -> 1.91 | O26: =N26*F26 -> 4202 | P26: =O26*C26 -> 392652.95
B27: 46115 | C27: =VLOOKUP(B:B,'Курс валют'!A:D,4,0) -> 92.7326 | D27: 03D2601 | E27: Отвердитель Starkbond 521C 10.0 бочка 200кг | F27: 800 | G27: 805.12 | H27: 0 | I27: =G27-F27 -> 5.12 | J27: =I27/F27*100 -> 0.64 | K27: 1.9 | L27: =H27/F27*100 -> 0 | M27: =P27/F27 -> 176.19194 | N27: =(F27*K27-H27*3.04)/F27 -> 1.9 | O27: =N27*F27 -> 1520 | P27: =O27*C27 -> 140953.55
B28: 46115 | C28: =VLOOKUP(B:B,'Курс валют'!A:D,4,0) -> 92.7326 | D28: 03D2602 | E28: Отвердитель Starkbond 521C 10.0 бочка 200кг | F28: 800 | G28: 805.12 | H28: 0 | I28: =G28-F28 -> 5.12 | J28: =I28/F28*100 -> 0.64 | K28: 1.89 | L28: =H28/F28*100 -> 0 | M28: =P28/F28 -> 175.26461 | N28: =(F28*K28-H28*3.04)/F28 -> 1.89 | O28: =N28*F28 -> 1512 | P28: =O28*C28 -> 140211.69
B29: 46115 | C29: =VLOOKUP(B:B,'Курс валют'!A:D,4,0) -> 92.7326 | D29: 03D2603 | E29: Отвердитель Starkbond 521C 10.0 бочка 200кг | F29: 800 | G29: 805.12 | H29: 0 | I29: =G29-F29 -> 5.12 | J29: =I29/F29*100 -> 0.64 | K29: 1.89 | L29: =H29/F29*100 -> 0 | M29: =P29/F29 -> 175.26461 | N29: =(F29*K29-H29*3.04)/F29 -> 1.89 | O29: =N29*F29 -> 1512 | P29: =O29*C29 -> 140211.69
B30: 46115 | C30: =VLOOKUP(B:B,'Курс валют'!A:D,4,0) -> 92.7326 | D30: 03D2604 | E30: Отвердитель Starkbond 521C 10.0 бочка 200кг | F30: 800 | G30: 805.12 | H30: 0 | I30: =G30-F30 -> 5.12 | J30: =I30/F30*100 -> 0.64 | K30: 1.86 | L30: =H30/F30*100 -> 0 | M30: =P30/F30 -> 172.48264 | N30: =(F30*K30-H30*3.04)/F30 -> 1.86 | O30: =N30*F30 -> 1488 | P30: =O30*C30 -> 137986.11
B31: 46115 | C31: =VLOOKUP(B:B,'Курс валют'!A:D,4,0) -> 92.7326 | D31: 03D2605 | E31: Отвердитель Starkbond 521C 10.0 бочка 200кг | F31: 800 | G31: 805.12 | H31: 0 | I31: =G31-F31 -> 5.12 | J31: =I31/F31*100 -> 0.64 | K31: 1.86 | L31: =H31/F31*100 -> 0 | M31: =P31/F31 -> 172.48264 | N31: =(F31*K31-H31*3.04)/F31 -> 1.86 | O31: =N31*F31 -> 1488 | P31: =O31*C31 -> 137986.11
B32: 46115 | C32: =VLOOKUP(B:B,'Курс валют'!A:D,4,0) -> 92.7326 | D32: 03D2606 | E32: Отвердитель Starkbond 521C 10.0 бочка 200кг | F32: 800 | G32: 805.12 | H32: 0 | I32: =G32-F32 -> 5.12 | J32: =I32/F32*100 -> 0.64 | K32: 1.9 | L32: =H32/F32*100 -> 0 | M32: =P32/F32 -> 176.19194 | N32: =(F32*K32-H32*3.04)/F32 -> 1.9 | O32: =N32*F32 -> 1520 | P32: =O32*C32 -> 140953.55
B33: 46115 | C33: =VLOOKUP(B:B,'Курс валют'!A:D,4,0) -> 92.7326 | D33: 03D2607 | E33: Отвердитель Starkbond 521C 10.0 бочка 200кг | F33: 800 | G33: 805.12 | H33: 0 | I33: =G33-F33 -> 5.12 | J33: =I33/F33*100 -> 0.64 | K33: 1.89 | L33: =H33/F33*100 -> 0 | M33: =P33/F33 -> 175.26461 | N33: =(F33*K33-H33*3.04)/F33 -> 1.89 | O33: =N33*F33 -> 1512 | P33: =O33*C33 -> 140211.69
B34: 46115 | C34: =VLOOKUP(B:B,'Курс валют'!A:D,4,0) -> 92.7326 | D34: 03D2608 | E34: Отвердитель Starkbond 521C 10.0 бочка 200кг | F34: 800 | G34: 805.12 | H34: 0 | I34: =G34-F34 -> 5.12 | J34: =I34/F34*100 -> 0.64 | K34: 1.89 | L34: =H34/F34*100 -> 0 | M34: =P34/F34 -> 175.26461 | N34: =(F34*K34-H34*3.04)/F34 -> 1.89 | O34: =N34*F34 -> 1512 | P34: =O34*C34 -> 140211.69
B35: 46115 | C35: =VLOOKUP(B:B,'Курс валют'!A:D,4,0) -> 92.7326 | D35: 03D2609 | E35: Отвердитель Starkbond 521C 10.0 бочка 200кг | F35: 800 | G35: 805.12 | H35: 0 | I35: =G35-F35 -> 5.12 | J35: =I35/F35*100 -> 0.64 | K35: 1.89 | L35: =H35/F35*100 -> 0 | M35: =P35/F35 -> 175.26461 | N35: =(F35*K35-H35*3.04)/F35 -> 1.89 | O35: =N35*F35 -> 1512 | P35: =O35*C35 -> 140211.69
B36: 46115 | C36: =VLOOKUP(B:B,'Курс валют'!A:D,4,0) -> 92.7326 | D36: 03D26R11 | E36: Клей Starkbond 2025 RC7 LV 220 кг | F36: 2200 | G36: 2238.52 | H36: 0 | I36: =G36-F36 -> 38.52 | J36: =I36/F36*100 -> 1.7509091 | K36: 1.95 | L36: =H36/F36*100 -> 0 | M36: =P36/F36 -> 180.82857 | N36: =(F36*K36-H36*3.04)/F36 -> 1.95 | O36: =N36*F36 -> 4290 | P36: =O36*C36 -> 397822.85
B37: 46115 | C37: =VLOOKUP(B:B,'Курс валют'!A:D,4,0) -> 92.7326 | D37: 03D2610 | E37: Отвердитель Starkbond 521C 10.0 бочка 200кг | F37: 800 | G37: 805.12 | H37: 0 | I37: =G37-F37 -> 5.12 | J37: =I37/F37*100 -> 0.64 | K37: 1.89 | L37: =H37/F37*100 -> 0 | M37: =P37/F37 -> 175.26461 | N37: =(F37*K37-H37*3.04)/F37 -> 1.89 | O37: =N37*F37 -> 1512 | P37: =O37*C37 -> 140211.69
... B56: 46117 | C56: =VLOOKUP(B:B,'Курс валют'!A:D,4,0) -> 92.1915 | D56: 05D2609 | E56: Клей Starkbond 522A бочка 220 кг | F56: 1100 | G56: 1105.51 | H56: 0 | I56: =G56-F56 -> 5.51 | J56: =I56/F56*100 -> 0.50090909 | K56: 2.5 | L56: =H56/F56*100 -> 0 | M56: =P56/F56 -> 230.47875 | N56: =(F56*K56-H56*3.04)/F56 -> 2.5 | O56: =N56*F56 -> 2750 | P56: =O56*C56 -> 253526.62
B57: 46118 | C57: =VLOOKUP(B:B,'Курс валют'!A:D,4,0) -> 92.1915 | D57: 26C2619. | E57: Клей Starkbond 521A ведро 22 кг | F57: 220 | G57: 220 | H57: 0 | I57: =G57-F57 -> 0 | J57: =I57/F57*100 -> 0 | K57: 3.75 | L57: =H57/F57*100 -> 0 | M57: =P57/F57 -> 345.71812 | N57: =(F57*K57-H57*3.04)/F57 -> 3.75 | O57: =N57*F57 -> 825 | P57: =O57*C57 -> 76057.988 | R57: Фасовка 521А 220кг 26C2619
B58: 46118 | C58: =VLOOKUP(B:B,'Курс валют'!A:D,4,0) -> 92.1915 | D58: 06D26R11 | E58: Клей Starkbond 2025 RC7 LV 220 кг | F58: 2200 | G58: 2233.52 | H58: 0 | I58: =G58-F58 -> 33.52 | J58: =I58/F58*100 -> 1.5236364 | K58: 1.92 | L58: =H58/F58*100 -> 0 | M58: =P58/F58 -> 177.00768 | N58: =(F58*K58-H58*3.04)/F58 -> 1.92 | O58: =N58*F58 -> 4224 | P58: =O58*C58 -> 389416.9
B59: 46118 | C59: =VLOOKUP(B:B,'Курс валют'!A:D,4,0) -> 92.1915 | D59: 06D2601 | E59: Sancos Pro Safety 165 канистра 14,8 кг | F59: 384.8 | G59: 392.5 | H59: 0 | J59: =I59/F59*100 -> 0 | K59: 1.8 | L59: =H59/F59*100 -> 0 | M59: =P59/F59 -> 165.9447 | N59: =(F59*K59-H59*3.04)/F59 -> 1.8 | O59: =N59*F59 -> 692.64 | P59: =O59*C59 -> 63855.521
B60: 46118 | C60: =VLOOKUP(B:B,'Курс валют'!A:D,4,0) -> 92.1915 | D60: 06D2602 | E60: клей Starkbond 521 A бочка 220кг | F60: 1100 | G60: 1107.5 | H60: 0 | I60: =G60-F60 -> 7.5 | J60: =I60/F60*100 -> 0.68181818 | K60: 2.4 | L60: =H60/F60*100 -> 0 | M60: =P60/F60 -> 221.2596 | N60: =(F60*K60-H60*3.04)/F60 -> 2.4 | O60: =N60*F60 -> 2640 | P60: =O60*C60 -> 243385.56 | R60: 521A (1100) из Мутного МИПС
B61: 46119 | C61: =VLOOKUP(B:B,'Курс валют'!A:D,4,0) -> 91.0034 | D61: 07D2601 | E61: Клей Starkbond 522A бочка 220 кг | F61: 1100 | G61: 1105.51 | H61: 0 | I61: =G61-F61 -> 5.51 | J61: =I61/F61*100 -> 0.50090909 | K61: 2.43 | L61: =H61/F61*100 -> 0 | M61: =P61/F61 -> 221.13826 | N61: =(F61*K61-H61*3.04)/F61 -> 2.43 | O61: =N61*F61 -> 2673 | P61: =O61*C61 -> 243252.09
B62: 46119 | C62: =VLOOKUP(B:B,'Курс валют'!A:D,4,0) -> 91.0034 | D62: 07D2602 | E62: Клей Starkbond 522A бочка 220 кг | F62: 1100 | G62: 1105.51 | H62: 0 | I62: =G62-F62 -> 5.51 | J62: =I62/F62*100 -> 0.50090909 | K62: 2.43 | L62: =H62/F62*100 -> 0 | M62: =P62/F62 -> 221.13826 | N62: =(F62*K62-H62*3.04)/F62 -> 2.43 | O62: =N62*F62 -> 2673 | P62: =O62*C62 -> 243252.09
B63: 46119 | C63: =VLOOKUP(B:B,'Курс валют'!A:D,4,0) -> 91.0034 | D63: 07D2603 | E63: Клей Starkbond 522A бочка 220 кг | F63: 1100 | G63: 1105.51 | H63: 0 | I63: =G63-F63 -> 5.51 | J63: =I63/F63*100 -> 0.50090909 | K63: 2.42 | L63: =H63/F63*100 -> 0 | M63: =P63/F63 -> 220.22823 | N63: =(F63*K63-H63*3.04)/F63 -> 2.42 | O63: =N63*F63 -> 2662 | P63: =O63*C63 -> 242251.05
B64: 46119 | C64: =VLOOKUP(B:B,'Курс валют'!A:D,4,0) -> 91.0034 | D64: 07D2604 | E64: Клей Starkbond 522A бочка 220 кг | F64: 1100 | G64: 1105.51 | H64: 0 | I64: =G64-F64 -> 5.51 | J64: =I64/F64*100 -> 0.50090909 | K64: 2.42 | L64: =H64/F64*100 -> 0 | M64: =P64/F64 -> 220.22823 | N64: =(F64*K64-H64*3.04)/F64 -> 2.42 | O64: =N64*F64 -> 2662 | P64: =O64*C64 -> 242251.05
B65: 46119 | C65: =VLOOKUP(B:B,'Курс валют'!A:D,4,0) -> 91.0034 | D65: 07D2605 | E65: Клей Starkbond 522A бочка 220 кг | F65: 1100 | G65: 1105.51 | H65: 0 | I65: =G65-F65 -> 5.51 | J65: =I65/F65*100 -> 0.50090909 | K65: 2.43 | L65: =H65/F65*100 -> 0 | M65: =P65/F65 -> 221.13826 | N65: =(F65*K65-H65*3.04)/F65 -> 2.43 | O65: =N65*F65 -> 2673 | P65: =O65*C65 -> 243252.09
B66: 46119 | C66: =VLOOKUP(B:B,'Курс валют'!A:D,4,0) -> 91.0034 | D66: 07D2606 | E66: Клей Starkbond 522A бочка 220 кг | F66: 1100 | G66: 1105.51 | H66: 0 | I66: =G66-F66 -> 5.51 | J66: =I66/F66*100 -> 0.50090909 | K66: 2.43 | L66: =H66/F66*100 -> 0 | M66: =P66/F66 -> 221.13826 | N66: =(F66*K66-H66*3.04)/F66 -> 2.43 | O66: =N66*F66 -> 2673 | P66: =O66*C66 -> 243252.09
B67: 46119 | C67: =VLOOKUP(B:B,'Курс валют'!A:D,4,0) -> 91.0034 | D67: 07D2607 | E67: Клей Starkbond 522A бочка 220 кг | F67: 1100 | G67: 1105.51 | H67: 0 | I67: =G67-F67 -> 5.51 | J67: =I67/F67*100 -> 0.50090909 | K67: 2.42 | L67: =H67/F67*100 -> 0 | M67: =P67/F67 -> 220.22823 | N67: =(F67*K67-H67*3.04)/F67 -> 2.42 | O67: =N67*F67 -> 2662 | P67: =O67*C67 -> 242251.05
B68: 46119 | C68: =VLOOKUP(B:B,'Курс валют'!A:D,4,0) -> 91.0034 | D68: 07D2608 | E68: Клей Starkbond 522A бочка 220 кг | F68: 1100 | G68: 1105.51 | H68: 0 | I68: =G68-F68 -> 5.51 | J68: =I68/F68*100 -> 0.50090909 | K68: 2.43 | L68: =H68/F68*100 -> 0 | M68: =P68/F68 -> 221.13826 | N68: =(F68*K68-H68*3.04)/F68 -> 2.43 | O68: =N68*F68 -> 2673 | P68: =O68*C68 -> 243252.09
B69: 46119 | C69: =VLOOKUP(B:B,'Курс валют'!A:D,4,0) -> 91.0034 | D69: 07D2609 | E69: Клей Starkbond 522A бочка 220 кг | F69: 1100 | G69: 1105.51 | H69: 0 | I69: =G69-F69 -> 5.51 | J69: =I69/F69*100 -> 0.50090909 | K69: 2.42 | L69: =H69/F69*100 -> 0 | M69: =P69/F69 -> 220.22823 | N69: =(F69*K69-H69*3.04)/F69 -> 2.42 | O69: =N69*F69 -> 2662 | P69: =O69*C69 -> 242251.05
B70: 46119 | C70: =VLOOKUP(B:B,'Курс валют'!A:D,4,0) -> 91.0034 | D70: 07D26R11 | E70: Клей Starkbond 2025 RC7 LV 220 кг | F70: 2200 | G70: 2233.52 | H70: 0 | I70: =G70-F70 -> 33.52 | J70: =I70/F70*100 -> 1.5236364 | K70: 1.92 | L70: =H70/F70*100 -> 0 | M70: =P70/F70 -> 174.72653 | N70: =(F70*K70-H70*3.04)/F70 -> 1.92 | O70: =N70*F70 -> 4224 | P70: =O70*C70 -> 384398.36
B71: 46119 | C71: =VLOOKUP(B:B,'Курс валют'!A:D,4,0) -> 91.0034 | D71: 07D2610 | E71: Клей Starkbond 522A бочка 220 кг | F71: 1100 | G71: 1105.51 | H71: 0 | I71: =G71-F71 -> 5.51 | J71: =I71/F71*100 -> 0.50090909 | K71: 2.42 | L71: =H71/F71*100 -> 0 | M71: =P71/F71 -> 220.22823 | N71: =(F71*K71-H71*3.04)/F71 -> 2.42 | O71: =N71*F71 -> 2662 | P71: =O71*C71 -> 242251.05
B72: 46120 | C72: =VLOOKUP(B:B,'Курс валют'!A:D,4,0) -> 91.0279 | D72: 08D26R11 | E72: Клей Starkbond 2025 RC7 LV 220 кг | F72: 2200 | G72: 2218.52 | H72: 0 | I72: =G72-F72 -> 18.52 | J72: =I72/F72*100 -> 0.84181818 | K72: 1.9 | L72: =H72/F72*100 -> 0 | M72: =P72/F72 -> 172.95301 | N72: =(F72*K72-H72*3.04)/F72 -> 1.9 | O72: =N72*F72 -> 4180 | P72: =O72*C72 -> 380496.62
... B180: 46132 | C180: =VLOOKUP(B:B,'Курс валют'!A:D,4,0) -> 89.6256 | D180: 20D26R21 | E180: клей Starkbond 745/3 А бочка 200кг | F180: 2000 | G180: 2060.65 | H180: 0 | I180: =G180-F180 -> 60.65 | J180: =I180/F180*100 -> 3.0325 | K180: 2.33 | L180: =H180/F180*100 -> 0 | M180: =P180/F180 -> 208.82765 | N180: =(F180*K180-H180*3.04)/F180 -> 2.33 | O180: =N180*F180 -> 4660 | P180: =O180*C180 -> 417655.3
B181: 46133 | C181: =VLOOKUP(B:B,'Курс валют'!A:D,4,0) -> 88.3769 | D181: 21D2611 | E181: Клей Starkbond 525A 2.0 ведро 20 кг | F181: 140 | G181: 146.2 | I181: =G181-F181 -> 6.2 | J181: =I181/F181*100 -> 4.4285714 | L181: =H181/F181*100 -> 0 | M181: =P181/F181 -> 0 | N181: =(F181*K181-H181*3.04)/F181 -> 0 | O181: =N181*F181 -> 0 | P181: =O181*C181 -> 0
B182: 46133 | C182: =VLOOKUP(B:B,'Курс валют'!A:D,4,0) -> 88.3769 | D182: 21D2612 | E182: Отвердитель Starkbond 525C 7.0 ведро 20 кг | F182: 80 | G182: 84.07 | H182: 0 | I182: =G182-F182 -> 4.07 | J182: =I182/F182*100 -> 5.0875 | K182: 2.97 | L182: =H182/F182*100 -> 0 | M182: =P182/F182 -> 262.47939 | N182: =(F182*K182-H182*3.04)/F182 -> 2.97 | O182: =N182*F182 -> 237.6 | P182: =O182*C182 -> 20998.351
B183: 46133 | C183: =VLOOKUP(B:B,'Курс валют'!A:D,4,0) -> 88.3769 | D183: 21D26R11 | E183: Клей Starkbond 2014 бочка 225кг | F183: 2250 | G183: 2273.1 | H183: 0 | I183: =G183-F183 -> 23.1 | J183: =I183/F183*100 -> 1.0266667 | K183: 1.94 | L183: =H183/F183*100 -> 0 | M183: =P183/F183 -> 171.45119 | N183: =(F183*K183-H183*3.04)/F183 -> 1.94 | O183: =N183*F183 -> 4365 | P183: =O183*C183 -> 385765.17
B184: 46133 | C184: =VLOOKUP(B:B,'Курс валют'!A:D,4,0) -> 88.3769 | D184: 31C2609. | E184: Клей Starkbond 521A ведро 22 кг | F184: 220 | G184: 220 | H184: 0 | I184: =G184-F184 -> 0 | J184: =I184/F184*100 -> 0 | K184: 2.51 | L184: =H184/F184*100 -> 0 | M184: =P184/F184 -> 221.82602 | N184: =(F184*K184-H184*3.04)/F184 -> 2.51 | O184: =N184*F184 -> 552.2 | P184: =O184*C184 -> 48801.724 | R184: Фасовка 521А 220кг 31C2609
B185: 46133 | C185: =VLOOKUP(B:B,'Курс валют'!A:D,4,0) -> 88.3769 | D185: 20C2604. | E185: Отвердитель Starkbond 521C 10.0 ведро 11кг | F185: 198 | G185: 200 | H185: 0 | I185: =G185-F185 -> 2 | J185: =I185/F185*100 -> 1.010101 | K185: 2.32 | L185: =H185/F185*100 -> 0 | M185: =P185/F185 -> 205.03441 | N185: =(F185*K185-H185*3.04)/F185 -> 2.32 | O185: =N185*F185 -> 459.36 | P185: =O185*C185 -> 40596.813 | R185: Фасовка 521С 10.0 20C2604
B186: 46133 | C186: =VLOOKUP(B:B,'Курс валют'!A:D,4,0) -> 88.3769 | D186: 21D26R21 | E186: Клей Starkbond 745/41 А (бочка 200 кг) | F186: 2000 | G186: 2056.55 | H186: 0 | I186: =G186-F186 -> 56.55 | J186: =I186/F186*100 -> 2.8275 | K186: 2.32 | L186: =H186/F186*100 -> 0 | M186: =P186/F186 -> 205.03441 | N186: =(F186*K186-H186*3.04)/F186 -> 2.32 | O186: =N186*F186 -> 4640 | P186: =O186*C186 -> 410068.82
B187: 46134 | C187: =VLOOKUP(B:B,'Курс валют'!A:D,4,0) -> 87.7659 | D187: 22D2601 | E187: клей Starkbond 521 A бочка 220кг | F187: 1100 | G187: 1105.8 | H187: 0 | I187: =G187-F187 -> 5.8 | J187: =I187/F187*100 -> 0.52727273 | K187: 2.42 | L187: =H187/F187*100 -> 0 | M187: =P187/F187 -> 212.39348 | N187: =(F187*K187-H187*3.04)/F187 -> 2.42 | O187: =N187*F187 -> 2662 | P187: =O187*C187 -> 233632.83
B188: 46134 | C188: =VLOOKUP(B:B,'Курс валют'!A:D,4,0) -> 87.7659 | D188: 22D2602 | E188: клей Starkbond 521 A бочка 220кг | F188: 1100 | G188: 1105.8 | H188: 0 | I188: =G188-F188 -> 5.8 | J188: =I188/F188*100 -> 0.52727273 | K188: 2.42 | L188: =H188/F188*100 -> 0 | M188: =P188/F188 -> 212.39348 | N188: =(F188*K188-H188*3.04)/F188 -> 2.42 | O188: =N188*F188 -> 2662 | P188: =O188*C188 -> 233632.83
B189: 46134 | C189: =VLOOKUP(B:B,'Курс валют'!A:D,4,0) -> 87.7659 | D189: 22D2603 | E189: клей Starkbond 521 A бочка 220кг | F189: 1100 | G189: 1105.8 | H189: 0 | I189: =G189-F189 -> 5.8 | J189: =I189/F189*100 -> 0.52727273 | K189: 2.42 | L189: =H189/F189*100 -> 0 | M189: =P189/F189 -> 212.39348 | N189: =(F189*K189-H189*3.04)/F189 -> 2.42 | O189: =N189*F189 -> 2662 | P189: =O189*C189 -> 233632.83
B190: 46134 | C190: =VLOOKUP(B:B,'Курс валют'!A:D,4,0) -> 87.7659 | D190: 22D2604 | E190: клей Starkbond 521 A бочка 220кг | F190: 1100 | G190: 1105.8 | H190: 0 | I190: =G190-F190 -> 5.8 | J190: =I190/F190*100 -> 0.52727273 | K190: 2.42 | L190: =H190/F190*100 -> 0 | M190: =P190/F190 -> 212.39348 | N190: =(F190*K190-H190*3.04)/F190 -> 2.42 | O190: =N190*F190 -> 2662 | P190: =O190*C190 -> 233632.83
B191: 46134 | C191: =VLOOKUP(B:B,'Курс валют'!A:D,4,0) -> 87.7659 | D191: 22D2605 | E191: клей Starkbond 521 A бочка 220кг | F191: 1100 | G191: 1105.8 | H191: 0 | I191: =G191-F191 -> 5.8 | J191: =I191/F191*100 -> 0.52727273 | K191: 2.42 | L191: =H191/F191*100 -> 0 | M191: =P191/F191 -> 212.39348 | N191: =(F191*K191-H191*3.04)/F191 -> 2.42 | O191: =N191*F191 -> 2662 | P191: =O191*C191 -> 233632.83
B192: 46134 | C192: =VLOOKUP(B:B,'Курс валют'!A:D,4,0) -> 87.7659 | D192: 22D2606 | E192: клей Starkbond 521 A бочка 220кг | F192: 1100 | G192: 1105.8 | H192: 0 | I192: =G192-F192 -> 5.8 | J192: =I192/F192*100 -> 0.52727273 | K192: 2.42 | L192: =H192/F192*100 -> 0 | M192: =P192/F192 -> 212.39348 | N192: =(F192*K192-H192*3.04)/F192 -> 2.42 | O192: =N192*F192 -> 2662 | P192: =O192*C192 -> 233632.83
B193: 46134 | C193: =VLOOKUP(B:B,'Курс валют'!A:D,4,0) -> 87.7659 | D193: 22D2607 | E193: клей Starkbond 521 A бочка 220кг | F193: 1100 | G193: 1105.8 | H193: 0 | I193: =G193-F193 -> 5.8 | J193: =I193/F193*100 -> 0.52727273 | K193: 2.41 | L193: =H193/F193*100 -> 0 | M193: =P193/F193 -> 211.51582 | N193: =(F193*K193-H193*3.04)/F193 -> 2.41 | O193: =N193*F193 -> 2651 | P193: =O193*C193 -> 232667.4
B194: 46134 | C194: =VLOOKUP(B:B,'Курс валют'!A:D,4,0) -> 87.7659 | D194: 22D2608 | E194: клей Starkbond 521 A бочка 220кг | F194: 1100 | G194: 1105.8 | H194: 0 | I194: =G194-F194 -> 5.8 | J194: =I194/F194*100 -> 0.52727273 | K194: 2.41 | L194: =H194/F194*100 -> 0 | M194: =P194/F194 -> 211.51582 | N194: =(F194*K194-H194*3.04)/F194 -> 2.41 | O194: =N194*F194 -> 2651 | P194: =O194*C194 -> 232667.4
B195: 46134 | C195: =VLOOKUP(B:B,'Курс валют'!A:D,4,0) -> 87.7659 | D195: 22D26R11. | E195: Клей Starkbond 2025 RC7 LV 220 кг | F195: 2200 | G195: 2228.52 | H195: 0 | I195: =G195-F195 -> 28.52 | J195: =I195/F195*100 -> 1.2963636 | K195: 1.82 | L195: =H195/F195*100 -> 0 | M195: =P195/F195 -> 159.73394 | N195: =(F195*K195-H195*3.04)/F195 -> 1.82 | O195: =N195*F195 -> 4004 | P195: =O195*C195 -> 351414.66
B196: 46135 | C196: =VLOOKUP(B:B,'Курс валют'!A:D,4,0) -> 87.9733 | D196: 23D2601 | E196: клей Starkbond 521 A бочка 220кг | F196: 1100 | G196: 1106 | H196: 0 | I196: =G196-F196 -> 6 | J196: =I196/F196*100 -> 0.54545455 | K196: 2.42 | L196: =H196/F196*100 -> 0 | M196: =P196/F196 -> 212.89539 | N196: =(F196*K196-H196*3.04)/F196 -> 2.42 | O196: =N196*F196 -> 2662 | P196: =O196*C196 -> 234184.92
B197: 46135 | C197: =VLOOKUP(B:B,'Курс валют'!A:D,4,0) -> 87.9733 | D197: 23D2602 | E197: клей Starkbond 521 A бочка 220кг | F197: 1100 | G197: 1105.8 | H197: 0 | I197: =G197-F197 -> 5.8 | J197: =I197/F197*100 -> 0.52727273 | K197: 2.42 | L197: =H197/F197*100 -> 0 | M197: =P197/F197 -> 212.89539 | N197: =(F197*K197-H197*3.04)/F197 -> 2.42 | O197: =N197*F197 -> 2662 | P197: =O197*C197 -> 234184.92
... B216: 46136 | C216: =VLOOKUP(B:B,'Курс валют'!A:D,4,0) -> 87.5261 | D216: 24D2603 | E216: Sancos PROPOL 101A бочка 90 кг | F216: 90 | G216: 93 | H216: 0 | I216: =G216-F216 -> 3 | J216: =I216/F216*100 -> 3.3333333 | K216: 2.24 | L216: =H216/F216*100 -> 0 | M216: =P216/F216 -> 196.05846 | N216: =(F216*K216-H216*3.04)/F216 -> 2.24 | O216: =N216*F216 -> 201.6 | P216: =O216*C216 -> 17645.262
B217: 46136 | C217: =VLOOKUP(B:B,'Курс валют'!A:D,4,0) -> 87.5261 | D217: 29C2606. | E217: Клей Starkbond 521A ведро 22 кг | F217: 220 | G217: 220 | H217: 0 | I217: =G217-F217 -> 0 | J217: =I217/F217*100 -> 0 | K217: 2.5 | L217: =H217/F217*100 -> 0 | M217: =P217/F217 -> 218.81525 | N217: =(F217*K217-H217*3.04)/F217 -> 2.5 | O217: =N217*F217 -> 550 | P217: =O217*C217 -> 48139.355 | R217: Фасовка 521А 220кг 29C2606
B218: 46137 | C218: =VLOOKUP(B:B,'Курс валют'!A:D,4,0) -> 88.2826 | D218: 25D2601 | E218: Клей Starkbond 745/40А ведро 20 кг | F218: 1400 | G218: 1400 | H218: 0 | I218: =G218-F218 -> 0 | J218: =I218/F218*100 -> 0 | K218: 2.64 | L218: =H218/F218*100 -> 0 | M218: =P218/F218 -> 233.06606 | N218: =(F218*K218-H218*3.04)/F218 -> 2.64 | O218: =N218*F218 -> 3696 | P218: =O218*C218 -> 326292.49 | R218: 745/40A (фасовка в ведра) 06B26R21, 07B26R21
