Workbook

Sheet сентябрь 2024- июнь 2026
A1: Дата передачи материалов | B1: Дата выпуска продукции | C1: курс | D1: № ЗП | E1: Продукт | F1: Вес готового продукта | G1: Израсходовано по факту | H1: Израсходовано по факту Polyether Polyol Puranol, Пропиленгликоль | I1: Потери, кг | J1: % потерь | K1: СС 1С на дату выпуска, EUR | L1: % пропиленгликоля в составе | M1: СС КГ, РУБ, Б/НДС | N1: СС Факт , EUR, Б/НДС | O1: СС Партии, EUR, Б/НДС | P1: СС Партии, РУБ, Б/НДС | R1: Примечание
A2: 45537 | B2: 45538 | C2: =VLOOKUP(B:B,'Курс валют'!A:D,4,0) -> 99.2613 | D2: 632 | E2: Отвердитель Starkbond 525C 2.0 Бочка 200 кг | F2: 3200 | G2: 3208.4 | H2: 0 | I2: =G2-F2 -> 8.4 | J2: =I2/F2*100 -> 0.2625 | K2: 3.43 | L2: =H2/F2*100 -> 0 | M2: =P2/F2 -> 340.46626 | N2: =(F2*K2-H2*3.04)/F2 -> 3.43 | O2: =N2*F2 -> 10976 | P2: =O2*C2 -> 1089492
A3: 45538 | B3: 45538 | C3: =VLOOKUP(B:B,'Курс валют'!A:D,4,0) -> 99.2613 | D3: 631 | E3: Клей Starkbond 2014 бочка 225кг | F3: 900 | G3: 927 | H3: 368 | I3: =G3-F3 -> 27 | J3: =I3/F3*100 -> 3 | K3: 3.24 | L3: =H3/F3*100 -> 40.888889 | M3: =P3/F3 -> 198.22261 | N3: =(F3*K3-H3*3.04)/F3 -> 1.9969778 | O3: =N3*F3 -> 1797.28 | P3: =O3*C3 -> 178400.35
A4: 45538 | B4: 45539 | C4: =VLOOKUP(B:B,'Курс валют'!A:D,4,0) -> 97.8121 | D4: 624 | E4: Клей Starkbond 745/41 А (бочка 200 кг) | F4: 1000 | G4: 1038 | H4: 219 | I4: =G4-F4 -> 38 | J4: =I4/F4*100 -> 3.8 | K4: 3.25 | L4: =H4/F4*100 -> 21.9 | M4: =P4/F4 -> 252.76994 | N4: =(F4*K4-H4*3.04)/F4 -> 2.58424 | O4: =N4*F4 -> 2584.24 | P4: =O4*C4 -> 252769.94
A5: 45538 | B5: 45539 | C5: =VLOOKUP(B:B,'Курс валют'!A:D,4,0) -> 97.8121 | D5: 633 | E5: Отвердитель Starkbond 525C 2.0 Бочка 200 кг | F5: 1600 | G5: 1624.2 | H5: 0 | I5: =G5-F5 -> 24.2 | J5: =I5/F5*100 -> 1.5125 | K5: 3.41 | L5: =H5/F5*100 -> 0 | M5: =P5/F5 -> 333.53926 | N5: =(F5*K5-H5*3.04)/F5 -> 3.41 | O5: =N5*F5 -> 5456 | P5: =O5*C5 -> 533662.82
A6: 45538 | B6: 45539 | C6: =VLOOKUP(B:B,'Курс валют'!A:D,4,0) -> 97.8121 | D6: 634 | E6: Клей Starkbond 521A ведро 22 кг | F6: 220 | G6: 220 | H6: 0 | I6: =G6-F6 -> 0 | J6: =I6/F6*100 -> 0 | K6: 4.09 | L6: =H6/F6*100 -> 0 | M6: =P6/F6 -> 400.05149 | N6: =(F6*K6-H6*3.04)/F6 -> 4.09 | O6: =N6*F6 -> 899.8 | P6: =O6*C6 -> 88011.328 | R6: перелив
A7: 45538 | B7: 45539 | C7: =VLOOKUP(B:B,'Курс валют'!A:D,4,0) -> 97.8121 | D7: 635 | E7: Отвердитель Starkbond 521C 10.0 ведро 11кг | F7: 198 | G7: 200 | H7: 0 | I7: =G7-F7 -> 2 | J7: =I7/F7*100 -> 1.010101 | K7: 2.26 | L7: =H7/F7*100 -> 0 | M7: =P7/F7 -> 221.05535 | N7: =(F7*K7-H7*3.04)/F7 -> 2.26 | O7: =N7*F7 -> 447.48 | P7: =O7*C7 -> 43768.959 | R7: перелив
A8: 45539 | B8: 45540 | C8: =VLOOKUP(B:B,'Курс валют'!A:D,4,0) -> 98.0725 | D8: 636 | E8: Клей Starkbond 2014 бочка 225кг | F8: 900 | G8: 935.5 | H8: 365 | I8: =G8-F8 -> 35.5 | J8: =I8/F8*100 -> 3.9444444 | K8: 3.27 | L8: =H8/F8*100 -> 40.555556 | M8: =P8/F8 -> 199.78458 | N8: =(F8*K8-H8*3.04)/F8 -> 2.0371111 | O8: =N8*F8 -> 1833.4 | P8: =O8*C8 -> 179806.12
A9: 45539 | B9: 45540 | C9: =VLOOKUP(B:B,'Курс валют'!A:D,4,0) -> 98.0725 | D9: 637 | E9: клей Starkbond 521 A бочка 220кг | F9: 6600 | G9: 6616 | H9: 3025 | I9: =G9-F9 -> 16 | J9: =I9/F9*100 -> 0.24242424 | K9: 3.87 | L9: =H9/F9*100 -> 45.833333 | M9: =P9/F9 -> 242.89289 | N9: =(F9*K9-H9*3.04)/F9 -> 2.4766667 | O9: =N9*F9 -> 16346 | P9: =O9*C9 -> 1603093.1
A10: 45539 | B10: 45540 | C10: =VLOOKUP(B:B,'Курс валют'!A:D,4,0) -> 98.0725 | D10: 638 | E10: Клей Starkbond 2014 бочка 225кг | F10: 900 | G10: 935 | H10: 365 | I10: =G10-F10 -> 35 | J10: =I10/F10*100 -> 3.8888889 | K10: 3.27 | L10: =H10/F10*100 -> 40.555556 | M10: =P10/F10 -> 199.78458 | N10: =(F10*K10-H10*3.04)/F10 -> 2.0371111 | O10: =N10*F10 -> 1833.4 | P10: =O10*C10 -> 179806.12
A11: 45540 | B11: 45540 | C11: =VLOOKUP(B:B,'Курс валют'!A:D,4,0) -> 98.0725 | D11: 640 | E11: отвердитель Starkbond 746/1 С ведро 20кг | F11: 120 | G11: 120 | H11: 0 | I11: =G11-F11 -> 0 | J11: =I11/F11*100 -> 0 | K11: 2.91 | L11: =H11/F11*100 -> 0 | M11: =P11/F11 -> 285.39098 | N11: =(F11*K11-H11*3.04)/F11 -> 2.91 | O11: =N11*F11 -> 349.2 | P11: =O11*C11 -> 34246.917 | R11: перелив
A12: 45541 | B12: 45544 | C12: =VLOOKUP(B:B,'Курс валют'!A:D,4,0) -> 99.7156 | D12: 641 | E12: Клей Starkbond 2014 бочка 225кг | F12: 900 | G12: 931.28 | H12: 365 | I12: =G12-F12 -> 31.28 | J12: =I12/F12*100 -> 3.4755556 | K12: 3.26 | L12: =H12/F12*100 -> 40.555556 | M12: =P12/F12 -> 202.1346 | N12: =(F12*K12-H12*3.04)/F12 -> 2.0271111 | O12: =N12*F12 -> 1824.4 | P12: =O12*C12 -> 181921.14
A13: 45541 | B13: 45544 | C13: =VLOOKUP(B:B,'Курс валют'!A:D,4,0) -> 99.7156 | D13: 642 | E13: Отвердитель Starkbond 521C 10.0 бочка 200кг | F13: 8000 | G13: 8010.5 | H13: 0 | I13: =G13-F13 -> 10.5 | J13: =I13/F13*100 -> 0.13125 | K13: 1.95 | L13: =H13/F13*100 -> 0 | M13: =P13/F13 -> 194.44542 | N13: =(F13*K13-H13*3.04)/F13 -> 1.95 | O13: =N13*F13 -> 15600 | P13: =O13*C13 -> 1555563.4
A14: 45541 | B14: 45544 | C14: =VLOOKUP(B:B,'Курс валют'!A:D,4,0) -> 99.7156 | D14: 643 | E14: Клей Starkbond 2014 бочка 225кг | F14: 900 | G14: 935.72 | H14: 365 | I14: =G14-F14 -> 35.72 | J14: =I14/F14*100 -> 3.9688889 | K14: 3.26 | L14: =H14/F14*100 -> 40.555556 | M14: =P14/F14 -> 202.1346 | N14: =(F14*K14-H14*3.04)/F14 -> 2.0271111 | O14: =N14*F14 -> 1824.4 | P14: =O14*C14 -> 181921.14
A15: 45541 | B15: 45544 | C15: =VLOOKUP(B:B,'Курс валют'!A:D,4,0) -> 99.7156 | D15: 644 | E15: отвердитель Starkbond 525C 3.0 ведро 20кг | F15: 200 | G15: 208 | H15: 0 | I15: =G15-F15 -> 8 | J15: =I15/F15*100 -> 4 | K15: 3.46 | L15: =H15/F15*100 -> 0 | M15: =P15/F15 -> 345.01598 | N15: =(F15*K15-H15*3.04)/F15 -> 3.46 | O15: =N15*F15 -> 692 | P15: =O15*C15 -> 69003.195
A16: 45541 | B16: 45544 | C16: =VLOOKUP(B:B,'Курс валют'!A:D,4,0) -> 99.7156 | D16: 645 | E16: Отвердитель Starkbond 521C 10.0 бочка 200кг | F16: 8000 | G16: 8010.5 | H16: 0 | I16: =G16-F16 -> 10.5 | J16: =I16/F16*100 -> 0.13125 | K16: 1.95 | L16: =H16/F16*100 -> 0 | M16: =P16/F16 -> 194.44542 | N16: =(F16*K16-H16*3.04)/F16 -> 1.95 | O16: =N16*F16 -> 15600 | P16: =O16*C16 -> 1555563.4
A17: 45541 | B17: 45544 | C17: =VLOOKUP(B:B,'Курс валют'!A:D,4,0) -> 99.7156 | D17: 646 | E17: Отвердитель Starkbond 521C 10.0 бочка 200кг | F17: 8000 | G17: 8020.5 | H17: 0 | I17: =G17-F17 -> 20.5 | J17: =I17/F17*100 -> 0.25625 | K17: 1.95 | L17: =H17/F17*100 -> 0 | M17: =P17/F17 -> 194.44542 | N17: =(F17*K17-H17*3.04)/F17 -> 1.95 | O17: =N17*F17 -> 15600 | P17: =O17*C17 -> 1555563.4
A18: 45542 | B18: 45545 | C18: =VLOOKUP(B:B,'Курс валют'!A:D,4,0) -> 99.9067 | D18: 647 | E18: Клей Starkbond 525A бочка 220 кг и ведро 22 кг | F18: 1100 | G18: 1137 | H18: 577 | I18: =G18-F18 -> 37 | J18: =I18/F18*100 -> 3.3636364 | K18: 4.05 | L18: =H18/F18*100 -> 52.454545 | M18: =P18/F18 -> 245.30909 | N18: =(F18*K18-H18*3.04)/F18 -> 2.4553818 | O18: =N18*F18 -> 2700.92 | P18: =O18*C18 -> 269840
A19: 45542 | B19: 45545 | C19: =VLOOKUP(B:B,'Курс валют'!A:D,4,0) -> 99.9067 | D19: 648 | E19: Клей Starkbond 522A бочка 220 кг | F19: 6600 | G19: 6620 | H19: 2750 | I19: =G19-F19 -> 20 | J19: =I19/F19*100 -> 0.3030303 | K19: 3.86 | L19: =H19/F19*100 -> 41.666667 | M19: =P19/F19 -> 259.09138 | N19: =(F19*K19-H19*3.04)/F19 -> 2.5933333 | O19: =N19*F19 -> 17116 | P19: =O19*C19 -> 1710003.1
A20: 45542 | B20: 45545 | C20: =VLOOKUP(B:B,'Курс валют'!A:D,4,0) -> 99.9067 | D20: 649 | E20: отвердитель Starkbond 525C 2.0 ведро 20кг | F20: 186 | G20: 200 | H20: 0 | I20: =G20-F20 -> 14 | J20: =I20/F20*100 -> 7.5268817 | K20: 3.94 | L20: =H20/F20*100 -> 0 | M20: =P20/F20 -> 393.6324 | N20: =(F20*K20-H20*3.04)/F20 -> 3.94 | O20: =N20*F20 -> 732.84 | P20: =O20*C20 -> 73215.626 | R20: перелив
A21: 45545 | B21: 45545 | C21: =VLOOKUP(B:B,'Курс валют'!A:D,4,0) -> 99.9067 | D21: 650 | E21: Клей Starkbond 522A бочка 220 кг | F21: 6600 | G21: 6620 | H21: 2750 | I21: =G21-F21 -> 20 | J21: =I21/F21*100 -> 0.3030303 | K21: 3.86 | L21: =H21/F21*100 -> 41.666667 | M21: =P21/F21 -> 259.09138 | N21: =(F21*K21-H21*3.04)/F21 -> 2.5933333 | O21: =N21*F21 -> 17116 | P21: =O21*C21 -> 1710003.1
A22: 45545 | B22: 45545 | C22: =VLOOKUP(B:B,'Курс валют'!A:D,4,0) -> 99.9067 | D22: 651 | E22: отвердитель Starkbond 746/1 С ведро 20кг | F22: 200 | G22: 200 | H22: 0 | I22: =G22-F22 -> 0 | J22: =I22/F22*100 -> 0 | K22: 2.79 | L22: =H22/F22*100 -> 0 | M22: =P22/F22 -> 278.73969 | N22: =(F22*K22-H22*3.04)/F22 -> 2.79 | O22: =N22*F22 -> 558 | P22: =O22*C22 -> 55747.939 | R22: перелив
A23: 45546 | B23: 45546 | C23: =VLOOKUP(B:B,'Курс валют'!A:D,4,0) -> 100.4995 | D23: 653 | E23: Клей Starkbond 745/41 А (бочка 200 кг) | F23: 1000 | G23: 1041 | H23: 220 | I23: =G23-F23 -> 41 | J23: =I23/F23*100 -> 4.1 | K23: 3.3 | L23: =H23/F23*100 -> 22 | M23: =P23/F23 -> 264.43428 | N23: =(F23*K23-H23*3.04)/F23 -> 2.6312 | O23: =N23*F23 -> 2631.2 | P23: =O23*C23 -> 264434.28
A24: 45546 | B24: 45547 | C24: =VLOOKUP(B:B,'Курс валют'!A:D,4,0) -> 100.7421 | D24: 654 | E24: Клей Starkbond 745/41 А (бочка 200 кг) | F24: 1000 | G24: 1030 | H24: 215 | I24: =G24-F24 -> 30 | J24: =I24/F24*100 -> 3 | K24: 3.28 | L24: =H24/F24*100 -> 21.5 | M24: =P24/F24 -> 264.58905 | N24: =(F24*K24-H24*3.04)/F24 -> 2.6264 | O24: =N24*F24 -> 2626.4 | P24: =O24*C24 -> 264589.05
A25: 45546 | B25: 45545 | C25: =VLOOKUP(B:B,'Курс валют'!A:D,4,0) -> 99.9067 | D25: 655 | E25: отвердитель Starkbond 746/1 С ведро 20кг | F25: 200 | G25: 200 | H25: 0 | I25: =G25-F25 -> 0 | J25: =I25/F25*100 -> 0 | K25: 2.79 | L25: =H25/F25*100 -> 0 | M25: =P25/F25 -> 278.73969 | N25: =(F25*K25-H25*3.04)/F25 -> 2.79 | O25: =N25*F25 -> 558 | P25: =O25*C25 -> 55747.939 | R25: перелив
A26: 45547 | B26: 45547 | C26: =VLOOKUP(B:B,'Курс валют'!A:D,4,0) -> 100.7421 | D26: 656 | E26: клей Starkbond 521 A бочка 220кг | F26: 6600 | G26: 6630 | H26: 3030 | I26: =G26-F26 -> 30 | J26: =I26/F26*100 -> 0.45454545 | K26: 4.24 | L26: =H26/F26*100 -> 45.909091 | M26: =P26/F26 -> 286.54717 | N26: =(F26*K26-H26*3.04)/F26 -> 2.8443636 | O26: =N26*F26 -> 18772.8 | P26: =O26*C26 -> 1891211.3
A27: 45540 | B27: 45541 | C27: =VLOOKUP(B:B,'Курс валют'!A:D,4,0) -> 99.1927 | D27: 639 | E27: клей Starkbond 521 A бочка 220кг | F27: 6600 | G27: 6615 | H27: 3015 | I27: =G27-F27 -> 15 | J27: =I27/F27*100 -> 0.22727273 | K27: 4.22 | L27: =H27/F27*100 -> 45.681818 | M27: =P27/F27 -> 280.84159 | N27: =(F27*K27-H27*3.04)/F27 -> 2.8312727 | O27: =N27*F27 -> 18686.4 | P27: =O27*C27 -> 1853554.5
A28: 45546 | B28: 45546 | C28: =VLOOKUP(B:B,'Курс валют'!A:D,4,0) -> 100.4995 | D28: 652 | E28: клей Starkbond 521 A бочка 220кг | F28: 6600 | G28: 6620 | H28: 3020 | I28: =G28-F28 -> 20 | J28: =I28/F28*100 -> 0.3030303 | K28: 4.2 | L28: =H28/F28*100 -> 45.757576 | M28: =P28/F28 -> 282.30005 | N28: =(F28*K28-H28*3.04)/F28 -> 2.8089697 | O28: =N28*F28 -> 18539.2 | P28: =O28*C28 -> 1863180.3
A29: 45547 | B29: 45547 | C29: =VLOOKUP(B:B,'Курс валют'!A:D,4,0) -> 100.7421 | D29: 657 | E29: Клей Starkbond 745/41 А (бочка 200 кг) | F29: 1000 | G29: 1040 | H29: 220 | I29: =G29-F29 -> 40 | J29: =I29/F29*100 -> 4 | K29: 3.28 | L29: =H29/F29*100 -> 22 | M29: =P29/F29 -> 263.05777 | N29: =(F29*K29-H29*3.04)/F29 -> 2.6112 | O29: =N29*F29 -> 2611.2 | P29: =O29*C29 -> 263057.77
A30: 45548 | B30: 45548 | C30: =VLOOKUP(B:B,'Курс валют'!A:D,4,0) -> 100.3907 | D30: 658 | E30: Клей Starkbond 522A бочка 220 кг | F30: 6600 | G30: 6620 | H30: 2750 | I30: =G30-F30 -> 20 | J30: =I30/F30*100 -> 0.3030303 | K30: 3.86 | L30: =H30/F30*100 -> 41.666667 | M30: =P30/F30 -> 260.34655 | N30: =(F30*K30-H30*3.04)/F30 -> 2.5933333 | O30: =N30*F30 -> 17116 | P30: =O30*C30 -> 1718287.2
A31: 45548 | B31: 45548 | C31: =VLOOKUP(B:B,'Курс валют'!A:D,4,0) -> 100.3907 | D31: 659 | E31: Клей Starkbond 745/41 А (бочка 200 кг) | F31: 1000 | G31: 1030 | H31: 240 | I31: =G31-F31 -> 30 | J31: =I31/F31*100 -> 3 | K31: 3.33 | L31: =H31/F31*100 -> 24 | M31: =P31/F31 -> 261.05598 | N31: =(F31*K31-H31*3.04)/F31 -> 2.6004 | O31: =N31*F31 -> 2600.4 | P31: =O31*C31 -> 261055.98
A32: 45548 | B32: 45551 | C32: =VLOOKUP(B:B,'Курс валют'!A:D,4,0) -> 100.7958 | D32: 660 | E32: Клей Starkbond 522A бочка 220 кг | F32: 6600 | G32: 6620 | H32: 2750 | I32: =G32-F32 -> 20 | J32: =I32/F32*100 -> 0.3030303 | K32: 3.86 | L32: =H32/F32*100 -> 41.666667 | M32: =P32/F32 -> 261.39711 | N32: =(F32*K32-H32*3.04)/F32 -> 2.5933333 | O32: =N32*F32 -> 17116 | P32: =O32*C32 -> 1725220.9
A33: 45548 | B33: 45551 | C33: =VLOOKUP(B:B,'Курс валют'!A:D,4,0) -> 100.7958 | D33: 661 | E33: Starkbond 2004 бочка 225 кг | F33: 900 | G33: 951 | H33: 500 | I33: =G33-F33 -> 51 | J33: =I33/F33*100 -> 5.6666667 | K33: 3.79 | L33: =H33/F33*100 -> 55.555556 | M33: =P33/F33 -> 211.78318 | N33: =(F33*K33-H33*3.04)/F33 -> 2.1011111 | O33: =N33*F33 -> 1891 | P33: =O33*C33 -> 190604.86
A34: 45548 | B34: 45551 | C34: =VLOOKUP(B:B,'Курс валют'!A:D,4,0) -> 100.7958 | D34: 662 | E34: Starkbond 2004 бочка 225 кг | F34: 900 | G34: 927 | H34: 500 | I34: =G34-F34 -> 27 | J34: =I34/F34*100 -> 3 | K34: 3.79 | L34: =H34/F34*100 -> 55.555556 | M34: =P34/F34 -> 211.78318 | N34: =(F34*K34-H34*3.04)/F34 -> 2.1011111 | O34: =N34*F34 -> 1891 | P34: =O34*C34 -> 190604.86
A35: 45548 | B35: 45551 | C35: =VLOOKUP(B:B,'Курс валют'!A:D,4,0) -> 100.7958 | D35: 663 | E35: клей Starkbond 521 A бочка 220кг | F35: 4400 | G35: 4410 | H35: 2010 | I35: =G35-F35 -> 10 | J35: =I35/F35*100 -> 0.22727273 | K35: 4.23 | L35: =H35/F35*100 -> 45.681818 | M35: =P35/F35 -> 286.38836 | N35: =(F35*K35-H35*3.04)/F35 -> 2.8412727 | O35: =N35*F35 -> 12501.6 | P35: =O35*C35 -> 1260108.8
A36: 45548 | B36: 45548 | C36: =VLOOKUP(B:B,'Курс валют'!A:D,4,0) -> 100.3907 | D36: 664 | E36: Отвердитель Starkbond 521C 11.0 бочка 200кг | F36: 1600 | G36: 1564.2 | H36: 0 | I36: =G36-F36 -> -35.8 | J36: =I36/F36*100 -> -2.2375 | K36: 1.94 | L36: =H36/F36*100 -> 0 | M36: =P36/F36 -> 194.75796 | N36: =(F36*K36-H36*3.04)/F36 -> 1.94 | O36: =N36*F36 -> 3104 | P36: =O36*C36 -> 311612.73
A37: 45548 | B37: 45551 | C37: =VLOOKUP(B:B,'Курс валют'!A:D,4,0) -> 100.7958 | D37: 665 | E37: Starkbond 2004 бочка 225 кг | F37: 900 | G37: 929 | H37: 500 | I37: =G37-F37 -> 29 | J37: =I37/F37*100 -> 3.2222222 | K37: 3.79 | L37: =H37/F37*100 -> 55.555556 | M37: =P37/F37 -> 211.78318 | N37: =(F37*K37-H37*3.04)/F37 -> 2.1011111 | O37: =N37*F37 -> 1891 | P37: =O37*C37 -> 190604.86
... A56: 45558 | B56: 45558 | C56: =VLOOKUP(B:B,'Курс валют'!A:D,4,0) -> 103.3773 | D56: 684 | E56: клей Starkbond 521 A бочка 220кг | F56: 6600 | G56: 6615 | H56: 3020 | I56: =G56-F56 -> 15 | J56: =I56/F56*100 -> 0.22727273 | K56: 3.87 | L56: =H56/F56*100 -> 45.757576 | M56: =P56/F56 -> 256.26919 | N56: =(F56*K56-H56*3.04)/F56 -> 2.4789697 | O56: =N56*F56 -> 16361.2 | P56: =O56*C56 -> 1691376.7
A57: 45558 | B57: 45558 | C57: =VLOOKUP(B:B,'Курс валют'!A:D,4,0) -> 103.3773 | D57: 685 | E57: отвердитель Starkbond 746 С ведро 20кг | F57: 220 | G57: 220 | H57: 0 | I57: =G57-F57 -> 0 | J57: =I57/F57*100 -> 0 | K57: 2.83 | L57: =H57/F57*100 -> 0 | M57: =P57/F57 -> 292.55776 | N57: =(F57*K57-H57*3.04)/F57 -> 2.83 | O57: =N57*F57 -> 622.6 | P57: =O57*C57 -> 64362.707 | R57: перелив
A58: 45559 | B58: 45560 | C58: =VLOOKUP(B:B,'Курс валют'!A:D,4,0) -> 103.41 | D58: 686 | E58: клей Starkbond 521 A бочка 220кг | F58: 6600 | G58: 6615 | H58: 3020 | I58: =G58-F58 -> 15 | J58: =I58/F58*100 -> 0.22727273 | K58: 3.87 | L58: =H58/F58*100 -> 45.757576 | M58: =P58/F58 -> 256.35026 | N58: =(F58*K58-H58*3.04)/F58 -> 2.4789697 | O58: =N58*F58 -> 16361.2 | P58: =O58*C58 -> 1691911.7
A59: 45559 | B59: 45560 | C59: =VLOOKUP(B:B,'Курс валют'!A:D,4,0) -> 103.41 | D59: 687 | E59: Клей Starkbond 2014 бочка 225кг | F59: 900 | G59: 928 | H59: 370 | I59: =G59-F59 -> 28 | J59: =I59/F59*100 -> 3.1111111 | K59: 3.22 | L59: =H59/F59*100 -> 41.111111 | M59: =P59/F59 -> 203.74068 | N59: =(F59*K59-H59*3.04)/F59 -> 1.9702222 | O59: =N59*F59 -> 1773.2 | P59: =O59*C59 -> 183366.61
A60: 45560 | B60: 45561 | C60: =VLOOKUP(B:B,'Курс валют'!A:D,4,0) -> 103.4758 | D60: 688 | E60: клей Starkbond 521 A бочка 220кг | F60: 6600 | G60: 6607 | H60: 3012 | I60: =G60-F60 -> 7 | J60: =I60/F60*100 -> 0.10606061 | K60: 3.86 | L60: =H60/F60*100 -> 45.636364 | M60: =P60/F60 -> 255.85991 | N60: =(F60*K60-H60*3.04)/F60 -> 2.4726545 | O60: =N60*F60 -> 16319.52 | P60: =O60*C60 -> 1688675.4
A61: 45560 | B61: 45561 | C61: =VLOOKUP(B:B,'Курс валют'!A:D,4,0) -> 103.4758 | D61: 689 | E61: Клей Starkbond 2014 бочка 225кг | F61: 900 | G61: 930 | H61: 370 | I61: =G61-F61 -> 30 | J61: =I61/F61*100 -> 3.3333333 | K61: 3.22 | L61: =H61/F61*100 -> 41.111111 | M61: =P61/F61 -> 203.87032 | N61: =(F61*K61-H61*3.04)/F61 -> 1.9702222 | O61: =N61*F61 -> 1773.2 | P61: =O61*C61 -> 183483.29
A62: 45560 | B62: 45561 | C62: =VLOOKUP(B:B,'Курс валют'!A:D,4,0) -> 103.4758 | D62: 690 | E62: Клей Starkbond 2014 бочка 225кг | F62: 900 | G62: 930 | H62: 368 | I62: =G62-F62 -> 30 | J62: =I62/F62*100 -> 3.3333333 | K62: 3.22 | L62: =H62/F62*100 -> 40.888889 | M62: =P62/F62 -> 204.56936 | N62: =(F62*K62-H62*3.04)/F62 -> 1.9769778 | O62: =N62*F62 -> 1779.28 | P62: =O62*C62 -> 184112.42
A63: 45561 | B63: 45562 | C63: =VLOOKUP(B:B,'Курс валют'!A:D,4,0) -> 103.1931 | D63: 691 | E63: клей Starkbond 521 A бочка 220кг | F63: 6600 | G63: 6610 | H63: 3015 | I63: =G63-F63 -> 10 | J63: =I63/F63*100 -> 0.15151515 | K63: 3.86 | L63: =H63/F63*100 -> 45.681818 | M63: =P63/F63 -> 255.01829 | N63: =(F63*K63-H63*3.04)/F63 -> 2.4712727 | O63: =N63*F63 -> 16310.4 | P63: =O63*C63 -> 1683120.7
A64: 45561 | B64: 45562 | C64: =VLOOKUP(B:B,'Курс валют'!A:D,4,0) -> 103.1931 | D64: 692 | E64: Клей Starkbond 2014 бочка 225кг | F64: 900 | G64: 926 | H64: 367 | I64: =G64-F64 -> 26 | J64: =I64/F64*100 -> 2.8888889 | K64: 3.2 | L64: =H64/F64*100 -> 40.777778 | M64: =P64/F64 -> 202.29517 | N64: =(F64*K64-H64*3.04)/F64 -> 1.9603556 | O64: =N64*F64 -> 1764.32 | P64: =O64*C64 -> 182065.65
A65: 45562 | B65: 45565 | C65: =VLOOKUP(B:B,'Курс валют'!A:D,4,0) -> 103.4694 | D65: 702 | E65: отвердитель Starkbond 746/1 С бочка 180 кг, ведро 20 кг | F65: 200 | G65: 200 | H65: 0 | I65: =G65-F65 -> 0 | J65: =I65/F65*100 -> 0 | K65: 2.65 | L65: =H65/F65*100 -> 0 | M65: =P65/F65 -> 274.19391 | N65: =(F65*K65-H65*3.04)/F65 -> 2.65 | O65: =N65*F65 -> 530 | P65: =O65*C65 -> 54838.782 | R65: перелив
A66: 45562 | B66: 45565 | C66: =VLOOKUP(B:B,'Курс валют'!A:D,4,0) -> 103.4694 | D66: 694 | E66: клей Starkbond 521 A бочка 220кг | F66: 6600 | G66: 6624 | H66: 3015 | I66: =G66-F66 -> 24 | J66: =I66/F66*100 -> 0.36363636 | K66: 3.97 | L66: =H66/F66*100 -> 45.681818 | M66: =P66/F66 -> 267.08274 | N66: =(F66*K66-H66*3.04)/F66 -> 2.5812727 | O66: =N66*F66 -> 17036.4 | P66: =O66*C66 -> 1762746.1
A67: 45562 | B67: 45565 | C67: =VLOOKUP(B:B,'Курс валют'!A:D,4,0) -> 103.4694 | D67: 696 | E67: клей Starkbond 521 A бочка 220кг | F67: 6600 | G67: 6610 | H67: 3015 | I67: =G67-F67 -> 10 | J67: =I67/F67*100 -> 0.15151515 | K67: 3.97 | L67: =H67/F67*100 -> 45.681818 | M67: =P67/F67 -> 267.08274 | N67: =(F67*K67-H67*3.04)/F67 -> 2.5812727 | O67: =N67*F67 -> 17036.4 | P67: =O67*C67 -> 1762746.1
A68: 45562 | B68: 45565 | C68: =VLOOKUP(B:B,'Курс валют'!A:D,4,0) -> 103.4694 | D68: 699 | E68: клей Starkbond 521 A бочка 220кг | F68: 6600 | G68: 6625 | H68: 3015 | I68: =G68-F68 -> 25 | J68: =I68/F68*100 -> 0.37878788 | K68: 3.97 | L68: =H68/F68*100 -> 45.681818 | M68: =P68/F68 -> 267.08274 | N68: =(F68*K68-H68*3.04)/F68 -> 2.5812727 | O68: =N68*F68 -> 17036.4 | P68: =O68*C68 -> 1762746.1
A69: 45565 | B69: 45565 | C69: =VLOOKUP(B:B,'Курс валют'!A:D,4,0) -> 103.4694 | D69: 695 | E69: Клей Starkbond 2014 бочка 225кг | F69: 900 | G69: 930.5 | H69: 370 | I69: =G69-F69 -> 30.5 | J69: =I69/F69*100 -> 3.3888889 | K69: 3.26 | L69: =H69/F69*100 -> 41.111111 | M69: =P69/F69 -> 207.99649 | N69: =(F69*K69-H69*3.04)/F69 -> 2.0102222 | O69: =N69*F69 -> 1809.2 | P69: =O69*C69 -> 187196.84
A70: 45565 | B70: 45568 | C70: =VLOOKUP(B:B,'Курс валют'!A:D,4,0) -> 104.4481 | D70: 697 | E70: Клей Starkbond 745/41 А (бочка 200 кг) | F70: 1000 | G70: 1030 | H70: 216 | I70: =G70-F70 -> 30 | J70: =I70/F70*100 -> 3 | K70: 3.18 | L70: =H70/F70*100 -> 21.6 | M70: =P70/F70 -> 263.56016 | N70: =(F70*K70-H70*3.04)/F70 -> 2.52336 | O70: =N70*F70 -> 2523.36 | P70: =O70*C70 -> 263560.16
A71: 30..09.24 | B71: 45568 | C71: =VLOOKUP(B:B,'Курс валют'!A:D,4,0) -> 104.4481 | D71: 698 | E71: Клей Starkbond 745/41 А (бочка 200 кг) | F71: 1000 | G71: 1027 | H71: 216 | I71: =G71-F71 -> 27 | J71: =I71/F71*100 -> 2.7 | K71: 3.18 | L71: =H71/F71*100 -> 21.6 | M71: =P71/F71 -> 263.56016 | N71: =(F71*K71-H71*3.04)/F71 -> 2.52336 | O71: =N71*F71 -> 2523.36 | P71: =O71*C71 -> 263560.16
A72: 45565 | B72: 45569 | C72: =VLOOKUP(B:B,'Курс валют'!A:D,4,0) -> 104.8664 | D72: 700 | E72: Клей Starkbond 745/41 А (бочка 200 кг) | F72: 1000 | G72: 1025 | H72: 216 | I72: =G72-F72 -> 25 | J72: =I72/F72*100 -> 2.5 | K72: 3.17 | L72: =H72/F72*100 -> 21.6 | M72: =P72/F72 -> 263.56702 | N72: =(F72*K72-H72*3.04)/F72 -> 2.51336 | O72: =N72*F72 -> 2513.36 | P72: =O72*C72 -> 263567.02
A73: 45565 | B73: 45567 | C73: =VLOOKUP(B:B,'Курс валют'!A:D,4,0) -> 103.6502 | D73: 701 | E73: клей Starkbond 745/3 А бочка 200кг | F73: 1000 | G73: 1023 | H73: 110 | I73: =G73-F73 -> 23 | J73: =I73/F73*100 -> 2.3 | K73: 2.75 | L73: =H73/F73*100 -> 11 | M73: =P73/F73 -> 250.37742 | N73: =(F73*K73-H73*3.04)/F73 -> 2.4156 | O73: =N73*F73 -> 2415.6 | P73: =O73*C73 -> 250377.42
A74: 45566 | B74: 45566 | C74: =VLOOKUP(B:B,'Курс валют'!A:D,4,0) -> 104.1735 | D74: 703 | E74: клей Starkbond 521 A бочка 220кг | F74: 6600 | G74: 6606 | H74: 3015 | I74: =G74-F74 -> 6 | J74: =I74/F74*100 -> 0.090909091 | K74: 3.79 | L74: =H74/F74*100 -> 45.681818 | M74: =P74/F74 -> 250.14898 | N74: =(F74*K74-H74*3.04)/F74 -> 2.4012727 | O74: =N74*F74 -> 15848.4 | P74: =O74*C74 -> 1650983.3
A75: 45566 | B75: 45566 | C75: =VLOOKUP(B:B,'Курс валют'!A:D,4,0) -> 104.1735 | D75: 621 | E75: Клей Starkbond 2014 ведро 10 кг ОБРАЗЦЫ | F75: 30 | G75: 37.9 | H75: 15 | I75: =G75-F75 -> 7.9 | J75: =I75/F75*100 -> 26.333333 | K75: 4.36 | L75: =H75/F75*100 -> 50 | M75: =P75/F75 -> 295.85274 | N75: =(F75*K75-H75*3.04)/F75 -> 2.84 | O75: =N75*F75 -> 85.2 | P75: =O75*C75 -> 8875.5822 | R75: Starkbond 2014 RB101 ведро 10 кг, Starkbond 2014 RC301 ведро 10 кг, Starkbond 2014 RH201 ведро 10 кг
A76: 45566 | B76: 45566 | C76: =VLOOKUP(B:B,'Курс валют'!A:D,4,0) -> 104.1735 | D76: 622 | E76: Клей Starkbond 2014 ведро 10 кг ОБРАЗЦЫ | F76: 30 | G76: 32.52 | H76: =5.334+5.333+5.333 -> 16 | I76: =G76-F76 -> 2.52 | J76: =I76/F76*100 -> 8.4 | K76: 4.43 | L76: =H76/F76*100 -> 53.333333 | M76: =P76/F76 -> 292.58864 | N76: =(F76*K76-H76*3.04)/F76 -> 2.8086667 | O76: =N76*F76 -> 84.26 | P76: =O76*C76 -> 8777.6591 | R76: Starkbond 2014 RB103 ведро 10 кг, Starkbond 2014 RH202 ведро 10 кг, Starkbond 2014 RB102 ведро 10 кг
A77: 45567 | B77: 45568 | C77: =VLOOKUP(B:B,'Курс валют'!A:D,4,0) -> 104.4481 | D77: 704 | E77: клей Starkbond 745/3 А бочка 200кг | F77: 1000 | G77: 1024 | H77: 112 | I77: =G77-F77 -> 24 | J77: =I77/F77*100 -> 2.4 | K77: 2.83 | L77: =H77/F77*100 -> 11.2 | M77: =P77/F77 -> 260.02563 | N77: =(F77*K77-H77*3.04)/F77 -> 2.48952 | O77: =N77*F77 -> 2489.52 | P77: =O77*C77 -> 260025.63
A78: 45567 | B78: 45568 | C78: =VLOOKUP(B:B,'Курс валют'!A:D,4,0) -> 104.4481 | D78: 705 | E78: отвердитель Starkbond 746/1 С бочка 200кг и ведро 20кг | F78: 800 | G78: 816.75 | H78: 0 | I78: =G78-F78 -> 16.75 | J78: =I78/F78*100 -> 2.09375 | K78: 2.44 | L78: =H78/F78*100 -> 0 | M78: =P78/F78 -> 254.85336 | N78: =(F78*K78-H78*3.04)/F78 -> 2.44 | O78: =N78*F78 -> 1952 | P78: =O78*C78 -> 203882.69 | R78: отвердитель Starkbond 746/1 С ведро 20кг, отвердитель Starkbond 746/1 С бочка 200кг
A79: 45567 | B79: 45568 | C79: =VLOOKUP(B:B,'Курс валют'!A:D,4,0) -> 104.4481 | D79: 706 | E79: Отвердитель Starkbond 521C 11.0 бочка 200кг | F79: 4000 | G79: 4026 | H79: 0 | I79: =G79-F79 -> 26 | J79: =I79/F79*100 -> 0.65 | K79: 1.99 | L79: =H79/F79*100 -> 0 | M79: =P79/F79 -> 207.85172 | N79: =(F79*K79-H79*3.04)/F79 -> 1.99 | O79: =N79*F79 -> 7960 | P79: =O79*C79 -> 831406.88
A80: 45567 | B80: 45568 | C80: =VLOOKUP(B:B,'Курс валют'!A:D,4,0) -> 104.4481 | D80: 707 | E80: Starkbond 2004 бочка 225 кг | F80: 900 | G80: 920.01 | H80: 492 | I80: =G80-F80 -> 20.01 | J80: =I80/F80*100 -> 2.2233333 | K80: 3.73 | L80: =H80/F80*100 -> 54.666667 | M80: =P80/F80 -> 216.0126 | N80: =(F80*K80-H80*3.04)/F80 -> 2.0681333 | O80: =N80*F80 -> 1861.32 | P80: =O80*C80 -> 194411.34
A81: 45568 | B81: 45569 | C81: =VLOOKUP(B:B,'Курс валют'!A:D,4,0) -> 104.8664 | D81: 714 | E81: Клей Starkbond 522A ведро 22 кг | F81: 220 | G81: 220 | H81: 0 | I81: =G81-F81 -> 0 | J81: =I81/F81*100 -> 0 | K81: 4.04 | L81: =H81/F81*100 -> 0 | M81: =P81/F81 -> 423.66026 | N81: =(F81*K81-H81*3.04)/F81 -> 4.04 | O81: =N81*F81 -> 888.8 | P81: =O81*C81 -> 93205.256 | R81: перелив
A82: 45568 | B82: 45569 | C82: =VLOOKUP(B:B,'Курс валют'!A:D,4,0) -> 104.8664 | D82: 708 | E82: Отвердитель Starkbond 521C 11.0 бочка 200кг | F82: 1600 | G82: 1605.906 | H82: 0 | I82: =G82-F82 -> 5.906 | J82: =I82/F82*100 -> 0.369125 | K82: 1.99 | L82: =H82/F82*100 -> 0 | M82: =P82/F82 -> 208.68414 | N82: =(F82*K82-H82*3.04)/F82 -> 1.99 | O82: =N82*F82 -> 3184 | P82: =O82*C82 -> 333894.62
A83: 45568 | B83: 45569 | C83: =VLOOKUP(B:B,'Курс валют'!A:D,4,0) -> 104.8664 | D83: 709 | E83: отвердитель Starkbond 521 C 3.0 бочка 200кг | F83: 1600 | G83: 1603.7 | H83: 151.72 | I83: =G83-F83 -> 3.7 | J83: =I83/F83*100 -> 0.23125 | K83: 2.03 | L83: =H83/F83*100 -> 9.4825 | M83: =P83/F83 -> 182.64916 | N83: =(F83*K83-H83*3.04)/F83 -> 1.741732 | O83: =N83*F83 -> 2786.7712 | P83: =O83*C83 -> 292238.66
A84: 45568 | B84: 45569 | C84: =VLOOKUP(B:B,'Курс валют'!A:D,4,0) -> 104.8664 | D84: 711 | E84: Starkbond 2004 бочка 225 кг | F84: 900 | G84: 928.67 | H84: 494.66 | I84: =G84-F84 -> 28.67 | J84: =I84/F84*100 -> 3.1855556 | K84: 3.75 | L84: =H84/F84*100 -> 54.962222 | M84: =P84/F84 -> 218.03281 | N84: =(F84*K84-H84*3.04)/F84 -> 2.0791484 | O84: =N84*F84 -> 1871.2336 | P84: =O84*C84 -> 196229.53
A85: 45569 | B85: 45572 | C85: =VLOOKUP(B:B,'Курс валют'!A:D,4,0) -> 104.7424 | D85: 710 | E85: Клей Starkbond 2014 бочка 225кг | F85: 900 | G85: 931 | H85: 370 | I85: =G85-F85 -> 31 | J85: =I85/F85*100 -> 3.4444444 | K85: 3.26 | L85: =H85/F85*100 -> 41.111111 | M85: =P85/F85 -> 210.5555 | N85: =(F85*K85-H85*3.04)/F85 -> 2.0102222 | O85: =N85*F85 -> 1809.2 | P85: =O85*C85 -> 189499.95
A86: 45569 | B86: 45572 | C86: =VLOOKUP(B:B,'Курс валют'!A:D,4,0) -> 104.7424 | D86: 713 | E86: Клей Starkbond 2014 бочка 225кг | F86: 900 | G86: 927 | H86: 368 | I86: =G86-F86 -> 27 | J86: =I86/F86*100 -> 3 | K86: 3.26 | L86: =H86/F86*100 -> 40.888889 | M86: =P86/F86 -> 211.26309 | N86: =(F86*K86-H86*3.04)/F86 -> 2.0169778 | O86: =N86*F86 -> 1815.28 | P86: =O86*C86 -> 190136.78
A87: 45569 | B87: 45572 | C87: =VLOOKUP(B:B,'Курс валют'!A:D,4,0) -> 104.7424 | D87: 716 | E87: Клей Starkbond 2014 бочка 225кг | F87: 900 | G87: 928 | H87: 367 | I87: =G87-F87 -> 28 | J87: =I87/F87*100 -> 3.1111111 | K87: 3.26 | L87: =H87/F87*100 -> 40.777778 | M87: =P87/F87 -> 211.61689 | N87: =(F87*K87-H87*3.04)/F87 -> 2.0203556 | O87: =N87*F87 -> 1818.32 | P87: =O87*C87 -> 190455.2
A88: 45569 | B88: 45572 | C88: =VLOOKUP(B:B,'Курс валют'!A:D,4,0) -> 104.7424 | D88: 712 | E88: отвердитель Starkbond 521 C 2.2 бочка 200кг | F88: 6400 | G88: 6411.6 | H88: 605 | I88: =G88-F88 -> 11.6 | J88: =I88/F88*100 -> 0.18125 | K88: 2.13 | L88: =H88/F88*100 -> 9.453125 | M88: =P88/F88 -> 193.00096 | N88: =(F88*K88-H88*3.04)/F88 -> 1.842625 | O88: =N88*F88 -> 11792.8 | P88: =O88*C88 -> 1235206.2
A89: 45569 | B89: 45572 | C89: =VLOOKUP(B:B,'Курс валют'!A:D,4,0) -> 104.7424 | D89: 715 | E89: отвердитель Starkbond 521 C 3.0 бочка 200кг | F89: 8000 | G89: 8009.2 | H89: 760 | I89: =G89-F89 -> 9.2 | J89: =I89/F89*100 -> 0.115 | K89: 2.12 | L89: =H89/F89*100 -> 9.5 | M89: =P89/F89 -> 191.80428 | N89: =(F89*K89-H89*3.04)/F89 -> 1.8312 | O89: =N89*F89 -> 14649.6 | P89: =O89*C89 -> 1534434.3
A90: 45569 | B90: 45572 | C90: =VLOOKUP(B:B,'Курс валют'!A:D,4,0) -> 104.7424 | D90: 717 | E90: отвердитель Starkbond 521 C 3.0 бочка 200кг | F90: 7200 | G90: 7212.5 | H90: 683 | I90: =G90-F90 -> 12.5 | J90: =I90/F90*100 -> 0.17361111 | K90: 2.12 | L90: =H90/F90*100 -> 9.4861111 | M90: =P90/F90 -> 191.84851 | N90: =(F90*K90-H90*3.04)/F90 -> 1.8316222 | O90: =N90*F90 -> 13187.68 | P90: =O90*C90 -> 1381309.3
A91: 45572 | B91: 45573 | C91: =VLOOKUP(B:B,'Курс валют'!A:D,4,0) -> 105.3069 | D91: 718 | E91: Клей Starkbond 2014 бочка 225кг | F91: 900 | G91: 935 | H91: 368 | I91: =G91-F91 -> 35 | J91: =I91/F91*100 -> 3.8888889 | K91: 3.23 | L91: =H91/F91*100 -> 40.888889 | M91: =P91/F91 -> 209.24247 | N91: =(F91*K91-H91*3.04)/F91 -> 1.9869778 | O91: =N91*F91 -> 1788.28 | P91: =O91*C91 -> 188318.22
A92: 45572 | B92: 45573 | C92: =VLOOKUP(B:B,'Курс валют'!A:D,4,0) -> 105.3069 | D92: 719 | E92: клей Starkbond 745/3 А бочка 200кг | F92: 1000 | G92: 1026 | H92: 111 | I92: =G92-F92 -> 26 | J92: =I92/F92*100 -> 2.6 | K92: 2.74 | L92: =H92/F92*100 -> 11.1 | M92: =P92/F92 -> 253.00615 | N92: =(F92*K92-H92*3.04)/F92 -> 2.40256 | O92: =N92*F92 -> 2402.56 | P92: =O92*C92 -> 253006.15
A93: 45572 | B93: 45573 | C93: =VLOOKUP(B:B,'Курс валют'!A:D,4,0) -> 105.3069 | D93: 720 | E93: клей Starkbond 521 A бочка 220кг | F93: 8800 | G93: 8811 | H93: 4016 | I93: =G93-F93 -> 11 | J93: =I93/F93*100 -> 0.125 | K93: 3.09 | L93: =H93/F93*100 -> 45.636364 | M93: =P93/F93 -> 179.30127 | N93: =(F93*K93-H93*3.04)/F93 -> 1.7026545 | O93: =N93*F93 -> 14983.36 | P93: =O93*C93 -> 1577851.2
A94: 45573 | B94: 45573 | C94: =VLOOKUP(B:B,'Курс валют'!A:D,4,0) -> 105.3069 | D94: 726 | E94: отвердитель Starkbond 746 С ведро 20кг | F94: 200 | G94: 200 | H94: 0 | I94: =G94-F94 -> 0 | J94: =I94/F94*100 -> 0 | K94: 2.64 | L94: =H94/F94*100 -> 0 | M94: =P94/F94 -> 278.01022 | N94: =(F94*K94-H94*3.04)/F94 -> 2.64 | O94: =N94*F94 -> 528 | P94: =O94*C94 -> 55602.043 | R94: перелив
A95: 45573 | B95: 45573 | C95: =VLOOKUP(B:B,'Курс валют'!A:D,4,0) -> 105.3069 | D95: 727 | E95: Клей Starkbond 745/3А (ведро 20кг) | F95: 200 | G95: 200 | H95: 0 | I95: =G95-F95 -> 0 | J95: =I95/F95*100 -> 0 | K95: 2.96 | L95: =H95/F95*100 -> 0 | M95: =P95/F95 -> 311.70842 | N95: =(F95*K95-H95*3.04)/F95 -> 2.96 | O95: =N95*F95 -> 592 | P95: =O95*C95 -> 62341.685 | R95: перелив
A96: 45573 | B96: 45574 | C96: =VLOOKUP(B:B,'Курс валют'!A:D,4,0) -> 105.6891 | D96: 721 | E96: Клей Starkbond 2014 бочка 225кг | F96: 900 | G96: 929 | H96: 368 | I96: =G96-F96 -> 29 | J96: =I96/F96*100 -> 3.2222222 | K96: 3.23 | L96: =H96/F96*100 -> 40.888889 | M96: =P96/F96 -> 210.00189 | N96: =(F96*K96-H96*3.04)/F96 -> 1.9869778 | O96: =N96*F96 -> 1788.28 | P96: =O96*C96 -> 189001.7
A97: 45573 | B97: 45574 | C97: =VLOOKUP(B:B,'Курс валют'!A:D,4,0) -> 105.6891 | D97: 722 | E97: Клей Starkbond 2014 бочка 225кг | F97: 900 | G97: 930 | H97: 367 | I97: =G97-F97 -> 30 | J97: =I97/F97*100 -> 3.3333333 | K97: 3.36 | L97: =H97/F97*100 -> 40.777778 | M97: =P97/F97 -> 224.09847 | N97: =(F97*K97-H97*3.04)/F97 -> 2.1203556 | O97: =N97*F97 -> 1908.32 | P97: =O97*C97 -> 201688.62
A98: 45573 | B98: 45574 | C98: =VLOOKUP(B:B,'Курс валют'!A:D,4,0) -> 105.6891 | D98: 723 | E98: клей Starkbond 521 A бочка 220кг | F98: 4400 | G98: 4411 | H98: 2011 | I98: =G98-F98 -> 11 | J98: =I98/F98*100 -> 0.25 | K98: 4.02 | L98: =H98/F98*100 -> 45.704545 | M98: =P98/F98 -> 278.02382 | N98: =(F98*K98-H98*3.04)/F98 -> 2.6305818 | O98: =N98*F98 -> 11574.56 | P98: =O98*C98 -> 1223304.8
A99: 45575 | B99: 45575 | C99: =VLOOKUP(B:B,'Курс валют'!A:D,4,0) -> 106.4175 | D99: 731 | E99: отвердитель Starkbond 746/1 С ведро 20кг | F99: 176 | G99: 180 | H99: 0 | I99: =G99-F99 -> 4 | J99: =I99/F99*100 -> 2.2727273 | K99: 2.93 | L99: =H99/F99*100 -> 0 | M99: =P99/F99 -> 311.80328 | N99: =(F99*K99-H99*3.04)/F99 -> 2.93 | O99: =N99*F99 -> 515.68 | P99: =O99*C99 -> 54877.376 | R99: перелив
A100: 45574 | B100: 45575 | C100: =VLOOKUP(B:B,'Курс валют'!A:D,4,0) -> 106.4175 | D100: 724 | E100: Клей Starkbond 2014 бочка 225кг | F100: 900 | G100: 931 | H100: 368 | I100: =G100-F100 -> 31 | J100: =I100/F100*100 -> 3.4444444 | K100: 3.38 | L100: =H100/F100*100 -> 40.888889 | M100: =P100/F100 -> 227.41183 | N100: =(F100*K100-H100*3.04)/F100 -> 2.1369778 | O100: =N100*F100 -> 1923.28 | P100: =O100*C100 -> 204670.65
A101: 45574 | B101: 45575 | C101: =VLOOKUP(B:B,'Курс валют'!A:D,4,0) -> 106.4175 | D101: 725 | E101: Клей Starkbond 2014 бочка 225кг | F101: 900 | G101: 929 | H101: 367 | I101: =G101-F101 -> 29 | J101: =I101/F101*100 -> 3.2222222 | K101: 3.38 | L101: =H101/F101*100 -> 40.777778 | M101: =P101/F101 -> 227.77129 | N101: =(F101*K101-H101*3.04)/F101 -> 2.1403556 | O101: =N101*F101 -> 1926.32 | P101: =O101*C101 -> 204994.16
A102: 45574 | B102: 45575 | C102: =VLOOKUP(B:B,'Курс валют'!A:D,4,0) -> 106.4175 | D102: 728 | E102: клей Starkbond 521 A бочка 220кг | F102: 2200 | G102: 2208 | H102: 1008 | I102: =G102-F102 -> 8 | J102: =I102/F102*100 -> 0.36363636 | K102: 4.28 | L102: =H102/F102*100 -> 45.818182 | M102: =P102/F102 -> 307.24087 | N102: =(F102*K102-H102*3.04)/F102 -> 2.8871273 | O102: =N102*F102 -> 6351.68 | P102: =O102*C102 -> 675929.91
A103: 45574 | B103: 45575 | C103: =VLOOKUP(B:B,'Курс валют'!A:D,4,0) -> 106.4175 | D103: 729 | E103: клей Starkbond 521 A бочка 220кг | F103: 4400 | G103: 4412 | H103: 2012 | I103: =G103-F103 -> 12 | J103: =I103/F103*100 -> 0.27272727 | K103: 4.28 | L103: =H103/F103*100 -> 45.727273 | M103: =P103/F103 -> 307.53497 | N103: =(F103*K103-H103*3.04)/F103 -> 2.8898909 | O103: =N103*F103 -> 12715.52 | P103: =O103*C103 -> 1353153.8
A104: 45574 | B104: 45574 | C104: =VLOOKUP(B:B,'Курс валют'!A:D,4,0) -> 105.6891 | D104: 730 | E104: Клей Starkbond 2014 бочка 225кг | F104: 900 | G104: 931 | H104: 368 | I104: =G104-F104 -> 31 | J104: =I104/F104*100 -> 3.4444444 | K104: 3.36 | L104: =H104/F104*100 -> 40.888889 | M104: =P104/F104 -> 223.74148 | N104: =(F104*K104-H104*3.04)/F104 -> 2.1169778 | O104: =N104*F104 -> 1905.28 | P104: =O104*C104 -> 201367.33
A105: 45575 | B105: 45575 | C105: =VLOOKUP(B:B,'Курс валют'!A:D,4,0) -> 106.4175 | D105: 732 | E105: Отвердитель Starkbond 525C 2.0 Бочка 200 кг | F105: 2400 | G105: 2424 | H105: 0 | I105: =G105-F105 -> 24 | J105: =I105/F105*100 -> 1 | K105: 3.33 | L105: =H105/F105*100 -> 0 | M105: =P105/F105 -> 354.37027 | N105: =(F105*K105-H105*3.04)/F105 -> 3.33 | O105: =N105*F105 -> 7992 | P105: =O105*C105 -> 850488.66
A106: 45576 | B106: 45579 | C106: =VLOOKUP(B:B,'Курс валют'!A:D,4,0) -> 105.1095 | D106: 736 | E106: Клей Starkbond 745/41 А (ведро 20кг) | F106: 400 | G106: 400 | H106: 0 | I106: =G106-F106 -> 0 | J106: =I106/F106*100 -> 0 | K106: 3.53 | L106: =H106/F106*100 -> 0 | M106: =P106/F106 -> 371.03654 | N106: =(F106*K106-H106*3.04)/F106 -> 3.53 | O106: =N106*F106 -> 1412 | P106: =O106*C106 -> 148414.61 | R106: перелив
A107: 45579 | B107: 45579 | C107: =VLOOKUP(B:B,'Курс валют'!A:D,4,0) -> 105.1095 | D107: 737 | E107: Клей Starkbond 745/40А ведро 20 кг | F107: 400 | G107: 400 | H107: 0 | I107: =G107-F107 -> 0 | J107: =I107/F107*100 -> 0 | K107: 3.5 | L107: =H107/F107*100 -> 0 | M107: =P107/F107 -> 367.88325 | N107: =(F107*K107-H107*3.04)/F107 -> 3.5 | O107: =N107*F107 -> 1400 | P107: =O107*C107 -> 147153.3 | R107: смена номенклатуры
A108: 45576 | B108: 45579 | C108: =VLOOKUP(B:B,'Курс валют'!A:D,4,0) -> 105.1095 | D108: 745 | E108: Клей Starkbond 745/41 А (бочка 200 кг) | F108: 2000 | G108: 2100 | H108: 0 | I108: =G108-F108 -> 100 | J108: =I108/F108*100 -> 5 | K108: 3.32 | L108: =H108/F108*100 -> 0 | M108: =P108/F108 -> 348.96354 | N108: =(F108*K108-H108*3.04)/F108 -> 3.32 | O108: =N108*F108 -> 6640 | P108: =O108*C108 -> 697927.08 | R108: довели до кондиции сентябрьскую партию
A109: 45576 | B109: 45579 | C109: =VLOOKUP(B:B,'Курс валют'!A:D,4,0) -> 105.1095 | D109: 733 | E109: Клей Starkbond 2014 бочка 225кг | F109: 900 | G109: 932 | H109: 368 | I109: =G109-F109 -> 32 | J109: =I109/F109*100 -> 3.5555556 | K109: 3.4 | L109: =H109/F109*100 -> 40.888889 | M109: =P109/F109 -> 226.71886 | N109: =(F109*K109-H109*3.04)/F109 -> 2.1569778 | O109: =N109*F109 -> 1941.28 | P109: =O109*C109 -> 204046.97
A110: 45576 | B110: 45579 | C110: =VLOOKUP(B:B,'Курс валют'!A:D,4,0) -> 105.1095 | D110: 734 | E110: клей Starkbond 521 A бочка 220кг | F110: 4400 | G110: 4412 | H110: 2012 | I110: =G110-F110 -> 12 | J110: =I110/F110*100 -> 0.27272727 | K110: 4.02 | L110: =H110/F110*100 -> 45.727273 | M110: =P110/F110 -> 276.42652 | N110: =(F110*K110-H110*3.04)/F110 -> 2.6298909 | O110: =N110*F110 -> 11571.52 | P110: =O110*C110 -> 1216276.7
A111: 45576 | B111: 45579 | C111: =VLOOKUP(B:B,'Курс валют'!A:D,4,0) -> 105.1095 | D111: 735 | E111: Клей Starkbond 2014 бочка 225кг | F111: 900 | G111: 935 | H111: 370 | I111: =G111-F111 -> 35 | J111: =I111/F111*100 -> 3.8888889 | K111: 3.4 | L111: =H111/F111*100 -> 41.111111 | M111: =P111/F111 -> 226.00878 | N111: =(F111*K111-H111*3.04)/F111 -> 2.1502222 | O111: =N111*F111 -> 1935.2 | P111: =O111*C111 -> 203407.9
A112: 45576 | B112: 45579 | C112: =VLOOKUP(B:B,'Курс валют'!A:D,4,0) -> 105.1095 | D112: 738 | E112: клей Starkbond 521 A бочка 220кг | F112: 8800 | G112: 8814 | H112: 4019 | I112: =G112-F112 -> 14 | J112: =I112/F112*100 -> 0.15909091 | K112: 4.02 | L112: =H112/F112*100 -> 45.670455 | M112: =P112/F112 -> 276.60807 | N112: =(F112*K112-H112*3.04)/F112 -> 2.6316182 | O112: =N112*F112 -> 23158.24 | P112: =O112*C112 -> 2434151
A113: 45576 | B113: 45579 | C113: =VLOOKUP(B:B,'Курс валют'!A:D,4,0) -> 105.1095 | D113: 739 | E113: Клей Starkbond 521A ведро 22 кг | F113: 220 | G113: 220 | H113: 0 | I113: =G113-F113 -> 0 | J113: =I113/F113*100 -> 0 | K113: 3.96 | L113: =H113/F113*100 -> 0 | M113: =P113/F113 -> 416.23362 | N113: =(F113*K113-H113*3.04)/F113 -> 3.96 | O113: =N113*F113 -> 871.2 | P113: =O113*C113 -> 91571.396 | R113: перелив
A114: 45576 | B114: 45579 | C114: =VLOOKUP(B:B,'Курс валют'!A:D,4,0) -> 105.1095 | D114: 740 | E114: Клей Starkbond 2014 бочка 225кг | F114: 900 | G114: 933 | H114: 370 | I114: =G114-F114 -> 33 | J114: =I114/F114*100 -> 3.6666667 | K114: 3.4 | L114: =H114/F114*100 -> 41.111111 | M114: =P114/F114 -> 226.00878 | N114: =(F114*K114-H114*3.04)/F114 -> 2.1502222 | O114: =N114*F114 -> 1935.2 | P114: =O114*C114 -> 203407.9
A115: 45576 | B115: 45579 | C115: =VLOOKUP(B:B,'Курс валют'!A:D,4,0) -> 105.1095 | D115: 741 | E115: Клей Starkbond 522A бочка 220 кг | F115: 6600 | G115: 6617 | H115: 2745 | I115: =G115-F115 -> 17 | J115: =I115/F115*100 -> 0.25757576 | K115: 3.88 | L115: =H115/F115*100 -> 41.590909 | M115: =P115/F115 -> 274.92823 | N115: =(F115*K115-H115*3.04)/F115 -> 2.6156364 | O115: =N115*F115 -> 17263.2 | P115: =O115*C115 -> 1814526.3
A116: 45576 | B116: 45579 | C116: =VLOOKUP(B:B,'Курс валют'!A:D,4,0) -> 105.1095 | D116: 742 | E116: Клей Starkbond 2014 бочка 225кг | F116: 900 | G116: 932 | H116: 368 | I116: =G116-F116 -> 32 | J116: =I116/F116*100 -> 3.5555556 | K116: 3.4 | L116: =H116/F116*100 -> 40.888889 | M116: =P116/F116 -> 226.71886 | N116: =(F116*K116-H116*3.04)/F116 -> 2.1569778 | O116: =N116*F116 -> 1941.28 | P116: =O116*C116 -> 204046.97
A117: 45580 | B117: 45580 | C117: =VLOOKUP(B:B,'Курс валют'!A:D,4,0) -> 105.4854 | D117: 747 | E117: Sancos Pro | F117: 9648.57 | G117: 9648.57 | H117: 0 | I117: =G117-F117 -> 0 | J117: =I117/F117*100 -> 0 | K117: 2.47 | L117: =H117/F117*100 -> 0 | M117: =P117/F117 -> 260.54894 | N117: =(F117*K117-H117*3.04)/F117 -> 2.47 | O117: =N117*F117 -> 23831.968 | P117: =O117*C117 -> 2513924.7 | R117: ПЕРЕВОД АРТИКУЛОВ | S117: Sancos PRONATE 501B бочка 240 кг, Sancos PROPOL 101A бочка 180 кг, Sancos Pro Safety 165 канистра 14,81 кг, Sancos Pro Safety 145 канистра 21.96 кг
A118: 45579 | B118: 45580 | C118: =VLOOKUP(B:B,'Курс валют'!A:D,4,0) -> 105.4854 | D118: 743 | E118: Клей Starkbond 522A бочка 220 кг | F118: 6600 | G118: 6612 | H118: 2742 | I118: =G118-F118 -> 12 | J118: =I118/F118*100 -> 0.18181818 | K118: 3.88 | L118: =H118/F118*100 -> 41.545455 | M118: =P118/F118 -> 276.05721 | N118: =(F118*K118-H118*3.04)/F118 -> 2.6170182 | O118: =N118*F118 -> 17272.32 | P118: =O118*C118 -> 1821977.6
...

Sheet Курс валют
A1: 45536 | B1: 1 | C1: EUR | D1: 100.7622 | E1: RUB
A2: 45537 | B2: 1 | C2: EUR | D2: 100.7622 | E2: RUB
A3: 45538 | B3: 1 | C3: EUR | D3: 99.2613 | E3: RUB
A4: 45539 | B4: 1 | C4: EUR | D4: 97.8121 | E4: RUB
A5: 45540 | B5: 1 | C5: EUR | D5: 98.0725 | E5: RUB
A6: 45541 | B6: 1 | C6: EUR | D6: 99.1927 | E6: RUB
A7: 45542 | B7: 1 | C7: EUR | D7: 99.7156 | E7: RUB
A8: 45543 | B8: 1 | C8: EUR | D8: 99.7156 | E8: RUB
A9: 45544 | B9: 1 | C9: EUR | D9: 99.7156 | E9: RUB
A10: 45545 | B10: 1 | C10: EUR | D10: 99.9067 | E10: RUB
A11: 45546 | B11: 1 | C11: EUR | D11: 100.4995 | E11: RUB
A12: 45547 | B12: 1 | C12: EUR | D12: 100.7421 | E12: RUB
... A460: 45997 | B460: 1 | C460: EUR | D460: 88.7028 | E460: RUB
A461: 45998 | B461: 1 | C461: EUR | D461: 88.7028 | E461: RUB | F461: 93.5626
A462: 45999 | B462: 1 | C462: EUR | D462: 88.7028 | E462: RUB
A463: 46000 | B463: 1 | C463: EUR | D463: 89.7054 | E463: RUB
A464: 46001 | B464: 1 | C464: EUR | D464: 89.4267 | E464: RUB
A465: 46002 | B465: 1 | C465: EUR | D465: 91.3806 | E465: RUB
A466: 46003 | B466: 1 | C466: EUR | D466: 92.9384 | E466: RUB
A467: 46004 | B467: 1 | C467: EUR | D467: 93.5626 | E467: RUB
A468: 46005 | B468: 1 | C468: EUR | D468: 93.5626 | E468: RUB
A469: 46006 | B469: 1 | C469: EUR | D469: 93.5626 | E469: RUB
A470: 46007 | B470: 1 | C470: EUR | D470: 93.2274 | E470: RUB
A471: 46008 | B471: 1 | C471: EUR | D471: 93.8054 | E471: RUB
A472: 46009 | B472: 1 | C472: EUR | D472: 94.1478 | E472: RUB
A473: 46010 | B473: 1 | C473: EUR | D473: 94.2524 | E473: RUB
... A665: 46202 | B665: 1 | C665: EUR | D665: 87.4027 | E665: RUB
A666: 46203 | B666: 1 | C666: EUR
A667: 46204 | B667: 1 | C667: EUR
A668: 46205 | B668: 1 | C668: EUR
A669: 46206 | B669: 1 | C669: EUR
A670: 46207 | B670: 1 | C670: EUR
A671: 46208 | B671: 1 | C671: EUR
A672: 46209 | B672: 1 | C672: EUR
A673: 46210 | B673: 1 | C673: EUR
A674: 46211 | B674: 1 | C674: EUR
A675: 46212
A676: 46213

Sheet Формула Среднего
A1: Продукт | B1: Сентябрь 24 | C1: Октябрь 24 | D1: Ноябрь 24 | E1: Декабрь 24 | F1: Январь 25 | G1: Февраль 2025 | H1: Март 25 | I1: Апрель 25 | J1: Май 25 | K1: Июнь 25 | L1: Июль 25 | M1: Август 25 | N1: Сентябрь 25 | O1: Октябрь 25 | P1: Ноябрь 25 | Q1: Декабрь 25 | R1: Январь 26 | S1: Февраль 26 | T1: Март 26 | U1: Апрель 2026 | V1: Май 2026 | W1: Июнь 2026 | X1: Июль 2026
A2: Отвердитель Starkbond 521C 10.0 бочка 200кг | B2: =IFERROR(AVERAGEIFS('сентябрь 2024- июнь 2026'!$K:$K,'сентябрь 2024- июнь 2026'!$E:$E,$A:$A),"-") -> 1.9593443 | C2: =IFERROR(AVERAGEIFS(#REF!,#REF!,$A:$A),"-") -> - | D2: =IFERROR(AVERAGEIFS(#REF!,#REF!,$A:$A),"-") -> - | E2: =IFERROR(AVERAGEIFS(#REF!,#REF!,$A:$A),"-") -> - | F2: =IFERROR(AVERAGEIFS(#REF!,#REF!,$A:$A),"-") -> - | G2: =IFERROR(AVERAGEIFS(#REF!,#REF!,A:A),"-") -> - | H2: =IFERROR(AVERAGEIFS(#REF!,#REF!,$A:$A),"-") -> - | I2: =IFERROR(AVERAGEIFS(#REF!,#REF!,$A:$A),"-") -> - | J2: =IFERROR(AVERAGEIFS(#REF!,#REF!,$A:$A),"-") -> - | K2: =IFERROR(AVERAGEIFS(#REF!,#REF!,$A:$A),"-") -> - | L2: =IFERROR(AVERAGEIFS(#REF!,#REF!,$A:$A),"-") -> - | M2: =IFERROR(AVERAGEIFS(#REF!,#REF!,$A:$A),"-") -> - | N2: =IFERROR(AVERAGEIFS(#REF!,#REF!,$A:$A),"-") -> - | O2: =IFERROR(AVERAGEIFS(#REF!,#REF!,$A:$A),"-") -> - | ... W2: =IFERROR(AVERAGEIFS(#REF!,#REF!,$A:$A),"-") -> - | X2: =IFERROR(AVERAGEIFS('[1]Июль 2026'!$K:$K,'[1]Июль 2026'!$E:$E,$A:$A),"-") -> -
A3: клей Starkbond 521 A бочка 220кг | B3: =IFERROR(AVERAGEIFS('сентябрь 2024- июнь 2026'!$K:$K,'сентябрь 2024- июнь 2026'!$E:$E,$A:$A),"-") -> 3.585498 | C3: =IFERROR(AVERAGEIFS(#REF!,#REF!,$A:$A),"-") -> - | D3: =IFERROR(AVERAGEIFS(#REF!,#REF!,$A:$A),"-") -> - | E3: =IFERROR(AVERAGEIFS(#REF!,#REF!,$A:$A),"-") -> - | F3: =IFERROR(AVERAGEIFS(#REF!,#REF!,$A:$A),"-") -> - | G3: =IFERROR(AVERAGEIFS(#REF!,#REF!,A:A),"-") -> - | H3: =IFERROR(AVERAGEIFS(#REF!,#REF!,$A:$A),"-") -> - | I3: =IFERROR(AVERAGEIFS(#REF!,#REF!,$A:$A),"-") -> - | J3: =IFERROR(AVERAGEIFS(#REF!,#REF!,$A:$A),"-") -> - | K3: =IFERROR(AVERAGEIFS(#REF!,#REF!,$A:$A),"-") -> - | L3: =IFERROR(AVERAGEIFS(#REF!,#REF!,$A:$A),"-") -> - | M3: =IFERROR(AVERAGEIFS(#REF!,#REF!,$A:$A),"-") -> - | N3: =IFERROR(AVERAGEIFS(#REF!,#REF!,$A:$A),"-") -> - | O3: =IFERROR(AVERAGEIFS(#REF!,#REF!,$A:$A),"-") -> - | ... W3: =IFERROR(AVERAGEIFS(#REF!,#REF!,$A:$A),"-") -> - | X3: =IFERROR(AVERAGEIFS('[1]Июль 2026'!$K:$K,'[1]Июль 2026'!$E:$E,$A:$A),"-") -> -
A4: Отвердитель Starkbond 521C 11.0 бочка 200кг | B4: =IFERROR(AVERAGEIFS('сентябрь 2024- июнь 2026'!$K:$K,'сентябрь 2024- июнь 2026'!$E:$E,$A:$A),"-") -> 1.9477291 | C4: =IFERROR(AVERAGEIFS(#REF!,#REF!,$A:$A),"-") -> - | D4: =IFERROR(AVERAGEIFS(#REF!,#REF!,$A:$A),"-") -> - | E4: =IFERROR(AVERAGEIFS(#REF!,#REF!,$A:$A),"-") -> - | F4: =IFERROR(AVERAGEIFS(#REF!,#REF!,$A:$A),"-") -> - | G4: =IFERROR(AVERAGEIFS(#REF!,#REF!,A:A),"-") -> - | H4: =IFERROR(AVERAGEIFS(#REF!,#REF!,$A:$A),"-") -> - | I4: =IFERROR(AVERAGEIFS(#REF!,#REF!,$A:$A),"-") -> - | J4: =IFERROR(AVERAGEIFS(#REF!,#REF!,$A:$A),"-") -> - | K4: =IFERROR(AVERAGEIFS(#REF!,#REF!,$A:$A),"-") -> - | L4: =IFERROR(AVERAGEIFS(#REF!,#REF!,$A:$A),"-") -> - | M4: =IFERROR(AVERAGEIFS(#REF!,#REF!,$A:$A),"-") -> - | N4: =IFERROR(AVERAGEIFS(#REF!,#REF!,$A:$A),"-") -> - | O4: =IFERROR(AVERAGEIFS(#REF!,#REF!,$A:$A),"-") -> - | ... W4: =IFERROR(AVERAGEIFS(#REF!,#REF!,$A:$A),"-") -> - | X4: =IFERROR(AVERAGEIFS('[1]Июль 2026'!$K:$K,'[1]Июль 2026'!$E:$E,$A:$A),"-") -> -
A5: отвердитель Starkbond 746/1 С бочка 200кг | B5: =IFERROR(AVERAGEIFS('сентябрь 2024- июнь 2026'!$K:$K,'сентябрь 2024- июнь 2026'!$E:$E,$A:$A),"-") -> 2.7052941 | C5: =IFERROR(AVERAGEIFS(#REF!,#REF!,$A:$A),"-") -> - | D5: =IFERROR(AVERAGEIFS(#REF!,#REF!,$A:$A),"-") -> - | E5: =IFERROR(AVERAGEIFS(#REF!,#REF!,$A:$A),"-") -> - | F5: =IFERROR(AVERAGEIFS(#REF!,#REF!,$A:$A),"-") -> - | G5: =IFERROR(AVERAGEIFS(#REF!,#REF!,A:A),"-") -> - | H5: =IFERROR(AVERAGEIFS(#REF!,#REF!,$A:$A),"-") -> - | I5: =IFERROR(AVERAGEIFS(#REF!,#REF!,$A:$A),"-") -> - | J5: =IFERROR(AVERAGEIFS(#REF!,#REF!,$A:$A),"-") -> - | K5: =IFERROR(AVERAGEIFS(#REF!,#REF!,$A:$A),"-") -> - | L5: =IFERROR(AVERAGEIFS(#REF!,#REF!,$A:$A),"-") -> - | M5: =IFERROR(AVERAGEIFS(#REF!,#REF!,$A:$A),"-") -> - | N5: =IFERROR(AVERAGEIFS(#REF!,#REF!,$A:$A),"-") -> - | O5: =IFERROR(AVERAGEIFS(#REF!,#REF!,$A:$A),"-") -> - | ... W5: =IFERROR(AVERAGEIFS(#REF!,#REF!,$A:$A),"-") -> - | X5: =IFERROR(AVERAGEIFS('[1]Июль 2026'!$K:$K,'[1]Июль 2026'!$E:$E,$A:$A),"-") -> -
A6: Отвердитель Starkbond 525C 2.0 Бочка 200 кг | B6: =IFERROR(AVERAGEIFS('сентябрь 2024- июнь 2026'!$K:$K,'сентябрь 2024- июнь 2026'!$E:$E,$A:$A),"-") -> 3.27125 | C6: =IFERROR(AVERAGEIFS(#REF!,#REF!,$A:$A),"-") -> - | D6: =IFERROR(AVERAGEIFS(#REF!,#REF!,$A:$A),"-") -> - | E6: =IFERROR(AVERAGEIFS(#REF!,#REF!,$A:$A),"-") -> - | F6: =IFERROR(AVERAGEIFS(#REF!,#REF!,$A:$A),"-") -> - | G6: =IFERROR(AVERAGEIFS(#REF!,#REF!,A:A),"-") -> - | H6: =IFERROR(AVERAGEIFS(#REF!,#REF!,$A:$A),"-") -> - | I6: =IFERROR(AVERAGEIFS(#REF!,#REF!,$A:$A),"-") -> - | J6: =IFERROR(AVERAGEIFS(#REF!,#REF!,$A:$A),"-") -> - | K6: =IFERROR(AVERAGEIFS(#REF!,#REF!,$A:$A),"-") -> - | L6: =IFERROR(AVERAGEIFS(#REF!,#REF!,$A:$A),"-") -> - | M6: =IFERROR(AVERAGEIFS(#REF!,#REF!,$A:$A),"-") -> - | N6: =IFERROR(AVERAGEIFS(#REF!,#REF!,$A:$A),"-") -> - | O6: =IFERROR(AVERAGEIFS(#REF!,#REF!,$A:$A),"-") -> - | ... W6: =IFERROR(AVERAGEIFS(#REF!,#REF!,$A:$A),"-") -> - | X6: =IFERROR(AVERAGEIFS('[1]Июль 2026'!$K:$K,'[1]Июль 2026'!$E:$E,$A:$A),"-") -> -
A7: Отвердитель Starkbond 525C 3.0 Бочка 200 кг | B7: =IFERROR(AVERAGEIFS('сентябрь 2024- июнь 2026'!$K:$K,'сентябрь 2024- июнь 2026'!$E:$E,$A:$A),"-") -> 2.7321739 | C7: =IFERROR(AVERAGEIFS(#REF!,#REF!,$A:$A),"-") -> - | D7: =IFERROR(AVERAGEIFS(#REF!,#REF!,$A:$A),"-") -> - | E7: =IFERROR(AVERAGEIFS(#REF!,#REF!,$A:$A),"-") -> - | F7: =IFERROR(AVERAGEIFS(#REF!,#REF!,$A:$A),"-") -> - | G7: =IFERROR(AVERAGEIFS(#REF!,#REF!,A:A),"-") -> - | H7: =IFERROR(AVERAGEIFS(#REF!,#REF!,$A:$A),"-") -> - | I7: =IFERROR(AVERAGEIFS(#REF!,#REF!,$A:$A),"-") -> - | J7: =IFERROR(AVERAGEIFS(#REF!,#REF!,$A:$A),"-") -> - | K7: =IFERROR(AVERAGEIFS(#REF!,#REF!,$A:$A),"-") -> - | L7: =IFERROR(AVERAGEIFS(#REF!,#REF!,$A:$A),"-") -> - | M7: =IFERROR(AVERAGEIFS(#REF!,#REF!,$A:$A),"-") -> - | N7: =IFERROR(AVERAGEIFS(#REF!,#REF!,$A:$A),"-") -> - | O7: =IFERROR(AVERAGEIFS(#REF!,#REF!,$A:$A),"-") -> - | ... W7: =IFERROR(AVERAGEIFS(#REF!,#REF!,$A:$A),"-") -> - | X7: =IFERROR(AVERAGEIFS('[1]Июль 2026'!$K:$K,'[1]Июль 2026'!$E:$E,$A:$A),"-") -> -
A8: отвердитель Starkbond 525C v0 (ведро 22 кг) | B8: =IFERROR(AVERAGEIFS('сентябрь 2024- июнь 2026'!$K:$K,'сентябрь 2024- июнь 2026'!$E:$E,$A:$A),"-") -> 2.86 | C8: =IFERROR(AVERAGEIFS(#REF!,#REF!,$A:$A),"-") -> - | D8: =IFERROR(AVERAGEIFS(#REF!,#REF!,$A:$A),"-") -> - | E8: =IFERROR(AVERAGEIFS(#REF!,#REF!,$A:$A),"-") -> - | F8: =IFERROR(AVERAGEIFS(#REF!,#REF!,$A:$A),"-") -> - | G8: =IFERROR(AVERAGEIFS(#REF!,#REF!,A:A),"-") -> - | H8: =IFERROR(AVERAGEIFS(#REF!,#REF!,$A:$A),"-") -> - | I8: =IFERROR(AVERAGEIFS(#REF!,#REF!,$A:$A),"-") -> - | J8: =IFERROR(AVERAGEIFS(#REF!,#REF!,$A:$A),"-") -> - | K8: =IFERROR(AVERAGEIFS(#REF!,#REF!,$A:$A),"-") -> - | L8: =IFERROR(AVERAGEIFS(#REF!,#REF!,$A:$A),"-") -> - | M8: =IFERROR(AVERAGEIFS(#REF!,#REF!,$A:$A),"-") -> - | N8: =IFERROR(AVERAGEIFS(#REF!,#REF!,$A:$A),"-") -> - | O8: =IFERROR(AVERAGEIFS(#REF!,#REF!,$A:$A),"-") -> - | ... W8: =IFERROR(AVERAGEIFS(#REF!,#REF!,$A:$A),"-") -> - | X8: =IFERROR(AVERAGEIFS('[1]Июль 2026'!$K:$K,'[1]Июль 2026'!$E:$E,$A:$A),"-") -> -
A9: Клей Starkbond 745/41 А (бочка 200 кг) | B9: =IFERROR(AVERAGEIFS('сентябрь 2024- июнь 2026'!$K:$K,'сентябрь 2024- июнь 2026'!$E:$E,$A:$A),"-") -> 2.7238333 | C9: =IFERROR(AVERAGEIFS(#REF!,#REF!,$A:$A),"-") -> - | D9: =IFERROR(AVERAGEIFS(#REF!,#REF!,$A:$A),"-") -> - | E9: =IFERROR(AVERAGEIFS(#REF!,#REF!,$A:$A),"-") -> - | F9: =IFERROR(AVERAGEIFS(#REF!,#REF!,$A:$A),"-") -> - | G9: =IFERROR(AVERAGEIFS(#REF!,#REF!,A:A),"-") -> - | H9: =IFERROR(AVERAGEIFS(#REF!,#REF!,$A:$A),"-") -> - | I9: =IFERROR(AVERAGEIFS(#REF!,#REF!,$A:$A),"-") -> - | J9: =IFERROR(AVERAGEIFS(#REF!,#REF!,$A:$A),"-") -> - | K9: =IFERROR(AVERAGEIFS(#REF!,#REF!,$A:$A),"-") -> - | L9: =IFERROR(AVERAGEIFS(#REF!,#REF!,$A:$A),"-") -> - | M9: =IFERROR(AVERAGEIFS(#REF!,#REF!,$A:$A),"-") -> - | N9: =IFERROR(AVERAGEIFS(#REF!,#REF!,$A:$A),"-") -> - | O9: =IFERROR(AVERAGEIFS(#REF!,#REF!,$A:$A),"-") -> - | ... W9: =IFERROR(AVERAGEIFS(#REF!,#REF!,$A:$A),"-") -> - | X9: =IFERROR(AVERAGEIFS('[1]Июль 2026'!$K:$K,'[1]Июль 2026'!$E:$E,$A:$A),"-") -> -
A10: Клей Starkbond 525A бочка 200 кг | B10: =IFERROR(AVERAGEIFS('сентябрь 2024- июнь 2026'!$K:$K,'сентябрь 2024- июнь 2026'!$E:$E,$A:$A),"-") -> 3.1417241 | C10: =IFERROR(AVERAGEIFS(#REF!,#REF!,$A:$A),"-") -> - | D10: =IFERROR(AVERAGEIFS(#REF!,#REF!,$A:$A),"-") -> - | E10: =IFERROR(AVERAGEIFS(#REF!,#REF!,$A:$A),"-") -> - | F10: =IFERROR(AVERAGEIFS(#REF!,#REF!,$A:$A),"-") -> - | G10: =IFERROR(AVERAGEIFS(#REF!,#REF!,A:A),"-") -> - | H10: =IFERROR(AVERAGEIFS(#REF!,#REF!,$A:$A),"-") -> - | I10: =IFERROR(AVERAGEIFS(#REF!,#REF!,$A:$A),"-") -> - | J10: =IFERROR(AVERAGEIFS(#REF!,#REF!,$A:$A),"-") -> - | K10: =IFERROR(AVERAGEIFS(#REF!,#REF!,$A:$A),"-") -> - | L10: =IFERROR(AVERAGEIFS(#REF!,#REF!,$A:$A),"-") -> - | M10: =IFERROR(AVERAGEIFS(#REF!,#REF!,$A:$A),"-") -> - | N10: =IFERROR(AVERAGEIFS(#REF!,#REF!,$A:$A),"-") -> - | O10: =IFERROR(AVERAGEIFS(#REF!,#REF!,$A:$A),"-") -> - | ... W10: =IFERROR(AVERAGEIFS(#REF!,#REF!,$A:$A),"-") -> - | X10: =IFERROR(AVERAGEIFS('[1]Июль 2026'!$K:$K,'[1]Июль 2026'!$E:$E,$A:$A),"-") -> -
A11: Клей Starkbond 522A бочка 220 кг | B11: =IFERROR(AVERAGEIFS('сентябрь 2024- июнь 2026'!$K:$K,'сентябрь 2024- июнь 2026'!$E:$E,$A:$A),"-") -> 2.7780488 | C11: =IFERROR(AVERAGEIFS(#REF!,#REF!,$A:$A),"-") -> - | D11: =IFERROR(AVERAGEIFS(#REF!,#REF!,$A:$A),"-") -> - | E11: =IFERROR(AVERAGEIFS(#REF!,#REF!,$A:$A),"-") -> - | F11: =IFERROR(AVERAGEIFS(#REF!,#REF!,$A:$A),"-") -> - | G11: =IFERROR(AVERAGEIFS(#REF!,#REF!,A:A),"-") -> - | H11: =IFERROR(AVERAGEIFS(#REF!,#REF!,$A:$A),"-") -> - | I11: =IFERROR(AVERAGEIFS(#REF!,#REF!,$A:$A),"-") -> - | J11: =IFERROR(AVERAGEIFS(#REF!,#REF!,$A:$A),"-") -> - | K11: =IFERROR(AVERAGEIFS(#REF!,#REF!,$A:$A),"-") -> - | L11: =IFERROR(AVERAGEIFS(#REF!,#REF!,$A:$A),"-") -> - | M11: =IFERROR(AVERAGEIFS(#REF!,#REF!,$A:$A),"-") -> - | N11: =IFERROR(AVERAGEIFS(#REF!,#REF!,$A:$A),"-") -> - | O11: =IFERROR(AVERAGEIFS(#REF!,#REF!,$A:$A),"-") -> - | ... W11: =IFERROR(AVERAGEIFS(#REF!,#REF!,$A:$A),"-") -> - | X11: =IFERROR(AVERAGEIFS('[1]Июль 2026'!$K:$K,'[1]Июль 2026'!$E:$E,$A:$A),"-") -> -
A12: Отвердитель Starkbond 747С ведро 5 кг | B12: =IFERROR(AVERAGEIFS('сентябрь 2024- июнь 2026'!$K:$K,'сентябрь 2024- июнь 2026'!$E:$E,$A:$A),"-") -> 3.17 | C12: =IFERROR(AVERAGEIFS(#REF!,#REF!,$A:$A),"-") -> - | D12: =IFERROR(AVERAGEIFS(#REF!,#REF!,$A:$A),"-") -> - | E12: =IFERROR(AVERAGEIFS(#REF!,#REF!,$A:$A),"-") -> - | F12: =IFERROR(AVERAGEIFS(#REF!,#REF!,$A:$A),"-") -> - | G12: =IFERROR(AVERAGEIFS(#REF!,#REF!,A:A),"-") -> - | H12: =IFERROR(AVERAGEIFS(#REF!,#REF!,$A:$A),"-") -> - | I12: =IFERROR(AVERAGEIFS(#REF!,#REF!,$A:$A),"-") -> - | J12: =IFERROR(AVERAGEIFS(#REF!,#REF!,$A:$A),"-") -> - | K12: =IFERROR(AVERAGEIFS(#REF!,#REF!,$A:$A),"-") -> - | L12: =IFERROR(AVERAGEIFS(#REF!,#REF!,$A:$A),"-") -> - | M12: =IFERROR(AVERAGEIFS(#REF!,#REF!,$A:$A),"-") -> - | N12: =IFERROR(AVERAGEIFS(#REF!,#REF!,$A:$A),"-") -> - | O12: =IFERROR(AVERAGEIFS(#REF!,#REF!,$A:$A),"-") -> - | ... W12: =IFERROR(AVERAGEIFS(#REF!,#REF!,$A:$A),"-") -> - | X12: =IFERROR(AVERAGEIFS('[1]Июль 2026'!$K:$K,'[1]Июль 2026'!$E:$E,$A:$A),"-") -> -
A13: Клей Starkbond 2014 бочка 225кг | B13: =IFERROR(AVERAGEIFS('сентябрь 2024- июнь 2026'!$K:$K,'сентябрь 2024- июнь 2026'!$E:$E,$A:$A),"-") -> 2.7523944 | C13: =IFERROR(AVERAGEIFS(#REF!,#REF!,$A:$A),"-") -> - | D13: =IFERROR(AVERAGEIFS(#REF!,#REF!,$A:$A),"-") -> - | E13: =IFERROR(AVERAGEIFS(#REF!,#REF!,$A:$A),"-") -> - | F13: =IFERROR(AVERAGEIFS(#REF!,#REF!,$A:$A),"-") -> - | G13: =IFERROR(AVERAGEIFS(#REF!,#REF!,A:A),"-") -> - | H13: =IFERROR(AVERAGEIFS(#REF!,#REF!,$A:$A),"-") -> - | I13: =IFERROR(AVERAGEIFS(#REF!,#REF!,$A:$A),"-") -> - | J13: =IFERROR(AVERAGEIFS(#REF!,#REF!,$A:$A),"-") -> - | K13: =IFERROR(AVERAGEIFS(#REF!,#REF!,$A:$A),"-") -> - | L13: =IFERROR(AVERAGEIFS(#REF!,#REF!,$A:$A),"-") -> - | M13: =IFERROR(AVERAGEIFS(#REF!,#REF!,$A:$A),"-") -> - | N13: =IFERROR(AVERAGEIFS(#REF!,#REF!,$A:$A),"-") -> - | O13: =IFERROR(AVERAGEIFS(#REF!,#REF!,$A:$A),"-") -> - | ... W13: =IFERROR(AVERAGEIFS(#REF!,#REF!,$A:$A),"-") -> - | X13: =IFERROR(AVERAGEIFS('[1]Июль 2026'!$K:$K,'[1]Июль 2026'!$E:$E,$A:$A),"-") -> -
... A85: Sancos Pro Safety 145 канистра 11,59 кг | B85: =IFERROR(AVERAGEIFS('сентябрь 2024- июнь 2026'!$K:$K,'сентябрь 2024- июнь 2026'!$E:$E,$A:$A),"-") -> 1.73 | C85: =IFERROR(AVERAGEIFS(#REF!,#REF!,$A:$A),"-") -> - | D85: =IFERROR(AVERAGEIFS(#REF!,#REF!,$A:$A),"-") -> - | E85: =IFERROR(AVERAGEIFS(#REF!,#REF!,$A:$A),"-") -> - | F85: =IFERROR(AVERAGEIFS(#REF!,#REF!,$A:$A),"-") -> - | G85: =IFERROR(AVERAGEIFS(#REF!,#REF!,A:A),"-") -> - | H85: =IFERROR(AVERAGEIFS(#REF!,#REF!,$A:$A),"-") -> - | I85: =IFERROR(AVERAGEIFS(#REF!,#REF!,$A:$A),"-") -> - | J85: =IFERROR(AVERAGEIFS(#REF!,#REF!,$A:$A),"-") -> - | K85: =IFERROR(AVERAGEIFS(#REF!,#REF!,$A:$A),"-") -> - | L85: =IFERROR(AVERAGEIFS(#REF!,#REF!,$A:$A),"-") -> - | M85: =IFERROR(AVERAGEIFS(#REF!,#REF!,$A:$A),"-") -> - | N85: =IFERROR(AVERAGEIFS(#REF!,#REF!,$A:$A),"-") -> - | O85: =IFERROR(AVERAGEIFS(#REF!,#REF!,$A:$A),"-") -> - | ... W85: =IFERROR(AVERAGEIFS(#REF!,#REF!,$A:$A),"-") -> - | X85: =IFERROR(AVERAGEIFS('[1]Июль 2026'!$K:$K,'[1]Июль 2026'!$E:$E,$A:$A),"-") -> -
B86: =IFERROR(AVERAGEIFS('сентябрь 2024- июнь 2026'!$K:$K,'сентябрь 2024- июнь 2026'!$E:$E,$A:$A),"-") -> - | C86: =IFERROR(AVERAGEIFS(#REF!,#REF!,$A:$A),"-") -> - | D86: =IFERROR(AVERAGEIFS(#REF!,#REF!,$A:$A),"-") -> - | E86: =IFERROR(AVERAGEIFS(#REF!,#REF!,$A:$A),"-") -> - | F86: =IFERROR(AVERAGEIFS(#REF!,#REF!,$A:$A),"-") -> - | G86: =IFERROR(AVERAGEIFS(#REF!,#REF!,A:A),"-") -> - | H86: =IFERROR(AVERAGEIFS(#REF!,#REF!,$A:$A),"-") -> - | I86: =IFERROR(AVERAGEIFS(#REF!,#REF!,$A:$A),"-") -> - | J86: =IFERROR(AVERAGEIFS(#REF!,#REF!,$A:$A),"-") -> - | K86: =IFERROR(AVERAGEIFS(#REF!,#REF!,$A:$A),"-") -> - | L86: =IFERROR(AVERAGEIFS(#REF!,#REF!,$A:$A),"-") -> - | M86: =IFERROR(AVERAGEIFS(#REF!,#REF!,$A:$A),"-") -> - | N86: =IFERROR(AVERAGEIFS(#REF!,#REF!,$A:$A),"-") -> - | O86: =IFERROR(AVERAGEIFS(#REF!,#REF!,$A:$A),"-") -> - | ... W86: =IFERROR(AVERAGEIFS(#REF!,#REF!,$A:$A),"-") -> - | X86: =IFERROR(AVERAGEIFS('[1]Июль 2026'!$K:$K,'[1]Июль 2026'!$E:$E,$A:$A),"-") -> -
B87: =IFERROR(AVERAGEIFS('сентябрь 2024- июнь 2026'!$K:$K,'сентябрь 2024- июнь 2026'!$E:$E,$A:$A),"-") -> - | C87: =IFERROR(AVERAGEIFS(#REF!,#REF!,$A:$A),"-") -> - | D87: =IFERROR(AVERAGEIFS(#REF!,#REF!,$A:$A),"-") -> - | E87: =IFERROR(AVERAGEIFS(#REF!,#REF!,$A:$A),"-") -> - | F87: =IFERROR(AVERAGEIFS(#REF!,#REF!,$A:$A),"-") -> - | G87: =IFERROR(AVERAGEIFS(#REF!,#REF!,A:A),"-") -> - | H87: =IFERROR(AVERAGEIFS(#REF!,#REF!,$A:$A),"-") -> - | I87: =IFERROR(AVERAGEIFS(#REF!,#REF!,$A:$A),"-") -> - | J87: =IFERROR(AVERAGEIFS(#REF!,#REF!,$A:$A),"-") -> - | K87: =IFERROR(AVERAGEIFS(#REF!,#REF!,$A:$A),"-") -> - | L87: =IFERROR(AVERAGEIFS(#REF!,#REF!,$A:$A),"-") -> - | M87: =IFERROR(AVERAGEIFS(#REF!,#REF!,$A:$A),"-") -> - | N87: =IFERROR(AVERAGEIFS(#REF!,#REF!,$A:$A),"-") -> - | O87: =IFERROR(AVERAGEIFS(#REF!,#REF!,$A:$A),"-") -> - | ... W87: =IFERROR(AVERAGEIFS(#REF!,#REF!,$A:$A),"-") -> - | X87: =IFERROR(AVERAGEIFS('[1]Июль 2026'!$K:$K,'[1]Июль 2026'!$E:$E,$A:$A),"-") -> -
B88: =IFERROR(AVERAGEIFS('сентябрь 2024- июнь 2026'!$K:$K,'сентябрь 2024- июнь 2026'!$E:$E,$A:$A),"-") -> - | C88: =IFERROR(AVERAGEIFS(#REF!,#REF!,$A:$A),"-") -> - | D88: =IFERROR(AVERAGEIFS(#REF!,#REF!,$A:$A),"-") -> - | E88: =IFERROR(AVERAGEIFS(#REF!,#REF!,$A:$A),"-") -> - | F88: =IFERROR(AVERAGEIFS(#REF!,#REF!,$A:$A),"-") -> - | G88: =IFERROR(AVERAGEIFS(#REF!,#REF!,A:A),"-") -> - | H88: =IFERROR(AVERAGEIFS(#REF!,#REF!,$A:$A),"-") -> - | I88: =IFERROR(AVERAGEIFS(#REF!,#REF!,$A:$A),"-") -> - | J88: =IFERROR(AVERAGEIFS(#REF!,#REF!,$A:$A),"-") -> - | K88: =IFERROR(AVERAGEIFS(#REF!,#REF!,$A:$A),"-") -> - | L88: =IFERROR(AVERAGEIFS(#REF!,#REF!,$A:$A),"-") -> - | M88: =IFERROR(AVERAGEIFS(#REF!,#REF!,$A:$A),"-") -> - | N88: =IFERROR(AVERAGEIFS(#REF!,#REF!,$A:$A),"-") -> - | O88: =IFERROR(AVERAGEIFS(#REF!,#REF!,$A:$A),"-") -> - | ... W88: =IFERROR(AVERAGEIFS(#REF!,#REF!,$A:$A),"-") -> - | X88: =IFERROR(AVERAGEIFS('[1]Июль 2026'!$K:$K,'[1]Июль 2026'!$E:$E,$A:$A),"-") -> -
B89: =IFERROR(AVERAGEIFS('сентябрь 2024- июнь 2026'!$K:$K,'сентябрь 2024- июнь 2026'!$E:$E,$A:$A),"-") -> - | C89: =IFERROR(AVERAGEIFS(#REF!,#REF!,$A:$A),"-") -> - | D89: =IFERROR(AVERAGEIFS(#REF!,#REF!,$A:$A),"-") -> - | E89: =IFERROR(AVERAGEIFS(#REF!,#REF!,$A:$A),"-") -> - | F89: =IFERROR(AVERAGEIFS(#REF!,#REF!,$A:$A),"-") -> - | G89: =IFERROR(AVERAGEIFS(#REF!,#REF!,A:A),"-") -> - | H89: =IFERROR(AVERAGEIFS(#REF!,#REF!,$A:$A),"-") -> - | I89: =IFERROR(AVERAGEIFS(#REF!,#REF!,$A:$A),"-") -> - | J89: =IFERROR(AVERAGEIFS(#REF!,#REF!,$A:$A),"-") -> - | K89: =IFERROR(AVERAGEIFS(#REF!,#REF!,$A:$A),"-") -> - | L89: =IFERROR(AVERAGEIFS(#REF!,#REF!,$A:$A),"-") -> - | M89: =IFERROR(AVERAGEIFS(#REF!,#REF!,$A:$A),"-") -> - | N89: =IFERROR(AVERAGEIFS(#REF!,#REF!,$A:$A),"-") -> - | O89: =IFERROR(AVERAGEIFS(#REF!,#REF!,$A:$A),"-") -> - | ... W89: =IFERROR(AVERAGEIFS(#REF!,#REF!,$A:$A),"-") -> - | X89: =IFERROR(AVERAGEIFS('[1]Июль 2026'!$K:$K,'[1]Июль 2026'!$E:$E,$A:$A),"-") -> -
B90: =IFERROR(AVERAGEIFS('сентябрь 2024- июнь 2026'!$K:$K,'сентябрь 2024- июнь 2026'!$E:$E,$A:$A),"-") -> - | C90: =IFERROR(AVERAGEIFS(#REF!,#REF!,$A:$A),"-") -> - | D90: =IFERROR(AVERAGEIFS(#REF!,#REF!,$A:$A),"-") -> - | E90: =IFERROR(AVERAGEIFS(#REF!,#REF!,$A:$A),"-") -> - | F90: =IFERROR(AVERAGEIFS(#REF!,#REF!,$A:$A),"-") -> - | G90: =IFERROR(AVERAGEIFS(#REF!,#REF!,A:A),"-") -> - | H90: =IFERROR(AVERAGEIFS(#REF!,#REF!,$A:$A),"-") -> - | I90: =IFERROR(AVERAGEIFS(#REF!,#REF!,$A:$A),"-") -> - | J90: =IFERROR(AVERAGEIFS(#REF!,#REF!,$A:$A),"-") -> - | K90: =IFERROR(AVERAGEIFS(#REF!,#REF!,$A:$A),"-") -> - | L90: =IFERROR(AVERAGEIFS(#REF!,#REF!,$A:$A),"-") -> - | M90: =IFERROR(AVERAGEIFS(#REF!,#REF!,$A:$A),"-") -> - | N90: =IFERROR(AVERAGEIFS(#REF!,#REF!,$A:$A),"-") -> - | O90: =IFERROR(AVERAGEIFS(#REF!,#REF!,$A:$A),"-") -> - | ... W90: =IFERROR(AVERAGEIFS(#REF!,#REF!,$A:$A),"-") -> - | X90: =IFERROR(AVERAGEIFS('[1]Июль 2026'!$K:$K,'[1]Июль 2026'!$E:$E,$A:$A),"-") -> -
B91: =IFERROR(AVERAGEIFS('сентябрь 2024- июнь 2026'!$K:$K,'сентябрь 2024- июнь 2026'!$E:$E,$A:$A),"-") -> - | C91: =IFERROR(AVERAGEIFS(#REF!,#REF!,$A:$A),"-") -> - | D91: =IFERROR(AVERAGEIFS(#REF!,#REF!,$A:$A),"-") -> - | E91: =IFERROR(AVERAGEIFS(#REF!,#REF!,$A:$A),"-") -> - | F91: =IFERROR(AVERAGEIFS(#REF!,#REF!,$A:$A),"-") -> - | G91: =IFERROR(AVERAGEIFS(#REF!,#REF!,A:A),"-") -> - | H91: =IFERROR(AVERAGEIFS(#REF!,#REF!,$A:$A),"-") -> - | I91: =IFERROR(AVERAGEIFS(#REF!,#REF!,$A:$A),"-") -> - | J91: =IFERROR(AVERAGEIFS(#REF!,#REF!,$A:$A),"-") -> - | K91: =IFERROR(AVERAGEIFS(#REF!,#REF!,$A:$A),"-") -> - | L91: =IFERROR(AVERAGEIFS(#REF!,#REF!,$A:$A),"-") -> - | M91: =IFERROR(AVERAGEIFS(#REF!,#REF!,$A:$A),"-") -> - | N91: =IFERROR(AVERAGEIFS(#REF!,#REF!,$A:$A),"-") -> - | O91: =IFERROR(AVERAGEIFS(#REF!,#REF!,$A:$A),"-") -> - | ... W91: =IFERROR(AVERAGEIFS(#REF!,#REF!,$A:$A),"-") -> - | X91: =IFERROR(AVERAGEIFS('[1]Июль 2026'!$K:$K,'[1]Июль 2026'!$E:$E,$A:$A),"-") -> -
B92: =IFERROR(AVERAGEIFS('сентябрь 2024- июнь 2026'!$K:$K,'сентябрь 2024- июнь 2026'!$E:$E,$A:$A),"-") -> - | C92: =IFERROR(AVERAGEIFS(#REF!,#REF!,$A:$A),"-") -> - | D92: =IFERROR(AVERAGEIFS(#REF!,#REF!,$A:$A),"-") -> - | E92: =IFERROR(AVERAGEIFS(#REF!,#REF!,$A:$A),"-") -> - | F92: =IFERROR(AVERAGEIFS(#REF!,#REF!,$A:$A),"-") -> - | G92: =IFERROR(AVERAGEIFS(#REF!,#REF!,A:A),"-") -> - | H92: =IFERROR(AVERAGEIFS(#REF!,#REF!,$A:$A),"-") -> - | I92: =IFERROR(AVERAGEIFS(#REF!,#REF!,$A:$A),"-") -> - | J92: =IFERROR(AVERAGEIFS(#REF!,#REF!,$A:$A),"-") -> - | K92: =IFERROR(AVERAGEIFS(#REF!,#REF!,$A:$A),"-") -> - | L92: =IFERROR(AVERAGEIFS(#REF!,#REF!,$A:$A),"-") -> - | M92: =IFERROR(AVERAGEIFS(#REF!,#REF!,$A:$A),"-") -> - | N92: =IFERROR(AVERAGEIFS(#REF!,#REF!,$A:$A),"-") -> - | O92: =IFERROR(AVERAGEIFS(#REF!,#REF!,$A:$A),"-") -> - | ... W92: =IFERROR(AVERAGEIFS(#REF!,#REF!,$A:$A),"-") -> - | X92: =IFERROR(AVERAGEIFS('[1]Июль 2026'!$K:$K,'[1]Июль 2026'!$E:$E,$A:$A),"-") -> -
B93: =IFERROR(AVERAGEIFS('сентябрь 2024- июнь 2026'!$K:$K,'сентябрь 2024- июнь 2026'!$E:$E,$A:$A),"-") -> - | C93: =IFERROR(AVERAGEIFS(#REF!,#REF!,$A:$A),"-") -> - | D93: =IFERROR(AVERAGEIFS(#REF!,#REF!,$A:$A),"-") -> - | E93: =IFERROR(AVERAGEIFS(#REF!,#REF!,$A:$A),"-") -> - | F93: =IFERROR(AVERAGEIFS(#REF!,#REF!,$A:$A),"-") -> - | G93: =IFERROR(AVERAGEIFS(#REF!,#REF!,A:A),"-") -> - | H93: =IFERROR(AVERAGEIFS(#REF!,#REF!,$A:$A),"-") -> - | I93: =IFERROR(AVERAGEIFS(#REF!,#REF!,$A:$A),"-") -> - | J93: =IFERROR(AVERAGEIFS(#REF!,#REF!,$A:$A),"-") -> - | K93: =IFERROR(AVERAGEIFS(#REF!,#REF!,$A:$A),"-") -> - | L93: =IFERROR(AVERAGEIFS(#REF!,#REF!,$A:$A),"-") -> - | M93: =IFERROR(AVERAGEIFS(#REF!,#REF!,$A:$A),"-") -> - | N93: =IFERROR(AVERAGEIFS(#REF!,#REF!,$A:$A),"-") -> - | O93: =IFERROR(AVERAGEIFS(#REF!,#REF!,$A:$A),"-") -> - | ... W93: =IFERROR(AVERAGEIFS(#REF!,#REF!,$A:$A),"-") -> - | X93: =IFERROR(AVERAGEIFS('[1]Июль 2026'!$K:$K,'[1]Июль 2026'!$E:$E,$A:$A),"-") -> -
B94: =IFERROR(AVERAGEIFS('сентябрь 2024- июнь 2026'!$K:$K,'сентябрь 2024- июнь 2026'!$E:$E,$A:$A),"-") -> - | C94: =IFERROR(AVERAGEIFS(#REF!,#REF!,$A:$A),"-") -> - | D94: =IFERROR(AVERAGEIFS(#REF!,#REF!,$A:$A),"-") -> - | E94: =IFERROR(AVERAGEIFS(#REF!,#REF!,$A:$A),"-") -> - | F94: =IFERROR(AVERAGEIFS(#REF!,#REF!,$A:$A),"-") -> - | G94: =IFERROR(AVERAGEIFS(#REF!,#REF!,A:A),"-") -> - | H94: =IFERROR(AVERAGEIFS(#REF!,#REF!,$A:$A),"-") -> - | I94: =IFERROR(AVERAGEIFS(#REF!,#REF!,$A:$A),"-") -> - | J94: =IFERROR(AVERAGEIFS(#REF!,#REF!,$A:$A),"-") -> - | K94: =IFERROR(AVERAGEIFS(#REF!,#REF!,$A:$A),"-") -> - | L94: =IFERROR(AVERAGEIFS(#REF!,#REF!,$A:$A),"-") -> - | M94: =IFERROR(AVERAGEIFS(#REF!,#REF!,$A:$A),"-") -> - | N94: =IFERROR(AVERAGEIFS(#REF!,#REF!,$A:$A),"-") -> - | O94: =IFERROR(AVERAGEIFS(#REF!,#REF!,$A:$A),"-") -> - | ... W94: =IFERROR(AVERAGEIFS(#REF!,#REF!,$A:$A),"-") -> - | X94: =IFERROR(AVERAGEIFS('[1]Июль 2026'!$K:$K,'[1]Июль 2026'!$E:$E,$A:$A),"-") -> -
B95: =IFERROR(AVERAGEIFS('сентябрь 2024- июнь 2026'!$K:$K,'сентябрь 2024- июнь 2026'!$E:$E,$A:$A),"-") -> - | C95: =IFERROR(AVERAGEIFS(#REF!,#REF!,$A:$A),"-") -> - | D95: =IFERROR(AVERAGEIFS(#REF!,#REF!,$A:$A),"-") -> - | E95: =IFERROR(AVERAGEIFS(#REF!,#REF!,$A:$A),"-") -> - | F95: =IFERROR(AVERAGEIFS(#REF!,#REF!,$A:$A),"-") -> - | G95: =IFERROR(AVERAGEIFS(#REF!,#REF!,A:A),"-") -> - | H95: =IFERROR(AVERAGEIFS(#REF!,#REF!,$A:$A),"-") -> - | I95: =IFERROR(AVERAGEIFS(#REF!,#REF!,$A:$A),"-") -> - | J95: =IFERROR(AVERAGEIFS(#REF!,#REF!,$A:$A),"-") -> - | K95: =IFERROR(AVERAGEIFS(#REF!,#REF!,$A:$A),"-") -> - | L95: =IFERROR(AVERAGEIFS(#REF!,#REF!,$A:$A),"-") -> - | M95: =IFERROR(AVERAGEIFS(#REF!,#REF!,$A:$A),"-") -> - | N95: =IFERROR(AVERAGEIFS(#REF!,#REF!,$A:$A),"-") -> - | O95: =IFERROR(AVERAGEIFS(#REF!,#REF!,$A:$A),"-") -> - | ... W95: =IFERROR(AVERAGEIFS(#REF!,#REF!,$A:$A),"-") -> - | X95: =IFERROR(AVERAGEIFS('[1]Июль 2026'!$K:$K,'[1]Июль 2026'!$E:$E,$A:$A),"-") -> -
B96: =IFERROR(AVERAGEIFS('сентябрь 2024- июнь 2026'!$K:$K,'сентябрь 2024- июнь 2026'!$E:$E,$A:$A),"-") -> - | C96: =IFERROR(AVERAGEIFS(#REF!,#REF!,$A:$A),"-") -> - | D96: =IFERROR(AVERAGEIFS(#REF!,#REF!,$A:$A),"-") -> - | E96: =IFERROR(AVERAGEIFS(#REF!,#REF!,$A:$A),"-") -> - | F96: =IFERROR(AVERAGEIFS(#REF!,#REF!,$A:$A),"-") -> - | G96: =IFERROR(AVERAGEIFS(#REF!,#REF!,A:A),"-") -> - | H96: =IFERROR(AVERAGEIFS(#REF!,#REF!,$A:$A),"-") -> - | I96: =IFERROR(AVERAGEIFS(#REF!,#REF!,$A:$A),"-") -> - | J96: =IFERROR(AVERAGEIFS(#REF!,#REF!,$A:$A),"-") -> - | K96: =IFERROR(AVERAGEIFS(#REF!,#REF!,$A:$A),"-") -> - | L96: =IFERROR(AVERAGEIFS(#REF!,#REF!,$A:$A),"-") -> - | M96: =IFERROR(AVERAGEIFS(#REF!,#REF!,$A:$A),"-") -> - | N96: =IFERROR(AVERAGEIFS(#REF!,#REF!,$A:$A),"-") -> - | O96: =IFERROR(AVERAGEIFS(#REF!,#REF!,$A:$A),"-") -> - | ... W96: =IFERROR(AVERAGEIFS(#REF!,#REF!,$A:$A),"-") -> - | X96: =IFERROR(AVERAGEIFS('[1]Июль 2026'!$K:$K,'[1]Июль 2026'!$E:$E,$A:$A),"-") -> -
B97: =IFERROR(AVERAGEIFS('сентябрь 2024- июнь 2026'!$K:$K,'сентябрь 2024- июнь 2026'!$E:$E,$A:$A),"-") -> - | C97: =IFERROR(AVERAGEIFS(#REF!,#REF!,$A:$A),"-") -> - | D97: =IFERROR(AVERAGEIFS(#REF!,#REF!,$A:$A),"-") -> - | E97: =IFERROR(AVERAGEIFS(#REF!,#REF!,$A:$A),"-") -> - | F97: =IFERROR(AVERAGEIFS(#REF!,#REF!,$A:$A),"-") -> - | G97: =IFERROR(AVERAGEIFS(#REF!,#REF!,A:A),"-") -> - | H97: =IFERROR(AVERAGEIFS(#REF!,#REF!,$A:$A),"-") -> - | I97: =IFERROR(AVERAGEIFS(#REF!,#REF!,$A:$A),"-") -> - | J97: =IFERROR(AVERAGEIFS(#REF!,#REF!,$A:$A),"-") -> - | K97: =IFERROR(AVERAGEIFS(#REF!,#REF!,$A:$A),"-") -> - | L97: =IFERROR(AVERAGEIFS(#REF!,#REF!,$A:$A),"-") -> - | M97: =IFERROR(AVERAGEIFS(#REF!,#REF!,$A:$A),"-") -> - | N97: =IFERROR(AVERAGEIFS(#REF!,#REF!,$A:$A),"-") -> - | O97: =IFERROR(AVERAGEIFS(#REF!,#REF!,$A:$A),"-") -> - | ... W97: =IFERROR(AVERAGEIFS(#REF!,#REF!,$A:$A),"-") -> - | X97: =IFERROR(AVERAGEIFS('[1]Июль 2026'!$K:$K,'[1]Июль 2026'!$E:$E,$A:$A),"-") -> -
... B109: =IFERROR(AVERAGEIFS('сентябрь 2024- июнь 2026'!$K:$K,'сентябрь 2024- июнь 2026'!$E:$E,$A:$A),"-") -> - | C109: =IFERROR(AVERAGEIFS(#REF!,#REF!,$A:$A),"-") -> - | D109: =IFERROR(AVERAGEIFS(#REF!,#REF!,$A:$A),"-") -> - | E109: =IFERROR(AVERAGEIFS(#REF!,#REF!,$A:$A),"-") -> - | F109: =IFERROR(AVERAGEIFS(#REF!,#REF!,$A:$A),"-") -> - | G109: =IFERROR(AVERAGEIFS(#REF!,#REF!,A:A),"-") -> - | H109: =IFERROR(AVERAGEIFS(#REF!,#REF!,$A:$A),"-") -> - | I109: =IFERROR(AVERAGEIFS(#REF!,#REF!,$A:$A),"-") -> - | J109: =IFERROR(AVERAGEIFS(#REF!,#REF!,$A:$A),"-") -> - | K109: =IFERROR(AVERAGEIFS(#REF!,#REF!,$A:$A),"-") -> - | L109: =IFERROR(AVERAGEIFS(#REF!,#REF!,$A:$A),"-") -> - | M109: =IFERROR(AVERAGEIFS(#REF!,#REF!,$A:$A),"-") -> - | N109: =IFERROR(AVERAGEIFS(#REF!,#REF!,$A:$A),"-") -> - | O109: =IFERROR(AVERAGEIFS(#REF!,#REF!,$A:$A),"-") -> - | ... W109: =IFERROR(AVERAGEIFS(#REF!,#REF!,$A:$A),"-") -> - | X109: =IFERROR(AVERAGEIFS('[1]Июль 2026'!$K:$K,'[1]Июль 2026'!$E:$E,$A:$A),"-") -> -
B110: =IFERROR(AVERAGEIFS('сентябрь 2024- июнь 2026'!$K:$K,'сентябрь 2024- июнь 2026'!$E:$E,$A:$A),"-") -> - | C110: =IFERROR(AVERAGEIFS(#REF!,#REF!,$A:$A),"-") -> - | D110: =IFERROR(AVERAGEIFS(#REF!,#REF!,$A:$A),"-") -> - | E110: =IFERROR(AVERAGEIFS(#REF!,#REF!,$A:$A),"-") -> - | F110: =IFERROR(AVERAGEIFS(#REF!,#REF!,$A:$A),"-") -> - | G110: =IFERROR(AVERAGEIFS(#REF!,#REF!,A:A),"-") -> - | H110: =IFERROR(AVERAGEIFS(#REF!,#REF!,$A:$A),"-") -> - | I110: =IFERROR(AVERAGEIFS(#REF!,#REF!,$A:$A),"-") -> - | J110: =IFERROR(AVERAGEIFS(#REF!,#REF!,$A:$A),"-") -> - | K110: =IFERROR(AVERAGEIFS(#REF!,#REF!,$A:$A),"-") -> - | L110: =IFERROR(AVERAGEIFS(#REF!,#REF!,$A:$A),"-") -> - | M110: =IFERROR(AVERAGEIFS(#REF!,#REF!,$A:$A),"-") -> - | N110: =IFERROR(AVERAGEIFS(#REF!,#REF!,$A:$A),"-") -> - | O110: =IFERROR(AVERAGEIFS(#REF!,#REF!,$A:$A),"-") -> - | ... X110: =IFERROR(AVERAGEIFS(#REF!,#REF!,$A:$A),"-") -> -
B111: =IFERROR(AVERAGEIFS('сентябрь 2024- июнь 2026'!$K:$K,'сентябрь 2024- июнь 2026'!$E:$E,$A:$A),"-") -> - | C111: =IFERROR(AVERAGEIFS(#REF!,#REF!,$A:$A),"-") -> - | D111: =IFERROR(AVERAGEIFS(#REF!,#REF!,$A:$A),"-") -> - | E111: =IFERROR(AVERAGEIFS(#REF!,#REF!,$A:$A),"-") -> - | F111: =IFERROR(AVERAGEIFS(#REF!,#REF!,$A:$A),"-") -> - | G111: =IFERROR(AVERAGEIFS(#REF!,#REF!,A:A),"-") -> - | H111: =IFERROR(AVERAGEIFS(#REF!,#REF!,$A:$A),"-") -> - | I111: =IFERROR(AVERAGEIFS(#REF!,#REF!,$A:$A),"-") -> - | J111: =IFERROR(AVERAGEIFS(#REF!,#REF!,$A:$A),"-") -> - | K111: =IFERROR(AVERAGEIFS(#REF!,#REF!,$A:$A),"-") -> - | L111: =IFERROR(AVERAGEIFS(#REF!,#REF!,$A:$A),"-") -> - | M111: =IFERROR(AVERAGEIFS(#REF!,#REF!,$A:$A),"-") -> - | N111: =IFERROR(AVERAGEIFS(#REF!,#REF!,$A:$A),"-") -> - | O111: =IFERROR(AVERAGEIFS(#REF!,#REF!,$A:$A),"-") -> - | ... X111: =IFERROR(AVERAGEIFS(#REF!,#REF!,$A:$A),"-") -> -
B112: =IFERROR(AVERAGEIFS('сентябрь 2024- июнь 2026'!$K:$K,'сентябрь 2024- июнь 2026'!$E:$E,$A:$A),"-") -> - | C112: =IFERROR(AVERAGEIFS(#REF!,#REF!,$A:$A),"-") -> - | D112: =IFERROR(AVERAGEIFS(#REF!,#REF!,$A:$A),"-") -> - | E112: =IFERROR(AVERAGEIFS(#REF!,#REF!,$A:$A),"-") -> - | F112: =IFERROR(AVERAGEIFS(#REF!,#REF!,$A:$A),"-") -> - | G112: =IFERROR(AVERAGEIFS(#REF!,#REF!,A:A),"-") -> - | H112: =IFERROR(AVERAGEIFS(#REF!,#REF!,$A:$A),"-") -> - | I112: =IFERROR(AVERAGEIFS(#REF!,#REF!,$A:$A),"-") -> - | J112: =IFERROR(AVERAGEIFS(#REF!,#REF!,$A:$A),"-") -> - | K112: =IFERROR(AVERAGEIFS(#REF!,#REF!,$A:$A),"-") -> - | L112: =IFERROR(AVERAGEIFS(#REF!,#REF!,$A:$A),"-") -> - | M112: =IFERROR(AVERAGEIFS(#REF!,#REF!,$A:$A),"-") -> - | N112: =IFERROR(AVERAGEIFS(#REF!,#REF!,$A:$A),"-") -> - | O112: =IFERROR(AVERAGEIFS(#REF!,#REF!,$A:$A),"-") -> - | ... X112: =IFERROR(AVERAGEIFS(#REF!,#REF!,$A:$A),"-") -> -
B113: =IFERROR(AVERAGEIFS('сентябрь 2024- июнь 2026'!$K:$K,'сентябрь 2024- июнь 2026'!$E:$E,$A:$A),"-") -> - | C113: =IFERROR(AVERAGEIFS(#REF!,#REF!,$A:$A),"-") -> - | D113: =IFERROR(AVERAGEIFS(#REF!,#REF!,$A:$A),"-") -> - | E113: =IFERROR(AVERAGEIFS(#REF!,#REF!,$A:$A),"-") -> - | F113: =IFERROR(AVERAGEIFS(#REF!,#REF!,$A:$A),"-") -> - | G113: =IFERROR(AVERAGEIFS(#REF!,#REF!,A:A),"-") -> - | H113: =IFERROR(AVERAGEIFS(#REF!,#REF!,$A:$A),"-") -> - | I113: =IFERROR(AVERAGEIFS(#REF!,#REF!,$A:$A),"-") -> - | J113: =IFERROR(AVERAGEIFS(#REF!,#REF!,$A:$A),"-") -> - | K113: =IFERROR(AVERAGEIFS(#REF!,#REF!,$A:$A),"-") -> - | L113: =IFERROR(AVERAGEIFS(#REF!,#REF!,$A:$A),"-") -> - | M113: =IFERROR(AVERAGEIFS(#REF!,#REF!,$A:$A),"-") -> - | N113: =IFERROR(AVERAGEIFS(#REF!,#REF!,$A:$A),"-") -> - | O113: =IFERROR(AVERAGEIFS(#REF!,#REF!,$A:$A),"-") -> - | ... X113: =IFERROR(AVERAGEIFS(#REF!,#REF!,$A:$A),"-") -> -
B114: =IFERROR(AVERAGEIFS('сентябрь 2024- июнь 2026'!$K:$K,'сентябрь 2024- июнь 2026'!$E:$E,$A:$A),"-") -> - | C114: =IFERROR(AVERAGEIFS(#REF!,#REF!,$A:$A),"-") -> - | D114: =IFERROR(AVERAGEIFS(#REF!,#REF!,$A:$A),"-") -> - | E114: =IFERROR(AVERAGEIFS(#REF!,#REF!,$A:$A),"-") -> - | F114: =IFERROR(AVERAGEIFS(#REF!,#REF!,$A:$A),"-") -> - | G114: =IFERROR(AVERAGEIFS(#REF!,#REF!,A:A),"-") -> - | H114: =IFERROR(AVERAGEIFS(#REF!,#REF!,$A:$A),"-") -> - | I114: =IFERROR(AVERAGEIFS(#REF!,#REF!,$A:$A),"-") -> - | J114: =IFERROR(AVERAGEIFS(#REF!,#REF!,$A:$A),"-") -> - | K114: =IFERROR(AVERAGEIFS(#REF!,#REF!,$A:$A),"-") -> - | L114: =IFERROR(AVERAGEIFS(#REF!,#REF!,$A:$A),"-") -> - | M114: =IFERROR(AVERAGEIFS(#REF!,#REF!,$A:$A),"-") -> - | N114: =IFERROR(AVERAGEIFS(#REF!,#REF!,$A:$A),"-") -> - | O114: =IFERROR(AVERAGEIFS(#REF!,#REF!,$A:$A),"-") -> - | ... X114: =IFERROR(AVERAGEIFS(#REF!,#REF!,$A:$A),"-") -> -
B115: =IFERROR(AVERAGEIFS('сентябрь 2024- июнь 2026'!$K:$K,'сентябрь 2024- июнь 2026'!$E:$E,$A:$A),"-") -> - | C115: =IFERROR(AVERAGEIFS(#REF!,#REF!,$A:$A),"-") -> - | D115: =IFERROR(AVERAGEIFS(#REF!,#REF!,$A:$A),"-") -> - | E115: =IFERROR(AVERAGEIFS(#REF!,#REF!,$A:$A),"-") -> - | F115: =IFERROR(AVERAGEIFS(#REF!,#REF!,$A:$A),"-") -> - | G115: =IFERROR(AVERAGEIFS(#REF!,#REF!,A:A),"-") -> - | H115: =IFERROR(AVERAGEIFS(#REF!,#REF!,$A:$A),"-") -> - | I115: =IFERROR(AVERAGEIFS(#REF!,#REF!,$A:$A),"-") -> - | J115: =IFERROR(AVERAGEIFS(#REF!,#REF!,$A:$A),"-") -> - | K115: =IFERROR(AVERAGEIFS(#REF!,#REF!,$A:$A),"-") -> - | L115: =IFERROR(AVERAGEIFS(#REF!,#REF!,$A:$A),"-") -> - | M115: =IFERROR(AVERAGEIFS(#REF!,#REF!,$A:$A),"-") -> - | N115: =IFERROR(AVERAGEIFS(#REF!,#REF!,$A:$A),"-") -> - | O115: =IFERROR(AVERAGEIFS(#REF!,#REF!,$A:$A),"-") -> - | ... X115: =IFERROR(AVERAGEIFS(#REF!,#REF!,$A:$A),"-") -> -
B116: =IFERROR(AVERAGEIFS('сентябрь 2024- июнь 2026'!$K:$K,'сентябрь 2024- июнь 2026'!$E:$E,$A:$A),"-") -> - | C116: =IFERROR(AVERAGEIFS(#REF!,#REF!,$A:$A),"-") -> - | D116: =IFERROR(AVERAGEIFS(#REF!,#REF!,$A:$A),"-") -> - | E116: =IFERROR(AVERAGEIFS(#REF!,#REF!,$A:$A),"-") -> - | F116: =IFERROR(AVERAGEIFS(#REF!,#REF!,$A:$A),"-") -> - | G116: =IFERROR(AVERAGEIFS(#REF!,#REF!,A:A),"-") -> - | H116: =IFERROR(AVERAGEIFS(#REF!,#REF!,$A:$A),"-") -> - | I116: =IFERROR(AVERAGEIFS(#REF!,#REF!,$A:$A),"-") -> - | J116: =IFERROR(AVERAGEIFS(#REF!,#REF!,$A:$A),"-") -> - | K116: =IFERROR(AVERAGEIFS(#REF!,#REF!,$A:$A),"-") -> - | L116: =IFERROR(AVERAGEIFS(#REF!,#REF!,$A:$A),"-") -> - | M116: =IFERROR(AVERAGEIFS(#REF!,#REF!,$A:$A),"-") -> - | N116: =IFERROR(AVERAGEIFS(#REF!,#REF!,$A:$A),"-") -> - | O116: =IFERROR(AVERAGEIFS(#REF!,#REF!,$A:$A),"-") -> - | ... X116: =IFERROR(AVERAGEIFS(#REF!,#REF!,$A:$A),"-") -> -
B117: =IFERROR(AVERAGEIFS('сентябрь 2024- июнь 2026'!$K:$K,'сентябрь 2024- июнь 2026'!$E:$E,$A:$A),"-") -> - | C117: =IFERROR(AVERAGEIFS(#REF!,#REF!,$A:$A),"-") -> - | D117: =IFERROR(AVERAGEIFS(#REF!,#REF!,$A:$A),"-") -> - | E117: =IFERROR(AVERAGEIFS(#REF!,#REF!,$A:$A),"-") -> - | F117: =IFERROR(AVERAGEIFS(#REF!,#REF!,$A:$A),"-") -> - | G117: =IFERROR(AVERAGEIFS(#REF!,#REF!,A:A),"-") -> - | H117: =IFERROR(AVERAGEIFS(#REF!,#REF!,$A:$A),"-") -> - | I117: =IFERROR(AVERAGEIFS(#REF!,#REF!,$A:$A),"-") -> - | J117: =IFERROR(AVERAGEIFS(#REF!,#REF!,$A:$A),"-") -> - | K117: =IFERROR(AVERAGEIFS(#REF!,#REF!,$A:$A),"-") -> - | L117: =IFERROR(AVERAGEIFS(#REF!,#REF!,$A:$A),"-") -> - | M117: =IFERROR(AVERAGEIFS(#REF!,#REF!,$A:$A),"-") -> - | N117: =IFERROR(AVERAGEIFS(#REF!,#REF!,$A:$A),"-") -> - | O117: =IFERROR(AVERAGEIFS(#REF!,#REF!,$A:$A),"-") -> - | ... X117: =IFERROR(AVERAGEIFS(#REF!,#REF!,$A:$A),"-") -> -
B118: =IFERROR(AVERAGEIFS('сентябрь 2024- июнь 2026'!$K:$K,'сентябрь 2024- июнь 2026'!$E:$E,$A:$A),"-") -> - | C118: =IFERROR(AVERAGEIFS(#REF!,#REF!,$A:$A),"-") -> - | D118: =IFERROR(AVERAGEIFS(#REF!,#REF!,$A:$A),"-") -> - | E118: =IFERROR(AVERAGEIFS(#REF!,#REF!,$A:$A),"-") -> - | F118: =IFERROR(AVERAGEIFS(#REF!,#REF!,$A:$A),"-") -> - | G118: =IFERROR(AVERAGEIFS(#REF!,#REF!,A:A),"-") -> - | H118: =IFERROR(AVERAGEIFS(#REF!,#REF!,$A:$A),"-") -> - | I118: =IFERROR(AVERAGEIFS(#REF!,#REF!,$A:$A),"-") -> - | J118: =IFERROR(AVERAGEIFS(#REF!,#REF!,$A:$A),"-") -> - | K118: =IFERROR(AVERAGEIFS(#REF!,#REF!,$A:$A),"-") -> - | L118: =IFERROR(AVERAGEIFS(#REF!,#REF!,$A:$A),"-") -> - | M118: =IFERROR(AVERAGEIFS(#REF!,#REF!,$A:$A),"-") -> - | N118: =IFERROR(AVERAGEIFS(#REF!,#REF!,$A:$A),"-") -> - | O118: =IFERROR(AVERAGEIFS(#REF!,#REF!,$A:$A),"-") -> - | ... X118: =IFERROR(AVERAGEIFS(#REF!,#REF!,$A:$A),"-") -> -
B119: =IFERROR(AVERAGEIFS('сентябрь 2024- июнь 2026'!$K:$K,'сентябрь 2024- июнь 2026'!$E:$E,$A:$A),"-") -> - | C119: =IFERROR(AVERAGEIFS(#REF!,#REF!,$A:$A),"-") -> - | D119: =IFERROR(AVERAGEIFS(#REF!,#REF!,$A:$A),"-") -> - | E119: =IFERROR(AVERAGEIFS(#REF!,#REF!,$A:$A),"-") -> - | F119: =IFERROR(AVERAGEIFS(#REF!,#REF!,$A:$A),"-") -> - | G119: =IFERROR(AVERAGEIFS(#REF!,#REF!,A:A),"-") -> - | H119: =IFERROR(AVERAGEIFS(#REF!,#REF!,$A:$A),"-") -> - | I119: =IFERROR(AVERAGEIFS(#REF!,#REF!,$A:$A),"-") -> - | J119: =IFERROR(AVERAGEIFS(#REF!,#REF!,$A:$A),"-") -> - | K119: =IFERROR(AVERAGEIFS(#REF!,#REF!,$A:$A),"-") -> - | L119: =IFERROR(AVERAGEIFS(#REF!,#REF!,$A:$A),"-") -> - | M119: =IFERROR(AVERAGEIFS(#REF!,#REF!,$A:$A),"-") -> - | N119: =IFERROR(AVERAGEIFS(#REF!,#REF!,$A:$A),"-") -> - | O119: =IFERROR(AVERAGEIFS(#REF!,#REF!,$A:$A),"-") -> - | ... X119: =IFERROR(AVERAGEIFS(#REF!,#REF!,$A:$A),"-") -> -
B120: =IFERROR(AVERAGEIFS('сентябрь 2024- июнь 2026'!$K:$K,'сентябрь 2024- июнь 2026'!$E:$E,$A:$A),"-") -> - | C120: =IFERROR(AVERAGEIFS(#REF!,#REF!,$A:$A),"-") -> - | D120: =IFERROR(AVERAGEIFS(#REF!,#REF!,$A:$A),"-") -> - | E120: =IFERROR(AVERAGEIFS(#REF!,#REF!,$A:$A),"-") -> - | F120: =IFERROR(AVERAGEIFS(#REF!,#REF!,$A:$A),"-") -> - | G120: =IFERROR(AVERAGEIFS(#REF!,#REF!,A:A),"-") -> - | H120: =IFERROR(AVERAGEIFS(#REF!,#REF!,$A:$A),"-") -> - | I120: =IFERROR(AVERAGEIFS(#REF!,#REF!,$A:$A),"-") -> - | J120: =IFERROR(AVERAGEIFS(#REF!,#REF!,$A:$A),"-") -> - | K120: =IFERROR(AVERAGEIFS(#REF!,#REF!,$A:$A),"-") -> - | L120: =IFERROR(AVERAGEIFS(#REF!,#REF!,$A:$A),"-") -> - | M120: =IFERROR(AVERAGEIFS(#REF!,#REF!,$A:$A),"-") -> - | N120: =IFERROR(AVERAGEIFS(#REF!,#REF!,$A:$A),"-") -> - | O120: =IFERROR(AVERAGEIFS(#REF!,#REF!,$A:$A),"-") -> - | ... X120: =IFERROR(AVERAGEIFS(#REF!,#REF!,$A:$A),"-") -> -
B121: =IFERROR(AVERAGEIFS('сентябрь 2024- июнь 2026'!$K:$K,'сентябрь 2024- июнь 2026'!$E:$E,$A:$A),"-") -> - | C121: =IFERROR(AVERAGEIFS(#REF!,#REF!,$A:$A),"-") -> - | D121: =IFERROR(AVERAGEIFS(#REF!,#REF!,$A:$A),"-") -> - | E121: =IFERROR(AVERAGEIFS(#REF!,#REF!,$A:$A),"-") -> - | F121: =IFERROR(AVERAGEIFS(#REF!,#REF!,$A:$A),"-") -> - | G121: =IFERROR(AVERAGEIFS(#REF!,#REF!,A:A),"-") -> - | H121: =IFERROR(AVERAGEIFS(#REF!,#REF!,$A:$A),"-") -> - | I121: =IFERROR(AVERAGEIFS(#REF!,#REF!,$A:$A),"-") -> - | J121: =IFERROR(AVERAGEIFS(#REF!,#REF!,$A:$A),"-") -> - | K121: =IFERROR(AVERAGEIFS(#REF!,#REF!,$A:$A),"-") -> - | L121: =IFERROR(AVERAGEIFS(#REF!,#REF!,$A:$A),"-") -> - | M121: =IFERROR(AVERAGEIFS(#REF!,#REF!,$A:$A),"-") -> - | N121: =IFERROR(AVERAGEIFS(#REF!,#REF!,$A:$A),"-") -> - | O121: =IFERROR(AVERAGEIFS(#REF!,#REF!,$A:$A),"-") -> - | ... X121: =IFERROR(AVERAGEIFS(#REF!,#REF!,$A:$A),"-") -> -
... B123: =IFERROR(AVERAGEIFS('сентябрь 2024- июнь 2026'!$K:$K,'сентябрь 2024- июнь 2026'!$E:$E,$A:$A),"-") -> - | C123: =IFERROR(AVERAGEIFS(#REF!,#REF!,$A:$A),"-") -> - | D123: =IFERROR(AVERAGEIFS(#REF!,#REF!,$A:$A),"-") -> - | E123: =IFERROR(AVERAGEIFS(#REF!,#REF!,$A:$A),"-") -> - | F123: =IFERROR(AVERAGEIFS(#REF!,#REF!,$A:$A),"-") -> - | G123: =IFERROR(AVERAGEIFS(#REF!,#REF!,A:A),"-") -> - | H123: =IFERROR(AVERAGEIFS(#REF!,#REF!,$A:$A),"-") -> - | I123: =IFERROR(AVERAGEIFS(#REF!,#REF!,$A:$A),"-") -> - | J123: =IFERROR(AVERAGEIFS(#REF!,#REF!,$A:$A),"-") -> - | K123: =IFERROR(AVERAGEIFS(#REF!,#REF!,$A:$A),"-") -> - | L123: =IFERROR(AVERAGEIFS(#REF!,#REF!,$A:$A),"-") -> - | M123: =IFERROR(AVERAGEIFS(#REF!,#REF!,$A:$A),"-") -> - | N123: =IFERROR(AVERAGEIFS(#REF!,#REF!,$A:$A),"-") -> - | O123: =IFERROR(AVERAGEIFS(#REF!,#REF!,$A:$A),"-") -> - | ... X123: =IFERROR(AVERAGEIFS(#REF!,#REF!,$A:$A),"-") -> -
B124: =IFERROR(AVERAGEIFS('сентябрь 2024- июнь 2026'!$K:$K,'сентябрь 2024- июнь 2026'!$E:$E,$A:$A),"-") -> - | C124: =IFERROR(AVERAGEIFS(#REF!,#REF!,$A:$A),"-") -> - | D124: =IFERROR(AVERAGEIFS(#REF!,#REF!,$A:$A),"-") -> - | E124: =IFERROR(AVERAGEIFS(#REF!,#REF!,$A:$A),"-") -> - | F124: =IFERROR(AVERAGEIFS(#REF!,#REF!,$A:$A),"-") -> - | G124: =IFERROR(AVERAGEIFS(#REF!,#REF!,A:A),"-") -> - | H124: =IFERROR(AVERAGEIFS(#REF!,#REF!,$A:$A),"-") -> - | I124: =IFERROR(AVERAGEIFS(#REF!,#REF!,$A:$A),"-") -> - | J124: =IFERROR(AVERAGEIFS(#REF!,#REF!,$A:$A),"-") -> - | K124: =IFERROR(AVERAGEIFS(#REF!,#REF!,$A:$A),"-") -> - | L124: =IFERROR(AVERAGEIFS(#REF!,#REF!,$A:$A),"-") -> - | M124: =IFERROR(AVERAGEIFS(#REF!,#REF!,$A:$A),"-") -> - | N124: =IFERROR(AVERAGEIFS(#REF!,#REF!,$A:$A),"-") -> - | O124: =IFERROR(AVERAGEIFS(#REF!,#REF!,$A:$A),"-") -> - | ... T124: =IFERROR(AVERAGEIFS(#REF!,#REF!,$A:$A),"-") -> -
B125: =IFERROR(AVERAGEIFS('сентябрь 2024- июнь 2026'!$K:$K,'сентябрь 2024- июнь 2026'!$E:$E,$A:$A),"-") -> - | C125: =IFERROR(AVERAGEIFS(#REF!,#REF!,$A:$A),"-") -> - | D125: =IFERROR(AVERAGEIFS(#REF!,#REF!,$A:$A),"-") -> - | E125: =IFERROR(AVERAGEIFS(#REF!,#REF!,$A:$A),"-") -> - | F125: =IFERROR(AVERAGEIFS(#REF!,#REF!,$A:$A),"-") -> - | G125: =IFERROR(AVERAGEIFS(#REF!,#REF!,A:A),"-") -> - | H125: =IFERROR(AVERAGEIFS(#REF!,#REF!,$A:$A),"-") -> - | I125: =IFERROR(AVERAGEIFS(#REF!,#REF!,$A:$A),"-") -> - | J125: =IFERROR(AVERAGEIFS(#REF!,#REF!,$A:$A),"-") -> - | K125: =IFERROR(AVERAGEIFS(#REF!,#REF!,$A:$A),"-") -> - | L125: =IFERROR(AVERAGEIFS(#REF!,#REF!,$A:$A),"-") -> - | M125: =IFERROR(AVERAGEIFS(#REF!,#REF!,$A:$A),"-") -> - | N125: =IFERROR(AVERAGEIFS(#REF!,#REF!,$A:$A),"-") -> - | O125: =IFERROR(AVERAGEIFS(#REF!,#REF!,$A:$A),"-") -> - | ... T125: =IFERROR(AVERAGEIFS(#REF!,#REF!,$A:$A),"-") -> -
B126: =IFERROR(AVERAGEIFS('сентябрь 2024- июнь 2026'!$K:$K,'сентябрь 2024- июнь 2026'!$E:$E,$A:$A),"-") -> - | C126: =IFERROR(AVERAGEIFS(#REF!,#REF!,$A:$A),"-") -> - | D126: =IFERROR(AVERAGEIFS(#REF!,#REF!,$A:$A),"-") -> - | E126: =IFERROR(AVERAGEIFS(#REF!,#REF!,$A:$A),"-") -> - | F126: =IFERROR(AVERAGEIFS(#REF!,#REF!,$A:$A),"-") -> - | G126: =IFERROR(AVERAGEIFS(#REF!,#REF!,A:A),"-") -> - | H126: =IFERROR(AVERAGEIFS(#REF!,#REF!,$A:$A),"-") -> - | I126: =IFERROR(AVERAGEIFS(#REF!,#REF!,$A:$A),"-") -> - | J126: =IFERROR(AVERAGEIFS(#REF!,#REF!,$A:$A),"-") -> - | K126: =IFERROR(AVERAGEIFS(#REF!,#REF!,$A:$A),"-") -> - | L126: =IFERROR(AVERAGEIFS(#REF!,#REF!,$A:$A),"-") -> - | M126: =IFERROR(AVERAGEIFS(#REF!,#REF!,$A:$A),"-") -> - | N126: =IFERROR(AVERAGEIFS(#REF!,#REF!,$A:$A),"-") -> - | O126: =IFERROR(AVERAGEIFS(#REF!,#REF!,$A:$A),"-") -> - | ... T126: =IFERROR(AVERAGEIFS(#REF!,#REF!,$A:$A),"-") -> -
B127: =IFERROR(AVERAGEIFS('сентябрь 2024- июнь 2026'!$K:$K,'сентябрь 2024- июнь 2026'!$E:$E,$A:$A),"-") -> - | C127: =IFERROR(AVERAGEIFS(#REF!,#REF!,$A:$A),"-") -> - | D127: =IFERROR(AVERAGEIFS(#REF!,#REF!,$A:$A),"-") -> - | E127: =IFERROR(AVERAGEIFS(#REF!,#REF!,$A:$A),"-") -> - | F127: =IFERROR(AVERAGEIFS(#REF!,#REF!,$A:$A),"-") -> - | G127: =IFERROR(AVERAGEIFS(#REF!,#REF!,A:A),"-") -> - | H127: =IFERROR(AVERAGEIFS(#REF!,#REF!,$A:$A),"-") -> - | I127: =IFERROR(AVERAGEIFS(#REF!,#REF!,$A:$A),"-") -> - | J127: =IFERROR(AVERAGEIFS(#REF!,#REF!,$A:$A),"-") -> - | K127: =IFERROR(AVERAGEIFS(#REF!,#REF!,$A:$A),"-") -> - | L127: =IFERROR(AVERAGEIFS(#REF!,#REF!,$A:$A),"-") -> - | M127: =IFERROR(AVERAGEIFS(#REF!,#REF!,$A:$A),"-") -> - | N127: =IFERROR(AVERAGEIFS(#REF!,#REF!,$A:$A),"-") -> - | O127: =IFERROR(AVERAGEIFS(#REF!,#REF!,$A:$A),"-") -> - | ... T127: =IFERROR(AVERAGEIFS(#REF!,#REF!,$A:$A),"-") -> -
B128: =IFERROR(AVERAGEIFS('сентябрь 2024- июнь 2026'!$K:$K,'сентябрь 2024- июнь 2026'!$E:$E,$A:$A),"-") -> - | C128: =IFERROR(AVERAGEIFS(#REF!,#REF!,$A:$A),"-") -> - | D128: =IFERROR(AVERAGEIFS(#REF!,#REF!,$A:$A),"-") -> - | E128: =IFERROR(AVERAGEIFS(#REF!,#REF!,$A:$A),"-") -> - | F128: =IFERROR(AVERAGEIFS(#REF!,#REF!,$A:$A),"-") -> - | G128: =IFERROR(AVERAGEIFS(#REF!,#REF!,A:A),"-") -> - | H128: =IFERROR(AVERAGEIFS(#REF!,#REF!,$A:$A),"-") -> - | I128: =IFERROR(AVERAGEIFS(#REF!,#REF!,$A:$A),"-") -> - | J128: =IFERROR(AVERAGEIFS(#REF!,#REF!,$A:$A),"-") -> - | K128: =IFERROR(AVERAGEIFS(#REF!,#REF!,$A:$A),"-") -> - | L128: =IFERROR(AVERAGEIFS(#REF!,#REF!,$A:$A),"-") -> - | M128: =IFERROR(AVERAGEIFS(#REF!,#REF!,$A:$A),"-") -> - | N128: =IFERROR(AVERAGEIFS(#REF!,#REF!,$A:$A),"-") -> - | O128: =IFERROR(AVERAGEIFS(#REF!,#REF!,$A:$A),"-") -> - | ... T128: =IFERROR(AVERAGEIFS(#REF!,#REF!,$A:$A),"-") -> -
B129: =IFERROR(AVERAGEIFS('сентябрь 2024- июнь 2026'!$K:$K,'сентябрь 2024- июнь 2026'!$E:$E,$A:$A),"-") -> - | C129: =IFERROR(AVERAGEIFS(#REF!,#REF!,$A:$A),"-") -> - | D129: =IFERROR(AVERAGEIFS(#REF!,#REF!,$A:$A),"-") -> - | E129: =IFERROR(AVERAGEIFS(#REF!,#REF!,$A:$A),"-") -> - | F129: =IFERROR(AVERAGEIFS(#REF!,#REF!,$A:$A),"-") -> - | G129: =IFERROR(AVERAGEIFS(#REF!,#REF!,A:A),"-") -> - | H129: =IFERROR(AVERAGEIFS(#REF!,#REF!,$A:$A),"-") -> - | I129: =IFERROR(AVERAGEIFS(#REF!,#REF!,$A:$A),"-") -> - | J129: =IFERROR(AVERAGEIFS(#REF!,#REF!,$A:$A),"-") -> - | K129: =IFERROR(AVERAGEIFS(#REF!,#REF!,$A:$A),"-") -> - | L129: =IFERROR(AVERAGEIFS(#REF!,#REF!,$A:$A),"-") -> - | M129: =IFERROR(AVERAGEIFS(#REF!,#REF!,$A:$A),"-") -> - | N129: =IFERROR(AVERAGEIFS(#REF!,#REF!,$A:$A),"-") -> - | O129: =IFERROR(AVERAGEIFS(#REF!,#REF!,$A:$A),"-") -> - | ... T129: =IFERROR(AVERAGEIFS(#REF!,#REF!,$A:$A),"-") -> -
B130: =IFERROR(AVERAGEIFS('сентябрь 2024- июнь 2026'!$K:$K,'сентябрь 2024- июнь 2026'!$E:$E,$A:$A),"-") -> - | C130: =IFERROR(AVERAGEIFS(#REF!,#REF!,$A:$A),"-") -> - | D130: =IFERROR(AVERAGEIFS(#REF!,#REF!,$A:$A),"-") -> - | E130: =IFERROR(AVERAGEIFS(#REF!,#REF!,$A:$A),"-") -> - | F130: =IFERROR(AVERAGEIFS(#REF!,#REF!,$A:$A),"-") -> - | G130: =IFERROR(AVERAGEIFS(#REF!,#REF!,A:A),"-") -> - | H130: =IFERROR(AVERAGEIFS(#REF!,#REF!,$A:$A),"-") -> - | I130: =IFERROR(AVERAGEIFS(#REF!,#REF!,$A:$A),"-") -> - | J130: =IFERROR(AVERAGEIFS(#REF!,#REF!,$A:$A),"-") -> - | K130: =IFERROR(AVERAGEIFS(#REF!,#REF!,$A:$A),"-") -> - | L130: =IFERROR(AVERAGEIFS(#REF!,#REF!,$A:$A),"-") -> - | M130: =IFERROR(AVERAGEIFS(#REF!,#REF!,$A:$A),"-") -> - | N130: =IFERROR(AVERAGEIFS(#REF!,#REF!,$A:$A),"-") -> - | O130: =IFERROR(AVERAGEIFS(#REF!,#REF!,$A:$A),"-") -> - | ... T130: =IFERROR(AVERAGEIFS(#REF!,#REF!,$A:$A),"-") -> -
B131: =IFERROR(AVERAGEIFS('сентябрь 2024- июнь 2026'!$K:$K,'сентябрь 2024- июнь 2026'!$E:$E,$A:$A),"-") -> - | C131: =IFERROR(AVERAGEIFS(#REF!,#REF!,$A:$A),"-") -> - | D131: =IFERROR(AVERAGEIFS(#REF!,#REF!,$A:$A),"-") -> - | E131: =IFERROR(AVERAGEIFS(#REF!,#REF!,$A:$A),"-") -> - | F131: =IFERROR(AVERAGEIFS(#REF!,#REF!,$A:$A),"-") -> - | G131: =IFERROR(AVERAGEIFS(#REF!,#REF!,A:A),"-") -> - | H131: =IFERROR(AVERAGEIFS(#REF!,#REF!,$A:$A),"-") -> - | I131: =IFERROR(AVERAGEIFS(#REF!,#REF!,$A:$A),"-") -> - | J131: =IFERROR(AVERAGEIFS(#REF!,#REF!,$A:$A),"-") -> - | K131: =IFERROR(AVERAGEIFS(#REF!,#REF!,$A:$A),"-") -> - | L131: =IFERROR(AVERAGEIFS(#REF!,#REF!,$A:$A),"-") -> - | M131: =IFERROR(AVERAGEIFS(#REF!,#REF!,$A:$A),"-") -> - | N131: =IFERROR(AVERAGEIFS(#REF!,#REF!,$A:$A),"-") -> - | O131: =IFERROR(AVERAGEIFS(#REF!,#REF!,$A:$A),"-") -> - | ... T131: =IFERROR(AVERAGEIFS(#REF!,#REF!,$A:$A),"-") -> -

Sheet СС
A2: номер заказа | B2: дата ТД | C2: наименование | D2: кол-во | E2: Сумма евро с НДС | F2: Сумма руб с НДС | G2: Себес с НДС, евро | H2: ндс | I2: Сумма евро без НДС | J2: Сумма руб без ндс | K2: Себес без НДС, евро
A3: ШККА-000109 | B3: 45796 | C3: Изоцианат лупранат MI компонент Б (бочка 225) | D3: 19000 | E3: 56430 | F3: 5189680.9 | I3: 56430 | J3: 5189680.9
C4: Возмещаемые расходы: Сверхнормативное использование контейнера, Kumport - Новороссийск, LAMU7000547 | E4: 1121.1 | F4: 103104 | H4: без ндс | I4: 1121.1 | J4: 103104
C5: Транспортно-экспедиционное обслуживание по маршруту FCA Kumport - Новороссийск, MDTRLS2504449, LAMU7000547, Инвйос 2025/R0376 от 14.05.25 | E5: 5255.16 | F5: 483300 | H5: без ндс | I5: 5255.16 | J5: 483300
C6: Комплекс услуг таможенного представителя по таможенному декларированию товаров, ДТ 10317120/190525/5087193, Инвйос 2025/R0376 от 14.05.25 | E6: 326.21 | F6: 30000 | H6: 0.2 | I6: 271.84 | J6: 25000
C7: Транспортно-экспедиционное обслуживание по маршруту НУТЭП - Склад, LAMU7000547, Инвйос 2025/R0376 от 14.05.25 | E7: 2598.77 | F7: 239000 | H7: 0 | I7: 2598.77 | J7: 239000
C8: Возмещаемые расходы: Хранение рефрижераторного контейнера, подключенного к электропитанию, с первых суток , LAMU7000547 | E8: 231.36 | F8: 21277.48 | H8: 0.2 | I8: 192.8 | J8: 17731.23
C9: Возмещаемые расходы: Фрахтовая надбавка DTHC (стивидорный сбор порта выгрузки), LAMU7000547 | E9: 840.82 | F9: 77327.63 | H9: 0.2 | I9: 700.69 | J9: 64439.69
C10: Возмещаемые расходы: Агентское вознаграждение (Hamburg Sud), LAMU7000547 | E10: 54.8 | F10: 5040 | H10: 0.2 | I10: 45.67 | J10: 4200 | M10: дельта | N10: =K16-K34 -> 0.49166667 | O10: евро
E11: 0 | H11: 0.2 | I11: 0 | J11: 0 | M11: Расход на 1100 | N11: 607.7 | O11: кг
C12: НДС на таможне | E12: 12791.46 | F12: 1176388.7 | I12: 12791.46 | J12: 1176388.7 | M12: Ошибка в 1С | N12: =N11*N10 -> 298.78583
C13: Пошлина | E13: 3045.59 | F13: 280092.54 | I13: 3045.59 | J13: 280092.54 | M13: На кг | N13: =N12/1100 -> 0.27162348
C14: Таможенный сбор | E14: 299.46 | F14: 27540 | I14: 299.46 | J14: 27540
C15: итого по заказу | D15: 19000 | E15: 82994.73 | F15: 7632751.2 | G15: 4.37 | I15: 66616.02 | J15: 6126455.8 | L15: бндс | M15: Корр по курсу
G16: 4.3681436 | K16: =G15-G15/6 -> 3.6416667 | M16: 45740 | N16: 93.2547
C17: * доп услуги пересчитаны в евро по курсу на 09.07.2025 | G17: 401.72375 | K17: 322.44504 | M17: 45869 | N17: 96.8504
M18: 45854 | N18: 92.9762 | O18: =AVERAGE(N17:N18) -> 94.9133
N19: =N16-O18 -> -1.6586
N20: =N19/89.9011 -> -0.018449162
A21: номер заказа | B21: дата ТД | C21: наименование | D21: кол-во | E21: Сумма евро с НДС | F21: Сумма руб с НДС | G21: Себес с НДС, евро | H21: ндс | I21: Сумма евро без НДС | J21: Сумма руб без ндс | K21: Себес без НДС, евро | M21: корр на кг | N21: =N13+N20 -> 0.25317432
A22: 83 | B22: 45971 | C22: Изоцианат Lupranate MI (бочка 225 кг) | D22: 20250 | E22: 49 916,25 | F22: 4 646 756,50 | I22: 49 916,25 | J22: 4 646 756,50
C23: Транспортно-экспедиционное обслуживание по маршруту FCA Istanbul - Mersin - Новороссийск, ULDMERNVK001004, SEGU9862812 40'RF, Инвойс 2025/R0476 от 23.09.2025 | E23: 5792.03 | F23: 523274.05 | H23: без ндс | I23: 5792.03 | J23: 523274.05
C24: Возмещаемые расходы за ТЭУ по оформлению документов: Документационные услуги в импорте/экспорте SEGU9862812 | E24: 863.37 | F24: 78000 | H24: 0 | I24: 863.37 | J24: 78000
C25: Комплекс услуг таможенного представителя по таможенному декларированию товаров, ДТ 10317120/101125/5178711, Инвойс 2025/R0476 от 23.09.2025 | E25: 332.06 | F25: 30000 | H25: 0.2 | I25: 276.72 | J25: 25000
C26: Возмещаемые услуги за услуги платежного агента SEGU9862812 | E26: 100.43 | F26: 9073.48 | H26: 0.2 | I26: 98.64 | J26: 8911.45
C27: Возмещаемые услуги за организацию хранения груженного станд 40'RF контейнера в импорте (неопасный груз) с 08.11-11.11 SEGU9862812 | E27: 287.79 | F27: 26000 | H27: 0 | I27: 287.79 | J27: 26000
C28: Транспортно-экспедиционное обслуживание по маршруту Новороссийск (НУТЭП) - г.Москва (Склад), SEGU9862812 40'RF, Инвойс 2025/R0476 от 23.09.2025 | E28: 2490.49 | F28: 225000 | H28: 0 | I28: 2490.49 | J28: 225000
E29: 0 | H29: 0 | I29: 0 | J29: 0
C30: НДС на таможне | E30: 12103.99 | F30: 1093520.4
C31: Пошлина | E31: 2881.9 | F31: 260362.01 | I31: 2881.9 | J31: 518185.47
C32: Таможенный сбор | E32: 236.25 | F32: 21344 | I32: 236.25 | J32: 30000
C33: итого по заказу | D33: 20250 | E33: 75004.57 | F33: 6913330.5 | G33: 3.7 | I33: 62843.44 | J33: 6081127.5 | L33: б/ндс | M33: 90.3438
G34: 3.78 | K34: =G34-G34/6 -> 3.15
C35: * доп услуги пересчитаны в евро по курсу на 02.12.2025 | G35: 341.4 | K35: 280.37112
A39: дата | B39: наименование | C39: кол-во | D39: Сумма евро с НДС | E39: Сумма руб с НДС | F39: Себес с НДС, евро | G39: ндс | H39: Сумма евро без НДС | I39: Сумма руб без ндс | J39: Себес без НДС, евро
A40: 45993 | B40: Изоцианат Wannate MDI 50-F (IBC) | C40: 49820 | D40: 106 258,00 | E40: 10 338 790,88 | H40: 106 258,00 | I40: 10 338 790,88
B41: Совершение таможенных операций с товарами за один (первый) контейнер в ДТ 10228020/021225/5169698 конт. AVGU7003291 | D41: 262.64 | E41: 24000 | G41: 0.2 | H41: 262.64 | I41: 20000 | L41: =D40/49820 -> 2.1328382
B42: Организация перевозок грузов в контейнерах AVGU7003291 AVGU7002192 по маршруту Shanghai, CN – Порт Санкт-Петербург, РФ | D42: 13768.82 | E42: 1 258 203,38 | G42: без ндс | H42: 13768.82 | I42: 1258203.4
B43: Организация перевозок грузов в контейнерах AVGU7003291 AVGU7002192 по маршруту Порт Санкт-Петербург, РФ – МО, пос. Некрасовский, ул. Ушакова, д. 27А, РФ | D43: 2473.17 | E43: 226000 | G43: 0 | H43: 2473.17 | I43: 226000
B44: Хранение: Рефрижераторный контейнер ИСО 20'/40' груженый, с 1 дня по день 5 (импорт) AVGU7003291 AVGU7002192 | D44: 230.77 | E44: 21088 | G44: 0 | H44: 230.77 | I44: 21088
B45: Страховая премия по полису № 250070-330-007169 от 17.10.2025 | D45: 108.56 | E45: 9920.23 | G45: 0.2 | H45: 108.56 | I45: 9920.23
D46: 0 | G46: 0.2 | H46: 0
D47: 0 | G47: 0.2 | H47: 0
B48: Аренда дизель-генераторной устоновки LCLU 9991684 (с 03.12.2025 по 05.12.2025, КРК № AVGU7002192) | D48: 146.64 | E48: 13400 | G48: 0.2 | H48: 146.64 | I48: 11166.66
B49: НДС на таможне | D49: 25487.4 | E49: 2329054.2
B50: Пошлина | D50: 6068.43 | E50: 554536.71 | H50: 6068.43 | I50: 554536.71
B51: Таможенный сбор | D51: 328.3 | E51: 30000 | H51: 328.3 | I51: 30000
B52: итого по заказу | C52: 49820 | D52: 155132.73 | E52: 14804993 | F52: 3.11 | H52: 129645.33 | I52: 12469706 | J52: 2.6 | L52: 91.3806
F53: 3.2519996
B54: * доп услуги пересчитаны в евро по курсу на 11.12.2025 | F54: 297.16968 | J54: 237.79743
C56: юани | D56: 896 760,00
A59: 45915 | B59: Заказ поставщику ШККА-000405 от 15.09.2025 0:00:00 | C59: 896 760,00 | D59: курс юани | F59: курс Е | H59: проверка
A60: 45919 | B60: Списание безналичных ДС ШККА-П002794 от 19.09.2025 17:59:46 | C60: 448 380,00 | D60: 11.67 | E60: 5 230 845,92 | F60: 98.9773 | G60: 52849
A61: 45932 | B61: Списание безналичных ДС ШККА-П002934 от 01.10.2025 23:59:59 | C61: 448 380,00 | D61: 11.392 | E61: 5 107 944,96 | F61: 95.6382 | G61: 53409
A62: 45993 | B62: Приобретение товаров и услуг ШККА-000638 от 02.12.2025 23:59:59 (вх. коносамент FBLSKX50295 от 16.10.2025) | C62: 896 760,00 | E62: 10 338 790,88 | G62: 106258
K64: Доля рублевых расходов
K65: 209.47 | L65: =(K65/2343)*100 -> 8.9402475
K66: Партия в евро
A70: Миракл
A71: номер заказа | B71: дата ТД | C71: наименование | D71: кол-во | E71: Сумма евро с НДС | F71: Сумма руб с НДС | G71: Себес с НДС, евро | H71: ндс | I71: Сумма евро без НДС | J71: Сумма руб без ндс | K71: Себес без НДС, евро
A72: 228 | C72: Изоцианат Wannate MDI 50-F (IBC) | D72: 47000 | E72: 96046.72 | F72: 8844308.9 | I72: 96046.72 | J72: 8844308.9
C73: Возмещаемые расходы: Хранение груженого контейнера в Rizhao, FBIU5178415 | E73: 443.2 | F73: 40811.42 | H73: без ндс | I73: 443.2 | J73: 40811.42
C74: Транспортно-экспедиционное обслуживание по маршруту ПКТ - Москва (Склад), FBIU5178415 40'RF, Инвойс №250417 от 16.07.25 | E74: 1954.75 | F74: 180000 | H74: 0 | I74: 1954.75 | J74: 180000
C75: Транспортно-экспедиционное обслуживание по маршруту Rizhao - Санкт-Петербург, NNLRZH251605233, FBIU5178415 40'RF, Инвойс №250417 от 16.07.25 | E75: 15034.06 | F75: 1384387.5 | H75: 0 | I75: 15034.06 | J75: 1384387.5
C76: Возмещаемые расходы: Перемещение контейнера для целей осмотра с использованием инспекционно-досмотрового комплекса (ИДК), FBIU5178415 | E76: 192.38 | F76: 17715 | H76: без ндс | I76: 192.38 | J76: 17715
C77: Комплекс услуг таможенного представителя по таможенному декларированию товаров, ДТ 10228020/290825/5127290, Инвойс №250417 от 16.07.25 | E77: 325.79 | F77: 30000 | H77: 0.2 | I77: 271.49 | J77: 25000
C78: Транспортно-экспедиционное обслуживание по маршруту ПКТ - Москва (Склад), FBIU5182400 40'RF, Инвойс №250417 от 16.07.25 | E78: 1954.75 | F78: 180000 | H78: 0 | I78: 1954.75 | J78: 180000
C79: Возмещаемые расходы: Хранение: Рефрижераторный контейнер ИСО 20'/40' груженый, с 1 дня по день 5 (импорт), FBIU5182400 | E79: 709.94 | F79: 65374 | H79: 0.2 | I79: 709.94 | J79: 65374
C80: НДС на таможне | E80: 23634.87 | F80: 2176379
C81: Пошлина | E81: 5627.35 | F81: 518185.47 | I81: 5627.35
C82: Таможенный сбор | E82: 325.79 | F82: 30000 | I82: 325.79
C83: итого по заказу | D83: 47000 | E83: 146249.61 | F83: 13467161 | G83: 3.11 | I83: 116607.3 | J83: 10449508 | K83: 2.48
G84: 3.11
C85: * доп услуги пересчитаны в евро по курсу на 17.10.25 | G85: 286.54 | K85: 228.45951
C87: MIRACLE (SHANGHAI) NEW MATERIALS CO., LTD
C88: 799000 | D88: юани
C89: 11.2382 | D89: курс на 29.08
C90: 93.4891 | D90: курс евро на 29.08
C92: 8979321.8
C93: 96 046,72
A100: ########## | B100: Полиол Puranol Polyether polyol G303 | C100: 20000 | D100: 20207.77 | E100: 1 842 001,00 | H100: 20207.77 | I100: 1 842 001,00
B101: Организация перевозки (фрахт) EXW Binzhou - via Qingdao - Vostochniy, DFSU1065714, к/с LED420562, т/х HUA XIN 5 178, прих. 16/08/2025 | D101: 2008.95 | E101: 182451.07 | G101: 0 | H101: 2008.95 | I101: 182451.07
B102: Организация перемещения контейнера в границах Порта для целей взвешивания на Восточный (Россия) 18.08.2025 178HX COC 20'DC DFSU1065714 | D102: 94.69 | E102: 8600 | G102: 0 | H102: 94.69 | I102: 8600
B103: Хранение на АО "ВОСТОЧНЫЙ ПОРТ" с момента окончания льготного периода,178HX, 20'DC с 25.08.2025 по 26.08.2025 DFSU1065714 | D103: 101.3 | E103: 9200 | G103: 0 | H103: 101.3 | I103: 9200
B104: Транспортно-экспедиционные услуги при организации международной перевозки: Взвешивание контейнера согласно реестру контейнеров №ЖТ-719 от 04.09.2025 г. | D104: 187.19 | E104: 17000 | G104: 0 | H104: 187.19 | I104: 17000
B105: Предоставление транзитных документов в тамож.органы для закрытия доставки при оформлении груза в ЦЭД, DFSU1065714 | D105: 418.47 | E105: 38005 | G105: 0.2 | H105: 348.72 | I105: 31670.83
B106: Организация ТЭО М.О. Старая Купавна - М.О. Дмитровский р-н, п. Некрасовский, DFSU1065714 | D106: 506.5 | E106: 46000 | G106: 0.2 | H106: 422.08 | I106: 38333.33
B107: Организация перевозки (жд) Владивосток-Москва, DFSU1065714, прих. 10/09/2025 | D107: 1706.69 | E107: 155000 | G107: 0.2 | H107: 1706.69 | I107: 155000
B108: Комплекс услуг таможенного представителя по таможенному декларированию товаров, ДТ 10702070/220925/5332413, Инвойс №FJ250729004 от 05.08.2025 | D108: 330.33 | E108: 30000 | G108: 0.2 | H108: 330.33 | I108: 25000
B109: НДС на таможне | D109: 4994.18 | E109: 453566.07
B110: Пошлина | D110: 960.42 | E110: 87224.24 | H110: 960.42 | I110: 87224.24
B111: Таможенный сбор | D111: 129.33 | E111: 11746 | H111: 129.33 | I111: 11746
B112: итого по заказу | C112: 20000 | D112: 31645.82 | E112: 2880793.4 | F112: 1.58 | H112: 26497.48 | I112: 2408226.5 | J112: 1.32
F113: 1.5860081
B114: * доп услуги пересчитаны в евро по курсу на 01.12.2025 | F114: 144.03967 | J114: 120.32375
B119: 170 000,00
A124: номер заказа | B124: дата ТД | C124: наименование | D124: кол-во | E124: Сумма евро с НДС | F124: Сумма руб с НДС | G124: Себес с НДС, евро | H124: ндс | I124: Сумма евро без НДС | J124: Сумма руб без ндс | K124: Себес без НДС, евро
A125: ШККА-000043 | B125: 45850 | C125: Изоцианат лупранат MI компонент Б (бочка 225) | D125: 20250 | E125: 49815 | F125: 4581321.2 | I125: 49815 | J125: 4581321.2
C126: Возмещаемые расходы: Хранение груженого контейнера в Турции Marport, AMCU9279394 | E126: 1725.52 | F126: 158690.58 | H126: без ндс | I126: 1725.52 | J126: 158690.58
C127: Транспортно-экспедиционное обслуживание по маршруту Marport - Новороссийск, ROS32659, AMCU9279394, Инвойс №2025/R0385 от 22.05.2025 | E127: 6630.09 | F127: 609747.06 | H127: без ндс | I127: 6630.09 | J127: 609747.06
...
